Workbook

Sheet Data Tables (Q)
A1: AN | B1: 2016 | C1: 2017 | D1: 2018 | E1: 2019 | F1: 2020 Q1 | G1: 2020 Q2 | H1: 2020 Q3 | I1: 2020 Q4 | J1: 2021 Q1 | K1: 2021 Q2 | L1: 2021 Q3 | M1: 2021 Q4 | N1: 2022 Q1 | O1: 2022 Q2 | P1: 2022 Q3 | Q1: 2022 Q4 | R1: 2023 Q1 | S1: 2023 Q2 | T1: 2023 Q3 | U1: 2023 Q4 | V1: 2024 Q1 | W1: 2024 Q2 | X1: 2024 Q3 | Y1: 2024 Q4 | Z1: 2025 Q1 | AA1: 2025 Q2 | AB1: 2025 Q3 | AC1: 2025 Q4
A2: Contract Model Score | B2: 130.07704 | C2: 132.82918 | D2: 132.99304 | E2: 132.10911 | F2: 131.79764 | G2: 133.71059 | H2: 135.28557 | I2: 135.79608 | J2: 134.60179 | K2: 135.14257 | L2: 135.36265 | M2: 134.41538 | N2: 134.0686 | O2: 135.89246 | P2: 136.14781 | Q2: 136.75155 | R2: 136.66305 | S2: 136.90907 | T2: 136.43849 | U2: 137.02135 | V2: 136.37212 | W2: 137.12198 | X2: 138.09052 | Y2: 136.80136 | Z2: 136.83702 | AA2: 138.03382 | AB2: 138.55808 | AC2: 139.3761 | AD2: 140.36297
A3: Model Score | B3: 0 | C3: 0 | D3: 0 | E3: 0 | F3: 0 | G3: 0 | H3: 0 | I3: 0 | J3: 0 | K3: 0 | L3: 0 | M3: 0 | N3: 0 | O3: 0 | P3: 0 | Q3: 0 | R3: 0 | S3: 0 | T3: 0 | U3: 0 | V3: 0 | W3: 0 | X3: 0 | Y3: 0 | Z3: 0 | AA3: 0 | AB3: 0 | AC3: 0 | AD3: 0
A4: Gross Loss Adjustments (Dealer level, high PTI, etc.) | B4: 0.36824634 | C4: 0.64268496 | D4: 0.73760946 | E4: 0.54113333 | F4: 0.64749521 | G4: 0.51566419 | H4: -0.19174308 | I4: 0.2567337 | J4: 0.53917167 | K4: 0.53578838 | L4: 0.54503838 | M4: 0.45373656 | N4: 0.86176791 | O4: 0.80063115 | P4: 0.87451807 | Q4: 0.86438829 | R4: 0.55900216 | S4: 0.92010091 | T4: 0.38592112 | U4: 0.33895356 | V4: 0.58664147 | W4: 1.0236504 | X4: 0.82057154 | Y4: 1.3243079 | Z4: 1.8938718 | AA4: 2.556068 | AB4: 3.0998623 | AC4: 3.5696834 | AD4: 2.6503283
A5: Recovery Adjustments excluding LTV (Mileage, vehicle type, etc.) | B5: -0.42682491 | C5: -0.49101527 | D5: -0.33145102 | E5: -0.46825812 | F5: -0.40547259 | G5: -0.82009987 | H5: -0.44087336 | I5: -0.031352964 | J5: -0.43522926 | K5: -0.66882046 | L5: -0.64378361 | M5: -0.94080084 | N5: -1.4183381 | O5: -2.6459525 | P5: -3.5505797 | Q5: -3.8736194 | R5: -3.150067 | S5: -2.7477242 | T5: -2.6814291 | U5: -2.4647213 | V5: -2.0924894 | W5: -1.8339517 | X5: -1.2461937 | Y5: -1.631803 | Z5: -0.06672953 | AA5: 0.54524695 | AB5: 1.1256274 | AC5: 1.2013578 | AD5: 2.1993762
A6: LTV Adjustments | B6: 0.42682491 | C6: 0.49101527 | D6: 0.33145102 | E6: 0.46825812 | F6: 0.40547259 | G6: 0.82009987 | H6: 0.44087336 | I6: 0.031352964 | J6: 0.43522926 | K6: 0.66882046 | L6: 0.64378361 | M6: 0.94080084 | N6: 1.4183381 | O6: 2.6459525 | P6: 3.5505797 | Q6: 3.8736194 | R6: 3.150067 | S6: 2.7477242 | T6: 2.6814291 | U6: 2.4647213 | V6: 2.0924894 | W6: 1.8339517 | X6: 1.2461937 | Y6: 1.631803 | Z6: 0.06672953 | AA6: -0.54524695 | AB6: -1.1256274 | AC6: -1.2013578 | AD6: -2.1993762
A7: RAGU Score | B7: 130.44529 | C7: 133.47187 | D7: 133.73065 | E7: 132.65024 | F7: 132.44513 | G7: 134.22626 | H7: 135.09383 | I7: 136.05282 | J7: 135.14096 | K7: 135.67836 | L7: 135.90769 | M7: 134.86912 | N7: 134.93036 | O7: 136.69309 | P7: 137.02232 | Q7: 137.61594 | R7: 137.22205 | S7: 137.82917 | T7: 136.82441 | U7: 137.3603 | V7: 136.95876 | W7: 138.14563 | X7: 138.91109 | Y7: 138.12566 | Z7: 138.7309 | AA7: 140.58989 | AB7: 141.65794 | AC7: 142.94578 | AD7: 143.01329
A8: LTV | B8: 1.9087244 | C8: 1.9020945 | D8: 1.9108652 | E8: 1.9482717 | F8: 1.902826 | G8: 1.9471127 | H8: 1.6704441 | I8: 1.6601973 | J8: 1.6894127 | K8: 1.515447 | L8: 1.5852082 | M8: 1.5827355 | N8: 1.6171228 | O8: 1.7022851 | P8: 1.7576372 | Q8: 1.81575 | R8: 1.8234154 | S8: 1.7206772 | T8: 1.6794167 | U8: 1.7109657 | V8: 1.7394377 | W8: 1.68966 | X8: 1.6017589 | Y8: 1.6130967 | Z8: 1.612319 | AA8: 1.570741 | AB8: 1.5773568 | AC8: 1.5580138 | AD8: 1.5879691
A10: FLD | F10: 2020 Q1 | G10: 2020 Q2 | H10: 2020 Q3 | I10: 2020 Q4 | J10: 2021 Q1 | K10: 2021 Q2 | L10: 2021 Q3 | M10: 2021 Q4 | N10: 2022 Q1 | O10: 2022 Q2 | P10: 2022 Q3 | Q10: 2022 Q4 | R10: 2023 Q1 | S10: 2023 Q2 | T10: 2023 Q3 | U10: 2023 Q4 | V10: 2024 Q1 | W10: 2024 Q2 | X10: 2024 Q3 | Y10: 2024 Q4 | Z10: 2025 Q1 | AA10: 2025 Q2 | AB10: 2025 Q3 | AC10: 2025 Q4
A11: Contract Model Score | F11: 131.95039 | G11: 135.66547 | H11: 137.78086 | I11: 140.37625 | J11: 136.75685 | K11: 136.18261 | L11: 135.63105 | M11: 134.62935 | N11: 134.17392 | O11: 135.83718 | P11: 136.96375 | Q11: 138.77228 | R11: 141.32316 | S11: 138.86319 | T11: 137.95666 | U11: 139.5662 | V11: 138.5244 | W11: 138.40978 | X11: 140.36331 | Y11: 138.38769 | Z11: 136.70743 | AA11: 138.3478 | AB11: 138.1021 | AC11: 138.94555 | AD11: 140.92699
A12: Model Score | F12: 0 | G12: 0 | H12: 0 | I12: 0 | J12: 0 | K12: 0 | L12: 0 | M12: 0 | N12: 0 | O12: 0 | P12: 0 | Q12: 0 | R12: 0 | S12: 0 | T12: 0 | U12: 0 | V12: 0 | W12: 0 | X12: 0 | Y12: 0 | Z12: 0 | AA12: 0 | AB12: 0 | AC12: 0 | AD12: 0
A13: Gross Loss Adjustments (Dealer level, high PTI, etc.) | F13: -2.5958615 | G13: -2.2718375 | H13: -1.6417215 | I13: -0.13010911 | J13: 1.0953963 | K13: -0.99165458 | L13: -1.0619348 | M13: 0.042055432 | N13: -0.21227366 | O13: 0.043550408 | P13: 0.48750697 | Q13: 0.45836499 | R13: 0.55308505 | S13: 0.29722802 | T13: 0.7107683 | U13: 0.98705958 | V13: 1.384667 | W13: 2.2016267 | X13: 3.1096998 | Y13: 3.0472917 | Z13: 3.0958106 | AA13: 2.6191118 | AB13: 3.4186632 | AC13: 2.2568239 | AD13: 1.8759566
A14: Recovery Adjustments excluding LTV (Mileage, vehicle type, etc.) | F14: 1.6480712 | G14: 1.6389226 | H14: 1.9811857 | I14: 2.0823456 | J14: 1.585956 | K14: 0.95962335 | L14: 0.61921158 | M14: 0.45613646 | N14: 0.48726161 | O14: -1.3199594 | P14: -2.6343136 | Q14: -2.5252511 | R14: -2.3959284 | S14: -1.8747561 | T14: -2.8208717 | U14: 0.14966026 | V14: -0.85316181 | W14: -1.3454548 | X14: -0.28346707 | Y14: -0.3487306 | Z14: 1.9955828 | AA14: 1.608932 | AB14: 2.1800694 | AC14: 2.4945801 | AD14: 1.957943
A15: LTV Adjustments | F15: -1.6480712 | G15: -1.6389226 | H15: -1.9811857 | I15: -2.0823456 | J15: -1.585956 | K15: -0.95962335 | L15: -0.61921158 | M15: -0.45613646 | N15: -0.48726161 | O15: 1.3199594 | P15: 2.6343136 | Q15: 2.5252511 | R15: 2.3959284 | S15: 1.8747561 | T15: 2.8208717 | U15: -0.14966026 | V15: 0.85316181 | W15: 1.3454548 | X15: 0.28346707 | Y15: 0.3487306 | Z15: -1.9955828 | AA15: -1.608932 | AB15: -2.1800694 | AC15: -2.4945801 | AD15: -1.957943
A16: RAGU Score | F16: 129.35453 | G16: 133.39363 | H16: 136.13914 | I16: 140.24614 | J16: 137.85224 | K16: 135.19096 | L16: 134.56911 | M16: 134.6714 | N16: 133.96165 | O16: 135.88073 | P16: 137.45126 | Q16: 139.23064 | R16: 141.87625 | S16: 139.16042 | T16: 138.66743 | U16: 140.55326 | V16: 139.90907 | W16: 140.61141 | X16: 143.47301 | Y16: 141.43498 | Z16: 139.80324 | AA16: 140.96691 | AB16: 141.52076 | AC16: 141.20238 | AD16: 142.80294
A17: LTV | F17: 1.4205628 | G17: 1.3731628 | H17: 1.2237836 | I17: 1.2677232 | J17: 1.3305309 | K17: 1.2336043 | L17: 1.2737699 | M17: 1.3338379 | N17: 1.3410876 | O17: 1.3387478 | P17: 1.3202801 | Q17: 1.3151241 | R17: 1.2676963 | S17: 1.3059301 | T17: 1.268125 | U17: 1.2894164 | V17: 1.3845444 | W17: 1.3691063 | X17: 1.3486685 | Y17: 1.3458292 | Z17: 1.3919187 | AA17: 1.4211805 | AB17: 1.4236177 | AC17: 1.421859 | AD17: 1.4738286
A19: FRN | B19: 2016 | C19: 2017 | D19: 2018 | E19: 2019 | F19: 2020 Q1 | G19: 2020 Q2 | H19: 2020 Q3 | I19: 2020 Q4 | J19: 2021 Q1 | K19: 2021 Q2 | L19: 2021 Q3 | M19: 2021 Q4 | N19: 2022 Q1 | O19: 2022 Q2 | P19: 2022 Q3 | Q19: 2022 Q4 | R19: 2023 Q1 | S19: 2023 Q2 | T19: 2023 Q3 | U19: 2023 Q4 | V19: 2024 Q1 | W19: 2024 Q2 | X19: 2024 Q3 | Y19: 2024 Q4 | Z19: 2025 Q1 | AA19: 2025 Q2 | AB19: 2025 Q3 | AC19: 2025 Q4
A20: Contract Model Score | B20: 131.17685 | C20: 136.73938 | D20: 136.80349 | E20: 132.53803 | F20: 131.13303 | G20: 132.90504 | H20: 133.93048 | I20: 132.80381 | J20: 135.44811 | K20: 135.18735 | L20: 134.94602 | M20: 132.89928 | N20: 134.06325 | O20: 136.81721 | P20: 138.00243 | Q20: 139.77793 | R20: 141.27719 | S20: 140.58734 | T20: 140.72103 | U20: 139.02514 | V20: 138.13163 | W20: 140.17356 | X20: 141.55375 | Y20: 139.97097 | Z20: 139.83315 | AA20: 140.63434 | AB20: 140.96388 | AC20: 141.85749 | AD20: 142.86763
A21: Model Score | B21: 0 | C21: 0 | D21: 0 | E21: 0 | F21: 0 | G21: 0 | H21: 0 | I21: 0 | J21: 0 | K21: 0 | L21: 0 | M21: 0 | N21: 0 | O21: 0 | P21: 0 | Q21: 0 | R21: 0 | S21: 0 | T21: 0 | U21: 0 | V21: 0 | W21: 0 | X21: 0 | Y21: 0 | Z21: 0 | AA21: 0 | AB21: 0 | AC21: 0 | AD21: 0
A22: Gross Loss Adjustments (Dealer level, high PTI, etc.) | B22: -0.3279542 | C22: 0.20210618 | D22: -0.19413065 | E22: 0.046002039 | F22: 0.53224606 | G22: 0.71345069 | H22: -0.27007229 | I22: -0.83970892 | J22: -0.28336522 | K22: 0.096546832 | L22: -0.09886035 | M22: -1.1380306 | N22: -1.0378799 | O22: 0.16751634 | P22: 0.29304325 | Q22: 0.031937011 | R22: 0.88138219 | S22: 1.4130578 | T22: 1.5239239 | U22: 0.72677022 | V22: 0.19579402 | W22: 0.25599345 | X22: 0.60350981 | Y22: 0.50464667 | Z22: 1.0655629 | AA22: 1.3018963 | AB22: 1.96225 | AC22: 2.9079781 | AD22: 2.5590043
A23: Recovery Adjustments excluding LTV (Mileage, vehicle type, etc.) | B23: -1.9652969 | C23: -2.2572101 | D23: -2.386967 | E23: -1.7982709 | F23: -1.2897912 | G23: -1.221421 | H23: -1.3451157 | I23: -1.0354668 | J23: -1.4612729 | K23: -1.3011568 | L23: -1.5164168 | M23: -1.901103 | N23: -2.1482385 | O23: -3.674188 | P23: -4.898855 | Q23: -5.2674839 | R23: -5.0410015 | S23: -4.6319201 | T23: -4.9097476 | U23: -4.2870588 | V23: -3.8100794 | W23: -4.1440132 | X23: -4.0810625 | Y23: -3.1606832 | Z23: -0.76388961 | AA23: -0.53897732 | AB23: -0.11087951 | AC23: 0.55000966 | AD23: 0.81415691
A24: LTV Adjustments | B24: 1.9652969 | C24: 2.2572101 | D24: 2.386967 | E24: 1.7982709 | F24: 1.2897912 | G24: 1.221421 | H24: 1.3451157 | I24: 1.0354668 | J24: 1.4612729 | K24: 1.3011568 | L24: 1.5164168 | M24: 1.901103 | N24: 2.1482385 | O24: 3.674188 | P24: 4.898855 | Q24: 5.2674839 | R24: 5.0410015 | S24: 4.6319201 | T24: 4.9097476 | U24: 4.2870588 | V24: 3.8100794 | W24: 4.1440132 | X24: 4.0810625 | Y24: 3.1606832 | Z24: 0.76388961 | AA24: 0.53897732 | AB24: 0.11087951 | AC24: -0.55000966 | AD24: -0.81415691
A25: RAGU Score | B25: 130.8489 | C25: 136.94149 | D25: 136.60936 | E25: 132.58403 | F25: 131.66528 | G25: 133.61849 | H25: 133.66041 | I25: 131.9641 | J25: 135.16475 | K25: 135.2839 | L25: 134.84716 | M25: 131.76125 | N25: 133.02537 | O25: 136.98472 | P25: 138.29548 | Q25: 139.80987 | R25: 142.15857 | S25: 142.0004 | T25: 142.24495 | U25: 139.75191 | V25: 138.32743 | W25: 140.42956 | X25: 142.15726 | Y25: 140.47562 | Z25: 140.89871 | AA25: 141.93623 | AB25: 142.92613 | AC25: 144.76547 | AD25: 145.42663
A26: LTV | B26: 2.1505904 | C26: 2.2073907 | D26: 2.1097029 | E26: 2.0875659 | F26: 1.9401142 | G26: 1.9433066 | H26: 1.9003889 | I26: 2.0278102 | J26: 1.7335845 | K26: 1.5120635 | L26: 1.6173419 | M26: 1.6867925 | N26: 1.6567267 | O26: 1.6631521 | P26: 1.6853642 | Q26: 1.6837623 | R26: 1.7260875 | S26: 1.5326979 | T26: 1.4887795 | U26: 1.4569228 | V26: 1.480038 | W26: 1.4758266 | X26: 1.4883312 | Y26: 1.4862274 | Z26: 1.484936 | AA26: 1.4354276 | AB26: 1.4298704 | AC26: 1.4260417 | AD26: 1.416614
A28: STG | B28: 2016 | C28: 2017 | D28: 2018 | E28: 2019 | F28: 2020 Q1 | G28: 2020 Q2 | H28: 2020 Q3 | I28: 2020 Q4 | J28: 2021 Q1 | K28: 2021 Q2 | L28: 2021 Q3 | M28: 2021 Q4 | N28: 2022 Q1 | O28: 2022 Q2 | P28: 2022 Q3 | Q28: 2022 Q4 | R28: 2023 Q1 | S28: 2023 Q2 | T28: 2023 Q3 | U28: 2023 Q4 | V28: 2024 Q1 | W28: 2024 Q2 | X28: 2024 Q3 | Y28: 2024 Q4 | Z28: 2025 Q1 | AA28: 2025 Q2 | AB28: 2025 Q3 | AC28: 2025 Q4
A29: Contract Model Score | B29: 129.64201 | C29: 131.65669 | D29: 131.56906 | E29: 129.50527 | F29: 130.0304 | G29: 133.13562 | H29: 135.5242 | I29: 135.28733 | J29: 135.28771 | K29: 135.49901 | L29: 135.05653 | M29: 133.65336 | N29: 134.55 | O29: 136.72731 | P29: 137.27114 | Q29: 138.30195 | R29: 139.23035 | S29: 137.71584 | T29: 138.53984 | U29: 137.48747 | V29: 136.76023 | W29: 137.47802 | X29: 138.54354 | Y29: 137.20905 | Z29: 136.6684 | AA29: 137.94719 | AB29: 138.66055 | AC29: 140.03752 | AD29: 141.71991
A30: Model Score | B30: 0 | C30: 0 | D30: 0 | E30: 0 | F30: 0 | G30: 0 | H30: 0 | I30: 0 | J30: 0 | K30: 0 | L30: 0 | M30: 0 | N30: 0 | O30: 0 | P30: 0 | Q30: 0 | R30: 0 | S30: 0 | T30: 0 | U30: 0 | V30: 0 | W30: 0 | X30: 0 | Y30: 0 | Z30: 0 | AA30: 0 | AB30: 0 | AC30: 0 | AD30: 0
A31: Gross Loss Adjustments (Dealer level, high PTI, etc.) | B31: 0.55168785 | C31: 0.53745688 | D31: 0.47283336 | E31: 0.26299826 | F31: -0.17705346 | G31: -0.23517459 | H31: 0.1178712 | I31: 0.041467995 | J31: 0.88577009 | K31: 1.0419584 | L31: 0.74064638 | M31: 0.42910054 | N31: -0.22394537 | O31: -0.019170193 | P31: -0.41911667 | Q31: 0.094722292 | R31: -0.06193691 | S31: 0.13109853 | T31: 1.1009589 | U31: 0.80118596 | V31: 1.1138993 | W31: 1.8836723 | X31: 2.1660502 | Y31: 2.1477406 | Z31: 2.2898541 | AA31: 2.0219847 | AB31: 2.3634477 | AC31: 3.1078509 | AD31: 2.787071
A32: Recovery Adjustments excluding LTV (Mileage, vehicle type, etc.) | B32: 0.12094838 | C32: 0.72195889 | D32: 0.25083049 | E32: 0.20393168 | F32: 0.11503546 | G32: 0.084406228 | H32: 0.29693969 | I32: 0.42110284 | J32: 0.31989764 | K32: 0.22431458 | L32: 0.23964494 | M32: 0.35702916 | N32: 0.26645598 | O32: -1.8569201 | P32: -2.5305798 | Q32: -2.4101186 | R32: -2.26922 | S32: -1.2760946 | T32: -1.0852773 | U32: -0.77288919 | V32: -0.93816727 | W32: -0.41542577 | X32: -0.10584601 | Y32: 0.20872339 | Z32: 2.2774923 | AA32: 2.9990137 | AB32: 2.9834456 | AC32: 3.4583655 | AD32: 3.7723243
A33: LTV Adjustments | B33: -0.12094838 | C33: -0.72195889 | D33: -0.25083049 | E33: -0.20393168 | F33: -0.11503546 | G33: -0.084406228 | H33: -0.29693969 | I33: -0.42110284 | J33: -0.31989764 | K33: -0.22431458 | L33: -0.23964494 | M33: -0.35702916 | N33: -0.26645598 | O33: 1.8569201 | P33: 2.5305798 | Q33: 2.4101186 | R33: 2.26922 | S33: 1.2760946 | T33: 1.0852773 | U33: 0.77288919 | V33: 0.93816727 | W33: 0.41542577 | X33: 0.10584601 | Y33: -0.20872339 | Z33: -2.2774923 | AA33: -2.9990137 | AB33: -2.9834456 | AC33: -3.4583655 | AD33: -3.7723243
A34: RAGU Score | B34: 130.1937 | C34: 132.19415 | D34: 132.0419 | E34: 129.76827 | F34: 129.85334 | G34: 132.90045 | H34: 135.64207 | I34: 135.32879 | J34: 136.17348 | K34: 136.54097 | L34: 135.79718 | M34: 134.08246 | N34: 134.32605 | O34: 136.70814 | P34: 136.85203 | Q34: 138.39667 | R34: 139.16841 | S34: 137.84694 | T34: 139.6408 | U34: 138.28866 | V34: 137.87413 | W34: 139.3617 | X34: 140.70959 | Y34: 139.35679 | Z34: 138.95825 | AA34: 139.96918 | AB34: 141.02399 | AC34: 143.14537 | AD34: 144.50698
A35: LTV | B35: 1.9469756 | C35: 1.9399714 | D35: 1.9874143 | E35: 2.0859967 | F35: 2.0790161 | G35: 2.1024128 | H35: 1.8209696 | I35: 1.8042176 | J35: 1.7006093 | K35: 1.5705129 | L35: 1.5917275 | M35: 1.6099823 | N35: 1.5700251 | O35: 1.519388 | P35: 1.5322192 | Q35: 1.4830261 | R35: 1.4792593 | S35: 1.5231119 | T35: 1.4212296 | U35: 1.4249082 | V35: 1.5339126 | W35: 1.4939963 | X35: 1.4531544 | Y35: 1.4626914 | Z35: 1.482253 | AA35: 1.4273906 | AB35: 1.431232 | AC35: 1.4246205 | AD35: 1.5008016
A37: ENT | F37: 2020 Q1 | G37: 2020 Q2 | H37: 2020 Q3 | I37: 2020 Q4 | J37: 2021 Q1 | K37: 2021 Q2 | L37: 2021 Q3 | M37: 2021 Q4 | N37: 2022 Q1 | O37: 2022 Q2 | P37: 2022 Q3 | Q37: 2022 Q4 | R37: 2023 Q1 | S37: 2023 Q2 | T37: 2023 Q3 | U37: 2023 Q4 | V37: 2024 Q1 | W37: 2024 Q2 | X37: 2024 Q3 | Y37: 2024 Q4 | Z37: 2025 Q1 | AA37: 2025 Q2 | AB37: 2025 Q3 | AC37: 2025 Q4
A38: Contract Model Score | F38: 132.38307 | G38: 133.22864 | H38: 136.30166 | I38: 135.38242 | J38: 133.8357 | K38: 131.8749 | L38: 131.13569 | M38: 129.4723 | N38: 129.34473 | O38: 131.45349 | P38: 131.71553 | Q38: 131.25851 | R38: 132.73385 | S38: 133.4422 | T38: 133.76755 | U38: 135.31367 | V38: 136.17456 | W38: 136.8171 | X38: 136.69241 | Y38: 134.94875 | Z38: 134.57148 | AA38: 136.41792 | AB38: 137.0063 | AC38: 137.20721 | AD38: 139.6199
A39: Model Score | F39: 0 | G39: 0 | H39: 0 | I39: 0 | J39: 0 | K39: 0 | L39: 0 | M39: 0 | N39: 0 | O39: 0 | P39: 0 | Q39: 0 | R39: 0 | S39: 0 | T39: 0 | U39: 0 | V39: 0 | W39: 0 | X39: 0 | Y39: 0 | Z39: 0 | AA39: 0 | AB39: 0 | AC39: 0 | AD39: 0
A40: Gross Loss Adjustments (Dealer level, high PTI, etc.) | F40: -0.32633691 | G40: -0.24531305 | H40: -0.51478673 | I40: -1.7810736 | J40: -1.1663098 | K40: -1.3644154 | L40: -1.5978945 | M40: -1.4141434 | N40: -0.94903172 | O40: -1.1360738 | P40: -1.6427646 | Q40: -1.4880232 | R40: -1.7934902 | S40: -1.2033484 | T40: -0.91964396 | U40: -0.029048574 | V40: -0.40067639 | W40: -0.30823236 | X40: -0.49476074 | Y40: 0.0030303055 | Z40: -0.11906764 | AA40: 0.49512343 | AB40: 0.49812475 | AC40: 1.8580984 | AD40: 2.1306717
A41: Recovery Adjustments excluding LTV (Mileage, vehicle type, etc.) | F41: -0.027081459 | G41: 0.12046618 | H41: 0.12293285 | I41: 0.1395859 | J41: 0.11321541 | K41: -0.13067199 | L41: -0.5798504 | M41: -0.82793303 | N41: -1.1634258 | O41: -1.1529434 | P41: -1.4743423 | Q41: -1.6760795 | R41: -1.7055951 | S41: -1.5804189 | T41: -1.606686 | U41: -1.5128964 | V41: -1.6522724 | W41: -1.413304 | X41: -1.0054698 | Y41: -0.33440007 | Z41: 0.16022976 | AA41: -0.076335538 | AB41: -0.036450372 | AC41: 0.22347571 | AD41: 0.32558553
A42: LTV Adjustments | F42: 0.027081459 | G42: -0.12046618 | H42: -0.12293285 | I42: -0.1395859 | J42: -0.11321541 | K42: 0.13067199 | L42: 0.5798504 | M42: 0.82793303 | N42: 1.1634258 | O42: 1.1529434 | P42: 1.4743423 | Q42: 1.6760795 | R42: 1.7055951 | S42: 1.5804189 | T42: 1.606686 | U42: 1.5128964 | V42: 1.6522724 | W42: 1.413304 | X42: 1.0054698 | Y42: 0.33440007 | Z42: -0.16022976 | AA42: 0.076335538 | AB42: 0.036450372 | AC42: -0.22347571 | AD42: -0.32558553
A43: RAGU Score | F43: 132.05673 | G43: 132.98333 | H43: 135.78687 | I43: 133.60135 | J43: 132.66939 | K43: 130.51048 | L43: 129.5378 | M43: 128.05816 | N43: 128.3957 | O43: 130.31741 | P43: 130.07277 | Q43: 129.77049 | R43: 130.94036 | S43: 132.23885 | T43: 132.84791 | U43: 135.28462 | V43: 135.77389 | W43: 136.50887 | X43: 136.19765 | Y43: 134.95178 | Z43: 134.45241 | AA43: 136.91305 | AB43: 137.50442 | AC43: 139.06531 | AD43: 141.75057
A44: LTV | F44: 1.4714253 | G44: 1.447645 | H44: 1.2670158 | I44: 1.3699695 | J44: 1.3586296 | K44: 1.2606936 | L44: 1.3395636 | M44: 1.3730102 | N44: 1.3886269 | O44: 1.3453919 | P44: 1.2914488 | Q44: 1.3464781 | R44: 1.3778236 | S44: 1.3216275 | T44: 1.2590349 | U44: 1.3089899 | V44: 1.3236306 | W44: 1.3018836 | X44: 1.3184884 | Y44: 1.3477314 | Z44: 1.3381453 | AA44: 1.3094736 | AB44: 1.310731 | AC44: 1.325224 | AD44: 1.3525404
A46: nonKMXENT | B46: 2016 | C46: 2017 | D46: 2018 | E46: 2019 | F46: 2020 Q1 | G46: 2020 Q2 | H46: 2020 Q3 | I46: 2020 Q4 | J46: 2021 Q1 | K46: 2021 Q2 | L46: 2021 Q3 | M46: 2021 Q4 | N46: 2022 Q1 | O46: 2022 Q2 | P46: 2022 Q3 | Q46: 2022 Q4 | R46: 2023 Q1 | S46: 2023 Q2 | T46: 2023 Q3 | U46: 2023 Q4 | V46: 2024 Q1 | W46: 2024 Q2 | X46: 2024 Q3 | Y46: 2024 Q4 | Z46: 2025 Q1 | AA46: 2025 Q2 | AB46: 2025 Q3 | AC46: 2025 Q4
A47: Contract Model Score | B47: 130.11008 | C47: 132.58762 | D47: 132.51897 | E47: 130.52533 | F47: 130.9115 | G47: 133.56818 | H47: 135.32872 | I47: 135.00452 | J47: 135.33466 | K47: 135.42705 | L47: 135.14249 | M47: 133.58237 | N47: 134.24542 | O47: 136.54105 | P47: 137.34925 | Q47: 138.63774 | R47: 139.45713 | S47: 138.75195 | T47: 138.87581 | U47: 138.31101 | V47: 137.53278 | W47: 138.76369 | X47: 140.0747 | Y47: 138.61957 | Z47: 138.13778 | AA47: 139.2205 | AB47: 139.61004 | AC47: 140.56262 | AD47: 141.88293
A48: Model Score | B48: 0.15460624 | C48: 0.095483442 | D48: 0.031115149 | E48: 0.0060876943 | F48: -0.0029307051 | G48: 0.0011452093 | H48: 0.0020306833 | I48: 0.0068054691 | J48: 0.0002510195 | K48: 3.5664492e-05 | L48: 0.0014876761 | M48: -0.0004078232 | N48: -0.00073390995 | O48: -0.0020528235 | P48: -0.0023160012 | Q48: 0.0038331118 | R48: -0.0026252353 | S48: 0.013029093 | T48: -0.017258762 | U48: -0.00033238216 | V48: -0.013738767 | W48: -0.01194578 | X48: -0.0008873842 | Y48: -0.0075405378 | Z48: -0.015620384 | AA48: -0.019234526 | AB48: -0.0075126623 | AC48: 0.0030028891 | AD48: 0.018497234
A49: Gross Loss Adjustments (Dealer level, high PTI, etc.) | B49: 0.25888132 | C49: 0.55879279 | D49: 0.56380279 | E49: 0.29260346 | F49: -0.34536813 | G49: -0.16919144 | H49: -0.27250734 | I49: -0.2097614 | J49: 0.4826877 | K49: 0.36739133 | L49: 0.15946083 | M49: -0.21753361 | N49: -0.37477073 | O49: 0.18302651 | P49: 0.21582075 | Q49: 0.27093986 | R49: 0.53023053 | S49: 0.83338682 | T49: 1.059104 | U49: 0.70732604 | V49: 0.6198774 | W49: 1.0663236 | X49: 1.3428172 | Y49: 1.3084092 | Z49: 1.7666816 | AA49: 1.8393361 | AB49: 2.4284818 | AC49: 2.9616526 | AD49: 2.5431882
A50: Recovery Adjustments excluding LTV (Mileage, vehicle type, etc.) | B50: -0.6406326 | C50: -0.027592127 | D50: -0.05850486 | E50: 0.15539393 | F50: 0.050620376 | G50: -0.19093385 | H50: -0.11925912 | I50: -0.038747037 | J50: -0.2874441 | K50: -0.35890708 | L50: -0.48173703 | M50: -0.74141052 | N50: -0.94122486 | O50: -2.6750432 | P50: -3.7926507 | Q50: -3.975755 | R50: -3.5962791 | S50: -3.0782048 | T50: -3.2617989 | U50: -2.7191865 | V50: -2.5643257 | W50: -2.5281509 | X50: -2.2985998 | Y50: -1.8283316 | Z50: 0.47644467 | AA50: 0.85227244 | AB50: 1.1756519 | AC50: 1.6895043 | AD50: 1.9548088
A51: LTV Adjustments | B51: 0.6406326 | C51: 0.027592127 | D51: 0.05850486 | E51: -0.15539393 | F51: -0.050620376 | G51: 0.19093385 | H51: 0.11925912 | I51: 0.038747037 | J51: 0.2874441 | K51: 0.35890708 | L51: 0.48173703 | M51: 0.74141052 | N51: 0.94122486 | O51: 2.6750432 | P51: 3.7926507 | Q51: 3.975755 | R51: 3.5962791 | S51: 3.0782048 | T51: 3.2617989 | U51: 2.7191865 | V51: 2.5643257 | W51: 2.5281509 | X51: 2.2985998 | Y51: 1.8283316 | Z51: -0.47644467 | AA51: -0.85227244 | AB51: -1.1756519 | AC51: -1.6895043 | AD51: -1.9548088
A52: RAGU Score | B52: 130.52357 | C52: 133.2419 | D52: 133.11388 | E52: 130.82402 | F52: 130.56321 | G52: 133.40013 | H52: 135.05824 | I52: 134.80156 | J52: 135.8176 | K52: 135.79448 | L52: 135.30344 | M52: 133.36443 | N52: 133.86992 | O52: 136.72203 | P52: 137.56275 | Q52: 138.91251 | R52: 139.98473 | S52: 139.59837 | T52: 139.91766 | U52: 139.01801 | V52: 138.13892 | W52: 139.81807 | X52: 141.41663 | Y52: 139.92043 | Z52: 139.88884 | AA52: 141.0406 | AB52: 142.03101 | AC52: 143.52728 | AD52: 144.44461
A53: LTV | B53: 1.9870402 | C53: 1.9345474 | D53: 1.9519859 | E53: 1.9473526 | F53: 1.9011611 | G53: 1.9285203 | H53: 1.7380756 | I53: 1.802961 | J53: 1.6728013 | K53: 1.4960642 | L53: 1.5544397 | M53: 1.6040944 | N53: 1.581687 | O53: 1.5829599 | P53: 1.6107491 | Q53: 1.6098502 | R53: 1.6411686 | S53: 1.5450514 | T53: 1.4803867 | U53: 1.4746229 | V53: 1.5286365 | W53: 1.4985573 | X53: 1.4793897 | Y53: 1.4841873 | Z53: 1.4931241 | AA53: 1.4519153 | AB53: 1.4523362 | AC53: 1.4444001 | AD53: 1.4740749
A55: KMX | B55: 2016 | C55: 2017 | D55: 2018 | E55: 2019 | F55: 2020 Q1 | G55: 2020 Q2 | H55: 2020 Q3 | I55: 2020 Q4 | J55: 2021 Q1 | K55: 2021 Q2 | L55: 2021 Q3 | M55: 2021 Q4 | N55: 2022 Q1 | O55: 2022 Q2 | P55: 2022 Q3 | Q55: 2022 Q4 | R55: 2023 Q1 | S55: 2023 Q2 | T55: 2023 Q3 | U55: 2023 Q4 | V55: 2024 Q1 | W55: 2024 Q2 | X55: 2024 Q3 | Y55: 2024 Q4 | Z55: 2025 Q1 | AA55: 2025 Q2 | AB55: 2025 Q3 | AC55: 2025 Q4
A56: Contract Model Score | B56: 136.56433 | C56: 139.10044 | D56: 137.77978 | E56: 136.87785 | F56: 135.86332 | G56: 138.37204 | H56: 138.7895 | I56: 136.9589 | J56: 135.46433 | K56: 135.73801 | L56: 134.50372 | M56: 133.19297 | N56: 133.26474 | O56: 134.70115 | P56: 136.05827 | Q56: 138.3337 | R56: 140.09672 | S56: 140.65864 | T56: 140.50459 | U56: 140.56078 | V56: 139.56825 | W56: 140.43212 | X56: 139.88511 | Y56: 139.76782 | Z56: 139.70877 | AA56: 139.86672 | AB56: 139.91791 | AC56: 140.94205 | AD56: 141.7731
A57: Model Score | B57: 0 | C57: 0 | D57: 0 | E57: 0 | F57: 0 | G57: 0 | H57: 0 | I57: 0 | J57: 0 | K57: 0 | L57: 0 | M57: 0 | N57: 0 | O57: 0 | P57: 0 | Q57: 0 | R57: 0 | S57: 0 | T57: 0 | U57: 0 | V57: 0 | W57: 0 | X57: 0 | Y57: 0 | Z57: 0 | AA57: 0 | AB57: 0 | AC57: 0 | AD57: 0
A58: Gross Loss Adjustments (Dealer level, high PTI, etc.) | B58: 3.4917016 | C58: 3.6344937 | D58: 3.2436434 | E58: 3.1758138 | F58: 3.1452339 | G58: 3.5295605 | H58: 3.3378406 | I58: 2.7285832 | J58: 2.3514675 | K58: 2.1369615 | L58: 1.732327 | M58: 1.1938497 | N58: 1.0375439 | O58: 1.1793371 | P58: 1.4351667 | Q58: 2.1262764 | R58: 2.675906 | S58: 2.9453693 | T58: 2.9477453 | U58: 3.1552479 | V58: 3.6291642 | W58: 4.1971459 | X58: 3.9955369 | Y58: 3.38239 | Z58: 2.398141 | AA58: 3.1916381 | AB58: 3.7761841 | AC58: 4.2259389 | AD58: 5.9003827
A59: Recovery Adjustments excluding LTV (Mileage, vehicle type, etc.) | B59: 0.3934361 | C59: 0.19052999 | D59: -0.015150945 | E59: -0.10624561 | F59: -1.2277111 | G59: -0.64988316 | H59: -1.1113617 | I59: -1.5738104 | J59: -1.0316844 | K59: 0.083963277 | L59: 0.85630615 | M59: 0.59321643 | N59: 0.94876595 | O59: 0.8433667 | P59: 0.67196722 | Q59: 0.06956567 | R59: -0.34499788 | S59: 0.36247147 | T59: 0.38762108 | U59: 0.37544466 | V59: 0.13457489 | W59: 1.3938032 | X59: 0.97466563 | Y59: 0.99995508 | Z59: 1.6132632 | AA59: 1.8149547 | AB59: 1.5444742 | AC59: 1.3621228 | AD59: 1.6768032
A60: LTV Adjustments | B60: -0.3934361 | C60: -0.19052999 | D60: 0.015150945 | E60: 0.10624561 | F60: 1.2277111 | G60: 0.64988316 | H60: 1.1113617 | I60: 1.5738104 | J60: 1.0316844 | K60: -0.083963277 | L60: -0.85630615 | M60: -0.59321643 | N60: -0.94876595 | O60: -0.8433667 | P60: -0.67196722 | Q60: -0.06956567 | R60: 0.34499788 | S60: -0.36247147 | T60: -0.38762108 | U60: -0.37544466 | V60: -0.13457489 | W60: -1.3938032 | X60: -0.97466563 | Y60: -0.99995508 | Z60: -1.6132632 | AA60: -1.8149547 | AB60: -1.5444742 | AC60: -1.3621228 | AD60: -1.6768032
A61: RAGU Score | B61: 140.05603 | C61: 142.73494 | D61: 141.02342 | E61: 140.05366 | F61: 139.00856 | G61: 141.9016 | H61: 142.12734 | I61: 139.68749 | J61: 137.81579 | K61: 137.87497 | L61: 136.23605 | M61: 134.38682 | N61: 134.30229 | O61: 135.88049 | P61: 137.49343 | Q61: 140.45997 | R61: 142.77262 | S61: 143.60401 | T61: 143.45234 | U61: 143.71603 | V61: 143.19741 | W61: 144.62926 | X61: 143.88065 | Y61: 143.15021 | Z61: 142.10691 | AA61: 143.05836 | AB61: 143.69409 | AC61: 145.16799 | AD61: 147.67348
A62: LTV | B62: 1.5867325 | C62: 1.5718898 | D62: 1.5856332 | E62: 1.6091822 | F62: 1.7019822 | G62: 1.7371846 | H62: 1.5806217 | I62: 1.7201942 | J62: 1.5765564 | K62: 1.4305316 | L62: 1.4803988 | M62: 1.4915802 | N62: 1.6111707 | O62: 1.5508732 | P62: 1.6203987 | Q62: 1.7308102 | R62: 1.7578933 | S62: 1.6625227 | T62: 1.8305188 | U62: 1.9379759 | V62: 1.8724777 | W62: 1.6407546 | X62: 1.686652 | Y62: 1.6796213 | Z62: 1.6311486 | AA62: 1.6044821 | AB62: 1.6159232 | AC62: 1.6042545 | AD62: 1.5711394
A64: POS | B64: 2016 | C64: 2017 | D64: 2018 | E64: 2019 | F64: 2020 Q1 | G64: 2020 Q2 | H64: 2020 Q3 | I64: 2020 Q4 | J64: 2021 Q1 | K64: 2021 Q2 | L64: 2021 Q3 | M64: 2021 Q4 | N64: 2022 Q1 | O64: 2022 Q2 | P64: 2022 Q3 | Q64: 2022 Q4 | R64: 2023 Q1 | S64: 2023 Q2 | T64: 2023 Q3 | U64: 2023 Q4 | V64: 2024 Q1 | W64: 2024 Q2 | X64: 2024 Q3 | Y64: 2024 Q4 | Z64: 2025 Q1 | AA64: 2025 Q2 | AB64: 2025 Q3 | AC64: 2025 Q4
A65: Contract Model Score | B65: 134.00914 | C65: 137.09023 | D65: 136.17908 | E65: 135.22818 | F65: 134.22836 | G65: 136.51598 | H65: 137.70277 | I65: 136.32022 | J65: 135.22491 | K65: 134.98869 | L65: 134.18994 | M65: 132.81075 | N65: 133.03763 | O65: 134.82195 | P65: 135.90569 | Q65: 137.14226 | R65: 138.55531 | S65: 138.99052 | T65: 139.07412 | U65: 138.9461 | V65: 138.34968 | W65: 139.22436 | X65: 139.53563 | Y65: 138.6092 | Z65: 138.29936 | AA65: 139.10189 | AB65: 139.41596 | AC65: 140.32 | AD65: 141.5783
A66: Model Score | B66: -2.3913398 | C66: -0.81249597 | D66: -0.35223323 | E66: -0.54820583 | F66: -0.49570355 | G66: -0.43749234 | H66: -0.24180603 | I66: -0.10293575 | J66: -0.005799583 | K66: 0.0515173 | L66: 0.057742199 | M66: 0.063759854 | N66: 0.015662878 | O66: 0.010457787 | P66: 0.027948346 | Q66: 0.039894369 | R66: 0.11432537 | S66: 0.16263366 | T66: -0.68939298 | U66: -0.53006289 | V66: -0.022763943 | W66: -0.026229776 | X66: 0.0020181515 | Y66: 0.0073049267 | Z66: 0.027926545 | AA66: 0.0158323 | AB66: 0.0019141889 | AC66: 0.0077344991 | AD66: 0.020116011
A67: Gross Loss Adjustments (Dealer level, high PTI, etc.) | B67: 0.95326653 | C67: 2.2816265 | D67: 2.2429101 | E67: 2.1765429 | F67: 1.5454606 | G67: 1.7853256 | H67: 1.8240662 | I67: 1.3598818 | J67: 1.403721 | K67: 1.0279504 | L67: 0.80768064 | M67: 0.43135913 | N67: 0.24189939 | O67: 0.63364187 | P67: 0.73883875 | Q67: 1.0893708 | R67: 1.5427354 | S67: 1.8915435 | T67: 1.4005346 | U67: 1.3610869 | V67: 1.9480105 | W67: 2.2011936 | X67: 2.3551872 | Y67: 2.0688417 | Z67: 1.7798419 | AA67: 2.2435917 | AB67: 2.8007235 | AC67: 3.4366692 | AD67: 4.5767022
A68: Recovery Adjustments excluding LTV (Mileage, vehicle type, etc.) | B68: -0.39529814 | C68: 0.1049153 | D68: -0.023979318 | E68: -0.0084275997 | F68: -0.64086922 | G68: -0.38805367 | H68: -0.66430204 | I68: -0.92274312 | J68: -0.67772537 | K68: -0.082923463 | L68: 0.26555042 | M68: 0.013662937 | N68: -0.016340123 | O68: -0.35240649 | P68: -0.82338669 | Q68: -1.1096588 | R68: -1.0733045 | S68: -0.56627512 | T68: -1.305432 | U68: -1.3707869 | V68: -1.0700978 | W68: -0.66381528 | X68: -0.51796559 | Y68: -0.28709829 | Z68: 0.96709908 | AA68: 1.1693674 | AB68: 1.2083615 | AC68: 1.3601029 | AD68: 1.6327792
A69: LTV Adjustments | B69: 0.39529814 | C69: -0.1049153 | D69: 0.023979318 | E69: 0.0084275997 | F69: 0.64086922 | G69: 0.38805367 | H69: 0.66430204 | I69: 0.92274312 | J69: 0.67772537 | K69: 0.082923463 | L69: -0.26555042 | M69: -0.013662937 | N69: 0.016340123 | O69: 0.35240649 | P69: 0.82338669 | Q69: 1.1096588 | R69: 1.0733045 | S69: 0.56627512 | T69: 1.305432 | U69: 1.3707869 | V69: 1.0700978 | W69: 0.66381528 | X69: 0.51796559 | Y69: 0.28709829 | Z69: -0.96709908 | AA69: -1.1693674 | AB69: -1.2083615 | AC69: -1.3601029 | AD69: -1.6327792
A70: RAGU Score | B70: 132.57107 | C70: 138.55936 | D70: 138.06976 | E70: 136.85652 | F70: 135.27812 | G70: 137.86382 | H70: 139.28503 | I70: 137.57717 | J70: 136.62283 | K70: 136.06816 | L70: 135.05536 | M70: 133.30587 | N70: 133.29519 | O70: 135.46605 | P70: 136.67248 | Q70: 138.27153 | R70: 140.21237 | S70: 141.0447 | T70: 139.78527 | U70: 139.77712 | V70: 140.27493 | W70: 141.39932 | X70: 141.89284 | Y70: 140.68534 | Z70: 140.10713 | AA70: 141.36131 | AB70: 142.21859 | AC70: 143.7644 | AD70: 146.17511
A71: LTV | B71: 1.9010572 | C71: 1.7314071 | D71: 1.7224403 | E71: 1.7236215 | F71: 1.7517667 | G71: 1.7698517 | H71: 1.5979277 | I71: 1.7028062 | J71: 1.5736175 | K71: 1.4252228 | L71: 1.4840807 | M71: 1.5134914 | N71: 1.5684678 | O71: 1.5358434 | P71: 1.5803796 | Q71: 1.6375647 | R71: 1.6715236 | S71: 1.5862494 | T71: 1.5770209 | U71: 1.5927629 | V71: 1.6672513 | W71: 1.5318505 | X71: 1.5561983 | Y71: 1.5539231 | Z71: 1.5332692 | AA71: 1.4987499 | AB71: 1.509268 | AC71: 1.5070089 | AD71: 1.52212

Sheet Data Tables (M)
A1: AN | B1: 2016 | C1: 2017 | D1: 2018 | E1: 2019 | F1: 2020 M01 | G1: 2020 M02 | H1: 2020 M03 | I1: 2020 M04 | J1: 2020 M05 | K1: 2020 M06 | L1: 2020 M07 | M1: 2020 M08 | N1: 2020 M09 | O1: 2020 M10 | P1: 2020 M11 | Q1: 2020 M12 | R1: 2021 M01 | S1: 2021 M02 | T1: 2021 M03 | U1: 2021 M04 | V1: 2021 M05 | W1: 2021 M06 | X1: 2021 M07 | Y1: 2021 M08 | Z1: 2021 M09 | AA1: 2021 M10 | AB1: 2021 M11 | AC1: 2021 M12 | AD1: 2022 M01 | AE1: 2022 M02 | AF1: 2022 M03 | AG1: 2022 M04 | AH1: 2022 M05 | AI1: 2022 M06 | AJ1: 2022 M07 | AK1: 2022 M08 | AL1: 2022 M09 | AM1: 2022 M10 | AN1: 2022 M11 | AO1: 2022 M12 | AP1: 2023 M01 | AQ1: 2023 M02 | AR1: 2023 M03 | AS1: 2023 M04 | AT1: 2023 M05 | AU1: 2023 M06 | AV1: 2023 M07 | AW1: 2023 M08 | AX1: 2023 M09 | AY1: 2023 M10 | AZ1: 2023 M11 | BA1: 2023 M12 | BB1: 2024 M01 | BC1: 2024 M02 | BD1: 2024 M03 | BE1: 2024 M04 | BF1: 2024 M05 | BG1: 2024 M06 | BH1: 2024 M07 | BI1: 2024 M08 | BJ1: 2024 M09 | BK1: 2024 M10 | BL1: 2024 M11 | BM1: 2024 M12 | BN1: 2025 M01 | BO1: 2025 M02 | BP1: 2025 M03 | BQ1: 2025 M04 | BR1: 2025 M05 | BS1: 2025 M06 | BT1: 2025 M07 | BU1: 2025 M08 | BV1: 2025 M09 | BW1: 2025 M10
A2: Contract Model Score | B2: 130.07638 | C2: 132.82981 | D2: 132.99275 | E2: 132.10946 | F2: 132.25849 | G2: 131.7487 | H2: 131.54256 | I2: 132.18971 | J2: 133.74885 | K2: 134.65103 | L2: 134.80159 | M2: 135.32143 | N2: 135.83703 | O2: 135.63732 | P2: 136.60482 | Q2: 135.25698 | R2: 135.3746 | S2: 135.08197 | T2: 134.04131 | U2: 134.85769 | V2: 135.429 | W2: 135.23156 | X2: 135.14534 | Y2: 136.06332 | Z2: 134.88069 | AA2: 134.92486 | AB2: 133.43768 | AC2: 134.76745 | AD2: 134.0616 | AE2: 133.46247 | AF2: 134.42836 | AG2: 135.32861 | AH2: 136.27415 | AI2: 136.14209 | AJ2: 136.0539 | AK2: 136.18039 | AL2: 136.20134 | AM2: 136.40054 | AN2: 137.34655 | AO2: 136.56024 | AP2: 137.35433 | AQ2: 136.77652 | AR2: 136.20403 | AS2: 137.32635 | AT2: 136.6899 | AU2: 136.75897 | AV2: 135.57234 | AW2: 136.72241 | AX2: 136.99429 | AY2: 137.341 | AZ2: 136.64692 | BA2: 137.19306 | BB2: 136.53374 | BC2: 136.58082 | BD2: 136.14985 | BE2: 137.03472 | BF2: 137.23467 | BG2: 137.10824 | BH2: 137.80106 | BI2: 138.46466 | BJ2: 138.07105 | BK2: 137.16197 | BL2: 136.31058 | BM2: 136.80042 | BN2: 136.83707 | BO2: 137.09434 | BP2: 136.69472 | BQ2: 137.57439 | BR2: 138.31007 | BS2: 138.27075 | BT2: 138.46662 | BU2: 138.34761 | BV2: 138.86903 | BW2: 138.81179 | BX2: 138.98924 | BY2: 140.30771 | BZ2: 141.16539
A3: Model Score | B3: 0 | C3: 0 | D3: 0 | E3: 0 | F3: 0 | G3: 0 | H3: 0 | I3: 0 | J3: 0 | K3: 0 | L3: 0 | M3: 0 | N3: 0 | O3: 0 | P3: 0 | Q3: 0 | R3: 0 | S3: 0 | T3: 0 | U3: 0 | V3: 0 | W3: 0 | X3: 0 | Y3: 0 | Z3: 0 | AA3: 0 | AB3: 0 | AC3: 0 | AD3: 0 | AE3: 0 | AF3: 0 | AG3: 0 | AH3: 0 | AI3: 0 | AJ3: 0 | AK3: 0 | AL3: 0 | AM3: 0 | AN3: 0 | AO3: 0 | AP3: 0 | AQ3: 0 | AR3: 0 | AS3: 0 | AT3: 0 | AU3: 0 | AV3: 0 | AW3: 0 | AX3: 0 | AY3: 0 | AZ3: 0 | BA3: 0 | BB3: 0 | BC3: 0 | BD3: 0 | BE3: 0 | BF3: 0 | BG3: 0 | BH3: 0 | BI3: 0 | BJ3: 0 | BK3: 0 | BL3: 0 | BM3: 0 | BN3: 0 | BO3: 0 | BP3: 0 | BQ3: 0 | BR3: 0 | BS3: 0 | BT3: 0 | BU3: 0 | BV3: 0 | BW3: 0 | BX3: 0 | BY3: 0 | BZ3: 0
A4: Gross Loss Adjustments (Dealer level, high PTI, etc.) | B4: 0.36824634 | C4: 0.64268496 | D4: 0.73760946 | E4: 0.54113333 | F4: 0.57165568 | G4: 0.69223442 | H4: 0.66883208 | I4: 0.12577 | J4: 0.64293784 | K4: 0.6643347 | L4: -0.17959572 | M4: -0.22631531 | N4: -0.17144155 | O4: 0.44803125 | P4: 0.38710147 | Q4: -0.039322186 | R4: 0.39465574 | S4: 0.46579813 | T4: 0.63813941 | U4: 0.87198097 | V4: 0.41573185 | W4: 0.22462946 | X4: 0.28258114 | Y4: 0.6200191 | Z4: 0.80979511 | AA4: 0.79932473 | AB4: 0.14845733 | AC4: 0.37063471 | AD4: 0.56398924 | AE4: 0.7861633 | AF4: 1.0561092 | AG4: 0.94025801 | AH4: 1.0571489 | AI4: 0.39892033 | AJ4: 0.640879 | AK4: 1.0413283 | AL4: 0.91169964 | AM4: 0.76213814 | AN4: 0.23943546 | AO4: 1.7098234 | AP4: 0.09158671 | AQ4: 0.80965966 | AR4: 0.78264112 | AS4: 0.50236752 | AT4: 0.94864848 | AU4: 0.97152034 | AV4: 0.28283895 | AW4: 0.28028629 | AX4: 0.61430211 | AY4: 0.85373043 | AZ4: -0.045155873 | BA4: 0.34233267 | BB4: 0.67568085 | BC4: 0.27299915 | BD4: 0.7432554 | BE4: 0.74268419 | BF4: 1.1666023 | BG4: 1.2551317 | BH4: 0.92266646 | BI4: 0.68851694 | BJ4: 0.83186138 | BK4: 1.1778896 | BL4: 1.2394094 | BM4: 1.5142589 | BN4: 1.6919738 | BO4: 1.9706517 | BP4: 1.9634127 | BQ4: 2.4180891 | BR4: 2.5340921 | BS4: 2.7462237 | BT4: 3.1017721 | BU4: 3.2140242 | BV4: 2.9831598 | BW4: 3.4666306 | BX4: 3.3749094 | BY4: 3.829675 | BZ4: 2.4651877
A5: Recovery Adjustments excluding LTV (Mileage, vehicle type, etc.) | B5: -0.42373409 | C5: -0.48874114 | D5: -0.32970888 | E5: -0.46809162 | F5: -0.26081624 | G5: -0.55894617 | H5: -0.40693332 | I5: -1.0451672 | J5: -0.91310193 | K5: -0.59544101 | L5: -0.59041094 | M5: -0.34566215 | N5: -0.35413793 | O5: -0.052312778 | P5: -0.099655718 | Q5: 0.046838666 | R5: -0.0068603896 | S5: -0.31879126 | T5: -0.68157655 | U5: -0.79987972 | V5: -0.51695191 | W5: -0.64621622 | X5: -0.76762862 | Y5: -0.60930554 | Z5: -0.51578181 | AA5: -0.97236119 | AB5: -1.0343443 | AC5: -0.82191547 | AD5: -1.3744011 | AE5: -1.3925048 | AF5: -1.455756 | AG5: -2.3625146 | AH5: -2.3686331 | AI5: -3.2032867 | AJ5: -3.3612438 | AK5: -3.3852506 | AL5: -3.9176595 | AM5: -3.8737766 | AN5: -4.5025 | AO5: -3.0821413 | AP5: -3.1391933 | AQ5: -3.5031374 | AR5: -2.7888434 | AS5: -1.3751811 | AT5: -2.6029269 | AU5: -3.1349278 | AV5: -2.9838855 | AW5: -2.3454054 | AX5: -2.776363 | AY5: -3.1919903 | AZ5: -2.4842227 | BA5: -1.6979352 | BB5: -2.1031094 | BC5: -2.0066516 | BD5: -2.1427992 | BE5: -2.1275859 | BF5: -1.7907941 | BG5: -1.4442518 | BH5: -0.67312087 | BI5: -1.5518085 | BJ5: -1.6476181 | BK5: -2.4488304 | BL5: -1.2804253 | BM5: -1.0640987 | BN5: 0.28368992 | BO5: -0.29183328 | BP5: -0.13020809 | BQ5: 0.43098919 | BR5: 0.52244481 | BS5: 0.70917434 | BT5: 1.3330113 | BU5: 1.1416425 | BV5: 0.87944886 | BW5: 1.5408932 | BX5: 0.98003521 | BY5: 1.044294 | BZ5: 1.3274132
A6: LTV Adjustments | B6: 0.42373409 | C6: 0.48874114 | D6: 0.32970888 | E6: 0.46809162 | F6: 0.26081624 | G6: 0.55894617 | H6: 0.40693332 | I6: 1.0451672 | J6: 0.91310193 | K6: 0.59544101 | L6: 0.59041094 | M6: 0.34566215 | N6: 0.35413793 | O6: 0.052312778 | P6: 0.099655718 | Q6: -0.046838666 | R6: 0.0068603896 | S6: 0.31879126 | T6: 0.68157655 | U6: 0.79987972 | V6: 0.51695191 | W6: 0.64621622 | X6: 0.76762862 | Y6: 0.60930554 | Z6: 0.51578181 | AA6: 0.97236119 | AB6: 1.0343443 | AC6: 0.82191547 | AD6: 1.3744011 | AE6: 1.3925048 | AF6: 1.455756 | AG6: 2.3625146 | AH6: 2.3686331 | AI6: 3.2032867 | AJ6: 3.3612438 | AK6: 3.3852506 | AL6: 3.9176595 | AM6: 3.8737766 | AN6: 4.5025 | AO6: 3.0821413 | AP6: 3.1391933 | AQ6: 3.5031374 | AR6: 2.7888434 | AS6: 1.3751811 | AT6: 2.6029269 | AU6: 3.1349278 | AV6: 2.9838855 | AW6: 2.3454054 | AX6: 2.776363 | AY6: 3.1919903 | AZ6: 2.4842227 | BA6: 1.6979352 | BB6: 2.1031094 | BC6: 2.0066516 | BD6: 2.1427992 | BE6: 2.1275859 | BF6: 1.7907941 | BG6: 1.4442518 | BH6: 0.67312087 | BI6: 1.5518085 | BJ6: 1.6476181 | BK6: 2.4488304 | BL6: 1.2804253 | BM6: 1.0640987 | BN6: -0.28368992 | BO6: 0.29183328 | BP6: 0.13020809 | BQ6: -0.43098919 | BR6: -0.52244481 | BS6: -0.70917434 | BT6: -1.3330113 | BU6: -1.1416425 | BV6: -0.87944886 | BW6: -1.5408932 | BX6: -0.98003521 | BY6: -1.044294 | BZ6: -1.3274132
A7: RAGU Score | B7: 130.44463 | C7: 133.47249 | D7: 133.73036 | E7: 132.6506 | F7: 132.83015 | G7: 132.44094 | H7: 132.21139 | I7: 132.31548 | J7: 134.39179 | K7: 135.31536 | L7: 134.622 | M7: 135.09511 | N7: 135.66559 | O7: 136.08535 | P7: 136.99192 | Q7: 135.21766 | R7: 135.76925 | S7: 135.54777 | T7: 134.67945 | U7: 135.72967 | V7: 135.84474 | W7: 135.45618 | X7: 135.42792 | Y7: 136.68334 | Z7: 135.69048 | AA7: 135.72418 | AB7: 133.58613 | AC7: 135.13808 | AD7: 134.62559 | AE7: 134.24863 | AF7: 135.48447 | AG7: 136.26886 | AH7: 137.33129 | AI7: 136.54101 | AJ7: 136.69478 | AK7: 137.22172 | AL7: 137.11304 | AM7: 137.16268 | AN7: 137.58599 | AO7: 138.27006 | AP7: 137.44592 | AQ7: 137.58618 | AR7: 136.98667 | AS7: 137.82872 | AT7: 137.63855 | AU7: 137.73049 | AV7: 135.85518 | AW7: 137.0027 | AX7: 137.60859 | AY7: 138.19474 | AZ7: 136.60177 | BA7: 137.53539 | BB7: 137.20942 | BC7: 136.85382 | BD7: 136.89311 | BE7: 137.77741 | BF7: 138.40128 | BG7: 138.36337 | BH7: 138.72372 | BI7: 139.15317 | BJ7: 138.90291 | BK7: 138.33986 | BL7: 137.54999 | BM7: 138.31468 | BN7: 138.52905 | BO7: 139.06499 | BP7: 138.65813 | BQ7: 139.99248 | BR7: 140.84416 | BS7: 141.01698 | BT7: 141.56839 | BU7: 141.56163 | BV7: 141.85219 | BW7: 142.27843 | BX7: 142.36415 | BY7: 144.13738 | BZ7: 143.63057
A8: LTV | B8: 1.9087244 | C8: 1.902091 | D8: 1.9108937 | E8: 1.9483136 | F8: 1.9743248 | G8: 1.9082235 | H8: 1.856177 | I8: 2.0421645 | J8: 1.9635875 | K8: 1.8734483 | L8: 1.7480386 | M8: 1.6307556 | N8: 1.6169849 | O8: 1.627103 | P8: 1.6162566 | Q8: 1.7297385 | R8: 1.7569392 | S8: 1.7395328 | T8: 1.6369949 | U8: 1.5676004 | V8: 1.4987905 | W8: 1.465296 | X8: 1.5741537 | Y8: 1.5370213 | Z8: 1.6529071 | AA8: 1.573601 | AB8: 1.5776981 | AC8: 1.5967355 | AD8: 1.6223278 | AE8: 1.5998584 | AF8: 1.6208823 | AG8: 1.6254256 | AH8: 1.7275354 | AI8: 1.7659015 | AJ8: 1.7710768 | AK8: 1.7458196 | AL8: 1.7580864 | AM8: 1.7706581 | AN8: 1.8249991 | AO8: 1.8664803 | AP8: 1.8553202 | AQ8: 1.8110606 | AR8: 1.8031962 | AS8: 2.2124736 | AT8: 1.7122764 | AU8: 1.6336149 | AV8: 1.651872 | AW8: 1.6689601 | AX8: 1.7189757 | AY8: 1.7444615 | AZ8: 1.6596403 | BA8: 1.7449293 | BB8: 1.7600159 | BC8: 1.7378801 | BD8: 1.7289584 | BE8: 1.7354878 | BF8: 1.6971948 | BG8: 1.6132392 | BH8: 1.5355618 | BI8: 1.6337418 | BJ8: 1.6548874 | BK8: 1.633333 | BL8: 1.6344019 | BM8: 1.5806312 | BN8: 1.6133944 | BO8: 1.6092359 | BP8: 1.6135305 | BQ8: 1.5849707 | BR8: 1.5457949 | BS8: 1.58286 | BT8: 1.610135 | BU8: 1.5759432 | BV8: 1.5422471 | BW8: 1.5285302 | BX8: 1.5754634 | BY8: 1.5733703 | BZ8: 1.575951
A10: FLD | B10: 2016 | C10: 2017 | D10: 2018 | E10: 2019 | F10: 2020 M01 | G10: 2020 M02 | H10: 2020 M03 | I10: 2020 M04 | J10: 2020 M05 | K10: 2020 M06 | L10: 2020 M07 | M10: 2020 M08 | N10: 2020 M09 | O10: 2020 M10 | P10: 2020 M11 | Q10: 2020 M12 | R10: 2021 M01 | S10: 2021 M02 | T10: 2021 M03 | U10: 2021 M04 | V10: 2021 M05 | W10: 2021 M06 | X10: 2021 M07 | Y10: 2021 M08 | Z10: 2021 M09 | AA10: 2021 M10 | AB10: 2021 M11 | AC10: 2021 M12 | AD10: 2022 M01 | AE10: 2022 M02 | AF10: 2022 M03 | AG10: 2022 M04 | AH10: 2022 M05 | AI10: 2022 M06 | AJ10: 2022 M07 | AK10: 2022 M08 | AL10: 2022 M09 | AM10: 2022 M10 | AN10: 2022 M11 | AO10: 2022 M12 | AP10: 2023 M01 | AQ10: 2023 M02 | AR10: 2023 M03 | AS10: 2023 M04 | AT10: 2023 M05 | AU10: 2023 M06 | AV10: 2023 M07 | AW10: 2023 M08 | AX10: 2023 M09 | AY10: 2023 M10 | AZ10: 2023 M11 | BA10: 2023 M12 | BB10: 2024 M01 | BC10: 2024 M02 | BD10: 2024 M03 | BE10: 2024 M04 | BF10: 2024 M05 | BG10: 2024 M06 | BH10: 2024 M07 | BI10: 2024 M08 | BJ10: 2024 M09 | BK10: 2024 M10 | BL10: 2024 M11 | BM10: 2024 M12 | BN10: 2025 M01 | BO10: 2025 M02 | BP10: 2025 M03 | BQ10: 2025 M04 | BR10: 2025 M05 | BS10: 2025 M06 | BT10: 2025 M07 | BU10: 2025 M08 | BV10: 2025 M09 | BW10: 2025 M10
A11: Contract Model Score | F11: 131.69826 | G11: 133.05465 | H11: 131.44449 | I11: 132.48641 | J11: 135.78589 | K11: 137.67459 | L11: 137.63211 | M11: 137.41028 | N11: 138.50084 | O11: 138.38307 | P11: 141.10563 | Q11: 142.82581 | R11: 139.61141 | S11: 137.15928 | T11: 135.9438 | U11: 136.43445 | V11: 136.59572 | W11: 135.44515 | X11: 134.80733 | Y11: 136.84616 | Z11: 135.30382 | AA11: 135.50762 | AB11: 134.08635 | AC11: 134.22879 | AD11: 134.31941 | AE11: 133.67712 | AF11: 134.40763 | AG11: 135.82593 | AH11: 135.4639 | AI11: 136.28085 | AJ11: 136.94589 | AK11: 136.9564 | AL11: 136.99007 | AM11: 136.88364 | AN11: 139.40723 | AO11: 140.81079 | AP11: 141.68261 | AQ11: 142.38723 | AR11: 140.53336 | AS11: 139.72135 | AT11: 139.3661 | AU11: 137.91442 | AV11: 137.55925 | AW11: 137.86885 | AX11: 138.47342 | AY11: 139.44975 | AZ11: 139.906 | BA11: 139.26533 | BB11: 139.00234 | BC11: 138.84908 | BD11: 138.16068 | BE11: 138.56896 | BF11: 138.04076 | BG11: 138.62568 | BH11: 139.01469 | BI11: 140.94279 | BJ11: 141.91136 | BK11: 140.46816 | BL11: 137.69296 | BM11: 137.35406 | BN11: 136.42157 | BO11: 136.41165 | BP11: 137.00481 | BQ11: 138.24833 | BR11: 138.66846 | BS11: 138.12845 | BT11: 138.59134 | BU11: 137.62711 | BV11: 138.14099 | BW11: 137.97814 | BX11: 138.55363 | BY11: 140.497 | BZ11: 140.50887
A12: Model Score | F12: 0 | G12: 0 | H12: 0 | I12: 0 | J12: 0 | K12: 0 | L12: 0 | M12: 0 | N12: 0 | O12: 0 | P12: 0 | Q12: 0 | R12: 0 | S12: 0 | T12: 0 | U12: 0 | V12: 0 | W12: 0 | X12: 0 | Y12: 0 | Z12: 0 | AA12: 0 | AB12: 0 | AC12: 0 | AD12: 0 | AE12: 0 | AF12: 0 | AG12: 0 | AH12: 0 | AI12: 0 | AJ12: 0 | AK12: 0 | AL12: 0 | AM12: 0 | AN12: 0 | AO12: 0 | AP12: 0 | AQ12: 0 | AR12: 0 | AS12: 0 | AT12: 0 | AU12: 0 | AV12: 0 | AW12: 0 | AX12: 0 | AY12: 0 | AZ12: 0 | BA12: 0 | BB12: 0 | BC12: 0 | BD12: 0 | BE12: 0 | BF12: 0 | BG12: 0 | BH12: 0 | BI12: 0 | BJ12: 0 | BK12: 0 | BL12: 0 | BM12: 0 | BN12: 0 | BO12: 0 | BP12: 0 | BQ12: 0 | BR12: 0 | BS12: 0 | BT12: 0 | BU12: 0 | BV12: 0 | BW12: 0 | BX12: 0 | BY12: 0 | BZ12: 0
A13: Gross Loss Adjustments (Dealer level, high PTI, etc.) | F13: -2.618575 | G13: -2.6624902 | H13: -2.5389513 | I13: -2.1830018 | J13: -1.9586573 | K13: -2.5707701 | L13: -1.6067569 | M13: -1.6606386 | N13: -1.6765047 | O13: -0.90522889 | P13: 0.36024613 | Q13: 0.66551943 | R13: 1.0371936 | S13: 1.0320993 | T13: 1.1273939 | U13: -0.72660418 | V13: -0.57187697 | W13: -1.7458607 | X13: -1.4396365 | Y13: -0.62671148 | Z13: -1.0999659 | AA13: 0.15266976 | AB13: 0.34156609 | AC13: -0.37692429 | AD13: -0.95914248 | AE13: 0.47156739 | AF13: -0.19542609 | AG13: 0.055371689 | AH13: -0.071605105 | AI13: 0.16413733 | AJ13: 0.65410285 | AK13: 0.62547319 | AL13: 0.16909963 | AM13: -0.14477349 | AN13: 0.58187573 | AO13: 1.2493131 | AP13: 0.23431445 | AQ13: 0.67631668 | AR13: 0.70833313 | AS13: -0.25253448 | AT13: 1.1425682 | AU13: -0.26808274 | AV13: 0.991446 | AW13: 1.2426692 | AX13: -0.19114949 | AY13: 0.89586973 | AZ13: 1.1787151 | BA13: 0.85292392 | BB13: 0.95865681 | BC13: 1.2223759 | BD13: 1.6502528 | BE13: 2.0845649 | BF13: 2.3110549 | BG13: 2.2344407 | BH13: 3.1494852 | BI13: 3.1046769 | BJ13: 3.0523775 | BK13: 3.3850368 | BL13: 3.2175223 | BM13: 2.670848 | BN13: 2.9369339 | BO13: 3.3899991 | BP13: 3.0108809 | BQ13: 2.3547494 | BR13: 2.6220427 | BS13: 2.9199365 | BT13: 3.1501689 | BU13: 3.4133049 | BV13: 3.6318685 | BW13: 1.8941598 | BX13: 2.1301768 | BY13: 2.8158702 | BZ13: 1.8121339
A14: Recovery Adjustments excluding LTV (Mileage, vehicle type, etc.) | F14: 1.8148448 | G14: 1.6026328 | H14: 1.562453 | I14: 1.3433097 | J14: 1.5864083 | K14: 1.8821582 | L14: 1.9656491 | M14: 1.9372469 | N14: 2.0645328 | O14: 1.7585422 | P14: 2.1473351 | Q14: 2.5543385 | R14: 2.1666251 | S14: 2.0072317 | T14: 1.3350477 | U14: 0.46112401 | V14: 1.1099199 | W14: 1.4146927 | X14: 1.1603245 | Y14: 0.74029744 | Z14: 0.0068205341 | AA14: 0.10197372 | AB14: 0.47718063 | AC14: 0.83318927 | AD14: 0.7206186 | AE14: 0.35193717 | AF14: 0.43036388 | AG14: -0.42704619 | AH14: -1.6006461 | AI14: -1.9895013 | AJ14: -1.809273 | AK14: -3.3023049 | AL14: -2.6425905 | AM14: -1.3418471 | AN14: -3.9047791 | AO14: -2.4849803 | AP14: -3.1981012 | AQ14: -0.85268756 | AR14: -3.1238051 | AS14: -2.7270648 | AT14: -1.1046641 | AU14: -2.2924481 | AV14: -2.4715076 | AW14: -2.3011928 | AX14: -3.7039286 | AY14: 0.19557174 | AZ14: 0.3144631 | BA14: -0.087560064 | BB14: -0.66780964 | BC14: -1.0347384 | BD14: -0.83075605 | BE14: -1.4648811 | BF14: -1.3652133 | BG14: -1.1534177 | BH14: -0.12819333 | BI14: -0.055719087 | BJ14: -0.76931086 | BK14: -0.45520256 | BL14: -0.27666099 | BM14: -0.32161283 | BN14: 2.524388 | BO14: 2.4857602 | BP14: 1.4356227 | BQ14: 1.5286053 | BR14: 1.4357785 | BS14: 1.8939837 | BT14: 2.0282036 | BU14: 2.0625761 | BV14: 2.3986336 | BW14: 2.2605458 | BX14: 2.5923597 | BY14: 2.6789998 | BZ14: 2.5098952
A15: LTV Adjustments | F15: -1.8148448 | G15: -1.6026328 | H15: -1.562453 | I15: -1.3433097 | J15: -1.5864083 | K15: -1.8821582 | L15: -1.9656491 | M15: -1.9372469 | N15: -2.0645328 | O15: -1.7585422 | P15: -2.1473351 | Q15: -2.5543385 | R15: -2.1666251 | S15: -2.0072317 | T15: -1.3350477 | U15: -0.46112401 | V15: -1.1099199 | W15: -1.4146927 | X15: -1.1603245 | Y15: -0.74029744 | Z15: -0.0068205341 | AA15: -0.10197372 | AB15: -0.47718063 | AC15: -0.83318927 | AD15: -0.7206186 | AE15: -0.35193717 | AF15: -0.43036388 | AG15: 0.42704619 | AH15: 1.6006461 | AI15: 1.9895013 | AJ15: 1.809273 | AK15: 3.3023049 | AL15: 2.6425905 | AM15: 1.3418471 | AN15: 3.9047791 | AO15: 2.4849803 | AP15: 3.1981012 | AQ15: 0.85268756 | AR15: 3.1238051 | AS15: 2.7270648 | AT15: 1.1046641 | AU15: 2.2924481 | AV15: 2.4715076 | AW15: 2.3011928 | AX15: 3.7039286 | AY15: -0.19557174 | AZ15: -0.3144631 | BA15: 0.087560064 | BB15: 0.66780964 | BC15: 1.0347384 | BD15: 0.83075605 | BE15: 1.4648811 | BF15: 1.3652133 | BG15: 1.1534177 | BH15: 0.12819333 | BI15: 0.055719087 | BJ15: 0.76931086 | BK15: 0.45520256 | BL15: 0.27666099 | BM15: 0.32161283 | BN15: -2.524388 | BO15: -2.4857602 | BP15: -1.4356227 | BQ15: -1.5286053 | BR15: -1.4357785 | BS15: -1.8939837 | BT15: -2.0282036 | BU15: -2.0625761 | BV15: -2.3986336 | BW15: -2.2605458 | BX15: -2.5923597 | BY15: -2.6789998 | BZ15: -2.5098952
A16: RAGU Score | F16: 129.07969 | G16: 130.39216 | H16: 128.90554 | I16: 130.30341 | J16: 133.82723 | K16: 135.10382 | L16: 136.02535 | M16: 135.74965 | N16: 136.82434 | O16: 137.47784 | P16: 141.46587 | Q16: 143.49133 | R16: 140.6486 | S16: 138.19138 | T16: 137.0712 | U16: 135.70784 | V16: 136.02385 | W16: 133.69929 | X16: 133.36769 | Y16: 136.21945 | Z16: 134.20385 | AA16: 135.66029 | AB16: 134.42791 | AC16: 133.85187 | AD16: 133.36027 | AE16: 134.14868 | AF16: 134.2122 | AG16: 135.8813 | AH16: 135.39229 | AI16: 136.44499 | AJ16: 137.59999 | AK16: 137.58187 | AL16: 137.15917 | AM16: 136.73887 | AN16: 139.98911 | AO16: 142.0601 | AP16: 141.91692 | AQ16: 143.06355 | AR16: 141.24169 | AS16: 139.46882 | AT16: 140.50866 | AU16: 137.64633 | AV16: 138.55069 | AW16: 139.11152 | AX16: 138.28227 | AY16: 140.34562 | AZ16: 141.08472 | BA16: 140.11826 | BB16: 139.961 | BC16: 140.07145 | BD16: 139.81093 | BE16: 140.65352 | BF16: 140.35181 | BG16: 140.86012 | BH16: 142.16418 | BI16: 144.04747 | BJ16: 144.96374 | BK16: 143.85319 | BL16: 140.91048 | BM16: 140.02491 | BN16: 139.35851 | BO16: 139.80165 | BP16: 140.01569 | BQ16: 140.60308 | BR16: 141.2905 | BS16: 141.04839 | BT16: 141.74151 | BU16: 141.04042 | BV16: 141.77286 | BW16: 139.8723 | BX16: 140.68381 | BY16: 143.31287 | BZ16: 142.321
A17: LTV | F17: 1.4633833 | G17: 1.4328789 | H17: 1.3835412 | I17: 1.3987303 | J17: 1.3783667 | K17: 1.3524544 | L17: 1.2508309 | M17: 1.21004 | N17: 1.1957329 | O17: 1.2530861 | P17: 1.3173324 | Q17: 1.2499791 | R17: 1.3737717 | S17: 1.3001825 | T17: 1.3285323 | U17: 1.2297302 | V17: 1.2119803 | W17: 1.2606704 | X17: 1.246185 | Y17: 1.2991607 | Z17: 1.2768913 | AA17: 1.3598356 | AB17: 1.321942 | AC17: 1.3166955 | AD17: 1.3759183 | AE17: 1.3415726 | AF17: 1.3186163 | AG17: 1.335758 | AH17: 1.3348466 | AI17: 1.346843 | AJ17: 1.3131393 | AK17: 1.26462 | AL17: 1.3894416 | AM17: 1.3936065 | AN17: 1.3072397 | AO17: 1.2021165 | AP17: 1.1990727 | AQ17: 1.2737711 | AR17: 1.3224622 | AS17: 1.688119 | AT17: 1.3001563 | AU17: 1.2582054 | AV17: 1.2687651 | AW17: 1.2539488 | AX17: 1.2839291 | AY17: 1.300465 | AZ17: 1.2636814 | BA17: 1.3086419 | BB17: 1.376199 | BC17: 1.3809875 | BD17: 1.3899521 | BE17: 1.3966715 | BF17: 1.356895 | BG17: 1.3452953 | BH17: 1.3392665 | BI17: 1.37763 | BJ17: 1.3322489 | BK17: 1.3359242 | BL17: 1.3871049 | BM17: 1.3236894 | BN17: 1.3656786 | BO17: 1.3961017 | BP17: 1.40358 | BQ17: 1.4338248 | BR17: 1.4206952 | BS17: 1.4071696 | BT17: 1.4259149 | BU17: 1.4255266 | BV17: 1.4202431 | BW17: 1.4132778 | BX17: 1.4049737 | BY17: 1.447947 | BZ17: 1.438111
A19: FRN | B19: 2016 | C19: 2017 | D19: 2018 | E19: 2019 | F19: 2020 M01 | G19: 2020 M02 | H19: 2020 M03 | I19: 2020 M04 | J19: 2020 M05 | K19: 2020 M06 | L19: 2020 M07 | M19: 2020 M08 | N19: 2020 M09 | O19: 2020 M10 | P19: 2020 M11 | Q19: 2020 M12 | R19: 2021 M01 | S19: 2021 M02 | T19: 2021 M03 | U19: 2021 M04 | V19: 2021 M05 | W19: 2021 M06 | X19: 2021 M07 | Y19: 2021 M08 | Z19: 2021 M09 | AA19: 2021 M10 | AB19: 2021 M11 | AC19: 2021 M12 | AD19: 2022 M01 | AE19: 2022 M02 | AF19: 2022 M03 | AG19: 2022 M04 | AH19: 2022 M05 | AI19: 2022 M06 | AJ19: 2022 M07 | AK19: 2022 M08 | AL19: 2022 M09 | AM19: 2022 M10 | AN19: 2022 M11 | AO19: 2022 M12 | AP19: 2023 M01 | AQ19: 2023 M02 | AR19: 2023 M03 | AS19: 2023 M04 | AT19: 2023 M05 | AU19: 2023 M06 | AV19: 2023 M07 | AW19: 2023 M08 | AX19: 2023 M09 | AY19: 2023 M10 | AZ19: 2023 M11 | BA19: 2023 M12 | BB19: 2024 M01 | BC19: 2024 M02 | BD19: 2024 M03 | BE19: 2024 M04 | BF19: 2024 M05 | BG19: 2024 M06 | BH19: 2024 M07 | BI19: 2024 M08 | BJ19: 2024 M09 | BK19: 2024 M10 | BL19: 2024 M11 | BM19: 2024 M12 | BN19: 2025 M01 | BO19: 2025 M02 | BP19: 2025 M03 | BQ19: 2025 M04 | BR19: 2025 M05 | BS19: 2025 M06 | BT19: 2025 M07 | BU19: 2025 M08 | BV19: 2025 M09 | BW19: 2025 M10
A20: Contract Model Score | B20: 131.18489 | C20: 136.72146 | D20: 136.81942 | E20: 132.54318 | F20: 131.2656 | G20: 131.24734 | H20: 131.00099 | I20: 131.49953 | J20: 133.24754 | K20: 133.3984 | L20: 134.41536 | M20: 134.0819 | N20: 133.20621 | O20: 132.62511 | P20: 131.11674 | Q20: 135.00101 | R20: 135.45485 | S20: 135.55568 | T20: 135.39896 | U20: 135.35416 | V20: 135.51119 | W20: 134.67649 | X20: 134.23647 | Y20: 135.97528 | Z20: 134.5695 | AA20: 134.42803 | AB20: 132.01635 | AC20: 132.29985 | AD20: 134.01481 | AE20: 133.66105 | AF20: 134.31365 | AG20: 135.70242 | AH20: 137.3415 | AI20: 137.64811 | AJ20: 138.18701 | AK20: 137.99667 | AL20: 137.85245 | AM20: 138.34232 | AN20: 140.94633 | AO20: 141.0318 | AP20: 141.07216 | AQ20: 141.68378 | AR20: 141.17134 | AS20: 140.558 | AT20: 140.54313 | AU20: 140.65163 | AV20: 139.52303 | AW20: 141.17927 | AX20: 141.16169 | AY20: 140.12829 | AZ20: 138.55401 | BA20: 138.66844 | BB20: 139.04265 | BC20: 138.51156 | BD20: 137.58847 | BE20: 139.37221 | BF20: 140.53108 | BG20: 140.72018 | BH20: 141.1387 | BI20: 141.99905 | BJ20: 141.69762 | BK20: 140.62793 | BL20: 139.96452 | BM20: 139.29146 | BN20: 139.70528 | BO20: 140.12303 | BP20: 139.74747 | BQ20: 140.31399 | BR20: 140.88037 | BS20: 140.75094 | BT20: 140.87437 | BU20: 140.73303 | BV20: 141.33269 | BW20: 141.69552 | BX20: 141.57111 | BY20: 142.27606 | BZ20: 143.13141
A21: Model Score | B21: 0 | C21: 0 | D21: 0 | E21: 0 | F21: 0 | G21: 0 | H21: 0 | I21: 0 | J21: 0 | K21: 0 | L21: 0 | M21: 0 | N21: 0 | O21: 0 | P21: 0 | Q21: 0 | R21: 0 | S21: 0 | T21: 0 | U21: 0 | V21: 0 | W21: 0 | X21: 0 | Y21: 0 | Z21: 0 | AA21: 0 | AB21: 0 | AC21: 0 | AD21: 0 | AE21: 0 | AF21: 0 | AG21: 0 | AH21: 0 | AI21: 0 | AJ21: 0 | AK21: 0 | AL21: 0 | AM21: 0 | AN21: 0 | AO21: 0 | AP21: 0 | AQ21: 0 | AR21: 0 | AS21: 0 | AT21: 0 | AU21: 0 | AV21: 0 | AW21: 0 | AX21: 0 | AY21: 0 | AZ21: 0 | BA21: 0 | BB21: 0 | BC21: 0 | BD21: 0 | BE21: 0 | BF21: 0 | BG21: 0 | BH21: 0 | BI21: 0 | BJ21: 0 | BK21: 0 | BL21: 0 | BM21: 0 | BN21: 0 | BO21: 0 | BP21: 0 | BQ21: 0 | BR21: 0 | BS21: 0 | BT21: 0 | BU21: 0 | BV21: 0 | BW21: 0 | BX21: 0 | BY21: 0 | BZ21: 0
A22: Gross Loss Adjustments (Dealer level, high PTI, etc.) | B22: -0.3279542 | C22: 0.20210618 | D22: -0.19413065 | E22: 0.046002039 | F22: 0.20894198 | G22: 0.68967077 | H22: 0.58006475 | I22: 0.78299466 | J22: 0.89891075 | K22: 0.54373793 | L22: -0.13643966 | M22: -0.25963901 | N22: -0.43965845 | O22: -1.0434957 | P22: -0.96327644 | Q22: -0.42262724 | R22: -0.521399 | S22: -0.21157282 | T22: -0.2161873 | U22: 0.11286327 | V22: 0.17191358 | W22: 0.001116978 | X22: -0.14946234 | Y22: -0.026524873 | Z22: -0.12457301 | AA22: -1.0385091 | AB22: -1.1368363 | AC22: -1.2443844 | AD22: -1.1831245 | AE22: -0.93602081 | AF22: -1.0153112 | AG22: -0.22657864 | AH22: 0.38735503 | AI22: 0.45232977 | AJ22: 0.61673918 | AK22: 0.40253296 | AL22: -0.092616345 | AM22: -0.14469933 | AN22: 0.35704152 | AO22: -0.060778089 | AP22: 0.62320541 | AQ22: 1.116869 | AR22: 0.93617837 | AS22: 0.44328767 | AT22: 1.4618212 | AU22: 1.6028527 | AV22: 1.8758773 | AW22: 1.3662616 | AX22: 1.4187327 | AY22: 0.94445742 | AZ22: 0.6824844 | BA22: 0.5955368 | BB22: 0.33511498 | BC22: 0.45476969 | BD22: -0.00090710823 | BE22: 0.073872436 | BF22: 0.47551786 | BG22: 0.23938814 | BH22: 0.52694693 | BI22: 0.70563261 | BJ22: 0.60852798 | BK22: 0.46896912 | BL22: 0.49669736 | BM22: 0.54916671 | BN22: 0.92679308 | BO22: 0.97399083 | BP22: 1.2081372 | BQ22: 0.98342701 | BR22: 1.4151719 | BS22: 1.5388387 | BT22: 1.1650482 | BU22: 2.2476351 | BV22: 2.7273791 | BW22: 2.7269527 | BX22: 2.8403056 | BY22: 3.1705305 | BZ22: 2.5083411
A23: Recovery Adjustments excluding LTV (Mileage, vehicle type, etc.) | B23: -1.9643152 | C23: -2.2549576 | D23: -2.3856371 | E23: -1.7974164 | F23: -1.3477151 | G23: -1.3081554 | H23: -1.2512549 | I23: -1.1845604 | J23: -1.4273071 | K23: -1.0905543 | L23: -1.4595002 | M23: -1.2372835 | N23: -1.309006 | O23: -1.340571 | P23: -1.2596264 | Q23: -0.3165767 | R23: -1.1915423 | S23: -1.0293345 | T23: -1.7482472 | U23: -1.570213 | V23: -0.9290697 | W23: -1.3849273 | X23: -1.2159223 | Y23: -1.594781 | Z23: -1.7502689 | AA23: -1.8532889 | AB23: -1.8203 | AC23: -2.0417508 | AD23: -2.0294067 | AE23: -2.0618875 | AF23: -2.2601404 | AG23: -3.3579094 | AH23: -3.2712737 | AI23: -4.4422727 | AJ23: -4.8135765 | AK23: -4.8697254 | AL23: -4.9976015 | AM23: -4.6856454 | AN23: -6.1201927 | AO23: -5.1105897 | AP23: -5.3078688 | AQ23: -5.023231 | AR23: -4.7155575 | AS23: -5.4879546 | AT23: -4.5002181 | AU23: -4.5173068 | AV23: -4.8156357 | AW23: -4.8797624 | AX23: -5.0086899 | AY23: -4.0039358 | AZ23: -4.5114913 | BA23: -4.2325631 | BB23: -3.8087918 | BC23: -4.3043927 | BD23: -3.5302766 | BE23: -4.2702909 | BF23: -4.0961827 | BG23: -4.0513363 | BH23: -3.7572002 | BI23: -4.1822751 | BJ23: -4.4279506 | BK23: -3.7060484 | BL23: -3.5448495 | BM23: -2.1655407 | BN23: -0.73329709 | BO23: -0.8383779 | BP23: -0.74024632 | BQ23: -0.6614938 | BR23: -0.63467556 | BS23: -0.29674043 | BT23: -0.33023497 | BU23: -0.060033507 | BV23: 0.13756168 | BW23: 0.47130716 | BX23: 0.48063936 | BY23: 0.69454008 | BZ23: -0.0073534138
A24: LTV Adjustments | B24: 1.9643152 | C24: 2.2549576 | D24: 2.3856371 | E24: 1.7974164 | F24: 1.3477151 | G24: 1.3081554 | H24: 1.2512549 | I24: 1.1845604 | J24: 1.4273071 | K24: 1.0905543 | L24: 1.4595002 | M24: 1.2372835 | N24: 1.309006 | O24: 1.340571 | P24: 1.2596264 | Q24: 0.3165767 | R24: 1.1915423 | S24: 1.0293345 | T24: 1.7482472 | U24: 1.570213 | V24: 0.9290697 | W24: 1.3849273 | X24: 1.2159223 | Y24: 1.594781 | Z24: 1.7502689 | AA24: 1.8532889 | AB24: 1.8203 | AC24: 2.0417508 | AD24: 2.0294067 | AE24: 2.0618875 | AF24: 2.2601404 | AG24: 3.3579094 | AH24: 3.2712737 | AI24: 4.4422727 | AJ24: 4.8135765 | AK24: 4.8697254 | AL24: 4.9976015 | AM24: 4.6856454 | AN24: 6.1201927 | AO24: 5.1105897 | AP24: 5.3078688 | AQ24: 5.023231 | AR24: 4.7155575 | AS24: 5.4879546 | AT24: 4.5002181 | AU24: 4.5173068 | AV24: 4.8156357 | AW24: 4.8797624 | AX24: 5.0086899 | AY24: 4.0039358 | AZ24: 4.5114913 | BA24: 4.2325631 | BB24: 3.8087918 | BC24: 4.3043927 | BD24: 3.5302766 | BE24: 4.2702909 | BF24: 4.0961827 | BG24: 4.0513363 | BH24: 3.7572002 | BI24: 4.1822751 | BJ24: 4.4279506 | BK24: 3.7060484 | BL24: 3.5448495 | BM24: 2.1655407 | BN24: 0.73329709 | BO24: 0.8383779 | BP24: 0.74024632 | BQ24: 0.6614938 | BR24: 0.63467556 | BS24: 0.29674043 | BT24: 0.33023497 | BU24: 0.060033507 | BV24: -0.13756168 | BW24: -0.47130716 | BX24: -0.48063936 | BY24: -0.69454008 | BZ24: 0.0073534138
A25: RAGU Score | B25: 130.85693 | C25: 136.92357 | D25: 136.62529 | E25: 132.58918 | F25: 131.47454 | G25: 131.93701 | H25: 131.58106 | I25: 132.28252 | J25: 134.14645 | K25: 133.94214 | L25: 134.27892 | M25: 133.82226 | N25: 132.76655 | O25: 131.58161 | P25: 130.15347 | Q25: 134.57838 | R25: 134.93345 | S25: 135.34411 | T25: 135.18277 | U25: 135.46703 | V25: 135.6831 | W25: 134.67761 | X25: 134.08701 | Y25: 135.94875 | Z25: 134.44493 | AA25: 133.38952 | AB25: 130.87951 | AC25: 131.05547 | AD25: 132.83169 | AE25: 132.72503 | AF25: 133.29834 | AG25: 135.47584 | AH25: 137.72886 | AI25: 138.10044 | AJ25: 138.80375 | AK25: 138.3992 | AL25: 137.75983 | AM25: 138.19762 | AN25: 141.30338 | AO25: 140.97102 | AP25: 141.69537 | AQ25: 142.80065 | AR25: 142.10751 | AS25: 141.00128 | AT25: 142.00495 | AU25: 142.25449 | AV25: 141.39891 | AW25: 142.54553 | AX25: 142.58042 | AY25: 141.07275 | AZ25: 139.23649 | BA25: 139.26398 | BB25: 139.37776 | BC25: 138.96633 | BD25: 137.58756 | BE25: 139.44608 | BF25: 141.0066 | BG25: 140.95957 | BH25: 141.66565 | BI25: 142.70468 | BJ25: 142.30615 | BK25: 141.09689 | BL25: 140.46122 | BM25: 139.84062 | BN25: 140.63207 | BO25: 141.09702 | BP25: 140.95561 | BQ25: 141.29742 | BR25: 142.29554 | BS25: 142.28978 | BT25: 142.03941 | BU25: 142.98067 | BV25: 144.06007 | BW25: 144.42248 | BX25: 144.41142 | BY25: 145.44659 | BZ25: 145.63975
A26: LTV | B26: 2.1505904 | C26: 2.2076014 | D26: 2.1097029 | E26: 2.0875659 | F26: 2.0194091 | G26: 1.9185204 | H26: 1.9174761 | I26: 1.8742113 | J26: 2.0008174 | K26: 1.9375934 | L26: 1.8542445 | M26: 1.9186936 | N26: 1.9378022 | O26: 2.0427444 | P26: 2.1737498 | Q26: 1.8361932 | R26: 1.8609857 | S26: 1.7791028 | T26: 1.6618226 | U26: 1.5607826 | V26: 1.4615419 | W26: 1.5105506 | X26: 1.5517052 | Y26: 1.610812 | Z26: 1.695937 | AA26: 1.67477 | AB26: 1.6795947 | AC26: 1.7077679 | AD26: 1.6418182 | AE26: 1.6727076 | AF26: 1.655978 | AG26: 1.665526 | AH26: 1.6904076 | AI26: 1.6318661 | AJ26: 1.7179344 | AK26: 1.6719485 | AL26: 1.6712705 | AM26: 1.6946157 | AN26: 1.6429487 | AO26: 1.7191114 | AP26: 1.7145931 | AQ26: 1.6492207 | AR26: 1.8258084 | AS26: 1.9137278 | AT26: 1.5680408 | AU26: 1.4119283 | AV26: 1.4010296 | AW26: 1.4783569 | AX26: 1.5641979 | AY26: 1.5003224 | AZ26: 1.4327012 | BA26: 1.4500527 | BB26: 1.4829097 | BC26: 1.4694373 | BD26: 1.4846876 | BE26: 1.4864752 | BF26: 1.4733606 | BG26: 1.4668326 | BH26: 1.478489 | BI26: 1.4858089 | BJ26: 1.5051471 | BK26: 1.5165136 | BL26: 1.4747937 | BM26: 1.4654566 | BN26: 1.4897119 | BO26: 1.4928432 | BP26: 1.4773369 | BQ26: 1.4487366 | BR26: 1.4408087 | BS26: 1.4148339 | BT26: 1.4380338 | BU26: 1.4321141 | BV26: 1.4164798 | BW26: 1.4135773 | BX26: 1.412653 | BY26: 1.4506468 | BZ26: 1.4247754
A28: STG | B28: 2016 | C28: 2017 | D28: 2018 | E28: 2019 | F28: 2020 M01 | G28: 2020 M02 | H28: 2020 M03 | I28: 2020 M04 | J28: 2020 M05 | K28: 2020 M06 | L28: 2020 M07 | M28: 2020 M08 | N28: 2020 M09 | O28: 2020 M10 | P28: 2020 M11 | Q28: 2020 M12 | R28: 2021 M01 | S28: 2021 M02 | T28: 2021 M03 | U28: 2021 M04 | V28: 2021 M05 | W28: 2021 M06 | X28: 2021 M07 | Y28: 2021 M08 | Z28: 2021 M09 | AA28: 2021 M10 | AB28: 2021 M11 | AC28: 2021 M12 | AD28: 2022 M01 | AE28: 2022 M02 | AF28: 2022 M03 | AG28: 2022 M04 | AH28: 2022 M05 | AI28: 2022 M06 | AJ28: 2022 M07 | AK28: 2022 M08 | AL28: 2022 M09 | AM28: 2022 M10 | AN28: 2022 M11 | AO28: 2022 M12 | AP28: 2023 M01 | AQ28: 2023 M02 | AR28: 2023 M03 | AS28: 2023 M04 | AT28: 2023 M05 | AU28: 2023 M06 | AV28: 2023 M07 | AW28: 2023 M08 | AX28: 2023 M09 | AY28: 2023 M10 | AZ28: 2023 M11 | BA28: 2023 M12 | BB28: 2024 M01 | BC28: 2024 M02 | BD28: 2024 M03 | BE28: 2024 M04 | BF28: 2024 M05 | BG28: 2024 M06 | BH28: 2024 M07 | BI28: 2024 M08 | BJ28: 2024 M09 | BK28: 2024 M10 | BL28: 2024 M11 | BM28: 2024 M12 | BN28: 2025 M01 | BO28: 2025 M02 | BP28: 2025 M03 | BQ28: 2025 M04 | BR28: 2025 M05 | BS28: 2025 M06 | BT28: 2025 M07 | BU28: 2025 M08 | BV28: 2025 M09 | BW28: 2025 M10
A29: Contract Model Score | B29: 129.63955 | C29: 131.6541 | D29: 131.56964 | E29: 129.50608 | F29: 129.78439 | G29: 130.3194 | H29: 130.01813 | I29: 130.28186 | J29: 133.55242 | K29: 134.9074 | L29: 135.24459 | M29: 135.85773 | N29: 135.50069 | O29: 135.75132 | P29: 135.13958 | Q29: 134.89594 | R29: 135.56415 | S29: 135.05332 | T29: 135.26623 | U29: 135.39571 | V29: 135.36165 | W29: 135.74131 | X29: 135.03843 | Y29: 135.73405 | Z29: 134.33915 | AA29: 134.68261 | AB29: 132.94521 | AC29: 133.34441 | AD29: 134.2864 | AE29: 134.70284 | AF29: 134.6113 | AG29: 136.26908 | AH29: 136.73318 | AI29: 137.23263 | AJ29: 136.95716 | AK29: 137.63345 | AL29: 137.23928 | AM29: 137.73629 | AN29: 139.05852 | AO29: 138.44604 | AP29: 139.96787 | AQ29: 138.75376 | AR29: 139.11148 | AS29: 137.41883 | AT29: 138.17301 | AU29: 137.51063 | AV29: 137.68289 | AW29: 138.42609 | AX29: 139.23481 | AY29: 138.36256 | AZ29: 137.34161 | BA29: 136.90455 | BB29: 137.3486 | BC29: 136.85059 | BD29: 136.43852 | BE29: 137.16962 | BF29: 137.44545 | BG29: 137.85018 | BH29: 138.12378 | BI29: 138.88324 | BJ29: 138.78355 | BK29: 137.96917 | BL29: 136.82707 | BM29: 136.74566 | BN29: 136.75775 | BO29: 136.52401 | BP29: 136.69779 | BQ29: 137.49793 | BR29: 137.93118 | BS29: 138.5378 | BT29: 138.60141 | BU29: 138.34121 | BV29: 139.08055 | BW29: 139.19216 | BX29: 139.60755 | BY29: 141.45995 | BZ29: 141.41083
A30: Model Score | B30: 0 | C30: 0 | D30: 0 | E30: 0 | F30: 0 | G30: 0 | H30: 0 | I30: 0 | J30: 0 | K30: 0 | L30: 0 | M30: 0 | N30: 0 | O30: 0 | P30: 0 | Q30: 0 | R30: 0 | S30: 0 | T30: 0 | U30: 0 | V30: 0 | W30: 0 | X30: 0 | Y30: 0 | Z30: 0 | AA30: 0 | AB30: 0 | AC30: 0 | AD30: 0 | AE30: 0 | AF30: 0 | AG30: 0 | AH30: 0 | AI30: 0 | AJ30: 0 | AK30: 0 | AL30: 0 | AM30: 0 | AN30: 0 | AO30: 0 | AP30: 0 | AQ30: 0 | AR30: 0 | AS30: 0 | AT30: 0 | AU30: 0 | AV30: 0 | AW30: 0 | AX30: 0 | AY30: 0 | AZ30: 0 | BA30: 0 | BB30: 0 | BC30: 0 | BD30: 0 | BE30: 0 | BF30: 0 | BG30: 0 | BH30: 0 | BI30: 0 | BJ30: 0 | BK30: 0 | BL30: 0 | BM30: 0 | BN30: 0 | BO30: 0 | BP30: 0 | BQ30: 0 | BR30: 0 | BS30: 0 | BT30: 0 | BU30: 0 | BV30: 0 | BW30: 0 | BX30: 0 | BY30: 0 | BZ30: 0
A31: Gross Loss Adjustments (Dealer level, high PTI, etc.) | B31: 0.55168785 | C31: 0.53745688 | D31: 0.47283336 | E31: 0.26299826 | F31: -0.14006327 | G31: -0.39696846 | H31: -0.054755614 | I31: -0.39040148 | J31: -0.25670413 | K31: -0.10090749 | L31: 0.037085538 | M31: 0.14030278 | N31: 0.20053176 | O31: 0.15018009 | P31: -0.058178669 | Q31: 0.018703212 | R31: 0.84907177 | S31: 0.94076465 | T31: 0.87702519 | U31: 1.0645563 | V31: 1.12465 | W31: 0.94081331 | X31: 0.70136914 | Y31: 0.8162152 | Z31: 0.70350256 | AA31: 0.35252759 | AB31: 0.52507361 | AC31: 0.41387917 | AD31: -0.28584588 | AE31: -0.42993155 | AF31: -0.017080394 | AG31: 0.02254805 | AH31: -0.074616006 | AI31: -0.0050332041 | AJ31: -0.078831581 | AK31: -0.6660321 | AL31: -0.53108413 | AM31: -0.080976064 | AN31: 0.19272576 | AO31: 0.28530912 | AP31: -0.52586668 | AQ31: -0.14058154 | AR31: 0.6149757 | AS31: -0.68925461 | AT31: 0.25991305 | AU31: 0.15895285 | AV31: 0.55954348 | AW31: 1.2530053 | AX31: 1.3334224 | AY31: 0.90841471 | AZ31: 0.61489963 | BA31: 0.91881009 | BB31: 1.047711 | BC31: 1.0422704 | BD31: 1.1860229 | BE31: 1.7359825 | BF31: 1.887161 | BG31: 2.0356688 | BH31: 2.1908535 | BI31: 1.9882855 | BJ31: 2.3083132 | BK31: 1.9504804 | BL31: 2.11595 | BM31: 2.3825183 | BN31: 2.3034933 | BO31: 2.289166 | BP31: 2.2805958 | BQ31: 2.0584523 | BR31: 1.904943 | BS31: 2.1110437 | BT31: 1.9557382 | BU31: 2.4279503 | BV31: 2.8233177 | BW31: 2.7007742 | BX31: 3.2512251 | BY31: 3.4440448 | BZ31: 2.7714897
A32: Recovery Adjustments excluding LTV (Mileage, vehicle type, etc.) | B32: 0.12590696 | C32: 0.72276277 | D32: 0.25150527 | E32: 0.20410717 | F32: 0.12772351 | G32: 0.16975296 | H32: 0.068162662 | I32: 0.054417779 | J32: -0.017957023 | K32: 0.1984117 | L32: 0.20104804 | M32: 0.34233737 | N32: 0.37334445 | O32: 0.6065326 | P32: 0.12767472 | Q32: 0.52106741 | R32: 0.59516867 | S32: 0.43574637 | T32: 0.13091405 | U32: 0.098670235 | V32: 0.62379281 | W32: -0.0012999195 | X32: 0.23316057 | Y32: 0.067441631 | Z32: 0.43409215 | AA32: 0.29324585 | AB32: 0.033588986 | AC32: 0.70632738 | AD32: 0.76704646 | AE32: 0.36208167 | AF32: -0.14846 | AG32: -1.2482881 | AH32: -1.9835576 | AI32: -2.4014186 | AJ32: -2.2481105 | AK32: -2.8353402 | AL32: -2.5060836 | AM32: -2.0207203 | AN32: -3.7666575 | AO32: -1.5400497 | AP32: -2.9676535 | AQ32: -2.03527 | AR32: -1.6245168 | AS32: -1.2182386 | AT32: -1.6391814 | AU32: -0.9455072 | AV32: -1.4364215 | AW32: -0.78256604 | AX32: -1.1055028 | AY32: -0.83763994 | AZ32: -0.85028619 | BA32: -0.62850762 | BB32: -1.2947901 | BC32: -1.0175751 | BD32: -0.7232226 | BE32: -0.88443501 | BF32: -0.39978238 | BG32: 0.082186193 | BH32: 0.5107734 | BI32: 0.13306039 | BJ32: -1.1399635 | BK32: -0.65827321 | BL32: 0.12592197 | BM32: 1.2497366 | BN32: 2.453559 | BO32: 2.1887686 | BP32: 2.2212716 | BQ32: 2.7315838 | BR32: 3.1096159 | BS32: 3.2137301 | BT32: 3.0244134 | BU32: 2.7796861 | BV32: 3.1545589 | BW32: 3.3276938 | BX32: 3.4204206 | BY32: 3.6541647 | BZ32: 4.1962148
A33: LTV Adjustments | B33: -0.12590696 | C33: -0.72276277 | D33: -0.25150527 | E33: -0.20410717 | F33: -0.12772351 | G33: -0.16975296 | H33: -0.068162662 | I33: -0.054417779 | J33: 0.017957023 | K33: -0.1984117 | L33: -0.20104804 | M33: -0.34233737 | N33: -0.37334445 | O33: -0.6065326 | P33: -0.12767472 | Q33: -0.52106741 | R33: -0.59516867 | S33: -0.43574637 | T33: -0.13091405 | U33: -0.098670235 | V33: -0.62379281 | W33: 0.0012999195 | X33: -0.23316057 | Y33: -0.067441631 | Z33: -0.43409215 | AA33: -0.29324585 | AB33: -0.033588986 | AC33: -0.70632738 | AD33: -0.76704646 | AE33: -0.36208167 | AF33: 0.14846 | AG33: 1.2482881 | AH33: 1.9835576 | AI33: 2.4014186 | AJ33: 2.2481105 | AK33: 2.8353402 | AL33: 2.5060836 | AM33: 2.0207203 | AN33: 3.7666575 | AO33: 1.5400497 | AP33: 2.9676535 | AQ33: 2.03527 | AR33: 1.6245168 | AS33: 1.2182386 | AT33: 1.6391814 | AU33: 0.9455072 | AV33: 1.4364215 | AW33: 0.78256604 | AX33: 1.1055028 | AY33: 0.83763994 | AZ33: 0.85028619 | BA33: 0.62850762 | BB33: 1.2947901 | BC33: 1.0175751 | BD33: 0.7232226 | BE33: 0.88443501 | BF33: 0.39978238 | BG33: -0.082186193 | BH33: -0.5107734 | BI33: -0.13306039 | BJ33: 1.1399635 | BK33: 0.65827321 | BL33: -0.12592197 | BM33: -1.2497366 | BN33: -2.453559 | BO33: -2.1887686 | BP33: -2.2212716 | BQ33: -2.7315838 | BR33: -3.1096159 | BS33: -3.2137301 | BT33: -3.0244134 | BU33: -2.7796861 | BV33: -3.1545589 | BW33: -3.3276938 | BX33: -3.4204206 | BY33: -3.6541647 | BZ33: -4.1962148
A34: RAGU Score | B34: 130.19124 | C34: 132.19156 | D34: 132.04247 | E34: 129.76908 | F34: 129.64432 | G34: 129.92243 | H34: 129.96337 | I34: 129.89146 | J34: 133.29572 | K34: 134.80649 | L34: 135.28167 | M34: 135.99803 | N34: 135.70122 | O34: 135.9015 | P34: 135.0814 | Q34: 134.91464 | R34: 136.41322 | S34: 135.99408 | T34: 136.14325 | U34: 136.46026 | V34: 136.4863 | W34: 136.68212 | X34: 135.7398 | Y34: 136.55026 | Z34: 135.04265 | AA34: 135.03514 | AB34: 133.47028 | AC34: 133.75829 | AD34: 134.00055 | AE34: 134.27291 | AF34: 134.59422 | AG34: 136.29163 | AH34: 136.65857 | AI34: 137.2276 | AJ34: 136.87832 | AK34: 136.96742 | AL34: 136.7082 | AM34: 137.65531 | AN34: 139.25125 | AO34: 138.73135 | AP34: 139.442 | AQ34: 138.61318 | AR34: 139.72646 | AS34: 136.72957 | AT34: 138.43292 | AU34: 137.66958 | AV34: 138.24243 | AW34: 139.6791 | AX34: 140.56823 | AY34: 139.27097 | AZ34: 137.95651 | BA34: 137.82336 | BB34: 138.39631 | BC34: 137.89287 | BD34: 137.62454 | BE34: 138.9056 | BF34: 139.33261 | BG34: 139.88584 | BH34: 140.31464 | BI34: 140.87153 | BJ34: 141.09187 | BK34: 139.91965 | BL34: 138.94302 | BM34: 139.12818 | BN34: 139.06124 | BO34: 138.81317 | BP34: 138.97839 | BQ34: 139.55638 | BR34: 139.83613 | BS34: 140.64884 | BT34: 140.55715 | BU34: 140.76916 | BV34: 141.90387 | BW34: 141.89293 | BX34: 142.85878 | BY34: 144.90399 | BZ34: 144.18232
A35: LTV | B35: 1.9471721 | C35: 1.9398222 | D35: 1.9871149 | E35: 2.085943 | F35: 2.0676889 | G35: 2.1290235 | H35: 2.0534122 | I35: 2.0944388 | J35: 2.1513491 | K35: 2.0657497 | L35: 1.8646704 | M35: 1.8045241 | N35: 1.774196 | O35: 1.7618149 | P35: 1.8444218 | Q35: 1.8116717 | R35: 1.8007957 | S35: 1.7048222 | T35: 1.649114 | U35: 1.6103487 | V35: 1.5547197 | W35: 1.5416426 | X35: 1.5257625 | Y35: 1.6111285 | Z35: 1.6459911 | AA35: 1.5697149 | AB35: 1.6688367 | AC35: 1.5946037 | AD35: 1.5834516 | AE35: 1.5721565 | AF35: 1.55897 | AG35: 1.5276832 | AH35: 1.5498877 | AI35: 1.474718 | AJ35: 1.5033621 | AK35: 1.5408392 | AL35: 1.5550565 | AM35: 1.4801122 | AN35: 1.5291428 | AO35: 1.4411967 | AP35: 1.4602523 | AQ35: 1.36991 | AR35: 1.6344753 | AS35: 2.0992586 | AT35: 1.5630749 | AU35: 1.3831632 | AV35: 1.3438099 | AW35: 1.4197733 | AX35: 1.4749354 | AY35: 1.4229092 | AZ35: 1.3855038 | BA35: 1.4712579 | BB35: 1.5184988 | BC35: 1.5346803 | BD35: 1.5406465 | BE35: 1.5329424 | BF35: 1.4988061 | BG35: 1.4468925 | BH35: 1.43139 | BI35: 1.4419955 | BJ35: 1.4942001 | BK35: 1.4719013 | BL35: 1.4590342 | BM35: 1.4558992 | BN35: 1.4802801 | BO35: 1.5097722 | BP35: 1.467235 | BQ35: 1.4576647 | BR35: 1.4188994 | BS35: 1.3993251 | BT35: 1.4441489 | BU35: 1.4203144 | BV35: 1.4269758 | BW35: 1.3912911 | BX35: 1.4423315 | BY35: 1.4510303 | BZ35: 1.5713354
A37: ENT | B37: 2016 | C37: 2017 | D37: 2018 | E37: 2019 | F37: 2020 M01 | G37: 2020 M02 | H37: 2020 M03 | I37: 2020 M04 | J37: 2020 M05 | K37: 2020 M06 | L37: 2020 M07 | M37: 2020 M08 | N37: 2020 M09 | O37: 2020 M10 | P37: 2020 M11 | Q37: 2020 M12 | R37: 2021 M01 | S37: 2021 M02 | T37: 2021 M03 | U37: 2021 M04 | V37: 2021 M05 | W37: 2021 M06 | X37: 2021 M07 | Y37: 2021 M08 | Z37: 2021 M09 | AA37: 2021 M10 | AB37: 2021 M11 | AC37: 2021 M12 | AD37: 2022 M01 | AE37: 2022 M02 | AF37: 2022 M03 | AG37: 2022 M04 | AH37: 2022 M05 | AI37: 2022 M06 | AJ37: 2022 M07 | AK37: 2022 M08 | AL37: 2022 M09 | AM37: 2022 M10 | AN37: 2022 M11 | AO37: 2022 M12 | AP37: 2023 M01 | AQ37: 2023 M02 | AR37: 2023 M03 | AS37: 2023 M04 | AT37: 2023 M05 | AU37: 2023 M06 | AV37: 2023 M07 | AW37: 2023 M08 | AX37: 2023 M09 | AY37: 2023 M10 | AZ37: 2023 M11 | BA37: 2023 M12 | BB37: 2024 M01 | BC37: 2024 M02 | BD37: 2024 M03 | BE37: 2024 M04 | BF37: 2024 M05 | BG37: 2024 M06 | BH37: 2024 M07 | BI37: 2024 M08 | BJ37: 2024 M09 | BK37: 2024 M10 | BL37: 2024 M11 | BM37: 2024 M12 | BN37: 2025 M01 | BO37: 2025 M02 | BP37: 2025 M03 | BQ37: 2025 M04 | BR37: 2025 M05 | BS37: 2025 M06 | BT37: 2025 M07 | BU37: 2025 M08 | BV37: 2025 M09 | BW37: 2025 M10
A38: Contract Model Score | F38: 129.42831 | G38: 133.57876 | H38: 133.13665 | I38: 130.57532 | J38: 133.68967 | K38: 135.91754 | L38: 136.54209 | M38: 136.23045 | N38: 136.12905 | O38: 135.90718 | P38: 135.82731 | Q38: 134.58041 | R38: 134.5807 | S38: 134.12233 | T38: 133.38292 | U38: 132.20794 | V38: 131.87001 | W38: 131.44439 | X38: 130.42029 | Y38: 132.17114 | Z38: 130.86404 | AA38: 129.94668 | AB38: 129.79633 | AC38: 128.6143 | AD38: 128.75316 | AE38: 129.14794 | AF38: 129.85816 | AG38: 130.64955 | AH38: 131.7484 | AI38: 132.02686 | AJ38: 132.30609 | AK38: 131.79146 | AL38: 131.18606 | AM38: 130.57426 | AN38: 131.29341 | AO38: 131.94153 | AP38: 132.08433 | AQ38: 132.6274 | AR38: 133.13309 | AS38: 133.87992 | AT38: 134.10541 | AU38: 132.545 | AV38: 132.38189 | AW38: 134.17477 | AX38: 135.03681 | AY38: 135.01758 | AZ38: 135.02678 | BA38: 135.90351 | BB38: 136.12985 | BC38: 136.14381 | BD38: 136.21437 | BE38: 136.55872 | BF38: 136.84039 | BG38: 137.22165 | BH38: 136.77385 | BI38: 136.60034 | BJ38: 136.68759 | BK38: 135.50937 | BL38: 134.76105 | BM38: 134.55901 | BN38: 134.35793 | BO38: 134.0252 | BP38: 135.00828 | BQ38: 136.09756 | BR38: 136.3901 | BS38: 136.90218 | BT38: 137.18613 | BU38: 137.01532 | BV38: 136.80392 | BW38: 136.94293 | BX38: 136.85527 | BY38: 137.97588 | BZ38: 139.31702
A39: Model Score | F39: 0 | G39: 0 | H39: 0 | I39: 0 | J39: 0 | K39: 0 | L39: 0 | M39: 0 | N39: 0 | O39: 0 | P39: 0 | Q39: 0 | R39: 0 | S39: 0 | T39: 0 | U39: 0 | V39: 0 | W39: 0 | X39: 0 | Y39: 0 | Z39: 0 | AA39: 0 | AB39: 0 | AC39: 0 | AD39: 0 | AE39: 0 | AF39: 0 | AG39: 0 | AH39: 0 | AI39: 0 | AJ39: 0 | AK39: 0 | AL39: 0 | AM39: 0 | AN39: 0 | AO39: 0 | AP39: 0 | AQ39: 0 | AR39: 0 | AS39: 0 | AT39: 0 | AU39: 0 | AV39: 0 | AW39: 0 | AX39: 0 | AY39: 0 | AZ39: 0 | BA39: 0 | BB39: 0 | BC39: 0 | BD39: 0 | BE39: 0 | BF39: 0 | BG39: 0 | BH39: 0 | BI39: 0 | BJ39: 0 | BK39: 0 | BL39: 0 | BM39: 0 | BN39: 0 | BO39: 0 | BP39: 0 | BQ39: 0 | BR39: 0 | BS39: 0 | BT39: 0 | BU39: 0 | BV39: 0 | BW39: 0 | BX39: 0 | BY39: 0 | BZ39: 0
A40: Gross Loss Adjustments (Dealer level, high PTI, etc.) | F40: -0.60878616 | G40: -0.41011236 | H40: -0.15302149 | I40: -0.31605584 | J40: -0.22502889 | K40: -0.18222042 | L40: -0.55605496 | M40: -0.38942739 | N40: -0.61134208 | O40: -1.6198018 | P40: -1.7435371 | Q40: -1.9600451 | R40: -1.274897 | S40: -1.3016149 | T40: -1.0551654 | U40: -1.2991584 | V40: -1.2580752 | W40: -1.5532874 | X40: -1.671019 | Y40: -1.5005991 | Z40: -1.6187685 | AA40: -1.121769 | AB40: -1.5579893 | AC40: -1.6012449 | AD40: -1.1857052 | AE40: -0.96647881 | AF40: -0.78930432 | AG40: -1.0627079 | AH40: -1.1446269 | AI40: -1.2144971 | AJ40: -1.5617077 | AK40: -1.7023649 | AL40: -1.6494484 | AM40: -1.4742689 | AN40: -1.5587436 | AO40: -1.4354094 | AP40: -2.160438 | AQ40: -1.5917293 | AR40: -1.606597 | AS40: -1.454741 | AT40: -0.9549464 | AU40: -1.3336226 | AV40: -1.276011 | AW40: -0.88785847 | AX40: -0.49951199 | AY40: 0.059055716 | AZ40: 0.042520402 | BA40: -0.19630267 | BB40: -0.47505983 | BC40: -0.22192446 | BD40: -0.46479705 | BE40: -0.52469549 | BF40: -0.14275008 | BG40: -0.16356774 | BH40: -0.70522259 | BI40: -0.37688992 | BJ40: -0.36969201 | BK40: 0.019184092 | BL40: 0.083120709 | BM40: -0.084740606 | BN40: -0.17056657 | BO40: -0.12897575 | BP40: -0.082647326 | BQ40: 0.23287539 | BR40: 0.5366148 | BS40: 0.79152891 | BT40: 0.48080515 | BU40: 0.48058157 | BV40: 0.53110303 | BW40: 1.5193725 | BX40: 1.9395646 | BY40: 2.2128568 | BZ40: 1.9848151
A41: Recovery Adjustments excluding LTV (Mileage, vehicle type, etc.) | F41: -0.10345867 | G41: -0.066336024 | H41: 0.030267205 | I41: -0.080126675 | J41: 0.14024863 | K41: 0.35505193 | L41: 0.18786426 | M41: 0.074854325 | N41: 0.10752399 | O41: 0.14132711 | P41: 0.1006134 | Q41: 0.17122063 | R41: 0.13482855 | S41: 0.17400282 | T41: 0.074903582 | U41: 0.0037719884 | V41: -0.11377156 | W41: -0.31942493 | X41: -0.46199619 | Y41: -0.58429858 | Z41: -0.70431001 | AA41: -0.63909177 | AB41: -0.84375505 | AC41: -1.0245777 | AD41: -1.2211286 | AE41: -1.1216097 | AF41: -1.1526139 | AG41: -1.1693297 | AH41: -1.0766668 | AI41: -1.2115377 | AJ41: -1.3815623 | AK41: -1.4108186 | AL41: -1.6069066 | AM41: -1.6296874 | AN41: -1.7692031 | AO41: -1.6356667 | AP41: -1.7639407 | AQ41: -1.6104949 | AR41: -1.7294254 | AS41: -1.5159157 | AT41: -1.5181737 | AU41: -1.6345962 | AV41: -1.5642973 | AW41: -1.5919934 | AX41: -1.6806924 | AY41: -1.4407205 | AZ41: -1.5437478 | BA41: -1.5530827 | BB41: -1.7041238 | BC41: -1.601939 | BD41: -1.6528063 | BE41: -1.6062193 | BF41: -1.3333293 | BG41: -1.1912995 | BH41: -1.0465544 | BI41: -1.0916528 | BJ41: -0.88008246 | BK41: -0.67847719 | BL41: -0.31328124 | BM41: 0.007296226 | BN41: 0.12546603 | BO41: 0.30647912 | BP41: 0.088471871 | BQ41: -0.14199258 | BR41: -0.050468636 | BS41: -0.017310043 | BT41: -0.060428212 | BU41: -0.016948729 | BV41: -0.026190567 | BW41: 0.090276915 | BX41: 0.18012653 | BY41: 0.4681828 | BZ41: 0.55795488
A42: LTV Adjustments | F42: 0.10345867 | G42: 0.066336024 | H42: -0.030267205 | I42: 0.080126675 | J42: -0.14024863 | K42: -0.35505193 | L42: -0.18786426 | M42: -0.074854325 | N42: -0.10752399 | O42: -0.14132711 | P42: -0.1006134 | Q42: -0.17122063 | R42: -0.13482855 | S42: -0.17400282 | T42: -0.074903582 | U42: -0.0037719884 | V42: 0.11377156 | W42: 0.31942493 | X42: 0.46199619 | Y42: 0.58429858 | Z42: 0.70431001 | AA42: 0.63909177 | AB42: 0.84375505 | AC42: 1.0245777 | AD42: 1.2211286 | AE42: 1.1216097 | AF42: 1.1526139 | AG42: 1.1693297 | AH42: 1.0766668 | AI42: 1.2115377 | AJ42: 1.3815623 | AK42: 1.4108186 | AL42: 1.6069066 | AM42: 1.6296874 | AN42: 1.7692031 | AO42: 1.6356667 | AP42: 1.7639407 | AQ42: 1.6104949 | AR42: 1.7294254 | AS42: 1.5159157 | AT42: 1.5181737 | AU42: 1.6345962 | AV42: 1.5642973 | AW42: 1.5919934 | AX42: 1.6806924 | AY42: 1.4407205 | AZ42: 1.5437478 | BA42: 1.5530827 | BB42: 1.7041238 | BC42: 1.601939 | BD42: 1.6528063 | BE42: 1.6062193 | BF42: 1.3333293 | BG42: 1.1912995 | BH42: 1.0465544 | BI42: 1.0916528 | BJ42: 0.88008246 | BK42: 0.67847719 | BL42: 0.31328124 | BM42: -0.007296226 | BN42: -0.12546603 | BO42: -0.30647912 | BP42: -0.088471871 | BQ42: 0.14199258 | BR42: 0.050468636 | BS42: 0.017310043 | BT42: 0.060428212 | BU42: 0.016948729 | BV42: 0.026190567 | BW42: -0.090276915 | BX42: -0.18012653 | BY42: -0.4681828 | BZ42: -0.55795488
A43: RAGU Score | F43: 128.81953 | G43: 133.16865 | H43: 132.98363 | I43: 130.25927 | J43: 133.46465 | K43: 135.73532 | L43: 135.98603 | M43: 135.84103 | N43: 135.51771 | O43: 134.28738 | P43: 134.08378 | Q43: 132.62037 | R43: 133.3058 | S43: 132.82071 | T43: 132.32775 | U43: 130.90878 | V43: 130.61194 | W43: 129.8911 | X43: 128.74927 | Y43: 130.67054 | Z43: 129.24527 | AA43: 128.82491 | AB43: 128.23834 | AC43: 127.01306 | AD43: 127.56745 | AE43: 128.18146 | AF43: 129.06886 | AG43: 129.58684 | AH43: 130.60378 | AI43: 130.81237 | AJ43: 130.74439 | AK43: 130.0891 | AL43: 129.53662 | AM43: 129.09999 | AN43: 129.73467 | AO43: 130.50612 | AP43: 129.92389 | AQ43: 131.03567 | AR43: 131.52649 | AS43: 132.42518 | AT43: 133.15047 | AU43: 131.21138 | AV43: 131.10588 | AW43: 133.28691 | AX43: 134.5373 | AY43: 135.07664 | AZ43: 135.0693 | BA43: 135.7072 | BB43: 135.65479 | BC43: 135.92189 | BD43: 135.74957 | BE43: 136.03402 | BF43: 136.69764 | BG43: 137.05809 | BH43: 136.06863 | BI43: 136.22345 | BJ43: 136.31789 | BK43: 135.52855 | BL43: 134.84417 | BM43: 134.47427 | BN43: 134.18736 | BO43: 133.89622 | BP43: 134.92563 | BQ43: 136.33043 | BR43: 136.92671 | BS43: 137.69371 | BT43: 137.66694 | BU43: 137.4959 | BV43: 137.33503 | BW43: 138.4623 | BX43: 138.79483 | BY43: 140.18873 | BZ43: 141.30183
A44: LTV | F44: 1.5537501 | G44: 1.4852944 | H44: 1.4261913 | I44: 1.4354772 | J44: 1.4822937 | K44: 1.422657 | L44: 1.282801 | M44: 1.2350747 | N44: 1.2857046 | O44: 1.3461998 | P44: 1.3839235 | Q44: 1.3796447 | R44: 1.3980221 | S44: 1.4080678 | T44: 1.3181376 | U44: 1.2616639 | V44: 1.2599693 | W44: 1.2571646 | X44: 1.2996829 | Y44: 1.3501028 | Z44: 1.3724563 | AA44: 1.3696664 | AB44: 1.353455 | AC44: 1.3976519 | AD44: 1.382371 | AE44: 1.3940531 | AF44: 1.3892161 | AG44: 1.3747063 | AH44: 1.3686839 | AI44: 1.2862901 | AJ44: 1.2902536 | AK44: 1.3054334 | AL44: 1.2789056 | AM44: 1.3094097 | AN44: 1.3622399 | AO44: 1.3701724 | AP44: 1.3463272 | AQ44: 1.3145555 | AR44: 1.4638631 | AS44: 1.7201957 | AT44: 1.2869046 | AU44: 1.263944 | AV44: 1.2505723 | AW44: 1.2450151 | AX44: 1.2876598 | AY44: 1.2826479 | AZ44: 1.3061113 | BA44: 1.3390351 | BB44: 1.347247 | BC44: 1.3359661 | BD44: 1.3031222 | BE44: 1.2986142 | BF44: 1.3058305 | BG44: 1.3022215 | BH44: 1.3213317 | BI44: 1.3181025 | BJ44: 1.3156947 | BK44: 1.3425929 | BL44: 1.3527328 | BM44: 1.3485968 | BN44: 1.3555444 | BO44: 1.3461621 | BP44: 1.3221603 | BQ44: 1.3185232 | BR44: 1.301428 | BS44: 1.3061133 | BT44: 1.3107131 | BU44: 1.3113251 | BV44: 1.3102061 | BW44: 1.309706 | BX44: 1.320121 | BY44: 1.3531596 | BZ44: 1.3705151
A46: nonKMXENT | B46: 2016 | C46: 2017 | D46: 2018 | E46: 2019 | F46: 2020 M01 | G46: 2020 M02 | H46: 2020 M03 | I46: 2020 M04 | J46: 2020 M05 | K46: 2020 M06 | L46: 2020 M07 | M46: 2020 M08 | N46: 2020 M09 | O46: 2020 M10 | P46: 2020 M11 | Q46: 2020 M12 | R46: 2021 M01 | S46: 2021 M02 | T46: 2021 M03 | U46: 2021 M04 | V46: 2021 M05 | W46: 2021 M06 | X46: 2021 M07 | Y46: 2021 M08 | Z46: 2021 M09 | AA46: 2021 M10 | AB46: 2021 M11 | AC46: 2021 M12 | AD46: 2022 M01 | AE46: 2022 M02 | AF46: 2022 M03 | AG46: 2022 M04 | AH46: 2022 M05 | AI46: 2022 M06 | AJ46: 2022 M07 | AK46: 2022 M08 | AL46: 2022 M09 | AM46: 2022 M10 | AN46: 2022 M11 | AO46: 2022 M12 | AP46: 2023 M01 | AQ46: 2023 M02 | AR46: 2023 M03 | AS46: 2023 M04 | AT46: 2023 M05 | AU46: 2023 M06 | AV46: 2023 M07 | AW46: 2023 M08 | AX46: 2023 M09 | AY46: 2023 M10 | AZ46: 2023 M11 | BA46: 2023 M12 | BB46: 2024 M01 | BC46: 2024 M02 | BD46: 2024 M03 | BE46: 2024 M04 | BF46: 2024 M05 | BG46: 2024 M06 | BH46: 2024 M07 | BI46: 2024 M08 | BJ46: 2024 M09 | BK46: 2024 M10 | BL46: 2024 M11 | BM46: 2024 M12 | BN46: 2025 M01 | BO46: 2025 M02 | BP46: 2025 M03 | BQ46: 2025 M04 | BR46: 2025 M05 | BS46: 2025 M06 | BT46: 2025 M07 | BU46: 2025 M08 | BV46: 2025 M09 | BW46: 2025 M10
A47: Contract Model Score | B47: 130.11158 | C47: 132.58721 | D47: 132.51957 | E47: 130.52624 | F47: 130.81177 | G47: 131.22817 | H47: 130.7757 | I47: 131.22612 | J47: 133.84373 | K47: 134.88885 | L47: 135.27071 | M47: 135.5069 | N47: 135.21012 | O47: 134.96814 | P47: 134.44184 | Q47: 135.62832 | R47: 135.75244 | S47: 135.37415 | T47: 135.13442 | U47: 135.4241 | V47: 135.59643 | W47: 135.26407 | X47: 134.74909 | Y47: 136.01685 | Z47: 134.64288 | AA47: 134.7203 | AB47: 132.74586 | AC47: 133.28021 | AD47: 134.15842 | AE47: 134.03079 | AF47: 134.4357 | AG47: 135.84631 | AH47: 136.74788 | AI47: 137.12473 | AJ47: 137.29008 | AK47: 137.43528 | AL47: 137.31444 | AM47: 137.65428 | AN47: 139.51001 | AO47: 139.24031 | AP47: 139.80431 | AQ47: 139.64378 | AR47: 139.15431 | AS47: 138.8767 | AT47: 138.79351 | AU47: 138.60873 | AV47: 137.85409 | AW47: 139.07422 | AX47: 139.50883 | AY47: 139.08714 | AZ47: 138.02994 | BA47: 137.97008 | BB47: 138.101 | BC47: 137.79132 | BD47: 137.14763 | BE47: 138.32927 | BF47: 138.79947 | BG47: 139.23287 | BH47: 139.61094 | BI47: 140.47913 | BJ47: 140.31903 | BK47: 139.36043 | BL47: 138.46656 | BM47: 138.01333 | BN47: 138.10769 | BO47: 138.2144 | BP47: 138.11228 | BQ47: 138.85022 | BR47: 139.3942 | BS47: 139.48226 | BT47: 139.65962 | BU47: 139.31728 | BV47: 139.85819 | BW47: 140.01767 | BX47: 140.18972 | BY47: 141.51071 | BZ47: 142.0291
A48: Model Score | B48: 0.14476272 | C48: 0.094604642 | D48: 0.031815879 | E48: 0.0062374264 | F48: -0.004273285 | G48: 0.0027114611 | H48: -0.0049884992 | I48: -0.00030313823 | J48: -0.0019177329 | K48: 0.0037951115 | L48: 0.0055458507 | M48: -0.00086868553 | N48: -0.00032506095 | O48: 0.010304222 | P48: -0.0019705042 | Q48: 0.0023404144 | R48: 0.00070014254 | S48: 0.0012397096 | T48: 0.00048403908 | U48: 0.0013413238 | V48: -0.0022883767 | W48: 0.0026789797 | X48: 0.0017501801 | Y48: 0.0019554345 | Z48: 0.0025118232 | AA48: 0.0033799321 | AB48: 0.00099183964 | AC48: -0.0090160291 | AD48: 0.00017069218 | AE48: -0.0015788161 | AF48: -0.00054191281 | AG48: 0.00073143445 | AH48: -0.0039262583 | AI48: -0.0061195726 | AJ48: -0.0043411982 | AK48: 0.0038125951 | AL48: -0.0041733927 | AM48: -0.00092146797 | AN48: 0.0077626225 | AO48: -0.0082170845 | AP48: 0.014796119 | AQ48: 0.013161865 | AR48: -0.046875662 | AS48: 0.19853803 | AT48: -0.011978595 | AU48: -0.01194234 | AV48: 0.0091509029 | AW48: -0.037464923 | AX48: -0.017435664 | AY48: -0.0090307931 | AZ48: -0.0047277947 | BA48: 0.0053223359 | BB48: -0.0082899705 | BC48: -0.015618544 | BD48: -0.012732583 | BE48: -0.013755352 | BF48: -0.010011768 | BG48: -0.0045763009 | BH48: -0.0053642968 | BI48: -0.0088524236 | BJ48: 0.017386473 | BK48: -0.021774105 | BL48: 0.018211229 | BM48: -0.0081282552 | BN48: -0.0022246706 | BO48: -0.028454618 | BP48: -0.019052237 | BQ48: -0.029106999 | BR48: -0.016921976 | BS48: -0.011307618 | BT48: -0.0097329219 | BU48: -0.015253242 | BV48: -0.00062547606 | BW48: 0.0012847425 | BX48: 0.017118307 | BY48: -0.0067288978 | BZ48: 0.0064384175
A49: Gross Loss Adjustments (Dealer level, high PTI, etc.) | B49: 0.25888132 | C49: 0.55879279 | D49: 0.56380279 | E49: 0.29260346 | F49: -0.42999134 | G49: -0.41114098 | H49: -0.24740628 | I49: -0.3243085 | J49: -0.062813534 | K49: -0.15315486 | L49: -0.28231842 | M49: -0.26065591 | N49: -0.27263505 | O49: -0.28791604 | P49: -0.25041292 | Q49: -0.073647759 | R49: 0.36529817 | S49: 0.50594971 | T49: 0.52414651 | U49: 0.48191027 | V49: 0.44491035 | W49: 0.16192078 | X49: 0.053763541 | Y49: 0.28541842 | Z49: 0.14262744 | AA49: -0.13440243 | AB49: -0.24015495 | AC49: -0.27822607 | AD49: -0.59556185 | AE49: -0.32031434 | AF49: -0.27839719 | AG49: 0.057353206 | AH49: 0.25733421 | AI49: 0.25681417 | AJ49: 0.40850591 | AK49: 0.25543471 | AL49: -0.011573194 | AM49: 0.035594152 | AN49: 0.32215515 | AO49: 0.61537714 | AP49: 0.15759476 | AQ49: 0.67722273 | AR49: 0.78890158 | AS49: 0.14208007 | AT49: 0.99093078 | AU49: 0.82918491 | AV49: 1.0516168 | AW49: 1.0802685 | AX49: 1.0435048 | AY49: 0.91352773 | AZ49: 0.58531499 | BA49: 0.67206219 | BB49: 0.65372992 | BC49: 0.64844157 | BD49: 0.58862116 | BE49: 0.87811837 | BF49: 1.2374975 | BG49: 1.0939884 | BH49: 1.3378446 | BI49: 1.3087671 | BJ49: 1.3852019 | BK49: 1.2311877 | BL49: 1.260714 | BM49: 1.4255329 | BN49: 1.6395425 | BO49: 1.7839274 | BP49: 1.8348904 | BQ49: 1.6679479 | BR49: 1.8567896 | BS49: 2.0222025 | BT49: 1.8680146 | BU49: 2.5978217 | BV49: 2.9317716 | BW49: 2.6990284 | BX49: 2.9097483 | BY49: 3.2937719 | BZ49: 2.4876898
A50: Recovery Adjustments excluding LTV (Mileage, vehicle type, etc.) | B50: -0.6388852 | C50: -0.026845659 | D50: -0.057946114 | E50: 0.15547296 | F50: 0.17382852 | G50: 0.010905553 | H50: -0.0052296666 | I50: -0.2344502 | J50: -0.31114413 | K50: -0.063510681 | L50: -0.19046285 | M50: -0.018632238 | N50: -0.13543944 | O50: -0.084772547 | P50: -0.30281325 | Q50: 0.29896969 | R50: 0.011703371 | S50: -0.061302756 | T50: -0.50979149 | U50: -0.56869678 | V50: -0.058849618 | W50: -0.41016266 | X50: -0.32095875 | Y50: -0.5717663 | Z50: -0.56443862 | AA50: -0.77872251 | AB50: -0.87734402 | AC50: -0.56701146 | AD50: -0.64658623 | AE50: -0.80072799 | AF50: -1.2036397 | AG50: -2.2640594 | AH50: -2.49278 | AI50: -3.3391836 | AJ50: -3.4889164 | AK50: -3.9050737 | AL50: -3.9548926 | AM50: -3.5087877 | AN50: -5.0080575 | AO50: -3.3928897 | AP50: -3.979162 | AQ50: -3.4556516 | AR50: -3.3085983 | AS50: -3.5879672 | AT50: -2.9377267 | AU50: -3.0963759 | AV50: -3.2930275 | AW50: -3.0616224 | AX50: -3.4372764 | AY50: -2.6441866 | AZ50: -2.914266 | BA50: -2.5432931 | BB50: -2.5635018 | BC50: -2.8451795 | BD50: -2.4018963 | BE50: -2.7908309 | BF50: -2.3840617 | BG50: -2.3767427 | BH50: -1.8887051 | BI50: -2.3114922 | BJ50: -2.8464407 | BK50: -2.460973 | BL50: -2.106814 | BM50: -0.91409647 | BN50: 0.61317659 | BO50: 0.44906672 | BP50: 0.40939508 | BQ50: 0.72351986 | BR50: 0.808283 | BS50: 1.0531235 | BT50: 1.0477508 | BU50: 1.1479608 | BV50: 1.362226 | BW50: 1.684115 | BX50: 1.6073537 | BY50: 1.7665338 | BZ50: 1.5423448
A51: LTV Adjustments | B51: 0.6388852 | C51: 0.026845659 | D51: 0.057946114 | E51: -0.15547296 | F51: -0.17382852 | G51: -0.010905553 | H51: 0.0052296666 | I51: 0.2344502 | J51: 0.31114413 | K51: 0.063510681 | L51: 0.19046285 | M51: 0.018632238 | N51: 0.13543944 | O51: 0.084772547 | P51: 0.30281325 | Q51: -0.29896969 | R51: -0.011703371 | S51: 0.061302756 | T51: 0.50979149 | U51: 0.56869678 | V51: 0.058849618 | W51: 0.41016266 | X51: 0.32095875 | Y51: 0.5717663 | Z51: 0.56443862 | AA51: 0.77872251 | AB51: 0.87734402 | AC51: 0.56701146 | AD51: 0.64658623 | AE51: 0.80072799 | AF51: 1.2036397 | AG51: 2.2640594 | AH51: 2.49278 | AI51: 3.3391836 | AJ51: 3.4889164 | AK51: 3.9050737 | AL51: 3.9548926 | AM51: 3.5087877 | AN51: 5.0080575 | AO51: 3.3928897 | AP51: 3.979162 | AQ51: 3.4556516 | AR51: 3.3085983 | AS51: 3.5879672 | AT51: 2.9377267 | AU51: 3.0963759 | AV51: 3.2930275 | AW51: 3.0616224 | AX51: 3.4372764 | AY51: 2.6441866 | AZ51: 2.914266 | BA51: 2.5432931 | BB51: 2.5635018 | BC51: 2.8451795 | BD51: 2.4018963 | BE51: 2.7908309 | BF51: 2.3840617 | BG51: 2.3767427 | BH51: 1.8887051 | BI51: 2.3114922 | BJ51: 2.8464407 | BK51: 2.460973 | BL51: 2.106814 | BM51: 0.91409647 | BN51: -0.61317659 | BO51: -0.44906672 | BP51: -0.40939508 | BQ51: -0.72351986 | BR51: -0.808283 | BS51: -1.0531235 | BT51: -1.0477508 | BU51: -1.1479608 | BV51: -1.362226 | BW51: -1.684115 | BX51: -1.6073537 | BY51: -1.7665338 | BZ51: -1.5423448
A52: RAGU Score | B52: 130.51522 | C52: 133.24061 | D52: 133.11519 | E52: 130.82508 | F52: 130.37751 | G52: 130.81974 | H52: 130.52331 | I52: 130.9015 | J52: 133.779 | K52: 134.73949 | L52: 134.99394 | M52: 135.24537 | N52: 134.93716 | O52: 134.69052 | P52: 134.18946 | Q52: 135.55701 | R52: 136.11844 | S52: 135.88134 | T52: 135.65905 | U52: 135.90735 | V52: 136.03905 | W52: 135.42867 | X52: 134.8046 | Y52: 136.30422 | Z52: 134.78802 | AA52: 134.58927 | AB52: 132.5067 | AC52: 132.99297 | AD52: 133.56303 | AE52: 133.70889 | AF52: 134.15676 | AG52: 135.9044 | AH52: 137.00129 | AI52: 137.37542 | AJ52: 137.69425 | AK52: 137.69452 | AL52: 137.2987 | AM52: 137.68895 | AN52: 139.83993 | AO52: 139.84747 | AP52: 139.9767 | AQ52: 140.33416 | AR52: 139.89633 | AS52: 139.21732 | AT52: 139.77247 | AU52: 139.42597 | AV52: 138.91486 | AW52: 140.11702 | AX52: 140.5349 | AY52: 139.99164 | AZ52: 138.61053 | BA52: 138.64747 | BB52: 138.74644 | BC52: 138.42414 | BD52: 137.72351 | BE52: 139.19364 | BF52: 140.02696 | BG52: 140.32228 | BH52: 140.94342 | BI52: 141.77904 | BJ52: 141.72162 | BK52: 140.56984 | BL52: 139.74548 | BM52: 139.43073 | BN52: 139.74501 | BO52: 139.96988 | BP52: 139.92812 | BQ52: 140.48906 | BR52: 141.23407 | BS52: 141.49315 | BT52: 141.5179 | BU52: 141.89985 | BV52: 142.78934 | BW52: 142.71798 | BX52: 143.11659 | BY52: 144.79775 | BZ52: 144.52323
A53: LTV | B53: 1.9871158 | C53: 1.934492 | D53: 1.9518253 | E53: 1.947363 | F53: 1.9289789 | G53: 1.9279253 | H53: 1.8656777 | I53: 1.9375063 | J53: 1.9703176 | K53: 1.8891437 | L53: 1.7537259 | M53: 1.7254995 | N53: 1.7282661 | O53: 1.777319 | P53: 1.8785495 | Q53: 1.7560091 | R53: 1.7802242 | S53: 1.7027629 | T53: 1.6130473 | U53: 1.5340264 | V53: 1.4661384 | W53: 1.482054 | X53: 1.5043845 | Y53: 1.5583721 | Z53: 1.6062173 | AA53: 1.584393 | AB53: 1.6231152 | AC53: 1.604914 | AD53: 1.5836633 | AE53: 1.5825251 | AF53: 1.5793716 | AG53: 1.5788553 | AH53: 1.6014391 | AI53: 1.5680937 | AJ53: 1.6114959 | AK53: 1.599928 | AL53: 1.6215947 | AM53: 1.6132002 | AN53: 1.6095096 | AO53: 1.6044767 | AP53: 1.6383362 | AQ53: 1.5827072 | AR53: 1.7086972 | AS53: 1.996546 | AT53: 1.570777 | AU53: 1.4322425 | AV53: 1.4234056 | AW53: 1.4741142 | AX53: 1.5324325 | AY53: 1.4993367 | AZ53: 1.4433369 | BA53: 1.4906636 | BB53: 1.536559 | BC53: 1.5254914 | BD53: 1.526934 | BE53: 1.5260563 | BF53: 1.4994795 | BG53: 1.4660685 | BH53: 1.4575459 | BI53: 1.4838199 | BJ53: 1.5058656 | BK53: 1.5052985 | BL53: 1.4811112 | BM53: 1.4656529 | BN53: 1.4922376 | BO53: 1.5047999 | BP53: 1.4868384 | BQ53: 1.470281 | BR53: 1.4486702 | BS53: 1.4340243 | BT53: 1.4637141 | BU53: 1.4513901 | BV53: 1.4397435 | BW53: 1.4230632 | BX53: 1.442925 | BY53: 1.469394 | BZ53: 1.4906849
A55: KMX | B55: 2016 | C55: 2017 | D55: 2018 | E55: 2019 | F55: 2020 M01 | G55: 2020 M02 | H55: 2020 M03 | I55: 2020 M04 | J55: 2020 M05 | K55: 2020 M06 | L55: 2020 M07 | M55: 2020 M08 | N55: 2020 M09 | O55: 2020 M10 | P55: 2020 M11 | Q55: 2020 M12 | R55: 2021 M01 | S55: 2021 M02 | T55: 2021 M03 | U55: 2021 M04 | V55: 2021 M05 | W55: 2021 M06 | X55: 2021 M07 | Y55: 2021 M08 | Z55: 2021 M09 | AA55: 2021 M10 | AB55: 2021 M11 | AC55: 2021 M12 | AD55: 2022 M01 | AE55: 2022 M02 | AF55: 2022 M03 | AG55: 2022 M04 | AH55: 2022 M05 | AI55: 2022 M06 | AJ55: 2022 M07 | AK55: 2022 M08 | AL55: 2022 M09 | AM55: 2022 M10 | AN55: 2022 M11 | AO55: 2022 M12 | AP55: 2023 M01 | AQ55: 2023 M02 | AR55: 2023 M03 | AS55: 2023 M04 | AT55: 2023 M05 | AU55: 2023 M06 | AV55: 2023 M07 | AW55: 2023 M08 | AX55: 2023 M09 | AY55: 2023 M10 | AZ55: 2023 M11 | BA55: 2023 M12 | BB55: 2024 M01 | BC55: 2024 M02 | BD55: 2024 M03 | BE55: 2024 M04 | BF55: 2024 M05 | BG55: 2024 M06 | BH55: 2024 M07 | BI55: 2024 M08 | BJ55: 2024 M09 | BK55: 2024 M10 | BL55: 2024 M11 | BM55: 2024 M12 | BN55: 2025 M01 | BO55: 2025 M02 | BP55: 2025 M03 | BQ55: 2025 M04 | BR55: 2025 M05 | BS55: 2025 M06 | BT55: 2025 M07 | BU55: 2025 M08 | BV55: 2025 M09 | BW55: 2025 M10
A56: Contract Model Score | B56: 136.5895 | C56: 139.09048 | D56: 137.77551 | E56: 136.87432 | F56: 136.07089 | G56: 136.072 | H56: 135.58403 | I56: 136.45711 | J56: 138.39856 | K56: 139.22263 | L56: 139.32036 | M56: 138.63708 | N56: 138.2905 | O56: 137.41781 | P56: 136.54466 | Q56: 136.92165 | R56: 136.31498 | S56: 135.27484 | T56: 135.16676 | U56: 135.82853 | V56: 135.82742 | W56: 135.5271 | X56: 133.76711 | Y56: 136.00476 | Z56: 133.7143 | AA56: 133.8042 | AB56: 133.04636 | AC56: 132.61153 | AD56: 132.07594 | AE56: 133.41692 | AF56: 133.82905 | AG56: 134.7299 | AH56: 134.34079 | AI56: 135.09973 | AJ56: 135.80114 | AK56: 136.29285 | AL56: 136.07444 | AM56: 137.27668 | AN56: 138.63281 | AO56: 139.28278 | AP56: 140.36935 | AQ56: 139.82238 | AR56: 140.14739 | AS56: 140.44521 | AT56: 140.7383 | AU56: 140.77704 | AV56: 140.66729 | AW56: 140.6335 | AX56: 140.22049 | AY56: 140.06891 | AZ56: 140.93026 | BA56: 140.84393 | BB56: 140.36274 | BC56: 138.53458 | BD56: 140.07862 | BE56: 140.5561 | BF56: 140.57663 | BG56: 140.14334 | BH56: 139.7155 | BI56: 139.73364 | BJ56: 140.27603 | BK56: 140.20095 | BL56: 139.56669 | BM56: 139.57157 | BN56: 139.95679 | BO56: 139.57119 | BP56: 139.68386 | BQ56: 139.80946 | BR56: 139.77613 | BS56: 140.02729 | BT56: 140.13278 | BU56: 139.79082 | BV56: 139.84377 | BW56: 140.21965 | BX56: 140.76906 | BY56: 141.84195 | BZ56: 141.74309
A57: Model Score | B57: 0 | C57: 0 | D57: 0 | E57: 0 | F57: 0 | G57: 0 | H57: 0 | I57: 0 | J57: 0 | K57: 0 | L57: 0 | M57: 0 | N57: 0 | O57: 0 | P57: 0 | Q57: 0 | R57: 0 | S57: 0 | T57: 0 | U57: 0 | V57: 0 | W57: 0 | X57: 0 | Y57: 0 | Z57: 0 | AA57: 0 | AB57: 0 | AC57: 0 | AD57: 0 | AF57: 0 | AG57: 0 | AH57: 0 | AI57: 0 | AJ57: 0 | AK57: 0 | AL57: 0 | AM57: 0 | AN57: 0 | AO57: 0 | AP57: 0 | AQ57: 0 | AR57: 0 | AS57: 0 | AT57: 0 | AU57: 0 | AV57: 0 | AW57: 0 | AX57: 0 | AY57: 0 | BA57: 0 | BB57: 0 | BC57: 0 | BD57: 0 | BE57: 0 | BF57: 0 | BG57: 0 | BH57: 0 | BI57: 0 | BJ57: 0 | BK57: 0 | BL57: 0 | BM57: 0 | BN57: 0 | BO57: 0 | BP57: 0 | BQ57: 0 | BR57: 0 | BS57: 0 | BT57: 0 | BU57: 0 | BV57: 0 | BW57: 0 | BX57: 0 | BY57: 0 | BZ57: 0
A58: Gross Loss Adjustments (Dealer level, high PTI, etc.) | B58: 3.4922814 | C58: 3.6344937 | D58: 3.2436872 | E58: 3.1758138 | F58: 3.1398187 | G58: 3.1539599 | H58: 3.1423493 | I58: 3.2019985 | J58: 3.5271756 | K58: 3.670096 | L58: 3.5299712 | M58: 3.2300371 | N58: 3.2183806 | O58: 3.0088825 | P58: 2.6152346 | Q58: 2.5435833 | R58: 2.4145344 | S58: 2.378202 | T58: 2.3115332 | U58: 2.1852345 | V58: 2.1325229 | W58: 2.074206 | X58: 1.7981692 | Y58: 1.8843891 | Z58: 1.5045428 | AA58: 1.4482617 | AB58: 1.0487565 | AC58: 1.0655974 | AD58: 0.97702345 | AF58: 1.0630689 | AG58: 1.1177189 | AH58: 1.1303963 | AI58: 1.3126921 | AJ58: 1.3971288 | AK58: 1.4831919 | AL58: 1.4229221 | AM58: 1.9587002 | AN58: 2.0986261 | AO58: 2.3693275 | AP58: 2.7816157 | AQ58: 2.7390857 | AR58: 2.5258095 | AS58: 2.7730181 | AT58: 3.0377905 | AU58: 3.0086986 | AV58: 3.0933108 | AW58: 2.8244776 | AX58: 2.9326503 | AY58: 2.7524054 | BA58: 3.4624397 | BB58: 3.455277 | BC58: 3.3660153 | BD58: 3.9494223 | BE58: 4.14497 | BF58: 4.2738201 | BG58: 4.1712112 | BH58: 4.0164603 | BI58: 3.9097006 | BJ58: 4.0733781 | BK58: 3.9719942 | BL58: 3.393385 | BM58: 2.8364618 | BN58: 2.5342397 | BO58: 2.2866928 | BP58: 2.4035881 | BQ58: 2.5297545 | BR58: 3.252369 | BS58: 3.858422 | BT58: 3.8092903 | BU58: 3.649851 | BV58: 3.8553343 | BW58: 3.7216301 | BX58: 3.7477126 | BY58: 5.1346271 | BZ58: 5.86302
A59: Recovery Adjustments excluding LTV (Mileage, vehicle type, etc.) | B59: 0.39805103 | C59: 0.19245283 | D59: -0.013543091 | E59: -0.10316802 | F59: -1.2009702 | G59: -1.3609803 | H59: -1.1507994 | I59: -0.97370944 | J59: -0.56547586 | K59: -0.57563832 | L59: -0.93560319 | M59: -1.0134186 | N59: -1.4168832 | O59: -1.3949661 | P59: -1.5958314 | Q59: -1.7456258 | R59: -1.7294517 | S59: -1.3262683 | T59: -0.57036956 | U59: -0.25074114 | V59: 0.10535863 | W59: 0.5381422 | X59: 0.85637706 | Y59: 1.0909855 | Z59: 0.61886591 | AA59: 0.57547445 | AB59: 0.50069954 | AC59: 0.73083325 | AD59: 0.82128767 | AF59: 0.99405448 | AG59: 0.79501495 | AH59: 0.91738583 | AI59: 0.80921557 | AJ59: 0.79443681 | AK59: 0.77286877 | AL59: 0.42935309 | AM59: 0.44841738 | AN59: -0.065593734 | AO59: -0.25342195 | AP59: -0.37512301 | AQ59: -0.40017045 | AR59: -0.2635966 | AS59: 0.10763904 | AT59: 0.43771397 | AU59: 0.53024176 | AV59: 0.49922781 | AW59: 0.41683401 | AX59: 0.24722194 | AY59: 0.34006375 | BA59: 0.44234629 | BB59: 0.16341837 | BC59: -0.30934203 | BD59: 0.52354845 | BE59: 1.373657 | BF59: 1.3744131 | BG59: 1.4361966 | BH59: 1.1569272 | BI59: 1.1356105 | BJ59: 0.5583978 | BK59: 0.77480621 | BL59: 1.0405074 | BM59: 1.1634127 | BN59: 1.4310525 | BO59: 1.657961 | BP59: 1.6797283 | BQ59: 1.9327595 | BR59: 1.6656841 | BS59: 1.8480279 | BT59: 1.8553619 | BU59: 1.7604046 | BV59: 1.0674649 | BW59: 1.0905578 | BX59: 1.219993 | BY59: 1.7719921 | BZ59: 1.7091152
A60: LTV Adjustments | B60: -0.39805103 | C60: -0.19245283 | D60: 0.013543091 | E60: 0.10316802 | F60: 1.2009702 | G60: 1.3609803 | H60: 1.1507994 | I60: 0.97370944 | J60: 0.56547586 | K60: 0.57563832 | L60: 0.93560319 | M60: 1.0134186 | N60: 1.4168832 | O60: 1.3949661 | P60: 1.5958314 | Q60: 1.7456258 | R60: 1.7294517 | S60: 1.3262683 | T60: 0.57036956 | U60: 0.25074114 | V60: -0.10535863 | W60: -0.5381422 | X60: -0.85637706 | Y60: -1.0909855 | Z60: -0.61886591 | AA60: -0.57547445 | AB60: -0.50069954 | AC60: -0.73083325 | AD60: -0.82128767 | AF60: -0.99405448 | AG60: -0.79501495 | AH60: -0.91738583 | AI60: -0.80921557 | AJ60: -0.79443681 | AK60: -0.77286877 | AL60: -0.42935309 | AM60: -0.44841738 | AN60: 0.065593734 | AO60: 0.25342195 | AP60: 0.37512301 | AQ60: 0.40017045 | AR60: 0.2635966 | AS60: -0.10763904 | AT60: -0.43771397 | AU60: -0.53024176 | AV60: -0.49922781 | AW60: -0.41683401 | AX60: -0.24722194 | AY60: -0.34006375 | BA60: -0.44234629 | BB60: -0.16341837 | BC60: 0.30934203 | BD60: -0.52354845 | BE60: -1.373657 | BF60: -1.3744131 | BG60: -1.4361966 | BH60: -1.1569272 | BI60: -1.1356105 | BJ60: -0.5583978 | BK60: -0.77480621 | BL60: -1.0405074 | BM60: -1.1634127 | BN60: -1.4310525 | BO60: -1.657961 | BP60: -1.6797283 | BQ60: -1.9327595 | BR60: -1.6656841 | BS60: -1.8480279 | BT60: -1.8553619 | BU60: -1.7604046 | BV60: -1.0674649 | BW60: -1.0905578 | BX60: -1.219993 | BY60: -1.7719921 | BZ60: -1.7091152
A61: RAGU Score | B61: 140.08178 | C61: 142.72498 | D61: 141.0192 | E61: 140.05014 | F61: 139.21071 | G61: 139.22596 | H61: 138.72638 | I61: 139.65911 | J61: 141.92574 | K61: 142.89273 | L61: 142.85033 | M61: 141.86711 | N61: 141.50888 | O61: 140.42669 | P61: 139.15989 | Q61: 139.46524 | R61: 138.72952 | S61: 137.65304 | T61: 137.47829 | U61: 138.01376 | V61: 137.95994 | W61: 137.60131 | X61: 135.56528 | Y61: 137.88915 | Z61: 135.21884 | AA61: 135.25246 | AB61: 134.09511 | AC61: 133.67712 | AD61: 133.05297 | AF61: 134.89212 | AG61: 135.84762 | AH61: 135.47118 | AI61: 136.41242 | AJ61: 137.19827 | AK61: 137.77604 | AL61: 137.49736 | AM61: 139.23538 | AN61: 140.73144 | AO61: 141.65211 | AP61: 143.15096 | AQ61: 142.56147 | AR61: 142.6732 | AS61: 143.21822 | AT61: 143.77609 | AU61: 143.78574 | AV61: 143.7606 | AW61: 143.45798 | AX61: 143.15314 | AY61: 142.82131 | BA61: 144.30637 | BB61: 143.81802 | BC61: 141.9006 | BD61: 144.02805 | BE61: 144.70107 | BF61: 144.85045 | BG61: 144.31455 | BH61: 143.73196 | BI61: 143.64334 | BJ61: 144.34941 | BK61: 144.17295 | BL61: 142.96008 | BM61: 142.40804 | BN61: 142.49103 | BO61: 141.85788 | BP61: 142.08745 | BQ61: 142.33922 | BR61: 143.0285 | BS61: 143.88571 | BT61: 143.94207 | BU61: 143.44067 | BV61: 143.6991 | BW61: 143.94128 | BX61: 144.51677 | BY61: 146.97658 | BZ61: 147.60611
A62: LTV | B62: 1.5850275 | C62: 1.5718898 | D62: 1.585609 | E62: 1.6091822 | F62: 1.7423547 | G62: 1.7069369 | H62: 1.6754506 | I62: 1.7505561 | J62: 1.7656216 | K62: 1.7085887 | L62: 1.6026613 | M62: 1.5482849 | N62: 1.5867366 | O62: 1.6719209 | P62: 1.7363212 | Q62: 1.7560464 | R62: 1.7265693 | S62: 1.6406435 | T62: 1.4813266 | U62: 1.4353197 | V62: 1.4283305 | W62: 1.4260054 | X62: 1.4542289 | Y62: 1.5011774 | Z62: 1.4858545 | AA62: 1.4816821 | AB62: 1.4951538 | AC62: 1.4991583 | AD62: 1.6369291 | AF62: 1.5101903 | AG62: 1.5631859 | AH62: 1.5465793 | AI62: 1.5415908 | AJ62: 1.5633593 | AK62: 1.6354017 | AL62: 1.6656693 | AM62: 1.6884543 | AN62: 1.7457721 | AO62: 1.7676352 | AP62: 1.7840074 | AQ62: 1.7269694 | AR62: 1.7686335 | AS62: 1.6781776 | AT62: 1.6339281 | AU62: 1.6796331 | AV62: 1.8435577 | AW62: 1.8176657 | AX62: 1.8310838 | AY62: 1.8048979 | BA62: 1.9285885 | BB62: 1.8748313 | BC62: 2.0143179 | BD62: 1.7479715 | BE62: 1.6647149 | BF62: 1.6262562 | BG62: 1.6304874 | BH62: 1.6977485 | BI62: 1.6740094 | BJ62: 1.6880949 | BK62: 1.6861757 | BL62: 1.6713989 | BM62: 1.6819233 | BN62: 1.6809218 | BO62: 1.6215466 | BP62: 1.6113325 | BQ62: 1.5987275 | BR62: 1.6174399 | BS62: 1.5967552 | BT62: 1.604962 | BU62: 1.607214 | BV62: 1.6341283 | BW62: 1.6332652 | BX62: 1.6211025 | BY62: 1.5605656 | BZ62: 1.5736051
A64: POS | B64: 2016 | C64: 2017 | D64: 2018 | E64: 2019 | F64: 2020 M01 | G64: 2020 M02 | H64: 2020 M03 | I64: 2020 M04 | J64: 2020 M05 | K64: 2020 M06 | L64: 2020 M07 | M64: 2020 M08 | N64: 2020 M09 | O64: 2020 M10 | P64: 2020 M11 | Q64: 2020 M12 | R64: 2021 M01 | S64: 2021 M02 | T64: 2021 M03 | U64: 2021 M04 | V64: 2021 M05 | W64: 2021 M06 | X64: 2021 M07 | Y64: 2021 M08 | Z64: 2021 M09 | AA64: 2021 M10 | AB64: 2021 M11 | AC64: 2021 M12 | AD64: 2022 M01 | AE64: 2022 M02 | AF64: 2022 M03 | AG64: 2022 M04 | AH64: 2022 M05 | AI64: 2022 M06 | AJ64: 2022 M07 | AK64: 2022 M08 | AL64: 2022 M09 | AM64: 2022 M10 | AN64: 2022 M11 | AO64: 2022 M12 | AP64: 2023 M01 | AQ64: 2023 M02 | AR64: 2023 M03 | AS64: 2023 M04 | AT64: 2023 M05 | AU64: 2023 M06 | AV64: 2023 M07 | AW64: 2023 M08 | AX64: 2023 M09 | AY64: 2023 M10 | AZ64: 2023 M11 | BA64: 2023 M12 | BB64: 2024 M01 | BC64: 2024 M02 | BD64: 2024 M03 | BE64: 2024 M04 | BF64: 2024 M05 | BG64: 2024 M06 | BH64: 2024 M07 | BI64: 2024 M08 | BJ64: 2024 M09 | BK64: 2024 M10 | BL64: 2024 M11 | BM64: 2024 M12 | BN64: 2025 M01 | BO64: 2025 M02 | BP64: 2025 M03 | BQ64: 2025 M04 | BR64: 2025 M05 | BS64: 2025 M06 | BT64: 2025 M07 | BU64: 2025 M08 | BV64: 2025 M09 | BW64: 2025 M10
A65: Contract Model Score | B65: 133.97017 | C65: 137.08805 | D65: 136.17767 | E65: 135.22403 | F65: 134.05865 | G65: 134.66007 | H65: 134.03644 | I65: 133.89068 | J65: 136.75845 | K65: 137.79257 | L65: 138.05387 | M65: 137.63875 | N65: 137.33388 | O65: 136.64385 | P65: 136.00634 | Q65: 136.30158 | R65: 135.97522 | S65: 135.14365 | T65: 134.92553 | U65: 135.08979 | V65: 135.09399 | W65: 134.75598 | X65: 133.54133 | Y65: 135.4591 | Z65: 133.55744 | AA65: 133.5372 | AB65: 132.55572 | AC65: 132.2655 | AD65: 132.18319 | AE65: 133.08406 | AF65: 133.50522 | AG65: 134.55731 | AH65: 134.67673 | AI65: 135.27614 | AJ65: 135.84781 | AK65: 136.07802 | AL65: 135.77857 | AM65: 136.26093 | AN65: 137.55745 | AO65: 137.80543 | AP65: 138.55656 | AQ65: 138.62984 | AR65: 138.50618 | AS65: 138.90742 | AT65: 139.36135 | AU65: 138.69173 | AV65: 138.57662 | AW65: 139.25133 | AX65: 139.35696 | AY65: 139.03921 | AZ65: 138.88184 | BA65: 138.91291 | BB65: 138.86981 | BC65: 138.0136 | BD65: 138.34092 | BE65: 138.97095 | BF65: 139.32092 | BG65: 139.41973 | BH65: 139.29997 | BI65: 139.60041 | BJ65: 139.76878 | BK65: 139.13918 | BL65: 138.491 | BM65: 138.20993 | BN65: 138.26959 | BO65: 138.27333 | BP65: 138.33087 | BQ65: 138.81098 | BR65: 139.1685 | BS65: 139.37981 | BT65: 139.5293 | BU65: 139.25464 | BV65: 139.45689 | BW65: 139.66882 | BX65: 140.04555 | BY65: 141.30085 | BZ65: 141.59996
A66: Model Score | B66: -2.3536778 | C66: -0.81646254 | D66: -0.35303694 | E66: -0.54597358 | F66: -0.63383755 | G66: -0.48107002 | H66: -0.42038598 | I66: -0.5606689 | J66: -0.40910978 | K66: -0.33633614 | L66: -0.29350318 | M66: -0.22893334 | N66: -0.19573283 | O66: -0.13553302 | P66: -0.10308741 | Q66: -0.065622553 | R66: -0.032244905 | S66: 0.0012214598 | T66: 0.0020552388 | U66: 0.046943336 | V66: 0.058243685 | W66: 0.05231097 | X66: 0.074250746 | Y66: 0.04540894 | Z66: 0.054816987 | AA66: 0.073216076 | AB66: 0.032491987 | AC66: 0.093870679 | AD66: 0.14773755 | AE66: -0.39985165 | AF66: 0.054283722 | AG66: 0.0032304105 | AH66: 0.0082844666 | AI66: 0.023396989 | AJ66: 0.015892304 | AK66: 0.034179231 | AL66: 0.033932748 | AM66: 0.061805138 | AN66: 0.023145831 | AO66: 0.020786276 | AP66: 0.021142992 | AQ66: -0.021740612 | AR66: 0.27417143 | AS66: 0.96804049 | AT66: -0.09409322 | AU66: -0.19657948 | AV66: -0.95003106 | AW66: -0.67259889 | AX66: -0.43450063 | AY66: -0.43671966 | AZ66: -1.7386919 | BA66: 0.016411567 | BB66: -0.025945097 | BC66: -0.024133047 | BD66: -0.012706914 | BE66: -0.030519923 | BF66: -0.026333431 | BG66: -0.017259384 | BH66: -0.0043646253 | BI66: 0.015129406 | BJ66: -0.0022159901 | BK66: -0.012416741 | BL66: 0.020517514 | BM66: 0.018295263 | BN66: 0.031184865 | BO66: 0.003133437 | BP66: 0.042290921 | BQ66: 0.028459394 | BR66: 0.013538415 | BS66: 0.0022175356 | BT66: -0.0024025684 | BU66: -0.005721839 | BV66: 0.014778475 | BW66: 0.010994809 | BX66: 0.0080253689 | BY66: -0.00047347028 | BZ66: 0.010307975
A67: Gross Loss Adjustments (Dealer level, high PTI, etc.) | B67: 0.95330798 | C67: 2.2816265 | D67: 2.2429229 | E67: 2.1765429 | F67: 1.4100542 | G67: 1.6102068 | H67: 1.5835485 | I67: 1.1753799 | J67: 1.9078184 | K67: 2.0307787 | L67: 1.9252132 | M67: 1.7595987 | N67: 1.7684083 | O67: 1.4946567 | P67: 1.3798067 | Q67: 1.1865414 | R67: 1.3894985 | S67: 1.4310875 | T67: 1.396966 | U67: 1.129762 | V67: 1.0562156 | W67: 0.86876736 | X67: 0.78079598 | Y67: 0.9539369 | Z67: 0.68232955 | AA67: 0.64168844 | AB67: 0.36077239 | AC67: 0.27302133 | AD67: 0.04959112 | AE67: -0.49836072 | AF67: 0.48984567 | AG67: 0.5484902 | AH67: 0.65737186 | AI67: 0.70775961 | AJ67: 0.82960765 | AK67: 0.76920452 | AL67: 0.61403238 | AM67: 0.93116651 | AN67: 1.1039884 | AO67: 1.280569 | AP67: 1.3136091 | AQ67: 1.719463 | AR67: 1.5658429 | AS67: 2.2792606 | AT67: 1.9712296 | AU67: 1.5680829 | AV67: 1.3141783 | AW67: 1.3480825 | AX67: 1.5399906 | AY67: 1.4537233 | AZ67: 0.42563865 | BA67: 1.7989329 | BB67: 1.8023721 | BC67: 2.0465994 | BD67: 1.9506329 | BE67: 1.9740689 | BF67: 2.3489755 | BG67: 2.3038336 | BH67: 2.2784145 | BI67: 2.4301413 | BJ67: 2.3722146 | BK67: 2.2150733 | BL67: 2.152398 | BM67: 1.8509726 | BN67: 1.7340802 | BO67: 1.7599016 | BP67: 1.8191856 | BQ67: 1.8200082 | BR67: 2.3072339 | BS67: 2.6662848 | BT67: 2.5205401 | BU67: 2.8210795 | BV67: 3.08471 | BW67: 3.0073304 | BX67: 3.1966185 | BY67: 4.1064345 | BZ67: 4.6195111
A68: Recovery Adjustments excluding LTV (Mileage, vehicle type, etc.) | B68: -0.39159333 | C68: 0.10678239 | D68: -0.022411573 | E68: -0.0062930866 | F68: -0.55575278 | G68: -0.76528164 | H68: -0.60959727 | I68: -0.51272099 | J68: -0.39005623 | K68: -0.30972317 | L68: -0.57764334 | M68: -0.57669314 | N68: -0.85839294 | O68: -0.81051355 | P68: -1.0549242 | Q68: -0.89624534 | R68: -1.0083272 | S68: -0.81150025 | T68: -0.45938104 | U68: -0.29709539 | V68: 0.025351512 | W68: 0.095741173 | X68: 0.3177716 | Y68: 0.37521976 | Z68: 0.10046654 | AA68: 0.020351805 | AB68: -0.058686785 | AC68: 0.090885878 | AD68: -0.021679572 | AE68: -0.84814161 | AF68: 0.16651439 | AG68: -0.30776569 | AH68: -0.18005604 | AI68: -0.59435999 | AJ68: -0.58141372 | AK68: -0.80451796 | AL68: -1.0829094 | AM68: -0.85876749 | AN68: -1.3810873 | AO68: -1.1084371 | AP68: -1.2736921 | AQ68: -1.0326611 | AR68: -0.92895249 | AS68: -0.26049189 | AT68: -0.56215548 | AU68: -0.75368939 | AV68: -1.1950403 | AW68: -1.2408671 | AX68: -1.4777853 | AY68: -1.1692497 | AZ68: -2.3920877 | BA68: -0.95053218 | BB68: -1.0846581 | BC68: -1.2413848 | BD68: -0.93066086 | BE68: -0.86804318 | BF68: -0.59249514 | BG68: -0.49823944 | BH68: -0.34991951 | BI68: -0.33550128 | BJ68: -0.92250266 | BK68: -0.77382876 | BL68: -0.2668386 | BM68: 0.18532134 | BN68: 0.90472015 | BO68: 1.0419906 | BP68: 0.95610928 | BQ68: 1.1281298 | BR68: 1.1063262 | BS68: 1.2872308 | BT68: 1.2712297 | BU68: 1.3004196 | BV68: 1.0606035 | BW68: 1.1962998 | BX68: 1.2479507 | BY68: 1.6469215 | BZ68: 1.5828045
A69: LTV Adjustments | B69: 0.39159333 | C69: -0.10678239 | D69: 0.022411573 | E69: 0.0062930866 | F69: 0.55575278 | G69: 0.76528164 | H69: 0.60959727 | I69: 0.51272099 | J69: 0.39005623 | K69: 0.30972317 | L69: 0.57764334 | M69: 0.57669314 | N69: 0.85839294 | O69: 0.81051355 | P69: 1.0549242 | Q69: 0.89624534 | R69: 1.0083272 | S69: 0.81150025 | T69: 0.45938104 | U69: 0.29709539 | V69: -0.025351512 | W69: -0.095741173 | X69: -0.3177716 | Y69: -0.37521976 | Z69: -0.10046654 | AA69: -0.020351805 | AB69: 0.058686785 | AC69: -0.090885878 | AD69: 0.021679572 | AE69: 0.84814161 | AF69: -0.16651439 | AG69: 0.30776569 | AH69: 0.18005604 | AI69: 0.59435999 | AJ69: 0.58141372 | AK69: 0.80451796 | AL69: 1.0829094 | AM69: 0.85876749 | AN69: 1.3810873 | AO69: 1.1084371 | AP69: 1.2736921 | AQ69: 1.0326611 | AR69: 0.92895249 | AS69: 0.26049189 | AT69: 0.56215548 | AU69: 0.75368939 | AV69: 1.1950403 | AW69: 1.2408671 | AX69: 1.4777853 | AY69: 1.1692497 | AZ69: 2.3920877 | BA69: 0.95053218 | BB69: 1.0846581 | BC69: 1.2413848 | BD69: 0.93066086 | BE69: 0.86804318 | BF69: 0.59249514 | BG69: 0.49823944 | BH69: 0.34991951 | BI69: 0.33550128 | BJ69: 0.92250266 | BK69: 0.77382876 | BL69: 0.2668386 | BM69: -0.18532134 | BN69: -0.90472015 | BO69: -1.0419906 | BP69: -0.95610928 | BQ69: -1.1281298 | BR69: -1.1063262 | BS69: -1.2872308 | BT69: -1.2712297 | BU69: -1.3004196 | BV69: -1.0606035 | BW69: -1.1962998 | BX69: -1.2479507 | BY69: -1.6469215 | BZ69: -1.5828045
A70: RAGU Score | B70: 132.5698 | C70: 138.55321 | D70: 138.06756 | E70: 136.8546 | F70: 134.83487 | G70: 135.7892 | H70: 135.19961 | I70: 134.50539 | J70: 138.25716 | K70: 139.48701 | L70: 139.68558 | M70: 139.16941 | N70: 138.90656 | O70: 138.00297 | P70: 137.28306 | Q70: 137.4225 | R70: 137.33248 | S70: 136.57595 | T70: 136.32455 | U70: 136.2665 | V70: 136.20845 | W70: 135.67706 | X70: 134.39638 | Y70: 136.45845 | Z70: 134.29459 | AA70: 134.2521 | AB70: 132.94899 | AC70: 132.63239 | AD70: 132.38052 | AE70: 132.18585 | AF70: 134.04935 | AG70: 135.10903 | AH70: 135.34239 | AI70: 136.0073 | AJ70: 136.69331 | AK70: 136.88141 | AL70: 136.42653 | AM70: 137.25391 | AN70: 138.68458 | AO70: 139.10679 | AP70: 139.89131 | AQ70: 140.32756 | AR70: 140.34619 | AS70: 142.15472 | AT70: 141.23849 | AU70: 140.06324 | AV70: 138.94077 | AW70: 139.92682 | AX70: 140.46245 | AY70: 140.05621 | AZ70: 137.56879 | BA70: 140.72826 | BB70: 140.64624 | BC70: 140.03606 | BD70: 140.27885 | BE70: 140.9145 | BF70: 141.64356 | BG70: 141.7063 | BH70: 141.57402 | BI70: 142.04568 | BJ70: 142.13878 | BK70: 141.34184 | BL70: 140.66392 | BM70: 140.0792 | BN70: 140.03485 | BO70: 140.03636 | BP70: 140.19235 | BQ70: 140.65945 | BR70: 141.48927 | BS70: 142.04831 | BT70: 142.04744 | BU70: 142.07 | BV70: 142.55638 | BW70: 142.68715 | BX70: 143.25019 | BY70: 145.40681 | BZ70: 146.22978
A71: LTV | B71: 1.9007606 | C71: 1.7313827 | D71: 1.7223672 | E71: 1.723625 | F71: 1.7997993 | G71: 1.7642871 | H71: 1.7151763 | I71: 1.7667218 | J71: 1.8004438 | K71: 1.746113 | L71: 1.6221841 | M71: 1.5686919 | N71: 1.5978729 | O71: 1.668137 | P71: 1.736738 | Q71: 1.7047749 | R71: 1.6998966 | S71: 1.6245633 | T71: 1.49555 | U71: 1.4371097 | V71: 1.4155777 | W71: 1.4188075 | X71: 1.4487039 | Y71: 1.4986436 | Z71: 1.506641 | AA71: 1.4995121 | AB71: 1.5182801 | AC71: 1.5239045 | AD71: 1.5769952 | AE71: 1.5305929 | AF71: 1.5159513 | AG71: 1.5449834 | AH71: 1.5415957 | AI71: 1.5181942 | AJ71: 1.5494931 | AK71: 1.5878068 | AL71: 1.603615 | AM71: 1.6099141 | AN71: 1.6520792 | AO71: 1.6577759 | AP71: 1.6690791 | AQ71: 1.6375364 | AR71: 1.7072075 | AS71: 1.7042845 | AT71: 1.5651377 | AU71: 1.5328054 | AV71: 1.5574747 | AW71: 1.5632984 | AX71: 1.6107554 | AY71: 1.5731908 | AZ71: 1.4029686 | BA71: 1.6648544 | BB71: 1.6661697 | BC71: 1.7727928 | BD71: 1.5929456 | BE71: 1.5457922 | BF71: 1.5280469 | BG71: 1.5197252 | BH71: 1.5478521 | BI71: 1.5605731 | BJ71: 1.5622004 | BK71: 1.5577194 | BL71: 1.5574987 | BM71: 1.5469876 | BN71: 1.5498536 | BO71: 1.5395445 | BP71: 1.519661 | BQ71: 1.5019408 | BR71: 1.5046835 | BS71: 1.4886668 | BT71: 1.5041807 | BU71: 1.5053464 | BV71: 1.5185865 | BW71: 1.5045787 | BX71: 1.5146106 | BY71: 1.5029989 | BZ71: 1.5336663

Sheet Waterfall Tables
A1: AN
A2: Vintage | B2: None | C2: Previous ACA chargeoff | D2: Small amount financed | E2: Zero cash down | F2: High mileage vehicle | G2: High PTI | H2: Car make | I2: Theft risk | J2: MCY high model score, low mileage | K2: Weekday/weekend decision | L2: Secured credit (Chime, etc.) | M2: Employment type | N2: High cash down EchoPark | O2: Authorized tradelines | P2: Clip | Q2: Vehicle Age | R2: Dealer Level (Non-KMX) | S2: Mileage/age | T2: Japanese | U2: Vehicle class | V2: Fuel type | W2: Luxury classification | X2: LOB | Y2: Driver flag | Z2: Impound probability | AA2: Job time | AB2: Low FICO | AC2: Low Vantage | AD2: Louisiana | AE2: Existing DQ | AF2: Null FICO with Vantage | AG2: Soft Pull
A3: 2016 Q1 | B3: 0 | C3: -0.088849019 | D3: -0.009560662 | E3: -0.055668889 | F3: -0.43648122 | G3: -0.017747536 | H3: 0.2844119 | I3: 0.2511436 | J3: 0 | K3: 0.017442999 | L3: -0.63058383 | M3: 0 | N3: 0 | O3: -0.042806452 | P3: 0.13421102 | Q3: 0 | R3: 0.666524 | S3: 0 | T3: 0 | U3: 0 | V3: 0 | W3: 0 | X3: 0 | Y3: 0 | Z3: 0 | AA3: 0 | AB3: 0 | AC3: 0 | AD3: 0 | AE3: 0 | AF3: -0.14050087 | AG3: 0
A4: 2016 Q2 | B4: 0 | C4: -0.016332403 | D4: -0.0084102165 | E4: -0.10106913 | F4: -0.41665541 | G4: -0.022255339 | H4: 0.27247612 | I4: 0.27296891 | J4: 0 | K4: -0.033041539 | L4: -0.025449251 | M4: 0 | N4: 0 | O4: -0.0158258 | P4: 0.041150486 | Q4: 0 | R4: 0.56269949 | S4: 0 | T4: 0 | U4: 0 | V4: 0 | W4: 0 | X4: 0 | Y4: 0 | Z4: 0 | AA4: 0 | AB4: 0 | AC4: 0 | AD4: 0 | AE4: 0 | AF4: 0.071119222 | AG4: 0
A5: 2016 Q3 | B5: 0 | C5: -0.0086610508 | D5: -0.0090471231 | E5: -0.12312524 | F5: -0.37133885 | G5: -0.013071307 | H5: 0.33112637 | I5: 0.2844547 | J5: 0 | K5: -0.05951543 | L5: 0.24055522 | M5: 0 | N5: 0 | O5: 0 | P5: 0.00035605691 | Q5: 0 | R5: 0.42579935 | S5: 0 | T5: 0 | U5: 0 | V5: 0 | W5: 0 | X5: 0 | Y5: 0 | Z5: 0 | AA5: 0 | AB5: 0 | AC5: 0 | AD5: 0 | AE5: 0 | AF5: 0.218672 | AG5: 0
A6: 2016 Q4 | B6: 0 | C6: -0.018426974 | D6: -0.01060248 | E6: -0.11562108 | F6: -0.33294813 | G6: -0.02198921 | H6: 0.39490129 | I6: 0.28135824 | J6: 0 | K6: -0.030195971 | L6: 0.2379768 | M6: 0 | N6: 0 | O6: 0 | P6: 0.0016167563 | Q6: 0 | R6: 0.51074025 | S6: 0 | T6: 0 | U6: 0 | V6: 0 | W6: 0 | X6: 0 | Y6: 0 | Z6: 0 | AA6: 0 | AB6: 0 | AC6: 0 | AD6: 0 | AE6: 0 | AF6: 0.21635181 | AG6: 0
A7: 2017 Q1 | B7: 0 | C7: -0.015804407 | D7: -0.014542724 | E7: -0.084214279 | F7: -0.35084252 | G7: -0.016345841 | H7: 0.32339842 | I7: 0.27959447 | J7: 0 | K7: -0.029003851 | L7: 0.23643041 | M7: 0 | N7: 0 | O7: -0.0092166125 | P7: 0.0014012386 | Q7: 0 | R7: 0.73157821 | S7: 0 | T7: 0 | U7: 0 | V7: 0 | W7: 0 | X7: 0 | Y7: 0 | Z7: 0 | AA7: 0 | AB7: 0 | AC7: 0 | AD7: 0 | AE7: 0 | AF7: 0.21491379 | AG7: 0
A8: 2017 Q2 | B8: 0 | C8: -0.023581612 | D8: -0.014813655 | E8: -0.11192379 | F8: -0.31483375 | G8: -0.011060914 | H8: 0.31222253 | I8: 0.28077869 | J8: 0 | K8: -0.056025421 | L8: 0.23761528 | M8: 0 | N8: 0 | O8: -0.0089687167 | P8: 0.0069448185 | Q8: 0 | R8: 0.52616729 | S8: 0 | T8: 0 | U8: 0 | V8: 0 | W8: 0 | X8: 0 | Y8: 0 | Z8: 0 | AA8: 0 | AB8: 0 | AC8: 0 | AD8: 0 | AE8: 0 | AF8: 0.21609898 | AG8: 0
A9: 2017 Q3 | B9: 0 | C9: -0.031593722 | D9: -0.010026636 | E9: -0.1308173 | F9: -0.32215106 | G9: -0.017742758 | H9: 0.33867224 | I9: 0.28057654 | J9: 0 | K9: -0.016288366 | L9: 0.23736072 | M9: 0 | N9: 0 | O9: -0.013442456 | P9: 0.0022972636 | Q9: 0 | R9: 0.60268324 | S9: 0 | T9: 0 | U9: 0 | V9: 0 | W9: 0 | X9: 0 | Y9: 0 | Z9: 0 | AA9: 0 | AB9: 0 | AC9: 0 | AD9: 0 | AE9: 0 | AF9: 0.21581828 | AG9: 0
A10: 2017 Q4 | B10: 0 | C10: -0.028999663 | D10: -0.010891458 | E10: -0.1193385 | F10: -0.30182908 | G10: -0.021758245 | H10: 0.31155832 | I10: 0.27933776 | J10: 0 | K10: -0.054242585 | L10: 0.23630397 | M10: 0 | N10: 0 | O10: -0.0059058477 | P10: 0.0011977711 | Q10: 0 | R10: 0.74321981 | S10: 0 | T10: 0 | U10: 0 | V10: 0 | W10: 0 | X10: 0 | Y10: 0 | Z10: 0 | AA10: 0 | AB10: 0 | AC10: 0 | AD10: 0 | AE10: 0 | AF10: 0.21485228 | AG10: 0
A11: 2018 Q1 | B11: 0 | C11: -0.028383621 | D11: -0.013130635 | E11: -0.092487996 | F11: -0.34469312 | G11: -0.010962788 | H11: 0.29344602 | I11: 0.27774239 | J11: 0 | K11: -0.02840682 | L11: 0.23498879 | M11: 0 | N11: 0 | O11: -0.022229646 | P11: 0.0010404969 | Q11: 0 | R11: 0.86504317 | S11: 0 | T11: 0 | U11: 0 | V11: 0 | W11: 0 | X11: 0 | Y11: 0 | Z11: 0 | AA11: 0 | AB11: 0 | AC11: 0 | AD11: 0 | AE11: 0 | AF11: 0.21367676 | AG11: 0
A12: 2018 Q2 | B12: 0 | C12: -0.021828868 | D12: -0.010576574 | E12: -0.083738872 | F12: -0.32091486 | G12: -0.014716883 | H12: 0.27210379 | I12: 0.27842983 | J12: 0 | K12: -0.038582272 | L12: 0.23546453 | M12: 0 | N12: 0 | O12: -0.01778007 | P12: 0.0024239912 | Q12: 0 | R12: 0.83497923 | S12: 0 | T12: 0 | U12: 0 | V12: 0 | W12: 0 | X12: 0 | Y12: 0 | Z12: 0 | AA12: 0 | AB12: 0 | AC12: 0 | AD12: 0 | AE12: 0 | AF12: 0.21404698 | AG12: 0
A13: 2018 Q3 | B13: 0 | C13: -0.026568185 | D13: -0.012874472 | E13: -0.13136604 | F13: -0.34734141 | G13: -0.0095121611 | H13: 0.33227491 | I13: 0.27904036 | J13: 0 | K13: -0.046784944 | L13: 0.23610745 | M13: 0 | N13: 0 | O13: -0.019099697 | P13: 0.0039980488 | Q13: 0 | R13: 0.71744418 | S13: 0 | T13: 0 | U13: 0 | V13: 0 | W13: 0 | X13: 0 | Y13: 0 | Z13: 0 | AA13: 0 | AB13: 0 | AC13: 0 | AD13: 0 | AE13: 0 | AF13: 0.21470604 | AG13: 0
A14: 2018 Q4 | B14: 0 | C14: -0.024672695 | D14: -0.010848323 | E14: -0.11390881 | F14: -0.40481772 | G14: -0.010395055 | H14: 0.30955733 | I14: 0.28002584 | J14: 0 | K14: -0.029127988 | L14: 0.23706238 | M14: 0 | N14: 0 | O14: -0.028696174 | P14: 0.0020729703 | Q14: 0 | R14: 0.65860642 | S14: 0 | T14: 0 | U14: 0 | V14: 0 | W14: 0 | X14: 0 | Y14: 0 | Z14: 0 | AA14: 0 | AB14: 0 | AC14: 0 | AD14: 0 | AE14: 0 | AF14: 0.21564574 | AG14: 0
... A39: 2025 Q1 | B39: 0 | C39: -0.0016042812 | D39: 0 | E39: 0 | F39: -0.013297931 | G39: 0 | H39: 1.7023993 | I39: 0 | J39: 0 | K39: 0.049289801 | L39: -0.24648853 | M39: 0.0080948058 | N39: 0 | O39: -0.032902349 | P39: -0.11680056 | Q39: 0 | R39: 1.252034 | S39: 0 | T39: 0 | U39: 0 | V39: 0 | W39: 0 | X39: 0 | Y39: 0 | Z39: 0 | AA39: 0 | AB39: 0 | AC39: 0 | AD39: 0 | AE39: 0 | AF39: -0.0014657352 | AG39: 0
B40: 0
B41: 0
B42: 0
B43: 0
B44: 0
B45: 0
A46: FRN | B46: 0
A47: Vintage | B47: 0 | C47: Previous ACA chargeoff | D47: Small amount financed | E47: Zero cash down | F47: High mileage vehicle | G47: High PTI | H47: Car make | I47: Theft risk | J47: MCY high model score, low mileage | K47: Weekday/weekend decision | L47: Secured credit (Chime, etc.) | M47: Employment type | N47: High cash down EchoPark | O47: Authorized tradelines | P47: Clip | Q47: Vehicle Age | R47: Dealer Level (Non-KMX) | S47: Mileage/age | T47: Japanese | U47: Vehicle class | V47: Fuel type | W47: Luxury classification | X47: LOB | Y47: Driver flag | Z47: Impound probability | AA47: Job time | AB47: Low FICO | AC47: Low Vantage | AD47: Louisiana | AE47: Existing DQ | AF47: Null FICO with Vantage | AG47: Soft Pull
A48: 2016 Q1 | B48: 0 | C48: -0.066487452 | D48: -0.015468452 | E48: -0.14534016 | F48: -0.6285997 | G48: -0.0093342212 | H48: 0.17529678 | I48: 0.25829076 | J48: 0 | K48: -0.099797012 | L48: -0.59657888 | M48: 0 | N48: 0 | O48: -0.03808574 | P48: 0.19956806 | Q48: 0 | R48: -0.91242482 | S48: 0 | T48: 0 | U48: 0 | V48: 0 | W48: 0 | X48: 0 | Y48: 0 | Z48: 0 | AA48: 0 | AB48: 0 | AC48: 0 | AD48: 0 | AE48: 0 | AF48: -0.070534535 | AG48: 0
A49: 2016 Q2 | B49: 0 | C49: -0.021585175 | D49: -0.012453993 | E49: -0.21920307 | F49: -0.59428089 | G49: -0.0082439271 | H49: 0.19597396 | I49: 0.29095851 | J49: 0 | K49: -0.11932985 | L49: 0.05143236 | M49: 0 | N49: 0 | O49: -0.010495363 | P49: 0.041691873 | Q49: 0 | R49: -0.75015297 | S49: 0 | T49: 0 | U49: 0 | V49: 0 | W49: 0 | X49: 0 | Y49: 0 | Z49: 0 | AA49: 0 | AB49: 0 | AC49: 0 | AD49: 0 | AE49: 0 | AF49: 0.14839927 | AG49: 0
A50: 2016 Q3 | B50: 0 | C50: -0.00057730205 | D50: -0.010364941 | E50: -0.24518989 | F50: -0.49533814 | G50: -0.014812538 | H50: 0.17699904 | I50: 0.29172756 | J50: 0 | K50: -0.10739042 | L50: 0.24721746 | M50: 0 | N50: 0 | O50: 0 | P50: 0.0024082344 | Q50: 0 | R50: -0.030255776 | S50: 0 | T50: 0 | U50: 0 | V50: 0 | W50: 0 | X50: 0 | Y50: 0 | Z50: 0 | AA50: 0 | AB50: 0 | AC50: 0 | AD50: 0 | AE50: 0 | AF50: 0.22502985 | AG50: 0
A51: 2016 Q4 | B51: 0 | C51: -0.013656674 | D51: -0.01462645 | E51: -0.22887229 | F51: -0.43866306 | G51: -0.0085183794 | H51: 0.16089446 | I51: 0.28767877 | J51: 0 | K51: -0.10790836 | L51: 0.24349288 | M51: 0 | N51: 0 | O51: -0.0011503766 | P51: 0.0033717002 | Q51: 0 | R51: 0.42097954 | S51: 0 | T51: 0 | U51: 0 | V51: 0 | W51: 0 | X51: 0 | Y51: 0 | Z51: 0 | AA51: 0 | AB51: 0 | AC51: 0 | AD51: 0 | AE51: 0 | AF51: 0.22146688 | AG51: 0
A52: 2017 Q1 | B52: 0 | C52: -0.0060864618 | D52: -0.030437735 | E52: -0.12809885 | F52: -0.37574677 | G52: -0.0069271107 | H52: 0.18746687 | I52: 0.29316511 | J52: 0 | K52: -0.11959357 | L52: 0.24813809 | M52: 0 | N52: 0 | O52: -0.017806779 | P52: 0.0059782634 | Q52: 0 | R52: -0.19214078 | S52: 0 | T52: 0 | U52: 0 | V52: 0 | W52: 0 | X52: 0 | Y52: 0 | Z52: 0 | AA52: 0 | AB52: 0 | AC52: 0 | AD52: 0 | AE52: 0 | AF52: 0.22569281 | AG52: 0
A53: 2017 Q2 | B53: 0 | C53: -0.0096765878 | D53: -0.037301417 | E53: -0.12666074 | F53: -0.3323577 | G53: 0 | H53: 0.22652935 | I53: 0.29250789 | J53: 0 | K53: -0.11888954 | L53: 0.247598 | M53: 0 | N53: 0 | O53: -0.0055099648 | P53: 0.0012741952 | Q53: 0 | R53: -0.2261259 | S53: 0 | T53: 0 | U53: 0 | V53: 0 | W53: 0 | X53: 0 | Y53: 0 | Z53: 0 | AA53: 0 | AB53: 0 | AC53: 0 | AD53: 0 | AE53: 0 | AF53: 0.22521111 | AG53: 0
A54: 2017 Q3 | B54: 0 | C54: -0.020905501 | D54: -0.048216142 | E54: -0.14365869 | F54: -0.30999971 | G54: 0 | H54: 0.17095009 | I54: 0.29361924 | J54: 0 | K54: -0.12155819 | L54: 0.2485119 | M54: 0 | N54: 0 | O54: -0.0083271219 | P54: 0.0014977648 | Q54: 0 | R54: -0.18755365 | S54: 0 | T54: 0 | U54: 0 | V54: 0 | W54: 0 | X54: 0 | Y54: 0 | Z54: 0 | AA54: 0 | AB54: 0 | AC54: 0 | AD54: 0 | AE54: 0 | AF54: 0.22602657 | AG54: 0
A55: 2017 Q4 | B55: 0 | C55: -0.011009458 | D55: -0.062386538 | E55: -0.15643326 | F55: -0.27984876 | G55: -0.0094114415 | H55: 0.15834046 | I55: 0.293549 | J55: 0 | K55: -0.12377057 | L55: 0.24797565 | M55: 0 | N55: 0 | O55: -0.014872248 | P55: 0.0069859529 | Q55: 0 | R55: 0.032548543 | S55: 0 | T55: 0 | U55: 0 | V55: 0 | W55: 0 | X55: 0 | Y55: 0 | Z55: 0 | AA55: 0 | AB55: 0 | AC55: 0 | AD55: 0 | AE55: 0 | AF55: 0.22525803 | AG55: 0
A56: 2018 Q1 | B56: 0 | C56: -0.0037112405 | D56: -0.062979423 | E56: -0.10290878 | F56: -0.33564161 | G56: -0.0081656737 | H56: 0.17707709 | I56: 0.29514473 | J56: 0 | K56: -0.10537582 | L56: 0.24976704 | M56: 0 | N56: 0 | O56: -0.0088560257 | P56: 0.0016022162 | Q56: 0 | R56: -0.32758673 | S56: 0 | T56: 0 | U56: 0 | V56: 0 | W56: 0 | X56: 0 | Y56: 0 | Z56: 0 | AA56: 0 | AB56: 0 | AC56: 0 | AD56: 0 | AE56: 0 | AF56: 0.22714694 | AG56: 0
A57: 2018 Q2 | B57: 0 | C57: -0.019040795 | D57: -0.048931757 | E57: -0.13637734 | F57: -0.37900483 | G57: 0 | H57: 0.15343342 | I57: 0.29709816 | J57: 0 | K57: -0.14362225 | L57: 0.25166089 | M57: 0 | N57: 0 | O57: -0.01896619 | P57: 0.0084890457 | Q57: 0 | R57: -0.55183173 | S57: 0 | T57: 0 | U57: 0 | V57: 0 | W57: 0 | X57: 0 | Y57: 0 | Z57: 0 | AA57: 0 | AB57: 0 | AC57: 0 | AD57: 0 | AE57: 0 | AF57: 0.2290111 | AG57: 0
A58: 2018 Q3 | B58: 0 | C58: -0.021657242 | D58: -0.055874623 | E58: -0.13086659 | F58: -0.38834316 | G58: 0 | H58: 0.13189847 | I58: 0.29727113 | J58: 0 | K58: -0.091788596 | L58: 0.25159003 | M58: 0 | N58: 0 | O58: -0.0032975088 | P58: 0.0099732251 | Q58: 0 | R58: -0.46083937 | S58: 0 | T58: 0 | U58: 0 | V58: 0 | W58: 0 | X58: 0 | Y58: 0 | Z58: 0 | AA58: 0 | AB58: 0 | AC58: 0 | AD58: 0 | AE58: 0 | AF58: 0.2288187 | AG58: 0
A59: 2018 Q4 | B59: 0 | C59: -0.015119677 | D59: -0.051643511 | E59: -0.18995899 | F59: -0.4322657 | G59: -0.0068365923 | H59: 0.18879901 | I59: 0.29803881 | J59: 0 | K59: -0.095723055 | L59: 0.25225077 | M59: 0 | N59: 0 | O59: -0.041091504 | P59: 0.015040954 | Q59: 0 | R59: -0.49889607 | S59: 0 | T59: 0 | U59: 0 | V59: 0 | W59: 0 | X59: 0 | Y59: 0 | Z59: 0 | AA59: 0 | AB59: 0 | AC59: 0 | AD59: 0 | AE59: 0 | AF59: 0.22942613 | AG59: 0
... A84: 2025 Q1 | B84: 0 | C84: -0.0058173884 | D84: 0 | E84: 0 | F84: -0.0065081629 | G84: 0 | H84: 1.5330391 | I84: 0 | J84: 0 | K84: -0.0051340888 | L84: -0.28711705 | M84: -0.0067693859 | N84: 0 | O84: -0.03630832 | P84: -0.086228609 | Q84: 0 | R84: 0.47955529 | S84: 0 | T84: 0 | U84: 0 | V84: 0 | W84: 0 | X84: 0 | Y84: 0 | Z84: 0 | AA84: 0 | AB84: 0 | AC84: 0 | AD84: 0 | AE84: 0 | AF84: 0.0026578804 | AG84: 0
B85: 0
B86: 0
B87: 0
B88: 0
B89: 0
A90: STG | B90: 0
A91: Vintage | B91: 0 | C91: Previous ACA chargeoff | D91: Small amount financed | E91: Zero cash down | F91: High mileage vehicle | G91: High PTI | H91: Car make | I91: Theft risk | J91: MCY high model score, low mileage | K91: Weekday/weekend decision | L91: Secured credit (Chime, etc.) | M91: Employment type | N91: High cash down EchoPark | O91: Authorized tradelines | P91: Clip | Q91: Vehicle Age | R91: Dealer Level (Non-KMX) | S91: Mileage/age | T91: Japanese | U91: Vehicle class | V91: Fuel type | W91: Luxury classification | X91: LOB | Y91: Driver flag | Z91: Impound probability | AA91: Job time | AB91: Low FICO | AC91: Low Vantage | AD91: Louisiana | AE91: Existing DQ | AF91: Null FICO with Vantage | AG91: Soft Pull
A92: 2016 Q1 | B92: 0 | C92: -0.091078532 | D92: -0.0095684872 | E92: -0.14538103 | F92: -0.38064137 | G92: -0.012235844 | H92: 0.35341087 | I92: 0.25315122 | J92: 0 | K92: -0.045844378 | L92: -0.63093451 | M92: 0 | N92: 0 | O92: -0.045542626 | P92: 0.10401354 | Q92: 0 | R92: 0.97238659 | S92: 0 | T92: 0 | U92: 0 | V92: 0 | W92: 0 | X92: 0 | Y92: 0 | Z92: 0 | AA92: 0 | AB92: 0 | AC92: 0 | AD92: 0 | AE92: 0 | AF92: -0.069292497 | AG92: 0
A93: 2016 Q2 | B93: 0 | C93: -0.018090698 | D93: -0.0072472404 | E93: -0.17177773 | F93: -0.37463703 | G93: -0.013990776 | H93: 0.29910132 | I93: 0.26934283 | J93: 0 | K93: -0.047048504 | L93: -0.0055836038 | M93: 0 | N93: 0 | O93: -0.014885544 | P93: 0.017415347 | Q93: 0 | R93: 1.094301 | S93: 0 | T93: 0 | U93: 0 | V93: 0 | W93: 0 | X93: 0 | Y93: 0 | Z93: 0 | AA93: 0 | AB93: 0 | AC93: 0 | AD93: 0 | AE93: 0 | AF93: 0.11669397 | AG93: 0
A94: 2016 Q3 | B94: 0 | C94: -0.0032172649 | D94: -0.006829119 | E94: -0.26099162 | F94: -0.35050482 | G94: -0.014546265 | H94: 0.27905334 | I94: 0.28211501 | J94: 0 | K94: -0.091686656 | L94: 0.23883065 | M94: 0 | N94: 0 | O94: 0 | P94: 0.0032867029 | Q94: 0 | R94: 0.63240486 | S94: 0 | T94: 0 | U94: 0 | V94: 0 | W94: 0 | X94: 0 | Y94: 0 | Z94: 0 | AA94: 0 | AB94: 0 | AC94: 0 | AD94: 0 | AE94: 0 | AF94: 0.21725405 | AG94: 0
A95: 2016 Q4 | B95: 0 | C95: -0.0072504695 | D95: -0.0059838668 | E95: -0.26603942 | F95: -0.34303693 | G95: -0.013215052 | H95: 0.27567249 | I95: 0.28254706 | J95: 0 | K95: -0.05819382 | L95: 0.23909213 | M95: 0 | N95: 0 | O95: 0 | P95: 0.0024544575 | Q95: 0 | R95: 0.64178642 | S95: 0 | T95: 0 | U95: 0 | V95: 0 | W95: 0 | X95: 0 | Y95: 0 | Z95: 0 | AA95: 0 | AB95: 0 | AC95: 0 | AD95: 0 | AE95: 0 | AF95: 0.21743051 | AG95: 0
A96: 2017 Q1 | B96: 0 | C96: -0.011198287 | D96: -0.0067422861 | E96: -0.17899301 | F96: -0.34655294 | G96: -0.013848969 | H96: 0.3137282 | I96: 0.28078417 | J96: 0 | K96: -0.083753819 | L96: 0.23748244 | M96: 0 | N96: 0 | O96: -0.014468919 | P96: 0.00075881154 | Q96: 0 | R96: 0.75442649 | S96: 0 | T96: 0 | U96: 0 | V96: 0 | W96: 0 | X96: 0 | Y96: 0 | Z96: 0 | AA96: 0 | AB96: 0 | AC96: 0 | AD96: 0 | AE96: 0 | AF96: 0.21589719 | AG96: 0
A97: 2017 Q2 | B97: 0 | C97: -0.0092107182 | D97: -0.0063933096 | E97: -0.21249064 | F97: -0.31373329 | G97: -0.018082519 | H97: 0.29570034 | I97: 0.27965948 | J97: 0 | K97: -0.092271235 | L97: 0.23671342 | M97: 0 | N97: 0 | O97: -0.0042582178 | P97: 0.0022624699 | Q97: 0 | R97: 0.75744224 | S97: 0 | T97: 0 | U97: 0 | V97: 0 | W97: 0 | X97: 0 | Y97: 0 | Z97: 0 | AA97: 0 | AB97: 0 | AC97: 0 | AD97: 0 | AE97: 0 | AF97: 0.21530546 | AG97: 0
A98: 2017 Q3 | B98: 0 | C98: -0.031617846 | D98: -0.0062505989 | E98: -0.25833418 | F98: -0.3116857 | G98: -0.019981751 | H98: 0.28242561 | I98: 0.27783583 | J98: 0 | K98: -0.08542652 | L98: 0.2351577 | M98: 0 | N98: 0 | O98: -0.01209805 | P98: 0.004671287 | Q98: 0 | R98: 0.96686246 | S98: 0 | T98: 0 | U98: 0 | V98: 0 | W98: 0 | X98: 0 | Y98: 0 | Z98: 0 | AA98: 0 | AB98: 0 | AC98: 0 | AD98: 0 | AE98: 0 | AF98: 0.2138833 | AG98: 0
A99: 2017 Q4 | B99: 0 | C99: -0.025271102 | D99: -0.0044305337 | E99: -0.2526816 | F99: -0.31146047 | G99: -0.025014072 | H99: 0.27794682 | I99: 0.28232246 | J99: 0 | K99: -0.087285029 | L99: 0.23894487 | M99: 0 | N99: 0 | O99: -0.0066110284 | P99: 0.0064212981 | Q99: 0 | R99: 0.5910451 | S99: 0 | T99: 0 | U99: 0 | V99: 0 | W99: 0 | X99: 0 | Y99: 0 | Z99: 0 | AA99: 0 | AB99: 0 | AC99: 0 | AD99: 0 | AE99: 0 | AF99: 0.21732179 | AG99: 0
A100: 2018 Q1 | B100: 0 | C100: -0.018256228 | D100: -0.0081043168 | E100: -0.18010387 | F100: -0.34296108 | G100: -0.0090977419 | H100: 0.29396258 | I100: 0.27909063 | J100: 0 | K100: -0.054247492 | L100: 0.23614784 | M100: 0 | N100: 0 | O100: -0.012780934 | P100: 0.0030365109 | Q100: 0 | R100: 0.82097909 | S100: 0 | T100: 0 | U100: 0 | V100: 0 | W100: 0 | X100: 0 | Y100: 0 | Z100: 0 | AA100: 0 | AB100: 0 | AC100: 0 | AD100: 0 | AE100: 0 | AF100: 0.21474151 | AG100: 0
A101: 2018 Q2 | B101: 0 | C101: -0.012622146 | D101: -0.0075697092 | E101: -0.20479022 | F101: -0.33138476 | G101: -0.011743598 | H101: 0.32203238 | I101: 0.27894566 | J101: 0 | K101: -0.074380555 | L101: 0.23598595 | M101: 0 | N101: 0 | O101: -0.018265334 | P101: 0.002859743 | Q101: 0 | R101: 0.85239485 | S101: 0 | T101: 0 | U101: 0 | V101: 0 | W101: 0 | X101: 0 | Y101: 0 | Z101: 0 | AA101: 0 | AB101: 0 | AC101: 0 | AD101: 0 | AE101: 0 | AF101: 0.21457119 | AG101: 0
A102: 2018 Q3 | B102: 0 | C102: -0.018712669 | D102: -0.0077433179 | E102: -0.28420244 | F102: -0.37867361 | G102: -0.011233117 | H102: 0.28516719 | I102: 0.28157634 | J102: 0 | K102: -0.062912849 | L102: 0.23845841 | M102: 0 | N102: 0 | O102: -0.023438059 | P102: 0.0046993695 | Q102: 0 | R102: 0.65274229 | S102: 0 | T102: 0 | U102: 0 | V102: 0 | W102: 0 | X102: 0 | Y102: 0 | Z102: 0 | AA102: 0 | AB102: 0 | AC102: 0 | AD102: 0 | AE102: 0 | AF102: 0.21696477 | AG102: 0
A103: 2018 Q4 | B103: 0 | C103: -0.018445759 | D103: -0.0078370801 | E103: -0.25650566 | F103: -0.41531571 | G103: -0.024647266 | H103: 0.27128521 | I103: 0.28249966 | J103: 0 | K103: -0.064023771 | L103: 0.2392466 | M103: 0 | N103: 0 | O103: -0.011256653 | P103: 0.0094368679 | Q103: 0 | R103: 0.56745839 | S103: 0 | T103: 0 | U103: 0 | V103: 0 | W103: 0 | X103: 0 | Y103: 0 | Z103: 0 | AA103: 0 | AB103: 0 | AC103: 0 | AD103: 0 | AE103: 0 | AF103: 0.2176856 | AG103: 0
... A128: 2025 Q1 | B128: 0 | C128: -0.002136841 | D128: 0 | E128: 0 | F128: -0.020436307 | G128: 0 | H128: 1.6711935 | I128: 0 | J128: 0 | K128: -0.018485462 | L128: -0.23716319 | M128: -0.0013200347 | N128: 0 | O128: -0.052797234 | P128: -0.088417135 | Q128: 0 | R128: 2.2904164 | S128: 0 | T128: 0 | U128: 0 | V128: 0 | W128: 0 | X128: 0 | Y128: 0 | Z128: 0 | AA128: 0 | AB128: 0 | AC128: 0 | AD128: 0 | AE128: 0 | AF128: 0.0028771196 | AG128: 0
B129: 0
B130: 0
B131: 0
B132: 0
A133: FLD | B133: 0
A134: Vintage | B134: 0 | C134: Previous ACA chargeoff | D134: Small amount financed | E134: Zero cash down | F134: High mileage vehicle | G134: High PTI | H134: Car make | I134: Theft risk | J134: MCY high model score, low mileage | K134: Weekday/weekend decision | L134: Secured credit (Chime, etc.) | M134: Employment type | N134: High cash down EchoPark | O134: Authorized tradelines | P134: Clip | Q134: Vehicle Age | R134: Dealer Level (Non-KMX) | S134: Mileage/age | T134: Japanese | U134: Vehicle class | V134: Fuel type | W134: Luxury classification | X134: LOB | Y134: Driver flag | Z134: Impound probability | AA134: Job time | AB134: Low FICO | AC134: Low Vantage | AD134: Louisiana | AE134: Existing DQ | AF134: Null FICO with Vantage | AG134: Soft Pull
A135: 2019 Q3 | B135: 0 | C135: -0.042212116 | D135: -0.0099141396 | E135: -0.21798384 | F135: -0.33973781 | G135: -0.077858336 | H135: 0.2353209 | I135: 0.26300398 | J135: 0 | K135: -0.055684829 | L135: -0.7392567 | M135: 0 | N135: 0 | O135: -0.080991995 | P135: 0.10951516 | Q135: 0 | R135: 0.29594119 | S135: 0 | T135: 0 | U135: 0 | V135: 0 | W135: 0 | X135: 0 | Y135: 0 | Z135: 0 | AA135: 0 | AB135: 0 | AC135: 0 | AD135: 0 | AE135: 0 | AF135: -0.061482649 | AG135: 0
A136: 2019 Q4 | B136: 0 | C136: 0 | D136: -0.0090808834 | E136: -0.23751189 | F136: -0.27638546 | G136: 0 | H136: 0.20283638 | I136: 0.24002301 | J136: 0 | K136: 0.083510483 | L136: -0.076318031 | M136: 0 | N136: 0 | O136: 0 | P136: 0.052853794 | Q136: 0 | R136: 3.1775803 | S136: 0 | T136: 0 | U136: 0 | V136: 0 | W136: 0 | X136: 0 | Y136: 0 | Z136: 0 | AA136: 0 | AB136: 0 | AC136: 0 | AD136: 0 | AE136: 0 | AF136: 0.056571607 | AG136: 0
A137: 2020 Q1 | B137: 0 | C137: 0 | D137: -0.0066976863 | E137: -0.35601349 | F137: -0.25736679 | G137: -0.044084827 | H137: 0.11294235 | I137: 0.27261247 | J137: 0 | K137: -0.012290365 | L137: 0.23074928 | M137: 0 | N137: 0 | O137: 0 | P137: 0 | Q137: 0 | R137: 1.5756844 | S137: 0 | T137: 0 | U137: 0 | V137: 0 | W137: 0 | X137: 0 | Y137: 0 | Z137: 0 | AA137: 0 | AB137: 0 | AC137: 0 | AD137: 0 | AE137: 0 | AF137: 0.20988111 | AG137: 0
A138: 2020 Q2 | B138: 0 | C138: 0 | D138: -0.0062449178 | E138: -0.47759908 | F138: -0.31568735 | G138: 0 | H138: 0.17367753 | I138: 0.29219397 | J138: 0 | K138: 0.023228861 | L138: 0.24719964 | M138: 0 | N138: 0 | O138: 0 | P138: 0 | Q138: 0 | R138: 0.12130033 | S138: 0 | T138: 0 | U138: 0 | V138: 0 | W138: 0 | X138: 0 | Y138: 0 | Z138: 0 | AA138: 0 | AB138: 0 | AC138: 0 | AD138: 0 | AE138: 0 | AF138: 0.22477065 | AG138: 0
A139: 2020 Q3 | B139: 0 | C139: 0 | D139: 0 | E139: -0.14689004 | F139: -0.12776922 | G139: 0 | H139: 0.21326186 | I139: 0.28389489 | J139: 0 | K139: -0.073631604 | L139: 0.24042547 | M139: 0 | N139: 0 | O139: -0.0098234864 | P139: 0 | Q139: 0 | R139: 0.14340082 | S139: 0 | T139: 0 | U139: 0 | V139: 0 | W139: 0 | X139: 0 | Y139: 0 | Z139: 0 | AA139: 0 | AB139: 0 | AC139: 0 | AD139: 0 | AE139: 0 | AF139: 0.21875662 | AG139: 0
A140: 2020 Q4 | B140: 0 | C140: 0 | D140: -0.0023229251 | E140: -0.13560248 | F140: -0.059212902 | G140: 0 | H140: 0.21372336 | I140: 0.29052039 | J140: 0 | K140: -0.15891026 | L140: 0.24532783 | M140: 0 | N140: 0 | O140: -0.035638776 | P140: 0 | Q140: 0 | R140: 0.090534468 | S140: 0 | T140: 0 | U140: 0 | V140: 0 | W140: 0 | X140: 0 | Y140: 0 | Z140: 0 | AA140: 0 | AB140: 0 | AC140: 0 | AD140: 0 | AE140: 0 | AF140: 0.22280002 | AG140: 0
A141: 2021 Q1 | B141: 0 | C141: -0.033356095 | D141: 0 | E141: -0.25692796 | F141: -0.0655235 | G141: 0 | H141: 0.13228028 | I141: 0.29006032 | J141: 0 | K141: -0.13461706 | L141: 0.24547676 | M141: 0 | N141: 0 | O141: -0.01325525 | P141: 0 | Q141: 0 | R141: 0 | S141: 0 | T141: 0 | U141: 0 | V141: 0 | W141: 0 | X141: 0 | Y141: 0 | Z141: 0 | AA141: 0 | AB141: 0 | AC141: 0 | AD141: 0 | AE141: 0 | AF141: 0.22325253 | AG141: 0
A142: 2021 Q2 | B142: 0 | C142: -0.032484737 | D142: 0 | E142: -0.32826733 | F142: -0.013439183 | G142: -0.041192884 | H142: 0.19137106 | I142: 0.25371329 | J142: 0 | K142: -0.11747863 | L142: 0.21498694 | M142: 0 | N142: 0 | O142: 0 | P142: 0 | Q142: 0 | R142: 2.6465638 | S142: 0 | T142: 0 | U142: 0 | V142: 0 | W142: 0 | X142: 0 | Y142: 0 | Z142: 0 | AA142: 0 | AB142: 0 | AC142: 0 | AD142: 0 | AE142: 0 | AF142: 0.19568244 | AG142: 0
A143: 2021 Q3 | B143: 0 | C143: 0 | D143: 0 | E143: -0.10473246 | F143: -0.024743692 | G143: -0.026821609 | H143: 0.23474928 | I143: 0.25632962 | J143: 0 | K143: -0.049097905 | L143: 0.21645568 | M143: 0 | N143: 0 | O143: -0.038715486 | P143: 0 | Q143: 0 | R143: 2.5195525 | S143: 0 | T143: 0 | U143: 0 | V143: 0 | W143: 0 | X143: 0 | Y143: 0 | Z143: 0 | AA143: 0 | AB143: 0 | AC143: 0 | AD143: 0 | AE143: 0 | AF143: 0.19657913 | AG143: 0
A144: 2021 Q4 | B144: 0 | C144: -0.015466174 | D144: -0.003380976 | E144: -0.28939198 | F144: -0.0067422208 | G144: 0 | H144: 0.15571763 | I144: 0.24818701 | J144: 0 | K144: -0.033578013 | L144: 0.20996725 | M144: 0 | N144: 0 | O144: -0.037044878 | P144: 0 | Q144: 0 | R144: 3.1696732 | S144: 0 | T144: 0 | U144: 0 | V144: 0 | W144: 0 | X144: 0 | Y144: 0 | Z144: 0 | AA144: 0 | AB144: 0 | AC144: 0 | AD144: 0 | AE144: 0 | AF144: 0.19091528 | AG144: 0
A145: 2022 Q1 | B145: 0 | C145: -0.020818951 | D145: 0 | E145: -0.18962254 | F145: -0.031145337 | G145: 0 | H145: 0.19965272 | I145: 0.27088628 | J145: 0 | K145: -0.12506961 | L145: 0.22874794 | M145: 0 | N145: 0 | O145: 0 | P145: 0 | Q145: 0 | R145: 1.5890791 | S145: 0 | T145: 0 | U145: 0 | V145: 0 | W145: 0 | X145: 0 | Y145: 0 | Z145: 0 | AA145: 0 | AB145: 0 | AC145: 0 | AD145: 0 | AE145: 0 | AF145: 0.20774262 | AG145: 0
A146: 2022 Q2 | B146: 0 | C146: -0.023393105 | D146: -0.002023148 | E146: -0.31929298 | F146: -0.026034792 | G146: -0.020209609 | H146: 0.18867647 | I146: 0.28356106 | J146: 0 | K146: -0.096239716 | L146: 0.23972989 | M146: 0 | N146: 0 | O146: -0.041551598 | P146: 0 | Q146: 0 | R146: 0.63023545 | S146: 0 | T146: 0 | U146: 0 | V146: 0 | W146: 0 | X146: 0 | Y146: 0 | Z146: 0 | AA146: 0 | AB146: 0 | AC146: 0 | AD146: 0 | AE146: 0 | AF146: 0.21788071 | AG146: 0
... A157: 2025 Q1 | B157: 0 | C157: -0.013794458 | D157: -0.00075988691 | E157: -0.17537584 | F157: -0.047721977 | G157: -0.071187448 | H157: 0.22059297 | I157: 0.27693616 | J157: 0 | K157: -0.033823786 | L157: 0.2340399 | M157: 0 | N157: 0 | O157: -0.042099819 | P157: 0.0019122036 | Q157: 0 | R157: 0.98796802 | S157: 0 | T157: 0 | U157: 0 | V157: 0 | W157: 0 | X157: 0 | Y157: 0 | Z157: 0 | AA157: 0 | AB157: 0 | AC157: 0 | AD157: 0 | AE157: 0 | AF157: 0.21265677 | AG157: 0
B158: 0 | C158: -0.012291591 | D158: -0.00029385588 | E158: -0.17413886 | F158: -0.062218914 | G158: -0.080213835 | H158: 0.20458715 | I158: 0.26942175 | J158: 0 | K158: -0.071417143 | L158: 0.22772776 | M158: 0 | N158: 0 | O158: -0.036895596 | P158: 0.0022232701 | Q158: 0 | R158: 1.6228995 | S158: 0 | T158: 0 | U158: 0 | V158: 0 | W158: 0 | X158: 0 | Y158: 0 | Z158: 0 | AA158: 0 | AB158: 0 | AC158: 0 | AD158: 0 | AE158: 0 | AF158: 0.20694394 | AG158: 0
B159: 0 | C159: -0.011635804 | D159: -0.0013698658 | E159: -0.12248411 | F159: -0.1367736 | G159: -0.041376945 | H159: 0.20772005 | I159: 0.27445766 | J159: 0 | K159: -0.058046452 | L159: 0.2322105 | M159: 0 | N159: 0 | O159: -0.039924404 | P159: 0 | Q159: 0 | R159: 1.0918486 | S159: 0 | T159: 0 | U159: 0 | V159: 0 | W159: 0 | X159: 0 | Y159: 0 | Z159: 0 | AA159: 0 | AB159: 0 | AC159: 0 | AD159: 0 | AE159: 0 | AF159: 0.21115093 | AG159: 0
B160: 0 | C160: -0.0089178714 | D160: -0.0021716267 | E160: -0.065105688 | F160: -0.057825077 | G160: -0.084586809 | H160: 0.18739103 | I160: 0.27905589 | J160: 0 | K160: -0.085539248 | L160: 0.23575157 | M160: 0 | N160: 0 | O160: -0.049046563 | P160: 0 | Q160: 0 | R160: 0.88721385 | S160: 0 | T160: 0 | U160: 0 | V160: 0 | W160: 0 | X160: 0 | Y160: 0 | Z160: 0 | AA160: 0 | AB160: 0 | AC160: 0 | AD160: 0 | AE160: 0 | AF160: 0.21416503 | AG160: 0
B161: 0 | C161: -0.0058626632 | D161: -0.0024358857 | E161: -0.07886478 | F161: -0.035421352 | G161: -0.026402699 | H161: 0.20347621 | I161: 0.15285399 | J161: 0 | K161: -0.051305045 | L161: 0.23421559 | M161: 0 | N161: 0 | O161: -0.037985855 | P161: 0.0028798199 | Q161: 0 | R161: 0.93655224 | S161: 0 | T161: 0 | U161: 0 | V161: 0 | W161: 0 | X161: 0 | Y161: 0 | Z161: 0 | AA161: 0 | AB161: 0 | AC161: 0 | AD161: 0 | AE161: 0 | AF161: 0.21283571 | AG161: 0
A162: ENT | B162: 0 | C162: 0 | D162: -0.003917651 | E162: -0.044848968 | F162: -0.013906228 | G162: -0.10029585 | H162: 0.31526159 | I162: 0.15973718 | J162: 0 | K162: -0.087246056 | L162: 0.23391365 | M162: 0 | N162: 0 | O162: -0.10450438 | P162: 0 | Q162: 0 | R162: 0.75502032 | S162: 0 | T162: 0 | U162: 0 | V162: 0 | W162: 0 | X162: 0 | Y162: 0 | Z162: 0 | AA162: 0 | AB162: 0 | AC162: 0 | AD162: 0 | AE162: 0 | AF162: 0.21280334 | AG162: 0
A163: Vintage | B163: 0 | C163: -0.0086255047 | D163: -0.0056347643 | E163: -0.0042178043 | F163: -0.011177866 | G163: -0.0092690823 | H163: 0.29196103 | I163: 0.13243076 | J163: 0 | K163: -0.011554212 | L163: 0.0085112495 | M163: 0 | N163: 0 | O163: -0.031178683 | P163: 0.0010383537 | Q163: 0 | R163: 1.3406773 | S163: 0 | T163: 0 | U163: 0 | V163: 0 | W163: 0 | X163: 0 | Y163: 0 | Z163: 0 | AA163: 0 | AB163: 0 | AC163: 0 | AD163: 0 | AE163: 0 | AF163: 0.20712166 | AG163: 0
A164: 2019 Q4 | B164: 0 | C164: 0 | D164: 0 | E164: -0.91301462 | F164: 0 | G164: -0.0060828657 | H164: 0.064952178 | I164: 0.30069135 | J164: 0 | K164: -0.10490832 | L164: 0.25410512 | M164: 0 | N164: 0 | O164: -0.011935971 | P164: 0 | Q164: 0 | R164: 0 | S164: 0 | T164: 0 | U164: 0 | V164: 0 | W164: 0 | X164: 0 | Y164: 0 | Z164: 0 | AA164: 0 | AB164: 0 | AC164: 0 | AD164: 0 | AE164: 0 | AF164: 0.23088259 | AG164: 0
A165: 2020 Q1 | B165: 0 | C165: -0.0060180705 | D165: 0 | E165: -0.38159159 | F165: -0.00059962951 | G165: -0.014968144 | H165: 0.051346829 | I165: 0.29508538 | J165: 0 | K165: -0.11182283 | L165: 0.2492465 | M165: 0 | N165: 0 | O165: -0.012673943 | P165: 0 | Q165: 0 | R165: 0 | S165: 0 | T165: 0 | U165: 0 | V165: 0 | W165: 0 | X165: 0 | Y165: 0 | Z165: 0 | AA165: 0 | AB165: 0 | AC165: 0 | AD165: 0 | AE165: 0 | AF165: 0.22639652 | AG165: 0
A166: 2020 Q2 | B166: 0 | C166: -0.0078167083 | D166: 0 | E166: -0.19851024 | F166: 0 | G166: -0.023540361 | H166: 0.026300831 | I166: 0.29427692 | J166: 0 | K166: -0.18587257 | L166: 0.24853763 | M166: 0 | N166: 0 | O166: -0.01281071 | P166: 0 | Q166: 0 | R166: 0 | S166: 0 | T166: 0 | U166: 0 | V166: 0 | W166: 0 | X166: 0 | Y166: 0 | Z166: 0 | AA166: 0 | AB166: 0 | AC166: 0 | AD166: 0 | AE166: 0 | AF166: 0.22573728 | AG166: 0
A167: 2020 Q3 | B167: 0 | C167: -0.010989553 | D167: 0 | E167: -0.20829735 | F167: -0.0009549216 | G167: -0.037552731 | H167: 0.073203946 | I167: 0.29268076 | J167: 0 | K167: -0.18181866 | L167: 0.24720798 | M167: 0 | N167: 0 | O167: -0.020119446 | P167: 0.0010565148 | Q167: 0 | R167: 0.087806471 | S167: 0 | T167: 0 | U167: 0 | V167: 0 | W167: 0 | X167: 0 | Y167: 0 | Z167: 0 | AA167: 0 | AB167: 0 | AC167: 0 | AD167: 0 | AE167: 0 | AF167: 0.22454049 | AG167: 0
A168: 2020 Q4 | B168: 0 | C168: -0.016162092 | D168: 0 | E168: -0.34827 | F168: 0 | G168: -0.048440732 | H168: 0.057374981 | I168: 0.29987006 | J168: 0 | K168: -0.14784345 | L168: 0.25328064 | M168: 0 | N168: 0 | O168: -0.016194671 | P168: 0.00071732288 | Q168: 0 | R168: -0.33114421 | S168: 0 | T168: 0 | U168: 0 | V168: 0 | W168: 0 | X168: 0 | Y168: 0 | Z168: 0 | AA168: 0 | AB168: 0 | AC168: 0 | AD168: 0 | AE168: 0 | AF168: 0.23005652 | AG168: 0
A169: 2021 Q1 | B169: 0 | C169: -0.010135597 | D169: 0 | E169: -0.26651389 | F169: -0.00047634651 | G169: -0.056031087 | H169: 0.073611697 | I169: 0.29600056 | J169: 0 | K169: -0.11869235 | L169: 0.25002983 | M169: 0 | N169: 0 | O169: -0.023081531 | P169: 9.926066e-05 | Q169: 0 | R169: -0.16025668 | S169: 0 | T169: 0 | U169: 0 | V169: 0 | W169: 0 | X169: 0 | Y169: 0 | Z169: 0 | AA169: 0 | AB169: 0 | AC169: 0 | AD169: 0 | AE169: 0 | AF169: 0.22711412 | AG169: 0
A170: 2021 Q2 | B170: 0 | C170: -0.0077402308 | D170: 0 | E170: -0.26414103 | F170: 0 | G170: -0.12376011 | H170: 0.12131368 | I170: 0.29546402 | J170: 0 | K170: -0.16206219 | L170: 0.24963824 | M170: 0 | N170: 0 | O170: -0.017523923 | P170: 0.00012517702 | Q170: 0 | R170: -0.10594406 | S170: 0 | T170: 0 | U170: 0 | V170: 0 | W170: 0 | X170: 0 | Y170: 0 | Z170: 0 | AA170: 0 | AB170: 0 | AC170: 0 | AD170: 0 | AE170: 0 | AF170: 0.22679478 | AG170: 0
A171: 2021 Q3 | B171: 0 | C171: -0.0062423296 | D171: 0 | E171: -0.40702472 | F171: 0 | G171: -0.11133221 | H171: 0.12461512 | I171: 0.29463735 | J171: 0 | K171: -0.17944943 | L171: 0.2490189 | M171: 0 | N171: 0 | O171: -0.030195397 | P171: 0 | Q171: 0 | R171: 0.072554215 | S171: 0 | T171: 0 | U171: 0 | V171: 0 | W171: 0 | X171: 0 | Y171: 0 | Z171: 0 | AA171: 0 | AB171: 0 | AC171: 0 | AD171: 0 | AE171: 0 | AF171: 0.22627879 | AG171: 0
A172: 2021 Q4 | B172: 0 | C172: -0.014094377 | D172: 0 | E172: -0.50301626 | F172: 0 | G172: -0.10230574 | H172: 0.14571045 | I172: 0.29356197 | J172: 0 | K172: -0.18914641 | L172: 0.24826527 | M172: 0 | N172: 0 | O172: -0.028210339 | P172: 0.00313187 | Q172: 0 | R172: 0.12286205 | S172: 0 | T172: 0 | U172: 0 | V172: 0 | W172: 0 | X172: 0 | Y172: 0 | Z172: 0 | AA172: 0 | AB172: 0 | AC172: 0 | AD172: 0 | AE172: 0 | AF172: 0.22568555 | AG172: 0
A173: 2022 Q1 | B173: 0 | C173: -0.0070807689 | D173: 0 | E173: -0.33761481 | F173: -0.00045862264 | G173: -0.092104138 | H173: 0.11160135 | I173: 0.29000857 | J173: 0 | K173: -0.18150716 | L173: 0.24511146 | M173: 0 | N173: 0 | O173: -0.019423972 | P173: 0.0018974911 | Q173: 0 | R173: 0.33387217 | S173: 0 | T173: 0 | U173: 0 | V173: 0 | W173: 0 | X173: 0 | Y173: 0 | Z173: 0 | AA173: 0 | AB173: 0 | AC173: 0 | AD173: 0 | AE173: 0 | AF173: 0.22273093 | AG173: 0
... A185: 2025 Q1 | B185: 0 | C185: -0.0010999407 | D185: 0 | E185: 0 | F185: 0 | G185: 0 | H185: 2.4499664 | I185: 0 | J185: 0 | K185: -0.079108279 | L185: -0.37316397 | M185: 0.0091965016 | N185: 0 | O185: -0.026768295 | P185: -0.089103734 | Q185: 0 | R185: 0.25091525 | S185: 0 | T185: 0 | U185: 0 | V185: 0 | W185: 0 | X185: 0 | Y185: 0 | Z185: 0 | AA185: 0 | AB185: 0 | AC185: 0 | AD185: 0 | AE185: 0 | AF185: 0.0010356647 | AG185: 0
B186: 0
B187: 0
A188: KMX | B188: 0
A189: Vintage | B189: 0 | C189: Previous ACA chargeoff | D189: Small amount financed | E189: Zero cash down | F189: High mileage vehicle | G189: High PTI | H189: Car make | I189: Theft risk | J189: MCY high model score, low mileage | K189: Weekday/weekend decision | L189: Secured credit (Chime, etc.) | M189: Employment type | N189: High cash down EchoPark | O189: Authorized tradelines | P189: Clip | Q189: Vehicle Age | R189: Dealer Level (Non-KMX) | S189: Mileage/age | T189: Japanese | U189: Vehicle class | V189: Fuel type | W189: Luxury classification | X189: LOB | Y189: Driver flag | Z189: Impound probability | AA189: Job time | AB189: Low FICO | AC189: Low Vantage | AD189: Louisiana | AE189: Existing DQ | AF189: Null FICO with Vantage | AG189: Soft Pull
A190: 2016 Q1 | B190: 0 | C190: 0 | D190: 0 | E190: 0 | F190: 0 | G190: -0.42935241 | H190: 0 | I190: 0 | J190: 0 | K190: 0 | L190: -0.23514772 | M190: 0 | N190: 0 | O190: 0.0042536417 | P190: 0.10144122 | Q190: 1.9962504 | R190: 0 | S190: 0 | T190: 0 | U190: 0 | V190: 0 | W190: 0 | X190: 0 | Y190: 0 | Z190: 0 | AA190: -0.61254974 | AB190: -0.18347931 | AC190: -0.0079853412 | AD190: -0.11420445 | AE190: -0.20275031 | AF190: -0.15191857 | AG190: 0.42250908
A191: 2016 Q2 | B191: 0 | C191: 0 | D191: 0 | E191: 0 | F191: 0 | G191: -0.28787541 | H191: 0 | I191: 0 | J191: 0 | K191: 0 | L191: 0.12315291 | M191: 0 | N191: 0 | O191: 0.17131424 | P191: 0.049254079 | Q191: 1.8802485 | R191: 0 | S191: 0 | T191: 0 | U191: 0 | V191: 0 | W191: 0 | X191: 0 | Y191: 0 | Z191: 0 | AA191: -0.71232911 | AB191: -0.20285202 | AC191: -0.0038364925 | AD191: -0.086625861 | AE191: -0.013534933 | AF191: 0.13256985 | AG191: 0.39444866
A192: 2016 Q3 | B192: 0 | C192: 0 | D192: 0 | E192: 0 | F192: 0 | G192: -0.35097826 | H192: 0 | I192: 0 | J192: 0 | K192: 0 | L192: 0.20092622 | M192: 0 | N192: 0 | O192: 0.20092622 | P192: 0.032236815 | Q192: 1.7618754 | R192: 0 | S192: 0 | T192: 0 | U192: 0 | V192: 0 | W192: 0 | X192: 0 | Y192: 0 | Z192: 0 | AA192: -0.82145812 | AB192: -0.21665616 | AC192: 0 | AD192: -0.10787365 | AE192: 0 | AF192: 0.17270386 | AG192: 0.3855845
A193: 2016 Q4 | B193: 0 | C193: 0 | D193: 0 | E193: 0 | F193: 0 | G193: -0.34073231 | H193: 0 | I193: 0 | J193: 0 | K193: 0 | L193: 0.19864418 | M193: 0 | N193: 0 | O193: 0.19864418 | P193: 0.068707691 | Q193: 1.8204952 | R193: 0 | S193: 0 | T193: 0 | U193: 0 | V193: 0 | W193: 0 | X193: 0 | Y193: 0 | Z193: 0 | AA193: -0.82917249 | AB193: -0.23499254 | AC193: 0 | AD193: -0.14771956 | AE193: 0 | AF193: 0.17337944 | AG193: 0.37913974
...

Sheet t-1 Data Table
A1: roa_dealer_group | B1: rowid | C1: lookup | D1: notes | E1: datetime_inserted | F1: effective_date | G1: halfbaked_date | H1: mroa | I1: orig_yield | J1: cnl_effect | K1: var_cost | L1: cost_of_debt | M1: run_rate_nb | N1: model_score | O1: model_name | P1: wal | Q1: wal_cfc | R1: wal_adj_factor | S1: apr | T1: apr_realization_factor | U1: discount | V1: fee_income | W1: pmt_proc_income | X1: addl_income | Y1: cnl | Z1: gross_loss | AA1: recovery | AB1: cnl_adj_factor | AC1: gross_loss_cfc | AD1: gross_loss_adj_factor | AE1: recovery_cfc | AF1: recovery_adj_factor | AG1: debt_int_rate | AH1: securitization_cost | AI1: debt_adv_rate | AJ1: orig_cost | AK1: serv_cost | AL1: addl_cost | AM1: days_till_half_baked | AN1: sort | AO1: latest_row_flag | AP1: loss_meeting_flag | AQ1: pricing_change_flag | AR1: is_current_flag | AS1: elasticity | AT1: nb_ratio | AU1: version_start_datetime | AV1: version_end_datetime | AW1: ticket_no | AX1: addl_cost_of_debt
A2: AN | B2: 392 | C2: AN392 | D2: AN/STG/FLD Hurdle updates (December Frontier mtg) | E2: 46028 | F2: 46013 | G2: 46029 | H2: 0.079392755 | I2: 0.26518303 | J2: 0.11333151 | K2: 0.027276764 | L2: 0.045182 | M2: 188.6976 | N2: 139.6 | O2: Franchise3.0 | P2: 2.11 | Q2: 2.2067215 | R2: 0.95616961 | S2: 0.25076585 | T2: 0.9228 | U2: 0.0527 | V2: 0.003 | W2: 0.0041 | X2: 0.0017 | Y2: 0.23912948 | Z2: 0.54886372 | AA2: 0.30973424 | AB2: 1.2526359 | AC2: 0.438167 | AD2: 1 | AE2: 0.24726597 | AF2: 1 | AG2: 0.0525 | AH2: 0.0026 | AI2: 0.82 | AJ2: 0.031600973 | AK2: 0.0123 | AL2: 0 | AM2: 16 | AN2: 2 | AO2: 1 | AP2: 0 | AQ2: 1 | AR2: 1 | AS2: 0.01 | AT2: 0.9935 | AU2: 46028 | AV2: 2958101 | AW2: ORGN-41969 | AX2: 0 | AZ2: 0.005 | BA2: 0.0027 | BB2: 0.071692755 | BC2: 147.3 | BD2: 1.94 | BE2: 1.58 | BF2: 0.25 | BG2: 3.6 | BH2: 0.5 | BI2: 3.9 | BJ2: 0 | BK2: -0.3
A3: ENT | B3: 276 | C3: ENT276 | D3: December Loss Meeting Adjustments | E3: 46028.768 | F3: 46009 | H3: 0.067304949 | I3: 0.25001964 | J3: 0.11025592 | K3: 0.027276764 | L3: 0.045182 | M3: 425 | N3: 138.8 | O3: Franchise3.0 | P3: 2.38 | Q3: 2.2952156 | R3: 1.0369396 | S3: 0.24028528 | T3: 0.9259 | U3: 0.0446 | V3: 0.003 | W3: 0.0041 | X3: 0.0017 | Y3: 0.2624091 | Z3: 0.53829361 | AA3: 0.27588451 | AB3: 1.0747351 | AC3: 0.50086165 | AD3: 1 | AE3: 0.2567 | AF3: 1 | AG3: 0.0525 | AH3: 0.0026 | AI3: 0.82 | AJ3: 0.035644699 | AK3: 0.0123 | AL3: 0 | AM3: 13 | AN3: 4 | AO3: 1 | AP3: 1 | AQ3: 0 | AR3: 1 | AS3: 0.01 | AT3: 0.9935 | AU3: 46028.768 | AV3: 2958101 | AX3: 0 | AZ3: 0.005 | BA3: 0.0027 | BB3: 0.059604949 | BC3: 141.7 | BD3: 1.45 | BE3: 1.33 | BF3: 0.235 | BG3: 1.7 | BH3: 0 | BI3: 1.5 | BJ3: 0 | BK3: -0.3
A4: FLD | B4: 275 | C4: FLD275 | D4: FRN/STG/FLD 100bps Hurdle Lower | E4: 46042 | F4: 46043 | G4: 46056 | H4: 0.062596102 | I4: 0.23677166 | J4: 0.1017168 | K4: 0.027276764 | L4: 0.045182 | M4: 224.91 | N4: 138.7 | O4: Franchise3.0 | P4: 2.35 | Q4: 2.2769093 | R4: 1.0321008 | S4: 0.23670091 | T4: 0.933 | U4: 0.01675482 | V4: 0.003 | W4: 0.0041 | X4: 0.0017 | Y4: 0.23903447 | Z4: 0.66510845 | AA4: 0.42607398 | AB4: 1.730601 | AC4: 0.38432223 | AD4: 1 | AE4: 0.2462 | AF4: 1 | AG4: 0.0525 | AH4: 0.0026 | AI4: 0.82 | AJ4: 0.035195396 | AK4: 0.0123 | AL4: 0 | AM4: 13 | AN4: 5 | AO4: 1 | AP4: 0 | AQ4: 1 | AR4: 1 | AS4: 0.01 | AT4: 0.9935 | AU4: 46042 | AV4: 2958101 | AW4: ORGN-42013 | AX4: 0 | AZ4: 0.005 | BA4: 0.0027 | BB4: 0.054896102 | BC4: 147.2 | BD4: 1.45 | BE4: 1.37 | BF4: 0.235 | BG4: 5.6 | BH4: 2 | BI4: 1 | BJ4: 0 | BK4: -0.1
A5: FRN | B5: 403 | C5: FRN403 | D5: FRN/STG/FLD 100bps Hurdle Lower | E5: 46042 | F5: 46043 | G5: 46062 | H5: 0.067963799 | I5: 0.27306685 | J5: 0.13264429 | K5: 0.027276764 | L5: 0.045182 | M5: 658.56 | N5: 142 | O5: Franchise3.0 | P5: 2 | Q5: 2.1786756 | R5: 0.9179889 | S5: 0.25645294 | T5: 0.9053 | U5: 0.0642 | V5: 0.003 | W5: 0.0041 | X5: 0.0017 | Y5: 0.26528857 | Z5: 0.57107129 | AA5: 0.30578271 | AB5: 1.2213548 | AC5: 0.46757197 | AD5: 1 | AE5: 0.25036353 | AF5: 1 | AG5: 0.0525 | AH5: 0.0026 | AI5: 0.82 | AJ5: 0.029953529 | AK5: 0.0123 | AL5: 0 | AM5: 19 | AN5: 6 | AO5: 1 | AP5: 0 | AQ5: 1 | AR5: 1 | AS5: 0.01 | AT5: 0.993 | AU5: 46042 | AV5: 2958101 | AW5: ORGN-42013 | AX5: 0 | AZ5: 0.005 | BA5: 0.0027 | BB5: 0.060263799 | BC5: 150.7 | BD5: 1.94 | BE5: 1.44 | BF5: 0.25 | BG5: 3.4 | BH5: 0 | BI5: 5.9 | BJ5: 0 | BK5: -0.6
A6: KMX | B6: 414 | C6: KMX414 | D6: December Loss Meeting Adjustments | E6: 46028.767 | F6: 46009 | H6: 0.067770733 | I6: 0.25026628 | J6: 0.12039678 | K6: 0.016916764 | L6: 0.045182 | M6: 1638.75 | N6: 141.60524 | O6: Mountain3 | P6: 2.36 | Q6: 2.3970424 | R6: 0.9845466 | S6: 0.24649264 | T6: 0.9203 | U6: 0.032377076 | V6: 0.003 | W6: 0.0041 | X6: 0.0026 | Y6: 0.2841364 | Z6: 0.63823782 | AA6: 0.35410142 | AB6: 1.2571682 | AC6: 0.50767895 | AD6: 1 | AE6: 0.28166591 | AF6: 1 | AG6: 0.0525 | AH6: 0.0026 | AI6: 0.82 | AJ6: 0.011367564 | AK6: 0.0121 | AL6: 0 | AM6: 4 | AN6: 1 | AO6: 1 | AP6: 1 | AQ6: 0 | AR6: 1 | AS6: 0.0065 | AT6: 0.94 | AU6: 46028.767 | AV6: 2958101 | AX6: 0 | AZ6: 0.005 | BA6: 0.0027 | BB6: 0.060070733 | BC6: 146.3 | BD6: 1.59 | BE6: 1.62 | BF6: 0.25 | BG6: 4.7 | BH6: 0.47 | BI6: -0.5 | BJ6: 0 | BK6: 0
A7: STG | B7: 411 | C7: STG411 | D7: FRN/STG/FLD 100bps Hurdle Lower | E7: 46042 | F7: 46043 | G7: 46060 | H7: 0.068045817 | I7: 0.25716918 | J7: 0.1166646 | K7: 0.027276764 | L7: 0.045182 | M7: 491.568 | N7: 138.6 | O7: Franchise3.0 | P7: 2.05 | Q7: 2.1801666 | R7: 0.9402951 | S7: 0.2456 | T7: 0.9215 | U7: 0.0452 | V7: 0.003 | W7: 0.0041 | X7: 0.0017 | Y7: 0.23916243 | Z7: 0.50639613 | AA7: 0.2672337 | AB7: 1.0882711 | AC7: 0.46532167 | AD7: 1 | AE7: 0.24555802 | AF7: 1 | AG7: 0.0525 | AH7: 0.0026 | AI7: 0.82 | AJ7: 0.030702367 | AK7: 0.0123 | AL7: 0 | AM7: 17 | AN7: 3 | AO7: 1 | AP7: 0 | AQ7: 1 | AR7: 1 | AS7: 0.01 | AT7: 0.995 | AU7: 46042 | AV7: 2958101 | AW7: ORGN-42013 | AX7: 0 | AZ7: 0.005 | BA7: 0.0027 | BB7: 0.060345817 | BC7: 151 | BD7: 1.94 | BE7: 1.45 | BF7: 0.25 | BG7: 3.7 | BH7: 3 | BI7: 5.7 | BJ7: 0 | BK7: 0
A8: NonKMXENT | M8: =SUM(M2,M4,M5,M7) | N8: =(M2*N2+M4*N4+M5*N5+M7*N7)/M8

Sheet distribution_rolledup
A1: roa_dealer_group | B1: 2016 | C1: 2017 | D1: 2018 | E1: 2019 | F1: 20201 | G1: 20202 | H1: 20203 | I1: 20204 | J1: 20211 | K1: 20212 | L1: 20213 | M1: 20214 | N1: 20221 | O1: 20222 | P1: 20223 | Q1: 20224 | R1: 20231 | S1: 20232 | T1: 20233 | U1: 20234 | V1: 20241 | W1: 20242 | X1: 20243 | Y1: 20244
A2: roa_dealer_group
A3: AN | B3: 0.13632879 | C3: 0.14437905 | D3: 0.1117387 | E3: 0.061138445 | F3: 0.057627615 | G3: 0.059112182 | H3: 0.048653702 | I3: 0.049697267 | J3: 0.048043084 | K3: 0.053449965 | L3: 0.041309421 | M3: 0.043412194 | N3: 0.039799267 | O3: 0.042594829 | P3: 0.049512519 | Q3: 0.044590175 | R3: 0.046034244 | S3: 0.048740295 | T3: 0.049392118 | U3: 0.059191728 | V3: 0.059998851 | W3: 0.060395456 | X3: 0.052556052 | Y3: 0.053144883 | Z3: 0.058869376 | AA3: 0.064949184 | AB3: 0.063788613 | AC3: 0.057503561
A4: ENT | E4: 0.0035037966 | F4: 0.07681912 | G4: 0.10027198 | H4: 0.087057922 | I4: 0.11120634 | J4: 0.13327728 | K4: 0.17504544 | L4: 0.15209764 | M4: 0.14082133 | N4: 0.12962489 | O4: 0.12475696 | P4: 0.12489133 | Q4: 0.18717176 | R4: 0.20763323 | S4: 0.19060656 | T4: 0.16353473 | U4: 0.17103147 | V4: 0.1541449 | W4: 0.13987855 | X4: 0.13666921 | Y4: 0.15194482 | Z4: 0.15823241 | AA4: 0.14592681 | AB4: 0.14116288 | AC4: 0.13328221
A5: FLD | E5: 0.015147625 | F5: 0.050613008 | G5: 0.040833289 | H5: 0.031133028 | I5: 0.017144042 | J5: 0.021178634 | K5: 0.040948054 | L5: 0.040064272 | M5: 0.032455053 | N5: 0.024748144 | O5: 0.02506867 | P5: 0.028075452 | Q5: 0.02619653 | R5: 0.014230322 | S5: 0.021409151 | T5: 0.023341074 | U5: 0.025229678 | V5: 0.032670344 | W5: 0.047948104 | X5: 0.036514839 | Y5: 0.03571671 | Z5: 0.045582068 | AA5: 0.044852788 | AB5: 0.044737696 | AC5: 0.062794499
A6: FRN | B6: 0.016158291 | C6: 0.027996002 | D6: 0.017103138 | E6: 0.016819172 | F6: 0.04596485 | G6: 0.065478304 | H6: 0.070236663 | I6: 0.080994429 | J6: 0.070801378 | K6: 0.10465389 | L6: 0.10439154 | M6: 0.12238182 | N6: 0.10580061 | O6: 0.11428738 | P6: 0.12854048 | Q6: 0.095478588 | R6: 0.05917033 | S6: 0.081172555 | T6: 0.094753264 | U6: 0.16513936 | V6: 0.17909316 | W6: 0.2055444 | X6: 0.18686457 | Y6: 0.20070278 | Z6: 0.1840832 | AA6: 0.20142581 | AB6: 0.21178024 | AC6: 0.17107459
A7: KMX | B7: 0.6220219 | C7: 0.66048827 | D7: 0.68106261 | E7: 0.72816299 | F7: 0.64136881 | G7: 0.60892731 | H7: 0.65229696 | I7: 0.64147256 | J7: 0.63378931 | K7: 0.51879531 | L7: 0.56162154 | M7: 0.55471527 | N7: 0.6080436 | O7: 0.59834995 | P7: 0.59103912 | Q7: 0.59243675 | R7: 0.63796686 | S7: 0.61526537 | T7: 0.614259 | U7: 0.48760551 | V7: 0.48605818 | W7: 0.41447141 | X7: 0.46955166 | Y7: 0.44073587 | Z7: 0.43785652 | AA7: 0.41312542 | AB7: 0.4165421 | AC7: 0.47148399
A8: STG | B8: 0.22549102 | C8: 0.16713668 | D8: 0.19009555 | E8: 0.17522797 | F8: 0.12760659 | G8: 0.12537694 | H8: 0.11062172 | I8: 0.09948536 | J8: 0.092910316 | K8: 0.10710734 | L8: 0.10051559 | M8: 0.10621433 | N8: 0.091983491 | O8: 0.094942212 | P8: 0.077941098 | Q8: 0.054126201 | R8: 0.034965012 | S8: 0.042806062 | T8: 0.054719811 | U8: 0.09180226 | V8: 0.088034553 | W8: 0.13176208 | X8: 0.11784368 | Y8: 0.11775493 | Z8: 0.11537643 | AA8: 0.12971999 | AB8: 0.12198847 | AC8: 0.10386116

Sheet POS
A1: POS | B1: 2016 | C1: 2017 | D1: 2018 | E1: 2019 | F1: 2020 Q1 | G1: 2020 Q2 | H1: 2020 Q3 | I1: 2020 Q4 | J1: 2021 Q1 | K1: 2021 Q2 | L1: 2021 Q3 | M1: 2021 Q4 | N1: 2022 Q1 | O1: 2022 Q2 | P1: 2022 Q3 | Q1: 2022 Q4 | R1: 2023 Q1 | S1: 2023 Q2 | T1: 2023 Q3 | U1: 2023 Q4 | V1: 2024 Q1 | W1: 2024 Q2 | X1: 2024 Q3 | Y1: 2024 Q4
A2: Contract MS | B2: ='AN Table'!B2*distribution_rolledup!B3+'FRN Table'!B2*distribution_rolledup!B6+'STG Table'!B2*distribution_rolledup!B8+'KMX Table'!B2*distribution_rolledup!B7 | C2: ='AN Table'!C2*distribution_rolledup!C3+'FRN Table'!C2*distribution_rolledup!C6+'STG Table'!C2*distribution_rolledup!C8+'KMX Table'!C2*distribution_rolledup!C7 | D2: ='AN Table'!D2*distribution_rolledup!D3+'FRN Table'!D2*distribution_rolledup!D6+'STG Table'!D2*distribution_rolledup!D8+'KMX Table'!D2*distribution_rolledup!D7 | E2: ='AN Table'!E2*distribution_rolledup!E3+'FRN Table'!E2*distribution_rolledup!E6+'STG Table'!E2*distribution_rolledup!E8+'KMX Table'!E2*distribution_rolledup!E7 | F2: ='AN Table'!F2*distribution_rolledup!F3+'FRN Table'!F2*distribution_rolledup!F6+'STG Table'!F2*distribution_rolledup!F8+'FLD Table'!B2*distribution_rolledup!F5+'ENT Table'!B2*distribution_rolledup!F4+'KMX Table'!F2*distribution_rolledup!F7 | G2: ='AN Table'!G2*distribution_rolledup!G3+'FRN Table'!G2*distribution_rolledup!G6+'STG Table'!G2*distribution_rolledup!G8+'FLD Table'!C2*distribution_rolledup!G5+'ENT Table'!C2*distribution_rolledup!G4+'KMX Table'!G2*distribution_rolledup!G7 | H2: ='AN Table'!H2*distribution_rolledup!H3+'FRN Table'!H2*distribution_rolledup!H6+'STG Table'!H2*distribution_rolledup!H8+'FLD Table'!D2*distribution_rolledup!H5+'ENT Table'!D2*distribution_rolledup!H4+'KMX Table'!H2*distribution_rolledup!H7 | I2: ='AN Table'!I2*distribution_rolledup!I3+'FRN Table'!I2*distribution_rolledup!I6+'STG Table'!I2*distribution_rolledup!I8+'FLD Table'!E2*distribution_rolledup!I5+'ENT Table'!E2*distribution_rolledup!I4+'KMX Table'!I2*distribution_rolledup!I7 | J2: ='AN Table'!J2*distribution_rolledup!J3+'FRN Table'!J2*distribution_rolledup!J6+'STG Table'!J2*distribution_rolledup!J8+'FLD Table'!F2*distribution_rolledup!J5+'ENT Table'!F2*distribution_rolledup!J4+'KMX Table'!J2*distribution_rolledup!J7 | K2: ='AN Table'!K2*distribution_rolledup!K3+'FRN Table'!K2*distribution_rolledup!K6+'STG Table'!K2*distribution_rolledup!K8+'FLD Table'!G2*distribution_rolledup!K5+'ENT Table'!G2*distribution_rolledup!K4+'KMX Table'!K2*distribution_rolledup!K7 | L2: ='AN Table'!L2*distribution_rolledup!L3+'FRN Table'!L2*distribution_rolledup!L6+'STG Table'!L2*distribution_rolledup!L8+'FLD Table'!H2*distribution_rolledup!L5+'ENT Table'!H2*distribution_rolledup!L4+'KMX Table'!L2*distribution_rolledup!L7 | M2: ='AN Table'!M2*distribution_rolledup!M3+'FRN Table'!M2*distribution_rolledup!M6+'STG Table'!M2*distribution_rolledup!M8+'FLD Table'!I2*distribution_rolledup!M5+'ENT Table'!I2*distribution_rolledup!M4+'KMX Table'!M2*distribution_rolledup!M7 | ... Y2: ='AN Table'!Y2*distribution_rolledup!Y3+'FRN Table'!Y2*distribution_rolledup!Y6+'STG Table'!Y2*distribution_rolledup!Y8+'FLD Table'!U2*distribution_rolledup!Y5+'ENT Table'!U2*distribution_rolledup!Y4+'KMX Table'!Y2*distribution_rolledup!Y7
A3: RAGU t0 | B3: ='AN Table'!B7*distribution_rolledup!B3+'FRN Table'!B7*distribution_rolledup!B6+'STG Table'!B7*distribution_rolledup!B8+'KMX Table'!B6*distribution_rolledup!B7 | C3: ='AN Table'!C7*distribution_rolledup!C3+'FRN Table'!C7*distribution_rolledup!C6+'STG Table'!C7*distribution_rolledup!C8+'KMX Table'!C6*distribution_rolledup!C7 | D3: ='AN Table'!D7*distribution_rolledup!D3+'FRN Table'!D7*distribution_rolledup!D6+'STG Table'!D7*distribution_rolledup!D8+'KMX Table'!D6*distribution_rolledup!D7 | E3: ='AN Table'!E7*distribution_rolledup!E3+'FRN Table'!E7*distribution_rolledup!E6+'STG Table'!E7*distribution_rolledup!E8+'KMX Table'!E6*distribution_rolledup!E7 | F3: ='AN Table'!F7*distribution_rolledup!F3+'FRN Table'!F7*distribution_rolledup!F6+'STG Table'!F7*distribution_rolledup!F8+'FLD Table'!B7*distribution_rolledup!F5+'ENT Table'!B7*distribution_rolledup!F4+'KMX Table'!F6*distribution_rolledup!F7 | G3: ='AN Table'!G7*distribution_rolledup!G3+'FRN Table'!G7*distribution_rolledup!G6+'STG Table'!G7*distribution_rolledup!G8+'FLD Table'!C7*distribution_rolledup!G5+'ENT Table'!C7*distribution_rolledup!G4+'KMX Table'!G6*distribution_rolledup!G7 | H3: ='AN Table'!H7*distribution_rolledup!H3+'FRN Table'!H7*distribution_rolledup!H6+'STG Table'!H7*distribution_rolledup!H8+'FLD Table'!D7*distribution_rolledup!H5+'ENT Table'!D7*distribution_rolledup!H4+'KMX Table'!H6*distribution_rolledup!H7 | I3: ='AN Table'!I7*distribution_rolledup!I3+'FRN Table'!I7*distribution_rolledup!I6+'STG Table'!I7*distribution_rolledup!I8+'FLD Table'!E7*distribution_rolledup!I5+'ENT Table'!E7*distribution_rolledup!I4+'KMX Table'!I6*distribution_rolledup!I7 | J3: ='AN Table'!J7*distribution_rolledup!J3+'FRN Table'!J7*distribution_rolledup!J6+'STG Table'!J7*distribution_rolledup!J8+'FLD Table'!F7*distribution_rolledup!J5+'ENT Table'!F7*distribution_rolledup!J4+'KMX Table'!J6*distribution_rolledup!J7 | K3: ='AN Table'!K7*distribution_rolledup!K3+'FRN Table'!K7*distribution_rolledup!K6+'STG Table'!K7*distribution_rolledup!K8+'FLD Table'!G7*distribution_rolledup!K5+'ENT Table'!G7*distribution_rolledup!K4+'KMX Table'!K6*distribution_rolledup!K7 | L3: ='AN Table'!L7*distribution_rolledup!L3+'FRN Table'!L7*distribution_rolledup!L6+'STG Table'!L7*distribution_rolledup!L8+'FLD Table'!H7*distribution_rolledup!L5+'ENT Table'!H7*distribution_rolledup!L4+'KMX Table'!L6*distribution_rolledup!L7 | M3: ='AN Table'!M7*distribution_rolledup!M3+'FRN Table'!M7*distribution_rolledup!M6+'STG Table'!M7*distribution_rolledup!M8+'FLD Table'!I7*distribution_rolledup!M5+'ENT Table'!I7*distribution_rolledup!M4+'KMX Table'!M6*distribution_rolledup!M7 | ... Y3: ='AN Table'!Y7*distribution_rolledup!Y3+'FRN Table'!Y7*distribution_rolledup!Y6+'STG Table'!Y7*distribution_rolledup!Y8+'FLD Table'!U7*distribution_rolledup!Y5+'ENT Table'!U7*distribution_rolledup!Y4+'KMX Table'!Y6*distribution_rolledup!Y7
A4: RAGU gross loss | B4: ='AN Table'!B8*distribution_rolledup!B3+'FRN Table'!B8*distribution_rolledup!B6+'STG Table'!B8*distribution_rolledup!B8+'KMX Table'!B7*distribution_rolledup!B7 | C4: ='AN Table'!C8*distribution_rolledup!C3+'FRN Table'!C8*distribution_rolledup!C6+'STG Table'!C8*distribution_rolledup!C8+'KMX Table'!C7*distribution_rolledup!C7 | D4: ='AN Table'!D8*distribution_rolledup!D3+'FRN Table'!D8*distribution_rolledup!D6+'STG Table'!D8*distribution_rolledup!D8+'KMX Table'!D7*distribution_rolledup!D7 | E4: ='AN Table'!E8*distribution_rolledup!E3+'FRN Table'!E8*distribution_rolledup!E6+'STG Table'!E8*distribution_rolledup!E8+'KMX Table'!E7*distribution_rolledup!E7 | F4: ='AN Table'!F8*distribution_rolledup!F3+'FRN Table'!F8*distribution_rolledup!F6+'STG Table'!F8*distribution_rolledup!F8+'FLD Table'!B8*distribution_rolledup!F5+'ENT Table'!B8*distribution_rolledup!F4+'KMX Table'!F7*distribution_rolledup!F7 | G4: ='AN Table'!G8*distribution_rolledup!G3+'FRN Table'!G8*distribution_rolledup!G6+'STG Table'!G8*distribution_rolledup!G8+'FLD Table'!C8*distribution_rolledup!G5+'ENT Table'!C8*distribution_rolledup!G4+'KMX Table'!G7*distribution_rolledup!G7 | H4: ='AN Table'!H8*distribution_rolledup!H3+'FRN Table'!H8*distribution_rolledup!H6+'STG Table'!H8*distribution_rolledup!H8+'FLD Table'!D8*distribution_rolledup!H5+'ENT Table'!D8*distribution_rolledup!H4+'KMX Table'!H7*distribution_rolledup!H7 | I4: ='AN Table'!I8*distribution_rolledup!I3+'FRN Table'!I8*distribution_rolledup!I6+'STG Table'!I8*distribution_rolledup!I8+'FLD Table'!E8*distribution_rolledup!I5+'ENT Table'!E8*distribution_rolledup!I4+'KMX Table'!I7*distribution_rolledup!I7 | J4: ='AN Table'!J8*distribution_rolledup!J3+'FRN Table'!J8*distribution_rolledup!J6+'STG Table'!J8*distribution_rolledup!J8+'FLD Table'!F8*distribution_rolledup!J5+'ENT Table'!F8*distribution_rolledup!J4+'KMX Table'!J7*distribution_rolledup!J7 | K4: ='AN Table'!K8*distribution_rolledup!K3+'FRN Table'!K8*distribution_rolledup!K6+'STG Table'!K8*distribution_rolledup!K8+'FLD Table'!G8*distribution_rolledup!K5+'ENT Table'!G8*distribution_rolledup!K4+'KMX Table'!K7*distribution_rolledup!K7 | L4: ='AN Table'!L8*distribution_rolledup!L3+'FRN Table'!L8*distribution_rolledup!L6+'STG Table'!L8*distribution_rolledup!L8+'FLD Table'!H8*distribution_rolledup!L5+'ENT Table'!H8*distribution_rolledup!L4+'KMX Table'!L7*distribution_rolledup!L7 | M4: ='AN Table'!M8*distribution_rolledup!M3+'FRN Table'!M8*distribution_rolledup!M6+'STG Table'!M8*distribution_rolledup!M8+'FLD Table'!I8*distribution_rolledup!M5+'ENT Table'!I8*distribution_rolledup!M4+'KMX Table'!M7*distribution_rolledup!M7 | ... Y4: ='AN Table'!Y8*distribution_rolledup!Y3+'FRN Table'!Y8*distribution_rolledup!Y6+'STG Table'!Y8*distribution_rolledup!Y8+'FLD Table'!U8*distribution_rolledup!Y5+'ENT Table'!U8*distribution_rolledup!Y4+'KMX Table'!Y7*distribution_rolledup!Y7
A5: RAGU tc | B5: ='AN Table'!B14*distribution_rolledup!B3+'FRN Table'!B14*distribution_rolledup!B6+'STG Table'!B14*distribution_rolledup!B8+'KMX Table'!B14*distribution_rolledup!B7 | C5: ='AN Table'!C14*distribution_rolledup!C3+'FRN Table'!C14*distribution_rolledup!C6+'STG Table'!C14*distribution_rolledup!C8+'KMX Table'!C14*distribution_rolledup!C7 | D5: ='AN Table'!D14*distribution_rolledup!D3+'FRN Table'!D14*distribution_rolledup!D6+'STG Table'!D14*distribution_rolledup!D8+'KMX Table'!D14*distribution_rolledup!D7 | E5: ='AN Table'!E14*distribution_rolledup!E3+'FRN Table'!E14*distribution_rolledup!E6+'STG Table'!E14*distribution_rolledup!E8+'KMX Table'!E14*distribution_rolledup!E7 | F5: ='AN Table'!F14*distribution_rolledup!F3+'FRN Table'!F14*distribution_rolledup!F6+'STG Table'!F14*distribution_rolledup!F8+'FLD Table'!B14*distribution_rolledup!F5+'ENT Table'!B14*distribution_rolledup!F4+'KMX Table'!F14*distribution_rolledup!F7 | G5: ='AN Table'!G14*distribution_rolledup!G3+'FRN Table'!G14*distribution_rolledup!G6+'STG Table'!G14*distribution_rolledup!G8+'FLD Table'!C14*distribution_rolledup!G5+'ENT Table'!C14*distribution_rolledup!G4+'KMX Table'!G14*distribution_rolledup!G7 | H5: ='AN Table'!H14*distribution_rolledup!H3+'FRN Table'!H14*distribution_rolledup!H6+'STG Table'!H14*distribution_rolledup!H8+'FLD Table'!D14*distribution_rolledup!H5+'ENT Table'!D14*distribution_rolledup!H4+'KMX Table'!H14*distribution_rolledup!H7 | I5: ='AN Table'!I14*distribution_rolledup!I3+'FRN Table'!I14*distribution_rolledup!I6+'STG Table'!I14*distribution_rolledup!I8+'FLD Table'!E14*distribution_rolledup!I5+'ENT Table'!E14*distribution_rolledup!I4+'KMX Table'!I14*distribution_rolledup!I7 | J5: ='AN Table'!J14*distribution_rolledup!J3+'FRN Table'!J14*distribution_rolledup!J6+'STG Table'!J14*distribution_rolledup!J8+'FLD Table'!F14*distribution_rolledup!J5+'ENT Table'!F14*distribution_rolledup!J4+'KMX Table'!J14*distribution_rolledup!J7 | K5: ='AN Table'!K14*distribution_rolledup!K3+'FRN Table'!K14*distribution_rolledup!K6+'STG Table'!K14*distribution_rolledup!K8+'FLD Table'!G14*distribution_rolledup!K5+'ENT Table'!G14*distribution_rolledup!K4+'KMX Table'!K14*distribution_rolledup!K7 | L5: ='AN Table'!L14*distribution_rolledup!L3+'FRN Table'!L14*distribution_rolledup!L6+'STG Table'!L14*distribution_rolledup!L8+'FLD Table'!H14*distribution_rolledup!L5+'ENT Table'!H14*distribution_rolledup!L4+'KMX Table'!L14*distribution_rolledup!L7 | M5: ='AN Table'!M14*distribution_rolledup!M3+'FRN Table'!M14*distribution_rolledup!M6+'STG Table'!M14*distribution_rolledup!M8+'FLD Table'!I14*distribution_rolledup!M5+'ENT Table'!I14*distribution_rolledup!M4+'KMX Table'!M14*distribution_rolledup!M7 | ... Y5: ='AN Table'!Y14*distribution_rolledup!Y3+'FRN Table'!Y14*distribution_rolledup!Y6+'STG Table'!Y14*distribution_rolledup!Y8+'FLD Table'!U14*distribution_rolledup!Y5+'ENT Table'!U14*distribution_rolledup!Y4+'KMX Table'!Y14*distribution_rolledup!Y7
A7: LTV | B7: ='AN Table'!B10*distribution_rolledup!B3+'FRN Table'!B10*distribution_rolledup!B6+'KMX Table'!B10*distribution_rolledup!B7+'STG Table'!B10*distribution_rolledup!B8 | C7: ='AN Table'!C10*distribution_rolledup!C3+'FRN Table'!C10*distribution_rolledup!C6+'KMX Table'!C10*distribution_rolledup!C7+'STG Table'!C10*distribution_rolledup!C8 | D7: ='AN Table'!D10*distribution_rolledup!D3+'FRN Table'!D10*distribution_rolledup!D6+'KMX Table'!D10*distribution_rolledup!D7+'STG Table'!D10*distribution_rolledup!D8 | E7: ='AN Table'!E10*distribution_rolledup!E3+'FRN Table'!E10*distribution_rolledup!E6+'KMX Table'!E10*distribution_rolledup!E7+'STG Table'!E10*distribution_rolledup!E8 | F7: ='AN Table'!F10*distribution_rolledup!F3+'ENT Table'!B10*distribution_rolledup!F4+'FLD Table'!B10*distribution_rolledup!F5+'FRN Table'!F10*distribution_rolledup!F6+'KMX Table'!F10*distribution_rolledup!F7+'STG Table'!F10*distribution_rolledup!F8 | G7: ='AN Table'!G10*distribution_rolledup!G3+'ENT Table'!C10*distribution_rolledup!G4+'FLD Table'!C10*distribution_rolledup!G5+'FRN Table'!G10*distribution_rolledup!G6+'KMX Table'!G10*distribution_rolledup!G7+'STG Table'!G10*distribution_rolledup!G8 | H7: ='AN Table'!H10*distribution_rolledup!H3+'ENT Table'!D10*distribution_rolledup!H4+'FLD Table'!D10*distribution_rolledup!H5+'FRN Table'!H10*distribution_rolledup!H6+'KMX Table'!H10*distribution_rolledup!H7+'STG Table'!H10*distribution_rolledup!H8 | I7: ='AN Table'!I10*distribution_rolledup!I3+'ENT Table'!E10*distribution_rolledup!I4+'FLD Table'!E10*distribution_rolledup!I5+'FRN Table'!I10*distribution_rolledup!I6+'KMX Table'!I10*distribution_rolledup!I7+'STG Table'!I10*distribution_rolledup!I8 | J7: ='AN Table'!J10*distribution_rolledup!J3+'ENT Table'!F10*distribution_rolledup!J4+'FLD Table'!F10*distribution_rolledup!J5+'FRN Table'!J10*distribution_rolledup!J6+'KMX Table'!J10*distribution_rolledup!J7+'STG Table'!J10*distribution_rolledup!J8 | K7: ='AN Table'!K10*distribution_rolledup!K3+'ENT Table'!G10*distribution_rolledup!K4+'FLD Table'!G10*distribution_rolledup!K5+'FRN Table'!K10*distribution_rolledup!K6+'KMX Table'!K10*distribution_rolledup!K7+'STG Table'!K10*distribution_rolledup!K8 | L7: ='AN Table'!L10*distribution_rolledup!L3+'ENT Table'!H10*distribution_rolledup!L4+'FLD Table'!H10*distribution_rolledup!L5+'FRN Table'!L10*distribution_rolledup!L6+'KMX Table'!L10*distribution_rolledup!L7+'STG Table'!L10*distribution_rolledup!L8 | M7: ='AN Table'!M10*distribution_rolledup!M3+'ENT Table'!I10*distribution_rolledup!M4+'FLD Table'!I10*distribution_rolledup!M5+'FRN Table'!M10*distribution_rolledup!M6+'KMX Table'!M10*distribution_rolledup!M7+'STG Table'!M10*distribution_rolledup!M8 | ... Y7: ='AN Table'!Y10*distribution_rolledup!Y3+'ENT Table'!U10*distribution_rolledup!Y4+'FLD Table'!U10*distribution_rolledup!Y5+'FRN Table'!Y10*distribution_rolledup!Y6+'KMX Table'!Y10*distribution_rolledup!Y7+'STG Table'!Y10*distribution_rolledup!Y8
A10: NonKMX RAGU tc | E10: =('AN Table'!E14*distribution_rolledup!E3+distribution_rolledup!E6*'FRN Table'!E14+distribution_rolledup!E8*'STG Table'!E14)/SUM(distribution_rolledup!E3,distribution_rolledup!E6,distribution_rolledup!E8) | F10: =(distribution_rolledup!F3*'AN Table'!F14+distribution_rolledup!F4*'ENT Table'!B14+distribution_rolledup!F5*'FLD Table'!B14+distribution_rolledup!F6*'FRN Table'!F14+distribution_rolledup!F8*'STG Table'!F14)/SUM(distribution_rolledup!F3:F6,distribution_rolledup!F8) | G10: =(distribution_rolledup!G3*'AN Table'!G14+distribution_rolledup!G4*'ENT Table'!C14+distribution_rolledup!G5*'FLD Table'!C14+distribution_rolledup!G6*'FRN Table'!G14+distribution_rolledup!G8*'STG Table'!G14)/SUM(distribution_rolledup!G3:G6,distribution_rolledup!G8) | H10: =(distribution_rolledup!H3*'AN Table'!H14+distribution_rolledup!H4*'ENT Table'!D14+distribution_rolledup!H5*'FLD Table'!D14+distribution_rolledup!H6*'FRN Table'!H14+distribution_rolledup!H8*'STG Table'!H14)/SUM(distribution_rolledup!H3:H6,distribution_rolledup!H8) | I10: =(distribution_rolledup!I3*'AN Table'!I14+distribution_rolledup!I4*'ENT Table'!E14+distribution_rolledup!I5*'FLD Table'!E14+distribution_rolledup!I6*'FRN Table'!I14+distribution_rolledup!I8*'STG Table'!I14)/SUM(distribution_rolledup!I3:I6,distribution_rolledup!I8) | J10: =(distribution_rolledup!J3*'AN Table'!J14+distribution_rolledup!J4*'ENT Table'!F14+distribution_rolledup!J5*'FLD Table'!F14+distribution_rolledup!J6*'FRN Table'!J14+distribution_rolledup!J8*'STG Table'!J14)/SUM(distribution_rolledup!J3:J6,distribution_rolledup!J8) | K10: =(distribution_rolledup!K3*'AN Table'!K14+distribution_rolledup!K4*'ENT Table'!G14+distribution_rolledup!K5*'FLD Table'!G14+distribution_rolledup!K6*'FRN Table'!K14+distribution_rolledup!K8*'STG Table'!K14)/SUM(distribution_rolledup!K3:K6,distribution_rolledup!K8) | L10: =(distribution_rolledup!L3*'AN Table'!L14+distribution_rolledup!L4*'ENT Table'!H14+distribution_rolledup!L5*'FLD Table'!H14+distribution_rolledup!L6*'FRN Table'!L14+distribution_rolledup!L8*'STG Table'!L14)/SUM(distribution_rolledup!L3:L6,distribution_rolledup!L8) | M10: =(distribution_rolledup!M3*'AN Table'!M14+distribution_rolledup!M4*'ENT Table'!I14+distribution_rolledup!M5*'FLD Table'!I14+distribution_rolledup!M6*'FRN Table'!M14+distribution_rolledup!M8*'STG Table'!M14)/SUM(distribution_rolledup!M3:M6,distribution_rolledup!M8) | ... Y10: =(distribution_rolledup!Y3*'AN Table'!Y14+distribution_rolledup!Y4*'ENT Table'!U14+distribution_rolledup!Y5*'FLD Table'!U14+distribution_rolledup!Y6*'FRN Table'!Y14+distribution_rolledup!Y8*'STG Table'!Y14)/SUM(distribution_rolledup!Y3:Y6,distribution_rolledup!Y8)
A11: NonKMX CNL tc | E11: =(distribution_rolledup!E3*'AN Table'!E15+distribution_rolledup!E6*'FRN Table'!E15+distribution_rolledup!E8*'STG Table'!E15)/SUM(distribution_rolledup!E3,distribution_rolledup!E6,distribution_rolledup!E8) | F11: =(distribution_rolledup!F3*'AN Table'!F15+distribution_rolledup!F4*'ENT Table'!B15+distribution_rolledup!F5*'FLD Table'!B15+distribution_rolledup!F6*'FRN Table'!F15+distribution_rolledup!F8*'STG Table'!F15)/SUM(distribution_rolledup!F3:F6,distribution_rolledup!F8) | G11: =(distribution_rolledup!G3*'AN Table'!G15+distribution_rolledup!G4*'ENT Table'!C15+distribution_rolledup!G5*'FLD Table'!C15+distribution_rolledup!G6*'FRN Table'!G15+distribution_rolledup!G8*'STG Table'!G15)/SUM(distribution_rolledup!G3:G6,distribution_rolledup!G8) | H11: =(distribution_rolledup!H3*'AN Table'!H15+distribution_rolledup!H4*'ENT Table'!D15+distribution_rolledup!H5*'FLD Table'!D15+distribution_rolledup!H6*'FRN Table'!H15+distribution_rolledup!H8*'STG Table'!H15)/SUM(distribution_rolledup!H3:H6,distribution_rolledup!H8) | I11: =(distribution_rolledup!I3*'AN Table'!I15+distribution_rolledup!I4*'ENT Table'!E15+distribution_rolledup!I5*'FLD Table'!E15+distribution_rolledup!I6*'FRN Table'!I15+distribution_rolledup!I8*'STG Table'!I15)/SUM(distribution_rolledup!I3:I6,distribution_rolledup!I8) | J11: =(distribution_rolledup!J3*'AN Table'!J15+distribution_rolledup!J4*'ENT Table'!F15+distribution_rolledup!J5*'FLD Table'!F15+distribution_rolledup!J6*'FRN Table'!J15+distribution_rolledup!J8*'STG Table'!J15)/SUM(distribution_rolledup!J3:J6,distribution_rolledup!J8) | K11: =(distribution_rolledup!K3*'AN Table'!K15+distribution_rolledup!K4*'ENT Table'!G15+distribution_rolledup!K5*'FLD Table'!G15+distribution_rolledup!K6*'FRN Table'!K15+distribution_rolledup!K8*'STG Table'!K15)/SUM(distribution_rolledup!K3:K6,distribution_rolledup!K8) | L11: =(distribution_rolledup!L3*'AN Table'!L15+distribution_rolledup!L4*'ENT Table'!H15+distribution_rolledup!L5*'FLD Table'!H15+distribution_rolledup!L6*'FRN Table'!L15+distribution_rolledup!L8*'STG Table'!L15)/SUM(distribution_rolledup!L3:L6,distribution_rolledup!L8) | M11: =(distribution_rolledup!M3*'AN Table'!M15+distribution_rolledup!M4*'ENT Table'!I15+distribution_rolledup!M5*'FLD Table'!I15+distribution_rolledup!M6*'FRN Table'!M15+distribution_rolledup!M8*'STG Table'!M15)/SUM(distribution_rolledup!M3:M6,distribution_rolledup!M8) | ... Y11: =(distribution_rolledup!Y3*'AN Table'!Y15+distribution_rolledup!Y4*'ENT Table'!U15+distribution_rolledup!Y5*'FLD Table'!U15+distribution_rolledup!Y6*'FRN Table'!Y15+distribution_rolledup!Y8*'STG Table'!Y15)/SUM(distribution_rolledup!Y3:Y6,distribution_rolledup!Y8)

Sheet AN Table
A1: AN | B1: 2016 | C1: 2017 | D1: 2018 | E1: 2019 | F1: 2020 Q1 | G1: 2020 Q2 | H1: 2020 Q3 | I1: 2020 Q4 | J1: 2021 Q1 | K1: 2021 Q2 | L1: 2021 Q3 | M1: 2021 Q4 | N1: 2022 Q1 | O1: 2022 Q2 | P1: 2022 Q3 | Q1: 2022 Q4 | R1: 2023 Q1 | S1: 2023 Q2 | T1: 2023 Q3 | U1: 2023 Q4 | V1: 2024 Q1 | W1: 2024 Q2 | X1: 2024 Q3 | Y1: 2024 Q4 | Z1: 2025 Q1 | AA1: 2025 Q2 | AB1: 2025 Q3 | AC1: 2025 Q4 | AD1: t-1 | AF1: t-1 manual input | AG1: Use Recent Month? | AH1: Use Reassessed Model Score?
A2: Contract Model Score¹ | B2: ='Data Tables (Q)'!B2 | C2: ='Data Tables (Q)'!C2 | D2: ='Data Tables (Q)'!D2 | E2: ='Data Tables (Q)'!E2 | F2: ='Data Tables (Q)'!F2 | G2: ='Data Tables (Q)'!G2 | H2: ='Data Tables (Q)'!H2 | I2: ='Data Tables (Q)'!I2 | ... AC2: ='Data Tables (Q)'!AC2 | AD2: ='Data Tables (M)'!BS2*AG2+AF2*(1-AG2) | AF2: ='t-1 Data Table'!N2 | AG2: 1 | AH2: 0
A3: Shift to FRN 3.1 Score² | B3: ='Data Tables (Q)'!B3*AH2 | C3: ='Data Tables (Q)'!C3*AI2 | D3: ='Data Tables (Q)'!D3*AJ2 | E3: ='Data Tables (Q)'!E3*AK2 | F3: ='Data Tables (Q)'!F3*AL2 | G3: ='Data Tables (Q)'!G3*AM2 | H3: ='Data Tables (Q)'!H3*AN2 | I3: ='Data Tables (Q)'!I3*AO2 | ... AC3: ='Data Tables (Q)'!AC3*BI2 | AD3: =('Data Tables (M)'!BC3*AG3+AF3*(1-AG3))*$AH$2 | AF3: 0 | AG3: 1
A4: Gross Loss Adjustments (Dealer Level, vehicle age, etc.)² | B4: ='Data Tables (Q)'!B4 | C4: ='Data Tables (Q)'!C4 | D4: ='Data Tables (Q)'!D4 | E4: ='Data Tables (Q)'!E4 | F4: ='Data Tables (Q)'!F4 | G4: ='Data Tables (Q)'!G4 | H4: ='Data Tables (Q)'!H4 | I4: ='Data Tables (Q)'!I4 | ... AC4: ='Data Tables (Q)'!AC4 | AD4: ='Data Tables (M)'!BS4*AG4+AF4*(1-AG4) | AG4: 1
A5: Recovery Adjustments excluding LTV (Mileage, LOB, etc.)³ | B5: ='Data Tables (Q)'!B5 | C5: ='Data Tables (Q)'!C5 | D5: ='Data Tables (Q)'!D5 | E5: ='Data Tables (Q)'!E5 | F5: ='Data Tables (Q)'!F5 | G5: ='Data Tables (Q)'!G5 | H5: ='Data Tables (Q)'!H5 | I5: ='Data Tables (Q)'!I5 | ... AC5: ='Data Tables (Q)'!AC5 | AD5: ='Data Tables (M)'!BS5*AG5+AF5*(1-AG5) | AG5: 1
A6: BBLTV Adjustments⁴ | B6: =(194%/B10-1)/10%*1.7 | C6: =(194%/C10-1)/10%*1.7 | D6: =(194%/D10-1)/10%*1.7 | E6: =(194%/E10-1)/10%*1.7 | F6: =(194%/F10-1)/10%*1.7 | G6: =(194%/G10-1)/10%*1.7 | H6: =(194%/H10-1)/10%*1.7 | I6: =(194%/I10-1)/10%*1.7 | ... AD6: =(194%/AD10-1)/10%*1.7
A7: RAGU Score | B7: =SUM(B2:B6) | C7: =SUM(C2:C6) | D7: =SUM(D2:D6) | E7: =SUM(E2:E6) | F7: =SUM(F2:F6) | G7: =SUM(G2:G6) | H7: =SUM(H2:H6) | I7: =SUM(I2:I6) | ... AD7: =SUM(AD2:AD6)
B8: =B2+B4 | C8: =C2+C4 | D8: =D2+D4 | E8: =E2+E4 | F8: =F2+F4 | G8: =G2+G4 | H8: =H2+H4 | I8: =I2+I4 | ... AD8: =AD2+AD4
A9: Context info
A10: BlackBook LTV (Baseline 194%) | B10: ='Data Tables (Q)'!B8 | C10: ='Data Tables (Q)'!C8 | D10: ='Data Tables (Q)'!D8 | E10: ='Data Tables (Q)'!E8 | F10: ='Data Tables (Q)'!F8 | G10: ='Data Tables (Q)'!G8 | H10: ='Data Tables (Q)'!H8 | I10: ='Data Tables (Q)'!I8 | ... AC10: ='Data Tables (Q)'!AC8 | AD10: ='Data Tables (M)'!BS8*AG10+AF10*(1-AG10) | AG10: 1
A11: Origination MMI | B11: 136.4 | C11: 141.3 | D11: 148 | E11: 151.5 | F11: 156.6 | G11: 149.5 | H11: 178.6 | I11: 176.8 | J11: 183.6 | K11: 218.6 | L11: 217 | M11: 252.9 | N11: 243.1 | O11: 245.1 | P11: 229.8 | Q11: 221.6 | R11: 229.4 | S11: 224.9 | T11: 212.6 | U11: 204.9 | V11: 204.2 | W11: 199.2 | X11: 202.8 | Y11: 203.3 | AA11: 205.86667 | AD11: 203
A12: MMI Impact⁵ | B12: 0.04 | C12: 0.11 | D12: 0.13 | E12: 0.146 | F12: 0.24456068 | G12: 0.33059156 | H12: 0.11738195 | I12: 0.16960025 | J12: 0.13323456 | K12: -0.042561451 | L12: -0.041246333 | M12: -0.18913444 | N12: -0.16706463 | O12: -0.1889941 | P12: -0.1447923 | Q12: -0.12461664 | R12: -0.16400894 | S12: -0.15141756 | T12: -0.10485319 | U12: -0.070296606 | V12: -0.064207992 | W12: -0.037128724 | X12: -0.03 | Y12: -0.03 | Z12: -0.03 | AA12: -0.026435638 | AD12: -0.03
A13: Adjustment to RAGU Score from MMI | B13: =B12/10%*1.7 | C13: =C12/10%*1.7 | D13: =D12/10%*1.7 | E13: =E12/10%*1.7 | F13: =F12/10%*1.7 | G13: =G12/10%*1.7 | H13: =H12/10%*1.7 | I13: =I12/10%*1.7 | ... AA13: =AA12/10%*1.7 | AD13: =AD12/10%*1.7
A14: RAGU Score (adjusted for MMI) | B14: =B7+B13 | C14: =C7+C13 | D14: =D7+D13 | E14: =E7+E13 | F14: =F7+F13 | G14: =G7+G13 | H14: =H7+H13 | I14: =I7+I13 | ... AA14: =AA7+AA13 | AD14: =AD7+AD13
A15: t_c CNL⁶ | B15: 0.28170196 | C15: 0.25167973 | D15: 0.2413702 | E15: 0.22113853 | F15: 0.19097109 | G15: 0.19152875 | H15: 0.18098296 | I15: 0.18074389 | J15: 0.21624478 | K15: 0.21737628 | L15: 0.25009127 | M15: 0.28129098 | N15: 0.31307465 | O15: 0.32412048 | P15: 0.31408391 | Q15: 0.3028242 | R15: 0.30358937
A16: Implied t-1 CNL | B16: =B15-($AD$14-B14)*1% | C16: =C15-($AD$14-C14)*1% | D16: =D15-($AD$14-D14)*1% | E16: =E15-($AD$14-E14)*1% | F16: =F15-($AD$14-F14)*1% | G16: =G15-($AD$14-G14)*1% | H16: =H15-($AD$14-H14)*1% | I16: =I15-($AD$14-I14)*1% | ... R16: =R15-($AD$14-R14)*1% | AD16: 0.2767
A19: 1: | B19: Model Score excludes buybacks and high amount financed.
A20: 2: | B20: We are currently working with Pricing to determine how to use FRN3.1 scores, there are large discrepancies between model scores as booked and FRN3.1 due to what might be centering issues.
A21: 3: | B21: Biggest impacts to Gross Loss Adjustments are Dealer Level, weekday/weekend decision, and high mileage classification.
B22: See Appendix for details on other factors
A23: 4: | B23: Biggest impacts to Recovery Adjustments are mileage/age, impound probability, and vehicle class.
A24: 5: | B24: LTV adjustments are made using the 10% LTV improvement->170bps to CNL heuristic, based on BlackBook LTV values.
A25: 6: | B25: MMI uses adjusted index (2019 seasonality). The MMI Impact compares the actual MMI to a 3% annual growth.
B26: A positive impact of X% means sold recovery will be X% better.
A27: 7: | B27: tc CNL uses UGLY Model projections, and 2023 Q1 blends 75% UGLY Model with 25% Loss Committee.

Sheet STG Table
A1: STG | B1: 2016 | C1: 2017 | D1: 2018 | E1: 2019 | F1: 2020 Q1 | G1: 2020 Q2 | H1: 2020 Q3 | I1: 2020 Q4 | J1: 2021 Q1 | K1: 2021 Q2 | L1: 2021 Q3 | M1: 2021 Q4 | N1: 2022 Q1 | O1: 2022 Q2 | P1: 2022 Q3 | Q1: 2022 Q4 | R1: 2023 Q1 | S1: 2023 Q2 | T1: 2023 Q3 | U1: 2023 Q4 | V1: 2024 Q1 | W1: 2024 Q2 | X1: 2024 Q3 | Y1: 2024 Q4 | Z1: 2025 Q1 | AA1: 2025 Q2 | AB1: 2025 Q3 | AC1: 2025 Q4 | AD1: t-1 | AF1: t-1 manual input | AG1: Use Recent Month? | AH1: Use Reassessed Model Score?
A2: Contract Model Score¹ | B2: ='Data Tables (Q)'!B29 | C2: ='Data Tables (Q)'!C29 | D2: ='Data Tables (Q)'!D29 | E2: ='Data Tables (Q)'!E29 | F2: ='Data Tables (Q)'!F29 | G2: ='Data Tables (Q)'!G29 | H2: ='Data Tables (Q)'!H29 | I2: ='Data Tables (Q)'!I29 | ... AC2: ='Data Tables (Q)'!AC29 | AD2: ='Data Tables (M)'!BS29*AG2+AF2*(1-AG2) | AF2: ='t-1 Data Table'!N7 | AG2: 1 | AH2: 0
A3: Shift to FRN 3.1 Score² | B3: ='Data Tables (Q)'!B30*AH2 | C3: ='Data Tables (Q)'!C30*AI2 | D3: ='Data Tables (Q)'!D30*AJ2 | E3: ='Data Tables (Q)'!E30*AK2 | F3: ='Data Tables (Q)'!F30*AL2 | G3: ='Data Tables (Q)'!G30*AM2 | H3: ='Data Tables (Q)'!H30*AN2 | I3: ='Data Tables (Q)'!I30*AO2 | ... AC3: ='Data Tables (Q)'!AC30*BI2 | AD3: =('Data Tables (M)'!BC30*AG3+AF3*(1-AG3))*$AH$2 | AF3: 0 | AG3: 1
A4: Gross Loss Adjustments (Dealer Level, vehicle age, etc.)² | B4: ='Data Tables (Q)'!B31 | C4: ='Data Tables (Q)'!C31 | D4: ='Data Tables (Q)'!D31 | E4: ='Data Tables (Q)'!E31 | F4: ='Data Tables (Q)'!F31 | G4: ='Data Tables (Q)'!G31 | H4: ='Data Tables (Q)'!H31 | I4: ='Data Tables (Q)'!I31 | ... AC4: ='Data Tables (Q)'!AC31 | AD4: ='Data Tables (M)'!BS31*AG4+AF4*(1-AG4) | AG4: 1
A5: Recovery Adjustments excluding LTV (Mileage, LOB, etc.)³ | B5: ='Data Tables (Q)'!B32 | C5: ='Data Tables (Q)'!C32 | D5: ='Data Tables (Q)'!D32 | E5: ='Data Tables (Q)'!E32 | F5: ='Data Tables (Q)'!F32 | G5: ='Data Tables (Q)'!G32 | H5: ='Data Tables (Q)'!H32 | I5: ='Data Tables (Q)'!I32 | ... AC5: ='Data Tables (Q)'!AC32 | AD5: ='Data Tables (M)'!BS32*AG5+AF5*(1-AG5) | AG5: 1
A6: BBLTV Adjustments⁴ | B6: =(194%/B10-1)/10%*1.7 | C6: =(194%/C10-1)/10%*1.7 | D6: =(194%/D10-1)/10%*1.7 | E6: =(194%/E10-1)/10%*1.7 | F6: =(194%/F10-1)/10%*1.7 | G6: =(194%/G10-1)/10%*1.7 | H6: =(194%/H10-1)/10%*1.7 | I6: =(194%/I10-1)/10%*1.7 | ... AD6: =(194%/AD10-1)/10%*1.7
A7: RAGU Score | B7: =SUM(B2:B6) | C7: =SUM(C2:C6) | D7: =SUM(D2:D6) | E7: =SUM(E2:E6) | F7: =SUM(F2:F6) | G7: =SUM(G2:G6) | H7: =SUM(H2:H6) | I7: =SUM(I2:I6) | ... AD7: =SUM(AD2:AD6)
B8: =B2+B4 | C8: =C2+C4 | D8: =D2+D4 | E8: =E2+E4 | F8: =F2+F4 | G8: =G2+G4 | H8: =H2+H4 | I8: =I2+I4 | ... AD8: =AD2+AD4
A9: Context info
A10: BlackBook LTV (Baseline 194%) | B10: ='Data Tables (Q)'!B35 | C10: ='Data Tables (Q)'!C35 | D10: ='Data Tables (Q)'!D35 | E10: ='Data Tables (Q)'!E35 | F10: ='Data Tables (Q)'!F35 | G10: ='Data Tables (Q)'!G35 | H10: ='Data Tables (Q)'!H35 | I10: ='Data Tables (Q)'!I35 | ... AC10: ='Data Tables (Q)'!AC35 | AD10: ='Data Tables (M)'!BS35*AG10+AF10*(1-AG10) | AF10: =194/142-1 | AG10: 1
A11: Origination MMI | B11: 136.4 | C11: 141.3 | D11: 148 | E11: 151.5 | F11: 156.6 | G11: 149.5 | H11: 178.6 | I11: 176.8 | J11: 183.6 | K11: 218.6 | L11: 217 | M11: 252.9 | N11: 243.1 | O11: 245.1 | P11: 229.8 | Q11: 221.6 | R11: 229.4 | S11: 224.9 | T11: 212.6 | U11: 204.9 | V11: 204.2 | W11: 199.2 | X11: 202.8 | Y11: 203.3 | AA11: 205.86667 | AD11: 203 | AF11: =AF10*17
A12: MMI Impact⁵ | B12: 0.04 | C12: 0.11 | D12: 0.13 | E12: 0.146 | F12: 0.24456068 | G12: 0.33059156 | H12: 0.11738195 | I12: 0.16960025 | J12: 0.13323456 | K12: -0.042561451 | L12: -0.041246333 | M12: -0.18913444 | N12: -0.16706463 | O12: -0.1889941 | P12: -0.1447923 | Q12: -0.12461664 | R12: -0.16400894 | S12: -0.15141756 | T12: -0.10485319 | U12: -0.070296606 | V12: -0.064207992 | W12: -0.037128724 | X12: -0.03 | Y12: -0.03 | Z12: -0.03 | AA12: -0.026435638 | AD12: -0.03
A13: Adjustment to RAGU Score from MMI | B13: =B12/10%*1.7 | C13: =C12/10%*1.7 | D13: =D12/10%*1.7 | E13: =E12/10%*1.7 | F13: =F12/10%*1.7 | G13: =G12/10%*1.7 | H13: =H12/10%*1.7 | I13: =I12/10%*1.7 | ... AA13: =AA12/10%*1.7 | AD13: =AD12/10%*1.7
A14: RAGU Score (adjusted for MMI) | B14: =B7+B13 | C14: =C7+C13 | D14: =D7+D13 | E14: =E7+E13 | F14: =F7+F13 | G14: =G7+G13 | H14: =H7+H13 | I14: =I7+I13 | ... AA14: =AA7+AA13 | AD14: =AD7+AD13
A15: t_c CNL⁶ | B15: 0.29154705 | C15: 0.26701329 | D15: 0.26145029 | E15: 0.23952914 | F15: 0.23186042 | G15: 0.21263925 | H15: 0.20377448 | I15: 0.20617832 | J15: 0.19926145 | K15: 0.25192153 | L15: 0.27834432 | M15: 0.31359567 | N15: 0.32930686 | O15: 0.30769927 | P15: 0.31605089 | Q15: 0.28515644 | R15: 0.28758836
A16: Implied t-1 CNL | B16: =B15-($AD$14-B14)*1% | C16: =C15-($AD$14-C14)*1% | D16: =D15-($AD$14-D14)*1% | E16: =E15-($AD$14-E14)*1% | F16: =F15-($AD$14-F14)*1% | G16: =G15-($AD$14-G14)*1% | H16: =H15-($AD$14-H14)*1% | I16: =I15-($AD$14-I14)*1% | ... R16: =R15-($AD$14-R14)*1% | AD16: 0.2475
A19: 1: | B19: Model Score excludes buybacks and high amount financed.
A20: 2: | B20: We are currently working with Pricing to determine how to use FRN3.1 scores, there are large discrepancies between model scores as booked and FRN3.1 due to what might be centering issues.
A21: 3: | B21: Biggest impacts to Gross Loss Adjustments are Dealer Level, weekday/weekend decision, and high mileage classification.
B22: Not accounting for potential differences in Gross Loss for test loans.
B23: See Appendix for details on other factors
A24: 4: | B24: Biggest impacts to Recovery Adjustments are mileage/age, impound probability, and vehicle class.
A25: 5: | B25: LTV adjustments are made using the 10% LTV improvement->170bps to CNL heuristic, based on BlackBook LTV values.
A26: 6: | B26: MMI uses adjusted index (2019 seasonality). The MMI Impact compares the actual MMI to a 3% annual growth.
B27: A positive impact of X% means sold recovery will be X% better.
A28: 7: | B28: tc CNL uses UGLY Model projections, and 2023 Q1 blends 75% UGLY Model with 25% Loss Committee.

Sheet FRN Table
A1: FRN | B1: 2016 | C1: 2017 | D1: 2018 | E1: 2019 | F1: 2020 Q1 | G1: 2020 Q2 | H1: 2020 Q3 | I1: 2020 Q4 | J1: 2021 Q1 | K1: 2021 Q2 | L1: 2021 Q3 | M1: 2021 Q4 | N1: 2022 Q1 | O1: 2022 Q2 | P1: 2022 Q3 | Q1: 2022 Q4 | R1: 2023 Q1 | S1: 2023 Q2 | T1: 2023 Q3 | U1: 2023 Q4 | V1: 2024 Q1 | W1: 2024 Q2 | X1: 2024 Q3 | Y1: 2024 Q4 | Z1: 2025 Q1 | AA1: 2025 Q2 | AB1: 2025 Q3 | AC1: 2025 Q4 | AD1: t-1 | AF1: t-1 manual input | AG1: Use Recent Month? | AH1: Use Reassessed Model Score?
A2: Contract Model Score¹ | B2: ='Data Tables (Q)'!B20 | C2: ='Data Tables (Q)'!C20 | D2: ='Data Tables (Q)'!D20 | E2: ='Data Tables (Q)'!E20 | F2: ='Data Tables (Q)'!F20 | G2: ='Data Tables (Q)'!G20 | H2: ='Data Tables (Q)'!H20 | I2: ='Data Tables (Q)'!I20 | ... AC2: ='Data Tables (Q)'!AC20 | AD2: ='Data Tables (M)'!BS20*AG2+AF2*(1-AG2) | AF2: ='t-1 Data Table'!N5 | AG2: 1 | AH2: 0
A3: Shift to FRN 3.1 Score² | B3: ='Data Tables (Q)'!B21*AH2 | C3: ='Data Tables (Q)'!C21*AI2 | D3: ='Data Tables (Q)'!D21*AJ2 | E3: ='Data Tables (Q)'!E21*AK2 | F3: ='Data Tables (Q)'!F21*AL2 | G3: ='Data Tables (Q)'!G21*AM2 | H3: ='Data Tables (Q)'!H21*AN2 | I3: ='Data Tables (Q)'!I21*AO2 | ... AC3: ='Data Tables (Q)'!AC21*BI2 | AD3: =('Data Tables (M)'!BC21*AG3+AF3*(1-AG3))*$AH$2 | AF3: 0 | AG3: 1
A4: Gross Loss Adjustments (Dealer Level, vehicle age, etc.)² | B4: ='Data Tables (Q)'!B22 | C4: ='Data Tables (Q)'!C22 | D4: ='Data Tables (Q)'!D22 | E4: ='Data Tables (Q)'!E22 | F4: ='Data Tables (Q)'!F22 | G4: ='Data Tables (Q)'!G22 | H4: ='Data Tables (Q)'!H22 | I4: ='Data Tables (Q)'!I22 | ... AC4: ='Data Tables (Q)'!AC22 | AD4: ='Data Tables (M)'!BS22*AG4+AF4*(1-AG4) | AG4: 1
A5: Recovery Adjustments excluding LTV (Mileage, LOB, etc.)³ | B5: ='Data Tables (Q)'!B23 | C5: ='Data Tables (Q)'!C23 | D5: ='Data Tables (Q)'!D23 | E5: ='Data Tables (Q)'!E23 | F5: ='Data Tables (Q)'!F23 | G5: ='Data Tables (Q)'!G23 | H5: ='Data Tables (Q)'!H23 | I5: ='Data Tables (Q)'!I23 | ... AC5: ='Data Tables (Q)'!AC23 | AD5: ='Data Tables (M)'!BS23*AG5+AF5*(1-AG5) | AG5: 1
A6: BBLTV Adjustments⁴ | B6: =(194%/B10-1)/10%*1.7 | C6: =(194%/C10-1)/10%*1.7 | D6: =(194%/D10-1)/10%*1.7 | E6: =(194%/E10-1)/10%*1.7 | F6: =(194%/F10-1)/10%*1.7 | G6: =(194%/G10-1)/10%*1.7 | H6: =(194%/H10-1)/10%*1.7 | I6: =(194%/I10-1)/10%*1.7 | ... AD6: =(194%/AD10-1)/10%*1.7
A7: RAGU Score | B7: =SUM(B2:B6) | C7: =SUM(C2:C6) | D7: =SUM(D2:D6) | E7: =SUM(E2:E6) | F7: =SUM(F2:F6) | G7: =SUM(G2:G6) | H7: =SUM(H2:H6) | I7: =SUM(I2:I6) | ... AD7: =SUM(AD2:AD6)
B8: =B2+B4 | C8: =C2+C4 | D8: =D2+D4 | E8: =E2+E4 | F8: =F2+F4 | G8: =G2+G4 | H8: =H2+H4 | I8: =I2+I4 | ... AD8: =AD2+AD4
A9: Context info
A10: BlackBook LTV (Baseline 194%) | B10: ='Data Tables (Q)'!B26 | C10: ='Data Tables (Q)'!C26 | D10: ='Data Tables (Q)'!D26 | E10: ='Data Tables (Q)'!E26 | F10: ='Data Tables (Q)'!F26 | G10: ='Data Tables (Q)'!G26 | H10: ='Data Tables (Q)'!H26 | I10: ='Data Tables (Q)'!I26 | ... AC10: ='Data Tables (Q)'!AC26 | AD10: ='Data Tables (M)'!BS26*AG10+AF10*(1-AG10) | AG10: 1
A11: Origination MMI | B11: 136.4 | C11: 141.3 | D11: 148 | E11: 151.5 | F11: 156.6 | G11: 149.5 | H11: 178.6 | I11: 176.8 | J11: 183.6 | K11: 218.6 | L11: 217 | M11: 252.9 | N11: 243.1 | O11: 245.1 | P11: 229.8 | Q11: 221.6 | R11: 229.4 | S11: 224.9 | T11: 212.6 | U11: 204.9 | V11: 204.2 | W11: 199.2 | X11: 202.8 | Y11: 203.3 | AA11: 205.86667 | AD11: 203
A12: MMI Impact⁵ | B12: 0.04 | C12: 0.11 | D12: 0.13 | E12: 0.146 | F12: 0.24456068 | G12: 0.33059156 | H12: 0.11738195 | I12: 0.16960025 | J12: 0.13323456 | K12: -0.042561451 | L12: -0.041246333 | M12: -0.18913444 | N12: -0.16706463 | O12: -0.1889941 | P12: -0.1447923 | Q12: -0.12461664 | R12: -0.16400894 | S12: -0.15141756 | T12: -0.10485319 | U12: -0.070296606 | V12: -0.064207992 | W12: -0.037128724 | X12: -0.03 | Y12: -0.03 | Z12: -0.03 | AA12: -0.026435638 | AD12: -0.03
A13: Adjustment to RAGU Score from MMI | B13: =B12/10%*1.7 | C13: =C12/10%*1.7 | D13: =D12/10%*1.7 | E13: =E12/10%*1.7 | F13: =F12/10%*1.7 | G13: =G12/10%*1.7 | H13: =H12/10%*1.7 | I13: =I12/10%*1.7 | ... AA13: =AA12/10%*1.7 | AD13: =AD12/10%*1.7
A14: RAGU Score (adjusted for MMI) | B14: =B7+B13 | C14: =C7+C13 | D14: =D7+D13 | E14: =E7+E13 | F14: =F7+F13 | G14: =G7+G13 | H14: =H7+H13 | I14: =I7+I13 | ... AA14: =AA7+AA13 | AD14: =AD7+AD13
A15: t_c CNL⁶ | B15: 0.36336386 | C15: 0.32343826 | D15: 0.28323748 | E15: 0.24889569 | F15: 0.22848192 | G15: 0.21527641 | H15: 0.24687227 | I15: 0.28284071 | J15: 0.23888263 | K15: 0.27508726 | L15: 0.30977847 | M15: 0.35995406 | N15: 0.3820747 | O15: 0.36047353 | P15: 0.3397475 | Q15: 0.31875734 | R15: 0.30830728
A16: Implied t-1 CNL | B16: =B15-($AD$14-B14)*1% | C16: =C15-($AD$14-C14)*1% | D16: =D15-($AD$14-D14)*1% | E16: =E15-($AD$14-E14)*1% | F16: =F15-($AD$14-F14)*1% | G16: =G15-($AD$14-G14)*1% | H16: =H15-($AD$14-H14)*1% | I16: =I15-($AD$14-I14)*1% | ... R16: =R15-($AD$14-R14)*1% | AD16: 0.281
A19: 1: | B19: Model Score excludes buybacks and high amount financed.
A20: 2: | B20: We are currently working with Pricing to determine how to use FRN3.1 scores, there are large discrepancies between model scores as booked and FRN3.1 due to what might be centering issues.
A21: 3: | B21: Biggest impacts to Gross Loss Adjustments are Dealer Level, weekday/weekend decision, and high mileage classification.
B22: Not accounting for potential differences in Gross Loss for test loans.
B23: See Appendix for details on other factors
A24: 4: | B24: Biggest impacts to Recovery Adjustments are mileage/age, impound probability, and vehicle class.
A25: 5: | B25: LTV adjustments are made using the 10% LTV improvement->170bps to CNL heuristic, based on BlackBook LTV values.
A26: 6: | B26: MMI uses adjusted index (2019 seasonality). The MMI Impact compares the actual MMI to a 3% annual growth.
B27: A positive impact of X% means sold recovery will be X% better.
A28: 7: | B28: tc CNL uses UGLY Model projections, and 2023 Q1 blends 75% UGLY Model with 25% Loss Committee.

Sheet FLD Table
A1: FLD | B1: 2020 Q1 | C1: 2020 Q2 | D1: 2020 Q3 | E1: 2020 Q4 | F1: 2021 Q1 | G1: 2021 Q2 | H1: 2021 Q3 | I1: 2021 Q4 | J1: 2022 Q1 | K1: 2022 Q2 | L1: 2022 Q3 | M1: 2022 Q4 | N1: 2023 Q1 | O1: 2023 Q2 | P1: 2023 Q3 | Q1: 2023 Q4 | R1: 2024 Q1 | S1: 2024 Q2 | T1: 2024 Q3 | U1: 2024 Q4 | V1: 2025 Q1 | W1: 2025 Q2 | X1: 2025 Q3 | Y1: 2025 Q4 | Z1: t-1 | AB1: t-1 manual input | AC1: Use Recent Month? | AD1: Use Reassessed Model Score?
A2: Contract Model Score¹ | B2: ='Data Tables (Q)'!F11 | C2: ='Data Tables (Q)'!G11 | D2: ='Data Tables (Q)'!H11 | E2: ='Data Tables (Q)'!I11 | F2: ='Data Tables (Q)'!J11 | G2: ='Data Tables (Q)'!K11 | H2: ='Data Tables (Q)'!L11 | I2: ='Data Tables (Q)'!M11 | ... Y2: ='Data Tables (Q)'!AC11 | Z2: ='Data Tables (M)'!BS11*AC2+AB2*(1-AC2) | AB2: ='t-1 Data Table'!N4 | AC2: 1 | AD2: 0
