Workbook

Sheet Data Tables (Q)
A1: AN | B1: 2016 | C1: 2017 | D1: 2018 | E1: 2019 | F1: 2020 Q1 | G1: 2020 Q2 | H1: 2020 Q3 | I1: 2020 Q4 | J1: 2021 Q1 | K1: 2021 Q2 | L1: 2021 Q3 | M1: 2021 Q4 | N1: 2022 Q1 | O1: 2022 Q2 | P1: 2022 Q3 | Q1: 2022 Q4 | R1: 2023 Q1 | S1: 2023 Q2 | T1: 2023 Q3 | U1: 2023 Q4 | V1: 2024 Q1 | W1: 2024 Q2 | X1: 2024 Q3 | Y1: 2024 Q4 | Z1: 2025 Q1 | AA1: 2025 Q2 | AB1: 2025 Q3 | AC1: 2025 Q4
A2: Contract Model Score | B2: 130.07704 | C2: 132.82918 | D2: 132.99304 | E2: 132.10911 | F2: 131.79764 | G2: 133.71059 | H2: 135.28557 | I2: 135.79608 | J2: 134.60179 | K2: 135.14257 | L2: 135.36265 | M2: 134.41538 | N2: 134.0686 | O2: 135.89246 | P2: 136.14781 | Q2: 136.75155 | R2: 136.66305 | S2: 136.90907 | T2: 136.43849 | U2: 137.02135 | V2: 136.37212 | W2: 137.12198 | X2: 138.09052 | Y2: 136.80136 | Z2: 136.83702 | AA2: 138.03382 | AB2: 138.55808 | AC2: 139.3761 | AD2: 140.46038
A3: Model Score | B3: 0 | C3: 0 | D3: 0 | E3: 0 | F3: 0 | G3: 0 | H3: 0 | I3: 0 | J3: 0 | K3: 0 | L3: 0 | M3: 0 | N3: 0 | O3: 0 | P3: 0 | Q3: 0 | R3: 0 | S3: 0 | T3: 0 | U3: 0 | V3: 0 | W3: 0 | X3: 0 | Y3: 0 | Z3: 0 | AA3: 0 | AB3: 0 | AC3: 0 | AD3: 0
A4: Gross Loss Adjustments (Dealer level, high PTI, etc.) | B4: 0.36824634 | C4: 0.64268496 | D4: 0.73760946 | E4: 0.54113333 | F4: 0.64749521 | G4: 0.51566419 | H4: -0.19174308 | I4: 0.2567337 | J4: 0.53917167 | K4: 0.53578838 | L4: 0.54503838 | M4: 0.45373656 | N4: 0.86176791 | O4: 0.76242484 | P4: 0.84667111 | Q4: 0.87913297 | R4: 0.57044205 | S4: 0.53802473 | T4: -0.091428861 | U4: 0.10384027 | V4: 0.58774847 | W4: 0.9875169 | X4: 0.73459088 | Y4: 1.3084266 | Z4: 1.905738 | AA4: 2.4385938 | AB4: 3.0483132 | AC4: 3.2623198 | AD4: 1.914656
A5: Recovery Adjustments excluding LTV (Mileage, vehicle type, etc.) | B5: -0.39258197 | C5: 0.31810502 | D5: 0.19702468 | E5: 0.1634963 | F5: -0.10819935 | G5: -0.56943614 | H5: -0.21425416 | I5: 0.68058865 | J5: 0.22441002 | K5: 0.2090722 | L5: -0.07596809 | M5: -0.50481626 | N5: -1.1464984 | O5: -0.99272578 | P5: -1.3374362 | Q5: -1.1137921 | R5: -1.2742672 | S5: -1.3069658 | T5: -1.5595382 | U5: -1.0846185 | V5: -1.7417311 | W5: -1.1027639 | X5: -0.63328552 | Y5: 0.18345643 | Z5: 0.080554239 | AA5: 0.55716861 | AB5: 0.84213839 | AC5: 1.31387 | AD5: 1.8234979
A6: LTV Adjustments | B6: 0.39258197 | C6: -0.31810502 | D6: -0.19702468 | E6: -0.1634963 | F6: 0.10819935 | G6: 0.56943614 | H6: 0.21425416 | I6: -0.68058865 | J6: -0.22441002 | K6: -0.2090722 | L6: 0.07596809 | M6: 0.50481626 | N6: 1.1464984 | O6: 0.99272578 | P6: 1.3374362 | Q6: 1.1137921 | R6: 1.2742672 | S6: 1.3069658 | T6: 1.5595382 | U6: 1.0846185 | V6: 1.7417311 | W6: 1.1027639 | X6: 0.63328552 | Y6: -0.18345643 | Z6: -0.080554239 | AA6: -0.55716861 | AB6: -0.84213839 | AC6: -1.31387 | AD6: -1.8234979
A7: RAGU Score | B7: 130.44529 | C7: 133.47187 | D7: 133.73065 | E7: 132.65024 | F7: 132.44513 | G7: 134.22626 | H7: 135.09383 | I7: 136.05282 | J7: 135.14096 | K7: 135.67836 | L7: 135.90769 | M7: 134.86912 | N7: 134.93036 | O7: 136.65488 | P7: 136.99448 | Q7: 137.63069 | R7: 137.23349 | S7: 137.44709 | T7: 136.34706 | U7: 137.12519 | V7: 136.95987 | W7: 138.1095 | X7: 138.82511 | Y7: 138.10978 | Z7: 138.74276 | AA7: 140.47241 | AB7: 141.60639 | AC7: 142.63842 | AD7: 142.37504
A8: LTV | B8: 1.9087244 | C8: 1.9022428 | D8: 1.9108901 | E8: 1.9482127 | F8: 1.902826 | G8: 1.9471127 | H8: 1.670784 | I8: 1.6601973 | J8: 1.6894127 | K8: 1.515447 | L8: 1.5852082 | M8: 1.5827355 | N8: 1.615349 | O8: 1.7131948 | P8: 1.7509586 | Q8: 1.815336 | R8: 1.8260098 | S8: 1.7142071 | T8: 1.6734988 | U8: 1.7098679 | V8: 1.735541 | W8: 1.683241 | X8: 1.5898075 | Y8: 1.6176035 | Z8: 1.6082016 | AA8: 1.5674695 | AB8: 1.5727056 | AC8: 1.5517231 | AD8: 1.5674185
A10: FLD | F10: 2020 Q1 | G10: 2020 Q2 | H10: 2020 Q3 | I10: 2020 Q4 | J10: 2021 Q1 | K10: 2021 Q2 | L10: 2021 Q3 | M10: 2021 Q4 | N10: 2022 Q1 | O10: 2022 Q2 | P10: 2022 Q3 | Q10: 2022 Q4 | R10: 2023 Q1 | S10: 2023 Q2 | T10: 2023 Q3 | U10: 2023 Q4 | V10: 2024 Q1 | W10: 2024 Q2 | X10: 2024 Q3 | Y10: 2024 Q4 | Z10: 2025 Q1 | AA10: 2025 Q2 | AB10: 2025 Q3 | AC10: 2025 Q4
A11: Contract Model Score | F11: 131.95039 | G11: 135.66547 | H11: 137.78086 | I11: 140.37625 | J11: 136.75685 | K11: 136.18261 | L11: 135.63105 | M11: 134.62935 | N11: 134.17392 | O11: 135.83718 | P11: 136.96375 | Q11: 138.77228 | R11: 141.32316 | S11: 138.86319 | T11: 137.95666 | U11: 139.5662 | V11: 138.5244 | W11: 138.40978 | X11: 140.36331 | Y11: 138.38769 | Z11: 136.70743 | AA11: 138.3478 | AB11: 138.1021 | AC11: 138.94555 | AD11: 141.12585
A12: Model Score | F12: 0 | G12: 0 | H12: 0 | I12: 0 | J12: 0 | K12: 0 | L12: 0 | M12: 0 | N12: 0 | O12: 0 | P12: 0 | Q12: 0 | R12: 0 | S12: 0 | T12: 0 | U12: 0 | V12: 0 | W12: 0 | X12: 0 | Y12: 0 | Z12: 0 | AA12: 0 | AB12: 0 | AC12: 0 | AD12: 0
A13: Gross Loss Adjustments (Dealer level, high PTI, etc.) | F13: -2.5958615 | G13: -2.2718375 | H13: -1.6417215 | I13: -0.13010911 | J13: 1.0953963 | K13: -0.99165458 | L13: -1.0619348 | M13: 0.042055432 | N13: -0.21227366 | O13: -0.013263308 | P13: 0.42673181 | Q13: 0.52563162 | R13: 0.66118191 | S13: -0.18861412 | T13: 0.32152445 | U13: 0.67156911 | V13: 1.443778 | W13: 2.2613562 | X13: 3.1268281 | Y13: 3.1597805 | Z13: 3.2253291 | AA13: 2.7901567 | AB13: 3.4402208 | AC13: 1.8901157 | AD13: 1.229186
A14: Recovery Adjustments excluding LTV (Mileage, vehicle type, etc.) | F14: -0.1173702 | G14: -0.20492955 | H14: 0.0032451687 | I14: 0.18043505 | J14: -0.25831759 | K14: -0.28531198 | L14: -0.093966231 | M14: -0.57675673 | N14: -1.2876293 | O14: -1.300891 | P14: -1.6502648 | Q14: -0.83079473 | R14: -1.382572 | S14: -1.5799359 | T14: -1.0542949 | U14: -1.3557994 | V14: -1.4970812 | W14: -0.6577689 | X14: -0.46079243 | Y14: 0.78463273 | Z14: 0.047183501 | AA14: 0.5632265 | AB14: 0.93591851 | AC14: 1.7099785 | AD14: 0.85639536
A15: LTV Adjustments | F15: 0.1173702 | G15: 0.20492955 | H15: -0.0032451687 | I15: -0.18043505 | J15: 0.25831759 | K15: 0.28531198 | L15: 0.093966231 | M15: 0.57675673 | N15: 1.2876293 | O15: 1.300891 | P15: 1.6502648 | Q15: 0.83079473 | R15: 1.382572 | S15: 1.5799359 | T15: 1.0542949 | U15: 1.3557994 | V15: 1.4970812 | W15: 0.6577689 | X15: 0.46079243 | Y15: -0.78463273 | Z15: -0.047183501 | AA15: -0.5632265 | AB15: -0.93591851 | AC15: -1.7099785 | AD15: -0.85639536
A16: RAGU Score | F16: 129.35453 | G16: 133.39363 | H16: 136.13914 | I16: 140.24614 | J16: 137.85224 | K16: 135.19096 | L16: 134.56911 | M16: 134.6714 | N16: 133.96165 | O16: 135.82392 | P16: 137.39048 | Q16: 139.29791 | R16: 141.98434 | S16: 138.67458 | T16: 138.27818 | U16: 140.23777 | V16: 139.96818 | W16: 140.67114 | X16: 143.49014 | Y16: 141.54747 | Z16: 139.93276 | AA16: 141.13795 | AB16: 141.54232 | AC16: 140.83567 | AD16: 142.35504
A17: LTV | F17: 1.4205628 | G17: 1.3731628 | H17: 1.2237836 | I17: 1.2677232 | J17: 1.3305309 | K17: 1.2336043 | L17: 1.2737699 | M17: 1.3338379 | N17: 1.3410876 | O17: 1.3363956 | P17: 1.3222392 | Q17: 1.3185246 | R17: 1.2673155 | S17: 1.2983826 | T17: 1.2656128 | U17: 1.2867607 | V17: 1.3826943 | W17: 1.3642501 | X17: 1.3452332 | Y17: 1.3398438 | Z17: 1.3796912 | AA17: 1.4106684 | AB17: 1.4121804 | AC17: 1.40963 | AD17: 1.4745501
A19: FRN | B19: 2016 | C19: 2017 | D19: 2018 | E19: 2019 | F19: 2020 Q1 | G19: 2020 Q2 | H19: 2020 Q3 | I19: 2020 Q4 | J19: 2021 Q1 | K19: 2021 Q2 | L19: 2021 Q3 | M19: 2021 Q4 | N19: 2022 Q1 | O19: 2022 Q2 | P19: 2022 Q3 | Q19: 2022 Q4 | R19: 2023 Q1 | S19: 2023 Q2 | T19: 2023 Q3 | U19: 2023 Q4 | V19: 2024 Q1 | W19: 2024 Q2 | X19: 2024 Q3 | Y19: 2024 Q4 | Z19: 2025 Q1 | AA19: 2025 Q2 | AB19: 2025 Q3 | AC19: 2025 Q4
A20: Contract Model Score | B20: 131.17685 | C20: 136.73938 | D20: 136.80349 | E20: 132.53803 | F20: 131.13303 | G20: 132.90504 | H20: 133.93048 | I20: 132.80381 | J20: 135.44811 | K20: 135.18735 | L20: 134.94602 | M20: 132.89928 | N20: 134.06325 | O20: 136.81721 | P20: 138.00243 | Q20: 139.77793 | R20: 141.27719 | S20: 140.58734 | T20: 140.72103 | U20: 139.02514 | V20: 138.13163 | W20: 140.17356 | X20: 141.55375 | Y20: 139.97097 | Z20: 139.83315 | AA20: 140.63434 | AB20: 140.96388 | AC20: 141.85749 | AD20: 142.8984
A21: Model Score | B21: 0 | C21: 0 | D21: 0 | E21: 0 | F21: 0 | G21: 0 | H21: 0 | I21: 0 | J21: 0 | K21: 0 | L21: 0 | M21: 0 | N21: 0 | O21: 0 | P21: 0 | Q21: 0 | R21: 0 | S21: 0 | T21: 0 | U21: 0 | V21: 0 | W21: 0 | X21: 0 | Y21: 0 | Z21: 0 | AA21: 0 | AB21: 0 | AC21: 0 | AD21: 0
A22: Gross Loss Adjustments (Dealer level, high PTI, etc.) | B22: -0.3279542 | C22: 0.20210618 | D22: -0.19413065 | E22: 0.046002039 | F22: 0.53224606 | G22: 0.71345069 | H22: -0.27007229 | I22: -0.83970892 | J22: -0.28336522 | K22: 0.096546832 | L22: -0.09886035 | M22: -1.1380306 | N22: -1.0378799 | O22: 0.13115547 | P22: 0.19142619 | Q22: -0.073111643 | R22: 0.7503485 | S22: 0.82560056 | T22: 0.86082024 | U22: 0.25128083 | V22: -0.094949442 | W22: 0.006680112 | X22: 0.37649879 | Y22: 0.43243354 | Z22: 1.0053154 | AA22: 1.111758 | AB22: 1.8168113 | AC22: 2.6050902 | AD22: 2.0098245
A23: Recovery Adjustments excluding LTV (Mileage, vehicle type, etc.) | B23: -0.48077299 | C23: 0.29742497 | D23: 0.28839507 | E23: 0.13368594 | F23: -0.35590629 | G23: -0.39916326 | H23: 0.015803735 | I23: 0.29142926 | J23: 0.22685781 | K23: 0.15910038 | L23: -0.16651055 | M23: -0.64123411 | N23: -1.406421 | O23: -1.3721178 | P23: -1.3559362 | Q23: -1.2985672 | R23: -1.2296732 | S23: -1.4790928 | T23: -1.4399127 | U23: -1.4356336 | V23: -1.4637224 | W23: -1.106972 | X23: -0.63836717 | Y23: 0.44202526 | Z23: 0.2294098 | AA23: 0.23943624 | AB23: 0.95567212 | AC23: 1.5113807 | AD23: 1.5112986
A24: LTV Adjustments | B24: 0.48077299 | C24: -0.29742497 | D24: -0.28839507 | E24: -0.13368594 | F24: 0.35590629 | G24: 0.39916326 | H24: -0.015803735 | I24: -0.29142926 | J24: -0.22685781 | K24: -0.15910038 | L24: 0.16651055 | M24: 0.64123411 | N24: 1.406421 | O24: 1.3721178 | P24: 1.3559362 | Q24: 1.2985672 | R24: 1.2296732 | S24: 1.4790928 | T24: 1.4399127 | U24: 1.4356336 | V24: 1.4637224 | W24: 1.106972 | X24: 0.63836717 | Y24: -0.44202526 | Z24: -0.2294098 | AA24: -0.23943624 | AB24: -0.95567212 | AC24: -1.5113807 | AD24: -1.5112986
A25: RAGU Score | B25: 130.8489 | C25: 136.94149 | D25: 136.60936 | E25: 132.58403 | F25: 131.66528 | G25: 133.61849 | H25: 133.66041 | I25: 131.9641 | J25: 135.16475 | K25: 135.2839 | L25: 134.84716 | M25: 131.76125 | N25: 133.02537 | O25: 136.94836 | P25: 138.19386 | Q25: 139.70482 | R25: 142.02754 | S25: 141.41294 | T25: 141.58185 | U25: 139.27642 | V25: 138.03669 | W25: 140.18024 | X25: 141.93025 | Y25: 140.40341 | Z25: 140.83847 | AA25: 141.74609 | AB25: 142.7807 | AC25: 144.46258 | AD25: 144.90822
A26: LTV | B26: 2.1505528 | C26: 2.2073907 | D26: 2.1097029 | E26: 2.0875659 | F26: 1.9401142 | G26: 1.9433066 | H26: 1.9003889 | I26: 2.0282542 | J26: 1.7336042 | K26: 1.5122458 | L26: 1.6173146 | M26: 1.6867925 | N26: 1.6567267 | O26: 1.6662777 | P26: 1.6871017 | Q26: 1.687404 | R26: 1.7328819 | S26: 1.5404666 | T26: 1.4968258 | U26: 1.4613721 | V26: 1.4832384 | W26: 1.4770275 | X26: 1.4906501 | Y26: 1.4849278 | Z26: 1.4878209 | AA26: 1.4286425 | AB26: 1.424556 | AC26: 1.4210557 | AD26: 1.4520697
A28: STG | B28: 2016 | C28: 2017 | D28: 2018 | E28: 2019 | F28: 2020 Q1 | G28: 2020 Q2 | H28: 2020 Q3 | I28: 2020 Q4 | J28: 2021 Q1 | K28: 2021 Q2 | L28: 2021 Q3 | M28: 2021 Q4 | N28: 2022 Q1 | O28: 2022 Q2 | P28: 2022 Q3 | Q28: 2022 Q4 | R28: 2023 Q1 | S28: 2023 Q2 | T28: 2023 Q3 | U28: 2023 Q4 | V28: 2024 Q1 | W28: 2024 Q2 | X28: 2024 Q3 | Y28: 2024 Q4 | Z28: 2025 Q1 | AA28: 2025 Q2 | AB28: 2025 Q3 | AC28: 2025 Q4
A29: Contract Model Score | B29: 129.64201 | C29: 131.65669 | D29: 131.56906 | E29: 129.50527 | F29: 130.0304 | G29: 133.13562 | H29: 135.5242 | I29: 135.28733 | J29: 135.28771 | K29: 135.49901 | L29: 135.05653 | M29: 133.65336 | N29: 134.55 | O29: 136.72731 | P29: 137.27114 | Q29: 138.30195 | R29: 139.23035 | S29: 137.71584 | T29: 138.53984 | U29: 137.48747 | V29: 136.76023 | W29: 137.47802 | X29: 138.54354 | Y29: 137.20905 | Z29: 136.6684 | AA29: 137.94719 | AB29: 138.66055 | AC29: 140.03752 | AD29: 141.52846
A30: Model Score | B30: 0 | C30: 0 | D30: 0 | E30: 0 | F30: 0 | G30: 0 | H30: 0 | I30: 0 | J30: 0 | K30: 0 | L30: 0 | M30: 0 | N30: 0 | O30: 0 | P30: 0 | Q30: 0 | R30: 0 | S30: 0 | T30: 0 | U30: 0 | V30: 0 | W30: 0 | X30: 0 | Y30: 0 | Z30: 0 | AA30: 0 | AB30: 0 | AC30: 0 | AD30: 0
A31: Gross Loss Adjustments (Dealer level, high PTI, etc.) | B31: 0.55168785 | C31: 0.53745688 | D31: 0.47283336 | E31: 0.26299826 | F31: -0.17705346 | G31: -0.23517459 | H31: 0.1178712 | I31: 0.041467995 | J31: 0.88577009 | K31: 1.0419584 | L31: 0.74064638 | M31: 0.42910054 | N31: -0.22394537 | O31: -0.040705244 | P31: -0.48924385 | Q31: 0.14118108 | R31: -0.038606969 | S31: -0.33664797 | T31: 0.57101574 | U31: 0.4741766 | V31: 0.95904886 | W31: 1.7697237 | X31: 2.0103731 | Y31: 2.1616877 | Z31: 2.2549256 | AA31: 1.949069 | AB31: 2.2586722 | AC31: 2.800372 | AD31: 2.1336389
A32: Recovery Adjustments excluding LTV (Mileage, vehicle type, etc.) | B32: -0.51258551 | C32: 0.27300264 | D32: 0.28674551 | E32: 0.0087854085 | F32: -0.0579634 | G32: -0.23514923 | H32: -0.17763246 | I32: 0.39104339 | J32: 0.16365721 | K32: 0.14110014 | L32: -0.19682375 | M32: -0.69220439 | N32: -1.0157167 | O32: -1.5663499 | P32: -1.5843627 | Q32: -1.3083488 | R32: -1.0537594 | S32: -0.95726796 | T32: -1.3703764 | U32: -1.3584952 | V32: -1.6674839 | W32: -1.1614308 | X32: -0.66741054 | Y32: 0.10374512 | Z32: 0.33099157 | AA32: 0.40683462 | AB32: 0.67784691 | AC32: 1.6772277 | AD32: 0.91825423
A33: LTV Adjustments | B33: 0.51258551 | C33: -0.27300264 | D33: -0.28674551 | E33: -0.0087854085 | F33: 0.0579634 | G33: 0.23514923 | H33: 0.17763246 | I33: -0.39104339 | J33: -0.16365721 | K33: -0.14110014 | L33: 0.19682375 | M33: 0.69220439 | N33: 1.0157167 | O33: 1.5663499 | P33: 1.5843627 | Q33: 1.3083488 | R33: 1.0537594 | S33: 0.95726796 | T33: 1.3703764 | U33: 1.3584952 | V33: 1.6674839 | W33: 1.1614308 | X33: 0.66741054 | Y33: -0.10374512 | Z33: -0.33099157 | AA33: -0.40683462 | AB33: -0.67784691 | AC33: -1.6772277 | AD33: -0.91825423
A34: RAGU Score | B34: 130.1937 | C34: 132.19415 | D34: 132.0419 | E34: 129.76827 | F34: 129.85334 | G34: 132.90045 | H34: 135.64207 | I34: 135.32879 | J34: 136.17348 | K34: 136.54097 | L34: 135.79718 | M34: 134.08246 | N34: 134.32605 | O34: 136.68661 | P34: 136.7819 | Q34: 138.44313 | R34: 139.19174 | S34: 137.37919 | T34: 139.11085 | U34: 137.96165 | V34: 137.71928 | W34: 139.24775 | X34: 140.55391 | Y34: 139.37074 | Z34: 138.92332 | AA34: 139.89626 | AB34: 140.91922 | AC34: 142.83789 | AD34: 143.66209
A35: LTV | B35: 1.9469756 | C35: 1.940031 | D35: 1.9871149 | E35: 2.0859933 | F35: 2.0792979 | G35: 2.1024128 | H35: 1.8205477 | I35: 1.8048166 | J35: 1.7006093 | K35: 1.5705129 | L35: 1.5917275 | M35: 1.6099823 | N35: 1.5700251 | O35: 1.5217243 | P35: 1.5389668 | Q35: 1.4816615 | R35: 1.4752199 | S35: 1.5151542 | T35: 1.4255162 | U35: 1.4294535 | V35: 1.5282342 | W35: 1.4897571 | X35: 1.4524382 | Y35: 1.4626335 | Z35: 1.4844701 | AA35: 1.4252153 | AB35: 1.4315317 | AC35: 1.4182828 | AD35: 1.4850732
A37: ENT | F37: 2020 Q1 | G37: 2020 Q2 | H37: 2020 Q3 | I37: 2020 Q4 | J37: 2021 Q1 | K37: 2021 Q2 | L37: 2021 Q3 | M37: 2021 Q4 | N37: 2022 Q1 | O37: 2022 Q2 | P37: 2022 Q3 | Q37: 2022 Q4 | R37: 2023 Q1 | S37: 2023 Q2 | T37: 2023 Q3 | U37: 2023 Q4 | V37: 2024 Q1 | W37: 2024 Q2 | X37: 2024 Q3 | Y37: 2024 Q4 | Z37: 2025 Q1 | AA37: 2025 Q2 | AB37: 2025 Q3 | AC37: 2025 Q4
A38: Contract Model Score | F38: 132.38307 | G38: 133.22864 | H38: 136.30166 | I38: 135.38242 | J38: 133.8357 | K38: 131.8749 | L38: 131.13569 | M38: 129.4723 | N38: 129.34473 | O38: 131.45349 | P38: 131.71553 | Q38: 131.25851 | R38: 132.73385 | S38: 133.4422 | T38: 133.76755 | U38: 135.31367 | V38: 136.17456 | W38: 136.8171 | X38: 136.69241 | Y38: 134.94875 | Z38: 134.57148 | AA38: 136.41792 | AB38: 137.0063 | AC38: 137.20721 | AD38: 139.55396
A39: Model Score | F39: 0 | G39: 0 | H39: 0 | I39: 0 | J39: 0 | K39: 0 | L39: 0 | M39: 0 | N39: 0 | O39: 0 | P39: 0 | Q39: 0 | R39: 0 | S39: 0 | T39: 0 | U39: 0 | V39: 0 | W39: 0 | X39: 0 | Y39: 0 | Z39: 0 | AA39: 0 | AB39: 0 | AC39: 0 | AD39: 0
A40: Gross Loss Adjustments (Dealer level, high PTI, etc.) | F40: -0.32633691 | G40: -0.24531305 | H40: -0.51478673 | I40: -1.7810736 | J40: -1.1663098 | K40: -1.3644154 | L40: -1.5978945 | M40: -1.4141434 | N40: -0.94809964 | O40: -1.1552447 | P40: -1.6752459 | Q40: -1.4947023 | R40: -1.8407645 | S40: -1.7181969 | T40: -1.5143745 | U40: -0.26488858 | V40: -0.33797291 | W40: -0.25306573 | X40: -0.34387396 | Y40: 0.25808423 | Z40: 0.1260553 | AA40: 0.68736219 | AB40: 0.6230396 | AC40: 1.6196659 | AD40: 1.5639228
A41: Recovery Adjustments excluding LTV (Mileage, vehicle type, etc.) | F41: -2.8893777 | G41: -2.6973233 | H41: -2.44732 | I41: -2.4631079 | J41: -2.4101873 | K41: -1.821715 | L41: -2.3608023 | M41: -2.2364697 | N41: -3.0902909 | O41: -3.435407 | P41: -4.1052264 | Q41: -4.2753205 | R41: -4.0226523 | S41: -3.8170759 | T41: -3.5395621 | U41: -2.9965075 | V41: -3.5568879 | W41: -3.2301753 | X41: -2.3887581 | Y41: 0.096156654 | Z41: 1.1548546 | AA41: 0.11886128 | AB41: 0.3810541 | AC41: 1.1634511 | AD41: 0.67722626
A42: LTV Adjustments | F42: 2.8893777 | G42: 2.6973233 | H42: 2.44732 | I42: 2.4631079 | J42: 2.4101873 | K42: 1.821715 | L42: 2.3608023 | M42: 2.2364697 | N42: 3.0902909 | O42: 3.435407 | P42: 4.1052264 | Q42: 4.2753205 | R42: 4.0226523 | S42: 3.8170759 | T42: 3.5395621 | U42: 2.9965075 | V42: 3.5568879 | W42: 3.2301753 | X42: 2.3887581 | Y42: -0.096156654 | Z42: -1.1548546 | AA42: -0.11886128 | AB42: -0.3810541 | AC42: -1.1634511 | AD42: -0.67722626
A43: RAGU Score | F43: 132.05673 | G43: 132.98333 | H43: 135.78687 | I43: 133.60135 | J43: 132.66939 | K43: 130.51048 | L43: 129.5378 | M43: 128.05816 | N43: 128.39663 | O43: 130.29824 | P43: 130.04029 | Q43: 129.76381 | R43: 130.89308 | S43: 131.724 | T43: 132.25318 | U43: 135.04878 | V43: 135.83659 | W43: 136.56403 | X43: 136.34854 | Y43: 135.20683 | Z43: 134.69754 | AA43: 137.10528 | AB43: 137.62934 | AC43: 138.82688 | AD43: 141.11789
A44: LTV | F44: 1.4714253 | G44: 1.4474478 | H44: 1.2669384 | I44: 1.3700476 | J44: 1.3586296 | K44: 1.2606972 | L44: 1.3395636 | M44: 1.3730102 | N44: 1.3911187 | O44: 1.3447795 | P44: 1.2919485 | Q44: 1.3472724 | R44: 1.375607 | S44: 1.3232001 | T44: 1.2558985 | U44: 1.3078145 | V44: 1.3169814 | W44: 1.2999196 | X44: 1.3145308 | Y44: 1.3452644 | Z44: 1.331159 | AA44: 1.3027503 | AB44: 1.3078482 | AC44: 1.3184408 | AD44: 1.3537993
A46: nonKMXENT | B46: 2016 | C46: 2017 | D46: 2018 | E46: 2019 | F46: 2020 Q1 | G46: 2020 Q2 | H46: 2020 Q3 | I46: 2020 Q4 | J46: 2021 Q1 | K46: 2021 Q2 | L46: 2021 Q3 | M46: 2021 Q4 | N46: 2022 Q1 | O46: 2022 Q2 | P46: 2022 Q3 | Q46: 2022 Q4 | R46: 2023 Q1 | S46: 2023 Q2 | T46: 2023 Q3 | U46: 2023 Q4 | V46: 2024 Q1 | W46: 2024 Q2 | X46: 2024 Q3 | Y46: 2024 Q4 | Z46: 2025 Q1 | AA46: 2025 Q2 | AB46: 2025 Q3 | AC46: 2025 Q4
A47: Contract Model Score | B47: 130.11008 | C47: 132.58762 | D47: 132.51897 | E47: 130.52533 | F47: 130.9115 | G47: 133.56818 | H47: 135.32872 | I47: 135.00452 | J47: 135.33466 | K47: 135.42705 | L47: 135.14249 | M47: 133.58237 | N47: 134.24542 | O47: 136.54105 | P47: 137.34925 | Q47: 138.63774 | R47: 139.45713 | S47: 138.75195 | T47: 138.87581 | U47: 138.31101 | V47: 137.53278 | W47: 138.76369 | X47: 140.0747 | Y47: 138.61957 | Z47: 138.13778 | AA47: 139.2205 | AB47: 139.61004 | AC47: 140.56262 | AD47: 141.89919
A48: Model Score | B48: 0.15460624 | C48: 0.095483442 | D48: 0.031115149 | E48: 0.0060876943 | F48: -0.0029307051 | G48: 0.0011452093 | H48: 0.0020306833 | I48: 0.0068054691 | J48: 0.0002510195 | K48: 3.5664492e-05 | L48: 0.0014876761 | M48: -0.0004078232 | N48: -0.00073390995 | O48: -0.0028985615 | P48: 0.0010086782 | Q48: 0.0061572198 | R48: -0.010726355 | S48: 0.015549725 | T48: -0.0066097194 | U48: 0.0072554823 | V48: 1.9547811e-05 | W48: 0.0018862827 | X48: -0.0008199157 | Y48: -0.0073169674 | Z48: -0.00025699108 | AA48: -0.0079701789 | AB48: -0.0054600031 | AC48: -0.0078103429 | AD48: -0.0098685329
A49: Gross Loss Adjustments (Dealer level, high PTI, etc.) | B49: 0.25888132 | C49: 0.55879279 | D49: 0.56380279 | E49: 0.29260346 | F49: -0.34536813 | G49: -0.16919144 | H49: -0.27250734 | I49: -0.2097614 | J49: 0.4826877 | K49: 0.36739133 | L49: 0.15946083 | M49: -0.21753361 | N49: -0.37477073 | O49: 0.14896658 | P49: 0.14075601 | Q49: 0.25217995 | R49: 0.50637845 | S49: 0.33808643 | T49: 0.51008801 | U49: 0.32674642 | V49: 0.43740081 | W49: 0.91186545 | X49: 1.1756041 | Y49: 1.2884607 | Z49: 1.7456869 | AA49: 1.730701 | AB49: 2.333011 | AC49: 2.6380327 | AD49: 1.9156188
A50: Recovery Adjustments excluding LTV (Mileage, vehicle type, etc.) | B50: -0.46216339 | C50: 0.29559717 | D50: 0.2606792 | E50: 0.060287224 | F50: -0.12551234 | G50: -0.33467937 | H50: -0.10792926 | I50: 0.39946824 | J50: 0.15508865 | K50: 0.10021524 | L50: -0.15396596 | M50: -0.63306938 | N50: -1.2209973 | O50: -1.3755239 | P50: -1.4529714 | Q50: -1.2058995 | R50: -1.2215231 | S50: -1.3254937 | T50: -1.3944898 | U50: -1.3482773 | V50: -1.5654854 | W50: -1.0736328 | X50: -0.63007452 | Y50: 0.33743461 | Z50: 0.21584491 | AA50: 0.36975345 | AB50: 0.85958685 | AC50: 1.5584764 | AD50: 1.294369
A51: LTV Adjustments | B51: 0.46216339 | C51: -0.29559717 | D51: -0.2606792 | E51: -0.060287224 | F51: 0.12551234 | G51: 0.33467937 | H51: 0.10792926 | I51: -0.39946824 | J51: -0.15508865 | K51: -0.10021524 | L51: 0.15396596 | M51: 0.63306938 | N51: 1.2209973 | O51: 1.3755239 | P51: 1.4529714 | Q51: 1.2058995 | R51: 1.2215231 | S51: 1.3254937 | T51: 1.3944898 | U51: 1.3482773 | V51: 1.5654854 | W51: 1.0736328 | X51: 0.63007452 | Y51: -0.33743461 | Z51: -0.21584491 | AA51: -0.36975345 | AB51: -0.85958685 | AC51: -1.5584764 | AD51: -1.294369
A52: RAGU Score | B52: 130.52357 | C52: 133.2419 | D52: 133.11388 | E52: 130.82402 | F52: 130.56321 | G52: 133.40013 | H52: 135.05824 | I52: 134.80156 | J52: 135.8176 | K52: 135.79448 | L52: 135.30344 | M52: 133.36443 | N52: 133.86992 | O52: 136.68712 | P52: 137.49101 | Q52: 138.89607 | R52: 139.95278 | S52: 139.10559 | T52: 139.37929 | U52: 138.64502 | V52: 137.9702 | W52: 139.67744 | X52: 141.24948 | Y52: 139.90071 | Z52: 139.88321 | AA52: 140.94323 | AB52: 141.93759 | AC52: 143.19285 | AD52: 143.80494
A53: LTV | B53: 1.9870302 | C53: 1.9346383 | D53: 1.9518241 | E53: 1.9473675 | F53: 1.9012907 | G53: 1.9285203 | H53: 1.7379662 | I53: 1.8033417 | J53: 1.6728073 | K53: 1.4961242 | L53: 1.55443 | M53: 1.6040944 | N53: 1.5814246 | O53: 1.5860567 | P53: 1.6132315 | Q53: 1.6124594 | R53: 1.6458771 | S53: 1.5435388 | T53: 1.4833595 | U53: 1.4779453 | V53: 1.526512 | W53: 1.4963125 | X53: 1.4786445 | Y53: 1.4832932 | Z53: 1.4921085 | AA53: 1.4462029 | AB53: 1.4474649 | AC53: 1.437394 | AD53: 1.4819849
A55: KMX | B55: 2016 | C55: 2017 | D55: 2018 | E55: 2019 | F55: 2020 Q1 | G55: 2020 Q2 | H55: 2020 Q3 | I55: 2020 Q4 | J55: 2021 Q1 | K55: 2021 Q2 | L55: 2021 Q3 | M55: 2021 Q4 | N55: 2022 Q1 | O55: 2022 Q2 | P55: 2022 Q3 | Q55: 2022 Q4 | R55: 2023 Q1 | S55: 2023 Q2 | T55: 2023 Q3 | U55: 2023 Q4 | V55: 2024 Q1 | W55: 2024 Q2 | X55: 2024 Q3 | Y55: 2024 Q4 | Z55: 2025 Q1 | AA55: 2025 Q2 | AB55: 2025 Q3 | AC55: 2025 Q4
A56: Contract Model Score | B56: 136.56461 | C56: 139.10048 | D56: 137.77978 | E56: 136.87786 | F56: 135.86332 | G56: 138.37204 | H56: 138.7895 | I56: 136.9589 | J56: 135.46433 | K56: 135.73801 | L56: 134.50372 | M56: 133.19297 | N56: 133.26474 | O56: 134.70115 | P56: 136.05827 | Q56: 138.3337 | R56: 140.09672 | S56: 140.65864 | T56: 140.50459 | U56: 140.56078 | V56: 139.56825 | W56: 140.43212 | X56: 139.88511 | Y56: 139.76782 | Z56: 139.70877 | AA56: 139.86672 | AB56: 139.91791 | AC56: 140.94205 | AD56: 141.78676
A57: Model Score | B57: 0 | C57: 0 | D57: 0 | E57: 0 | F57: 0 | G57: 0 | H57: 0 | I57: 0 | J57: 0 | K57: 0 | L57: 0 | M57: 0 | N57: 0 | O57: 0 | P57: 0 | Q57: 0 | R57: 0 | S57: 0 | T57: 0 | U57: 0 | V57: 0 | W57: 0 | X57: 0 | Y57: 0 | Z57: 0 | AA57: 0 | AB57: 0 | AC57: 0 | AD57: 0
A58: Gross Loss Adjustments (Dealer level, high PTI, etc.) | B58: 4.6948977 | C58: 4.6241736 | D58: 4.4679388 | E58: 4.4875446 | F58: 4.4149785 | G58: 4.4449193 | H58: 4.2599067 | I58: 3.9751836 | J58: 3.816408 | K58: 3.5804747 | L58: 3.4558858 | M58: 3.1688959 | N58: 2.9615707 | O58: 2.8082243 | P58: 2.6116439 | Q58: 2.7411801 | R58: 2.8563006 | S58: 2.997515 | T58: 2.9935717 | U58: 3.2679493 | V58: 3.7323346 | W58: 4.2936449 | X58: 4.1119242 | Y58: 3.9276019 | Z58: 2.0974563 | AA58: 2.4756026 | AB58: 2.131958 | AC58: 2.0035602 | AD58: 2.7586085
A59: Recovery Adjustments excluding LTV (Mileage, vehicle type, etc.) | B59: -1.5913845 | C59: -2.6604678 | D59: -2.5961763 | E59: -2.6409276 | F59: -3.097567 | G59: -2.834124 | H59: -3.1364393 | I59: -2.8396896 | J59: -2.6834108 | K59: -2.4553768 | L59: -1.7564129 | M59: -2.4198337 | N59: -2.6255544 | O59: -3.116632 | P59: -3.6031679 | Q59: -3.7513148 | R59: -4.1776837 | S59: -4.0828996 | T59: -4.0688291 | U59: -3.2955658 | V59: -3.5170506 | W59: -3.3558261 | X59: -3.8617872 | Y59: -3.9820937 | Z59: -4.1579065 | AA59: -3.6143435 | AB59: -3.1649618 | AC59: -2.7544481 | AD59: -2.898265
A60: LTV Adjustments | B60: 1.5913845 | C60: 2.6604678 | D60: 2.5961763 | E60: 2.6409276 | F60: 3.097567 | G60: 2.834124 | H60: 3.1364393 | I60: 2.8396896 | J60: 2.6834108 | K60: 2.4553768 | L60: 1.7564129 | M60: 2.4198337 | N60: 2.6255544 | O60: 3.116632 | P60: 3.6031679 | Q60: 3.7513148 | R60: 4.1776837 | S60: 4.0828996 | T60: 4.0688291 | U60: 3.2955658 | V60: 3.5170506 | W60: 3.3558261 | X60: 3.8617872 | Y60: 3.9820937 | Z60: 4.1579065 | AA60: 3.6143435 | AB60: 3.1649618 | AC60: 2.7544481 | AD60: 2.898265
A61: RAGU Score | B61: 141.25951 | C61: 143.72465 | D61: 142.24772 | E61: 141.3654 | F61: 140.2783 | G61: 142.81696 | H61: 143.0494 | I61: 140.93409 | J61: 139.28074 | K61: 139.31848 | L61: 137.95961 | M61: 136.36187 | N61: 136.22631 | O61: 137.50937 | P61: 138.66991 | Q61: 141.07488 | R61: 142.95302 | S61: 143.65615 | T61: 143.49817 | U61: 143.82873 | V61: 143.30058 | W61: 144.72576 | X61: 143.99704 | Y61: 143.69542 | Z61: 141.80622 | AA61: 142.34233 | AB61: 142.04987 | AC61: 142.94561 | AD61: 144.54537
A62: LTV | B62: 1.586932 | C62: 1.5720151 | D62: 1.5856332 | E62: 1.6092026 | F62: 1.7020431 | G62: 1.7371846 | H62: 1.5806217 | I62: 1.7202884 | J62: 1.5765842 | K62: 1.4305316 | L62: 1.4805214 | M62: 1.4915802 | N62: 1.6130355 | O62: 1.5540459 | P62: 1.6280059 | Q62: 1.7468276 | R62: 1.7705954 | S62: 1.6782516 | T62: 1.8466432 | U62: 1.9539518 | V62: 1.8857882 | W62: 1.6503232 | X62: 1.6909127 | Y62: 1.6869388 | Z62: 1.6353697 | AA62: 1.6103106 | AB62: 1.6219656 | AC62: 1.6048692 | AD62: 1.5672015
A64: POS | B64: 2016 | C64: 2017 | D64: 2018 | E64: 2019 | F64: 2020 Q1 | G64: 2020 Q2 | H64: 2020 Q3 | I64: 2020 Q4 | J64: 2021 Q1 | K64: 2021 Q2 | L64: 2021 Q3 | M64: 2021 Q4 | N64: 2022 Q1 | O64: 2022 Q2 | P64: 2022 Q3 | Q64: 2022 Q4 | R64: 2023 Q1 | S64: 2023 Q2 | T64: 2023 Q3 | U64: 2023 Q4 | V64: 2024 Q1 | W64: 2024 Q2 | X64: 2024 Q3 | Y64: 2024 Q4 | Z64: 2025 Q1 | AA64: 2025 Q2 | AB64: 2025 Q3 | AC64: 2025 Q4
A65: Contract Model Score | B65: 134.00922 | C65: 137.09024 | D65: 136.17908 | E65: 135.22818 | F65: 134.22836 | G65: 136.51598 | H65: 137.70277 | I65: 136.32022 | J65: 135.22491 | K65: 134.98869 | L65: 134.18994 | M65: 132.81075 | N65: 133.03763 | O65: 134.82195 | P65: 135.90569 | Q65: 137.14226 | R65: 138.55531 | S65: 138.99052 | T65: 139.07412 | U65: 138.9461 | V65: 138.34968 | W65: 139.22436 | X65: 139.53563 | Y65: 138.6092 | Z65: 138.29936 | AA65: 139.10189 | AB65: 139.41596 | AC65: 140.32 | AD65: 141.60079
A66: Model Score | B66: -2.3911778 | C66: -0.81242854 | D66: -0.35223323 | E66: -0.54817537 | F66: -0.49563473 | G66: -0.43749234 | H66: -0.24180603 | I66: -0.10288451 | J66: -0.00578979 | K66: 0.0515173 | L66: 0.057763043 | M66: 0.063759854 | N66: 0.015518968 | O66: -0.0010698586 | P66: -0.00087217979 | Q66: 0.006990934 | R66: 0.13977384 | S66: 0.22978382 | T66: -0.63837415 | U66: -0.5046117 | V66: 0.0040064067 | W66: 0.0019423191 | X66: -0.0011499063 | Y66: -0.0032891709 | Z66: -0.0010866271 | AA66: -0.011151167 | AB66: -0.0091706184 | AC66: -0.0095421664 | AD66: 0.00066989909
A67: Gross Loss Adjustments (Dealer level, high PTI, etc.) | B67: 1.21183 | C67: 2.8360282 | D67: 3.0100166 | E67: 3.0362527 | F67: 2.2326705 | G67: 2.2712617 | H67: 2.3657796 | I67: 2.104076 | J67: 2.2933944 | K67: 1.7855568 | L67: 1.7759696 | M67: 1.5387835 | N67: 1.1948447 | O67: 1.6201295 | P67: 1.4220746 | Q67: 1.4589458 | R67: 1.6867754 | S67: 1.8124516 | T67: 1.1414238 | U67: 1.2040286 | V67: 1.9770035 | W67: 2.2258244 | X67: 2.4187403 | Y67: 2.3576272 | Z67: 1.6547396 | AA67: 1.8976985 | AB67: 2.0154811 | AC67: 2.1989102 | AD67: 2.3859438
A68: Recovery Adjustments excluding LTV (Mileage, vehicle type, etc.) | B68: -0.70437547 | C68: -1.3599369 | D68: -1.5292209 | E68: -1.72072 | F68: -2.0015567 | G68: -1.9420602 | H68: -2.1238196 | I68: -1.8692201 | J68: -1.9013709 | K68: -1.5383872 | L68: -1.3495792 | M68: -1.8257217 | N68: -2.1853629 | O68: -2.6797192 | P68: -3.0662265 | Q68: -3.2984233 | R68: -3.7293955 | S68: -3.5671447 | T68: -3.0485808 | U68: -2.3651032 | V68: -2.8399786 | W68: -2.3598384 | X68: -2.4512272 | Y68: -1.6963871 | Z68: -1.6206511 | AA68: -1.3568727 | AB68: -1.0545155 | AC68: -0.58399286 | AD68: -1.2732508
A69: LTV Adjustments | B69: 0.70437547 | C69: 1.3599369 | D69: 1.5292209 | E69: 1.72072 | F69: 2.0015567 | G69: 1.9420602 | H69: 2.1238196 | I69: 1.8692201 | J69: 1.9013709 | K69: 1.5383872 | L69: 1.3495792 | M69: 1.8257217 | N69: 2.1853629 | O69: 2.6797192 | P69: 3.0662265 | Q69: 3.2984233 | R69: 3.7293955 | S69: 3.5671447 | T69: 3.0485808 | U69: 2.3651032 | V69: 2.8399786 | W69: 2.3598384 | X69: 2.4512272 | Y69: 1.6963871 | Z69: 1.6206511 | AA69: 1.3568727 | AB69: 1.0545155 | AC69: 0.58399286 | AD69: 1.2732508
A70: RAGU Score | B70: 132.82987 | C70: 139.11384 | D70: 138.83687 | E70: 137.71626 | F70: 135.9654 | G70: 138.34975 | H70: 139.82674 | I70: 138.32141 | J70: 137.51251 | K70: 136.82576 | L70: 136.02367 | M70: 134.4133 | N70: 134.24799 | O70: 136.44101 | P70: 137.32689 | Q70: 138.6082 | R70: 140.38186 | S70: 141.03275 | T70: 139.57717 | U70: 139.64552 | V70: 140.33069 | W70: 141.45213 | X70: 141.95322 | Y70: 140.96353 | Z70: 139.95301 | AA70: 140.98843 | AB70: 141.42227 | AC70: 142.50936 | AD70: 143.9874
A71: LTV | B71: 1.9010808 | C71: 1.7315138 | D71: 1.7223799 | E71: 1.7236382 | F71: 1.7518449 | G71: 1.7698283 | H71: 1.5978857 | I71: 1.7029817 | J71: 1.5736361 | K71: 1.4252426 | L71: 1.4841463 | M71: 1.5134914 | N71: 1.56965 | O71: 1.5382522 | P71: 1.5843331 | Q71: 1.647394 | R71: 1.6826199 | S71: 1.6003094 | T71: 1.5911868 | U71: 1.604031 | V71: 1.6758802 | W71: 1.5366705 | X71: 1.5613443 | Y71: 1.5571499 | Z71: 1.5321425 | AA71: 1.4953428 | AB71: 1.5093694 | AC71: 1.503249 | AD71: 1.5205455

Sheet Data Tables (M)
A1: AN | B1: 2016 | C1: 2017 | D1: 2018 | E1: 2019 | F1: 2020 M01 | G1: 2020 M02 | H1: 2020 M03 | I1: 2020 M04 | J1: 2020 M05 | K1: 2020 M06 | L1: 2020 M07 | M1: 2020 M08 | N1: 2020 M09 | O1: 2020 M10 | P1: 2020 M11 | Q1: 2020 M12 | R1: 2021 M01 | S1: 2021 M02 | T1: 2021 M03 | U1: 2021 M04 | V1: 2021 M05 | W1: 2021 M06 | X1: 2021 M07 | Y1: 2021 M08 | Z1: 2021 M09 | AA1: 2021 M10 | AB1: 2021 M11 | AC1: 2021 M12 | AD1: 2022 M01 | AE1: 2022 M02 | AF1: 2022 M03 | AG1: 2022 M04 | AH1: 2022 M05 | AI1: 2022 M06 | AJ1: 2022 M07 | AK1: 2022 M08 | AL1: 2022 M09 | AM1: 2022 M10 | AN1: 2022 M11 | AO1: 2022 M12 | AP1: 2023 M01 | AQ1: 2023 M02 | AR1: 2023 M03 | AS1: 2023 M04 | AT1: 2023 M05 | AU1: 2023 M06 | AV1: 2023 M07 | AW1: 2023 M08 | AX1: 2023 M09 | AY1: 2023 M10 | AZ1: 2023 M11 | BA1: 2023 M12 | BB1: 2024 M01 | BC1: 2024 M02 | BD1: 2024 M03 | BE1: 2024 M04 | BF1: 2024 M05 | BG1: 2024 M06 | BH1: 2024 M07 | BI1: 2024 M08 | BJ1: 2024 M09 | BK1: 2024 M10 | BL1: 2024 M11 | BM1: 2024 M12 | BN1: 2025 M01 | BO1: 2025 M02 | BP1: 2025 M03 | BQ1: 2025 M04 | BR1: 2025 M05 | BS1: 2025 M06 | BT1: 2025 M07 | BU1: 2025 M08 | BV1: 2025 M09 | BW1: 2025 M10 | BX1: 2025 M11 | BY1: 2025 M12 | BZ1: 2026 M01
A2: Contract Model Score | B2: 130.07638 | C2: 132.82981 | D2: 132.99275 | E2: 132.10946 | F2: 132.25849 | G2: 131.7487 | H2: 131.54256 | I2: 132.18971 | J2: 133.74885 | K2: 134.65103 | L2: 134.80159 | M2: 135.32143 | N2: 135.83703 | O2: 135.63732 | P2: 136.60482 | Q2: 135.25698 | R2: 135.3746 | S2: 135.08197 | T2: 134.04131 | U2: 134.85769 | V2: 135.429 | W2: 135.23156 | X2: 135.14534 | Y2: 136.06332 | Z2: 134.88069 | AA2: 134.92486 | AB2: 133.43768 | AC2: 134.76745 | AD2: 134.0616 | AE2: 133.46247 | AF2: 134.42836 | AG2: 135.32861 | AH2: 136.27415 | AI2: 136.14209 | AJ2: 136.0539 | AK2: 136.18039 | AL2: 136.20134 | AM2: 136.40054 | AN2: 137.34655 | AO2: 136.56024 | AP2: 137.35433 | AQ2: 136.77652 | AR2: 136.20403 | AS2: 137.32635 | AT2: 136.6899 | AU2: 136.75897 | AV2: 135.57234 | AW2: 136.72241 | AX2: 136.99429 | AY2: 137.19306 | AZ2: 136.53374 | BA2: 136.58082 | BB2: 136.14985 | BC2: 137.03472 | BD2: 137.23467 | BE2: 137.10824 | BF2: 137.80106 | BG2: 138.46466 | BH2: 138.07105 | BI2: 137.16197 | BJ2: 136.31058 | BK2: 136.80042 | BL2: 136.83707 | BM2: 137.09434 | BN2: 136.69472 | BO2: 137.57439 | BP2: 138.31007 | BQ2: 138.27075 | BR2: 138.46662 | BS2: 138.34761 | BT2: 138.86903 | BU2: 138.81179 | BV2: 138.98924 | BW2: 140.30771 | BX2: 140.4025 | BY2: 137.341 | BZ2: 136.64692 | CA2: 140.81499
A3: Model Score | B3: 0 | C3: 0 | D3: 0 | E3: 0 | F3: 0 | G3: 0 | H3: 0 | I3: 0 | J3: 0 | K3: 0 | L3: 0 | M3: 0 | N3: 0 | O3: 0 | P3: 0 | Q3: 0 | R3: 0 | S3: 0 | T3: 0 | U3: 0 | V3: 0 | W3: 0 | X3: 0 | Y3: 0 | Z3: 0 | AA3: 0 | AB3: 0 | AC3: 0 | AD3: 0 | AE3: 0 | AF3: 0 | AG3: 0 | AH3: 0 | AI3: 0 | AJ3: 0 | AK3: 0 | AL3: 0 | AM3: 0 | AN3: 0 | AO3: 0 | AP3: 0 | AQ3: 0 | AR3: 0 | AS3: 0 | AT3: 0 | AU3: 0 | AV3: 0 | AW3: 0 | AX3: 0 | AY3: 0 | AZ3: 0 | BA3: 0 | BB3: 0 | BC3: 0 | BD3: 0 | BE3: 0 | BF3: 0 | BG3: 0 | BH3: 0 | BI3: 0 | BJ3: 0 | BK3: 0 | BL3: 0 | BM3: 0 | BN3: 0 | BO3: 0 | BP3: 0 | BQ3: 0 | BR3: 0 | BS3: 0 | BT3: 0 | BU3: 0 | BV3: 0 | BW3: 0 | BX3: 0
A4: Gross Loss Adjustments (Dealer level, high PTI, etc.) | B4: 0.66321459 | C4: 1.0385795 | D4: 1.1380113 | E4: 1.1999234 | F4: 1.363498 | G4: 1.4890326 | H4: 1.4551035 | I4: 0.95163864 | J4: 1.4384026 | K4: 1.4548572 | L4: 0.6330598 | M4: 0.57072414 | N4: 0.63123428 | O4: 1.2672486 | P4: 1.2015072 | Q4: 0.78183178 | R4: 1.202423 | S4: 1.2781026 | T4: 1.4387594 | U4: 1.6599887 | V4: 1.2247999 | W4: 1.0389789 | X4: 1.0486893 | Y4: 1.3860844 | Z4: 1.5658651 | AA4: 1.5637281 | AB4: 0.9553726 | AC4: 1.1725708 | AD4: 1.3500946 | AE4: 1.5398787 | AF4: 1.8252304 | AG4: 1.8290847 | AH4: 2.5043044 | AI4: 0.8989561 | AJ4: 0.91030944 | AK4: -0.33803067 | AL4: 1.6979652 | AM4: -1.812468 | AN4: 1.5911042 | AO4: -0.85166303 | AP4: 1.47558 | AQ4: 1.1167384 | AR4: 0.08872574 | AS4: 3.1185061 | AT4: -1.4776426 | AU4: -1.2971092 | AV4: -1.8509514 | AW4: 1.1530122 | AX4: 4.3341447 | AY4: 1.8896377 | AZ4: 0.98233763 | BA4: 1.0913693 | BB4: 0.90847572 | BC4: 1.1475105 | BD4: 1.4501609 | BE4: 1.5039823 | BF4: 1.5817047 | BG4: 0.93728365 | BH4: 0.97573692 | BI4: 0.94632961 | BJ4: 1.1939329 | BK4: 0.98178419 | BL4: 1.7335169 | BM4: 1.5894201 | BN4: 0.7650227 | BO4: 1.9688479 | BP4: 1.4714886 | BQ4: 2.7699838 | BR4: 2.7445103 | BS4: 2.9079804 | BT4: 3.1276505 | BU4: 3.0665305 | BV4: 3.0046783 | BW4: 3.3612264 | BX4: 1.6742972
A5: Recovery Adjustments excluding LTV (Mileage, vehicle type, etc.) | B5: -0.43387446 | C5: 0.25208665 | D5: 0.23835097 | E5: 0.083969258 | F5: -0.16900385 | G5: -0.066268575 | H5: -0.37281442 | I5: -0.55892049 | J5: -0.42429522 | K5: -0.16532972 | L5: -0.39771018 | M5: 0.023328623 | N5: 0.17751563 | O5: 0.24090843 | P5: -0.073562787 | Q5: 0.89192764 | R5: 1.0585003 | S5: -0.20632461 | T5: -0.29325404 | U5: -0.019292746 | V5: 0.29077176 | W5: 0.17819197 | X5: -0.28841322 | Y5: -0.47832537 | Z5: -0.36451377 | AA5: -0.3124721 | AB5: -1.5628734 | AC5: -1.1041396 | AD5: 0.242783 | AE5: -0.66124799 | AF5: -1.2296851 | AG5: -2.271026 | AH5: -0.086659548 | AI5: 0.55523182 | AJ5: -2.6532631 | AK5: -0.85788277 | AL5: -3.2618726 | AM5: 4.5268125 | AN5: 0.13955307 | AO5: -0.68617029 | AP5: -2.2350777 | AQ5: -3.1453828 | AR5: -1.3145268 | AS5: -5.3223482 | AT5: -0.98840288 | AU5: -2.8654298 | AV5: -0.91046055 | AW5: -2.8747319 | AX5: -4.1975832 | AY5: -0.85144109 | AZ5: -2.1919821 | BA5: -0.54056974 | BB5: -1.7836194 | BC5: -2.0063219 | BD5: -1.2370276 | BE5: -0.20553532 | BF5: -0.11813114 | BG5: -1.094554 | BH5: -1.1770372 | BI5: -0.33003849 | BJ5: -0.13258979 | BK5: 1.9015271 | BL5: 1.5940937 | BM5: 1.1338343 | BN5: -0.19350888 | BO5: 0.17929852 | BP5: 0.46934362 | BQ5: 1.3796446 | BR5: 0.080108917 | BS5: 0.18026339 | BT5: 1.7756142 | BU5: 1.7362769 | BV5: 0.16131662 | BW5: 0.23263656 | BX5: 0.89607298
A6: LTV Adjustments | B6: 0.43387446 | C6: -0.25208665 | D6: -0.23835097 | E6: -0.083969258 | F6: 0.16900385 | G6: 0.066268575 | H6: 0.37281442 | I6: 0.55892049 | J6: 0.42429522 | K6: 0.16532972 | L6: 0.39771018 | M6: -0.023328623 | N6: -0.17751563 | O6: -0.24090843 | P6: 0.073562787 | Q6: -0.89192764 | R6: -1.0585003 | S6: 0.20632461 | T6: 0.29325404 | U6: 0.019292746 | V6: -0.29077176 | W6: -0.17819197 | X6: 0.28841322 | Y6: 0.47832537 | Z6: 0.36451377 | AA6: 0.3124721 | AB6: 1.5628734 | AC6: 1.1041396 | AD6: -0.242783 | AE6: 0.66124799 | AF6: 1.2296851 | AG6: 2.271026 | AH6: 0.086659548 | AI6: -0.55523182 | AJ6: 2.6532631 | AK6: 0.85788277 | AL6: 3.2618726 | AM6: -4.5268125 | AN6: -0.13955307 | AO6: 0.68617029 | AP6: 2.2350777 | AQ6: 3.1453828 | AR6: 1.3145268 | AS6: 5.3223482 | AT6: 0.98840288 | AU6: 2.8654298 | AV6: 0.91046055 | AW6: 2.8747319 | AX6: 4.1975832 | AY6: 0.85144109 | AZ6: 2.1919821 | BA6: 0.54056974 | BB6: 1.7836194 | BC6: 2.0063219 | BD6: 1.2370276 | BE6: 0.20553532 | BF6: 0.11813114 | BG6: 1.094554 | BH6: 1.1770372 | BI6: 0.33003849 | BJ6: 0.13258979 | BK6: -1.9015271 | BL6: -1.5940937 | BM6: -1.1338343 | BN6: 0.19350888 | BO6: -0.17929852 | BP6: -0.46934362 | BQ6: -1.3796446 | BR6: -0.080108917 | BS6: -0.18026339 | BT6: -1.7756142 | BU6: -1.7362769 | BV6: -0.16131662 | BW6: -0.23263656 | BX6: -0.89607298
A7: RAGU Score | B7: 130.73959 | C7: 133.86839 | D7: 134.13076 | E7: 133.30939 | F7: 133.62199 | G7: 133.23774 | H7: 132.99766 | I7: 133.14135 | J7: 135.18725 | K7: 136.10589 | L7: 135.43465 | M7: 135.89215 | N7: 136.46827 | O7: 136.90457 | P7: 137.80633 | Q7: 136.03881 | R7: 136.57702 | S7: 136.36007 | T7: 135.48007 | U7: 136.51767 | V7: 136.6538 | W7: 136.27053 | X7: 136.19403 | Y7: 137.44941 | Z7: 136.44655 | AA7: 136.48859 | AB7: 134.39305 | AC7: 135.94002 | AD7: 135.4117 | AE7: 135.00235 | AF7: 136.25359 | AG7: 137.15769 | AH7: 138.77845 | AI7: 137.04105 | AJ7: 136.96421 | AK7: 135.84236 | AL7: 137.89931 | AM7: 134.58807 | AN7: 138.93766 | AO7: 135.70858 | AP7: 138.82991 | AQ7: 137.89326 | AR7: 136.29276 | AS7: 140.44486 | AT7: 135.21226 | AU7: 135.46186 | AV7: 133.72139 | AW7: 137.87542 | AX7: 141.32843 | AY7: 139.0827 | AZ7: 137.51608 | BA7: 137.67219 | BB7: 137.05833 | BC7: 138.18223 | BD7: 138.68483 | BE7: 138.61222 | BF7: 139.38276 | BG7: 139.40194 | BH7: 139.04679 | BI7: 138.1083 | BJ7: 137.50451 | BK7: 137.78221 | BL7: 138.57059 | BM7: 138.68376 | BN7: 137.45974 | BO7: 139.54324 | BP7: 139.78155 | BQ7: 141.04074 | BR7: 141.21113 | BS7: 141.25559 | BT7: 141.99669 | BU7: 141.87833 | BV7: 141.99392 | BW7: 143.66893 | BX7: 142.07679
A8: LTV | B8: 1.9087244 | C8: 1.902091 | D8: 1.9108901 | E8: 1.9482277 | F8: 1.9743248 | G8: 1.9082235 | H8: 1.856177 | I8: 2.0421645 | J8: 1.9635875 | K8: 1.8734483 | L8: 1.7480386 | M8: 1.6307556 | N8: 1.6161995 | O8: 1.627103 | P8: 1.6162566 | Q8: 1.7297385 | R8: 1.7569392 | S8: 1.7395328 | T8: 1.6369949 | U8: 1.5676004 | V8: 1.4987905 | W8: 1.465296 | X8: 1.5741537 | Y8: 1.5370213 | Z8: 1.6529071 | AA8: 1.573601 | AB8: 1.5776981 | AC8: 1.5967355 | AD8: 1.6223278 | AE8: 1.5998584 | AF8: 1.624587 | AG8: 1.6364888 | AH8: 2.0755362 | AI8: 2.2403166 | AJ8: 1.676993 | AK8: 1.7609987 | AL8: 1.8527636 | AM8: 1.5283483 | AN8: 1.9048561 | AO8: 2.0039267 | AP8: 1.8622775 | AQ8: 1.9348544 | AR8: 1.6267681 | AS8: 5.1897588 | AT8: 2.3546434 | AU8: 1.5797646 | AV8: 1.8767694 | AW8: 1.6518024 | AX8: 1.8714843 | AY8: 1.9250555 | AZ8: 1.8325892 | BA8: 1.7607486 | BB8: 1.697528 | BC8: 1.7896662 | BD8: 1.6368387 | BE8: 1.5935566 | BF8: 1.5326083 | BG8: 1.7243401 | BH8: 1.5915305 | BI8: 1.6797055 | BJ8: 1.6056774 | BK8: 1.6168399 | BL8: 1.5025317 | BM8: 1.5982709 | BN8: 1.6194769 | BO8: 1.5877404 | BP8: 1.5365227 | BQ8: 1.5535723 | BR8: 1.5932123 | BS8: 1.5539282 | BT8: 1.5224133 | BU8: 1.5716474 | BV8: 1.6168236 | BW8: 1.5274442 | BX8: 1.5637771
A10: FLD | B10: 2016 | C10: 2017 | D10: 2018 | E10: 2019 | F10: 2020 M01 | G10: 2020 M02 | H10: 2020 M03 | I10: 2020 M04 | J10: 2020 M05 | K10: 2020 M06 | L10: 2020 M07 | M10: 2020 M08 | N10: 2020 M09 | O10: 2020 M10 | P10: 2020 M11 | Q10: 2020 M12 | R10: 2021 M01 | S10: 2021 M02 | T10: 2021 M03 | U10: 2021 M04 | V10: 2021 M05 | W10: 2021 M06 | X10: 2021 M07 | Y10: 2021 M08 | Z10: 2021 M09 | AA10: 2021 M10 | AB10: 2021 M11 | AC10: 2021 M12 | AD10: 2022 M01 | AE10: 2022 M02 | AF10: 2022 M03 | AG10: 2022 M04 | AH10: 2022 M05 | AI10: 2022 M06 | AJ10: 2022 M07 | AK10: 2022 M08 | AL10: 2022 M09 | AM10: 2022 M10 | AN10: 2022 M11 | AO10: 2022 M12 | AP10: 2023 M01 | AQ10: 2023 M02 | AR10: 2023 M03 | AS10: 2023 M04 | AT10: 2023 M05 | AU10: 2023 M06 | AV10: 2023 M07 | AW10: 2023 M08 | AX10: 2023 M09 | AY10: 2023 M10 | AZ10: 2023 M11 | BA10: 2023 M12 | BB10: 2024 M01 | BC10: 2024 M02 | BD10: 2024 M03 | BE10: 2024 M04 | BF10: 2024 M05 | BG10: 2024 M06 | BH10: 2024 M07 | BI10: 2024 M08 | BJ10: 2024 M09 | BK10: 2024 M10 | BL10: 2024 M11 | BM10: 2024 M12 | BN10: 2025 M01 | BO10: 2025 M02 | BP10: 2025 M03 | BQ10: 2025 M04 | BR10: 2025 M05 | BS10: 2025 M06 | BT10: 2025 M07 | BU10: 2025 M08 | BV10: 2025 M09 | BW10: 2025 M10 | BX10: 2025 M11 | BY10: 2025 M12 | BZ10: 2026 M01
A11: Contract Model Score | F11: 131.69826 | G11: 133.05465 | H11: 131.44449 | I11: 132.48641 | J11: 135.78589 | K11: 137.67459 | L11: 137.63211 | M11: 137.41028 | N11: 138.50084 | O11: 138.38307 | P11: 141.10563 | Q11: 142.82581 | R11: 139.61141 | S11: 137.15928 | T11: 135.9438 | U11: 136.43445 | V11: 136.59572 | W11: 135.44515 | X11: 134.80733 | Y11: 136.84616 | Z11: 135.30382 | AA11: 135.50762 | AB11: 134.08635 | AC11: 134.22879 | AD11: 134.31941 | AE11: 133.67712 | AF11: 134.40763 | AG11: 135.82593 | AH11: 135.4639 | AI11: 136.28085 | AJ11: 136.94589 | AK11: 136.9564 | AL11: 136.99007 | AM11: 136.88364 | AN11: 139.40723 | AO11: 140.81079 | AP11: 141.68261 | AQ11: 142.38723 | AR11: 139.72135 | AS11: 139.3661 | AT11: 137.91442 | AU11: 137.55925 | AV11: 137.86885 | AW11: 139.26533 | AX11: 139.00234 | AY11: 138.84908 | AZ11: 138.16068 | BA11: 138.56896 | BB11: 138.04076 | BC11: 138.62568 | BD11: 139.01469 | BE11: 140.94279 | BF11: 141.91136 | BG11: 140.46816 | BH11: 137.69296 | BI11: 137.35406 | BJ11: 136.42157 | BK11: 136.41165 | BL11: 137.00481 | BM11: 138.24833 | BN11: 138.66846 | BO11: 138.12845 | BP11: 138.59134 | BQ11: 137.62711 | BR11: 138.14099 | BS11: 137.97814 | BT11: 138.55363 | BU11: 140.497 | BV11: 140.95712 | BW11: 140.53336 | BX11: 138.47342 | BY11: 139.44975 | BZ11: 139.906 | CA11: 140.27371
A12: Model Score | F12: 0 | G12: 0 | H12: 0 | I12: 0 | J12: 0 | K12: 0 | L12: 0 | M12: 0 | N12: 0 | O12: 0 | P12: 0 | Q12: 0 | R12: 0 | S12: 0 | T12: 0 | U12: 0 | V12: 0 | W12: 0 | X12: 0 | Y12: 0 | Z12: 0 | AA12: 0 | AB12: 0 | AC12: 0 | AD12: 0 | AE12: 0 | AF12: 0 | AG12: 0 | AH12: 0 | AI12: 0 | AJ12: 0 | AK12: 0 | AL12: 0 | AM12: 0 | AN12: 0 | AO12: 0 | AP12: 0 | AQ12: 0 | AR12: 0 | AS12: 0 | AT12: 0 | AU12: 0 | AV12: 0 | AW12: 0 | AX12: 0 | AY12: 0 | AZ12: 0 | BA12: 0 | BB12: 0 | BC12: 0 | BD12: 0 | BE12: 0 | BF12: 0 | BG12: 0 | BH12: 0 | BI12: 0 | BJ12: 0 | BK12: 0 | BL12: 0 | BM12: 0 | BN12: 0 | BO12: 0 | BP12: 0 | BQ12: 0 | BR12: 0 | BS12: 0 | BT12: 0 | BU12: 0 | BV12: 0
A13: Gross Loss Adjustments (Dealer level, high PTI, etc.) | F13: -1.7373722 | G13: -1.7682932 | H13: -1.6529277 | I13: -1.3030934 | J13: -1.0779784 | K13: -1.6965029 | L13: -0.75865575 | M13: -0.81339298 | N13: -0.8738907 | O13: -0.1282815 | P13: 1.1625912 | Q13: 1.4586807 | R13: 1.7413121 | S13: 1.7447552 | T13: 1.8633974 | U13: 0.01567843 | V13: 0.1746438 | W13: -0.98139609 | X13: -0.75002454 | Y13: 0.035125271 | Z13: -0.37976676 | AA13: 0.83082329 | AB13: 1.0277881 | AC13: 0.30039834 | AD13: -0.24235921 | AE13: 1.1461668 | AF13: 0.50274448 | AG13: 1.3914212 | AH13: -2.7876062 | AI13: 1.598522 | AJ13: -1.6446668 | AK13: 1.8056091 | AL13: 2.8774126 | AM13: 2.7745654 | AN13: 3.829454 | AO13: 4.0233398 | AP13: 1.4636107 | AQ13: 3.0169226 | AR13: 7.434023 | AS13: 3.2980094 | AT13: 0.86624726 | AU13: 0.13328613 | AV13: 2.7758939 | AW13: 0.43246278 | AX13: 1.7243706 | AY13: 2.2109081 | AZ13: 3.0459566 | BA13: 3.1397674 | BB13: 2.6673478 | BC13: 3.3425122 | BD13: 3.7915011 | BE13: 4.0317794 | BF13: 4.4562698 | BG13: 3.3965137 | BH13: 3.2409935 | BI13: 2.7337418 | BJ13: 2.3621841 | BK13: 2.5799921 | BL13: 2.1403075 | BM13: 1.8790669 | BN13: 2.8567136 | BO13: 3.2222441 | BP13: 2.8667787 | BQ13: 2.9253432 | BR13: 2.962984 | BS13: 1.6061097 | BT13: 1.3448314 | BU13: 1.4541099 | BV13: 1.2513006
A14: Recovery Adjustments excluding LTV (Mileage, vehicle type, etc.) | F14: 0.35942655 | G14: -0.050127184 | H14: -0.3137726 | I14: -0.50408555 | J14: -0.22432408 | K14: -0.49510039 | L14: -0.55419498 | M14: 0.32762561 | N14: 0.40507979 | O14: 0.076148375 | P14: 0.79886416 | Q14: 1.3534816 | R14: 0.27780611 | S14: -0.57126316 | T14: -0.34752137 | U14: 0.13841611 | V14: 0.016224391 | W14: 0.75700717 | X14: 0.43477555 | Y14: -0.094845458 | Z14: -0.15566479 | AA14: -1.0170333 | AB14: -0.44847924 | AC14: -0.89548706 | AD14: -1.1297844 | AE14: -1.5451233 | AF14: -1.5978422 | AG14: -1.9049101 | AH14: -0.31753543 | AI14: -1.4514564 | AJ14: -1.2506444 | AK14: -2.9904916 | AL14: -3.9118968 | AM14: -3.5947953 | AN14: -1.7457099 | AO14: -3.9333088 | AP14: -4.3545049 | AQ14: 0.22438971 | AR14: -5.6767479 | AS14: -2.468277 | AT14: -1.7091528 | AU14: -1.2407166 | AV14: 1.6085841 | AW14: 0.75525786 | AX14: -2.0174631 | AY14: -1.6035247 | AZ14: -1.4915808 | BA14: -2.0271994 | BB14: -0.63790238 | BC14: -1.5258409 | BD14: -0.39595406 | BE14: -1.5189043 | BF14: 0.01851038 | BG14: 0.41494536 | BH14: -1.2281996 | BI14: 2.1886028 | BJ14: 0.18756286 | BK14: 0.33515863 | BL14: -0.78005684 | BM14: 0.48911342 | BN14: 0.42784479 | BO14: -0.53193379 | BP14: 0.74093627 | BQ14: 0.06371616 | BR14: -0.41171436 | BS14: 1.4761491 | BT14: 0.0031092168 | BU14: 2.101889 | BV14: 2.2212356
A15: LTV Adjustments | F15: -0.35942655 | G15: 0.050127184 | H15: 0.3137726 | I15: 0.50408555 | J15: 0.22432408 | K15: 0.49510039 | L15: 0.55419498 | M15: -0.32762561 | N15: -0.40507979 | O15: -0.076148375 | P15: -0.79886416 | Q15: -1.3534816 | R15: -0.27780611 | S15: 0.57126316 | T15: 0.34752137 | U15: -0.13841611 | V15: -0.016224391 | W15: -0.75700717 | X15: -0.43477555 | Y15: 0.094845458 | Z15: 0.15566479 | AA15: 1.0170333 | AB15: 0.44847924 | AC15: 0.89548706 | AD15: 1.1297844 | AE15: 1.5451233 | AF15: 1.5978422 | AG15: 1.9049101 | AH15: 0.31753543 | AI15: 1.4514564 | AJ15: 1.2506444 | AK15: 2.9904916 | AL15: 3.9118968 | AM15: 3.5947953 | AN15: 1.7457099 | AO15: 3.9333088 | AP15: 4.3545049 | AQ15: -0.22438971 | AR15: 5.6767479 | AS15: 2.468277 | AT15: 1.7091528 | AU15: 1.2407166 | AV15: -1.6085841 | AW15: -0.75525786 | AX15: 2.0174631 | AY15: 1.6035247 | AZ15: 1.4915808 | BA15: 2.0271994 | BB15: 0.63790238 | BC15: 1.5258409 | BD15: 0.39595406 | BE15: 1.5189043 | BF15: -0.01851038 | BG15: -0.41494536 | BH15: 1.2281996 | BI15: -2.1886028 | BJ15: -0.18756286 | BK15: -0.33515863 | BL15: 0.78005684 | BM15: -0.48911342 | BN15: -0.42784479 | BO15: 0.53193379 | BP15: -0.74093627 | BQ15: -0.06371616 | BR15: 0.41171436 | BS15: -1.4761491 | BT15: -0.0031092168 | BU15: -2.101889 | BV15: -2.2212356
A16: RAGU Score | F16: 129.96089 | G16: 131.28636 | H16: 129.79156 | I16: 131.18332 | J16: 134.70791 | K16: 135.97809 | L16: 136.87346 | M16: 136.59689 | N16: 137.62695 | O16: 138.25479 | P16: 142.26822 | Q16: 144.28449 | R16: 141.35272 | S16: 138.90403 | T16: 137.8072 | U16: 136.45013 | V16: 136.77037 | W16: 134.46376 | X16: 134.0573 | Y16: 136.88128 | Z16: 134.92405 | AA16: 136.33845 | AB16: 135.11413 | AC16: 134.52919 | AD16: 134.07705 | AE16: 134.82328 | AF16: 134.91037 | AG16: 137.21735 | AH16: 132.67629 | AI16: 137.87937 | AJ16: 135.30122 | AK16: 138.76201 | AL16: 139.86749 | AM16: 139.65821 | AN16: 143.23669 | AO16: 144.83413 | AP16: 143.14622 | AQ16: 145.40416 | AR16: 147.15538 | AS16: 142.6641 | AT16: 138.78066 | AU16: 137.69253 | AV16: 140.64475 | AW16: 139.6978 | AX16: 140.72671 | AY16: 141.05999 | AZ16: 141.20663 | BA16: 141.70872 | BB16: 140.7081 | BC16: 141.9682 | BD16: 142.80619 | BE16: 144.97457 | BF16: 146.36763 | BG16: 143.86467 | BH16: 140.93395 | BI16: 140.08781 | BJ16: 138.78376 | BK16: 138.99164 | BL16: 139.14512 | BM16: 140.12739 | BN16: 141.52517 | BO16: 141.3507 | BP16: 141.45812 | BQ16: 140.55246 | BR16: 141.10398 | BS16: 139.58425 | BT16: 139.89846 | BU16: 141.95111 | BV16: 142.20842
A17: LTV | F17: 1.4633833 | G17: 1.4328789 | H17: 1.3835412 | I17: 1.3987303 | J17: 1.3782717 | K17: 1.3524544 | L17: 1.2508309 | M17: 1.21004 | N17: 1.1957329 | O17: 1.2530861 | P17: 1.3173324 | Q17: 1.2499791 | R17: 1.3737717 | S17: 1.3001825 | T17: 1.3285323 | U17: 1.2297302 | V17: 1.2119803 | W17: 1.2606704 | X17: 1.246185 | Y17: 1.2991607 | Z17: 1.2768913 | AA17: 1.3598356 | AB17: 1.321942 | AC17: 1.3166955 | AD17: 1.3759183 | AE17: 1.3415726 | AF17: 1.3186163 | AG17: 1.3312274 | AH17: 1.3375786 | AI17: 1.3787396 | AJ17: 1.3692844 | AK17: 1.3280318 | AL17: 1.6929744 | AM17: 1.4141001 | AN17: 1.4592922 | AO17: 1.2674946 | AP17: 1.0157032 | AQ17: 1.2871118 | AR17: 1.4262285 | AS17: 1.3644385 | AT17: 1.2197282 | AU17: 1.3848582 | AV17: 1.4189847 | AW17: 1.3149134 | AX17: 1.3392866 | AY17: 1.3450408 | AZ17: 1.3709559 | BA17: 1.4149511 | BB17: 1.3246312 | BC17: 1.3784484 | BD17: 1.3175541 | BE17: 1.3235298 | BF17: 1.3460769 | BG17: 1.2261802 | BH17: 1.3539596 | BI17: 1.3451356 | BJ17: 1.3387531 | BK17: 1.3910422 | BL17: 1.3702807 | BM17: 1.4432888 | BN17: 1.386518 | BO17: 1.4267052 | BP17: 1.3679674 | BQ17: 1.4169798 | BR17: 1.4090583 | BS17: 1.3528876 | BT17: 1.379123 | BU17: 1.3880331 | BV17: 1.479477
A19: FRN | B19: 2016 | C19: 2017 | D19: 2018 | E19: 2019 | F19: 2020 M01 | G19: 2020 M02 | H19: 2020 M03 | I19: 2020 M04 | J19: 2020 M05 | K19: 2020 M06 | L19: 2020 M07 | M19: 2020 M08 | N19: 2020 M09 | O19: 2020 M10 | P19: 2020 M11 | Q19: 2020 M12 | R19: 2021 M01 | S19: 2021 M02 | T19: 2021 M03 | U19: 2021 M04 | V19: 2021 M05 | W19: 2021 M06 | X19: 2021 M07 | Y19: 2021 M08 | Z19: 2021 M09 | AA19: 2021 M10 | AB19: 2021 M11 | AC19: 2021 M12 | AD19: 2022 M01 | AE19: 2022 M02 | AF19: 2022 M03 | AG19: 2022 M04 | AH19: 2022 M05 | AI19: 2022 M06 | AJ19: 2022 M07 | AK19: 2022 M08 | AL19: 2022 M09 | AM19: 2022 M10 | AN19: 2022 M11 | AO19: 2022 M12 | AP19: 2023 M01 | AQ19: 2023 M02 | AR19: 2023 M03 | AS19: 2023 M04 | AT19: 2023 M05 | AU19: 2023 M06 | AV19: 2023 M07 | AW19: 2023 M08 | AX19: 2023 M09 | AY19: 2023 M10 | AZ19: 2023 M11 | BA19: 2023 M12 | BB19: 2024 M01 | BC19: 2024 M02 | BD19: 2024 M03 | BE19: 2024 M04 | BF19: 2024 M05 | BG19: 2024 M06 | BH19: 2024 M07 | BI19: 2024 M08 | BJ19: 2024 M09 | BK19: 2024 M10 | BL19: 2024 M11 | BM19: 2024 M12 | BN19: 2025 M01 | BO19: 2025 M02 | BP19: 2025 M03 | BQ19: 2025 M04 | BR19: 2025 M05 | BS19: 2025 M06 | BT19: 2025 M07 | BU19: 2025 M08 | BV19: 2025 M09 | BW19: 2025 M10 | BX19: 2025 M11 | BY19: 2025 M12 | BZ19: 2026 M01
A20: Contract Model Score | B20: 131.18489 | C20: 136.72146 | D20: 136.81942 | E20: 132.54318 | F20: 131.2656 | G20: 131.24734 | H20: 131.00099 | I20: 131.49953 | J20: 133.24754 | K20: 133.3984 | L20: 134.41536 | M20: 134.0819 | N20: 133.20621 | O20: 132.62511 | P20: 131.11674 | Q20: 135.00101 | R20: 135.45485 | S20: 135.55568 | T20: 135.39896 | U20: 135.35416 | V20: 135.51119 | W20: 134.67649 | X20: 134.23647 | Y20: 135.97528 | Z20: 134.5695 | AA20: 134.42803 | AB20: 132.01635 | AC20: 132.29985 | AD20: 134.01481 | AE20: 133.66105 | AF20: 134.31365 | AG20: 135.70242 | AH20: 137.3415 | AI20: 137.64811 | AJ20: 138.18701 | AK20: 137.99667 | AL20: 137.85245 | AM20: 138.34232 | AN20: 140.94633 | AO20: 141.0318 | AP20: 141.07216 | AQ20: 141.68378 | AR20: 141.17134 | AS20: 140.558 | AT20: 140.54313 | AU20: 140.65163 | AV20: 139.52303 | AW20: 141.17927 | AX20: 141.16169 | AY20: 138.66844 | AZ20: 139.04265 | BA20: 138.51156 | BB20: 137.58847 | BC20: 139.37221 | BD20: 140.53108 | BE20: 140.72018 | BF20: 141.1387 | BG20: 141.99905 | BH20: 141.69762 | BI20: 140.62793 | BJ20: 139.96452 | BK20: 139.29146 | BL20: 139.70528 | BM20: 140.12303 | BN20: 139.74747 | BO20: 140.31399 | BP20: 140.88037 | BQ20: 140.75094 | BR20: 140.87437 | BS20: 140.73303 | BT20: 141.33269 | BU20: 141.69552 | BV20: 141.57111 | BW20: 142.27606 | BX20: 142.85904 | BY20: 140.12829 | BZ20: 138.55401 | CA20: 144.29157
A21: Model Score | B21: 0 | C21: 0 | D21: 0 | E21: 0 | F21: 0 | G21: 0 | H21: 0 | I21: 0 | J21: 0 | K21: 0 | L21: 0 | M21: 0 | N21: 0 | O21: 0 | P21: 0 | Q21: 0 | R21: 0 | S21: 0 | T21: 0 | U21: 0 | V21: 0 | W21: 0 | X21: 0 | Y21: 0 | Z21: 0 | AA21: 0 | AB21: 0 | AC21: 0 | AD21: 0 | AE21: 0 | AF21: 0 | AG21: 0 | AH21: 0 | AI21: 0 | AJ21: 0 | AK21: 0 | AL21: 0 | AM21: 0 | AN21: 0 | AO21: 0 | AP21: 0 | AQ21: 0 | AR21: 0 | AS21: 0 | AT21: 0 | AU21: 0 | AV21: 0 | AW21: 0 | AX21: 0 | AY21: 0 | AZ21: 0 | BA21: 0 | BB21: 0 | BC21: 0 | BD21: 0 | BE21: 0 | BF21: 0 | BG21: 0 | BH21: 0 | BI21: 0 | BJ21: 0 | BK21: 0 | BL21: 0 | BM21: 0 | BN21: 0 | BO21: 0 | BP21: 0 | BQ21: 0 | BR21: 0 | BS21: 0 | BT21: 0 | BU21: 0 | BV21: 0 | BW21: 0 | BX21: 0
A22: Gross Loss Adjustments (Dealer level, high PTI, etc.) | B22: -0.040003629 | C22: 0.57455492 | D22: 0.12243283 | E22: 0.78145362 | F22: 1.0141222 | G22: 1.4974347 | H22: 1.3924236 | I22: 1.590529 | J22: 1.691881 | K22: 1.3546638 | L22: 0.69064984 | M22: 0.57792768 | N22: 0.40205567 | O22: -0.19286348 | P22: -0.10964835 | Q22: 0.41701637 | R22: 0.29982442 | S22: 0.61940318 | T22: 0.60974748 | U22: 0.92003369 | V22: 0.98576779 | W22: 0.81739563 | X22: 0.65110737 | Y22: 0.76217447 | Z22: 0.67788991 | AA22: -0.27169981 | AB22: -0.356482 | AC22: -0.4689839 | AD22: -0.39979835 | AE22: -0.13521444 | AF22: -0.22183017 | AG22: 0.31944825 | AH22: 0.83388804 | AI22: 0.20709188 | AJ22: 0.26214958 | AK22: 0.95535432 | AL22: 0.26495611 | AM22: -1.1940459 | AN22: 0.94115709 | AO22: -1.1316226 | AP22: 0.93065374 | AQ22: 1.2148198 | AR22: 0.13674895 | AS22: -4.8428543 | AT22: 1.9101684 | AU22: 0.64726212 | AV22: 0.35689769 | AW22: 1.6365111 | AX22: -10 | AY22: -0.37965143 | AZ22: 0.17374082 | BA22: -0.6742371 | BB22: -0.37827903 | BC22: -0.028685022 | BD22: 0.55645953 | BE22: 0.09334272 | BF22: 0.25847951 | BG22: 0.64105215 | BH22: 0.52224182 | BI22: 1.1068606 | BJ22: 1.2512509 | BK22: 0.38033277 | BL22: 1.2882127 | BM22: 0.87304419 | BN22: 1.150892 | BO22: 1.302778 | BP22: 1.0747574 | BQ22: 1.8494632 | BR22: 1.6609088 | BS22: 1.5637332 | BT22: 2.1808531 | BU22: 2.9565227 | BV22: 3.316971 | BW22: 3.3633397 | BX22: 2.9825787
A23: Recovery Adjustments excluding LTV (Mileage, vehicle type, etc.) | B23: -0.44541836 | C23: 0.12151064 | D23: 0.12296463 | E23: -0.057485299 | F23: 0.86506221 | G23: 0.10089329 | H23: -0.40811267 | I23: -0.67737006 | J23: -0.1305448 | K23: -0.063980348 | L23: -0.29674852 | M23: -0.10384621 | N23: 0.14516574 | O23: 0.42438675 | P23: 0.15679778 | Q23: 0.70906288 | R23: 0.47152535 | S23: 0.36785036 | T23: 0.014881875 | U23: 0.31021904 | V23: 0.0079610051 | W23: -0.039474092 | X23: -0.37581342 | Y23: -0.40622575 | Z23: 0.1274192 | AA23: -0.35901536 | AB23: -0.70516925 | AC23: -0.31337673 | AD23: -0.97839603 | AE23: -0.89376823 | AF23: -1.5615412 | AG23: -1.1364871 | AH23: -2.1854589 | AI23: -2.3483223 | AJ23: -2.3383244 | AK23: -1.0929416 | AL23: -1.6651902 | AM23: 0.43487244 | AN23: -2.2542992 | AO23: -2.4107561 | AP23: 3.4819326 | AQ23: -3.1947126 | AR23: -1.6107774 | AS23: -3.6141104 | AT23: -2.1836762 | AU23: -0.94480217 | AV23: -4.6985486 | AW23: 0.7237003 | AX23: -4.4417319 | AY23: -1.7956886 | AZ23: -1.3072352 | BA23: -1.058562 | BB23: -1.7295122 | BC23: -1.4207238 | BD23: -0.97784348 | BE23: -1.7394157 | BF23: -0.69469879 | BG23: -0.76222417 | BH23: -0.77282432 | BI23: -0.93159796 | BJ23: 0.18195619 | BK23: 1.2602126 | BL23: 0.42315465 | BM23: 0.60791971 | BN23: 0.18218872 | BO23: 0.16518629 | BP23: 0.12935852 | BQ23: 0.16239567 | BR23: 0.14105996 | BS23: 0.2368658 | BT23: 1.4025926 | BU23: 1.187159 | BV23: 1.973283 | BW23: 2.4277931 | BX23: 2.9544591
A24: LTV Adjustments | B24: 0.44541836 | C24: -0.12151064 | D24: -0.12296463 | E24: 0.057485299 | F24: -0.86506221 | G24: -0.10089329 | H24: 0.40811267 | I24: 0.67737006 | J24: 0.1305448 | K24: 0.063980348 | L24: 0.29674852 | M24: 0.10384621 | N24: -0.14516574 | O24: -0.42438675 | P24: -0.15679778 | Q24: -0.70906288 | R24: -0.47152535 | S24: -0.36785036 | T24: -0.014881875 | U24: -0.31021904 | V24: -0.0079610051 | W24: 0.039474092 | X24: 0.37581342 | Y24: 0.40622575 | Z24: -0.1274192 | AA24: 0.35901536 | AB24: 0.70516925 | AC24: 0.31337673 | AD24: 0.97839603 | AE24: 0.89376823 | AF24: 1.5615412 | AG24: 1.1364871 | AH24: 2.1854589 | AI24: 2.3483223 | AJ24: 2.3383244 | AK24: 1.0929416 | AL24: 1.6651902 | AM24: -0.43487244 | AN24: 2.2542992 | AO24: 2.4107561 | AP24: -3.4819326 | AQ24: 3.1947126 | AR24: 1.6107774 | AS24: 3.6141104 | AT24: 2.1836762 | AU24: 0.94480217 | AV24: 4.6985486 | AW24: -0.7237003 | AX24: 4.4417319 | AY24: 1.7956886 | AZ24: 1.3072352 | BA24: 1.058562 | BB24: 1.7295122 | BC24: 1.4207238 | BD24: 0.97784348 | BE24: 1.7394157 | BF24: 0.69469879 | BG24: 0.76222417 | BH24: 0.77282432 | BI24: 0.93159796 | BJ24: -0.18195619 | BK24: -1.2602126 | BL24: -0.42315465 | BM24: -0.60791971 | BN24: -0.18218872 | BO24: -0.16518629 | BP24: -0.12935852 | BQ24: -0.16239567 | BR24: -0.14105996 | BS24: -0.2368658 | BT24: -1.4025926 | BU24: -1.187159 | BV24: -1.973283 | BW24: -2.4277931 | BX24: -2.9544591
A25: RAGU Score | B25: 131.14489 | C25: 137.29602 | D25: 136.94185 | E25: 133.32463 | F25: 132.27972 | G25: 132.74477 | H25: 132.39342 | I25: 133.09006 | J25: 134.93942 | K25: 134.75307 | L25: 135.10601 | M25: 134.65982 | N25: 133.60826 | O25: 132.43225 | P25: 131.0071 | Q25: 135.41802 | R25: 135.75467 | S25: 136.17509 | T25: 136.00871 | U25: 136.2742 | V25: 136.49696 | W25: 135.49389 | X25: 134.88758 | Y25: 136.73745 | Z25: 135.24739 | AA25: 134.15633 | AB25: 131.65987 | AC25: 131.83087 | AD25: 133.61502 | AE25: 133.52583 | AF25: 134.09182 | AG25: 136.02187 | AH25: 138.17539 | AI25: 137.8552 | AJ25: 138.44916 | AK25: 138.95202 | AL25: 138.11741 | AM25: 137.14827 | AN25: 141.88749 | AO25: 139.90017 | AP25: 142.00282 | AQ25: 142.8986 | AR25: 141.30808 | AS25: 135.71514 | AT25: 142.4533 | AU25: 141.2989 | AV25: 139.87993 | AW25: 142.81578 | AX25: 131.16169 | AY25: 138.28879 | AZ25: 139.21639 | BA25: 137.83732 | BB25: 137.21019 | BC25: 139.34352 | BD25: 141.08754 | BE25: 140.81352 | BF25: 141.39718 | BG25: 142.6401 | BH25: 142.21986 | BI25: 141.73479 | BJ25: 141.21578 | BK25: 139.67179 | BL25: 140.99349 | BM25: 140.99608 | BN25: 140.89836 | BO25: 141.61677 | BP25: 141.95512 | BQ25: 142.60041 | BR25: 142.53527 | BS25: 142.29677 | BT25: 143.51354 | BU25: 144.65205 | BV25: 144.88808 | BW25: 145.6394 | BX25: 145.84162
A26: LTV | B26: 2.1505528 | C26: 2.2073907 | D26: 2.1097029 | E26: 2.0875659 | F26: 2.0194091 | G26: 1.9185204 | H26: 1.9174761 | I26: 1.8742113 | J26: 2.0008174 | K26: 1.9375934 | L26: 1.8533141 | M26: 1.9186936 | N26: 1.9383992 | O26: 2.0427444 | P26: 2.1737347 | Q26: 1.8361932 | R26: 1.8609857 | S26: 1.7791028 | T26: 1.6618226 | U26: 1.5595819 | V26: 1.4615419 | W26: 1.5105506 | X26: 1.5517052 | Y26: 1.610812 | Z26: 1.695937 | AA26: 1.67477 | AB26: 1.6795947 | AC26: 1.7077679 | AD26: 1.6418182 | AE26: 1.6727076 | AF26: 1.655978 | AG26: 1.668858 | AH26: 1.7857036 | AI26: 1.6580934 | AJ26: 1.8637755 | AK26: 2.031157 | AL26: 1.6469266 | AM26: 1.666092 | AN26: 1.6759706 | AO26: 1.4921203 | AP26: 2.0740089 | AQ26: 1.3264035 | AR26: 1.9014931 | AS26: 3.0445155 | AT26: 1.9726026 | AU26: 1.554958 | AV26: 1.8467201 | AW26: 1.6511792 | AX26: 1.3457691 | AY26: 1.5262134 | AZ26: 1.5082192 | BA26: 1.4602687 | BB26: 1.4884281 | BC26: 1.4865341 | BD26: 1.5047788 | BE26: 1.4756972 | BF26: 1.4997432 | BG26: 1.5363732 | BH26: 1.4876361 | BI26: 1.5637789 | BJ26: 1.4645949 | BK26: 1.4505847 | BL26: 1.464124 | BM26: 1.4538271 | BN26: 1.4686109 | BO26: 1.4434687 | BP26: 1.3840699 | BQ26: 1.3761983 | BR26: 1.4057748 | BS26: 1.3921124 | BT26: 1.3984415 | BU26: 1.3543769 | BV26: 1.3899383 | BW26: 1.4384254 | BX26: 1.4802729
A28: STG | B28: 2016 | C28: 2017 | D28: 2018 | E28: 2019 | F28: 2020 M01 | G28: 2020 M02 | H28: 2020 M03 | I28: 2020 M04 | J28: 2020 M05 | K28: 2020 M06 | L28: 2020 M07 | M28: 2020 M08 | N28: 2020 M09 | O28: 2020 M10 | P28: 2020 M11 | Q28: 2020 M12 | R28: 2021 M01 | S28: 2021 M02 | T28: 2021 M03 | U28: 2021 M04 | V28: 2021 M05 | W28: 2021 M06 | X28: 2021 M07 | Y28: 2021 M08 | Z28: 2021 M09 | AA28: 2021 M10 | AB28: 2021 M11 | AC28: 2021 M12 | AD28: 2022 M01 | AE28: 2022 M02 | AF28: 2022 M03 | AG28: 2022 M04 | AH28: 2022 M05 | AI28: 2022 M06 | AJ28: 2022 M07 | AK28: 2022 M08 | AL28: 2022 M09 | AM28: 2022 M10 | AN28: 2022 M11 | AO28: 2022 M12 | AP28: 2023 M01 | AQ28: 2023 M02 | AR28: 2023 M03 | AS28: 2023 M04 | AT28: 2023 M05 | AU28: 2023 M06 | AV28: 2023 M07 | AW28: 2023 M08 | AX28: 2023 M09 | AY28: 2023 M10 | AZ28: 2023 M11 | BA28: 2023 M12 | BB28: 2024 M01 | BC28: 2024 M02 | BD28: 2024 M03 | BE28: 2024 M04 | BF28: 2024 M05 | BG28: 2024 M06 | BH28: 2024 M07 | BI28: 2024 M08 | BJ28: 2024 M09 | BK28: 2024 M10 | BL28: 2024 M11 | BM28: 2024 M12 | BN28: 2025 M01 | BO28: 2025 M02 | BP28: 2025 M03 | BQ28: 2025 M04 | BR28: 2025 M05 | BS28: 2025 M06 | BT28: 2025 M07 | BU28: 2025 M08 | BV28: 2025 M09 | BW28: 2025 M10 | BX28: 2025 M11 | BY28: 2025 M12 | BZ28: 2026 M01
A29: Contract Model Score | B29: 129.63955 | C29: 131.6541 | D29: 131.56964 | E29: 129.50608 | F29: 129.78439 | G29: 130.3194 | H29: 130.01813 | I29: 130.28186 | J29: 133.55242 | K29: 134.9074 | L29: 135.24459 | M29: 135.85773 | N29: 135.50069 | O29: 135.75132 | P29: 135.13958 | Q29: 134.89594 | R29: 135.56415 | S29: 135.05332 | T29: 135.26623 | U29: 135.39571 | V29: 135.36165 | W29: 135.74131 | X29: 135.03843 | Y29: 135.73405 | Z29: 134.33915 | AA29: 134.68261 | AB29: 132.94521 | AC29: 133.34441 | AD29: 134.2864 | AE29: 134.70284 | AF29: 134.6113 | AG29: 136.26908 | AH29: 136.73318 | AI29: 137.23263 | AJ29: 136.95716 | AK29: 137.63345 | AL29: 137.23928 | AM29: 137.73629 | AN29: 139.05852 | AO29: 138.44604 | AP29: 139.96787 | AQ29: 138.75376 | AR29: 139.11148 | AS29: 137.41883 | AT29: 138.17301 | AU29: 137.51063 | AV29: 137.68289 | AW29: 138.42609 | AX29: 139.23481 | AY29: 136.90455 | AZ29: 137.3486 | BA29: 136.85059 | BB29: 136.43852 | BC29: 137.16962 | BD29: 137.44545 | BE29: 137.85018 | BF29: 138.12378 | BG29: 138.88324 | BH29: 138.78355 | BI29: 137.96917 | BJ29: 136.82707 | BK29: 136.74566 | BL29: 136.75775 | BM29: 136.52401 | BN29: 136.69779 | BO29: 137.49793 | BP29: 137.93118 | BQ29: 138.5378 | BR29: 138.60141 | BS29: 138.34121 | BT29: 139.08055 | BU29: 139.19216 | BV29: 139.60755 | BW29: 141.45995 | BX29: 141.64596 | BY29: 138.36256 | BZ29: 137.34161 | CA29: 141.01662
A30: Model Score | B30: 0 | C30: 0 | D30: 0 | E30: 0 | F30: 0 | G30: 0 | H30: 0 | I30: 0 | J30: 0 | K30: 0 | L30: 0 | M30: 0 | N30: 0 | O30: 0 | P30: 0 | Q30: 0 | R30: 0 | S30: 0 | T30: 0 | U30: 0 | V30: 0 | W30: 0 | X30: 0 | Y30: 0 | Z30: 0 | AA30: 0 | AB30: 0 | AC30: 0 | AD30: 0 | AE30: 0 | AF30: 0 | AG30: 0 | AH30: 0 | AI30: 0 | AJ30: 0 | AK30: 0 | AL30: 0 | AM30: 0 | AN30: 0 | AO30: 0 | AP30: 0 | AQ30: 0 | AR30: 0 | AS30: 0 | AT30: 0 | AU30: 0 | AV30: 0 | AW30: 0 | AX30: 0 | AY30: 0 | AZ30: 0 | BA30: 0 | BB30: 0 | BC30: 0 | BD30: 0 | BE30: 0 | BF30: 0 | BG30: 0 | BH30: 0 | BI30: 0 | BJ30: 0 | BK30: 0 | BL30: 0 | BM30: 0 | BN30: 0 | BO30: 0 | BP30: 0 | BQ30: 0 | BR30: 0 | BS30: 0 | BT30: 0 | BU30: 0 | BV30: 0 | BW30: 0 | BX30: 0
A31: Gross Loss Adjustments (Dealer level, high PTI, etc.) | B31: 0.82200867 | C31: 0.94331678 | D31: 0.8732775 | E31: 0.94815913 | F31: 0.67803508 | G31: 0.41528649 | H31: 0.74987391 | I31: 0.43142049 | J31: 0.5519861 | K31: 0.70277859 | L31: 0.82669385 | M31: 0.93011174 | N31: 0.99300002 | O31: 0.94218232 | P31: 0.74733995 | Q31: 0.82287702 | R31: 1.6307511 | S31: 1.7202458 | T31: 1.6635727 | U31: 1.8395175 | V31: 1.908889 | W31: 1.7264935 | X31: 1.4791288 | Y31: 1.5973358 | Z31: 1.4824169 | AA31: 1.1204565 | AB31: 1.2908944 | AC31: 1.1923053 | AD31: 0.49474395 | AE31: 0.37581117 | AF31: 0.77009603 | AG31: 0.47569723 | AH31: 1.9082218 | AI31: 2.4529663 | AJ31: 1.432604 | AK31: 0.018182118 | AL31: -1.6039225 | AM31: 0.80705772 | AN31: 0.72028839 | AO31: 0.95564856 | AP31: 1.5559155 | AQ31: -5.4976385 | AR31: 3.8958982 | AS31: 3.2941837 | AT31: -1.5539318 | AU31: -0.53627028 | AV31: 1.2414827 | AW31: 1.9185926 | AX31: 0.687229 | AY31: 1.8467538 | AZ31: 1.7677956 | BA31: 0.31402868 | BB31: 0.7898659 | BC31: 1.9076542 | BD31: 2.2496134 | BE31: 2.536935 | BF31: 2.1349158 | BG31: 2.0094308 | BH31: 2.2206432 | BI31: 1.9681101 | BJ31: 1.7988874 | BK31: 1.2810308 | BL31: 1.4300117 | BM31: 1.5529908 | BN31: 1.1800563 | BO31: 1.733736 | BP31: 1.7240162 | BQ31: 2.2645703 | BR31: 1.865663 | BS31: 1.7808388 | BT31: 2.4208732 | BU31: 2.4373103 | BV31: 3.1042446 | BW31: 3.7259265 | BX31: 2.4731799
A32: Recovery Adjustments excluding LTV (Mileage, vehicle type, etc.) | B32: -0.47932338 | C32: 0.39115157 | D32: 0.2771793 | E32: 0.080689838 | F32: -0.25821088 | G32: -0.088448241 | H32: -0.36391365 | I32: -0.13476753 | J32: -0.50051884 | K32: -0.43257335 | L32: -0.29134712 | M32: -0.014379243 | N32: 0.036133011 | O32: 0.19985294 | P32: 0.29665909 | Q32: 0.6274533 | R32: 0.58881346 | S32: 0.58917334 | T32: 0.19857717 | U32: -0.029299117 | V32: -0.12092275 | W32: 0.078046436 | X32: 0.11288784 | Y32: -0.15754904 | Z32: -0.36432325 | AA32: -0.83840099 | AB32: -0.42988161 | AC32: -0.76597522 | AD32: -0.58293348 | AE32: -0.90818436 | AF32: -1.748248 | AG32: -0.93445967 | AH32: 1.0612811 | AI32: -2.4078632 | AJ32: -0.74508335 | AK32: -2.4905576 | AL32: -4.6129882 | AM32: -0.17280682 | AN32: 1.1888569 | AO32: -1.8674456 | AP32: -3.8253981 | AQ32: -0.7897144 | AR32: 0.4639765 | AS32: -4.4345162 | AT32: -1.7768972 | AU32: -3.8775635 | AV32: 0.82442004 | AW32: 0.97350816 | AX32: -1.5401931 | AY32: -1.8210804 | AZ32: -0.71113369 | BA32: -0.53444327 | BB32: -1.5072009 | BC32: -1.4880608 | BD32: -0.83286341 | BE32: -0.35286014 | BF32: 0.29517208 | BG32: -0.78186767 | BH32: -0.21896991 | BI32: -0.33982766 | BJ32: -0.23780951 | BK32: 1.6958971 | BL32: 1.4264151 | BM32: 1.0112008 | BN32: 0.30745822 | BO32: 0.83652629 | BP32: 0.057706203 | BQ32: -1.0329316 | BR32: 2.3276804 | BS32: 0.89173883 | BT32: 1.5090151 | BU32: 0.65393353 | BV32: 3.0232831 | BW32: 0.99974112 | BX32: 0.96045826
A33: LTV Adjustments | B33: 0.47932338 | C33: -0.39115157 | D33: -0.2771793 | E33: -0.080689838 | F33: 0.25821088 | G33: 0.088448241 | H33: 0.36391365 | I33: 0.13476753 | J33: 0.50051884 | K33: 0.43257335 | L33: 0.29134712 | M33: 0.014379243 | N33: -0.036133011 | O33: -0.19985294 | P33: -0.29665909 | Q33: -0.6274533 | R33: -0.58881346 | S33: -0.58917334 | T33: -0.19857717 | U33: 0.029299117 | V33: 0.12092275 | W33: -0.078046436 | X33: -0.11288784 | Y33: 0.15754904 | Z33: 0.36432325 | AA33: 0.83840099 | AB33: 0.42988161 | AC33: 0.76597522 | AD33: 0.58293348 | AE33: 0.90818436 | AF33: 1.748248 | AG33: 0.93445967 | AH33: -1.0612811 | AI33: 2.4078632 | AJ33: 0.74508335 | AK33: 2.4905576 | AL33: 4.6129882 | AM33: 0.17280682 | AN33: -1.1888569 | AO33: 1.8674456 | AP33: 3.8253981 | AQ33: 0.7897144 | AR33: -0.4639765 | AS33: 4.4345162 | AT33: 1.7768972 | AU33: 3.8775635 | AV33: -0.82442004 | AW33: -0.97350816 | AX33: 1.5401931 | AY33: 1.8210804 | AZ33: 0.71113369 | BA33: 0.53444327 | BB33: 1.5072009 | BC33: 1.4880608 | BD33: 0.83286341 | BE33: 0.35286014 | BF33: -0.29517208 | BG33: 0.78186767 | BH33: 0.21896991 | BI33: 0.33982766 | BJ33: 0.23780951 | BK33: -1.6958971 | BL33: -1.4264151 | BM33: -1.0112008 | BN33: -0.30745822 | BO33: -0.83652629 | BP33: -0.057706203 | BQ33: 1.0329316 | BR33: -2.3276804 | BS33: -0.89173883 | BT33: -1.5090151 | BU33: -0.65393353 | BV33: -3.0232831 | BW33: -0.99974112 | BX33: -0.96045826
A34: RAGU Score | B34: 130.46156 | C34: 132.59742 | D34: 132.44292 | E34: 130.45424 | F34: 130.46242 | G34: 130.73468 | H34: 130.768 | I34: 130.71328 | J34: 134.10441 | K34: 135.61017 | L34: 136.07128 | M34: 136.78784 | N34: 136.49369 | O34: 136.69351 | P34: 135.88692 | Q34: 135.71881 | R34: 137.1949 | S34: 136.77356 | T34: 136.9298 | U34: 137.23522 | V34: 137.27054 | W34: 137.4678 | X34: 136.51756 | Y34: 137.33138 | Z34: 135.82157 | AA34: 135.80307 | AB34: 134.2361 | AC34: 134.53671 | AD34: 134.78114 | AE34: 135.07865 | AF34: 135.3814 | AG34: 136.74478 | AH34: 138.6414 | AI34: 139.6856 | AJ34: 138.38976 | AK34: 137.65163 | AL34: 135.63536 | AM34: 138.54334 | AN34: 139.77881 | AO34: 139.40169 | AP34: 141.52378 | AQ34: 133.25612 | AR34: 143.00738 | AS34: 140.71301 | AT34: 136.61908 | AU34: 136.97436 | AV34: 138.92437 | AW34: 140.34469 | AX34: 139.92204 | AY34: 138.7513 | AZ34: 139.11639 | BA34: 137.16462 | BB34: 137.22838 | BC34: 139.07728 | BD34: 139.69506 | BE34: 140.38711 | BF34: 140.2587 | BG34: 140.89268 | BH34: 141.0042 | BI34: 139.93728 | BJ34: 138.62596 | BK34: 138.02669 | BL34: 138.18776 | BM34: 138.077 | BN34: 137.87785 | BO34: 139.23166 | BP34: 139.6552 | BQ34: 140.80237 | BR34: 140.46707 | BS34: 140.12205 | BT34: 141.50143 | BU34: 141.62947 | BV34: 142.7118 | BW34: 145.18587 | BX34: 144.11914
A35: LTV | B35: 1.9469756 | C35: 1.9399714 | D35: 1.9873601 | E35: 2.0859967 | F35: 2.0676889 | G35: 2.1290235 | H35: 2.0540996 | I35: 2.0944388 | J35: 2.1513491 | K35: 2.0657497 | L35: 1.8646704 | M35: 1.8045241 | N35: 1.774196 | O35: 1.763457 | P35: 1.8444218 | Q35: 1.8116717 | R35: 1.8007957 | S35: 1.7048222 | T35: 1.649114 | U35: 1.6103487 | V35: 1.5547197 | W35: 1.5493184 | X35: 1.5257625 | Y35: 1.6111285 | Z35: 1.6459911 | AA35: 1.5715921 | AB35: 1.6688367 | AC35: 1.5946037 | AD35: 1.5834516 | AE35: 1.5721565 | AF35: 1.55897 | AG35: 1.5365354 | AH35: 1.7429162 | AI35: 1.5592624 | AJ35: 1.7688528 | AK35: 1.5819754 | AL35: 1.6419623 | AM35: 1.3753977 | AN35: 1.3456268 | AO35: 2.1005117 | AP35: 0.85337384 | AQ35: 1.2910038 | AR35: 1.6395104 | AS35: 6.5609117 | AT35: 1.7781131 | AU35: 1.5592245 | AV35: 1.6482663 | AW35: 1.7437847 | AX35: 2.3904306 | AY35: 1.6198295 | AZ35: 1.4763011 | BA35: 1.507895 | BB35: 1.5198383 | BC35: 1.576527 | BD35: 1.4853391 | BE35: 1.4597719 | BF35: 1.4682441 | BG35: 1.4714205 | BH35: 1.5338191 | BI35: 1.497031 | BJ35: 1.4522129 | BK35: 1.5158906 | BL35: 1.4839641 | BM35: 1.4957652 | BN35: 1.4707445 | BO35: 1.4441365 | BP35: 1.4000733 | BQ35: 1.3586424 | BR35: 1.4664219 | BS35: 1.4125682 | BT35: 1.4054031 | BU35: 1.3857517 | BV35: 1.4433239 | BW35: 1.3866469 | BX35: 1.4819447
A37: ENT | B37: 2016 | C37: 2017 | D37: 2018 | E37: 2019 | F37: 2020 M01 | G37: 2020 M02 | H37: 2020 M03 | I37: 2020 M04 | J37: 2020 M05 | K37: 2020 M06 | L37: 2020 M07 | M37: 2020 M08 | N37: 2020 M09 | O37: 2020 M10 | P37: 2020 M11 | Q37: 2020 M12 | R37: 2021 M01 | S37: 2021 M02 | T37: 2021 M03 | U37: 2021 M04 | V37: 2021 M05 | W37: 2021 M06 | X37: 2021 M07 | Y37: 2021 M08 | Z37: 2021 M09 | AA37: 2021 M10 | AB37: 2021 M11 | AC37: 2021 M12 | AD37: 2022 M01 | AE37: 2022 M02 | AF37: 2022 M03 | AG37: 2022 M04 | AH37: 2022 M05 | AI37: 2022 M06 | AJ37: 2022 M07 | AK37: 2022 M08 | AL37: 2022 M09 | AM37: 2022 M10 | AN37: 2022 M11 | AO37: 2022 M12 | AP37: 2023 M01 | AQ37: 2023 M02 | AR37: 2023 M03 | AS37: 2023 M04 | AT37: 2023 M05 | AU37: 2023 M06 | AV37: 2023 M07 | AW37: 2023 M08 | AX37: 2023 M09 | AY37: 2023 M10 | AZ37: 2023 M11 | BA37: 2023 M12 | BB37: 2024 M01 | BC37: 2024 M02 | BD37: 2024 M03 | BE37: 2024 M04 | BF37: 2024 M05 | BG37: 2024 M06 | BH37: 2024 M07 | BI37: 2024 M08 | BJ37: 2024 M09 | BK37: 2024 M10 | BL37: 2024 M11 | BM37: 2024 M12 | BN37: 2025 M01 | BO37: 2025 M02 | BP37: 2025 M03 | BQ37: 2025 M04 | BR37: 2025 M05 | BS37: 2025 M06 | BT37: 2025 M07 | BU37: 2025 M08 | BV37: 2025 M09 | BW37: 2025 M10 | BX37: 2025 M11 | BY37: 2025 M12 | BZ37: 2026 M01
A38: Contract Model Score | F38: 129.42831 | G38: 133.57876 | H38: 133.13665 | I38: 130.57532 | J38: 133.68967 | K38: 135.91754 | L38: 136.54209 | M38: 136.23045 | N38: 136.12905 | O38: 135.90718 | P38: 135.82731 | Q38: 134.58041 | R38: 134.5807 | S38: 134.12233 | T38: 133.38292 | U38: 132.20794 | V38: 131.87001 | W38: 131.44439 | X38: 130.42029 | Y38: 132.17114 | Z38: 130.86404 | AA38: 129.94668 | AB38: 129.79633 | AC38: 128.6143 | AD38: 128.75316 | AE38: 129.14794 | AF38: 129.85816 | AG38: 130.64955 | AH38: 131.7484 | AI38: 132.02686 | AJ38: 132.30609 | AK38: 131.79146 | AL38: 131.18606 | AM38: 130.57426 | AN38: 131.29341 | AO38: 131.94153 | AP38: 132.08433 | AQ38: 132.6274 | AR38: 133.13309 | AS38: 133.87992 | AT38: 134.10541 | AU38: 132.545 | AV38: 132.38189 | AW38: 134.17477 | AX38: 135.03681 | AY38: 135.90351 | AZ38: 136.12985 | BA38: 136.14381 | BB38: 136.21437 | BC38: 136.55872 | BD38: 136.84039 | BE38: 137.22165 | BF38: 136.77385 | BG38: 136.60034 | BH38: 136.68759 | BI38: 135.50937 | BJ38: 134.76105 | BK38: 134.55901 | BL38: 134.35793 | BM38: 134.0252 | BN38: 135.00828 | BO38: 136.09756 | BP38: 136.3901 | BQ38: 136.90218 | BR38: 137.18613 | BS38: 137.01532 | BT38: 136.80392 | BU38: 136.94293 | BV38: 136.85527 | BW38: 137.97588 | BX38: 139.55614 | BY38: 135.01758 | BZ38: 135.02678 | CA38: 139.78443
A39: Model Score | F39: 0 | G39: 0 | H39: 0 | I39: 0 | J39: 0 | K39: 0 | L39: 0 | M39: 0 | N39: 0 | O39: 0 | P39: 0 | Q39: 0 | R39: 0 | S39: 0 | T39: 0 | U39: 0 | V39: 0 | W39: 0 | X39: 0 | Y39: 0 | Z39: 0 | AA39: 0 | AB39: 0 | AC39: 0 | AD39: 0 | AE39: 0 | AF39: 0 | AG39: 0 | AH39: 0 | AI39: 0 | AJ39: 0 | AK39: 0 | AL39: 0 | AM39: 0 | AN39: 0 | AO39: 0 | AP39: 0 | AQ39: 0 | AR39: 0 | AS39: 0 | AT39: 0 | AU39: 0 | AV39: 0 | AW39: 0 | AX39: 0 | AY39: 0 | AZ39: 0 | BA39: 0 | BB39: 0 | BC39: 0 | BD39: 0 | BE39: 0 | BF39: 0 | BG39: 0 | BH39: 0 | BI39: 0 | BJ39: 0 | BK39: 0 | BL39: 0 | BM39: 0 | BN39: 0 | BO39: 0 | BP39: 0 | BQ39: 0 | BR39: 0 | BS39: 0 | BT39: 0 | BU39: 0 | BV39: 0 | BW39: 0 | BX39: 0
A40: Gross Loss Adjustments (Dealer level, high PTI, etc.) | F40: 0.26191256 | G40: 0.45378474 | H40: 0.70216268 | I40: 0.54469005 | J40: 0.63262209 | K40: 0.67397508 | L40: 0.29998557 | M40: 0.45998063 | N40: 0.2445194 | O40: -0.74262511 | P40: -0.85970184 | Q40: -1.0730841 | R40: -0.41821787 | S40: -0.43359003 | T40: -0.188365 | U40: -0.42501383 | V40: -0.38957206 | W40: -0.68408201 | X40: -0.80241223 | Y40: -0.62791517 | Z40: -0.73801772 | AA40: -0.24301438 | AB40: -0.68128769 | AC40: -0.71071464 | AD40: -0.30773601 | AE40: -0.085054457 | AF40: 0.082903834 | AG40: -0.22885202 | AH40: -0.35636695 | AI40: -1.5702718 | AJ40: -2.4411514 | AK40: -1.6950548 | AL40: -1.5097445 | AM40: -1.314571 | AN40: -1.3980934 | AO40: -1.6413346 | AP40: -1.8996952 | AQ40: -0.86004256 | AR40: -2.895401 | AS40: -1.3104587 | AT40: -1.5866155 | AU40: -1.4902306 | AV40: -0.99570189 | AW40: -1.4432413 | AX40: -4.0091704 | AY40: 0.6751703 | AZ40: -0.26889749 | BA40: 0.26834764 | BB40: -0.56872407 | BC40: -0.034062653 | BD40: 0.087236828 | BE40: 0.025692241 | BF40: -0.52823437 | BG40: -0.02500174 | BH40: -0.21881836 | BI40: -0.063765 | BJ40: 0.017679169 | BK40: -0.32115008 | BL40: -0.45485974 | BM40: -0.40369486 | BN40: -1.0617921 | BO40: 0.28904705 | BP40: 0.73509705 | BQ40: 0.79246533 | BR40: 0.45080784 | BS40: 0.28556219 | BT40: -0.010716636 | BU40: 1.8236432 | BV40: 1.9106605 | BW40: 2.0232363 | BX40: 1.1963365
A41: Recovery Adjustments excluding LTV (Mileage, vehicle type, etc.) | F41: -2.2010027 | G41: -3.064841 | H41: -3.145654 | I41: -2.9210053 | J41: -2.7289388 | K41: -2.5043996 | L41: -2.735723 | M41: -2.1909368 | N41: -2.3655618 | O41: -2.5257025 | P41: -2.3639735 | Q41: -2.5026246 | R41: -2.7062786 | S41: -2.3690859 | T41: -2.284395 | U41: -1.9223072 | V41: -1.4326136 | W41: -2.0667656 | X41: -2.2531677 | Y41: -2.3912112 | Z41: -2.3637329 | AA41: -2.1547662 | AB41: -2.2458794 | AC41: -2.4947293 | AD41: -2.8254102 | AE41: -3.2549507 | AF41: -3.2585263 | AG41: -3.3093562 | AH41: -3.2911148 | AI41: -3.2521834 | AJ41: -4.0955985 | AK41: -3.6724407 | AL41: -3.9993671 | AM41: -4.1359866 | AN41: -3.3468106 | AO41: -4.0241319 | AP41: -4.2846204 | AQ41: -4.8594688 | AR41: -3.6119126 | AS41: -2.7523195 | AT41: -4.6527462 | AU41: -4.3040903 | AV41: -3.7118964 | AW41: -3.213235 | AX41: -4.7271959 | AY41: -3.2181036 | AZ41: -3.6976892 | BA41: -3.4706992 | BB41: -3.4656042 | BC41: -3.3592617 | BD41: -3.2705077 | BE41: -3.0139747 | BF41: -2.5484283 | BG41: -2.4139635 | BH41: -2.3102368 | BI41: -0.80506699 | BJ41: 0.16853497 | BK41: 0.81722186 | BL41: 0.63490684 | BM41: 1.7234456 | BN41: 1.1601777 | BO41: -0.25299892 | BP41: 0.87555504 | BQ41: 0.77345278 | BR41: 0.095649307 | BS41: 0.7596712 | BT41: 0.21522885 | BU41: 1.1578242 | BV41: 0.88335956 | BW41: 2.3214781 | BX41: 0.31347395
A42: LTV Adjustments | F42: 2.2010027 | G42: 3.064841 | H42: 3.145654 | I42: 2.9210053 | J42: 2.7289388 | K42: 2.5043996 | L42: 2.735723 | M42: 2.1909368 | N42: 2.3655618 | O42: 2.5257025 | P42: 2.3639735 | Q42: 2.5026246 | R42: 2.7062786 | S42: 2.3690859 | T42: 2.284395 | U42: 1.9223072 | V42: 1.4326136 | W42: 2.0667656 | X42: 2.2531677 | Y42: 2.3912112 | Z42: 2.3637329 | AA42: 2.1547662 | AB42: 2.2458794 | AC42: 2.4947293 | AD42: 2.8254102 | AE42: 3.2549507 | AF42: 3.2585263 | AG42: 3.3093562 | AH42: 3.2911148 | AI42: 3.2521834 | AJ42: 4.0955985 | AK42: 3.6724407 | AL42: 3.9993671 | AM42: 4.1359866 | AN42: 3.3468106 | AO42: 4.0241319 | AP42: 4.2846204 | AQ42: 4.8594688 | AR42: 3.6119126 | AS42: 2.7523195 | AT42: 4.6527462 | AU42: 4.3040903 | AV42: 3.7118964 | AW42: 3.213235 | AX42: 4.7271959 | AY42: 3.2181036 | AZ42: 3.6976892 | BA42: 3.4706992 | BB42: 3.4656042 | BC42: 3.3592617 | BD42: 3.2705077 | BE42: 3.0139747 | BF42: 2.5484283 | BG42: 2.4139635 | BH42: 2.3102368 | BI42: 0.80506699 | BJ42: -0.16853497 | BK42: -0.81722186 | BL42: -0.63490684 | BM42: -1.7234456 | BN42: -1.1601777 | BO42: 0.25299892 | BP42: -0.87555504 | BQ42: -0.77345278 | BR42: -0.095649307 | BS42: -0.7596712 | BT42: -0.21522885 | BU42: -1.1578242 | BV42: -0.88335956 | BW42: -2.3214781 | BX42: -0.31347395
A43: RAGU Score | F43: 129.69023 | G43: 134.03255 | H43: 133.83882 | I43: 131.12001 | J43: 134.3223 | K43: 136.59151 | L43: 136.84207 | M43: 136.69043 | N43: 136.37357 | O43: 135.16455 | P43: 134.96761 | Q43: 133.50733 | R43: 134.16248 | S43: 133.68874 | T43: 133.19455 | U43: 131.78293 | V43: 131.48044 | W43: 130.76031 | X43: 129.61788 | Y43: 131.54322 | Z43: 130.12602 | AA43: 129.70366 | AB43: 129.11504 | AC43: 127.90359 | AD43: 128.44542 | AE43: 129.06289 | AF43: 129.94106 | AG43: 130.42069 | AH43: 131.39204 | AI43: 130.45659 | AJ43: 129.86494 | AK43: 130.09641 | AL43: 129.67632 | AM43: 129.25969 | AN43: 129.89532 | AO43: 130.3002 | AP43: 130.18463 | AQ43: 131.76735 | AR43: 130.23769 | AS43: 132.56947 | AT43: 132.5188 | AU43: 131.05477 | AV43: 131.38619 | AW43: 132.73152 | AX43: 131.02764 | AY43: 136.57868 | AZ43: 135.86095 | BA43: 136.41216 | BB43: 135.64565 | BC43: 136.52465 | BD43: 136.92762 | BE43: 137.24735 | BF43: 136.24561 | BG43: 136.57533 | BH43: 136.46877 | BI43: 135.4456 | BJ43: 134.77873 | BK43: 134.23786 | BL43: 133.90307 | BM43: 133.6215 | BN43: 133.94649 | BO43: 136.3866 | BP43: 137.12519 | BQ43: 137.69464 | BR43: 137.63694 | BS43: 137.30088 | BT43: 136.79321 | BU43: 138.76657 | BV43: 138.76593 | BW43: 139.99911 | BX43: 140.75248
A44: LTV | F44: 1.5537501 | G44: 1.4852944 | H44: 1.4261913 | I44: 1.4354772 | J44: 1.4822937 | K44: 1.422657 | L44: 1.282801 | M44: 1.2352951 | N44: 1.2857046 | O44: 1.3461806 | P44: 1.3839235 | Q44: 1.3796447 | R44: 1.3980221 | S44: 1.4080678 | T44: 1.3181376 | U44: 1.2616639 | V44: 1.2630405 | W44: 1.2571646 | X44: 1.2996829 | Y44: 1.3501028 | Z44: 1.3724563 | AA44: 1.3696664 | AB44: 1.353455 | AC44: 1.3976519 | AD44: 1.382371 | AE44: 1.3940531 | AF44: 1.3892161 | AG44: 1.3796954 | AH44: 1.3503958 | AI44: 1.2630238 | AJ44: 1.2689376 | AK44: 1.2983418 | AL44: 1.3032818 | AM44: 1.3110727 | AN44: 1.3663849 | AO44: 1.372769 | AP44: 1.3521455 | AQ44: 1.3496457 | AR44: 1.5397835 | AS44: 1.6333402 | AT44: 1.298042 | AU44: 1.3006578 | AV44: 1.2911028 | AW44: 1.2305745 | AX44: 1.2826559 | AY44: 1.3274923 | AZ44: 1.3654909 | BA44: 1.3091644 | BB44: 1.288656 | BC44: 1.2973333 | BD44: 1.3034826 | BE44: 1.3099805 | BF44: 1.3267889 | BG44: 1.3090282 | BH44: 1.2974924 | BI44: 1.3547199 | BJ44: 1.3666321 | BK44: 1.3435173 | BL44: 1.3464264 | BM44: 1.3340837 | BN44: 1.311378 | BO44: 1.3019144 | BP44: 1.2983427 | BQ44: 1.310002 | BR44: 1.2933876 | BS44: 1.3049158 | BT44: 1.3071323 | BU44: 1.2917671 | BV44: 1.3108335 | BW44: 1.3258543 | BX44: 1.3207742
A46: nonKMXENT | B46: 2016 | C46: 2017 | D46: 2018 | E46: 2019 | F46: 2020 M01 | G46: 2020 M02 | H46: 2020 M03 | I46: 2020 M04 | J46: 2020 M05 | K46: 2020 M06 | L46: 2020 M07 | M46: 2020 M08 | N46: 2020 M09 | O46: 2020 M10 | P46: 2020 M11 | Q46: 2020 M12 | R46: 2021 M01 | S46: 2021 M02 | T46: 2021 M03 | U46: 2021 M04 | V46: 2021 M05 | W46: 2021 M06 | X46: 2021 M07 | Y46: 2021 M08 | Z46: 2021 M09 | AA46: 2021 M10 | AB46: 2021 M11 | AC46: 2021 M12 | AD46: 2022 M01 | AE46: 2022 M02 | AF46: 2022 M03 | AG46: 2022 M04 | AH46: 2022 M05 | AI46: 2022 M06 | AJ46: 2022 M07 | AK46: 2022 M08 | AL46: 2022 M09 | AM46: 2022 M10 | AN46: 2022 M11 | AO46: 2022 M12 | AP46: 2023 M01 | AQ46: 2023 M02 | AR46: 2023 M03 | AS46: 2023 M04 | AT46: 2023 M05 | AU46: 2023 M06 | AV46: 2023 M07 | AW46: 2023 M08 | AX46: 2023 M09 | AY46: 2023 M10 | AZ46: 2023 M11 | BA46: 2023 M12 | BB46: 2024 M01 | BC46: 2024 M02 | BD46: 2024 M03 | BE46: 2024 M04 | BF46: 2024 M05 | BG46: 2024 M06 | BH46: 2024 M07 | BI46: 2024 M08 | BJ46: 2024 M09 | BK46: 2024 M10 | BL46: 2024 M11 | BM46: 2024 M12 | BN46: 2025 M01 | BO46: 2025 M02 | BP46: 2025 M03 | BQ46: 2025 M04 | BR46: 2025 M05 | BS46: 2025 M06 | BT46: 2025 M07 | BU46: 2025 M08 | BV46: 2025 M09 | BW46: 2025 M10 | BX46: 2025 M11 | BY46: 2025 M12 | BZ46: 2026 M01
A47: Contract Model Score | B47: 130.11158 | C47: 132.58721 | D47: 132.51957 | E47: 130.52624 | F47: 130.81177 | G47: 131.22817 | H47: 130.7757 | I47: 131.22612 | J47: 133.84373 | K47: 134.88885 | L47: 135.27071 | M47: 135.5069 | N47: 135.21012 | O47: 134.96814 | P47: 134.44184 | Q47: 135.62832 | R47: 135.75244 | S47: 135.37415 | T47: 135.13442 | U47: 135.4241 | V47: 135.59643 | W47: 135.26407 | X47: 134.74909 | Y47: 136.01685 | Z47: 134.64288 | AA47: 134.7203 | AB47: 132.74586 | AC47: 133.28021 | AD47: 134.15842 | AE47: 134.03079 | AF47: 134.4357 | AG47: 135.84631 | AH47: 136.74788 | AI47: 137.12473 | AJ47: 137.29008 | AK47: 137.43528 | AL47: 137.31444 | AM47: 137.65428 | AN47: 139.51001 | AO47: 139.24031 | AP47: 139.80431 | AQ47: 139.64378 | AR47: 139.15431 | AS47: 138.8767 | AT47: 138.79351 | AU47: 138.60873 | AV47: 137.85409 | AW47: 139.07422 | AX47: 139.50883 | AY47: 139.08714 | AZ47: 138.02994 | BA47: 137.97008 | BB47: 138.101 | BC47: 137.79132 | BD47: 137.14763 | BE47: 138.32927 | BF47: 138.79947 | BG47: 139.23287 | BH47: 139.61094 | BI47: 140.47913 | BJ47: 140.31903 | BK47: 139.36043 | BL47: 138.46656 | BM47: 138.01333 | BN47: 138.10769 | BO47: 138.2144 | BP47: 138.11228 | BQ47: 138.85022 | BR47: 139.3942 | BS47: 139.48226 | BT47: 139.65962 | BU47: 139.31728 | BV47: 139.85819 | BW47: 140.01767 | BX47: 140.18972 | BY47: 141.51071 | BZ47: 141.87881 | CA47: 141.97034
A48: Model Score | B48: 0.14476272 | C48: 0.094604642 | D48: 0.031815879 | E48: 0.0062374264 | F48: -0.004273285 | G48: 0.0027114611 | H48: -0.0049884992 | I48: -0.00030313823 | J48: -0.0019177329 | K48: 0.0037951115 | L48: 0.0055458507 | M48: -0.00086868553 | N48: -0.00032506095 | O48: 0.010304222 | P48: -0.0019705042 | Q48: 0.0023404144 | R48: 0.00070014254 | S48: 0.0012397096 | T48: 0.00048403908 | U48: 0.0013413238 | V48: -0.0022883767 | W48: 0.0026789797 | X48: 0.0017501801 | Y48: 0.0019554345 | Z48: 0.0025118232 | AA48: 0.0033799321 | AB48: 0.00099183964 | AC48: -0.0090160291 | AD48: 0.00017069218 | AE48: -0.0015788161 | AF48: -0.00054191281 | AG48: -0.0029653818 | AH48: 0.10084966 | AI48: 0.0645025 | AJ48: 0.079440931 | AK48: -0.25567715 | AL48: 0.056911969 | AM48: 0.036335264 | AN48: -0.13786187 | AO48: 0.2886953 | AP48: 0.3494827 | AQ48: 0.055655636 | AR48: -0.62353493 | AS48: 0.61782686 | AT48: 0.36228113 | AU48: 0.026328754 | AV48: -0.25139716 | AW48: -0.47229628 | AX48: 0.030063086 | BA48: 0.13618425 | BB48: -0.00041178368 | BC48: 0.012449756 | BD48: 0.013866805 | BE48: 0.03016562 | BF48: -0.12478032 | BG48: -0.13800336 | BH48: -0.039322604 | BI48: 0.054199487 | BJ48: -0.10636721 | BK48: -0.16839051 | BL48: -0.13821339 | BM48: -0.060311142 | BN48: -0.13116356 | BO48: -0.11393004 | BP48: -0.11995584 | BQ48: -0.1186818 | BR48: -0.16330905 | BS48: -0.20205604 | BT48: -0.13658555 | BU48: -0.10314193 | BV48: -0.16239464 | BW48: -0.35964456 | BX48: -0.2281356 | BY48: -0.10844235 | BZ48: -0.2162096
A49: Gross Loss Adjustments (Dealer level, high PTI, etc.) | B49: 0.54106738 | C49: 0.95399385 | D49: 0.95829457 | E49: 0.99127311 | F49: 0.39341938 | G49: 0.41206449 | H49: 0.56956768 | I49: 0.50413967 | J49: 0.75000197 | K49: 0.66014367 | L49: 0.52997106 | M49: 0.5500763 | N49: 0.53776149 | O49: 0.52663529 | P49: 0.57274775 | Q49: 0.74399677 | R49: 1.1591992 | S49: 1.3021865 | T49: 1.319676 | U49: 1.2648884 | V49: 1.2383063 | W49: 0.95972642 | X49: 0.82546642 | Y49: 1.0510215 | Z49: 0.9174564 | AA49: 0.62150983 | AB49: 0.52834602 | AC49: 0.49129216 | AD49: 0.17852273 | AE49: 0.45973531 | AF49: 0.49765715 | AG49: 0.70533925 | AH49: 0.98012223 | AI49: 1.0042598 | AJ49: 0.43965161 | AK49: 0.39676887 | AL49: 0.62856946 | AM49: -0.58104008 | AN49: 1.4274611 | AO49: 0.1946444 | AP49: 1.313816 | AQ49: 0.0069911485 | AR49: 0.36245704 | AS49: -0.70636074 | AT49: 0.59355849 | AU49: -0.052008648 | AV49: -0.28017543 | AW49: 1.7357854 | AX49: -3.2408956 | BA49: 0.54480246 | BB49: 0.91481517 | BC49: 0.20836612 | BD49: 0.49622137 | BE49: 1.1329154 | BF49: 1.5240835 | BG49: 1.4183922 | BH49: 1.4294911 | BI49: 1.5178753 | BJ49: 1.6278882 | BK49: 1.5736964 | BL49: 1.6225803 | BM49: 1.0364312 | BN49: 1.533767 | BO49: 1.4288764 | BP49: 1.2598956 | BQ49: 1.6210639 | BR49: 1.5983496 | BS49: 2.3514024 | BT49: 2.042927 | BU49: 2.0602206 | BV49: 2.5672853 | BW49: 2.4659569 | BX49: 2.6896289 | BY49: 3.0666606 | BZ49: 2.2178739
A50: Recovery Adjustments excluding LTV (Mileage, vehicle type, etc.) | B50: -0.45776292 | C50: 0.31142589 | D50: 0.24836889 | E50: 0.047635528 | F50: 0.0062184779 | G50: -0.045274639 | H50: -0.36406325 | I50: -0.37978988 | J50: -0.3645404 | K50: -0.29693159 | L50: -0.34936085 | M50: 0.01282863 | N50: 0.13715416 | O50: 0.26948707 | P50: 0.20731864 | Q50: 0.76585671 | R50: 0.6413431 | S50: 0.27924393 | T50: -0.023469864 | U50: 0.10197871 | V50: 0.0097643389 | W50: 0.14381124 | X50: -0.076501212 | Y50: -0.28501135 | Z50: -0.15958456 | AA50: -0.60043191 | AB50: -0.69959874 | AC50: -0.66501553 | AD50: -0.69808798 | AE50: -0.94949219 | AF50: -1.5721426 | AG50: -1.3255121 | AH50: -0.90783052 | AI50: -1.8305466 | AJ50: -1.9324866 | AK50: -1.6382731 | AL50: -2.4225989 | AM50: 0.83951731 | AN50: -0.53095658 | AO50: -2.1984223 | AP50: -1.595606 | AQ50: -2.0152072 | AR50: -1.331797 | AS50: -4.2438904 | AT50: -1.9234109 | AU50: -2.3365271 | AV50: -2.1470546 | AW50: -0.35994009 | AX50: -3.6376334 | BA50: -1.4193733 | BB50: -1.4212139 | BC50: -0.90263636 | BD50: -1.663014 | BE50: -1.6326958 | BF50: -0.93064387 | BG50: -1.0901967 | BH50: -0.3030227 | BI50: -0.92297594 | BJ50: -0.56209108 | BK50: -0.52749202 | BL50: -0.14207201 | BM50: 1.5936887 | BN50: 0.88394835 | BO50: 0.75917235 | BP50: 0.0053041238 | BQ50: 0.41781171 | BR50: 0.20779235 | BS50: -0.1711225 | BT50: 0.85958903 | BU50: 0.36967561 | BV50: 1.14261 | BW50: 1.2030153 | BX50: 1.4440283 | BY50: 1.6415558 | BZ50: 1.8581001
A51: LTV Adjustments | B51: 0.45776292 | C51: -0.31142589 | D51: -0.24836889 | E51: -0.047635528 | F51: -0.0062184779 | G51: 0.045274639 | H51: 0.36406325 | I51: 0.37978988 | J51: 0.3645404 | K51: 0.29693159 | L51: 0.34936085 | M51: -0.01282863 | N51: -0.13715416 | O51: -0.26948707 | P51: -0.20731864 | Q51: -0.76585671 | R51: -0.6413431 | S51: -0.27924393 | T51: 0.023469864 | U51: -0.10197871 | V51: -0.0097643389 | W51: -0.14381124 | X51: 0.076501212 | Y51: 0.28501135 | Z51: 0.15958456 | AA51: 0.60043191 | AB51: 0.69959874 | AC51: 0.66501553 | AD51: 0.69808798 | AE51: 0.94949219 | AF51: 1.5721426 | AG51: 1.3255121 | AH51: 0.90783052 | AI51: 1.8305466 | AJ51: 1.9324866 | AK51: 1.6382731 | AL51: 2.4225989 | AM51: -0.83951731 | AN51: 0.53095658 | AO51: 2.1984223 | AP51: 1.595606 | AQ51: 2.0152072 | AR51: 1.331797 | AS51: 4.2438904 | AT51: 1.9234109 | AU51: 2.3365271 | AV51: 2.1470546 | AW51: 0.35994009 | AX51: 3.6376334 | BA51: 1.4193733 | BB51: 1.4212139 | BC51: 0.90263636 | BD51: 1.663014 | BE51: 1.6326958 | BF51: 0.93064387 | BG51: 1.0901967 | BH51: 0.3030227 | BI51: 0.92297594 | BJ51: 0.56209108 | BK51: 0.52749202 | BL51: 0.14207201 | BM51: -1.5936887 | BN51: -0.88394835 | BO51: -0.75917235 | BP51: -0.0053041238 | BQ51: -0.41781171 | BR51: -0.20779235 | BS51: 0.1711225 | BT51: -0.85958903 | BU51: -0.36967561 | BV51: -1.14261 | BW51: -1.2030153 | BX51: -1.4440283 | BY51: -1.6415558 | BZ51: -1.8581001
A52: RAGU Score | B52: 130.79741 | C52: 133.63581 | D52: 133.50969 | E52: 131.52375 | F52: 131.20092 | G52: 131.64295 | H52: 131.34028 | I52: 131.72995 | J52: 134.59181 | K52: 135.55278 | L52: 135.80623 | M52: 136.05611 | N52: 135.74756 | O52: 135.50507 | P52: 135.01262 | Q52: 136.37465 | R52: 136.91234 | S52: 136.67757 | T52: 136.45458 | U52: 136.69033 | V52: 136.83244 | W52: 136.22648 | X52: 135.57631 | Y52: 137.06983 | Z52: 135.56285 | AA52: 135.34519 | AB52: 133.2752 | AC52: 133.76248 | AD52: 134.33711 | AE52: 134.48894 | AF52: 134.93281 | AG52: 136.54869 | AH52: 137.82885 | AI52: 138.19349 | AJ52: 137.80918 | AK52: 137.57637 | AL52: 137.99993 | AM52: 137.10958 | AN52: 140.79961 | AO52: 139.72365 | AP52: 141.46761 | AQ52: 139.70643 | AR52: 138.89323 | AS52: 138.78816 | AT52: 139.74935 | AU52: 138.58305 | AV52: 137.32252 | AW52: 140.33771 | AX52: 136.298 | BA52: 138.65107 | BB52: 139.01541 | BC52: 138.01213 | BD52: 137.65771 | BE52: 139.49235 | BF52: 140.19877 | BG52: 140.51326 | BH52: 141.0011 | BI52: 142.0512 | BJ52: 141.84055 | BK52: 140.76574 | BL52: 139.95093 | BM52: 138.98945 | BN52: 139.51029 | BO52: 139.52935 | BP52: 139.25222 | BQ52: 140.3526 | BR52: 140.82924 | BS52: 141.6316 | BT52: 141.56596 | BU52: 141.27436 | BV52: 142.26308 | BW52: 142.12398 | BX52: 142.65121 | BY52: 144.46893 | BZ52: 143.88048
A53: LTV | B53: 1.9870302 | C53: 1.934546 | D53: 1.9519636 | E53: 1.9473727 | F53: 1.9289789 | G53: 1.9279253 | H53: 1.8659757 | I53: 1.9375063 | J53: 1.970304 | K53: 1.8891437 | L53: 1.7534724 | M53: 1.7254995 | N53: 1.7282895 | O53: 1.777961 | P53: 1.8785444 | Q53: 1.7560091 | R53: 1.7802242 | S53: 1.7027629 | T53: 1.6130473 | U53: 1.5336502 | V53: 1.4661384 | W53: 1.4849166 | X53: 1.5043845 | Y53: 1.5583721 | Z53: 1.6062173 | AA53: 1.585044 | AB53: 1.6231152 | AC53: 1.604914 | AD53: 1.5836633 | AE53: 1.5825251 | AF53: 1.5799601 | AG53: 1.5858631 | AH53: 1.76803 | AI53: 1.7161175 | AJ53: 1.7525306 | AK53: 1.7377475 | AL53: 1.69742 | AM53: 1.5467172 | AN53: 1.5610306 | AO53: 1.6871451 | AP53: 1.5354216 | AQ53: 1.4906534 | AR53: 1.7456093 | AS53: 3.7253999 | AT53: 1.8994128 | AU53: 1.5193059 | AV53: 1.7475154 | AW53: 1.6291949 | AX53: 1.7829605 | BA53: 1.5969438 | BB53: 1.5466571 | BC53: 1.516746 | BD53: 1.5166211 | BE53: 1.5436168 | BF53: 1.4961382 | BG53: 1.4758396 | BH53: 1.4709149 | BI53: 1.5164949 | BJ53: 1.501475 | BK53: 1.5292281 | BL53: 1.4670664 | BM53: 1.4778264 | BN53: 1.4618771 | BO53: 1.4782105 | BP53: 1.4757603 | BQ53: 1.4661906 | BR53: 1.4149518 | BS53: 1.4042974 | BT53: 1.4474645 | BU53: 1.427688 | BV53: 1.4255718 | BW53: 1.3902727 | BX53: 1.4263932 | BY53: 1.4277896 | BZ53: 1.4949398
A55: KMX | B55: 2016 | C55: 2017 | D55: 2018 | E55: 2019 | F55: 2020 M01 | G55: 2020 M02 | H55: 2020 M03 | I55: 2020 M04 | J55: 2020 M05 | K55: 2020 M06 | L55: 2020 M07 | M55: 2020 M08 | N55: 2020 M09 | O55: 2020 M10 | P55: 2020 M11 | Q55: 2020 M12 | R55: 2021 M01 | S55: 2021 M02 | T55: 2021 M03 | U55: 2021 M04 | V55: 2021 M05 | W55: 2021 M06 | X55: 2021 M07 | Y55: 2021 M08 | Z55: 2021 M09 | AA55: 2021 M10 | AB55: 2021 M11 | AC55: 2021 M12 | AD55: 2022 M01 | AE55: 2022 M02 | AF55: 2022 M03 | AG55: 2022 M04 | AH55: 2022 M05 | AI55: 2022 M06 | AJ55: 2022 M07 | AK55: 2022 M08 | AL55: 2022 M09 | AM55: 2022 M10 | AN55: 2022 M11 | AO55: 2022 M12 | AP55: 2023 M01 | AQ55: 2023 M02 | AR55: 2023 M03 | AS55: 2023 M04 | AT55: 2023 M05 | AU55: 2023 M06 | AV55: 2023 M07 | AW55: 2023 M08 | AX55: 2023 M09 | AY55: 2023 M10 | AZ55: 2023 M11 | BA55: 2023 M12 | BB55: 2024 M01 | BC55: 2024 M02 | BD55: 2024 M03 | BE55: 2024 M04 | BF55: 2024 M05 | BG55: 2024 M06 | BH55: 2024 M07 | BI55: 2024 M08 | BJ55: 2024 M09 | BK55: 2024 M10 | BL55: 2024 M11 | BM55: 2024 M12 | BN55: 2025 M01 | BO55: 2025 M02 | BP55: 2025 M03 | BQ55: 2025 M04 | BR55: 2025 M05 | BS55: 2025 M06 | BT55: 2025 M07 | BU55: 2025 M08 | BV55: 2025 M09 | BW55: 2025 M10 | BX55: 2025 M11 | BY55: 2025 M12 | BZ55: 2026 M01
A56: Contract Model Score | B56: 136.58958 | C56: 139.09048 | D56: 137.77552 | E56: 136.87433 | F56: 136.07089 | G56: 136.072 | H56: 135.58403 | I56: 136.45711 | J56: 138.39856 | K56: 139.22263 | L56: 139.32036 | M56: 138.63708 | N56: 138.2905 | O56: 137.41781 | P56: 136.54466 | Q56: 136.92165 | R56: 136.31498 | S56: 135.27484 | T56: 135.16676 | U56: 135.82853 | V56: 135.82742 | W56: 135.5271 | X56: 133.76711 | Y56: 136.00476 | Z56: 133.7143 | AA56: 133.8042 | AB56: 133.04636 | AC56: 132.61153 | AD56: 132.07594 | AE56: 133.41692 | AF56: 133.82905 | AG56: 134.7299 | AH56: 134.34079 | AI56: 135.09973 | AJ56: 135.80114 | AK56: 136.29285 | AL56: 136.07444 | AM56: 137.27668 | AN56: 138.63281 | AO56: 139.28278 | AP56: 140.36935 | AQ56: 139.82238 | AR56: 140.14739 | AS56: 140.44521 | AT56: 140.7383 | AU56: 140.77704 | AV56: 140.66729 | AW56: 140.6335 | AX56: 140.22049 | AY56: 140.06891 | AZ56: 140.93026 | BA56: 140.84393 | BB56: 140.36274 | BC56: 138.53458 | BD56: 140.07862 | BE56: 140.5561 | BF56: 140.57663 | BG56: 140.14334 | BH56: 139.7155 | BI56: 139.73364 | BJ56: 140.27603 | BK56: 140.20095 | BL56: 139.56669 | BM56: 139.57157 | BN56: 139.95679 | BO56: 139.57119 | BP56: 139.68386 | BQ56: 139.80946 | BR56: 139.77613 | BS56: 140.02729 | BT56: 140.13278 | BU56: 139.79082 | BV56: 139.84377 | BW56: 140.21965 | BX56: 140.76906 | BY56: 141.84195 | BZ56: 141.71918 | CA56: 141.39322
A57: Model Score | B57: 0 | C57: 0 | D57: 0 | E57: 0 | F57: 0 | G57: 0 | H57: 0 | I57: 0 | J57: 0 | K57: 0 | L57: 0 | M57: 0 | N57: 0 | O57: 0 | P57: 0 | Q57: 0 | R57: 0 | S57: 0 | T57: 0 | U57: 0 | V57: 0 | W57: 0 | X57: 0 | Y57: 0 | Z57: 0 | AA57: 0 | AB57: 0 | AC57: 0 | AD57: 0 | AF57: 0 | AG57: 0 | AH57: 0 | AI57: 0 | AJ57: 0 | AK57: 0 | AL57: 0 | AM57: 0 | AN57: 0 | AO57: 0 | AP57: 0 | AQ57: 0 | AR57: 0 | AS57: 0 | AT57: 0 | AU57: 0 | AV57: 0 | AW57: 0 | BA57: 0 | BB57: 0 | BC57: 0 | BD57: 0 | BE57: 0 | BF57: 0 | BG57: 0 | BH57: 0 | BI57: 0 | BJ57: 0 | BK57: 0 | BL57: 0 | BM57: 0 | BN57: 0 | BO57: 0 | BP57: 0 | BQ57: 0 | BR57: 0 | BS57: 0 | BT57: 0 | BU57: 0 | BV57: 0 | BW57: 0 | BX57: 0 | BY57: 0 | BZ57: 0
A58: Gross Loss Adjustments (Dealer level, high PTI, etc.) | B58: 4.6948977 | C58: 4.6240718 | D58: 4.4679388 | E58: 4.4875446 | F58: 4.439349 | G58: 4.3909115 | H58: 4.417525 | I58: 4.3963414 | J58: 4.4150991 | K58: 4.489529 | L58: 4.3649482 | M58: 4.1750586 | N58: 4.222411 | O58: 4.1560834 | P58: 3.9417534 | Q58: 3.8078992 | R58: 3.7723651 | S58: 3.878751 | T58: 3.8049339 | U58: 3.6318648 | V58: 3.5382747 | W58: 3.551671 | X58: 3.5906339 | Y58: 3.4163915 | Z58: 3.3571345 | AA58: 3.3111685 | AB58: 3.0517679 | AC58: 3.1421464 | AD58: 3.1106299 | AF58: 2.91603 | AG58: 2.870262 | AH58: 2.7549446 | AI58: 2.7133909 | AJ58: 2.3203969 | AK58: 2.6651173 | AL58: 2.2379048 | AM58: 2.7579948 | AN58: 2.4869358 | AO58: 2.8366352 | AP58: 3.1507727 | AQ58: 3.1472568 | AR58: 2.6576857 | AS58: 2.9482811 | AT58: 3.137575 | AU58: 3.2272892 | AV58: 2.8773265 | AW58: 3.0175103 | BA58: 4.3705019 | BB58: 4.0339478 | BC58: 4.130711 | BD58: 4.5155794 | BE58: 4.8670008 | BF58: 4.9564759 | BG58: 4.9643881 | BH58: 4.9283692 | BI58: 4.72125 | BJ58: 4.8437008 | BK58: 4.6746477 | BL58: 3.9847392 | BM58: 3.3904832 | BN58: 2.7176926 | BO58: 2.3912605 | BP58: 2.3749626 | BQ58: 2.9516086 | BR58: 3.7668745 | BS58: 4.2575859 | BT58: 4.4189414 | BU58: 3.4866714 | BV58: 3.7838202 | BW58: 4.0321297 | BX58: 3.6710029 | BY58: 4.8405102 | BZ58: 4.5710958
A59: Recovery Adjustments excluding LTV (Mileage, vehicle type, etc.) | B59: -1.5995484 | C59: -2.6365864 | D59: -2.6047163 | E59: -2.6305795 | F59: -2.9917081 | G59: -3.1604236 | H59: -3.1244193 | I59: -2.8220275 | J59: -2.8685939 | K59: -2.7294222 | L59: -2.9871899 | M59: -3.2546835 | N59: -3.168427 | O59: -3.049643 | P59: -2.7500498 | Q59: -2.6780095 | R59: -2.8632051 | S59: -2.6565294 | T59: -2.6099693 | U59: -2.5631869 | V59: -2.5856648 | W59: -2.0669936 | X59: -1.6463622 | Y59: -1.7060108 | Z59: -1.7892201 | AA59: -2.2289025 | AB59: -2.5760979 | AC59: -2.4581158 | AD59: -2.5236664 | AF59: -2.6470178 | AG59: -2.9307624 | AH59: -2.8847397 | AI59: -3.0004066 | AJ59: -2.8525928 | AK59: -3.8742436 | AL59: -3.4019685 | AM59: -3.9072047 | AN59: -3.7844785 | AO59: -3.437491 | AP59: -4.0748236 | AQ59: -4.5018318 | AR59: -4.4288704 | AS59: -4.1277958 | AT59: -3.8583138 | AU59: -3.5690085 | AV59: -3.7938056 | AW59: -4.5744284 | BA59: -3.638568 | BB59: -2.8794899 | BC59: -3.6375243 | BD59: -3.4758261 | BE59: -3.2869607 | BF59: -3.3510287 | BG59: -3.5204617 | BH59: -3.7219905 | BI59: -3.8399459 | BJ59: -3.9577946 | BK59: -4.0314844 | BL59: -3.8574369 | BM59: -4.0889143 | BN59: -3.9243157 | BO59: -3.9226033 | BP59: -3.7719354 | BQ59: -3.5120349 | BR59: -3.3265764 | BS59: -3.1010435 | BT59: -3.3070074 | BU59: -3.0384954 | BV59: -3.1204724 | BW59: -2.5316705 | BX59: -3.2264076 | BY59: -2.1794629 | BZ59: -2.8669072
A60: LTV Adjustments | B60: 1.5995484 | C60: 2.6365864 | D60: 2.6047163 | E60: 2.6305795 | F60: 2.9917081 | G60: 3.1604236 | H60: 3.1244193 | I60: 2.8220275 | J60: 2.8685939 | K60: 2.7294222 | L60: 2.9871899 | M60: 3.2546835 | N60: 3.168427 | O60: 3.049643 | P60: 2.7500498 | Q60: 2.6780095 | R60: 2.8632051 | S60: 2.6565294 | T60: 2.6099693 | U60: 2.5631869 | V60: 2.5856648 | W60: 2.0669936 | X60: 1.6463622 | Y60: 1.7060108 | Z60: 1.7892201 | AA60: 2.2289025 | AB60: 2.5760979 | AC60: 2.4581158 | AD60: 2.5236664 | AF60: 2.6470178 | AG60: 2.9307624 | AH60: 2.8847397 | AI60: 3.0004066 | AJ60: 2.8525928 | AK60: 3.8742436 | AL60: 3.4019685 | AM60: 3.9072047 | AN60: 3.7844785 | AO60: 3.437491 | AP60: 4.0748236 | AQ60: 4.5018318 | AR60: 4.4288704 | AS60: 4.1277958 | AT60: 3.8583138 | AU60: 3.5690085 | AV60: 3.7938056 | AW60: 4.5744284 | BA60: 3.638568 | BB60: 2.8794899 | BC60: 3.6375243 | BD60: 3.4758261 | BE60: 3.2869607 | BF60: 3.3510287 | BG60: 3.5204617 | BH60: 3.7219905 | BI60: 3.8399459 | BJ60: 3.9577946 | BK60: 4.0314844 | BL60: 3.8574369 | BM60: 4.0889143 | BN60: 3.9243157 | BO60: 3.9226033 | BP60: 3.7719354 | BQ60: 3.5120349 | BR60: 3.3265764 | BS60: 3.1010435 | BT60: 3.3070074 | BU60: 3.0384954 | BV60: 3.1204724 | BW60: 2.5316705 | BX60: 3.2264076 | BY60: 2.1794629 | BZ60: 2.8669072
A61: RAGU Score | B61: 141.28448 | C61: 143.71455 | D61: 142.24346 | E61: 141.36188 | F61: 140.51024 | G61: 140.46291 | H61: 140.00155 | I61: 140.85345 | J61: 142.81366 | K61: 143.71216 | L61: 143.68531 | M61: 142.81213 | N61: 142.51291 | O61: 141.57389 | P61: 140.48641 | Q61: 140.72955 | R61: 140.08735 | S61: 139.15359 | T61: 138.97169 | U61: 139.46039 | V61: 139.3657 | W61: 139.07877 | X61: 137.35774 | Y61: 139.42115 | Z61: 137.07144 | AA61: 137.11537 | AB61: 136.09813 | AC61: 135.75367 | AD61: 135.18657 | AF61: 136.74508 | AG61: 137.60016 | AH61: 137.09573 | AI61: 137.81312 | AJ61: 138.12154 | AK61: 138.95797 | AL61: 138.31234 | AM61: 140.03467 | AN61: 141.11975 | AO61: 142.11942 | AP61: 143.52012 | AQ61: 142.96964 | AR61: 142.80508 | AS61: 143.39349 | AT61: 143.87587 | AU61: 144.00433 | AV61: 143.54462 | AW61: 143.65101 | BA61: 145.21444 | BB61: 144.39669 | BC61: 142.6653 | BD61: 144.5942 | BE61: 145.4231 | BF61: 145.5331 | BG61: 145.10772 | BH61: 144.64386 | BI61: 144.45489 | BJ61: 145.11973 | BK61: 144.8756 | BL61: 143.55143 | BM61: 142.96206 | BN61: 142.67449 | BO61: 141.96245 | BP61: 142.05882 | BQ61: 142.76107 | BR61: 143.54301 | BS61: 144.28487 | BT61: 144.55172 | BU61: 143.27749 | BV61: 143.62759 | BW61: 144.25178 | BX61: 144.44006 | BY61: 146.68246 | BZ61: 146.29028
A62: LTV | B62: 1.586932 | C62: 1.5718898 | D62: 1.5856332 | E62: 1.6092026 | F62: 1.7425852 | G62: 1.7069369 | H62: 1.6754506 | I62: 1.7505561 | J62: 1.7656216 | K62: 1.7085887 | L62: 1.6026613 | M62: 1.5486625 | N62: 1.5876728 | O62: 1.6719209 | P62: 1.7363212 | Q62: 1.7560464 | R62: 1.7265693 | S62: 1.6406435 | T62: 1.4813918 | U62: 1.4353197 | V62: 1.4283305 | W62: 1.4261179 | X62: 1.4542289 | Y62: 1.5011774 | Z62: 1.4862306 | AA62: 1.4816821 | AB62: 1.4951538 | AC62: 1.4991583 | AD62: 1.6369291 | AF62: 1.5101903 | AG62: 1.563685 | AH62: 1.658791 | AI62: 1.6331301 | AJ62: 1.5946109 | AK62: 1.6928886 | AL62: 1.707081 | AM62: 1.7415007 | AN62: 1.7928601 | AO62: 1.7936274 | AP62: 1.8338607 | AQ62: 1.7686176 | AR62: 1.8303153 | AS62: 1.8232192 | AT62: 1.6709909 | AU62: 1.7887788 | AV62: 2.0258206 | AW62: 1.8024835 | BA62: 1.9504069 | BB62: 1.8985264 | BC62: 1.9781912 | BD62: 1.7214237 | BE62: 1.6827328 | BF62: 1.6006441 | BG62: 1.6079871 | BH62: 1.6956433 | BI62: 1.6379446 | BJ62: 1.6577445 | BK62: 1.6493316 | BL62: 1.6868003 | BM62: 1.6628693 | BN62: 1.6839021 | BO62: 1.5908455 | BP62: 1.6000569 | BQ62: 1.57447 | BR62: 1.5895239 | BS62: 1.6026301 | BT62: 1.5476448 | BU62: 1.5745336 | BV62: 1.6150981 | BW62: 1.6092213 | BX62: 1.559777 | BY62: 1.5040949 | BZ62: 1.4876446
A64: POS | B64: 2016 | C64: 2017 | D64: 2018 | E64: 2019 | F64: 2020 M01 | G64: 2020 M02 | H64: 2020 M03 | I64: 2020 M04 | J64: 2020 M05 | K64: 2020 M06 | L64: 2020 M07 | M64: 2020 M08 | N64: 2020 M09 | O64: 2020 M10 | P64: 2020 M11 | Q64: 2020 M12 | R64: 2021 M01 | S64: 2021 M02 | T64: 2021 M03 | U64: 2021 M04 | V64: 2021 M05 | W64: 2021 M06 | X64: 2021 M07 | Y64: 2021 M08 | Z64: 2021 M09 | AA64: 2021 M10 | AB64: 2021 M11 | AC64: 2021 M12 | AD64: 2022 M01 | AE64: 2022 M02 | AF64: 2022 M03 | AG64: 2022 M04 | AH64: 2022 M05 | AI64: 2022 M06 | AJ64: 2022 M07 | AK64: 2022 M08 | AL64: 2022 M09 | AM64: 2022 M10 | AN64: 2022 M11 | AO64: 2022 M12 | AP64: 2023 M01 | AQ64: 2023 M02 | AR64: 2023 M03 | AS64: 2023 M04 | AT64: 2023 M05 | AU64: 2023 M06 | AV64: 2023 M07 | AW64: 2023 M08 | AX64: 2023 M09 | AY64: 2023 M10 | AZ64: 2023 M11 | BA64: 2023 M12 | BB64: 2024 M01 | BC64: 2024 M02 | BD64: 2024 M03 | BE64: 2024 M04 | BF64: 2024 M05 | BG64: 2024 M06 | BH64: 2024 M07 | BI64: 2024 M08 | BJ64: 2024 M09 | BK64: 2024 M10 | BL64: 2024 M11 | BM64: 2024 M12 | BN64: 2025 M01 | BO64: 2025 M02 | BP64: 2025 M03 | BQ64: 2025 M04 | BR64: 2025 M05 | BS64: 2025 M06 | BT64: 2025 M07 | BU64: 2025 M08 | BV64: 2025 M09 | BW64: 2025 M10 | BX64: 2025 M11 | BY64: 2025 M12 | BZ64: 2026 M01
A65: Contract Model Score | B65: 133.97026 | C65: 137.08805 | D65: 136.17768 | E65: 135.22403 | F65: 134.05865 | G65: 134.66007 | H65: 134.03644 | I65: 133.89068 | J65: 136.75845 | K65: 137.79257 | L65: 138.05387 | M65: 137.63875 | N65: 137.33388 | O65: 136.64385 | P65: 136.00634 | Q65: 136.30158 | R65: 135.97522 | S65: 135.14365 | T65: 134.92553 | U65: 135.08979 | V65: 135.09399 | W65: 134.75598 | X65: 133.54133 | Y65: 135.4591 | Z65: 133.55744 | AA65: 133.5372 | AB65: 132.55572 | AC65: 132.2655 | AD65: 132.18319 | AE65: 133.08406 | AF65: 133.50522 | AG65: 134.55731 | AH65: 134.67673 | AI65: 135.27614 | AJ65: 135.84781 | AK65: 136.07802 | AL65: 135.77857 | AM65: 136.26093 | AN65: 137.55745 | AO65: 137.80543 | AP65: 138.55656 | AQ65: 138.62984 | AR65: 138.50618 | AS65: 138.90742 | AT65: 139.36135 | AU65: 138.69173 | AV65: 138.57662 | AW65: 139.25133 | AX65: 139.35696 | AY65: 138.91291 | AZ65: 138.86981 | BA65: 138.0136 | BB65: 138.34092 | BC65: 138.97095 | BD65: 139.32092 | BE65: 139.41973 | BF65: 139.29997 | BG65: 139.60041 | BH65: 139.76878 | BI65: 139.13918 | BJ65: 138.491 | BK65: 138.20993 | BL65: 138.26959 | BM65: 138.27333 | BN65: 138.33087 | BO65: 138.81098 | BP65: 139.1685 | BQ65: 139.37981 | BR65: 139.5293 | BS65: 139.25464 | BT65: 139.45689 | BU65: 139.66882 | BV65: 140.04555 | BW65: 141.30085 | BX65: 141.54262 | BY65: 139.03921 | BZ65: 138.88184 | CA65: 141.41906
A66: Model Score | B66: -2.3534024 | C66: -0.81646254 | D66: -0.35300377 | E66: -0.54593932 | F66: -0.63351395 | G66: -0.48107002 | H66: -0.42038598 | I66: -0.5606689 | J66: -0.40910978 | K66: -0.33633614 | L66: -0.29350318 | M66: -0.22877567 | N66: -0.19564637 | O66: -0.13553302 | P66: -0.10308741 | Q66: -0.065622553 | R66: -0.032244905 | S66: 0.0012214598 | T66: 0.0020733691 | U66: 0.046943336 | V66: 0.058053005 | W66: 0.052350712 | X66: 0.074250746 | Y66: 0.04540894 | Z66: 0.054842947 | AA66: 0.073216076 | AB66: 0.032491987 | AC66: 0.093870679 | AD66: 0.14773755 | AE66: -0.39985165 | AF66: 0.054283722 | AG66: 0.00015324912 | AH66: -0.21037369 | AI66: -0.17365996 | AJ66: -0.37510767 | AK66: -0.40630495 | AL66: -0.25469524 | AM66: -0.10356874 | AN66: -0.30781745 | AO66: -0.14799877 | AP66: -0.85020879 | AQ66: -0.36361185 | AR66: 0.052422514 | AS66: 0.90714405 | AT66: 0.020157784 | AU66: -0.22003357 | AV66: -1.0142827 | AW66: -1.1124435 | AX66: -2.4194133 | AY66: 0.52702781 | AZ66: 0.13016361 | BA66: 0.060762208 | BB66: 0.1761845 | BC66: 0.11345714 | BD66: 0.10910621 | BE66: -0.010353373 | BF66: -0.075197569 | BG66: -0.1337059 | BH66: -0.1015708 | BI66: -0.026803629 | BJ66: 0.025448042 | BK66: 0.10402387 | BL66: 0.12857715 | BM66: 0.082720642 | BN66: 0.066619944 | BO66: 0.015788142 | BP66: -0.079787848 | BQ66: -0.033364744 | BR66: -0.041521497 | BS66: -0.0061269762 | BT66: -0.050039785 | BU66: -0.17929723 | BV66: -0.016939603 | BW66: 0.0043053065 | BX66: -0.05922275
A67: Gross Loss Adjustments (Dealer level, high PTI, etc.) | B67: 1.4333966 | C67: 3.0097639 | D67: 3.1573318 | E67: 3.2778811 | F67: 2.4852191 | G67: 2.6715138 | H67: 2.6508163 | I67: 2.1651595 | J67: 2.7674404 | K67: 2.851243 | L67: 2.7547909 | M67: 2.6530092 | N67: 2.6988377 | O67: 2.5107785 | P67: 2.5239006 | Q67: 2.2725413 | R67: 2.529962 | S67: 2.6760388 | T67: 2.6223075 | U67: 2.2892741 | V67: 2.1758494 | W67: 2.0231407 | X67: 2.1292116 | Y67: 2.1667153 | Z67: 2.0843817 | AA67: 2.0411393 | AB67: 1.8594207 | AC67: 1.7488154 | AD67: 1.4780176 | AE67: 0.30962207 | AF67: 1.9382921 | AG67: 1.8912416 | AH67: 2.1077378 | AI67: 1.7213289 | AJ67: 1.1220609 | AK67: 1.436344 | AL67: 1.2117764 | AM67: 1.2822008 | AN67: 1.4846586 | AO67: 1.4645866 | AP67: 1.3756611 | AQ67: 1.8787356 | AR67: 1.3092627 | AS67: 2.4327894 | AT67: 1.9998392 | AU67: 1.5847598 | AV67: 1.0287266 | AW67: 1.3286078 | AX67: -3.6848113 | AY67: 2.8901376 | AZ67: 2.4297957 | BA67: 2.7782277 | BB67: 2.4042359 | BC67: 2.7225811 | BD67: 3.1623459 | BE67: 3.1400791 | BF67: 3.038877 | BG67: 3.2210007 | BH67: 3.1263051 | BI67: 2.9392572 | BJ67: 2.7560537 | BK67: 2.1313083 | BL67: 1.8151585 | BM67: 1.7195155 | BN67: 1.4682974 | BO67: 2.0686147 | BP67: 2.6551357 | BQ67: 3.1857312 | BR67: 3.0528736 | BS67: 2.6226328 | BT67: 2.9733833 | BU67: 3.1847277 | BV67: 3.1674063 | BW67: 4.029751 | BX67: 3.7189532
A68: Recovery Adjustments excluding LTV (Mileage, vehicle type, etc.) | B68: -0.70206127 | C68: -1.3393963 | D68: -1.5391228 | E68: -1.7182243 | F68: -1.7396741 | G68: -2.07288 | H68: -2.1525649 | I68: -1.8799383 | J68: -2.0252876 | K68: -1.8760693 | L68: -2.1124134 | M68: -2.1318459 | N68: -2.0902375 | O68: -1.9813525 | P68: -1.9147798 | Q68: -1.6745551 | R68: -1.8844111 | S68: -1.9050709 | T68: -1.8739496 | U68: -1.6722185 | V68: -1.5431082 | W68: -1.3213506 | X68: -1.240004 | Y68: -1.3649782 | Z68: -1.37966 | AA68: -1.7168546 | AB68: -1.964082 | AC68: -1.835304 | AD68: -1.8868881 | AE68: -1.5835258 | AF68: -2.4177498 | AG68: -2.5219461 | AH68: -2.5917302 | AI68: -2.7783358 | AJ68: -2.8984983 | AK68: -3.386168 | AL68: -3.2694614 | AM68: -2.8786439 | AN68: -3.0791183 | AO68: -3.3994861 | AP68: -3.8949095 | AQ68: -4.2443372 | AR68: -3.9835147 | AS68: -4.0065715 | AT68: -3.7641898 | AU68: -3.5401116 | AV68: -3.362767 | AW68: -2.9538944 | AX68: -4.2250825 | AY68: -3.0339236 | AZ68: -2.6339898 | BA68: -3.0090185 | BB68: -2.9054205 | BC68: -2.7596453 | BD68: -2.5778348 | BE68: -2.6498532 | BF68: -2.5068879 | BG68: -2.9038101 | BH68: -2.751779 | BI68: -2.423275 | BJ68: -2.253149 | BK68: -1.6943752 | BL68: -1.6536833 | BM68: -1.83083 | BN68: -1.8098398 | BO68: -1.6956981 | BP68: -1.6293346 | BQ68: -1.6627241 | BR68: -1.4489967 | BS68: -1.4753069 | BT68: -1.5834132 | BU68: -0.78092858 | BV68: -1.3821923 | BW68: -0.59466358 | BX68: -1.5231535
A69: LTV Adjustments | B69: 0.70206127 | C69: 1.3393963 | D69: 1.5391228 | E69: 1.7182243 | F69: 1.7396741 | G69: 2.07288 | H69: 2.1525649 | I69: 1.8799383 | J69: 2.0252876 | K69: 1.8760693 | L69: 2.1124134 | M69: 2.1318459 | N69: 2.0902375 | O69: 1.9813525 | P69: 1.9147798 | Q69: 1.6745551 | R69: 1.8844111 | S69: 1.9050709 | T69: 1.8739496 | U69: 1.6722185 | V69: 1.5431082 | W69: 1.3213506 | X69: 1.240004 | Y69: 1.3649782 | Z69: 1.37966 | AA69: 1.7168546 | AB69: 1.964082 | AC69: 1.835304 | AD69: 1.8868881 | AE69: 1.5835258 | AF69: 2.4177498 | AG69: 2.5219461 | AH69: 2.5917302 | AI69: 2.7783358 | AJ69: 2.8984983 | AK69: 3.386168 | AL69: 3.2694614 | AM69: 2.8786439 | AN69: 3.0791183 | AO69: 3.3994861 | AP69: 3.8949095 | AQ69: 4.2443372 | AR69: 3.9835147 | AS69: 4.0065715 | AT69: 3.7641898 | AU69: 3.5401116 | AV69: 3.362767 | AW69: 2.9538944 | AX69: 4.2250825 | AY69: 3.0339236 | AZ69: 2.6339898 | BA69: 3.0090185 | BB69: 2.9054205 | BC69: 2.7596453 | BD69: 2.5778348 | BE69: 2.6498532 | BF69: 2.5068879 | BG69: 2.9038101 | BH69: 2.751779 | BI69: 2.423275 | BJ69: 2.253149 | BK69: 1.6943752 | BL69: 1.6536833 | BM69: 1.83083 | BN69: 1.8098398 | BO69: 1.6956981 | BP69: 1.6293346 | BQ69: 1.6627241 | BR69: 1.4489967 | BS69: 1.4753069 | BT69: 1.5834132 | BU69: 0.78092858 | BV69: 1.3821923 | BW69: 0.59466358 | BX69: 1.5231535
A70: RAGU Score | B70: 133.05025 | C70: 139.28135 | D70: 138.98201 | E70: 137.95597 | F70: 135.91036 | G70: 136.85051 | H70: 136.26687 | I70: 135.49517 | J70: 139.11678 | K70: 140.30748 | L70: 140.51516 | M70: 140.06298 | N70: 139.83707 | O70: 139.0191 | P70: 138.42715 | Q70: 138.5085 | R70: 138.47294 | S70: 137.82091 | T70: 137.54991 | U70: 137.42601 | V70: 137.32789 | W70: 136.83148 | X70: 135.74479 | Y70: 137.67123 | Z70: 135.69666 | AA70: 135.65155 | AB70: 134.44763 | AC70: 134.10818 | AD70: 133.80894 | AE70: 132.99383 | AF70: 135.4978 | AG70: 136.44871 | AH70: 136.57409 | AI70: 136.82381 | AJ70: 136.59476 | AK70: 137.10806 | AL70: 136.73565 | AM70: 137.43957 | AN70: 138.73429 | AO70: 139.12202 | AP70: 139.08201 | AQ70: 140.14496 | AR70: 139.86786 | AS70: 142.24735 | AT70: 141.38135 | AU70: 140.05646 | AV70: 138.59107 | AW70: 139.4675 | AX70: 133.25274 | AY70: 142.33008 | AZ70: 141.42977 | BA70: 140.85259 | BB70: 140.92134 | BC70: 141.80699 | BD70: 142.59237 | BE70: 142.54945 | BF70: 142.26365 | BG70: 142.68771 | BH70: 142.79351 | BI70: 142.05164 | BJ70: 141.27251 | BK70: 140.44526 | BL70: 140.21333 | BM70: 140.07556 | BN70: 139.86579 | BO70: 140.89538 | BP70: 141.74385 | BQ70: 142.53217 | BR70: 142.54065 | BS70: 141.87115 | BT70: 142.38024 | BU70: 142.67425 | BV70: 143.19602 | BW70: 145.3349 | BX70: 145.20235
A71: LTV | B71: 1.9010808 | C71: 1.7314065 | D71: 1.722432 | E71: 1.72364 | F71: 1.7999121 | G71: 1.7642871 | H71: 1.7152815 | I71: 1.7667218 | J71: 1.8004394 | K71: 1.746113 | L71: 1.6221022 | M71: 1.5689334 | N71: 1.598436 | O71: 1.6683305 | P71: 1.7367366 | Q71: 1.7047749 | R71: 1.6998966 | S71: 1.6245633 | T71: 1.4955882 | U71: 1.4369982 | V71: 1.4160322 | W71: 1.4198302 | X71: 1.4487039 | Y71: 1.4986436 | Z71: 1.5068496 | AA71: 1.499713 | AB71: 1.5182801 | AC71: 1.5239045 | AD71: 1.5769952 | AE71: 1.5305929 | AF71: 1.5161134 | AG71: 1.5480143 | AH71: 1.6421928 | AI71: 1.5971164 | AJ71: 1.5662073 | AK71: 1.6318559 | AL71: 1.6345063 | AM71: 1.6205636 | AN71: 1.6613282 | AO71: 1.6840098 | AP71: 1.6535841 | AQ71: 1.642578 | AR71: 1.7629242 | AS71: 1.8725693 | AT71: 1.6330932 | AU71: 1.6297662 | AV71: 1.7489776 | AW71: 1.5834404 | AX71: 1.4938802 | AY71: 1.7713795 | AZ71: 1.7090247 | BA71: 1.7923332 | BB71: 1.5847585 | BC71: 1.5645823 | BD71: 1.5241509 | BE71: 1.5248303 | BF71: 1.5714893 | BG71: 1.5589361 | BH71: 1.5554603 | BI71: 1.5636397 | BJ71: 1.5797838 | BK71: 1.5594958 | BL71: 1.5578209 | BM71: 1.5226338 | BN71: 1.514617 | BO71: 1.4930047 | BP71: 1.4927014 | BQ71: 1.5011276 | BR71: 1.4767712 | BS71: 1.4933918 | BT71: 1.5260006 | BU71: 1.4892614 | BV71: 1.4900494 | BW71: 1.4631703 | BX71: 1.4719479

Sheet Waterfall Tables
A1: AN
A2: Vintage | B2: None | C2: Previous ACA chargeoff | D2: Small amount financed | E2: Zero cash down | F2: High mileage vehicle | G2: High PTI | H2: Car make | I2: Theft risk | J2: MCY high model score, low mileage | K2: Weekday/weekend decision | L2: Secured credit (Chime, etc.) | M2: Employment type | N2: High cash down EchoPark | O2: Authorized tradelines | P2: Clip | Q2: Vehicle Age | R2: Dealer Level (Non-KMX) | S2: Mileage/age | T2: Japanese | U2: Vehicle class | V2: Fuel type | W2: Luxury classification | X2: LOB | Y2: Driver flag | Z2: Impound probability | AA2: Job time | AB2: Low FICO | AC2: Low Vantage | AD2: Louisiana | AE2: Existing DQ | AF2: Null FICO with Vantage | AG2: Soft Pull
A3: 2016 Q1 | B3: 0 | C3: -0.088849019 | D3: -0.009560662 | E3: -0.055668889 | F3: -0.43648122 | G3: -0.017747536 | H3: 0.2844119 | I3: 0.2511436 | J3: 0 | K3: 0.017442999 | L3: -0.63058383 | M3: 0 | N3: 0 | O3: -0.042806452 | P3: 0.13421102 | Q3: 0 | R3: 0.666524 | S3: 0 | T3: 0 | U3: 0 | V3: 0 | W3: 0 | X3: 0 | Y3: 0 | Z3: 0 | AA3: 0 | AB3: 0 | AC3: 0 | AD3: 0 | AE3: 0 | AF3: -0.14050087 | AG3: 0
A4: 2016 Q2 | B4: 0 | C4: -0.016332403 | D4: -0.0084102165 | E4: -0.10106913 | F4: -0.41665541 | G4: -0.022255339 | H4: 0.27247612 | I4: 0.27296891 | J4: 0 | K4: -0.033041539 | L4: -0.025449251 | M4: 0 | N4: 0 | O4: -0.0158258 | P4: 0.041150486 | Q4: 0 | R4: 0.56269949 | S4: 0 | T4: 0 | U4: 0 | V4: 0 | W4: 0 | X4: 0 | Y4: 0 | Z4: 0 | AA4: 0 | AB4: 0 | AC4: 0 | AD4: 0 | AE4: 0 | AF4: 0.071119222 | AG4: 0
A5: 2016 Q3 | B5: 0 | C5: -0.0086610508 | D5: -0.0090471231 | E5: -0.12312524 | F5: -0.37133885 | G5: -0.013071307 | H5: 0.33112637 | I5: 0.2844547 | J5: 0 | K5: -0.05951543 | L5: 0.24055522 | M5: 0 | N5: 0 | O5: 0 | P5: 0.00035605691 | Q5: 0 | R5: 0.42579935 | S5: 0 | T5: 0 | U5: 0 | V5: 0 | W5: 0 | X5: 0 | Y5: 0 | Z5: 0 | AA5: 0 | AB5: 0 | AC5: 0 | AD5: 0 | AE5: 0 | AF5: 0.218672 | AG5: 0
A6: 2016 Q4 | B6: 0 | C6: -0.018426974 | D6: -0.01060248 | E6: -0.11562108 | F6: -0.33294813 | G6: -0.02198921 | H6: 0.39490129 | I6: 0.28135824 | J6: 0 | K6: -0.030195971 | L6: 0.2379768 | M6: 0 | N6: 0 | O6: 0 | P6: 0.0016167563 | Q6: 0 | R6: 0.51074025 | S6: 0 | T6: 0 | U6: 0 | V6: 0 | W6: 0 | X6: 0 | Y6: 0 | Z6: 0 | AA6: 0 | AB6: 0 | AC6: 0 | AD6: 0 | AE6: 0 | AF6: 0.21635181 | AG6: 0
A7: 2017 Q1 | B7: 0 | C7: -0.015804407 | D7: -0.014542724 | E7: -0.084214279 | F7: -0.35084252 | G7: -0.016345841 | H7: 0.32339842 | I7: 0.27959447 | J7: 0 | K7: -0.029003851 | L7: 0.23643041 | M7: 0 | N7: 0 | O7: -0.0092166125 | P7: 0.0014012386 | Q7: 0 | R7: 0.73157821 | S7: 0 | T7: 0 | U7: 0 | V7: 0 | W7: 0 | X7: 0 | Y7: 0 | Z7: 0 | AA7: 0 | AB7: 0 | AC7: 0 | AD7: 0 | AE7: 0 | AF7: 0.21491379 | AG7: 0
A8: 2017 Q2 | B8: 0 | C8: -0.023581612 | D8: -0.014813655 | E8: -0.11192379 | F8: -0.31483375 | G8: -0.011060914 | H8: 0.31222253 | I8: 0.28077869 | J8: 0 | K8: -0.056025421 | L8: 0.23761528 | M8: 0 | N8: 0 | O8: -0.0089687167 | P8: 0.0069448185 | Q8: 0 | R8: 0.52616729 | S8: 0 | T8: 0 | U8: 0 | V8: 0 | W8: 0 | X8: 0 | Y8: 0 | Z8: 0 | AA8: 0 | AB8: 0 | AC8: 0 | AD8: 0 | AE8: 0 | AF8: 0.21609898 | AG8: 0
A9: 2017 Q3 | B9: 0 | C9: -0.031593722 | D9: -0.010026636 | E9: -0.1308173 | F9: -0.32215106 | G9: -0.017742758 | H9: 0.33867224 | I9: 0.28057654 | J9: 0 | K9: -0.016288366 | L9: 0.23736072 | M9: 0 | N9: 0 | O9: -0.013442456 | P9: 0.0022972636 | Q9: 0 | R9: 0.60268324 | S9: 0 | T9: 0 | U9: 0 | V9: 0 | W9: 0 | X9: 0 | Y9: 0 | Z9: 0 | AA9: 0 | AB9: 0 | AC9: 0 | AD9: 0 | AE9: 0 | AF9: 0.21581828 | AG9: 0
A10: 2017 Q4 | B10: 0 | C10: -0.028999663 | D10: -0.010891458 | E10: -0.1193385 | F10: -0.30182908 | G10: -0.021758245 | H10: 0.31155832 | I10: 0.27933776 | J10: 0 | K10: -0.054242585 | L10: 0.23630397 | M10: 0 | N10: 0 | O10: -0.0059058477 | P10: 0.0011977711 | Q10: 0 | R10: 0.74321981 | S10: 0 | T10: 0 | U10: 0 | V10: 0 | W10: 0 | X10: 0 | Y10: 0 | Z10: 0 | AA10: 0 | AB10: 0 | AC10: 0 | AD10: 0 | AE10: 0 | AF10: 0.21485228 | AG10: 0
A11: 2018 Q1 | B11: 0 | C11: -0.028383621 | D11: -0.013130635 | E11: -0.092487996 | F11: -0.34469312 | G11: -0.010962788 | H11: 0.29344602 | I11: 0.27774239 | J11: 0 | K11: -0.02840682 | L11: 0.23498879 | M11: 0 | N11: 0 | O11: -0.022229646 | P11: 0.0010404969 | Q11: 0 | R11: 0.86504317 | S11: 0 | T11: 0 | U11: 0 | V11: 0 | W11: 0 | X11: 0 | Y11: 0 | Z11: 0 | AA11: 0 | AB11: 0 | AC11: 0 | AD11: 0 | AE11: 0 | AF11: 0.21367676 | AG11: 0
A12: 2018 Q2 | B12: 0 | C12: -0.021828868 | D12: -0.010576574 | E12: -0.083738872 | F12: -0.32091486 | G12: -0.014716883 | H12: 0.27210379 | I12: 0.27842983 | J12: 0 | K12: -0.038582272 | L12: 0.23546453 | M12: 0 | N12: 0 | O12: -0.01778007 | P12: 0.0024239912 | Q12: 0 | R12: 0.83497923 | S12: 0 | T12: 0 | U12: 0 | V12: 0 | W12: 0 | X12: 0 | Y12: 0 | Z12: 0 | AA12: 0 | AB12: 0 | AC12: 0 | AD12: 0 | AE12: 0 | AF12: 0.21404698 | AG12: 0
A13: 2018 Q3 | B13: 0 | C13: -0.026568185 | D13: -0.012874472 | E13: -0.13136604 | F13: -0.34734141 | G13: -0.0095121611 | H13: 0.33227491 | I13: 0.27904036 | J13: 0 | K13: -0.046784944 | L13: 0.23610745 | M13: 0 | N13: 0 | O13: -0.019099697 | P13: 0.0039980488 | Q13: 0 | R13: 0.71744418 | S13: 0 | T13: 0 | U13: 0 | V13: 0 | W13: 0 | X13: 0 | Y13: 0 | Z13: 0 | AA13: 0 | AB13: 0 | AC13: 0 | AD13: 0 | AE13: 0 | AF13: 0.21470604 | AG13: 0
A14: 2018 Q4 | B14: 0 | C14: -0.024672695 | D14: -0.010848323 | E14: -0.11390881 | F14: -0.40481772 | G14: -0.010395055 | H14: 0.30955733 | I14: 0.28002584 | J14: 0 | K14: -0.029127988 | L14: 0.23706238 | M14: 0 | N14: 0 | O14: -0.028696174 | P14: 0.0020729703 | Q14: 0 | R14: 0.65860642 | S14: 0 | T14: 0 | U14: 0 | V14: 0 | W14: 0 | X14: 0 | Y14: 0 | Z14: 0 | AA14: 0 | AB14: 0 | AC14: 0 | AD14: 0 | AE14: 0 | AF14: 0.21564574 | AG14: 0
... A39: 2025 Q1 | B39: 0 | C39: -0.0016042812 | D39: 0 | E39: 0 | F39: -0.013297931 | G39: 0 | H39: 1.7023993 | I39: 0 | J39: 0 | K39: 0.049289801 | L39: -0.24648853 | M39: 0.0080948058 | N39: 0 | O39: -0.032902349 | P39: -0.11680056 | Q39: 0 | R39: 1.252034 | S39: 0 | T39: 0 | U39: 0 | V39: 0 | W39: 0 | X39: 0 | Y39: 0 | Z39: 0 | AA39: 0 | AB39: 0 | AC39: 0 | AD39: 0 | AE39: 0 | AF39: -0.0014657352 | AG39: 0
B40: 0
B41: 0
B42: 0
B43: 0
B44: 0
B45: 0
A46: FRN | B46: 0
A47: Vintage | B47: 0 | C47: Previous ACA chargeoff | D47: Small amount financed | E47: Zero cash down | F47: High mileage vehicle | G47: High PTI | H47: Car make | I47: Theft risk | J47: MCY high model score, low mileage | K47: Weekday/weekend decision | L47: Secured credit (Chime, etc.) | M47: Employment type | N47: High cash down EchoPark | O47: Authorized tradelines | P47: Clip | Q47: Vehicle Age | R47: Dealer Level (Non-KMX) | S47: Mileage/age | T47: Japanese | U47: Vehicle class | V47: Fuel type | W47: Luxury classification | X47: LOB | Y47: Driver flag | Z47: Impound probability | AA47: Job time | AB47: Low FICO | AC47: Low Vantage | AD47: Louisiana | AE47: Existing DQ | AF47: Null FICO with Vantage | AG47: Soft Pull
A48: 2016 Q1 | B48: 0 | C48: -0.066487452 | D48: -0.015468452 | E48: -0.14534016 | F48: -0.6285997 | G48: -0.0093342212 | H48: 0.17529678 | I48: 0.25829076 | J48: 0 | K48: -0.099797012 | L48: -0.59657888 | M48: 0 | N48: 0 | O48: -0.03808574 | P48: 0.19956806 | Q48: 0 | R48: -0.91242482 | S48: 0 | T48: 0 | U48: 0 | V48: 0 | W48: 0 | X48: 0 | Y48: 0 | Z48: 0 | AA48: 0 | AB48: 0 | AC48: 0 | AD48: 0 | AE48: 0 | AF48: -0.070534535 | AG48: 0
A49: 2016 Q2 | B49: 0 | C49: -0.021585175 | D49: -0.012453993 | E49: -0.21920307 | F49: -0.59428089 | G49: -0.0082439271 | H49: 0.19597396 | I49: 0.29095851 | J49: 0 | K49: -0.11932985 | L49: 0.05143236 | M49: 0 | N49: 0 | O49: -0.010495363 | P49: 0.041691873 | Q49: 0 | R49: -0.75015297 | S49: 0 | T49: 0 | U49: 0 | V49: 0 | W49: 0 | X49: 0 | Y49: 0 | Z49: 0 | AA49: 0 | AB49: 0 | AC49: 0 | AD49: 0 | AE49: 0 | AF49: 0.14839927 | AG49: 0
A50: 2016 Q3 | B50: 0 | C50: -0.00057730205 | D50: -0.010364941 | E50: -0.24518989 | F50: -0.49533814 | G50: -0.014812538 | H50: 0.17699904 | I50: 0.29172756 | J50: 0 | K50: -0.10739042 | L50: 0.24721746 | M50: 0 | N50: 0 | O50: 0 | P50: 0.0024082344 | Q50: 0 | R50: -0.030255776 | S50: 0 | T50: 0 | U50: 0 | V50: 0 | W50: 0 | X50: 0 | Y50: 0 | Z50: 0 | AA50: 0 | AB50: 0 | AC50: 0 | AD50: 0 | AE50: 0 | AF50: 0.22502985 | AG50: 0
A51: 2016 Q4 | B51: 0 | C51: -0.013656674 | D51: -0.01462645 | E51: -0.22887229 | F51: -0.43866306 | G51: -0.0085183794 | H51: 0.16089446 | I51: 0.28767877 | J51: 0 | K51: -0.10790836 | L51: 0.24349288 | M51: 0 | N51: 0 | O51: -0.0011503766 | P51: 0.0033717002 | Q51: 0 | R51: 0.42097954 | S51: 0 | T51: 0 | U51: 0 | V51: 0 | W51: 0 | X51: 0 | Y51: 0 | Z51: 0 | AA51: 0 | AB51: 0 | AC51: 0 | AD51: 0 | AE51: 0 | AF51: 0.22146688 | AG51: 0
A52: 2017 Q1 | B52: 0 | C52: -0.0060864618 | D52: -0.030437735 | E52: -0.12809885 | F52: -0.37574677 | G52: -0.0069271107 | H52: 0.18746687 | I52: 0.29316511 | J52: 0 | K52: -0.11959357 | L52: 0.24813809 | M52: 0 | N52: 0 | O52: -0.017806779 | P52: 0.0059782634 | Q52: 0 | R52: -0.19214078 | S52: 0 | T52: 0 | U52: 0 | V52: 0 | W52: 0 | X52: 0 | Y52: 0 | Z52: 0 | AA52: 0 | AB52: 0 | AC52: 0 | AD52: 0 | AE52: 0 | AF52: 0.22569281 | AG52: 0
A53: 2017 Q2 | B53: 0 | C53: -0.0096765878 | D53: -0.037301417 | E53: -0.12666074 | F53: -0.3323577 | G53: 0 | H53: 0.22652935 | I53: 0.29250789 | J53: 0 | K53: -0.11888954 | L53: 0.247598 | M53: 0 | N53: 0 | O53: -0.0055099648 | P53: 0.0012741952 | Q53: 0 | R53: -0.2261259 | S53: 0 | T53: 0 | U53: 0 | V53: 0 | W53: 0 | X53: 0 | Y53: 0 | Z53: 0 | AA53: 0 | AB53: 0 | AC53: 0 | AD53: 0 | AE53: 0 | AF53: 0.22521111 | AG53: 0
A54: 2017 Q3 | B54: 0 | C54: -0.020905501 | D54: -0.048216142 | E54: -0.14365869 | F54: -0.30999971 | G54: 0 | H54: 0.17095009 | I54: 0.29361924 | J54: 0 | K54: -0.12155819 | L54: 0.2485119 | M54: 0 | N54: 0 | O54: -0.0083271219 | P54: 0.0014977648 | Q54: 0 | R54: -0.18755365 | S54: 0 | T54: 0 | U54: 0 | V54: 0 | W54: 0 | X54: 0 | Y54: 0 | Z54: 0 | AA54: 0 | AB54: 0 | AC54: 0 | AD54: 0 | AE54: 0 | AF54: 0.22602657 | AG54: 0
A55: 2017 Q4 | B55: 0 | C55: -0.011009458 | D55: -0.062386538 | E55: -0.15643326 | F55: -0.27984876 | G55: -0.0094114415 | H55: 0.15834046 | I55: 0.293549 | J55: 0 | K55: -0.12377057 | L55: 0.24797565 | M55: 0 | N55: 0 | O55: -0.014872248 | P55: 0.0069859529 | Q55: 0 | R55: 0.032548543 | S55: 0 | T55: 0 | U55: 0 | V55: 0 | W55: 0 | X55: 0 | Y55: 0 | Z55: 0 | AA55: 0 | AB55: 0 | AC55: 0 | AD55: 0 | AE55: 0 | AF55: 0.22525803 | AG55: 0
A56: 2018 Q1 | B56: 0 | C56: -0.0037112405 | D56: -0.062979423 | E56: -0.10290878 | F56: -0.33564161 | G56: -0.0081656737 | H56: 0.17707709 | I56: 0.29514473 | J56: 0 | K56: -0.10537582 | L56: 0.24976704 | M56: 0 | N56: 0 | O56: -0.0088560257 | P56: 0.0016022162 | Q56: 0 | R56: -0.32758673 | S56: 0 | T56: 0 | U56: 0 | V56: 0 | W56: 0 | X56: 0 | Y56: 0 | Z56: 0 | AA56: 0 | AB56: 0 | AC56: 0 | AD56: 0 | AE56: 0 | AF56: 0.22714694 | AG56: 0
A57: 2018 Q2 | B57: 0 | C57: -0.019040795 | D57: -0.048931757 | E57: -0.13637734 | F57: -0.37900483 | G57: 0 | H57: 0.15343342 | I57: 0.29709816 | J57: 0 | K57: -0.14362225 | L57: 0.25166089 | M57: 0 | N57: 0 | O57: -0.01896619 | P57: 0.0084890457 | Q57: 0 | R57: -0.55183173 | S57: 0 | T57: 0 | U57: 0 | V57: 0 | W57: 0 | X57: 0 | Y57: 0 | Z57: 0 | AA57: 0 | AB57: 0 | AC57: 0 | AD57: 0 | AE57: 0 | AF57: 0.2290111 | AG57: 0
A58: 2018 Q3 | B58: 0 | C58: -0.021657242 | D58: -0.055874623 | E58: -0.13086659 | F58: -0.38834316 | G58: 0 | H58: 0.13189847 | I58: 0.29727113 | J58: 0 | K58: -0.091788596 | L58: 0.25159003 | M58: 0 | N58: 0 | O58: -0.0032975088 | P58: 0.0099732251 | Q58: 0 | R58: -0.46083937 | S58: 0 | T58: 0 | U58: 0 | V58: 0 | W58: 0 | X58: 0 | Y58: 0 | Z58: 0 | AA58: 0 | AB58: 0 | AC58: 0 | AD58: 0 | AE58: 0 | AF58: 0.2288187 | AG58: 0
A59: 2018 Q4 | B59: 0 | C59: -0.015119677 | D59: -0.051643511 | E59: -0.18995899 | F59: -0.4322657 | G59: -0.0068365923 | H59: 0.18879901 | I59: 0.29803881 | J59: 0 | K59: -0.095723055 | L59: 0.25225077 | M59: 0 | N59: 0 | O59: -0.041091504 | P59: 0.015040954 | Q59: 0 | R59: -0.49889607 | S59: 0 | T59: 0 | U59: 0 | V59: 0 | W59: 0 | X59: 0 | Y59: 0 | Z59: 0 | AA59: 0 | AB59: 0 | AC59: 0 | AD59: 0 | AE59: 0 | AF59: 0.22942613 | AG59: 0
... A84: 2025 Q1 | B84: 0 | C84: -0.0058173884 | D84: 0 | E84: 0 | F84: -0.0065081629 | G84: 0 | H84: 1.5330391 | I84: 0 | J84: 0 | K84: -0.0051340888 | L84: -0.28711705 | M84: -0.0067693859 | N84: 0 | O84: -0.03630832 | P84: -0.086228609 | Q84: 0 | R84: 0.47955529 | S84: 0 | T84: 0 | U84: 0 | V84: 0 | W84: 0 | X84: 0 | Y84: 0 | Z84: 0 | AA84: 0 | AB84: 0 | AC84: 0 | AD84: 0 | AE84: 0 | AF84: 0.0026578804 | AG84: 0
B85: 0
B86: 0
B87: 0
B88: 0
B89: 0
A90: STG | B90: 0
A91: Vintage | B91: 0 | C91: Previous ACA chargeoff | D91: Small amount financed | E91: Zero cash down | F91: High mileage vehicle | G91: High PTI | H91: Car make | I91: Theft risk | J91: MCY high model score, low mileage | K91: Weekday/weekend decision | L91: Secured credit (Chime, etc.) | M91: Employment type | N91: High cash down EchoPark | O91: Authorized tradelines | P91: Clip | Q91: Vehicle Age | R91: Dealer Level (Non-KMX) | S91: Mileage/age | T91: Japanese | U91: Vehicle class | V91: Fuel type | W91: Luxury classification | X91: LOB | Y91: Driver flag | Z91: Impound probability | AA91: Job time | AB91: Low FICO | AC91: Low Vantage | AD91: Louisiana | AE91: Existing DQ | AF91: Null FICO with Vantage | AG91: Soft Pull
A92: 2016 Q1 | B92: 0 | C92: -0.091078532 | D92: -0.0095684872 | E92: -0.14538103 | F92: -0.38064137 | G92: -0.012235844 | H92: 0.35341087 | I92: 0.25315122 | J92: 0 | K92: -0.045844378 | L92: -0.63093451 | M92: 0 | N92: 0 | O92: -0.045542626 | P92: 0.10401354 | Q92: 0 | R92: 0.97238659 | S92: 0 | T92: 0 | U92: 0 | V92: 0 | W92: 0 | X92: 0 | Y92: 0 | Z92: 0 | AA92: 0 | AB92: 0 | AC92: 0 | AD92: 0 | AE92: 0 | AF92: -0.069292497 | AG92: 0
A93: 2016 Q2 | B93: 0 | C93: -0.018090698 | D93: -0.0072472404 | E93: -0.17177773 | F93: -0.37463703 | G93: -0.013990776 | H93: 0.29910132 | I93: 0.26934283 | J93: 0 | K93: -0.047048504 | L93: -0.0055836038 | M93: 0 | N93: 0 | O93: -0.014885544 | P93: 0.017415347 | Q93: 0 | R93: 1.094301 | S93: 0 | T93: 0 | U93: 0 | V93: 0 | W93: 0 | X93: 0 | Y93: 0 | Z93: 0 | AA93: 0 | AB93: 0 | AC93: 0 | AD93: 0 | AE93: 0 | AF93: 0.11669397 | AG93: 0
A94: 2016 Q3 | B94: 0 | C94: -0.0032172649 | D94: -0.006829119 | E94: -0.26099162 | F94: -0.35050482 | G94: -0.014546265 | H94: 0.27905334 | I94: 0.28211501 | J94: 0 | K94: -0.091686656 | L94: 0.23883065 | M94: 0 | N94: 0 | O94: 0 | P94: 0.0032867029 | Q94: 0 | R94: 0.63240486 | S94: 0 | T94: 0 | U94: 0 | V94: 0 | W94: 0 | X94: 0 | Y94: 0 | Z94: 0 | AA94: 0 | AB94: 0 | AC94: 0 | AD94: 0 | AE94: 0 | AF94: 0.21725405 | AG94: 0
A95: 2016 Q4 | B95: 0 | C95: -0.0072504695 | D95: -0.0059838668 | E95: -0.26603942 | F95: -0.34303693 | G95: -0.013215052 | H95: 0.27567249 | I95: 0.28254706 | J95: 0 | K95: -0.05819382 | L95: 0.23909213 | M95: 0 | N95: 0 | O95: 0 | P95: 0.0024544575 | Q95: 0 | R95: 0.64178642 | S95: 0 | T95: 0 | U95: 0 | V95: 0 | W95: 0 | X95: 0 | Y95: 0 | Z95: 0 | AA95: 0 | AB95: 0 | AC95: 0 | AD95: 0 | AE95: 0 | AF95: 0.21743051 | AG95: 0
A96: 2017 Q1 | B96: 0 | C96: -0.011198287 | D96: -0.0067422861 | E96: -0.17899301 | F96: -0.34655294 | G96: -0.013848969 | H96: 0.3137282 | I96: 0.28078417 | J96: 0 | K96: -0.083753819 | L96: 0.23748244 | M96: 0 | N96: 0 | O96: -0.014468919 | P96: 0.00075881154 | Q96: 0 | R96: 0.75442649 | S96: 0 | T96: 0 | U96: 0 | V96: 0 | W96: 0 | X96: 0 | Y96: 0 | Z96: 0 | AA96: 0 | AB96: 0 | AC96: 0 | AD96: 0 | AE96: 0 | AF96: 0.21589719 | AG96: 0
A97: 2017 Q2 | B97: 0 | C97: -0.0092107182 | D97: -0.0063933096 | E97: -0.21249064 | F97: -0.31373329 | G97: -0.018082519 | H97: 0.29570034 | I97: 0.27965948 | J97: 0 | K97: -0.092271235 | L97: 0.23671342 | M97: 0 | N97: 0 | O97: -0.0042582178 | P97: 0.0022624699 | Q97: 0 | R97: 0.75744224 | S97: 0 | T97: 0 | U97: 0 | V97: 0 | W97: 0 | X97: 0 | Y97: 0 | Z97: 0 | AA97: 0 | AB97: 0 | AC97: 0 | AD97: 0 | AE97: 0 | AF97: 0.21530546 | AG97: 0
A98: 2017 Q3 | B98: 0 | C98: -0.031617846 | D98: -0.0062505989 | E98: -0.25833418 | F98: -0.3116857 | G98: -0.019981751 | H98: 0.28242561 | I98: 0.27783583 | J98: 0 | K98: -0.08542652 | L98: 0.2351577 | M98: 0 | N98: 0 | O98: -0.01209805 | P98: 0.004671287 | Q98: 0 | R98: 0.96686246 | S98: 0 | T98: 0 | U98: 0 | V98: 0 | W98: 0 | X98: 0 | Y98: 0 | Z98: 0 | AA98: 0 | AB98: 0 | AC98: 0 | AD98: 0 | AE98: 0 | AF98: 0.2138833 | AG98: 0
A99: 2017 Q4 | B99: 0 | C99: -0.025271102 | D99: -0.0044305337 | E99: -0.2526816 | F99: -0.31146047 | G99: -0.025014072 | H99: 0.27794682 | I99: 0.28232246 | J99: 0 | K99: -0.087285029 | L99: 0.23894487 | M99: 0 | N99: 0 | O99: -0.0066110284 | P99: 0.0064212981 | Q99: 0 | R99: 0.5910451 | S99: 0 | T99: 0 | U99: 0 | V99: 0 | W99: 0 | X99: 0 | Y99: 0 | Z99: 0 | AA99: 0 | AB99: 0 | AC99: 0 | AD99: 0 | AE99: 0 | AF99: 0.21732179 | AG99: 0
A100: 2018 Q1 | B100: 0 | C100: -0.018256228 | D100: -0.0081043168 | E100: -0.18010387 | F100: -0.34296108 | G100: -0.0090977419 | H100: 0.29396258 | I100: 0.27909063 | J100: 0 | K100: -0.054247492 | L100: 0.23614784 | M100: 0 | N100: 0 | O100: -0.012780934 | P100: 0.0030365109 | Q100: 0 | R100: 0.82097909 | S100: 0 | T100: 0 | U100: 0 | V100: 0 | W100: 0 | X100: 0 | Y100: 0 | Z100: 0 | AA100: 0 | AB100: 0 | AC100: 0 | AD100: 0 | AE100: 0 | AF100: 0.21474151 | AG100: 0
A101: 2018 Q2 | B101: 0 | C101: -0.012622146 | D101: -0.0075697092 | E101: -0.20479022 | F101: -0.33138476 | G101: -0.011743598 | H101: 0.32203238 | I101: 0.27894566 | J101: 0 | K101: -0.074380555 | L101: 0.23598595 | M101: 0 | N101: 0 | O101: -0.018265334 | P101: 0.002859743 | Q101: 0 | R101: 0.85239485 | S101: 0 | T101: 0 | U101: 0 | V101: 0 | W101: 0 | X101: 0 | Y101: 0 | Z101: 0 | AA101: 0 | AB101: 0 | AC101: 0 | AD101: 0 | AE101: 0 | AF101: 0.21457119 | AG101: 0
A102: 2018 Q3 | B102: 0 | C102: -0.018712669 | D102: -0.0077433179 | E102: -0.28420244 | F102: -0.37867361 | G102: -0.011233117 | H102: 0.28516719 | I102: 0.28157634 | J102: 0 | K102: -0.062912849 | L102: 0.23845841 | M102: 0 | N102: 0 | O102: -0.023438059 | P102: 0.0046993695 | Q102: 0 | R102: 0.65274229 | S102: 0 | T102: 0 | U102: 0 | V102: 0 | W102: 0 | X102: 0 | Y102: 0 | Z102: 0 | AA102: 0 | AB102: 0 | AC102: 0 | AD102: 0 | AE102: 0 | AF102: 0.21696477 | AG102: 0
A103: 2018 Q4 | B103: 0 | C103: -0.018445759 | D103: -0.0078370801 | E103: -0.25650566 | F103: -0.41531571 | G103: -0.024647266 | H103: 0.27128521 | I103: 0.28249966 | J103: 0 | K103: -0.064023771 | L103: 0.2392466 | M103: 0 | N103: 0 | O103: -0.011256653 | P103: 0.0094368679 | Q103: 0 | R103: 0.56745839 | S103: 0 | T103: 0 | U103: 0 | V103: 0 | W103: 0 | X103: 0 | Y103: 0 | Z103: 0 | AA103: 0 | AB103: 0 | AC103: 0 | AD103: 0 | AE103: 0 | AF103: 0.2176856 | AG103: 0
... A128: 2025 Q1 | B128: 0 | C128: -0.002136841 | D128: 0 | E128: 0 | F128: -0.020436307 | G128: 0 | H128: 1.6711935 | I128: 0 | J128: 0 | K128: -0.018485462 | L128: -0.23716319 | M128: -0.0013200347 | N128: 0 | O128: -0.052797234 | P128: -0.088417135 | Q128: 0 | R128: 2.2904164 | S128: 0 | T128: 0 | U128: 0 | V128: 0 | W128: 0 | X128: 0 | Y128: 0 | Z128: 0 | AA128: 0 | AB128: 0 | AC128: 0 | AD128: 0 | AE128: 0 | AF128: 0.0028771196 | AG128: 0
B129: 0
B130: 0
B131: 0
B132: 0
A133: FLD | B133: 0
A134: Vintage | B134: 0 | C134: Previous ACA chargeoff | D134: Small amount financed | E134: Zero cash down | F134: High mileage vehicle | G134: High PTI | H134: Car make | I134: Theft risk | J134: MCY high model score, low mileage | K134: Weekday/weekend decision | L134: Secured credit (Chime, etc.) | M134: Employment type | N134: High cash down EchoPark | O134: Authorized tradelines | P134: Clip | Q134: Vehicle Age | R134: Dealer Level (Non-KMX) | S134: Mileage/age | T134: Japanese | U134: Vehicle class | V134: Fuel type | W134: Luxury classification | X134: LOB | Y134: Driver flag | Z134: Impound probability | AA134: Job time | AB134: Low FICO | AC134: Low Vantage | AD134: Louisiana | AE134: Existing DQ | AF134: Null FICO with Vantage | AG134: Soft Pull
A135: 2019 Q3 | B135: 0 | C135: -0.042212116 | D135: -0.0099141396 | E135: -0.21798384 | F135: -0.33973781 | G135: -0.077858336 | H135: 0.2353209 | I135: 0.26300398 | J135: 0 | K135: -0.055684829 | L135: -0.7392567 | M135: 0 | N135: 0 | O135: -0.080991995 | P135: 0.10951516 | Q135: 0 | R135: 0.29594119 | S135: 0 | T135: 0 | U135: 0 | V135: 0 | W135: 0 | X135: 0 | Y135: 0 | Z135: 0 | AA135: 0 | AB135: 0 | AC135: 0 | AD135: 0 | AE135: 0 | AF135: -0.061482649 | AG135: 0
A136: 2019 Q4 | B136: 0 | C136: 0 | D136: -0.0090808834 | E136: -0.23751189 | F136: -0.27638546 | G136: 0 | H136: 0.20283638 | I136: 0.24002301 | J136: 0 | K136: 0.083510483 | L136: -0.076318031 | M136: 0 | N136: 0 | O136: 0 | P136: 0.052853794 | Q136: 0 | R136: 3.1775803 | S136: 0 | T136: 0 | U136: 0 | V136: 0 | W136: 0 | X136: 0 | Y136: 0 | Z136: 0 | AA136: 0 | AB136: 0 | AC136: 0 | AD136: 0 | AE136: 0 | AF136: 0.056571607 | AG136: 0
A137: 2020 Q1 | B137: 0 | C137: 0 | D137: -0.0066976863 | E137: -0.35601349 | F137: -0.25736679 | G137: -0.044084827 | H137: 0.11294235 | I137: 0.27261247 | J137: 0 | K137: -0.012290365 | L137: 0.23074928 | M137: 0 | N137: 0 | O137: 0 | P137: 0 | Q137: 0 | R137: 1.5756844 | S137: 0 | T137: 0 | U137: 0 | V137: 0 | W137: 0 | X137: 0 | Y137: 0 | Z137: 0 | AA137: 0 | AB137: 0 | AC137: 0 | AD137: 0 | AE137: 0 | AF137: 0.20988111 | AG137: 0
A138: 2020 Q2 | B138: 0 | C138: 0 | D138: -0.0062449178 | E138: -0.47759908 | F138: -0.31568735 | G138: 0 | H138: 0.17367753 | I138: 0.29219397 | J138: 0 | K138: 0.023228861 | L138: 0.24719964 | M138: 0 | N138: 0 | O138: 0 | P138: 0 | Q138: 0 | R138: 0.12130033 | S138: 0 | T138: 0 | U138: 0 | V138: 0 | W138: 0 | X138: 0 | Y138: 0 | Z138: 0 | AA138: 0 | AB138: 0 | AC138: 0 | AD138: 0 | AE138: 0 | AF138: 0.22477065 | AG138: 0
A139: 2020 Q3 | B139: 0 | C139: 0 | D139: 0 | E139: -0.14689004 | F139: -0.12776922 | G139: 0 | H139: 0.21326186 | I139: 0.28389489 | J139: 0 | K139: -0.073631604 | L139: 0.24042547 | M139: 0 | N139: 0 | O139: -0.0098234864 | P139: 0 | Q139: 0 | R139: 0.14340082 | S139: 0 | T139: 0 | U139: 0 | V139: 0 | W139: 0 | X139: 0 | Y139: 0 | Z139: 0 | AA139: 0 | AB139: 0 | AC139: 0 | AD139: 0 | AE139: 0 | AF139: 0.21875662 | AG139: 0
A140: 2020 Q4 | B140: 0 | C140: 0 | D140: -0.0023229251 | E140: -0.13560248 | F140: -0.059212902 | G140: 0 | H140: 0.21372336 | I140: 0.29052039 | J140: 0 | K140: -0.15891026 | L140: 0.24532783 | M140: 0 | N140: 0 | O140: -0.035638776 | P140: 0 | Q140: 0 | R140: 0.090534468 | S140: 0 | T140: 0 | U140: 0 | V140: 0 | W140: 0 | X140: 0 | Y140: 0 | Z140: 0 | AA140: 0 | AB140: 0 | AC140: 0 | AD140: 0 | AE140: 0 | AF140: 0.22280002 | AG140: 0
A141: 2021 Q1 | B141: 0 | C141: -0.033356095 | D141: 0 | E141: -0.25692796 | F141: -0.0655235 | G141: 0 | H141: 0.13228028 | I141: 0.29006032 | J141: 0 | K141: -0.13461706 | L141: 0.24547676 | M141: 0 | N141: 0 | O141: -0.01325525 | P141: 0 | Q141: 0 | R141: 0 | S141: 0 | T141: 0 | U141: 0 | V141: 0 | W141: 0 | X141: 0 | Y141: 0 | Z141: 0 | AA141: 0 | AB141: 0 | AC141: 0 | AD141: 0 | AE141: 0 | AF141: 0.22325253 | AG141: 0
A142: 2021 Q2 | B142: 0 | C142: -0.032484737 | D142: 0 | E142: -0.32826733 | F142: -0.013439183 | G142: -0.041192884 | H142: 0.19137106 | I142: 0.25371329 | J142: 0 | K142: -0.11747863 | L142: 0.21498694 | M142: 0 | N142: 0 | O142: 0 | P142: 0 | Q142: 0 | R142: 2.6465638 | S142: 0 | T142: 0 | U142: 0 | V142: 0 | W142: 0 | X142: 0 | Y142: 0 | Z142: 0 | AA142: 0 | AB142: 0 | AC142: 0 | AD142: 0 | AE142: 0 | AF142: 0.19568244 | AG142: 0
A143: 2021 Q3 | B143: 0 | C143: 0 | D143: 0 | E143: -0.10473246 | F143: -0.024743692 | G143: -0.026821609 | H143: 0.23474928 | I143: 0.25632962 | J143: 0 | K143: -0.049097905 | L143: 0.21645568 | M143: 0 | N143: 0 | O143: -0.038715486 | P143: 0 | Q143: 0 | R143: 2.5195525 | S143: 0 | T143: 0 | U143: 0 | V143: 0 | W143: 0 | X143: 0 | Y143: 0 | Z143: 0 | AA143: 0 | AB143: 0 | AC143: 0 | AD143: 0 | AE143: 0 | AF143: 0.19657913 | AG143: 0
A144: 2021 Q4 | B144: 0 | C144: -0.015466174 | D144: -0.003380976 | E144: -0.28939198 | F144: -0.0067422208 | G144: 0 | H144: 0.15571763 | I144: 0.24818701 | J144: 0 | K144: -0.033578013 | L144: 0.20996725 | M144: 0 | N144: 0 | O144: -0.037044878 | P144: 0 | Q144: 0 | R144: 3.1696732 | S144: 0 | T144: 0 | U144: 0 | V144: 0 | W144: 0 | X144: 0 | Y144: 0 | Z144: 0 | AA144: 0 | AB144: 0 | AC144: 0 | AD144: 0 | AE144: 0 | AF144: 0.19091528 | AG144: 0
A145: 2022 Q1 | B145: 0 | C145: -0.020818951 | D145: 0 | E145: -0.18962254 | F145: -0.031145337 | G145: 0 | H145: 0.19965272 | I145: 0.27088628 | J145: 0 | K145: -0.12506961 | L145: 0.22874794 | M145: 0 | N145: 0 | O145: 0 | P145: 0 | Q145: 0 | R145: 1.5890791 | S145: 0 | T145: 0 | U145: 0 | V145: 0 | W145: 0 | X145: 0 | Y145: 0 | Z145: 0 | AA145: 0 | AB145: 0 | AC145: 0 | AD145: 0 | AE145: 0 | AF145: 0.20774262 | AG145: 0
A146: 2022 Q2 | B146: 0 | C146: -0.023393105 | D146: -0.002023148 | E146: -0.31929298 | F146: -0.026034792 | G146: -0.020209609 | H146: 0.18867647 | I146: 0.28356106 | J146: 0 | K146: -0.096239716 | L146: 0.23972989 | M146: 0 | N146: 0 | O146: -0.041551598 | P146: 0 | Q146: 0 | R146: 0.63023545 | S146: 0 | T146: 0 | U146: 0 | V146: 0 | W146: 0 | X146: 0 | Y146: 0 | Z146: 0 | AA146: 0 | AB146: 0 | AC146: 0 | AD146: 0 | AE146: 0 | AF146: 0.21788071 | AG146: 0
... A157: 2025 Q1 | B157: 0 | C157: -0.013794458 | D157: -0.00075988691 | E157: -0.17537584 | F157: -0.047721977 | G157: -0.071187448 | H157: 0.22059297 | I157: 0.27693616 | J157: 0 | K157: -0.033823786 | L157: 0.2340399 | M157: 0 | N157: 0 | O157: -0.042099819 | P157: 0.0019122036 | Q157: 0 | R157: 0.98796802 | S157: 0 | T157: 0 | U157: 0 | V157: 0 | W157: 0 | X157: 0 | Y157: 0 | Z157: 0 | AA157: 0 | AB157: 0 | AC157: 0 | AD157: 0 | AE157: 0 | AF157: 0.21265677 | AG157: 0
B158: 0 | C158: -0.012291591 | D158: -0.00029385588 | E158: -0.17413886 | F158: -0.062218914 | G158: -0.080213835 | H158: 0.20458715 | I158: 0.26942175 | J158: 0 | K158: -0.071417143 | L158: 0.22772776 | M158: 0 | N158: 0 | O158: -0.036895596 | P158: 0.0022232701 | Q158: 0 | R158: 1.6228995 | S158: 0 | T158: 0 | U158: 0 | V158: 0 | W158: 0 | X158: 0 | Y158: 0 | Z158: 0 | AA158: 0 | AB158: 0 | AC158: 0 | AD158: 0 | AE158: 0 | AF158: 0.20694394 | AG158: 0
B159: 0 | C159: -0.011635804 | D159: -0.0013698658 | E159: -0.12248411 | F159: -0.1367736 | G159: -0.041376945 | H159: 0.20772005 | I159: 0.27445766 | J159: 0 | K159: -0.058046452 | L159: 0.2322105 | M159: 0 | N159: 0 | O159: -0.039924404 | P159: 0 | Q159: 0 | R159: 1.0918486 | S159: 0 | T159: 0 | U159: 0 | V159: 0 | W159: 0 | X159: 0 | Y159: 0 | Z159: 0 | AA159: 0 | AB159: 0 | AC159: 0 | AD159: 0 | AE159: 0 | AF159: 0.21115093 | AG159: 0
B160: 0 | C160: -0.0089178714 | D160: -0.0021716267 | E160: -0.065105688 | F160: -0.057825077 | G160: -0.084586809 | H160: 0.18739103 | I160: 0.27905589 | J160: 0 | K160: -0.085539248 | L160: 0.23575157 | M160: 0 | N160: 0 | O160: -0.049046563 | P160: 0 | Q160: 0 | R160: 0.88721385 | S160: 0 | T160: 0 | U160: 0 | V160: 0 | W160: 0 | X160: 0 | Y160: 0 | Z160: 0 | AA160: 0 | AB160: 0 | AC160: 0 | AD160: 0 | AE160: 0 | AF160: 0.21416503 | AG160: 0
B161: 0 | C161: -0.0058626632 | D161: -0.0024358857 | E161: -0.07886478 | F161: -0.035421352 | G161: -0.026402699 | H161: 0.20347621 | I161: 0.15285399 | J161: 0 | K161: -0.051305045 | L161: 0.23421559 | M161: 0 | N161: 0 | O161: -0.037985855 | P161: 0.0028798199 | Q161: 0 | R161: 0.93655224 | S161: 0 | T161: 0 | U161: 0 | V161: 0 | W161: 0 | X161: 0 | Y161: 0 | Z161: 0 | AA161: 0 | AB161: 0 | AC161: 0 | AD161: 0 | AE161: 0 | AF161: 0.21283571 | AG161: 0
A162: ENT | B162: 0 | C162: 0 | D162: -0.003917651 | E162: -0.044848968 | F162: -0.013906228 | G162: -0.10029585 | H162: 0.31526159 | I162: 0.15973718 | J162: 0 | K162: -0.087246056 | L162: 0.23391365 | M162: 0 | N162: 0 | O162: -0.10450438 | P162: 0 | Q162: 0 | R162: 0.75502032 | S162: 0 | T162: 0 | U162: 0 | V162: 0 | W162: 0 | X162: 0 | Y162: 0 | Z162: 0 | AA162: 0 | AB162: 0 | AC162: 0 | AD162: 0 | AE162: 0 | AF162: 0.21280334 | AG162: 0
A163: Vintage | B163: 0 | C163: -0.0086255047 | D163: -0.0056347643 | E163: -0.0042178043 | F163: -0.011177866 | G163: -0.0092690823 | H163: 0.29196103 | I163: 0.13243076 | J163: 0 | K163: -0.011554212 | L163: 0.0085112495 | M163: 0 | N163: 0 | O163: -0.031178683 | P163: 0.0010383537 | Q163: 0 | R163: 1.3406773 | S163: 0 | T163: 0 | U163: 0 | V163: 0 | W163: 0 | X163: 0 | Y163: 0 | Z163: 0 | AA163: 0 | AB163: 0 | AC163: 0 | AD163: 0 | AE163: 0 | AF163: 0.20712166 | AG163: 0
A164: 2019 Q4 | B164: 0 | C164: 0 | D164: 0 | E164: -0.91301462 | F164: 0 | G164: -0.0060828657 | H164: 0.064952178 | I164: 0.30069135 | J164: 0 | K164: -0.10490832 | L164: 0.25410512 | M164: 0 | N164: 0 | O164: -0.011935971 | P164: 0 | Q164: 0 | R164: 0 | S164: 0 | T164: 0 | U164: 0 | V164: 0 | W164: 0 | X164: 0 | Y164: 0 | Z164: 0 | AA164: 0 | AB164: 0 | AC164: 0 | AD164: 0 | AE164: 0 | AF164: 0.23088259 | AG164: 0
A165: 2020 Q1 | B165: 0 | C165: -0.0060180705 | D165: 0 | E165: -0.38159159 | F165: -0.00059962951 | G165: -0.014968144 | H165: 0.051346829 | I165: 0.29508538 | J165: 0 | K165: -0.11182283 | L165: 0.2492465 | M165: 0 | N165: 0 | O165: -0.012673943 | P165: 0 | Q165: 0 | R165: 0 | S165: 0 | T165: 0 | U165: 0 | V165: 0 | W165: 0 | X165: 0 | Y165: 0 | Z165: 0 | AA165: 0 | AB165: 0 | AC165: 0 | AD165: 0 | AE165: 0 | AF165: 0.22639652 | AG165: 0
A166: 2020 Q2 | B166: 0 | C166: -0.0078167083 | D166: 0 | E166: -0.19851024 | F166: 0 | G166: -0.023540361 | H166: 0.026300831 | I166: 0.29427692 | J166: 0 | K166: -0.18587257 | L166: 0.24853763 | M166: 0 | N166: 0 | O166: -0.01281071 | P166: 0 | Q166: 0 | R166: 0 | S166: 0 | T166: 0 | U166: 0 | V166: 0 | W166: 0 | X166: 0 | Y166: 0 | Z166: 0 | AA166: 0 | AB166: 0 | AC166: 0 | AD166: 0 | AE166: 0 | AF166: 0.22573728 | AG166: 0
A167: 2020 Q3 | B167: 0 | C167: -0.010989553 | D167: 0 | E167: -0.20829735 | F167: -0.0009549216 | G167: -0.037552731 | H167: 0.073203946 | I167: 0.29268076 | J167: 0 | K167: -0.18181866 | L167: 0.24720798 | M167: 0 | N167: 0 | O167: -0.020119446 | P167: 0.0010565148 | Q167: 0 | R167: 0.087806471 | S167: 0 | T167: 0 | U167: 0 | V167: 0 | W167: 0 | X167: 0 | Y167: 0 | Z167: 0 | AA167: 0 | AB167: 0 | AC167: 0 | AD167: 0 | AE167: 0 | AF167: 0.22454049 | AG167: 0
A168: 2020 Q4 | B168: 0 | C168: -0.016162092 | D168: 0 | E168: -0.34827 | F168: 0 | G168: -0.048440732 | H168: 0.057374981 | I168: 0.29987006 | J168: 0 | K168: -0.14784345 | L168: 0.25328064 | M168: 0 | N168: 0 | O168: -0.016194671 | P168: 0.00071732288 | Q168: 0 | R168: -0.33114421 | S168: 0 | T168: 0 | U168: 0 | V168: 0 | W168: 0 | X168: 0 | Y168: 0 | Z168: 0 | AA168: 0 | AB168: 0 | AC168: 0 | AD168: 0 | AE168: 0 | AF168: 0.23005652 | AG168: 0
A169: 2021 Q1 | B169: 0 | C169: -0.010135597 | D169: 0 | E169: -0.26651389 | F169: -0.00047634651 | G169: -0.056031087 | H169: 0.073611697 | I169: 0.29600056 | J169: 0 | K169: -0.11869235 | L169: 0.25002983 | M169: 0 | N169: 0 | O169: -0.023081531 | P169: 9.926066e-05 | Q169: 0 | R169: -0.16025668 | S169: 0 | T169: 0 | U169: 0 | V169: 0 | W169: 0 | X169: 0 | Y169: 0 | Z169: 0 | AA169: 0 | AB169: 0 | AC169: 0 | AD169: 0 | AE169: 0 | AF169: 0.22711412 | AG169: 0
A170: 2021 Q2 | B170: 0 | C170: -0.0077402308 | D170: 0 | E170: -0.26414103 | F170: 0 | G170: -0.12376011 | H170: 0.12131368 | I170: 0.29546402 | J170: 0 | K170: -0.16206219 | L170: 0.24963824 | M170: 0 | N170: 0 | O170: -0.017523923 | P170: 0.00012517702 | Q170: 0 | R170: -0.10594406 | S170: 0 | T170: 0 | U170: 0 | V170: 0 | W170: 0 | X170: 0 | Y170: 0 | Z170: 0 | AA170: 0 | AB170: 0 | AC170: 0 | AD170: 0 | AE170: 0 | AF170: 0.22679478 | AG170: 0
A171: 2021 Q3 | B171: 0 | C171: -0.0062423296 | D171: 0 | E171: -0.40702472 | F171: 0 | G171: -0.11133221 | H171: 0.12461512 | I171: 0.29463735 | J171: 0 | K171: -0.17944943 | L171: 0.2490189 | M171: 0 | N171: 0 | O171: -0.030195397 | P171: 0 | Q171: 0 | R171: 0.072554215 | S171: 0 | T171: 0 | U171: 0 | V171: 0 | W171: 0 | X171: 0 | Y171: 0 | Z171: 0 | AA171: 0 | AB171: 0 | AC171: 0 | AD171: 0 | AE171: 0 | AF171: 0.22627879 | AG171: 0
A172: 2021 Q4 | B172: 0 | C172: -0.014094377 | D172: 0 | E172: -0.50301626 | F172: 0 | G172: -0.10230574 | H172: 0.14571045 | I172: 0.29356197 | J172: 0 | K172: -0.18914641 | L172: 0.24826527 | M172: 0 | N172: 0 | O172: -0.028210339 | P172: 0.00313187 | Q172: 0 | R172: 0.12286205 | S172: 0 | T172: 0 | U172: 0 | V172: 0 | W172: 0 | X172: 0 | Y172: 0 | Z172: 0 | AA172: 0 | AB172: 0 | AC172: 0 | AD172: 0 | AE172: 0 | AF172: 0.22568555 | AG172: 0
A173: 2022 Q1 | B173: 0 | C173: -0.0070807689 | D173: 0 | E173: -0.33761481 | F173: -0.00045862264 | G173: -0.092104138 | H173: 0.11160135 | I173: 0.29000857 | J173: 0 | K173: -0.18150716 | L173: 0.24511146 | M173: 0 | N173: 0 | O173: -0.019423972 | P173: 0.0018974911 | Q173: 0 | R173: 0.33387217 | S173: 0 | T173: 0 | U173: 0 | V173: 0 | W173: 0 | X173: 0 | Y173: 0 | Z173: 0 | AA173: 0 | AB173: 0 | AC173: 0 | AD173: 0 | AE173: 0 | AF173: 0.22273093 | AG173: 0
... A185: 2025 Q1 | B185: 0 | C185: -0.0010999407 | D185: 0 | E185: 0 | F185: 0 | G185: 0 | H185: 2.4499664 | I185: 0 | J185: 0 | K185: -0.079108279 | L185: -0.37316397 | M185: 0.0091965016 | N185: 0 | O185: -0.026768295 | P185: -0.089103734 | Q185: 0 | R185: 0.25091525 | S185: 0 | T185: 0 | U185: 0 | V185: 0 | W185: 0 | X185: 0 | Y185: 0 | Z185: 0 | AA185: 0 | AB185: 0 | AC185: 0 | AD185: 0 | AE185: 0 | AF185: 0.0010356647 | AG185: 0
B186: 0
B187: 0
A188: KMX | B188: 0
A189: Vintage | B189: 0 | C189: Previous ACA chargeoff | D189: Small amount financed | E189: Zero cash down | F189: High mileage vehicle | G189: High PTI | H189: Car make | I189: Theft risk | J189: MCY high model score, low mileage | K189: Weekday/weekend decision | L189: Secured credit (Chime, etc.) | M189: Employment type | N189: High cash down EchoPark | O189: Authorized tradelines | P189: Clip | Q189: Vehicle Age | R189: Dealer Level (Non-KMX) | S189: Mileage/age | T189: Japanese | U189: Vehicle class | V189: Fuel type | W189: Luxury classification | X189: LOB | Y189: Driver flag | Z189: Impound probability | AA189: Job time | AB189: Low FICO | AC189: Low Vantage | AD189: Louisiana | AE189: Existing DQ | AF189: Null FICO with Vantage | AG189: Soft Pull
A190: 2016 Q1 | B190: 0 | C190: 0 | D190: 0 | E190: 0 | F190: 0 | G190: -0.42935241 | H190: 0 | I190: 0 | J190: 0 | K190: 0 | L190: -0.23514772 | M190: 0 | N190: 0 | O190: 0.0042536417 | P190: 0.10144122 | Q190: 1.9962504 | R190: 0 | S190: 0 | T190: 0 | U190: 0 | V190: 0 | W190: 0 | X190: 0 | Y190: 0 | Z190: 0 | AA190: -0.61254974 | AB190: -0.18347931 | AC190: -0.0079853412 | AD190: -0.11420445 | AE190: -0.20275031 | AF190: -0.15191857 | AG190: 0.42250908
A191: 2016 Q2 | B191: 0 | C191: 0 | D191: 0 | E191: 0 | F191: 0 | G191: -0.28787541 | H191: 0 | I191: 0 | J191: 0 | K191: 0 | L191: 0.12315291 | M191: 0 | N191: 0 | O191: 0.17131424 | P191: 0.049254079 | Q191: 1.8802485 | R191: 0 | S191: 0 | T191: 0 | U191: 0 | V191: 0 | W191: 0 | X191: 0 | Y191: 0 | Z191: 0 | AA191: -0.71232911 | AB191: -0.20285202 | AC191: -0.0038364925 | AD191: -0.086625861 | AE191: -0.013534933 | AF191: 0.13256985 | AG191: 0.39444866
A192: 2016 Q3 | B192: 0 | C192: 0 | D192: 0 | E192: 0 | F192: 0 | G192: -0.35097826 | H192: 0 | I192: 0 | J192: 0 | K192: 0 | L192: 0.20092622 | M192: 0 | N192: 0 | O192: 0.20092622 | P192: 0.032236815 | Q192: 1.7618754 | R192: 0 | S192: 0 | T192: 0 | U192: 0 | V192: 0 | W192: 0 | X192: 0 | Y192: 0 | Z192: 0 | AA192: -0.82145812 | AB192: -0.21665616 | AC192: 0 | AD192: -0.10787365 | AE192: 0 | AF192: 0.17270386 | AG192: 0.3855845
A193: 2016 Q4 | B193: 0 | C193: 0 | D193: 0 | E193: 0 | F193: 0 | G193: -0.34073231 | H193: 0 | I193: 0 | J193: 0 | K193: 0 | L193: 0.19864418 | M193: 0 | N193: 0 | O193: 0.19864418 | P193: 0.068707691 | Q193: 1.8204952 | R193: 0 | S193: 0 | T193: 0 | U193: 0 | V193: 0 | W193: 0 | X193: 0 | Y193: 0 | Z193: 0 | AA193: -0.82917249 | AB193: -0.23499254 | AC193: 0 | AD193: -0.14771956 | AE193: 0 | AF193: 0.17337944 | AG193: 0.37913974
...

Sheet t-1 Data Table
A1: roa_dealer_group | B1: rowid | C1: lookup | D1: notes | E1: datetime_inserted | F1: effective_date | G1: halfbaked_date | H1: mroa | I1: orig_yield | J1: cnl_effect | K1: var_cost | L1: cost_of_debt | M1: run_rate_nb | N1: model_score | O1: model_name | P1: wal | Q1: wal_cfc | R1: wal_adj_factor | S1: apr | T1: apr_realization_factor | U1: discount | V1: fee_income | W1: pmt_proc_income | X1: addl_income | Y1: cnl | Z1: gross_loss | AA1: recovery | AB1: cnl_adj_factor | AC1: gross_loss_cfc | AD1: gross_loss_adj_factor | AE1: recovery_cfc | AF1: recovery_adj_factor | AG1: debt_int_rate | AH1: securitization_cost | AI1: debt_adv_rate | AJ1: orig_cost | AK1: serv_cost | AL1: addl_cost | AM1: days_till_half_baked | AN1: sort | AO1: latest_row_flag | AP1: loss_meeting_flag | AQ1: pricing_change_flag | AR1: is_current_flag | AS1: elasticity | AT1: nb_ratio | AU1: version_start_datetime | AV1: version_end_datetime | AW1: ticket_no | AX1: addl_cost_of_debt
A2: AN | B2: 393 | C2: AN393 | D2: January Loss Meeting Adjustments | E2: 46048.577 | F2: 46045 | H2: 0.079841893 | I2: 0.26518303 | J2: 0.11288237 | K2: 0.027276764 | L2: 0.045182 | M2: 188.6976 | N2: 139.6 | O2: Franchise3.0 | P2: 2.11 | Q2: 2.2067215 | R2: 0.95616961 | S2: 0.25076585 | T2: 0.9228 | U2: 0.0527 | V2: 0.003 | W2: 0.0041 | X2: 0.0017 | Y2: 0.2381818 | Z2: 0.54668855 | AA2: 0.30850675 | AB2: 1.2476717 | AC2: 0.438167 | AD2: 1 | AE2: 0.24726597 | AF2: 1 | AG2: 0.0525 | AH2: 0.0026 | AI2: 0.82 | AJ2: 0.031600973 | AK2: 0.0123 | AL2: 0 | AM2: 16 | AN2: 2 | AO2: 1 | AP2: 1 | AQ2: 0 | AR2: 1 | AS2: 0.01 | AT2: 0.9935 | AU2: 46048.577 | AV2: 2958101 | AX2: 0 | AZ2: 0.005 | BA2: 0.0027 | BB2: 0.072141893 | BC2: 147.3 | BD2: 1.94 | BE2: 1.58 | BF2: 0.25 | BG2: 3.6 | BH2: 0.5 | BI2: 3.9 | BJ2: 0 | BK2: -0.3
A3: ENT | B3: 277 | C3: ENT277 | D3: January Loss Meeting Adjustments | E3: 46048.581 | F3: 46045 | H3: 0.064707554 | I3: 0.25001964 | J3: 0.11285332 | K3: 0.027276764 | L3: 0.045182 | M3: 425 | N3: 138.8 | O3: Franchise3.0 | P3: 2.38 | Q3: 2.2952156 | R3: 1.0369396 | S3: 0.24028528 | T3: 0.9259 | U3: 0.0446 | V3: 0.003 | W3: 0.0041 | X3: 0.0017 | Y3: 0.2685909 | Z3: 0.55097466 | AA3: 0.28238376 | AB3: 1.1000536 | AC3: 0.50086165 | AD3: 1 | AE3: 0.2567 | AF3: 1 | AG3: 0.0525 | AH3: 0.0026 | AI3: 0.82 | AJ3: 0.035644699 | AK3: 0.0123 | AL3: 0 | AM3: 13 | AN3: 4 | AO3: 1 | AP3: 1 | AQ3: 0 | AR3: 1 | AS3: 0.01 | AT3: 0.9935 | AU3: 46048.581 | AV3: 2958101 | AX3: 0 | AZ3: 0.005 | BA3: 0.0027 | BB3: 0.057007554 | BC3: 141.7 | BD3: 1.45 | BE3: 1.33 | BF3: 0.235 | BG3: 1.7 | BH3: 0 | BI3: 1.5 | BJ3: 0 | BK3: -0.3
A4: FLD | B4: 276 | C4: FLD276 | D4: January Loss Meeting Adjustments | E4: 46048.581 | F4: 46045 | H4: 0.067639793 | I4: 0.23677166 | J4: 0.096673106 | K4: 0.027276764 | L4: 0.045182 | M4: 224.91 | N4: 138.7 | O4: Franchise3.0 | P4: 2.35 | Q4: 2.2769093 | R4: 1.0321008 | S4: 0.23670091 | T4: 0.933 | U4: 0.01675482 | V4: 0.003 | W4: 0.0041 | X4: 0.0017 | Y4: 0.2271818 | Z4: 0.63212863 | AA4: 0.40494683 | AB4: 1.6447881 | AC4: 0.38432223 | AD4: 1 | AE4: 0.2462 | AF4: 1 | AG4: 0.0525 | AH4: 0.0026 | AI4: 0.82 | AJ4: 0.035195396 | AK4: 0.0123 | AL4: 0 | AM4: 13 | AN4: 5 | AO4: 1 | AP4: 1 | AQ4: 0 | AR4: 1 | AS4: 0.01 | AT4: 0.9935 | AU4: 46048.581 | AV4: 2958101 | AX4: 0 | AZ4: 0.005 | BA4: 0.0027 | BB4: 0.059939793 | BC4: 147.2 | BD4: 1.45 | BE4: 1.37 | BF4: 0.235 | BG4: 5.6 | BH4: 2 | BI4: 1 | BJ4: 0 | BK4: -0.1
A5: FRN | B5: 404 | C5: FRN404 | D5: January Loss Meeting Adjustments | E5: 46048.581 | F5: 46045 | H5: 0.068789886 | I5: 0.27306685 | J5: 0.1318182 | K5: 0.027276764 | L5: 0.045182 | M5: 658.56 | N5: 142 | O5: Franchise3.0 | P5: 2 | Q5: 2.1786756 | R5: 0.9179889 | S5: 0.25645294 | T5: 0.9053 | U5: 0.0642 | V5: 0.003 | W5: 0.0041 | X5: 0.0017 | Y5: 0.2636364 | Z5: 0.56751475 | AA5: 0.30387835 | AB5: 1.2137484 | AC5: 0.46757197 | AD5: 1 | AE5: 0.25036353 | AF5: 1 | AG5: 0.0525 | AH5: 0.0026 | AI5: 0.82 | AJ5: 0.029953529 | AK5: 0.0123 | AL5: 0 | AM5: 19 | AN5: 6 | AO5: 1 | AP5: 1 | AQ5: 0 | AR5: 1 | AS5: 0.01 | AT5: 0.993 | AU5: 46048.581 | AV5: 2958101 | AX5: 0 | AZ5: 0.005 | BA5: 0.0027 | BB5: 0.061089886 | BC5: 150.7 | BD5: 1.94 | BE5: 1.44 | BF5: 0.25 | BG5: 3.4 | BH5: 0 | BI5: 5.9 | BJ5: 0 | BK5: -0.6
A6: KMX | B6: 419 | C6: KMX419 | D6: KMX LTV/RAGU True-up (MTN3.1 expansion) | E6: 46063 | F6: 46062 | H6: 0.069424462 | I6: 0.24842568 | J6: 0.11690245 | K6: 0.016916764 | L6: 0.045182 | M6: 1885.52 | N6: 142.20524 | O6: Mountain3 | P6: 2.36 | Q6: 2.3970424 | R6: 0.9845466 | S6: 0.24449264 | T6: 0.9203 | U6: 0.032377076 | V6: 0.003 | W6: 0.0041 | X6: 0.0026 | Y6: 0.27588978 | Z6: 0.63021777 | AA6: 0.35432799 | AB6: 1.2579726 | AC6: 0.50097895 | AD6: 1 | AE6: 0.28166591 | AF6: 1 | AG6: 0.0525 | AH6: 0.0026 | AI6: 0.82 | AJ6: 0.011367564 | AK6: 0.0121 | AL6: 0 | AM6: 4 | AN6: 1 | AO6: 1 | AP6: 0 | AQ6: 0 | AR6: 1 | AS6: 0.0065 | AT6: 0.94 | AU6: 46063.199 | AV6: 2958101 | AX6: 0 | AZ6: 0.005 | BA6: 0.0027 | BB6: 0.061724462 | BC6: 148.1 | BD6: 1.59 | BE6: 1.57 | BF6: 0.25 | BG6: 4.7 | BH6: 0.47 | BI6: 0.2 | BJ6: 0 | BK6: 0.5
A7: STG | B7: 412 | C7: STG412 | D7: January Loss Meeting Adjustments | E7: 46048.58 | F7: 46045 | H7: 0.071517489 | I7: 0.25716918 | J7: 0.11319293 | K7: 0.027276764 | L7: 0.045182 | M7: 491.568 | N7: 138.6 | O7: Franchise3.0 | P7: 2.05 | Q7: 2.1801666 | R7: 0.9402951 | S7: 0.2456 | T7: 0.9215 | U7: 0.0452 | V7: 0.003 | W7: 0.0041 | X7: 0.0017 | Y7: 0.2320455 | Z7: 0.49132694 | AA7: 0.25928144 | AB7: 1.0558866 | AC7: 0.46532167 | AD7: 1 | AE7: 0.24555802 | AF7: 1 | AG7: 0.0525 | AH7: 0.0026 | AI7: 0.82 | AJ7: 0.030702367 | AK7: 0.0123 | AL7: 0 | AM7: 17 | AN7: 3 | AO7: 1 | AP7: 1 | AQ7: 0 | AR7: 1 | AS7: 0.01 | AT7: 0.995 | AU7: 46048.58 | AV7: 2958101 | AX7: 0 | AZ7: 0.005 | BA7: 0.0027 | BB7: 0.063817489 | BC7: 151 | BD7: 1.94 | BE7: 1.45 | BF7: 0.25 | BG7: 3.7 | BH7: 3 | BI7: 5.7 | BJ7: 0 | BK7: 0
A8: NonKMXENT | M8: =SUM(M2,M4,M5,M7) -> 1563.7356 | N8: =(M2*N2+M4*N4+M5*N5+M7*N7)/M8 -> 140.16695

Sheet distribution_rolledup
A1: roa_dealer_group | B1: 2016 | C1: 2017 | D1: 2018 | E1: 2019 | F1: 20201 | G1: 20202 | H1: 20203 | I1: 20204 | J1: 20211 | K1: 20212 | L1: 20213 | M1: 20214 | N1: 20221 | O1: 20222 | P1: 20223 | Q1: 20224 | R1: 20231 | S1: 20232 | T1: 20233 | U1: 20234 | V1: 20241 | W1: 20242 | X1: 20243 | Y1: 20244
A2: roa_dealer_group
A3: AN | B3: 0.13632879 | C3: 0.14437905 | D3: 0.1117387 | E3: 0.061138445 | F3: 0.057627615 | G3: 0.059112182 | H3: 0.048653702 | I3: 0.049697267 | J3: 0.048043084 | K3: 0.053449965 | L3: 0.041309421 | M3: 0.043412194 | N3: 0.039799267 | O3: 0.042594829 | P3: 0.049512519 | Q3: 0.044590175 | R3: 0.046034244 | S3: 0.048740295 | T3: 0.049392118 | U3: 0.059191728 | V3: 0.059998851 | W3: 0.060395456 | X3: 0.052556052 | Y3: 0.053144883 | Z3: 0.058869376 | AA3: 0.064949184 | AB3: 0.063788613 | AC3: 0.057503561
A4: ENT | E4: 0.0035037966 | F4: 0.07681912 | G4: 0.10027198 | H4: 0.087057922 | I4: 0.11120634 | J4: 0.13327728 | K4: 0.17504544 | L4: 0.15209764 | M4: 0.14082133 | N4: 0.12962489 | O4: 0.12475696 | P4: 0.12489133 | Q4: 0.18717176 | R4: 0.20763323 | S4: 0.19060656 | T4: 0.16353473 | U4: 0.17103147 | V4: 0.1541449 | W4: 0.13987855 | X4: 0.13666921 | Y4: 0.15194482 | Z4: 0.15823241 | AA4: 0.14592681 | AB4: 0.14116288 | AC4: 0.13328221
A5: FLD | E5: 0.015147625 | F5: 0.050613008 | G5: 0.040833289 | H5: 0.031133028 | I5: 0.017144042 | J5: 0.021178634 | K5: 0.040948054 | L5: 0.040064272 | M5: 0.032455053 | N5: 0.024748144 | O5: 0.02506867 | P5: 0.028075452 | Q5: 0.02619653 | R5: 0.014230322 | S5: 0.021409151 | T5: 0.023341074 | U5: 0.025229678 | V5: 0.032670344 | W5: 0.047948104 | X5: 0.036514839 | Y5: 0.03571671 | Z5: 0.045582068 | AA5: 0.044852788 | AB5: 0.044737696 | AC5: 0.062794499
A6: FRN | B6: 0.016158291 | C6: 0.027996002 | D6: 0.017103138 | E6: 0.016819172 | F6: 0.04596485 | G6: 0.065478304 | H6: 0.070236663 | I6: 0.080994429 | J6: 0.070801378 | K6: 0.10465389 | L6: 0.10439154 | M6: 0.12238182 | N6: 0.10580061 | O6: 0.11428738 | P6: 0.12854048 | Q6: 0.095478588 | R6: 0.05917033 | S6: 0.081172555 | T6: 0.094753264 | U6: 0.16513936 | V6: 0.17909316 | W6: 0.2055444 | X6: 0.18686457 | Y6: 0.20070278 | Z6: 0.1840832 | AA6: 0.20142581 | AB6: 0.21178024 | AC6: 0.17107459
A7: KMX | B7: 0.6220219 | C7: 0.66048827 | D7: 0.68106261 | E7: 0.72816299 | F7: 0.64136881 | G7: 0.60892731 | H7: 0.65229696 | I7: 0.64147256 | J7: 0.63378931 | K7: 0.51879531 | L7: 0.56162154 | M7: 0.55471527 | N7: 0.6080436 | O7: 0.59834995 | P7: 0.59103912 | Q7: 0.59243675 | R7: 0.63796686 | S7: 0.61526537 | T7: 0.614259 | U7: 0.48760551 | V7: 0.48605818 | W7: 0.41447141 | X7: 0.46955166 | Y7: 0.44073587 | Z7: 0.43785652 | AA7: 0.41312542 | AB7: 0.4165421 | AC7: 0.47148399
A8: STG | B8: 0.22549102 | C8: 0.16713668 | D8: 0.19009555 | E8: 0.17522797 | F8: 0.12760659 | G8: 0.12537694 | H8: 0.11062172 | I8: 0.09948536 | J8: 0.092910316 | K8: 0.10710734 | L8: 0.10051559 | M8: 0.10621433 | N8: 0.091983491 | O8: 0.094942212 | P8: 0.077941098 | Q8: 0.054126201 | R8: 0.034965012 | S8: 0.042806062 | T8: 0.054719811 | U8: 0.09180226 | V8: 0.088034553 | W8: 0.13176208 | X8: 0.11784368 | Y8: 0.11775493 | Z8: 0.11537643 | AA8: 0.12971999 | AB8: 0.12198847 | AC8: 0.10386116

Sheet POS
A1: POS | B1: 2016 | C1: 2017 | D1: 2018 | E1: 2019 | F1: 2020 Q1 | G1: 2020 Q2 | H1: 2020 Q3 | I1: 2020 Q4 | J1: 2021 Q1 | K1: 2021 Q2 | L1: 2021 Q3 | M1: 2021 Q4 | N1: 2022 Q1 | O1: 2022 Q2 | P1: 2022 Q3 | Q1: 2022 Q4 | R1: 2023 Q1 | S1: 2023 Q2 | T1: 2023 Q3 | U1: 2023 Q4 | V1: 2024 Q1 | W1: 2024 Q2 | X1: 2024 Q3 | Y1: 2024 Q4
A2: Contract MS | B2: ='AN Table'!B2*distribution_rolledup!B3+'FRN Table'!B2*distribution_rolledup!B6+'STG Table'!B2*distribution_rolledup!B8+'KMX Table'!B2*distribution_rolledup!B7 -> 134.03213 | C2: ='AN Table'!C2*distribution_rolledup!C3+'FRN Table'!C2*distribution_rolledup!C6+'STG Table'!C2*distribution_rolledup!C8+'KMX Table'!C2*distribution_rolledup!C7 -> 136.8848 | D2: ='AN Table'!D2*distribution_rolledup!D3+'FRN Table'!D2*distribution_rolledup!D6+'STG Table'!D2*distribution_rolledup!D8+'KMX Table'!D2*distribution_rolledup!D7 -> 136.04759 | E2: ='AN Table'!E2*distribution_rolledup!E3+'FRN Table'!E2*distribution_rolledup!E6+'STG Table'!E2*distribution_rolledup!E8+'KMX Table'!E2*distribution_rolledup!E7 -> 132.66846 | F2: ='AN Table'!F2*distribution_rolledup!F3+'FRN Table'!F2*distribution_rolledup!F6+'STG Table'!F2*distribution_rolledup!F8+'FLD Table'!B2*distribution_rolledup!F5+'ENT Table'!B2*distribution_rolledup!F4+'KMX Table'!F2*distribution_rolledup!F7 -> 134.20188 | G2: ='AN Table'!G2*distribution_rolledup!G3+'FRN Table'!G2*distribution_rolledup!G6+'STG Table'!G2*distribution_rolledup!G8+'FLD Table'!C2*distribution_rolledup!G5+'ENT Table'!C2*distribution_rolledup!G4+'KMX Table'!G2*distribution_rolledup!G7 -> 136.45574 | H2: ='AN Table'!H2*distribution_rolledup!H3+'FRN Table'!H2*distribution_rolledup!H6+'STG Table'!H2*distribution_rolledup!H8+'FLD Table'!D2*distribution_rolledup!H5+'ENT Table'!D2*distribution_rolledup!H4+'KMX Table'!H2*distribution_rolledup!H7 -> 137.66854 | I2: ='AN Table'!I2*distribution_rolledup!I3+'FRN Table'!I2*distribution_rolledup!I6+'STG Table'!I2*distribution_rolledup!I8+'FLD Table'!E2*distribution_rolledup!I5+'ENT Table'!E2*distribution_rolledup!I4+'KMX Table'!I2*distribution_rolledup!I7 -> 136.28155 | J2: ='AN Table'!J2*distribution_rolledup!J3+'FRN Table'!J2*distribution_rolledup!J6+'STG Table'!J2*distribution_rolledup!J8+'FLD Table'!F2*distribution_rolledup!J5+'ENT Table'!F2*distribution_rolledup!J4+'KMX Table'!J2*distribution_rolledup!J7 -> 135.21565 | K2: ='AN Table'!K2*distribution_rolledup!K3+'FRN Table'!K2*distribution_rolledup!K6+'STG Table'!K2*distribution_rolledup!K8+'FLD Table'!G2*distribution_rolledup!K5+'ENT Table'!G2*distribution_rolledup!K4+'KMX Table'!K2*distribution_rolledup!K7 -> 134.96494 | L2: ='AN Table'!L2*distribution_rolledup!L3+'FRN Table'!L2*distribution_rolledup!L6+'STG Table'!L2*distribution_rolledup!L8+'FLD Table'!H2*distribution_rolledup!L5+'ENT Table'!H2*distribution_rolledup!L4+'KMX Table'!L2*distribution_rolledup!L7 -> 134.17384 | M2: ='AN Table'!M2*distribution_rolledup!M3+'FRN Table'!M2*distribution_rolledup!M6+'STG Table'!M2*distribution_rolledup!M8+'FLD Table'!I2*distribution_rolledup!M5+'ENT Table'!I2*distribution_rolledup!M4+'KMX Table'!M2*distribution_rolledup!M7 -> 132.78166 | ... Y2: ='AN Table'!Y2*distribution_rolledup!Y3+'FRN Table'!Y2*distribution_rolledup!Y6+'STG Table'!Y2*distribution_rolledup!Y8+'FLD Table'!U2*distribution_rolledup!Y5+'ENT Table'!U2*distribution_rolledup!Y4+'KMX Table'!Y2*distribution_rolledup!Y7 -> 138.56811
A3: RAGU t0 | B3: ='AN Table'!B7*distribution_rolledup!B3+'FRN Table'!B7*distribution_rolledup!B6+'STG Table'!B7*distribution_rolledup!B8+'KMX Table'!B6*distribution_rolledup!B7 -> 136.97369 | C3: ='AN Table'!C7*distribution_rolledup!C3+'FRN Table'!C7*distribution_rolledup!C6+'STG Table'!C7*distribution_rolledup!C8+'KMX Table'!C6*distribution_rolledup!C7 -> 140.41583 | D3: ='AN Table'!D7*distribution_rolledup!D3+'FRN Table'!D7*distribution_rolledup!D6+'STG Table'!D7*distribution_rolledup!D8+'KMX Table'!D6*distribution_rolledup!D7 -> 139.31896 | E3: ='AN Table'!E7*distribution_rolledup!E3+'FRN Table'!E7*distribution_rolledup!E6+'STG Table'!E7*distribution_rolledup!E8+'KMX Table'!E6*distribution_rolledup!E7 -> 135.56952 | F3: ='AN Table'!F7*distribution_rolledup!F3+'FRN Table'!F7*distribution_rolledup!F6+'STG Table'!F7*distribution_rolledup!F8+'FLD Table'!B7*distribution_rolledup!F5+'ENT Table'!B7*distribution_rolledup!F4+'KMX Table'!F6*distribution_rolledup!F7 -> 135.42671 | G3: ='AN Table'!G7*distribution_rolledup!G3+'FRN Table'!G7*distribution_rolledup!G6+'STG Table'!G7*distribution_rolledup!G8+'FLD Table'!C7*distribution_rolledup!G5+'ENT Table'!C7*distribution_rolledup!G4+'KMX Table'!G6*distribution_rolledup!G7 -> 137.24691 | H3: ='AN Table'!H7*distribution_rolledup!H3+'FRN Table'!H7*distribution_rolledup!H6+'STG Table'!H7*distribution_rolledup!H8+'FLD Table'!D7*distribution_rolledup!H5+'ENT Table'!D7*distribution_rolledup!H4+'KMX Table'!H6*distribution_rolledup!H7 -> 140.7886 | I3: ='AN Table'!I7*distribution_rolledup!I3+'FRN Table'!I7*distribution_rolledup!I6+'STG Table'!I7*distribution_rolledup!I8+'FLD Table'!E7*distribution_rolledup!I5+'ENT Table'!E7*distribution_rolledup!I4+'KMX Table'!I6*distribution_rolledup!I7 -> 137.49636 | J3: ='AN Table'!J7*distribution_rolledup!J3+'FRN Table'!J7*distribution_rolledup!J6+'STG Table'!J7*distribution_rolledup!J8+'FLD Table'!F7*distribution_rolledup!J5+'ENT Table'!F7*distribution_rolledup!J4+'KMX Table'!J6*distribution_rolledup!J7 -> 138.11823 | K3: ='AN Table'!K7*distribution_rolledup!K3+'FRN Table'!K7*distribution_rolledup!K6+'STG Table'!K7*distribution_rolledup!K8+'FLD Table'!G7*distribution_rolledup!K5+'ENT Table'!G7*distribution_rolledup!K4+'KMX Table'!K6*distribution_rolledup!K7 -> 139.67342 | L3: ='AN Table'!L7*distribution_rolledup!L3+'FRN Table'!L7*distribution_rolledup!L6+'STG Table'!L7*distribution_rolledup!L8+'FLD Table'!H7*distribution_rolledup!L5+'ENT Table'!H7*distribution_rolledup!L4+'KMX Table'!L6*distribution_rolledup!L7 -> 137.79135 | M3: ='AN Table'!M7*distribution_rolledup!M3+'FRN Table'!M7*distribution_rolledup!M6+'STG Table'!M7*distribution_rolledup!M8+'FLD Table'!I7*distribution_rolledup!M5+'ENT Table'!I7*distribution_rolledup!M4+'KMX Table'!M6*distribution_rolledup!M7 -> 135.74874 | ... Y3: ='AN Table'!Y7*distribution_rolledup!Y3+'FRN Table'!Y7*distribution_rolledup!Y6+'STG Table'!Y7*distribution_rolledup!Y8+'FLD Table'!U7*distribution_rolledup!Y5+'ENT Table'!U7*distribution_rolledup!Y4+'KMX Table'!Y6*distribution_rolledup!Y7 -> 142.48308
A4: RAGU gross loss | B4: ='AN Table'!B8*distribution_rolledup!B3+'FRN Table'!B8*distribution_rolledup!B6+'STG Table'!B8*distribution_rolledup!B8+'KMX Table'!B7*distribution_rolledup!B7 -> 137.12176 | C4: ='AN Table'!C8*distribution_rolledup!C3+'FRN Table'!C8*distribution_rolledup!C6+'STG Table'!C8*distribution_rolledup!C8+'KMX Table'!C7*distribution_rolledup!C7 -> 140.12729 | D4: ='AN Table'!D8*distribution_rolledup!D3+'FRN Table'!D8*distribution_rolledup!D6+'STG Table'!D8*distribution_rolledup!D8+'KMX Table'!D7*distribution_rolledup!D7 -> 139.25952 | E4: ='AN Table'!E8*distribution_rolledup!E3+'FRN Table'!E8*distribution_rolledup!E6+'STG Table'!E8*distribution_rolledup!E8+'KMX Table'!E7*distribution_rolledup!E7 -> 136.01607 | F4: ='AN Table'!F8*distribution_rolledup!F3+'FRN Table'!F8*distribution_rolledup!F6+'STG Table'!F8*distribution_rolledup!F8+'FLD Table'!B8*distribution_rolledup!F5+'ENT Table'!B8*distribution_rolledup!F4+'KMX Table'!F7*distribution_rolledup!F7 -> 136.91625 | G4: ='AN Table'!G8*distribution_rolledup!G3+'FRN Table'!G8*distribution_rolledup!G6+'STG Table'!G8*distribution_rolledup!G8+'FLD Table'!C8*distribution_rolledup!G5+'ENT Table'!C8*distribution_rolledup!G4+'KMX Table'!G7*distribution_rolledup!G7 -> 139.09272 | H4: ='AN Table'!H8*distribution_rolledup!H3+'FRN Table'!H8*distribution_rolledup!H6+'STG Table'!H8*distribution_rolledup!H8+'FLD Table'!D8*distribution_rolledup!H5+'ENT Table'!D8*distribution_rolledup!H4+'KMX Table'!H7*distribution_rolledup!H7 -> 140.33607 | I4: ='AN Table'!I8*distribution_rolledup!I3+'FRN Table'!I8*distribution_rolledup!I6+'STG Table'!I8*distribution_rolledup!I8+'FLD Table'!E8*distribution_rolledup!I5+'ENT Table'!E8*distribution_rolledup!I4+'KMX Table'!I7*distribution_rolledup!I7 -> 138.5801 | J4: ='AN Table'!J8*distribution_rolledup!J3+'FRN Table'!J8*distribution_rolledup!J6+'STG Table'!J8*distribution_rolledup!J8+'FLD Table'!F8*distribution_rolledup!J5+'ENT Table'!F8*distribution_rolledup!J4+'KMX Table'!J7*distribution_rolledup!J7 -> 137.59034 | K4: ='AN Table'!K8*distribution_rolledup!K3+'FRN Table'!K8*distribution_rolledup!K6+'STG Table'!K8*distribution_rolledup!K8+'FLD Table'!G8*distribution_rolledup!K5+'ENT Table'!G8*distribution_rolledup!K4+'KMX Table'!K7*distribution_rolledup!K7 -> 136.69338 | L4: ='AN Table'!L8*distribution_rolledup!L3+'FRN Table'!L8*distribution_rolledup!L6+'STG Table'!L8*distribution_rolledup!L8+'FLD Table'!H8*distribution_rolledup!L5+'ENT Table'!H8*distribution_rolledup!L4+'KMX Table'!L7*distribution_rolledup!L7 -> 135.9158 | M4: ='AN Table'!M8*distribution_rolledup!M3+'FRN Table'!M8*distribution_rolledup!M6+'STG Table'!M8*distribution_rolledup!M8+'FLD Table'!I8*distribution_rolledup!M5+'ENT Table'!I8*distribution_rolledup!M4+'KMX Table'!M7*distribution_rolledup!M7 -> 134.26772 | ... Y4: ='AN Table'!Y8*distribution_rolledup!Y3+'FRN Table'!Y8*distribution_rolledup!Y6+'STG Table'!Y8*distribution_rolledup!Y8+'FLD Table'!U8*distribution_rolledup!Y5+'ENT Table'!U8*distribution_rolledup!Y4+'KMX Table'!Y7*distribution_rolledup!Y7 -> 140.86209
A5: RAGU tc | B5: ='AN Table'!B14*distribution_rolledup!B3+'FRN Table'!B14*distribution_rolledup!B6+'STG Table'!B14*distribution_rolledup!B8+'KMX Table'!B14*distribution_rolledup!B7 -> 137.88144 | C5: ='AN Table'!C14*distribution_rolledup!C3+'FRN Table'!C14*distribution_rolledup!C6+'STG Table'!C14*distribution_rolledup!C8+'KMX Table'!C14*distribution_rolledup!C7 -> 142.95089 | D5: ='AN Table'!D14*distribution_rolledup!D3+'FRN Table'!D14*distribution_rolledup!D6+'STG Table'!D14*distribution_rolledup!D8+'KMX Table'!D14*distribution_rolledup!D7 -> 142.33942 | E5: ='AN Table'!E14*distribution_rolledup!E3+'FRN Table'!E14*distribution_rolledup!E6+'STG Table'!E14*distribution_rolledup!E8+'KMX Table'!E14*distribution_rolledup!E7 -> 138.97839 | F5: ='AN Table'!F14*distribution_rolledup!F3+'FRN Table'!F14*distribution_rolledup!F6+'STG Table'!F14*distribution_rolledup!F8+'FLD Table'!B14*distribution_rolledup!F5+'ENT Table'!B14*distribution_rolledup!F4+'KMX Table'!F14*distribution_rolledup!F7 -> 141.02005 | G5: ='AN Table'!G14*distribution_rolledup!G3+'FRN Table'!G14*distribution_rolledup!G6+'STG Table'!G14*distribution_rolledup!G8+'FLD Table'!C14*distribution_rolledup!G5+'ENT Table'!C14*distribution_rolledup!G4+'KMX Table'!G14*distribution_rolledup!G7 -> 144.70969 | H5: ='AN Table'!H14*distribution_rolledup!H3+'FRN Table'!H14*distribution_rolledup!H6+'STG Table'!H14*distribution_rolledup!H8+'FLD Table'!D14*distribution_rolledup!H5+'ENT Table'!D14*distribution_rolledup!H4+'KMX Table'!H14*distribution_rolledup!H7 -> 143.48499 | I5: ='AN Table'!I14*distribution_rolledup!I3+'FRN Table'!I14*distribution_rolledup!I6+'STG Table'!I14*distribution_rolledup!I8+'FLD Table'!E14*distribution_rolledup!I5+'ENT Table'!E14*distribution_rolledup!I4+'KMX Table'!I14*distribution_rolledup!I7 -> 141.37545 | J5: ='AN Table'!J14*distribution_rolledup!J3+'FRN Table'!J14*distribution_rolledup!J6+'STG Table'!J14*distribution_rolledup!J8+'FLD Table'!F14*distribution_rolledup!J5+'ENT Table'!F14*distribution_rolledup!J4+'KMX Table'!J14*distribution_rolledup!J7 -> 141.15619 | K5: ='AN Table'!K14*distribution_rolledup!K3+'FRN Table'!K14*distribution_rolledup!K6+'STG Table'!K14*distribution_rolledup!K8+'FLD Table'!G14*distribution_rolledup!K5+'ENT Table'!G14*distribution_rolledup!K4+'KMX Table'!K14*distribution_rolledup!K7 -> 138.74775 | L5: ='AN Table'!L14*distribution_rolledup!L3+'FRN Table'!L14*distribution_rolledup!L6+'STG Table'!L14*distribution_rolledup!L8+'FLD Table'!H14*distribution_rolledup!L5+'ENT Table'!H14*distribution_rolledup!L4+'KMX Table'!L14*distribution_rolledup!L7 -> 136.87812 | M5: ='AN Table'!M14*distribution_rolledup!M3+'FRN Table'!M14*distribution_rolledup!M6+'STG Table'!M14*distribution_rolledup!M8+'FLD Table'!I14*distribution_rolledup!M5+'ENT Table'!I14*distribution_rolledup!M4+'KMX Table'!M14*distribution_rolledup!M7 -> 131.57307 | ... Y5: ='AN Table'!Y14*distribution_rolledup!Y3+'FRN Table'!Y14*distribution_rolledup!Y6+'STG Table'!Y14*distribution_rolledup!Y8+'FLD Table'!U14*distribution_rolledup!Y5+'ENT Table'!U14*distribution_rolledup!Y4+'KMX Table'!Y14*distribution_rolledup!Y7 -> 141.85205
A7: LTV | B7: ='AN Table'!B10*distribution_rolledup!B3+'FRN Table'!B10*distribution_rolledup!B6+'KMX Table'!B10*distribution_rolledup!B7+'STG Table'!B10*distribution_rolledup!B8 -> 1.7210953 | C7: ='AN Table'!C10*distribution_rolledup!C3+'FRN Table'!C10*distribution_rolledup!C6+'KMX Table'!C10*distribution_rolledup!C7+'STG Table'!C10*distribution_rolledup!C8 -> 1.69899 | D7: ='AN Table'!D10*distribution_rolledup!D3+'FRN Table'!D10*distribution_rolledup!D6+'KMX Table'!D10*distribution_rolledup!D7+'STG Table'!D10*distribution_rolledup!D8 -> 1.7072601 | E7: ='AN Table'!E10*distribution_rolledup!E3+'FRN Table'!E10*distribution_rolledup!E6+'KMX Table'!E10*distribution_rolledup!E7+'STG Table'!E10*distribution_rolledup!E8 -> 1.6915079 | F7: ='AN Table'!F10*distribution_rolledup!F3+'ENT Table'!B10*distribution_rolledup!F4+'FLD Table'!B10*distribution_rolledup!F5+'FRN Table'!F10*distribution_rolledup!F6+'KMX Table'!F10*distribution_rolledup!F7+'STG Table'!F10*distribution_rolledup!F8 -> 1.7407344 | G7: ='AN Table'!G10*distribution_rolledup!G3+'ENT Table'!C10*distribution_rolledup!G4+'FLD Table'!C10*distribution_rolledup!G5+'FRN Table'!G10*distribution_rolledup!G6+'KMX Table'!G10*distribution_rolledup!G7+'STG Table'!G10*distribution_rolledup!G8 -> 1.764965 | H7: ='AN Table'!H10*distribution_rolledup!H3+'ENT Table'!D10*distribution_rolledup!H4+'FLD Table'!D10*distribution_rolledup!H5+'FRN Table'!H10*distribution_rolledup!H6+'KMX Table'!H10*distribution_rolledup!H7+'STG Table'!H10*distribution_rolledup!H8 -> 1.5955908 | I7: ='AN Table'!I10*distribution_rolledup!I3+'ENT Table'!E10*distribution_rolledup!I4+'FLD Table'!E10*distribution_rolledup!I5+'FRN Table'!I10*distribution_rolledup!I6+'KMX Table'!I10*distribution_rolledup!I7+'STG Table'!I10*distribution_rolledup!I8 -> 1.7039471 | J7: ='AN Table'!J10*distribution_rolledup!J3+'ENT Table'!F10*distribution_rolledup!J4+'FLD Table'!F10*distribution_rolledup!J5+'FRN Table'!J10*distribution_rolledup!J6+'KMX Table'!J10*distribution_rolledup!J7+'STG Table'!J10*distribution_rolledup!J8 -> 1.5703858 | K7: ='AN Table'!K10*distribution_rolledup!K3+'ENT Table'!G10*distribution_rolledup!K4+'FLD Table'!G10*distribution_rolledup!K5+'FRN Table'!K10*distribution_rolledup!K6+'KMX Table'!K10*distribution_rolledup!K7+'STG Table'!K10*distribution_rolledup!K8 -> 1.4208225 | L7: ='AN Table'!L10*distribution_rolledup!L3+'ENT Table'!H10*distribution_rolledup!L4+'FLD Table'!H10*distribution_rolledup!L5+'FRN Table'!L10*distribution_rolledup!L6+'KMX Table'!L10*distribution_rolledup!L7+'STG Table'!L10*distribution_rolledup!L8 -> 1.4805813 | M7: ='AN Table'!M10*distribution_rolledup!M3+'ENT Table'!I10*distribution_rolledup!M4+'FLD Table'!I10*distribution_rolledup!M5+'FRN Table'!M10*distribution_rolledup!M6+'KMX Table'!M10*distribution_rolledup!M7+'STG Table'!M10*distribution_rolledup!M8 -> 1.5101871 | ... Y7: ='AN Table'!Y10*distribution_rolledup!Y3+'ENT Table'!U10*distribution_rolledup!Y4+'FLD Table'!U10*distribution_rolledup!Y5+'FRN Table'!Y10*distribution_rolledup!Y6+'KMX Table'!Y10*distribution_rolledup!Y7+'STG Table'!Y10*distribution_rolledup!Y8 -> 1.551984
A10: NonKMX RAGU tc | E10: =('AN Table'!E14*distribution_rolledup!E3+distribution_rolledup!E6*'FRN Table'!E14+distribution_rolledup!E8*'STG Table'!E14)/SUM(distribution_rolledup!E3,distribution_rolledup!E6,distribution_rolledup!E8) -> 132.26712 | F10: =(distribution_rolledup!F3*'AN Table'!F14+distribution_rolledup!F4*'ENT Table'!B14+distribution_rolledup!F5*'FLD Table'!B14+distribution_rolledup!F6*'FRN Table'!F14+distribution_rolledup!F8*'STG Table'!F14)/SUM(distribution_rolledup!F3:F6,distribution_rolledup!F8) -> 133.98675 | G10: =(distribution_rolledup!G3*'AN Table'!G14+distribution_rolledup!G4*'ENT Table'!C14+distribution_rolledup!G5*'FLD Table'!C14+distribution_rolledup!G6*'FRN Table'!G14+distribution_rolledup!G8*'STG Table'!G14)/SUM(distribution_rolledup!G3:G6,distribution_rolledup!G8) -> 137.64434 | H10: =(distribution_rolledup!H3*'AN Table'!H14+distribution_rolledup!H4*'ENT Table'!D14+distribution_rolledup!H5*'FLD Table'!D14+distribution_rolledup!H6*'FRN Table'!H14+distribution_rolledup!H8*'STG Table'!H14)/SUM(distribution_rolledup!H3:H6,distribution_rolledup!H8) -> 138.25168 | I10: =(distribution_rolledup!I3*'AN Table'!I14+distribution_rolledup!I4*'ENT Table'!E14+distribution_rolledup!I5*'FLD Table'!E14+distribution_rolledup!I6*'FRN Table'!I14+distribution_rolledup!I8*'STG Table'!I14)/SUM(distribution_rolledup!I3:I6,distribution_rolledup!I8) -> 137.77285 | J10: =(distribution_rolledup!J3*'AN Table'!J14+distribution_rolledup!J4*'ENT Table'!F14+distribution_rolledup!J5*'FLD Table'!F14+distribution_rolledup!J6*'FRN Table'!J14+distribution_rolledup!J8*'STG Table'!J14)/SUM(distribution_rolledup!J3:J6,distribution_rolledup!J8) -> 137.98614 | K10: =(distribution_rolledup!K3*'AN Table'!K14+distribution_rolledup!K4*'ENT Table'!G14+distribution_rolledup!K5*'FLD Table'!G14+distribution_rolledup!K6*'FRN Table'!K14+distribution_rolledup!K8*'STG Table'!K14)/SUM(distribution_rolledup!K3:K6,distribution_rolledup!K8) -> 136.18928 | L10: =(distribution_rolledup!L3*'AN Table'!L14+distribution_rolledup!L4*'ENT Table'!H14+distribution_rolledup!L5*'FLD Table'!H14+distribution_rolledup!L6*'FRN Table'!L14+distribution_rolledup!L8*'STG Table'!L14)/SUM(distribution_rolledup!L3:L6,distribution_rolledup!L8) -> 134.39692 | M10: =(distribution_rolledup!M3*'AN Table'!M14+distribution_rolledup!M4*'ENT Table'!I14+distribution_rolledup!M5*'FLD Table'!I14+distribution_rolledup!M6*'FRN Table'!M14+distribution_rolledup!M8*'STG Table'!M14)/SUM(distribution_rolledup!M3:M6,distribution_rolledup!M8) -> 129.61982 | ... Y10: =(distribution_rolledup!Y3*'AN Table'!Y14+distribution_rolledup!Y4*'ENT Table'!U14+distribution_rolledup!Y5*'FLD Table'!U14+distribution_rolledup!Y6*'FRN Table'!Y14+distribution_rolledup!Y8*'STG Table'!Y14)/SUM(distribution_rolledup!Y3:Y6,distribution_rolledup!Y8) -> 142.20208
A11: NonKMX CNL tc | E11: =(distribution_rolledup!E3*'AN Table'!E15+distribution_rolledup!E6*'FRN Table'!E15+distribution_rolledup!E8*'STG Table'!E15)/SUM(distribution_rolledup!E3,distribution_rolledup!E6,distribution_rolledup!E8) -> 0.23571046 | F11: =(distribution_rolledup!F3*'AN Table'!F15+distribution_rolledup!F4*'ENT Table'!B15+distribution_rolledup!F5*'FLD Table'!B15+distribution_rolledup!F6*'FRN Table'!F15+distribution_rolledup!F8*'STG Table'!F15)/SUM(distribution_rolledup!F3:F6,distribution_rolledup!F8) -> 0.18977271 | G11: =(distribution_rolledup!G3*'AN Table'!G15+distribution_rolledup!G4*'ENT Table'!C15+distribution_rolledup!G5*'FLD Table'!C15+distribution_rolledup!G6*'FRN Table'!G15+distribution_rolledup!G8*'STG Table'!G15)/SUM(distribution_rolledup!G3:G6,distribution_rolledup!G8) -> 0.18499408 | H11: =(distribution_rolledup!H3*'AN Table'!H15+distribution_rolledup!H4*'ENT Table'!D15+distribution_rolledup!H5*'FLD Table'!D15+distribution_rolledup!H6*'FRN Table'!H15+distribution_rolledup!H8*'STG Table'!H15)/SUM(distribution_rolledup!H3:H6,distribution_rolledup!H8) -> 0.19153107 | I11: =(distribution_rolledup!I3*'AN Table'!I15+distribution_rolledup!I4*'ENT Table'!E15+distribution_rolledup!I5*'FLD Table'!E15+distribution_rolledup!I6*'FRN Table'!I15+distribution_rolledup!I8*'STG Table'!I15)/SUM(distribution_rolledup!I3:I6,distribution_rolledup!I8) -> 0.20021223 | J11: =(distribution_rolledup!J3*'AN Table'!J15+distribution_rolledup!J4*'ENT Table'!F15+distribution_rolledup!J5*'FLD Table'!F15+distribution_rolledup!J6*'FRN Table'!J15+distribution_rolledup!J8*'STG Table'!J15)/SUM(distribution_rolledup!J3:J6,distribution_rolledup!J8) -> 0.19683083 | K11: =(distribution_rolledup!K3*'AN Table'!K15+distribution_rolledup!K4*'ENT Table'!G15+distribution_rolledup!K5*'FLD Table'!G15+distribution_rolledup!K6*'FRN Table'!K15+distribution_rolledup!K8*'STG Table'!K15)/SUM(distribution_rolledup!K3:K6,distribution_rolledup!K8) -> 0.24624143 | L11: =(distribution_rolledup!L3*'AN Table'!L15+distribution_rolledup!L4*'ENT Table'!H15+distribution_rolledup!L5*'FLD Table'!H15+distribution_rolledup!L6*'FRN Table'!L15+distribution_rolledup!L8*'STG Table'!L15)/SUM(distribution_rolledup!L3:L6,distribution_rolledup!L8) -> 0.28240026 | M11: =(distribution_rolledup!M3*'AN Table'!M15+distribution_rolledup!M4*'ENT Table'!I15+distribution_rolledup!M5*'FLD Table'!I15+distribution_rolledup!M6*'FRN Table'!M15+distribution_rolledup!M8*'STG Table'!M15)/SUM(distribution_rolledup!M3:M6,distribution_rolledup!M8) -> 0.3270186 | ... Y11: =(distribution_rolledup!Y3*'AN Table'!Y15+distribution_rolledup!Y4*'ENT Table'!U15+distribution_rolledup!Y5*'FLD Table'!U15+distribution_rolledup!Y6*'FRN Table'!Y15+distribution_rolledup!Y8*'STG Table'!Y15)/SUM(distribution_rolledup!Y3:Y6,distribution_rolledup!Y8) -> 0

Sheet AN Table
A1: AN | B1: 2016 | C1: 2017 | D1: 2018 | E1: 2019 | F1: 2020 Q1 | G1: 2020 Q2 | H1: 2020 Q3 | I1: 2020 Q4 | J1: 2021 Q1 | K1: 2021 Q2 | L1: 2021 Q3 | M1: 2021 Q4 | N1: 2022 Q1 | O1: 2022 Q2 | P1: 2022 Q3 | Q1: 2022 Q4 | R1: 2023 Q1 | S1: 2023 Q2 | T1: 2023 Q3 | U1: 2023 Q4 | V1: 2024 Q1 | W1: 2024 Q2 | X1: 2024 Q3 | Y1: 2024 Q4 | Z1: 2025 Q1 | AA1: 2025 Q2 | AB1: 2025 Q3 | AC1: 2025 Q4 | AD1: 2026 Q1 | AE1: t-1 | AG1: t-1 manual input | AH1: Use Recent Month? | AI1: Use Reassessed Model Score?
A2: Contract Model Score¹ | B2: ='Data Tables (Q)'!B2 -> 130.07704 | C2: ='Data Tables (Q)'!C2 -> 132.82918 | D2: ='Data Tables (Q)'!D2 -> 132.99304 | E2: ='Data Tables (Q)'!E2 -> 132.10911 | F2: ='Data Tables (Q)'!F2 -> 131.79764 | G2: ='Data Tables (Q)'!G2 -> 133.71059 | H2: ='Data Tables (Q)'!H2 -> 135.28557 | I2: ='Data Tables (Q)'!I2 -> 135.79608 | ... AD2: ='Data Tables (Q)'!AD2 -> 140.46038 | AE2: ='Data Tables (M)'!BS2*AH2+AG2*(1-AH2) -> 138.34761 | AG2: ='t-1 Data Table'!N2 -> 139.6 | AH2: 1 | AI2: 0
A3: Shift to FRN 3.1 Score² | B3: ='Data Tables (Q)'!B3*AI2 -> 0 | C3: ='Data Tables (Q)'!C3*AJ2 -> 0 | D3: ='Data Tables (Q)'!D3*AK2 -> 0 | E3: ='Data Tables (Q)'!E3*AL2 -> 0 | F3: ='Data Tables (Q)'!F3*AM2 -> 0 | G3: ='Data Tables (Q)'!G3*AN2 -> 0 | H3: ='Data Tables (Q)'!H3*AO2 -> 0 | I3: ='Data Tables (Q)'!I3*AP2 -> 0 | ... AD3: ='Data Tables (Q)'!AD3*BK2 -> 0 | AE3: =('Data Tables (M)'!BC3*AH3+AG3*(1-AH3))*$AI$2 -> 0 | AG3: 0 | AH3: 1
A4: Gross Loss Adjustments (Dealer Level, vehicle age, etc.)² | B4: ='Data Tables (Q)'!B4 -> 0.36824634 | C4: ='Data Tables (Q)'!C4 -> 0.64268496 | D4: ='Data Tables (Q)'!D4 -> 0.73760946 | E4: ='Data Tables (Q)'!E4 -> 0.54113333 | F4: ='Data Tables (Q)'!F4 -> 0.64749521 | G4: ='Data Tables (Q)'!G4 -> 0.51566419 | H4: ='Data Tables (Q)'!H4 -> -0.19174308 | I4: ='Data Tables (Q)'!I4 -> 0.2567337 | ... AD4: ='Data Tables (Q)'!AD4 -> 1.914656 | AE4: ='Data Tables (M)'!BS4*AH4+AG4*(1-AH4) -> 2.9079804 | AH4: 1
A5: Recovery Adjustments excluding LTV (Mileage, LOB, etc.)³ | B5: ='Data Tables (Q)'!B5 -> -0.39258197 | C5: ='Data Tables (Q)'!C5 -> 0.31810502 | D5: ='Data Tables (Q)'!D5 -> 0.19702468 | E5: ='Data Tables (Q)'!E5 -> 0.1634963 | F5: ='Data Tables (Q)'!F5 -> -0.10819935 | G5: ='Data Tables (Q)'!G5 -> -0.56943614 | H5: ='Data Tables (Q)'!H5 -> -0.21425416 | I5: ='Data Tables (Q)'!I5 -> 0.68058865 | ... AD5: ='Data Tables (Q)'!AD5 -> 1.8234979 | AE5: ='Data Tables (M)'!BS5*AH5+AG5*(1-AH5) -> 0.18026339 | AH5: 1
A6: BBLTV Adjustments⁴ | B6: =(194%/B10-1)/10%*1.7 -> 0.27855508 | C6: =(194%/C10-1)/10%*1.7 -> 0.33742894 | D6: =(194%/D10-1)/10%*1.7 -> 0.2589731 | E6: =(194%/E10-1)/10%*1.7 -> -0.071663328 | F6: =(194%/F10-1)/10%*1.7 -> 0.33211591 | G6: =(194%/G10-1)/10%*1.7 -> -0.062099711 | H6: =(194%/H10-1)/10%*1.7 -> 2.7392366 | I6: =(194%/I10-1)/10%*1.7 -> 2.8651084 | ... AE6: =(194%/AE10-1)/10%*1.7 -> 4.2236317
A7: RAGU Score | B7: =SUM(B2:B6) -> 130.33126 | C7: =SUM(C2:C6) -> 134.1274 | D7: =SUM(D2:D6) -> 134.18665 | E7: =SUM(E2:E6) -> 132.74207 | F7: =SUM(F2:F6) -> 132.66905 | G7: =SUM(G2:G6) -> 133.59472 | H7: =SUM(H2:H6) -> 137.61881 | I7: =SUM(I2:I6) -> 139.59851 | ... AE7: =SUM(AE2:AE6) -> 145.65948
B8: =B2+B4 -> 130.44529 | C8: =C2+C4 -> 133.47187 | D8: =D2+D4 -> 133.73065 | E8: =E2+E4 -> 132.65024 | F8: =F2+F4 -> 132.44513 | G8: =G2+G4 -> 134.22626 | H8: =H2+H4 -> 135.09383 | I8: =I2+I4 -> 136.05282 | ... AE8: =AE2+AE4 -> 141.25559
A9: Context info
A10: BlackBook LTV (Baseline 194%) | B10: ='Data Tables (Q)'!B8 -> 1.9087244 | C10: ='Data Tables (Q)'!C8 -> 1.9022428 | D10: ='Data Tables (Q)'!D8 -> 1.9108901 | E10: ='Data Tables (Q)'!E8 -> 1.9482127 | F10: ='Data Tables (Q)'!F8 -> 1.902826 | G10: ='Data Tables (Q)'!G8 -> 1.9471127 | H10: ='Data Tables (Q)'!H8 -> 1.670784 | I10: ='Data Tables (Q)'!I8 -> 1.6601973 | ... AD10: ='Data Tables (Q)'!AD8 -> 1.5674185 | AE10: ='Data Tables (M)'!BS8*AH10+AG10*(1-AH10) -> 1.5539282 | AH10: 1
A11: Origination MMI | B11: 136.4 | C11: 141.3 | D11: 148 | E11: 151.5 | F11: 156.6 | G11: 149.5 | H11: 178.6 | I11: 176.8 | J11: 183.6 | K11: 218.6 | L11: 217 | M11: 252.9 | N11: 243.1 | O11: 245.1 | P11: 229.8 | Q11: 221.6 | R11: 229.4 | S11: 224.9 | T11: 212.6 | U11: 204.9 | V11: 204.2 | W11: 199.2 | X11: 202.8 | Y11: 203.3 | AA11: 205.86667 | AE11: 203
A12: MMI Impact⁵ | B12: 0.04 | C12: 0.11 | D12: 0.13 | E12: 0.146 | F12: 0.24456068 | G12: 0.33059156 | H12: 0.11738195 | I12: 0.16960025 | J12: 0.13323456 | K12: -0.042561451 | L12: -0.041246333 | M12: -0.18913444 | N12: -0.16706463 | O12: -0.1889941 | P12: -0.1447923 | Q12: -0.12461664 | R12: -0.16400894 | S12: -0.15141756 | T12: -0.10485319 | U12: -0.070296606 | V12: -0.064207992 | W12: -0.037128724 | X12: -0.03 | Y12: -0.03 | Z12: -0.03 | AA12: -0.026435638 | AE12: -0.03
A13: Adjustment to RAGU Score from MMI | B13: =B12/10%*1.7 -> 0.68 | C13: =C12/10%*1.7 -> 1.87 | D13: =D12/10%*1.7 -> 2.21 | E13: =E12/10%*1.7 -> 2.482 | F13: =F12/10%*1.7 -> 4.1575315 | G13: =G12/10%*1.7 -> 5.6200565 | H13: =H12/10%*1.7 -> 1.9954932 | I13: =I12/10%*1.7 -> 2.8832042 | ... AA13: =AA12/10%*1.7 -> -0.44940584 | AE13: =AE12/10%*1.7 -> -0.51
A14: RAGU Score (adjusted for MMI) | B14: =B7+B13 -> 131.01126 | C14: =C7+C13 -> 135.9974 | D14: =D7+D13 -> 136.39665 | E14: =E7+E13 -> 135.22407 | F14: =F7+F13 -> 136.82658 | G14: =G7+G13 -> 139.21478 | H14: =H7+H13 -> 139.61431 | I14: =I7+I13 -> 142.48172 | ... AA14: =AA7+AA13 -> 144.62046 | AE14: =AE7+AE13 -> 145.14948
A15: t_c CNL⁶ | B15: 0.28170196 | C15: 0.25167973 | D15: 0.2413702 | E15: 0.22113853 | F15: 0.19097109 | G15: 0.19152875 | H15: 0.18098296 | I15: 0.18074389 | J15: 0.21624478 | K15: 0.21737628 | L15: 0.25009127 | M15: 0.28129098 | N15: 0.31307465 | O15: 0.32412048 | P15: 0.31408391 | Q15: 0.3028242 | R15: 0.30358937
A16: Implied t-1 CNL | B16: =B15-($AE$14-B14)*1% -> 0.14031975 | C16: =C15-($AE$14-C14)*1% -> 0.1601589 | D16: =D15-($AE$14-D14)*1% -> 0.15384183 | E16: =E15-($AE$14-E14)*1% -> 0.12188446 | F16: =F15-($AE$14-F14)*1% -> 0.10774206 | G16: =G15-($AE$14-G14)*1% -> 0.13218171 | H16: =H15-($AE$14-H14)*1% -> 0.12563121 | I16: =I15-($AE$14-I14)*1% -> 0.15406626 | ... R16: =R15-($AE$14-R14)*1% -> 0.19441764 | AE16: 0.2767
A19: 1: | B19: Model Score excludes buybacks and high amount financed.
A20: 2: | B20: We are currently working with Pricing to determine how to use FRN3.1 scores, there are large discrepancies between model scores as booked and FRN3.1 due to what might be centering issues.
A21: 3: | B21: Biggest impacts to Gross Loss Adjustments are Dealer Level, weekday/weekend decision, and high mileage classification.
B22: See Appendix for details on other factors
A23: 4: | B23: Biggest impacts to Recovery Adjustments are mileage/age, impound probability, and vehicle class.
A24: 5: | B24: LTV adjustments are made using the 10% LTV improvement->170bps to CNL heuristic, based on BlackBook LTV values.
A25: 6: | B25: MMI uses adjusted index (2019 seasonality). The MMI Impact compares the actual MMI to a 3% annual growth.
B26: A positive impact of X% means sold recovery will be X% better.
A27: 7: | B27: tc CNL uses UGLY Model projections, and 2023 Q1 blends 75% UGLY Model with 25% Loss Committee.
B32: 2016 | C32: 2017 | D32: 2018 | E32: 2019 | F32: 2020 Q1 | G32: 2020 Q2 | H32: 2020 Q3 | I32: 2020 Q4 | J32: 2021 Q1 | K32: 2021 Q2 | L32: 2021 Q3 | M32: 2021 Q4 | N32: 2022 Q1 | O32: 2022 Q2 | P32: 2022 Q3 | Q32: 2022 Q4 | R32: 2023 Q1 | S32: 2023 Q2 | T32: 2023 Q3 | U32: 2023 Q4 | V32: 2024 Q1 | W32: 2024 Q2 | X32: 2024 Q3 | Y32: 2024 Q4 | Z32: 2025 Q1 | AA32: 2025 Q2 | AB32: 2025 Q3 | AC32: 2025 Q4
A33: an fraud | B33: 130.46515 | C33: 134.56422 | D33: 134.58326 | E33: 133.43826 | F33: 133.33824 | G33: 134.64263 | H33: 138.68763 | I33: 140.00541 | J33: 138.75863 | K33: 141.35768 | L33: 140.07357 | M33: 139.06987 | N33: 137.92781 | O33: 138.42983 | P33: 137.40824 | Q33: 137.78028 | R33: 137.38958 | S33: 139.34931 | T33: 138.59028 | U33: 138.66445 | V33: 137.45819 | W33: 139.72534 | X33: 142.01342 | Y33: 141.49747 | Z33: 141.95185 | AA33: 145.17986 | AB33: 146.08928 | AC33: 148.42861
A34: an no fraud | B34: 130.46515 | C34: 134.56422 | D34: 134.58326 | E34: 133.43826 | F34: 133.33824 | G34: 134.64263 | H34: 138.68763 | I34: 140.00541 | J34: 138.75863 | K34: 141.35768 | L34: 140.07357 | M34: 139.06987 | N34: 137.92781 | O34: 138.42983 | P34: 137.40824 | Q34: 137.96517 | R34: 137.55322 | S34: 139.57514 | T34: 138.74392 | U34: 138.88913 | V34: 137.45007 | W34: 139.84196 | X34: 142.05848 | Y34: 141.49099 | Z34: 141.89855 | AA34: 145.00908 | AB34: 145.89632 | AC34: 148.33449
A35: FRN f | B35: 128.93896 | C35: 135.40687 | D35: 135.88597 | E35: 132.28921 | F35: 132.3627 | G35: 134.04158 | H35: 134.67309 | I35: 132.46164 | J35: 138.04108 | K35: 140.99455 | L35: 138.74044 | M35: 134.44924 | N35: 135.61167 | O35: 138.92679 | P35: 139.58052 | Q35: 141.35866 | R35: 143.12282 | S35: 145.305 | T35: 146.11 | U35: 143.96604 | V35: 141.62492 | W35: 144.74602 | X35: 146.8521 | Y35: 145.87892 | Z35: 145.95345 | AA35: 148.51223 | AB35: 150.05003 | AC35: 152.67536
A36: frn n | B36: 128.93896 | C36: 135.40687 | D36: 135.88597 | E36: 132.28921 | F36: 132.3627 | G36: 134.04158 | H36: 134.67309 | I36: 132.46164 | J36: 138.04108 | K36: 140.99455 | L36: 138.74044 | M36: 134.44924 | N36: 135.61167 | O36: 138.92679 | P36: 139.58052 | Q36: 141.36659 | R36: 143.04129 | S36: 145.30748 | T36: 146.11616 | U36: 143.88321 | V36: 141.43505 | W36: 144.44949 | X36: 146.60957 | Y36: 145.75188 | Z36: 145.95465 | AA36: 148.467 | AB36: 149.88835 | AC36: 152.59916
A37: STG F | B37: 129.9999 | C37: 132.90265 | D37: 132.32799 | E37: 129.39286 | F37: 129.46248 | G37: 132.02712 | H37: 137.51482 | I37: 137.93394 | J37: 139.59341 | K37: 141.24737 | L37: 140.26115 | M37: 137.62341 | N37: 137.81713 | O37: 140.57923 | P37: 140.39519 | Q37: 142.90666 | R37: 143.2152 | S37: 141.66209 | T37: 144.77885 | U37: 143.48916 | V37: 140.6343 | W37: 143.58596 | X37: 146.02021 | Y37: 145.2938 | Z37: 143.67483 | AA37: 146.63333 | AB37: 147.73486 | AC37: 150.85335
A38: STG N | B38: 129.9999 | C38: 132.90265 | D38: 132.32799 | E38: 129.39286 | F38: 129.46248 | G38: 132.02712 | H38: 137.51482 | I38: 137.93394 | J38: 139.59341 | K38: 141.24737 | L38: 140.26115 | M38: 137.62341 | N38: 137.81713 | O38: 140.57923 | P38: 140.39519 | Q38: 142.93925 | R38: 143.22779 | S38: 141.7824 | T38: 144.88809 | U38: 143.6701 | V38: 140.7332 | W38: 143.80317 | X38: 146.12578 | Y38: 145.36614 | Z38: 143.58344 | AA38: 146.54973 | AB38: 147.48897 | AC38: 150.76992
A39: FLD F | F39: 130.36213 | G39: 135.10235 | H39: 139.84898 | I39: 143.34284 | J39: 140.84801 | K39: 139.19957 | L39: 137.50637 | M39: 136.0175 | N39: 134.79642 | O39: 136.36041 | P39: 138.44797 | Q39: 140.21609 | R39: 143.41495 | S39: 140.30457 | T39: 139.7766 | U39: 141.83344 | V39: 139.51191 | W39: 141.0369 | X39: 144.18003 | Y39: 143.43405 | Z39: 140.1094 | AA39: 141.64584 | AB39: 142.594 | AC39: 142.79902
A40: FLD N | F40: 130.36213 | G40: 135.10235 | H40: 139.84898 | I40: 143.34284 | J40: 140.84801 | K40: 139.19957 | L40: 137.50637 | M40: 136.0175 | N40: 134.79642 | O40: 136.36041 | P40: 138.44797 | Q40: 140.19533 | R40: 143.21402 | S40: 140.28476 | T40: 139.6665 | U40: 141.85118 | V40: 139.41936 | W40: 140.84057 | X40: 143.99682 | Y40: 143.20205 | Z40: 139.9979 | AA40: 141.52353 | AB40: 142.44301 | AC40: 142.74744
A41: ENT F | F41: 129.75845 | G41: 131.14941 | H41: 136.63393 | I41: 133.00073 | J41: 132.26325 | K41: 132.12686 | L41: 129.46932 | M41: 127.64167 | N41: 126.88601 | O41: 128.7822 | P41: 128.11707 | Q41: 126.88952 | R41: 127.90548 | S41: 130.33997 | T41: 132.21628 | U41: 134.32746 | V41: 133.72657 | W41: 135.26208 | X41: 135.59105 | Y41: 136.11509 | Z41: 136.27239 | AA41: 138.64294 | AB41: 139.40567 | AC41: 141.83465
A42: ENT N | F42: 129.75845 | G42: 131.14941 | H42: 136.63393 | I42: 133.00073 | J42: 132.26325 | K42: 132.12686 | L42: 129.46932 | M42: 127.64167 | N42: 126.88601 | O42: 128.7822 | P42: 128.11707 | Q42: 126.97348 | R42: 127.86217 | S42: 130.37168 | T42: 132.22709 | U42: 134.0996 | V42: 133.29724 | W42: 134.80924 | X42: 135.15495 | Y42: 135.89798 | Z42: 136.21857 | AA42: 138.48361 | AB42: 139.24255 | AC42: 141.8269

Sheet FRN Table
A1: FRN | B1: 2016 | C1: 2017 | D1: 2018 | E1: 2019 | F1: 2020 Q1 | G1: 2020 Q2 | H1: 2020 Q3 | I1: 2020 Q4 | J1: 2021 Q1 | K1: 2021 Q2 | L1: 2021 Q3 | M1: 2021 Q4 | N1: 2022 Q1 | O1: 2022 Q2 | P1: 2022 Q3 | Q1: 2022 Q4 | R1: 2023 Q1 | S1: 2023 Q2 | T1: 2023 Q3 | U1: 2023 Q4 | V1: 2024 Q1 | W1: 2024 Q2 | X1: 2024 Q3 | Y1: 2024 Q4 | Z1: 2025 Q1 | AA1: 2025 Q2 | AB1: 2025 Q3 | AC1: 2025 Q4 | AD1: 2026 Q1 | AE1: t-1 | AG1: t-1 manual input | AH1: Use Recent Month? | AI1: Use Reassessed Model Score?
A2: Contract Model Score¹ | B2: ='Data Tables (Q)'!B20 -> 131.17685 | C2: ='Data Tables (Q)'!C20 -> 136.73938 | D2: ='Data Tables (Q)'!D20 -> 136.80349 | E2: ='Data Tables (Q)'!E20 -> 132.53803 | F2: ='Data Tables (Q)'!F20 -> 131.13303 | G2: ='Data Tables (Q)'!G20 -> 132.90504 | H2: ='Data Tables (Q)'!H20 -> 133.93048 | I2: ='Data Tables (Q)'!I20 -> 132.80381 | ... AD2: ='Data Tables (Q)'!AD20 -> 142.8984 | AE2: ='Data Tables (M)'!BS20*AH2+AG2*(1-AH2) -> 140.73303 | AG2: ='t-1 Data Table'!N5 -> 142 | AH2: 1 | AI2: 0
A3: Shift to FRN 3.1 Score² | B3: ='Data Tables (Q)'!B21*AI2 -> 0 | C3: ='Data Tables (Q)'!C21*AJ2 -> 0 | D3: ='Data Tables (Q)'!D21*AK2 -> 0 | E3: ='Data Tables (Q)'!E21*AL2 -> 0 | F3: ='Data Tables (Q)'!F21*AM2 -> 0 | G3: ='Data Tables (Q)'!G21*AN2 -> 0 | H3: ='Data Tables (Q)'!H21*AO2 -> 0 | I3: ='Data Tables (Q)'!I21*AP2 -> 0 | ... AD3: ='Data Tables (Q)'!AD21*BK2 -> 0 | AE3: =('Data Tables (M)'!BC21*AH3+AG3*(1-AH3))*$AI$2 -> 0 | AG3: 0 | AH3: 1
A4: Gross Loss Adjustments (Dealer Level, vehicle age, etc.)² | B4: ='Data Tables (Q)'!B22 -> -0.3279542 | C4: ='Data Tables (Q)'!C22 -> 0.20210618 | D4: ='Data Tables (Q)'!D22 -> -0.19413065 | E4: ='Data Tables (Q)'!E22 -> 0.046002039 | F4: ='Data Tables (Q)'!F22 -> 0.53224606 | G4: ='Data Tables (Q)'!G22 -> 0.71345069 | H4: ='Data Tables (Q)'!H22 -> -0.27007229 | I4: ='Data Tables (Q)'!I22 -> -0.83970892 | ... AD4: ='Data Tables (Q)'!AD22 -> 2.0098245 | AE4: ='Data Tables (M)'!BS22*AH4+AG4*(1-AH4) -> 1.5637332 | AH4: 1
A5: Recovery Adjustments excluding LTV (Mileage, LOB, etc.)³ | B5: ='Data Tables (Q)'!B23 -> -0.48077299 | C5: ='Data Tables (Q)'!C23 -> 0.29742497 | D5: ='Data Tables (Q)'!D23 -> 0.28839507 | E5: ='Data Tables (Q)'!E23 -> 0.13368594 | F5: ='Data Tables (Q)'!F23 -> -0.35590629 | G5: ='Data Tables (Q)'!G23 -> -0.39916326 | H5: ='Data Tables (Q)'!H23 -> 0.015803735 | I5: ='Data Tables (Q)'!I23 -> 0.29142926 | ... AD5: ='Data Tables (Q)'!AD23 -> 1.5112986 | AE5: ='Data Tables (M)'!BS23*AH5+AG5*(1-AH5) -> 0.2368658 | AH5: 1
A6: BBLTV Adjustments⁴ | B6: =(194%/B10-1)/10%*1.7 -> -1.6644079 | C6: =(194%/C10-1)/10%*1.7 -> -2.059283 | D6: =(194%/D10-1)/10%*1.7 -> -1.3674674 | E6: =(194%/E10-1)/10%*1.7 -> -1.2016963 | F6: =(194%/F10-1)/10%*1.7 -> -0.0010010975 | G6: =(194%/G10-1)/10%*1.7 -> -0.028926451 | H6: =(194%/H10-1)/10%*1.7 -> 0.35434237 | I6: =(194%/I10-1)/10%*1.7 -> -0.73971065 | ... AE6: =(194%/AE10-1)/10%*1.7 -> 6.6906158
A7: RAGU Score | B7: =SUM(B2:B6) -> 128.70372 | C7: =SUM(C2:C6) -> 135.17963 | D7: =SUM(D2:D6) -> 135.53028 | E7: =SUM(E2:E6) -> 131.51602 | F7: =SUM(F2:F6) -> 131.30837 | G7: =SUM(G2:G6) -> 133.1904 | H7: =SUM(H2:H6) -> 134.03055 | I7: =SUM(I2:I6) -> 131.51582 | ... AE7: =SUM(AE2:AE6) -> 149.22425
B8: =B2+B4 -> 130.8489 | C8: =C2+C4 -> 136.94149 | D8: =D2+D4 -> 136.60936 | E8: =E2+E4 -> 132.58403 | F8: =F2+F4 -> 131.66528 | G8: =G2+G4 -> 133.61849 | H8: =H2+H4 -> 133.66041 | I8: =I2+I4 -> 131.9641 | ... AE8: =AE2+AE4 -> 142.29677
A9: Context info
A10: BlackBook LTV (Baseline 194%) | B10: ='Data Tables (Q)'!B26 -> 2.1505528 | C10: ='Data Tables (Q)'!C26 -> 2.2073907 | D10: ='Data Tables (Q)'!D26 -> 2.1097029 | E10: ='Data Tables (Q)'!E26 -> 2.0875659 | F10: ='Data Tables (Q)'!F26 -> 1.9401142 | G10: ='Data Tables (Q)'!G26 -> 1.9433066 | H10: ='Data Tables (Q)'!H26 -> 1.9003889 | I10: ='Data Tables (Q)'!I26 -> 2.0282542 | ... AD10: ='Data Tables (Q)'!AD26 -> 1.4520697 | AE10: ='Data Tables (M)'!BS26*AH10+AG10*(1-AH10) -> 1.3921124 | AH10: 1
A11: Origination MMI | B11: 136.4 | C11: 141.3 | D11: 148 | E11: 151.5 | F11: 156.6 | G11: 149.5 | H11: 178.6 | I11: 176.8 | J11: 183.6 | K11: 218.6 | L11: 217 | M11: 252.9 | N11: 243.1 | O11: 245.1 | P11: 229.8 | Q11: 221.6 | R11: 229.4 | S11: 224.9 | T11: 212.6 | U11: 204.9 | V11: 204.2 | W11: 199.2 | X11: 202.8 | Y11: 203.3 | AA11: 205.86667 | AE11: 203
A12: MMI Impact⁵ | B12: 0.04 | C12: 0.11 | D12: 0.13 | E12: 0.146 | F12: 0.24456068 | G12: 0.33059156 | H12: 0.11738195 | I12: 0.16960025 | J12: 0.13323456 | K12: -0.042561451 | L12: -0.041246333 | M12: -0.18913444 | N12: -0.16706463 | O12: -0.1889941 | P12: -0.1447923 | Q12: -0.12461664 | R12: -0.16400894 | S12: -0.15141756 | T12: -0.10485319 | U12: -0.070296606 | V12: -0.064207992 | W12: -0.037128724 | X12: -0.03 | Y12: -0.03 | Z12: -0.03 | AA12: -0.026435638 | AE12: -0.03
A13: Adjustment to RAGU Score from MMI | B13: =B12/10%*1.7 -> 0.68 | C13: =C12/10%*1.7 -> 1.87 | D13: =D12/10%*1.7 -> 2.21 | E13: =E12/10%*1.7 -> 2.482 | F13: =F12/10%*1.7 -> 4.1575315 | G13: =G12/10%*1.7 -> 5.6200565 | H13: =H12/10%*1.7 -> 1.9954932 | I13: =I12/10%*1.7 -> 2.8832042 | ... AA13: =AA12/10%*1.7 -> -0.44940584 | AE13: =AE12/10%*1.7 -> -0.51
A14: RAGU Score (adjusted for MMI) | B14: =B7+B13 -> 129.38372 | C14: =C7+C13 -> 137.04963 | D14: =D7+D13 -> 137.74028 | E14: =E7+E13 -> 133.99802 | F14: =F7+F13 -> 135.4659 | G14: =G7+G13 -> 138.81046 | H14: =H7+H13 -> 136.02605 | I14: =I7+I13 -> 134.39902 | ... AA14: =AA7+AA13 -> 147.62098 | AE14: =AE7+AE13 -> 148.71425
A15: t_c CNL⁶ | B15: 0.36336386 | C15: 0.32343826 | D15: 0.28323748 | E15: 0.24889569 | F15: 0.22848192 | G15: 0.21527641 | H15: 0.24687227 | I15: 0.28284071 | J15: 0.23888263 | K15: 0.27508726 | L15: 0.30977847 | M15: 0.35995406 | N15: 0.3820747 | O15: 0.36047353 | P15: 0.3397475 | Q15: 0.31875734 | R15: 0.30830728
A16: Implied t-1 CNL | B16: =B15-($AE$14-B14)*1% -> 0.17005856 | C16: =C15-($AE$14-C14)*1% -> 0.20679205 | D16: =D15-($AE$14-D14)*1% -> 0.17349785 | E16: =E15-($AE$14-E14)*1% -> 0.10173343 | F16: =F15-($AE$14-F14)*1% -> 0.095998443 | G16: =G15-($AE$14-G14)*1% -> 0.11623854 | H16: =H15-($AE$14-H14)*1% -> 0.11999025 | I16: =I15-($AE$14-I14)*1% -> 0.13968846 | ... R16: =R15-($AE$14-R14)*1% -> 0.22158074 | AE16: 0.281
A19: 1: | B19: Model Score excludes buybacks and high amount financed.
A20: 2: | B20: We are currently working with Pricing to determine how to use FRN3.1 scores, there are large discrepancies between model scores as booked and FRN3.1 due to what might be centering issues.
A21: 3: | B21: Biggest impacts to Gross Loss Adjustments are Dealer Level, weekday/weekend decision, and high mileage classification.
B22: Not accounting for potential differences in Gross Loss for test loans.
B23: See Appendix for details on other factors
A24: 4: | B24: Biggest impacts to Recovery Adjustments are mileage/age, impound probability, and vehicle class.
A25: 5: | B25: LTV adjustments are made using the 10% LTV improvement->170bps to CNL heuristic, based on BlackBook LTV values.
A26: 6: | B26: MMI uses adjusted index (2019 seasonality). The MMI Impact compares the actual MMI to a 3% annual growth.
B27: A positive impact of X% means sold recovery will be X% better.
A28: 7: | B28: tc CNL uses UGLY Model projections, and 2023 Q1 blends 75% UGLY Model with 25% Loss Committee.

Sheet STG Table
