Workbook

Sheet Main
A1: NONKMX LOB | B1: FLD
A2: Start | B2: 2025 Q1 | E2: SECTION 1: POS Breakdown (excl. STE)
A3: End | B3: 2025 Q4
E4: 1a. POS Ragu Breakdown
A5: nonKMX LOBs: | E5: =factory!U26 -> POS | F5: =B2 -> 2025 Q1 | G5: =B3 -> 2025 Q4 | H5: Delta
A6: AN | E6: Model Score | F6: =factory!V27 -> 138.29936 | G6: =factory!W27 -> 140.32 | H6: =G6-F6 -> 2.0206382
A7: STG | E7: Gross Loss | F7: =factory!V28 -> 0.21131625 | G7: =factory!W28 -> 1.9565456 | H7: =G7-F7 -> 1.7452294
A8: ENT | E8: Recovery + LTV | F8: =factory!V29 -> 2.1597741 | G8: =factory!W29 -> 3.7818078 | H8: =G8-F8 -> 1.6220337
A9: FLD | E9: RAGU Score | F9: =factory!V30 -> 140.67045 | G9: =factory!W30 -> 146.05835 | H9: =G9-F9 -> 5.3879013
A10: FRN
E11: 1b. POS Recovery Mix | J11: 1c. POS Gross-Loss Mix
E12: POS | F12: =B2 -> 2025 Q1 | G12: =B3 -> 2025 Q4 | H12: Delta | J12: POS | K12: =B2 -> 2025 Q1 | L12: =B3 -> 2025 Q4 | M12: Delta
E13: KMX | F13: =INDEX('POS decomp'!$I21:$S21,MATCH(F$12,'POS decomp'!$I$20:$S$20, 0)) -> -0.95588293 | G13: =INDEX('POS decomp'!$I21:$S21,MATCH(G$12,'POS decomp'!$I$20:$S$20, 0)) -> 0.02024678 | H13: =G13-F13 -> 0.97612971 | J13: KMX | K13: =INDEX('POS decomp'!$AB21:$AL21,MATCH(K$12,'POS decomp'!$AB$20:$AL$20, 0)) -> -0.15422945 | L13: =INDEX('POS decomp'!$AB21:$AL21,MATCH(L$12,'POS decomp'!$AB$20:$AL$20, 0)) -> 0.7223938 | M13: =L13-K13 -> 0.87662325
E14: AN | F14: =INDEX('POS decomp'!$I22:$S22,MATCH(F$12,'POS decomp'!$I$20:$S$20, 0)) -> 0.27284125 | G14: =INDEX('POS decomp'!$I22:$S22,MATCH(G$12,'POS decomp'!$I$20:$S$20, 0)) -> 0.40054145 | H14: =G14-F14 -> 0.1277002 | J14: AN | K14: =INDEX('POS decomp'!$AB22:$AL22,MATCH(K$12,'POS decomp'!$AB$20:$AL$20, 0)) -> 0.083317327 | L14: =INDEX('POS decomp'!$AB22:$AL22,MATCH(L$12,'POS decomp'!$AB$20:$AL$20, 0)) -> 0.18577643 | M14: =L14-K14 -> 0.1024591
E15: FRN | F15: =INDEX('POS decomp'!$I23:$S23,MATCH(F$12,'POS decomp'!$I$20:$S$20, 0)) -> 1.1738563 | G15: =INDEX('POS decomp'!$I23:$S23,MATCH(G$12,'POS decomp'!$I$20:$S$20, 0)) -> 1.5164243 | H15: =G15-F15 -> 0.34256796 | J15: FRN | K15: =INDEX('POS decomp'!$AB23:$AL23,MATCH(K$12,'POS decomp'!$AB$20:$AL$20, 0)) -> 0.1194035 | L15: =INDEX('POS decomp'!$AB23:$AL23,MATCH(L$12,'POS decomp'!$AB$20:$AL$20, 0)) -> 0.46468388 | M15: =L15-K15 -> 0.34528038
E16: STG | F16: =INDEX('POS decomp'!$I24:$S24,MATCH(F$12,'POS decomp'!$I$20:$S$20, 0)) -> 0.75299844 | G16: =INDEX('POS decomp'!$I24:$S24,MATCH(G$12,'POS decomp'!$I$20:$S$20, 0)) -> 0.92455929 | H16: =G16-F16 -> 0.17156085 | J16: STG | K16: =INDEX('POS decomp'!$AB24:$AL24,MATCH(K$12,'POS decomp'!$AB$20:$AL$20, 0)) -> 0.20623123 | L16: =INDEX('POS decomp'!$AB24:$AL24,MATCH(L$12,'POS decomp'!$AB$20:$AL$20, 0)) -> 0.30022634 | M16: =L16-K16 -> 0.093995118
E17: FLD | F17: =INDEX('POS decomp'!$I25:$S25,MATCH(F$12,'POS decomp'!$I$20:$S$20, 0)) -> 0.11460964 | G17: =INDEX('POS decomp'!$I25:$S25,MATCH(G$12,'POS decomp'!$I$20:$S$20, 0)) -> 0.21373009 | H17: =G17-F17 -> 0.099120451 | J17: FLD | K17: =INDEX('POS decomp'!$AB25:$AL25,MATCH(K$12,'POS decomp'!$AB$20:$AL$20, 0)) -> 0.10732218 | L17: =INDEX('POS decomp'!$AB25:$AL25,MATCH(L$12,'POS decomp'!$AB$20:$AL$20, 0)) -> 0.099445766 | M17: =L17-K17 -> -0.0078764126
E18: ENT | F18: =INDEX('POS decomp'!$I26:$S26,MATCH(F$12,'POS decomp'!$I$20:$S$20, 0)) -> 0.80243801 | G18: =INDEX('POS decomp'!$I26:$S26,MATCH(G$12,'POS decomp'!$I$20:$S$20, 0)) -> 0.7158481 | H18: =G18-F18 -> -0.086589916 | J18: ENT | K18: =INDEX('POS decomp'!$AB26:$AL26,MATCH(K$12,'POS decomp'!$AB$20:$AL$20, 0)) -> -0.15072853 | L18: =INDEX('POS decomp'!$AB26:$AL26,MATCH(L$12,'POS decomp'!$AB$20:$AL$20, 0)) -> 0.1840194 | M18: =L18-K18 -> 0.33474793
E19: POS | F19: =SUM(F13:F18) -> 2.1608607 | G19: =SUM(G13:G18) -> 3.79135 | H19: =G19-F19 -> 1.6304893 | J19: POS | K19: =SUM(K13:K18) -> 0.21131625 | L19: =SUM(L13:L18) -> 1.9565456 | M19: =L19-K19 -> 1.7452294
E23: SECTION 2: KMX Breakdown
E25: 2a. KMX Ragu Breakdown | J25: 2c. KMX Gross-Loss Breakdown
E26: =factory!Q26 -> KMX | F26: =B2 -> 2025 Q1 | G26: =B3 -> 2025 Q4 | H26: Delta | J26: KMX | K26: =B2 -> 2025 Q1 | L26: =B3 -> 2025 Q4 | M26: Delta
E27: Model Score | F27: =factory!R27 -> 139.70877 | G27: =factory!S27 -> 140.94205 | H27: =G27-F27 -> 1.2332866 | J27: Chime | K27: =factory!G116+factory!G102 -> -1.292241 | L27: =factory!H116+factory!H102 -> -1.1293258 | M27: =L27-K27 -> 0.16291519
E28: Gross Loss | F28: =factory!R28 -> -0.34039323 | G28: =factory!S28 -> 1.489745 | H28: =G28-F28 -> 1.8301382 | J28: population % | K28: =INDEX('KMX populations'!$B28:$L28,MATCH("KMX | "&K$26,'KMX populations'!$B$1:$L$1, 0)) -> 0.23263723 | L28: =INDEX('KMX populations'!$B28:$L28,MATCH("KMX | "&L$26,'KMX populations'!$B$1:$L$1, 0)) -> 0.15797197 | M28: =L28-K28 -> -0.074665257
E29: Recovery + LTV | F29: =factory!R29 -> -2.1096884 | G29: =factory!S29 -> 0.041753596 | H29: =G29-F29 -> 2.151442 | J29: Job Time | K29: =factory!G117 -> -0.63280526 | L29: =factory!H117 -> -0.49157282 | M29: =L29-K29 -> 0.14123244
E30: RAGU Score | F30: =factory!R30 -> 137.25869 | G30: =factory!S30 -> 142.47355 | H30: =G30-F30 -> 5.2148668 | J30: population % | K30: =INDEX('KMX populations'!B2:L2,MATCH("KMX | "&K$26,'KMX populations'!$B$1:$L$1, 0)) -> 0.16212339 | L30: =INDEX('KMX populations'!C2:M2,MATCH("KMX | "&L$26,'KMX populations'!$B$1:$L$1, 0)) -> 0.10980213 | M30: =L30-K30 -> -0.052321259
J31: Vehicle Age | K31: =factory!G107 -> 0.41491423 | L31: =factory!H107 -> 0.22464027 | M31: =L31-K31 -> -0.19027396
J32: Age | K32: =F38 -> 5.9169485 | L32: =G38 -> 6.1398487 | M32: =L32-K32 -> 0.22290017
J33: Soft Pull Factors | K33: =factory!G104+factory!G121 -> 0.046908282 | L33: =factory!H104+factory!H121 -> 1.2686239 | M33: =L33-K33 -> 1.2217157
J34: Low Vantage % | K34: =INDEX('KMX populations'!B29:L29,MATCH("KMX | "&K$26,'KMX populations'!$B$1:$L$1, 0)) -> 0.017535469 | L34: =INDEX('KMX populations'!C29:M29,MATCH("KMX | "&L$26,'KMX populations'!$B$1:$L$1, 0)) -> 0.0097220634 | M34: =L34-K34 -> -0.0078134061
E35: 2b. KMX Recovery Breakdown | J35: Low Cash Down % | K35: =INDEX('KMX populations'!B30:L30,MATCH("KMX | "&K$26,'KMX populations'!$B$1:$L$1, 0)) -> 0.089324619 | L35: =INDEX('KMX populations'!C30:M30,MATCH("KMX | "&L$26,'KMX populations'!$B$1:$L$1, 0)) -> 0.16184376 | M35: =L35-K35 -> 0.072519142
E36: KMX | F36: =B2 -> 2025 Q1 | G36: =B3 -> 2025 Q4 | H36: Delta | J36: State | K36: =factory!G112+factory!G113+factory!G114+factory!G115 -> -0.089100438 | L36: =factory!H112+factory!H113+factory!H114+factory!H115 -> 0.11138264 | M36: =L36-K36 -> 0.20048308
E37: LTV | F37: =INDEX(rec[ltv],MATCH($E$36&" "&F$36,rec[lookup], 0)) -> 1.6047279 | G37: =INDEX(rec[ltv],MATCH($E$36&" "&G$36,rec[lookup], 0)) -> 1.5761078 | H37: =G37-F37 -> -0.028620095 | J37: Louisiana % | K37: =INDEX('KMX populations'!B25:L25,MATCH("KMX | "&K$26,'KMX populations'!$B$1:$L$1, 0)) -> 0.0053137786 | L37: =INDEX('KMX populations'!C25:M25,MATCH("KMX | "&L$26,'KMX populations'!$B$1:$L$1, 0)) -> 0.0046894659 | M37: =L37-K37 -> -0.00062431277
E38: Age | F38: =INDEX(rec[age],MATCH($E$36&" "&F$36,rec[lookup], 0)) -> 5.9169485 | G38: =INDEX(rec[age],MATCH($E$36&" "&G$36,rec[lookup], 0)) -> 6.1398487 | H38: =G38-F38 -> 0.22290017 | J38: Georgia % | K38: =INDEX('KMX populations'!B26:L26,MATCH("KMX | "&K$26,'KMX populations'!$B$1:$L$1, 0)) -> 0.11584037 | L38: =INDEX('KMX populations'!C26:M26,MATCH("KMX | "&L$26,'KMX populations'!$B$1:$L$1, 0)) -> 0.077090244 | M38: =L38-K38 -> -0.03875013
E39: Mileage | F39: =INDEX(rec[mileage],MATCH($E$36&" "&F$36,rec[lookup], 0)) -> 60448 | G39: =INDEX(rec[mileage],MATCH($E$36&" "&G$36,rec[lookup], 0)) -> 60705 | H39: =G39-F39 -> 257 | J39: Texas/California % | K39: =INDEX('KMX populations'!B27:L27,MATCH("KMX | "&K$26,'KMX populations'!$B$1:$L$1, 0)) -> 0.25522079 | L39: =INDEX('KMX populations'!C27:M27,MATCH("KMX | "&L$26,'KMX populations'!$B$1:$L$1, 0)) -> 0.33752716 | M39: =L39-K39 -> 0.082306377
E40: Toyota/Honda | F40: =INDEX(rec[toyho],MATCH($E$36&" "&F$36,rec[lookup], 0)) -> 0.13852349 | G40: =INDEX(rec[toyho],MATCH($E$36&" "&G$36,rec[lookup], 0)) -> 0.23679363 | H40: =G40-F40 -> 0.098270144 | J40: Other Adjustments | K40: =SUM(factory!G98:G124)-K36-K33-K31-K29-K27 -> 1.2119309 | L40: =SUM(factory!H98:H124)-L36-L33-L31-L29-L27 -> 1.5059967 | M40: =L40-K40 -> 0.29406581
E41: Truck % | F41: =INDEX(rec[truck],MATCH($E$36&" "&F$36,rec[lookup], 0)) -> 0.053208054 | G41: =INDEX(rec[truck],MATCH($E$36&" "&G$36,rec[lookup], 0)) -> 0.068150004 | H41: =G41-F41 -> 0.01494195 | J41: Final Gross Loss | K41: =SUM(K27,K29,K31,K33,K36,K40) -> -0.34039323 | L41: =SUM(L27,L29,L31,L33,L36,L40) -> 1.489745 | M41: =L41-K41 -> 1.8301382
E42: Driver % | F42: =INDEX(rec[driver],MATCH($E$36&" "&F$36,rec[lookup], 0)) -> 0.0099865772 | G42: =INDEX(rec[driver],MATCH($E$36&" "&G$36,rec[lookup], 0)) -> 0.0087674059 | H42: =G42-F42 -> -0.0012191713
E46: SECTION 3: nonKMX LOB Breakdown
E48: =_xlfn.CONCAT("3a. ",B1," Ragu Breakdown") -> 3a. FLD Ragu Breakdown | J48: =_xlfn.CONCAT("3c. ",B1," Gross-Loss Breakdown") -> 3c. FLD Gross-Loss Breakdown
E49: =B1 -> FLD | F49: =B2 -> 2025 Q1 | G49: =B3 -> 2025 Q4 | H49: Delta | J49: =B1 -> FLD | K49: =B2 -> 2025 Q1 | L49: =B3 -> 2025 Q4 | M49: Delta
E50: Model Score | F50: =factory!M27 -> 136.70743 | G50: =factory!N27 -> 138.94555 | H50: =G50-F50 -> 2.2381222 | J50: Chime | K50: =factory!H49 -> -0.69044883 | L50: =factory!O49 -> -0.3397985 | M50: =L50-K50 -> 0.35065032
E51: Gross Loss | F51: =factory!M28 -> 2.4076495 | G51: =factory!N28 -> 1.6204382 | H51: =G51-F51 -> -0.78721128 | J51: population % | K51: =factory!I22 -> 0.22720478 | L51: =factory!J22 -> 0.18085669 | M51: =L51-K51 -> -0.046348094
E52: Recovery + LTV | F52: =factory!M29 -> 2.5711353 | G52: =factory!N29 -> 3.4826662 | H52: =G52-F52 -> 0.91153087 | J52: Student Loans | K52: =factory!H47 -> -0.22237148 | L52: =factory!O47 -> 0.0017976749 | M52: =L52-K52 -> 0.22416916
E53: RAGU Score | F53: =factory!M30 -> 141.68621 | G53: =factory!N30 -> 144.04866 | H53: =G53-F53 -> 2.3624418 | J53: population % | K53: =factory!I19 -> 0.26208271 | L53: =factory!J19 -> 0.20306716 | M53: =L53-K53 -> -0.05901555
J54: Toyota/Honda | K54: =factory!H43 -> 1.0003718 | L54: =factory!O43 -> 1.2487891 | M54: =L54-K54 -> 0.24841732
J55: population % | K55: =factory!I14 -> 0.20627803 | L55: =factory!J14 -> 0.25171867 | M55: =L55-K55 -> 0.04544064
J56: Fraud | K56: =factory!H52 -> 0.20695952 | L56: =factory!O52 -> 0.184275 | M56: =L56-K56 -> -0.022684517
E57: =_xlfn.CONCAT("3b. ",B1," Recovery Breakdown") -> 3b. FLD Recovery Breakdown | J57: Low Fraud % | K57: =factory!M13 -> 0.2137 | L57: =factory!N13 -> 0.1659 | M57: =L57-K57 -> -0.0478
E58: =B1 -> FLD | F58: =B2 -> 2025 Q1 | G58: =B3 -> 2025 Q4 | H58: Delta | J58: High Fraud % | K58: =factory!M14 -> 0.032 | L58: =factory!N14 -> 0.0739 | M58: =L58-K58 -> 0.0419
E59: LTV | F59: =INDEX(rec[ltv],MATCH($B$1&" "&F$58,rec[lookup], 0)) -> 1.4051985 | G59: =INDEX(rec[ltv],MATCH($B$1&" "&G$58,rec[lookup], 0)) -> 1.4340867 | H59: =G59-F59 -> 0.028888204 | J59: Dealer Level Loss | K59: =factory!H54 -> 2.1259614 | L59: =factory!O54 -> 0.54505149 | M59: =L59-K59 -> -1.58091
E60: Age | F60: =INDEX(rec[age],MATCH($B$1&" "&F$58,rec[lookup], 0)) -> 5.6023905 | G60: =INDEX(rec[age],MATCH($B$1&" "&G$58,rec[lookup], 0)) -> 4.9316693 | H60: =G60-F60 -> -0.67072118 | J60: Good Dealer % | K60: =factory!M7 -> 0.48391282 | L60: =factory!N7 -> 0.5343 | M60: =L60-K60 -> 0.050387179
E61: Mileage | F61: =INDEX(rec[mileage],MATCH($B$1&" "&F$58,rec[lookup], 0)) -> 63746 | G61: =INDEX(rec[mileage],MATCH($B$1&" "&G$58,rec[lookup], 0)) -> 57653 | H61: =G61-F61 -> -6093 | J61: Bad Dealer % | K61: =factory!M8 -> 0.051282051 | L61: =factory!N8 -> 0.059375 | M61: =L61-K61 -> 0.0080929487
E62: Toyota/Honda | F62: =K55 -> 0.20627803 | G62: =L55 -> 0.25171867 | H62: =G62-F62 -> 0.04544064 | J62: Other Adjustments | K62: =SUM(factory!H38:H57,-factory!H43-factory!H47-factory!H49-factory!H52-factory!H54) -> -0.012822938 | L62: =SUM(factory!O38:O57,-factory!O43-factory!O47-factory!O49-factory!O52-factory!O54) -> -0.019676552 | M62: =L62-K62 -> -0.0068536143
E63: Truck % | F63: =INDEX(rec[truck],MATCH($B$1&" "&F$58,rec[lookup], 0)) -> 0.046138415 | G63: =INDEX(rec[truck],MATCH($B$1&" "&G$58,rec[lookup], 0)) -> 0.054168879 | H63: =G63-F63 -> 0.0080304642 | J63: Final Gross Loss | K63: =SUM(K50,K52,K54,K56,K59,K62) -> 2.4076495 | L63: =SUM(L50,L52,L54,L56,L59,L62) -> 1.6204382 | M63: =L63-K63 -> -0.78721128
E64: Driver % | F64: =INDEX(rec[driver],MATCH($B$1&" "&F$58,rec[lookup], 0)) -> 0.032597793 | G64: =INDEX(rec[driver],MATCH($B$1&" "&G$58,rec[lookup], 0)) -> 0.039830058 | H64: =G64-F64 -> 0.007232265

Sheet KMX populations
B1: KMX | 2023 Q3 | C1: KMX | 2023 Q4 | D1: KMX | 2024 Q1 | E1: KMX | 2024 Q2 | F1: KMX | 2024 Q3 | G1: KMX | 2024 Q4 | H1: KMX | 2025 Q1 | I1: KMX | 2025 Q2 | J1: KMX | 2025 Q3 | K1: KMX | 2025 Q4 | L1: KMX | 2026 Q1
A2: job_time_flag | B2: 0.23563763 | C2: 0.2236671 | D2: 0.18614265 | E2: 0.16362192 | F2: 0.18165758 | G2: 0.17851864 | H2: 0.16212339 | I2: 0.11662371 | J2: 0.12642773 | K2: 0.14219679 | L2: 0.10980213
A3: low_fico_flag | B3: 0.052872475 | C3: 0.046442504 | D3: 0.039245949 | E3: 0.032204491 | F3: 0.029495353 | G3: 0.03957957 | H3: 0.0013815824 | I3: 0 | J3: 0 | K3: 0 | L3: 0.00045750886
A4: high_model_score_flag | B4: 0.23484848 | C4: 0.24168679 | D4: 0.197718 | E4: 0.2465882 | F4: 0.23112374 | G4: 0.24092626 | H4: 0.23763218 | I4: 0.26823454 | J4: 0.25915715 | K4: 0.26619708 | L4: 0.29532197
A5: low_vantage_flag | B5: 0 | C5: 0 | D5: 0 | E5: 0 | F5: 0 | G5: 0.00073903761 | H5: 0.014666029 | I5: 0.013402062 | J5: 0.010502823 | K5: 0.011739673 | L5: 0.0083495368
A6: normal_pti_flag | B6: 0.83475379 | C6: 0.83559354 | D6: 0.86963951 | E6: 0.86417792 | F6: 0.86896075 | G6: 0.86804073 | H6: 0.85812211 | I6: 0.87177835 | J6: 0.87770776 | K6: 0.87563284 | L6: 0.89820428
A7: high_pti_tier_1_flag | B7: 0.11300505 | C7: 0.10013004 | D7: 0.081964502 | E7: 0.081449924 | F7: 0.077809356 | G7: 0.074314337 | H7: 0.084170253 | I7: 0.077963918 | J7: 0.073782329 | K7: 0.075647516 | L7: 0.065652522
A8: high_pti_tier_2_flag | B8: 0.046875 | C8: 0.056474085 | D8: 0.044592658 | E8: 0.047801285 | F8: 0.046240111 | G8: 0.048940713 | H8: 0.049311866 | I8: 0.046585052 | J8: 0.044833924 | K8: 0.044097146 | L8: 0.033398147
A9: high_pti_tier_3_flag | B9: 0.0053661616 | C9: 0.0078023407 | D9: 0.0038033293 | E9: 0.0065708715 | F9: 0.0069897842 | G9: 0.0087042207 | H9: 0.0083957702 | I9: 0.0036726804 | J9: 0.0036759879 | K9: 0.0046224961 | L9: 0.0027450532
A10: existing_dq_flag | B10: 0.068181818 | C10: 0.071335686 | D10: 0.081303054 | E10: 0.080077984 | F10: 0.073123896 | G10: 0.094678929 | H10: 0.13061268 | I10: 0.10199742 | J10: 0.10213995 | K10: 0.11387483 | L10: 0.088642342
A11: seasonal_employment_flag | B11: 0 | C11: 0 | D11: 0 | E11: 0 | F11: 0 | G11: 0 | H11: 0.0079706679 | I11: 0.0067654639 | J11: 0.0073519758 | K11: 0.0079242791 | L11: 0.0043463342
A12: secured_credit_flag | B12: 0.24447601 | C12: 0.22422441 | D12: 0.274887 | E12: 0.26196837 | F12: 0.26684077 | G12: 0.24954837 | H12: 0.32849779 | I12: 0.3125 | J12: 0.35906525 | K12: 0.35732629 | L12: 0.24259408
A13: kmx_auth_tradelines_flag | B13: 0.050978535 | C13: 0.040126324 | D13: 0.03318267 | E13: 0.039641851 | F13: 0.040095245 | G13: 0.040482838 | H13: 0.038206068 | I13: 0.041237113 | J13: 0.039779441 | K13: 0.043069924 | L13: 0.026878646
... A37: --- N_RECORDS | B37: 6336 | C37: 5383 | D37: 18142 | E37: 13849 | F37: 13019 | G37: 12178 | H37: 18819 | I37: 15520 | J37: 15234 | K37: 13629 | L37: 8743

Sheet ragu
A1: measures | B1: AN 2023 Q3 | C1: AN 2023 Q4 | D1: AN 2024 Q1 | E1: AN 2024 Q2 | F1: AN 2024 Q3 | G1: AN 2024 Q4 | H1: AN 2025 Q1 | I1: AN 2025 Q2 | J1: AN 2025 Q3 | K1: AN 2025 Q4 | L1: AN 2026 Q1 | M1: FRN 2023 Q3 | N1: FRN 2023 Q4 | O1: FRN 2024 Q1 | P1: FRN 2024 Q2 | Q1: FRN 2024 Q3 | R1: FRN 2024 Q4 | S1: FRN 2025 Q1 | T1: FRN 2025 Q2 | U1: FRN 2025 Q3 | V1: FRN 2025 Q4 | W1: FRN 2026 Q1 | X1: STG 2023 Q3 | Y1: STG 2023 Q4 | Z1: STG 2024 Q1 | AA1: STG 2024 Q2 | AB1: STG 2024 Q3 | AC1: STG 2024 Q4 | AD1: STG 2025 Q1 | AE1: STG 2025 Q2 | AF1: STG 2025 Q3 | AG1: STG 2025 Q4 | AH1: STG 2026 Q1 | AI1: FLD 2023 Q3 | AJ1: FLD 2023 Q4 | AK1: FLD 2024 Q1 | AL1: FLD 2024 Q2 | AM1: FLD 2024 Q3 | AN1: FLD 2024 Q4 | AO1: FLD 2025 Q1 | AP1: FLD 2025 Q2 | AQ1: FLD 2025 Q3 | AR1: FLD 2025 Q4 | AS1: FLD 2026 Q1 | AT1: ENT 2023 Q3 | AU1: ENT 2023 Q4 | AV1: ENT 2024 Q1 | AW1: ENT 2024 Q2 | AX1: ENT 2024 Q3 | AY1: ENT 2024 Q4 | AZ1: ENT 2025 Q1 | BA1: ENT 2025 Q2 | BB1: ENT 2025 Q3 | BC1: ENT 2025 Q4 | BD1: ENT 2026 Q1 | BE1: KMX 2023 Q3 | BF1: KMX 2023 Q4 | BG1: KMX 2024 Q1 | BH1: KMX 2024 Q2 | BI1: KMX 2024 Q3 | BJ1: KMX 2024 Q4 | BK1: KMX 2025 Q1 | BL1: KMX 2025 Q2 | BM1: KMX 2025 Q3 | BN1: KMX 2025 Q4 | BO1: KMX 2026 Q1 | BP1: POS 2023 Q3 | BQ1: POS 2023 Q4 | BR1: POS 2024 Q1 | BS1: POS 2024 Q2 | BT1: POS 2024 Q3 | BU1: POS 2024 Q4 | BV1: POS 2025 Q1 | BW1: POS 2025 Q2 | BX1: POS 2025 Q3 | BY1: POS 2025 Q4 | BZ1: POS 2026 Q1
A2: AN | B2: 2023 Q3 | C2: 2023 Q4 | D2: 2024 Q1 | E2: 2024 Q2 | F2: 2024 Q3 | G2: 2024 Q4 | H2: 2025 Q1 | I2: 2025 Q2 | J2: 2025 Q3 | K2: 2025 Q4 | L2: 2026 Q1 | M2: 2023 Q3 | N2: 2023 Q4 | O2: 2024 Q1 | P2: 2024 Q2 | Q2: 2024 Q3 | R2: 2024 Q4 | S2: 2025 Q1 | T2: 2025 Q2 | U2: 2025 Q3 | V2: 2025 Q4 | W2: 2026 Q1 | X2: 2023 Q3 | Y2: 2023 Q4 | Z2: 2024 Q1 | AA2: 2024 Q2 | AB2: 2024 Q3 | AC2: 2024 Q4 | AD2: 2025 Q1 | AE2: 2025 Q2 | AF2: 2025 Q3 | AG2: 2025 Q4 | AH2: 2026 Q1 | AI2: 2023 Q3 | AJ2: 2023 Q4 | AK2: 2024 Q1 | AL2: 2024 Q2 | AM2: 2024 Q3 | AN2: 2024 Q4 | AO2: 2025 Q1 | AP2: 2025 Q2 | AQ2: 2025 Q3 | AR2: 2025 Q4 | AS2: 2026 Q1 | AT2: 2023 Q3 | AU2: 2023 Q4 | AV2: 2024 Q1 | AW2: 2024 Q2 | AX2: 2024 Q3 | AY2: 2024 Q4 | AZ2: 2025 Q1 | BA2: 2025 Q2 | BB2: 2025 Q3 | BC2: 2025 Q4 | BD2: 2026 Q1 | BE2: 2023 Q3 | BF2: 2023 Q4 | BG2: 2024 Q1 | BH2: 2024 Q2 | BI2: 2024 Q3 | BJ2: 2024 Q4 | BK2: 2025 Q1 | BL2: 2025 Q2 | BM2: 2025 Q3 | BN2: 2025 Q4 | BO2: 2026 Q1 | BP2: 2023 Q3 | BQ2: 2023 Q4 | BR2: 2024 Q1 | BS2: 2024 Q2 | BT2: 2024 Q3 | BU2: 2024 Q4 | BV2: 2025 Q1 | BW2: 2025 Q2 | BX2: 2025 Q3 | BY2: 2025 Q4 | BZ2: 2026 Q1
A3: ms | B3: 136.43849 | C3: 137.02135 | D3: 136.37212 | E3: 137.12198 | F3: 138.09052 | G3: 136.80136 | H3: 136.83702 | I3: 138.03382 | J3: 138.55808 | K3: 139.3761 | L3: 140.32164 | M3: 140.72103 | N3: 139.02514 | O3: 138.13163 | P3: 140.17356 | Q3: 141.55375 | R3: 139.97097 | S3: 139.83315 | T3: 140.63434 | U3: 140.96388 | V3: 141.85749 | W3: 142.87187 | X3: 138.53984 | Y3: 137.48747 | Z3: 136.76023 | AA3: 137.47802 | AB3: 138.54354 | AC3: 137.20905 | AD3: 136.6684 | AE3: 137.94719 | AF3: 138.66055 | AG3: 140.03752 | AH3: 141.49333 | AI3: 137.95666 | AJ3: 139.5662 | AK3: 138.5244 | AL3: 138.40978 | AM3: 140.36331 | AN3: 138.38769 | AO3: 136.70743 | AP3: 138.3478 | AQ3: 138.1021 | AR3: 138.94555 | AS3: 140.98773 | AT3: 133.76755 | AU3: 135.31367 | AV3: 136.17456 | AW3: 136.8171 | AX3: 136.69241 | AY3: 134.94875 | AZ3: 134.57148 | BA3: 136.41792 | BB3: 137.0063 | BC3: 137.20721 | BD3: 139.53493 | BE3: 140.50459 | BF3: 140.56078 | BG3: 139.56825 | BH3: 140.43212 | BI3: 139.88511 | BJ3: 139.76782 | BK3: 139.70877 | BL3: 139.86672 | BM3: 139.91791 | BN3: 140.94205 | BO3: 141.86953 | BP3: 139.07412 | BQ3: 138.9461 | BR3: 138.34968 | BS3: 139.22436 | BT3: 139.53563 | BU3: 138.6092 | BV3: 138.29936 | BW3: 139.10189 | BX3: 139.41596 | BY3: 140.32 | BZ3: 141.6242
A4: gl | B4: 0.6947113 | C4: 0.83003342 | D4: 0.65750359 | E4: 1.1812862 | F4: 0.97222553 | G4: 1.180284 | H4: 1.4582901 | I4: 2.4723015 | J4: 2.9310683 | K4: 3.3295966 | L4: 2.1031239 | M4: 1.6245882 | N4: 0.89105376 | O4: -0.19253143 | P4: 0.30849242 | Q4: 0.75767443 | R4: 0.52844615 | S4: 0.66878042 | T4: 1.2730461 | U4: 1.7966555 | V4: 2.7856639 | W4: 2.4440368 | X4: 1.4591709 | Y4: 1.2751302 | Z4: 1.0228541 | AA4: 2.0236416 | AB4: 2.2713522 | AC4: 2.0658579 | AD4: 1.8397214 | AE4: 2.0295688 | AF4: 2.2461463 | AG4: 2.9427504 | AH4: 2.3362459 | AI4: 1.0312225 | AJ4: 1.5139703 | AK4: 1.5512225 | AL4: 2.4386011 | AM4: 3.2825892 | AN4: 2.9662031 | AO4: 2.4076495 | AP4: 2.4907613 | AQ4: 3.0095789 | AR4: 1.6204382 | AS4: 1.1822025 | AT4: -0.72060842 | AU4: 0.4554259 | AV4: -0.58479913 | AW4: -0.32981376 | AX4: -0.47903773 | AY4: -0.28282436 | AZ4: -0.97520672 | BA4: 0.20726925 | BB4: 0.17758706 | BC4: 1.4255253 | BD4: 1.653816 | BE4: 1.500187 | BF4: 1.7611724 | BG4: 1.326646 | BH4: 2.2203145 | BI4: 1.9527827 | BJ4: 0.88362919 | BK4: -0.34039323 | BL4: 1.3978451 | BM4: 1.3198684 | BN4: 1.489745 | BO4: 2.0379889 | BP4: 0.93343132 | BQ4: 1.162946 | BR4: 0.7294941 | BS4: 1.4238402 | BT4: 1.4538116 | BU4: 0.86334079 | BV4: 0.21131625 | BW4: 1.4023257 | BX4: 1.5483029 | BY4: 1.9565456 | BZ4: 2.0460009
A5: rec | B5: -0.5325065 | C5: -0.25281508 | D5: -0.51081514 | E5: -0.06446555 | F5: 0.40869613 | G5: 1.2565312 | H5: 1.2681184 | I5: 1.9615167 | J5: 1.9504711 | K5: 2.9249529 | L5: 2.6126789 | M5: -0.53513029 | N5: -0.29126158 | O5: -0.43501302 | P5: 0.12781075 | Q5: 0.68635613 | R5: 1.4450343 | S5: 1.4081364 | T5: 1.7577979 | U5: 2.3062475 | V5: 2.8824874 | W5: 2.5987195 | X5: -0.26484568 | Y5: -0.090781414 | Z5: -0.31181896 | AA5: -0.11172011 | AB5: 0.44366114 | AC5: 1.5712764 | AD5: 1.5005718 | AE5: 1.589614 | AF5: 2.0673227 | AG5: 2.8088479 | AH5: 2.3179109 | AI5: 0.077495249 | AJ5: 0.083209397 | AK5: -0.28108863 | AL5: 0.27026879 | AM5: 0.72383376 | AN5: 1.8740137 | AO5: 1.7048188 | AP5: 1.7517113 | AQ5: 2.3146098 | AR5: 2.9958084 | AS5: 2.0638714 | AT5: -1.6322343 | AU5: -0.95299059 | AV5: -1.610546 | AW5: -1.1654003 | AX5: -0.24395432 | AY5: 2.4662444 | AZ5: 3.6740393 | BA5: 2.5640409 | BB5: 2.8515548 | BC5: 3.8490643 | BD5: 3.2315254 | BE5: -1.1552307 | BF5: -0.26620532 | BG5: -0.55823831 | BH5: -0.24605374 | BI5: -0.88286085 | BJ5: -1.0127231 | BK5: -1.3841086 | BL5: -0.66998588 | BM5: -0.18604374 | BN5: 0.28406997 | BO5: 0.20388839 | BP5: -1.0013974 | BQ5: -0.38134586 | BR5: -0.65915819 | BS5: -0.24549331 | BT5: -0.24816513 | BU5: 0.47763897 | BV5: 0.50879879 | BW5: 0.83371984 | BX5: 1.1832471 | BY5: 1.7490713 | BZ5: 1.2862663
A6: ltv | B6: 2.7072148 | C6: 2.2880395 | D6: 2.0027207 | E6: 2.5931537 | F6: 3.7446502 | G6: 3.3881857 | H6: 3.5073793 | I6: 4.0402816 | J6: 3.9702313 | K6: 4.2537913 | L6: 3.9510615 | M6: 5.0332926 | N6: 5.5678321 | O6: 5.235131 | P6: 5.3286289 | Q6: 5.1245756 | R6: 5.2098344 | S6: 5.1666469 | T6: 6.0848516 | U6: 6.1510731 | V6: 6.2080978 | W6: 5.3992753 | X6: 6.1354791 | Y6: 6.0717535 | Z6: 4.5804624 | AA6: 5.1378366 | AB6: 5.7066459 | AC6: 5.5483695 | AD6: 5.2166813 | AE6: 6.1403637 | AF6: 6.0382608 | AG6: 6.2534723 | AH6: 5.4380796 | AI6: 2.4767312 | AJ6: 2.1566317 | AK6: 0.82751227 | AL6: 1.0685351 | AM6: 1.32396 | AN6: 1.3976667 | AO6: 0.86631646 | AP6: 0.47398655 | AQ6: 0.45527757 | AR6: 0.48685779 | AS6: -0.34927165 | AT6: 2.6273819 | AU6: 1.8482391 | AV6: 1.7170448 | AW6: 1.9627113 | AX6: 1.7519385 | AY6: 1.3235352 | AZ6: 1.517698 | BA6: 1.9215073 | BB6: 1.8477536 | BC6: 1.6963273 | BD6: 1.2281394 | BE6: -3.6348155 | BF6: -4.8715329 | BG6: -4.102263 | BH6: -0.95598475 | BI6: -1.5608471 | BJ6: -1.5029132 | BK6: -0.72557978 | BL6: -0.32987472 | BM6: -0.515438 | BN6: -0.24231637 | BO6: 0.42277832 | BP6: =BP7-BP5 -> 0.50648984 | BQ6: -0.12326585 | BR6: -0.36969668 | BS6: 1.7502492 | BT6: 1.2521387 | BU6: 1.3408715 | BV6: 1.6509753 | BW6: 2.3823476 | BX6: 2.0616616 | BY6: 2.0327365 | BZ6: 1.8643971
A7: recltv | B7: 2.1747083 | C7: 2.0352244 | D7: 1.4919056 | E7: 2.5286881 | F7: 4.1533463 | G7: 4.644717 | H7: 4.7754977 | I7: 6.0017983 | J7: 5.9207025 | K7: 7.1787442 | L7: 6.5637405 | M7: 4.4981623 | N7: 5.2765706 | O7: 4.800118 | P7: 5.4564396 | Q7: 5.8109318 | R7: 6.6548687 | S7: 6.5747833 | T7: 7.8426495 | U7: 8.4573206 | V7: 9.0905852 | W7: 7.9979948 | X7: 5.8706334 | Y7: 5.9809721 | Z7: 4.2686434 | AA7: 5.0261164 | AB7: 6.150307 | AC7: 7.1196459 | AD7: 6.717253 | AE7: 7.7299777 | AF7: 8.1055835 | AG7: 9.0623202 | AH7: 7.7559905 | AI7: 2.5542264 | AJ7: 2.2398411 | AK7: 0.54642364 | AL7: 1.3388039 | AM7: 2.0477938 | AN7: 3.2716804 | AO7: 2.5711353 | AP7: 2.2256978 | AQ7: 2.7698874 | AR7: 3.4826662 | AS7: 1.7145998 | AT7: 0.99514758 | AU7: 0.89524852 | AV7: 0.10649875 | AW7: 0.797311 | AX7: 1.5079842 | AY7: 3.7897796 | AZ7: 5.1917373 | BA7: 4.4855482 | BB7: 4.6993084 | BC7: 5.5453916 | BD7: 4.4596648 | BE7: -4.7900462 | BF7: -5.1377382 | BG7: -4.6605013 | BH7: -1.2020385 | BI7: -2.443708 | BJ7: -2.5156363 | BK7: -2.1096884 | BL7: -0.9998606 | BM7: -0.70148174 | BN7: 0.041753596 | BO7: 0.62666671 | BP7: -0.49490755 | BQ7: 0.50673926 | BR7: -1.0288549 | BS7: 1.5047559 | BT7: 1.0039736 | BU7: 1.8185104 | BV7: 2.1597741 | BW7: 3.2160674 | BX7: 3.2449087 | BY7: 3.7818078 | BZ7: 3.1506634
A8: RAGU Score | B8: 139.30791 | C8: 139.88661 | D8: 138.52153 | E8: 140.83196 | F8: 143.21609 | G8: 142.62636 | H8: 143.07081 | I8: 146.50792 | J8: 147.40985 | K8: 149.88444 | L8: 148.9885 | M8: 146.84378 | N8: 145.19277 | O8: 142.73922 | P8: 145.93849 | Q8: 148.12236 | R8: 147.15429 | S8: 147.07671 | T8: 149.75003 | U8: 151.21786 | V8: 153.73374 | W8: 153.3139 | X8: 145.86964 | Y8: 144.74358 | Z8: 142.05173 | AA8: 144.52778 | AB8: 146.96519 | AC8: 146.39455 | AD8: 145.22537 | AE8: 147.70674 | AF8: 149.01228 | AG8: 152.04259 | AH8: 151.58557 | AI8: 141.54211 | AJ8: 143.32001 | AK8: 140.62205 | AL8: 142.18719 | AM8: 145.69369 | AN8: 144.62557 | AO8: 141.68621 | AP8: 143.06426 | AQ8: 143.88156 | AR8: 144.04866 | AS8: 143.88453 | AT8: 134.04209 | AU8: 136.66434 | AV8: 135.69626 | AW8: 137.2846 | AX8: 137.72136 | AY8: 138.45571 | AZ8: 138.78801 | BA8: 141.11074 | BB8: 141.88319 | BC8: 144.17813 | BD8: 145.64841 | BE8: 137.21474 | BF8: 137.18421 | BG8: 136.2344 | BH8: 141.45039 | BI8: 139.39419 | BJ8: 138.13581 | BK8: 137.25869 | BL8: 140.26471 | BM8: 140.5363 | BN8: 142.47355 | BO8: 144.53418 | BP8: =SUM(BP3:BP6) -> 139.51265 | BQ8: =SUM(BQ3:BQ6) -> 139.60443 | BR8: 138.05032 | BS8: 142.15296 | BT8: 141.99342 | BU8: 141.29105 | BV8: 140.67045 | BW8: 143.72028 | BX8: 144.20917 | BY8: 146.05835 | BZ8: 146.82086
A11: FRN | B11: 2023 Q3 | C11: 2023 Q4 | D11: 2024 Q1 | E11: 2024 Q2 | F11: 2024 Q3 | G11: 2024 Q4 | H11: 2025 Q1 | I11: 2025 Q2 | J11: 2025 Q3 | K11: 2025 Q4 | L11: 2026 Q1
A12: Contract Model Score¹ | B12: 140.72103 | C12: 139.02514 | D12: 138.13163 | E12: 140.17356 | F12: 141.55375 | G12: 139.97097 | H12: 139.83315 | I12: 140.63434 | J12: 140.96388 | K12: 141.85749 | L12: 142.87187
A13: Shift to FRN 3.1 Score² | B13: 0 | C13: 0 | D13: 0 | E13: 0 | F13: 0 | G13: 0 | H13: 0 | I13: 0 | J13: 0 | K13: 0 | L13: 0
A14: Gross Loss Adjustments (Dealer Level, vehicle age, etc.)² | B14: 1.6245882 | C14: 0.89105376 | D14: -0.19253143 | E14: 0.30849242 | F14: 0.75767443 | G14: 0.52844615 | H14: 0.66878042 | I14: 1.2730461 | J14: 1.7966555 | K14: 2.7856639 | L14: 2.4440368
A15: Recovery Adjustments excluding LTV (Mileage, LOB, etc.)³ | B15: -0.53513029 | C15: -0.29126158 | D15: -0.43501302 | E15: 0.12781075 | F15: 0.68635613 | G15: 1.4450343 | H15: 1.4081364 | I15: 1.7577979 | J15: 2.3062475 | K15: 2.8824874 | L15: 2.5987195
A16: BBLTV Adjustments⁴ | B16: 5.0332926 | C16: 5.5678321 | D16: 5.235131 | E16: 5.3286289 | F16: 5.1245756 | G16: 5.2098344 | H16: 5.1666469 | I16: 6.0848516 | J16: 6.1510731 | K16: 6.2080978 | L16: 5.3992753
A17: RAGU Score | B17: 146.84378 | C17: 145.19277 | D17: 142.73922 | E17: 145.93849 | F17: 148.12236 | G17: 147.15429 | H17: 147.07671 | I17: 149.75003 | J17: 151.21786 | K17: 153.73374 | L17: 153.3139
B18: 142.34561 | C18: 139.9162 | D18: 137.9391 | E18: 140.48205 | F18: 142.31143 | G18: 140.49942 | H18: 140.50193 | I18: 141.90738 | J18: 142.76054 | K18: 144.64315 | L18: 145.3159
A21: STG
A22: Contract Model Score¹
A23: Shift to FRN 3.1 Score²
A24: Gross Loss Adjustments (Dealer Level, vehicle age, etc.)²
A25: Recovery Adjustments excluding LTV (Mileage, LOB, etc.)³
A26: BBLTV Adjustments⁴
A27: RAGU Score
A30: FLD
A31: Contract Model Score¹
A32: Shift to FRN 3.1 Score²
A33: Gross Loss Adjustments (Dealer Level, vehicle age, etc.)²
A34: Recovery Adjustments excluding LTV (Mileage, LOB, etc.)³
... A47: RAGU Score
A51: POS | B51: 2023 Q3 | C51: 2023 Q4 | D51: 2024 Q1 | E51: 2024 Q2 | F51: 2024 Q3 | G51: 2024 Q4 | H51: 2025 Q1 | I51: 2025 Q2 | J51: 2025 Q3 | K51: 2025 Q4 | L51: 2026 Q1
A52: Contract Model Score | B52: 139.07412 | C52: 138.9461 | D52: 138.34968 | E52: 139.22436 | F52: 139.53563 | G52: 138.6092 | H52: 138.29936 | I52: 139.10189 | J52: 139.41596 | K52: 140.32 | L52: 141.62088
A53: Model Score | B53: -0.63837415 | C53: -0.5046117 | D53: 0.0040064067 | E53: 0.0019423191 | F53: -0.0011499063 | G53: -0.0032891709 | H53: -0.0010866271 | I53: -0.011151167 | J53: -0.0091706184 | K53: -0.0095421664 | L53: -3.023251e-05
A54: Gross Loss Adjustments (Dealer level, high PTI, etc.) | B54: 0.93343132 | C54: 1.162946 | D54: 0.7294941 | E54: 1.4238402 | F54: 1.4538116 | G54: 0.86334079 | H54: 0.21131625 | I54: 1.4023257 | J54: 1.5483029 | K54: 1.9565456 | L54: 2.0743527
A55: Recovery Adjustments excluding LTV (Mileage, vehicle type, etc.) | B55: -3.0640587 | C55: -2.3321053 | D55: -2.8143854 | E55: -2.3144091 | F55: -2.3932679 | G55: -1.6793889 | H55: -1.5987119 | I55: -1.2958988 | J55: -1.0729186 | K55: -0.59155057 | L55: -1.1132246
A56: LTV Adjustments | B56: 3.0640587 | C56: 2.3321053 | D56: 2.8143854 | E56: 2.3144091 | F56: 2.3932679 | G56: 1.6793889 | H56: 1.5987119 | I56: 1.2958988 | J56: 1.0729186 | K56: 0.59155057 | L56: 1.1132246
A57: RAGU Score | B57: 139.36918 | C57: 139.60443 | D57: 139.08318 | E57: 140.65014 | F57: 140.98829 | G57: 139.46925 | H57: 138.50959 | I57: 140.49306 | J57: 140.95509 | K57: 142.267 | L57: 143.6952
A58: LTV
A65: KMX | B65: 2023 Q3 | C65: 2023 Q4 | D65: 2024 Q1 | E65: 2024 Q2 | F65: 2024 Q3 | G65: 2024 Q4 | H65: 2025 Q1 | I65: 2025 Q2 | J65: 2025 Q3 | K65: 2025 Q4 | L65: 2026 Q1
A66: Contract Model Score² | B66: 140.50459 | C66: 140.56078 | D66: 139.56825 | E66: 140.43212 | F66: 139.88511 | G66: 139.76782 | H66: 139.70877 | I66: 139.86672 | J66: 139.91791 | K66: 140.94205 | L66: 141.8801
A67: Shift to Mountain3 Score³ | B67: 0 | C67: 0 | F67: 0 | G67: 0 | H67: 0
A68: Gross Loss Adjustments (vehicle age, weekday/weekend, etc.³) | B68: 1.500187 | C68: 1.7611724 | D68: 1.326646 | E68: 2.2203145 | F68: 1.9527827 | G68: 0.88362919 | H68: -0.34039323 | I68: 1.3978451 | J68: 1.3198684 | K68: 1.489745 | L68: 2.0810794
A70: BBLTV Adjustment to Recovery⁴ (Accounts for mileage/age and wholesale/retail gap⁵) | B70: -3.6345132 | C70: -4.8715329 | D70: -4.102263 | E70: -0.95598475 | F70: -1.5608471 | G70: -1.5029132 | H70: -0.72557978 | I70: -0.32987472 | J70: -0.515438 | K70: -0.24231637 | L70: 0.42686357
A71: RAGU Score | B71: 138.37027 | C71: 137.45042 | D71: 136.79263 | E71: 141.69645 | F71: 140.27705 | G71: 139.14853 | H71: 138.64279 | I71: 140.93469 | J71: 140.72234 | K71: 142.18948 | L71: 144.38804

Sheet POS decomp
A1: lookup | B1: time | C1: gl | D1: recltv | E1: RAGU Score | AN1: measures | AO1: AN 2023 Q3 | AP1: AN 2023 Q4 | AQ1: AN 2024 Q1 | AR1: AN 2024 Q2 | AS1: AN 2024 Q3 | AT1: AN 2024 Q4 | AU1: AN 2025 Q1 | AV1: AN 2025 Q2 | AW1: AN 2025 Q3 | AX1: AN 2025 Q4 | AY1: AN 2026 Q1
A2: AN 2023 Q3 | B2: 2023 Q3 | C2: 0.6947113 | D2: 2.1747083 | E2: 139.30791 | I2: 2023 Q3 | J2: 2023 Q4 | K2: 2024 Q1 | L2: 2024 Q2 | M2: 2024 Q3 | N2: 2024 Q4 | O2: 2025 Q1 | P2: 2025 Q2 | Q2: 2025 Q3 | R2: 2025 Q4 | S2: 2026 Q1 | AB2: 2023 Q3 | AC2: 2023 Q4 | AD2: 2024 Q1 | AE2: 2024 Q2 | AF2: 2024 Q3 | AG2: 2024 Q4 | AH2: 2025 Q1 | AI2: 2025 Q2 | AJ2: 2025 Q3 | AK2: 2025 Q4 | AL2: 2026 Q1 | AO2: 2023 Q3 | AP2: 2023 Q4 | AQ2: 2024 Q1 | AR2: 2024 Q2 | AS2: 2024 Q3 | AT2: 2024 Q4 | AU2: 2025 Q1 | AV2: 2025 Q2 | AW2: 2025 Q3 | AX2: 2025 Q4 | AY2: 2026 Q1
A3: AN 2023 Q4 | B3: 2023 Q4 | C3: 0.83003342 | D3: 2.0352244 | E3: 139.88661 | H3: AN | I3: 2.1747083 | J3: 2.0352244 | K3: 1.4919056 | L3: 2.5286881 | M3: 4.1533463 | N3: 4.644717 | O3: 4.7754977 | P3: 6.0017983 | Q3: 5.9207025 | R3: 7.1787442 | S3: 6.5637405 | AA3: AN | AB3: 0.6947113 | AC3: 0.83003342 | AD3: 0.65750359 | AE3: 1.1812862 | AF3: 0.97222553 | AG3: 1.180284 | AH3: 1.4582901 | AI3: 2.4723015 | AJ3: 2.9310683 | AK3: 3.3295966 | AL3: 2.1031239 | AN3: AN | AO3: 136.43849 | AP3: 137.02135 | AQ3: 136.37212 | AR3: 137.12198 | AS3: 138.09052 | AT3: 136.80136 | AU3: 136.83702 | AV3: 138.03382 | AW3: 138.55808 | AX3: 139.3761 | AY3: 140.32164
A4: AN 2024 Q1 | B4: 2024 Q1 | C4: 0.65750359 | D4: 1.4919056 | E4: 138.52153 | H4: FRN | I4: 4.4981623 | J4: 5.2765706 | K4: 4.800118 | L4: 5.4564396 | M4: 5.8109318 | N4: 6.6548687 | O4: 6.5747833 | P4: 7.8426495 | Q4: 8.4573206 | R4: 9.0905852 | S4: 7.9979948 | AA4: FRN | AB4: 1.6245882 | AC4: 0.89105376 | AD4: -0.19253143 | AE4: 0.30849242 | AF4: 0.75767443 | AG4: 0.52844615 | AH4: 0.66878042 | AI4: 1.2730461 | AJ4: 1.7966555 | AK4: 2.7856639 | AL4: 2.4440368 | AN4: FRN 2023 Q3 | AO4: 140.72103 | AP4: 139.02514 | AQ4: 138.13163 | AR4: 140.17356 | AS4: 141.55375 | AT4: 139.97097 | AU4: 139.83315 | AV4: 140.63434 | AW4: 140.96388 | AX4: 141.85749 | AY4: 142.87187
A5: AN 2024 Q2 | B5: 2024 Q2 | C5: 1.1812862 | D5: 2.5286881 | E5: 140.83196 | H5: STG | I5: 5.8706334 | J5: 5.9809721 | K5: 4.2686434 | L5: 5.0261164 | M5: 6.150307 | N5: 7.1196459 | O5: 6.717253 | P5: 7.7299777 | Q5: 8.1055835 | R5: 9.0623202 | S5: 7.7559905 | AA5: STG | AB5: 1.4591709 | AC5: 1.2751302 | AD5: 1.0228541 | AE5: 2.0236416 | AF5: 2.2713522 | AG5: 2.0658579 | AH5: 1.8397214 | AI5: 2.0295688 | AJ5: 2.2461463 | AK5: 2.9427504 | AL5: 2.3362459 | AN5: STG 2023 Q3 | AO5: 138.53984 | AP5: 137.48747 | AQ5: 136.76023 | AR5: 137.47802 | AS5: 138.54354 | AT5: 137.20905 | AU5: 136.6684 | AV5: 137.94719 | AW5: 138.66055 | AX5: 140.03752 | AY5: 141.49333
A6: AN 2024 Q3 | B6: 2024 Q3 | C6: 0.97222553 | D6: 4.1533463 | E6: 143.21609 | H6: FLD | I6: 2.5542264 | J6: 2.2398411 | K6: 0.54642364 | L6: 1.3388039 | M6: 2.0477938 | N6: 3.2716804 | O6: 2.5711353 | P6: 2.2256978 | Q6: 2.7698874 | R6: 3.4826662 | S6: 1.7145998 | AA6: FLD | AB6: 1.0312225 | AC6: 1.5139703 | AD6: 1.5512225 | AE6: 2.4386011 | AF6: 3.2825892 | AG6: 2.9662031 | AH6: 2.4076495 | AI6: 2.4907613 | AJ6: 3.0095789 | AK6: 1.6204382 | AL6: 1.1822025 | AN6: FLD 2023 Q3 | AO6: 137.95666 | AP6: 139.5662 | AQ6: 138.5244 | AR6: 138.40978 | AS6: 140.36331 | AT6: 138.38769 | AU6: 136.70743 | AV6: 138.3478 | AW6: 138.1021 | AX6: 138.94555 | AY6: 140.98773
A7: AN 2024 Q4 | B7: 2024 Q4 | C7: 1.180284 | D7: 4.644717 | E7: 142.62636 | H7: ENT | I7: 0.99514758 | J7: 0.89524852 | K7: 0.10649875 | L7: 0.797311 | M7: 1.5079842 | N7: 3.7897796 | O7: 5.1917373 | P7: 4.4855482 | Q7: 4.6993084 | R7: 5.5453916 | S7: 4.4596648 | AA7: ENT | AB7: -0.72060842 | AC7: 0.4554259 | AD7: -0.58479913 | AE7: -0.32981376 | AF7: -0.47903773 | AG7: -0.28282436 | AH7: -0.97520672 | AI7: 0.20726925 | AJ7: 0.17758706 | AK7: 1.4255253 | AL7: 1.653816 | AN7: ENT 2023 Q3 | AO7: 133.76755 | AP7: 135.31367 | AQ7: 136.17456 | AR7: 136.8171 | AS7: 136.69241 | AT7: 134.94875 | AU7: 134.57148 | AV7: 136.41792 | AW7: 137.0063 | AX7: 137.20721 | AY7: 139.53493
A8: AN 2025 Q1 | B8: 2025 Q1 | C8: 1.4582901 | D8: 4.7754977 | E8: 143.07081 | H8: KMX | I8: -4.7900462 | J8: -5.1377382 | K8: -4.6605013 | L8: -1.2020385 | M8: -2.443708 | N8: -2.5156363 | O8: -2.1096884 | P8: -0.9998606 | Q8: -0.70148174 | R8: 0.041753596 | S8: 0.62666671 | AA8: KMX | AB8: 1.500187 | AC8: 1.7611724 | AD8: 1.326646 | AE8: 2.2203145 | AF8: 1.9527827 | AG8: 0.88362919 | AH8: -0.34039323 | AI8: 1.3978451 | AJ8: 1.3198684 | AK8: 1.489745 | AL8: 2.0379889 | AN8: KMX 2023 Q3 | AO8: 140.50459 | AP8: 140.56078 | AQ8: 139.56825 | AR8: 140.43212 | AS8: 139.88511 | AT8: 139.76782 | AU8: 139.70877 | AV8: 139.86672 | AW8: 139.91791 | AX8: 140.94205 | AY8: 141.86953
A9: AN 2025 Q2 | B9: 2025 Q2 | C9: 2.4723015 | D9: 6.0017983 | E9: 146.50792 | H9: POS | I9: -0.49490755 | J9: 0.50673926 | K9: -1.0288549 | L9: 1.5047559 | M9: 1.0039736 | N9: 1.8185104 | O9: 2.1597741 | P9: 3.2160674 | Q9: 3.2449087 | R9: 3.7818078 | S9: 3.1506634 | AA9: POS | AB9: 0.93343132 | AC9: 1.162946 | AD9: 0.7294941 | AE9: 1.4238402 | AF9: 1.4538116 | AG9: 0.86334079 | AH9: 0.21131625 | AI9: 1.4023257 | AJ9: 1.5483029 | AK9: 1.9565456 | AL9: 2.0460009 | AN9: POS 2023 Q3 | AO9: 139.07412 | AP9: 138.9461 | AQ9: 138.34968 | AR9: 139.22436 | AS9: 139.53563 | AT9: 138.6092 | AU9: 138.29936 | AV9: 139.10189 | AW9: 139.41596 | AX9: 140.32 | AY9: 141.6242
A10: AN 2025 Q3 | B10: 2025 Q3 | C10: 2.9310683 | D10: 5.9207025 | E10: 147.40985
A11: AN 2025 Q4 | B11: 2025 Q4 | C11: 3.3295966 | D11: 7.1787442 | E11: 149.88444 | I11: 2023 Q3 | J11: 2023 Q4 | K11: 2024 Q1 | L11: 2024 Q2 | M11: 2024 Q3 | N11: 2024 Q4 | O11: 2025 Q1 | P11: 2025 Q2 | Q11: 2025 Q3 | R11: 2025 Q4 | S11: 2026 Q1 | AB11: 2023 Q3 | AC11: 2023 Q4 | AD11: 2024 Q1 | AE11: 2024 Q2 | AF11: 2024 Q3 | AG11: 2024 Q4 | AH11: 2025 Q1 | AI11: 2025 Q2 | AJ11: 2025 Q3 | AK11: 2025 Q4 | AL11: 2026 Q1 | AO11: 2023 Q3 | AP11: 2023 Q4 | AQ11: 2024 Q1 | AR11: 2024 Q2 | AS11: 2024 Q3 | AT11: 2024 Q4 | AU11: 2025 Q1 | AV11: 2025 Q2 | AW11: 2025 Q3 | AX11: 2025 Q4 | AY11: 2026 Q1
A12: AN 2026 Q1 | B12: 2026 Q1 | C12: 2.1031239 | D12: 6.5637405 | E12: 148.9885 | H12: AN | I12: 0.070929096 | J12: 0.074291945 | K12: 0.058184072 | L12: 0.058338772 | M12: 0.050205911 | N12: 0.051413163 | O12: 0.057133574 | P12: 0.063714886 | Q12: 0.062308989 | R12: 0.055795476 | S12: 0.050346189 | AA12: AN | AB12: 0.070929096 | AC12: 0.074291945 | AD12: 0.058184072 | AE12: 0.058338772 | AF12: 0.050205911 | AG12: 0.051413163 | AH12: 0.057133574 | AI12: 0.063714886 | AJ12: 0.062308989 | AK12: 0.055795476 | AL12: 0.050346189 | AN12: AN | AO12: 0.070929096 | AP12: 0.074291945 | AQ12: 0.058184072 | AR12: 0.058338772 | AS12: 0.050205911 | AT12: 0.051413163 | AU12: 0.057133574 | AV12: 0.063714886 | AW12: 0.062308989 | AX12: 0.055795476 | AY12: 0.050346189
A13: FRN 2023 Q3 | B13: 2023 Q3 | C13: 1.6245882 | D13: 4.4981623 | E13: 146.84378 | H13: FRN | I13: 0.13173055 | J13: 0.20736686 | K13: 0.16866511 | L13: 0.19601919 | M13: 0.17732092 | N13: 0.19095899 | O13: 0.17853916 | P13: 0.19503196 | Q13: 0.18284774 | R13: 0.16681261 | S13: 0.14858861 | AA13: FRN | AB13: 0.13173055 | AC13: 0.20736686 | AD13: 0.16866511 | AE13: 0.19601919 | AF13: 0.17732092 | AG13: 0.19095899 | AH13: 0.17853916 | AI13: 0.19503196 | AJ13: 0.18284774 | AK13: 0.16681261 | AL13: 0.14858861 | AN13: FRN | AO13: 0.13173055 | AP13: 0.20736686 | AQ13: 0.16866511 | AR13: 0.19601919 | AS13: 0.17732092 | AT13: 0.19095899 | AU13: 0.17853916 | AV13: 0.19503196 | AW13: 0.18284774 | AX13: 0.16681261 | AY13: 0.14858861
A14: FRN 2023 Q4 | B14: 2023 Q4 | C14: 0.89105376 | D14: 5.2765706 | E14: 145.19277 | H14: STG | I14: 0.087174269 | J14: 0.12225414 | K14: 0.088081451 | L14: 0.12671234 | M14: 0.11313255 | N14: 0.11311045 | O14: 0.11209916 | P14: 0.12922528 | Q14: 0.11076505 | R14: 0.10202236 | S14: 0.09685136 | AA14: STG | AB14: 0.087174269 | AC14: 0.12225414 | AD14: 0.088081451 | AE14: 0.12671234 | AF14: 0.11313255 | AG14: 0.11311045 | AH14: 0.11209916 | AI14: 0.12922528 | AJ14: 0.11076505 | AK14: 0.10202236 | AL14: 0.09685136 | AN14: STG | AO14: 0.087174269 | AP14: 0.12225414 | AQ14: 0.088081451 | AR14: 0.12671234 | AS14: 0.11313255 | AT14: 0.11311045 | AU14: 0.11209916 | AV14: 0.12922528 | AW14: 0.11076505 | AX14: 0.10202236 | AY14: 0.09685136
A15: FRN 2024 Q1 | B15: 2024 Q1 | C15: -0.19253143 | D15: 4.800118 | E15: 142.73922 | H15: FLD | I15: 0.04692546 | J15: 0.041137795 | K15: 0.034871177 | L15: 0.047661722 | M15: 0.035567417 | N15: 0.034023293 | O15: 0.044575499 | P15: 0.044732128 | Q15: 0.052429385 | R15: 0.061369675 | S15: 0.054321767 | AA15: FLD | AB15: 0.04692546 | AC15: 0.041137795 | AD15: 0.034871177 | AE15: 0.047661722 | AF15: 0.035567417 | AG15: 0.034023293 | AH15: 0.044575499 | AI15: 0.044732128 | AJ15: 0.052429385 | AK15: 0.061369675 | AL15: 0.054321767 | AN15: FLD | AO15: 0.04692546 | AP15: 0.041137795 | AQ15: 0.034871177 | AR15: 0.047661722 | AS15: 0.035567417 | AT15: 0.034023293 | AU15: 0.044575499 | AV15: 0.044732128 | AW15: 0.052429385 | AX15: 0.061369675 | AY15: 0.054321767
A16: FRN 2024 Q2 | B16: 2024 Q2 | C16: 0.30849242 | D16: 5.4564396 | E16: 145.93849 | H16: ENT | I16: 0.22533796 | J16: 0.21369115 | K16: 0.14808641 | L16: 0.13590997 | M16: 0.13206647 | N16: 0.14770705 | O16: 0.1545606 | P16: 0.14292378 | Q16: 0.13160231 | R16: 0.12908883 | S16: 0.098914219 | AA16: ENT | AB16: 0.22533796 | AC16: 0.21369115 | AD16: 0.14808641 | AE16: 0.13590997 | AF16: 0.13206647 | AG16: 0.14770705 | AH16: 0.1545606 | AI16: 0.14292378 | AJ16: 0.13160231 | AK16: 0.12908883 | AL16: 0.098914219 | AN16: ENT | AO16: 0.22533796 | AP16: 0.21369115 | AQ16: 0.14808641 | AR16: 0.13590997 | AS16: 0.13206647 | AT16: 0.14770705 | AU16: 0.1545606 | AV16: 0.14292378 | AW16: 0.13160231 | AX16: 0.12908883 | AY16: 0.098914219
A17: FRN 2024 Q3 | B17: 2024 Q3 | C17: 0.75767443 | D17: 5.8109318 | E17: 148.12236 | H17: KMX | I17: 0.43790266 | J17: 0.34125811 | K17: 0.50211178 | L17: 0.435358 | M17: 0.49170673 | N17: 0.46278705 | O17: 0.453092 | P17: 0.42437197 | Q17: 0.46004653 | R17: 0.48491105 | S17: 0.55097786 | AA17: KMX | AB17: 0.43790266 | AC17: 0.34125811 | AD17: 0.50211178 | AE17: 0.435358 | AF17: 0.49170673 | AG17: 0.46278705 | AH17: 0.453092 | AI17: 0.42437197 | AJ17: 0.46004653 | AK17: 0.48491105 | AL17: 0.55097786 | AN17: KMX | AO17: 0.43790266 | AP17: 0.34125811 | AQ17: 0.50211178 | AR17: 0.435358 | AS17: 0.49170673 | AT17: 0.46278705 | AU17: 0.453092 | AV17: 0.42437197 | AW17: 0.46004653 | AX17: 0.48491105 | AY17: 0.55097786
A18: FRN 2024 Q4 | B18: 2024 Q4 | C18: 0.52844615 | D18: 6.6548687 | E18: 147.15429
A19: FRN 2025 Q1 | B19: 2025 Q1 | C19: 0.66878042 | D19: 6.5747833 | E19: 147.07671
A20: FRN 2025 Q2 | B20: 2025 Q2 | C20: 1.2730461 | D20: 7.8426495 | E20: 149.75003 | H20: rec+ltv | I20: 2023 Q3 | J20: 2023 Q4 | K20: 2024 Q1 | L20: 2024 Q2 | M20: 2024 Q3 | N20: 2024 Q4 | O20: 2025 Q1 | P20: 2025 Q2 | Q20: 2025 Q3 | R20: 2025 Q4 | S20: 2026 Q1 | AA20: GL | AB20: 2023 Q3 | AC20: 2023 Q4 | AD20: 2024 Q1 | AE20: 2024 Q2 | AF20: 2024 Q3 | AG20: 2024 Q4 | AH20: 2025 Q1 | AI20: 2025 Q2 | AJ20: 2025 Q3 | AK20: 2025 Q4 | AL20: 2026 Q1 | AN20: GL | AO20: 2023 Q3 | AP20: 2023 Q4 | AQ20: 2024 Q1 | AR20: 2024 Q2 | AS20: 2024 Q3 | AT20: 2024 Q4 | AU20: 2025 Q1 | AV20: 2025 Q2 | AW20: 2025 Q3 | AX20: 2025 Q4 | AY20: 2026 Q1
A21: FRN 2025 Q3 | B21: 2025 Q3 | C21: 1.7966555 | D21: 8.4573206 | E21: 151.21786 | H21: KMX | I21: =I8*I17 -> -2.097574 | J21: =J8*J17 -> -1.7532948 | K21: =K8*K17 -> -2.3400926 | L21: =L8*L17 -> -0.52331708 | M21: =M8*M17 -> -1.2015877 | N21: =N8*N17 -> -1.1642039 | O21: =O8*O17 -> -0.95588293 | P21: =P8*P17 -> -0.42431282 | ... S21: =S8*S17 -> 0.34527948 | AA21: KMX | AB21: =AB8*AB17 -> 0.65693586 | AC21: =AC8*AC17 -> 0.60101438 | AD21: =AD8*AD17 -> 0.66612457 | AE21: =AE8*AE17 -> 0.96663166 | AF21: =AF8*AF17 -> 0.96019638 | AG21: =AG8*AG17 -> 0.40893214 | AH21: =AH8*AH17 -> -0.15422945 | AI21: =AI8*AI17 -> 0.59320628 | ... AL21: =AL8*AL17 -> 1.1228868 | AN21: KMX | AO21: =AO8*AO17 -> 61.527336 | AP21: =AP8*AP17 -> 47.967506 | AQ21: =AQ8*AQ17 -> 70.078862 | AR21: =AR8*AR17 -> 61.138246 | AS21: =AS8*AS17 -> 68.782453 | AT21: =AT8*AT17 -> 64.682736 | AU21: =AU8*AU17 -> 63.300925 | AV21: =AV8*AV17 -> 59.355517 | ... AY21: =AY8*AY17 -> 78.166967
A22: FRN 2025 Q4 | B22: 2025 Q4 | C22: 2.7856639 | D22: 9.0905852 | E22: 153.73374 | H22: AN | I22: =I3*I12 -> 0.15425009 | J22: =J3*J12 -> 0.15120078 | K22: =K3*K12 -> 0.08680514 | L22: =L3*L12 -> 0.14752056 | M22: =M3*M12 -> 0.20852254 | N22: =N3*N12 -> 0.23879959 | O22: =O3*O12 -> 0.27284125 | P22: =P3*P12 -> 0.38240389 | ... S22: =S3*S12 -> 0.33045932 | AA22: AN | AB22: =AB3*AB12 -> 0.049275244 | AC22: =AC3*AC12 -> 0.061664797 | AD22: =AD3*AD12 -> 0.038256236 | AE22: =AE3*AE12 -> 0.06891479 | AF22: =AF3*AF12 -> 0.048811468 | AG22: =AG3*AG12 -> 0.060682134 | AH22: =AH3*AH12 -> 0.083317327 | AI22: =AI3*AI12 -> 0.15752241 | ... AL22: =AL3*AL12 -> 0.10588427 | AN22: AN | AO22: =AO3*AO12 -> 9.677459 | AP22: =AP3*AP12 -> 10.179583 | AQ22: =AQ3*AQ12 -> 7.9346852 | AR22: =AR3*AR12 -> 7.9995282 | AS22: =AS3*AS12 -> 6.9329604 | AT22: =AT3*AT12 -> 7.0333904 | AU22: =AU3*AU12 -> 7.8179883 | AV22: =AV3*AV12 -> 8.7948091 | ... AY22: =AY3*AY12 -> 7.0646598
A23: FRN 2026 Q1 | B23: 2026 Q1 | C23: 2.4440368 | D23: 7.9979948 | E23: 153.3139 | H23: FRN | I23: =I4*I13 -> 0.5925454 | J23: =J4*J13 -> 1.0941859 | K23: =K4*K13 -> 0.80961243 | L23: =L4*L13 -> 1.0695669 | M23: =M4*M13 -> 1.0303998 | N23: =N4*N13 -> 1.270807 | O23: =O4*O13 -> 1.1738563 | P23: =P4*P13 -> 1.5295673 | ... S23: =S4*S13 -> 1.1884109 | AA23: FRN | AB23: =AB4*AB13 -> 0.2140079 | AC23: =AC4*AC13 -> 0.18477502 | AD23: =AD4*AD13 -> -0.032473335 | AE23: =AE4*AE13 -> 0.060470433 | AF23: =AF4*AF13 -> 0.13435153 | AG23: =AG4*AG13 -> 0.10091154 | AH23: =AH4*AH13 -> 0.1194035 | AI23: =AI4*AI13 -> 0.24828469 | ... AL23: =AL4*AL13 -> 0.36315603 | AN23: FRN | AO23: =AO4*AO13 -> 18.537258 | AP23: =AP4*AP13 -> 28.829207 | AQ23: =AQ4*AQ13 -> 23.297988 | AR23: =AR4*AR13 -> 27.476708 | AS23: =AS4*AS13 -> 25.100442 | AT23: =AT4*AT13 -> 26.728716 | AU23: =AU4*AU13 -> 24.965694 | AV23: =AV4*AV13 -> 27.42819 | ... AY23: =AY4*AY13 -> 21.229132
A24: STG 2023 Q3 | B24: 2023 Q3 | C24: 1.4591709 | D24: 5.8706334 | E24: 145.86964 | H24: STG | I24: =I5*I14 -> 0.51176818 | J24: =J5*J14 -> 0.73119863 | K24: =K5*K14 -> 0.37598831 | L24: =L5*L14 -> 0.636871 | M24: =M5*M14 -> 0.69579993 | N24: =N5*N14 -> 0.80530638 | O24: =O5*O14 -> 0.75299844 | P24: =P5*P14 -> 0.9989085 | ... S24: =S5*S14 -> 0.75117824 | AA24: STG | AB24: =AB5*AB14 -> 0.12720216 | AC24: =AC5*AC14 -> 0.15588995 | AD24: =AD5*AD14 -> 0.090094472 | AE24: =AE5*AE14 -> 0.25642037 | AF24: =AF5*AF14 -> 0.25696388 | AG24: =AG5*AG14 -> 0.23367012 | AH24: =AH5*AH14 -> 0.20623123 | AI24: =AI5*AI14 -> 0.26227159 | ... AL24: =AL5*AL14 -> 0.2262686 | AN24: STG | AO24: =AO5*AO14 -> 12.077109 | AP24: =AP5*AP14 -> 16.808413 | AQ24: =AQ5*AQ14 -> 12.04604 | AR24: =AR5*AR14 -> 17.420163 | AS24: =AS5*AS14 -> 15.673784 | AT24: =AT5*AT14 -> 15.519778 | AU24: =AU5*AU14 -> 15.320413 | AV24: =AV5*AV14 -> 17.826264 | ... AY24: =AY5*AY14 -> 13.703821
A25: STG 2023 Q4 | B25: 2023 Q4 | C25: 1.2751302 | D25: 5.9809721 | E25: 144.74358 | H25: FLD | I25: =I6*I15 -> 0.11985825 | J25: =J6*J15 -> 0.092142124 | K25: =K6*K15 -> 0.019054436 | L25: =L6*L15 -> 0.063809701 | M25: =M6*M15 -> 0.072834735 | N25: =N6*N15 -> 0.11131334 | O25: =O6*O15 -> 0.11460964 | P25: =P6*P15 -> 0.099560201 | ... S25: =S6*S15 -> 0.093140089 | AA25: FLD | AB25: =AB6*AB15 -> 0.048390588 | AC25: =AC6*AC15 -> 0.0622814 | AD25: =AD6*AD15 -> 0.054092955 | AE25: =AE6*AE15 -> 0.11622793 | AF25: =AF6*AF15 -> 0.11675322 | AG25: =AG6*AG15 -> 0.10092 | AH25: =AH6*AH15 -> 0.10732218 | AI25: =AI6*AI15 -> 0.11141705 | ... AL25: =AL6*AL15 -> 0.064219327 | AN25: FLD | AO25: =AO6*AO15 -> 6.4736796 | AP25: =AP6*AP15 -> 5.7414457 | AQ25: =AQ6*AQ15 -> 4.8305089 | AR25: =AR6*AR15 -> 6.5968485 | AS25: =AS6*AS15 -> 4.9923603 | AT25: =AT6*AT15 -> 4.7084047 | AU25: =AU6*AU15 -> 6.0938019 | AV25: =AV6*AV15 -> 6.1885914 | ... AY25: =AY6*AY15 -> 7.6587026
A26: STG 2024 Q1 | B26: 2024 Q1 | C26: 1.0228541 | D26: 4.2686434 | E26: 142.05173 | H26: ENT | I26: =I7*I16 -> 0.22424453 | J26: =J7*J16 -> 0.19130668 | K26: =K7*K16 -> 0.015771018 | L26: =L7*L16 -> 0.10836252 | M26: =M7*M16 -> 0.19915415 | N26: =N7*N16 -> 0.55977717 | O26: =O7*O16 -> 0.80243801 | P26: =P7*P16 -> 0.64109149 | ... S26: =S7*S16 -> 0.44112426 | AA26: ENT | AB26: =AB7*AB16 -> -0.16238043 | AC26: =AC7*AC16 -> 0.097320484 | AD26: =AD7*AD16 -> -0.086600805 | AE26: =AE7*AE16 -> -0.044824978 | AF26: =AF7*AF16 -> -0.06326482 | AG26: =AG7*AG16 -> -0.041775152 | AH26: =AH7*AH16 -> -0.15072853 | AI26: =AI7*AI16 -> 0.029623704 | ... AL26: =AL7*AL16 -> 0.16358592 | AN26: ENT | AO26: =AO7*AO16 -> 30.142908 | AP26: =AP7*AP16 -> 28.915333 | AQ26: =AQ7*AQ16 -> 20.165603 | AR26: =AR7*AR16 -> 18.594808 | AS26: =AS7*AS16 -> 18.052484 | AT26: =AT7*AT16 -> 19.932882 | AU26: =AU7*AU16 -> 20.799448 | AV26: =AV7*AV16 -> 19.497365 | ... AY26: =AY7*AY16 -> 13.801989
A27: STG 2024 Q2 | B27: 2024 Q2 | C27: 2.0236416 | D27: 5.0261164 | E27: 144.52778
A28: STG 2024 Q3 | B28: 2024 Q3 | C28: 2.2713522 | D28: 6.150307 | E28: 146.96519
A29: STG 2024 Q4 | B29: 2024 Q4 | C29: 2.0658579 | D29: 7.1196459 | E29: 146.39455 | H29: SUM | I29: =SUM(I21:I26) -> -0.49490755 | J29: =SUM(J21:J26) -> 0.50673926 | K29: =SUM(K21:K26) -> -1.0328613 | L29: =SUM(L21:L26) -> 1.5028136 | M29: =SUM(M21:M26) -> 1.0051235 | N29: =SUM(N21:N26) -> 1.8217996 | O29: =SUM(O21:O26) -> 2.1608607 | P29: =SUM(P21:P26) -> 3.2272186 | ... S29: =SUM(S21:S26) -> 3.1495923 | AA29: SUM | AB29: =SUM(AB21:AB26) -> 0.93343132 | AC29: =SUM(AC21:AC26) -> 1.162946 | AD29: =SUM(AD21:AD26) -> 0.7294941 | AE29: =SUM(AE21:AE26) -> 1.4238402 | AF29: =SUM(AF21:AF26) -> 1.4538116 | AG29: =SUM(AG21:AG26) -> 0.86334079 | AH29: =SUM(AH21:AH26) -> 0.21131625 | AI29: =SUM(AI21:AI26) -> 1.4023257 | ... AL29: =SUM(AL21:AL26) -> 2.0460009 | AN29: SUM | AO29: =SUM(AO21:AO26) -> 138.43575 | AP29: =SUM(AP21:AP26) -> 138.44149 | AQ29: =SUM(AQ21:AQ26) -> 138.35369 | AR29: =SUM(AR21:AR26) -> 139.2263 | AS29: =SUM(AS21:AS26) -> 139.53448 | AT29: =SUM(AT21:AT26) -> 138.60591 | AU29: =SUM(AU21:AU26) -> 138.29827 | AV29: =SUM(AV21:AV26) -> 139.09074 | ... AY29: =SUM(AY21:AY26) -> 141.62527
A30: STG 2025 Q1 | B30: 2025 Q1 | C30: 1.8397214 | D30: 6.717253 | E30: 145.22537 | I30: =SUMPRODUCT(I3:I8,I12:I17) -> -0.49490755 | J30: =SUMPRODUCT(J3:J8,J12:J17) -> 0.50673926 | K30: =SUMPRODUCT(K3:K8,K12:K17) -> -1.0328613 | L30: =SUMPRODUCT(L3:L8,L12:L17) -> 1.5028136 | M30: =SUMPRODUCT(M3:M8,M12:M17) -> 1.0051235 | N30: =SUMPRODUCT(N3:N8,N12:N17) -> 1.8217996 | O30: =SUMPRODUCT(O3:O8,O12:O17) -> 2.1608607 | P30: =SUMPRODUCT(P3:P8,P12:P17) -> 3.2272186 | ... S30: =SUMPRODUCT(S3:S8,S12:S17) -> 3.1495923
A31: STG 2025 Q2 | B31: 2025 Q2 | C31: 2.0295688 | D31: 7.7299777 | E31: 147.70674 | AN31: kmx | AO31: 140.50459 | AR31: 140.43212 | AU31: 139.70877 | AW31: 139.91791 | AY31: 141.86953
A32: STG 2025 Q3 | B32: 2025 Q3 | C32: 2.2461463 | D32: 8.1055835 | E32: 149.01228 | H32: nonkmx | I32: =SUM(I22:I26) -> 1.6026664 | J32: =SUM(J22:J26) -> 2.2600341 | K32: =SUM(K22:K26) -> 1.3072313 | L32: =SUM(L22:L26) -> 2.0261307 | M32: =SUM(M22:M26) -> 2.2067111 | N32: =SUM(N22:N26) -> 2.9860035 | O32: =SUM(O22:O26) -> 3.1167437 | P32: =SUM(P22:P26) -> 3.6515314 | ... S32: =SUM(S22:S26) -> 2.8043128 | AA32: nonkmx | AB32: =SUM(AB22:AB26) -> 0.27649545 | AC32: =SUM(AC22:AC26) -> 0.56193165 | AD32: =SUM(AD22:AD26) -> 0.063369523 | AE32: =SUM(AE22:AE26) -> 0.45720854 | AF32: =SUM(AF22:AF26) -> 0.49361527 | AG32: =SUM(AG22:AG26) -> 0.45440864 | AH32: =SUM(AH22:AH26) -> 0.3655457 | AI32: =SUM(AI22:AI26) -> 0.80911944 | ... AL32: =SUM(AL22:AL26) -> 0.92311414 | AN32: nonkmx | AO32: =(AO29-AO31*AO17)/(1-AO17) -> 136.82401 | AR32: =(AR29-AR31*AR17)/(1-AR17) -> 138.29658 | AU32: =(AU29-AU31*AU17)/(1-AU17) -> 137.12973 | AW32: =(AW29-AW31*AW17)/(1-AW17) -> 138.9713 | AY32: =(AY29-AY31*AY17)/(1-AY17) -> 141.32556
A33: STG 2025 Q4 | B33: 2025 Q4 | C33: 2.9427504 | D33: 9.0623202 | E33: 152.04259
A34: STG 2026 Q1 | B34: 2026 Q1 | C34: 2.3362459 | D34: 7.7559905 | E34: 151.58557 | AN34: kmx | AO34: 140.50459 | AP34: 140.43212 | AQ34: 139.70877 | AR34: 139.91791 | AS34: 141.86953
A35: FLD 2023 Q3 | B35: 2023 Q3 | C35: 1.0312225 | D35: 2.5542264 | E35: 141.54211 | AN35: nonkmx | AO35: 136.82401 | AP35: 138.29658 | AQ35: 137.12973 | AR35: 138.9713 | AS35: 141.32556
A36: FLD 2023 Q4 | B36: 2023 Q4 | C36: 1.5139703 | D36: 2.2398411 | E36: 143.32001
A37: FLD 2024 Q1 | B37: 2024 Q1 | C37: 1.5512225 | D37: 0.54642364 | E37: 140.62205
A38: FLD 2024 Q2 | B38: 2024 Q2 | C38: 2.4386011 | D38: 1.3388039 | E38: 142.18719
A39: FLD 2024 Q3 | B39: 2024 Q3 | C39: 3.2825892 | D39: 2.0477938 | E39: 145.69369
A40: FLD 2024 Q4 | B40: 2024 Q4 | C40: 2.9662031 | D40: 3.2716804 | E40: 144.62557
A41: FLD 2025 Q1 | B41: 2025 Q1 | C41: 2.4076495 | D41: 2.5711353 | E41: 141.68621
A42: FLD 2025 Q2 | B42: 2025 Q2 | C42: 2.4907613 | D42: 2.2256978 | E42: 143.06426
A43: FLD 2025 Q3 | B43: 2025 Q3 | C43: 3.0095789 | D43: 2.7698874 | E43: 143.88156
A44: FLD 2025 Q4 | B44: 2025 Q4 | C44: 1.6204382 | D44: 3.4826662 | E44: 144.04866
A45: FLD 2026 Q1 | B45: 2026 Q1 | C45: 1.1822025 | D45: 1.7145998 | E45: 143.88453
A46: ENT 2023 Q3 | B46: 2023 Q3 | C46: -0.72060842 | D46: 0.99514758 | E46: 134.04209
A47: ENT 2023 Q4 | B47: 2023 Q4 | C47: 0.4554259 | D47: 0.89524852 | E47: 136.66434
... A78: POS 2026 Q1 | B78: 2026 Q1 | C78: 2.0460009 | D78: 3.1506634 | E78: 146.82086

Sheet factory
A1: LOB | B1: =Main!B1 -> FLD
A2: Start | B2: =Main!B2 -> 2025 Q1
A3: End | B3: =Main!B3 -> 2025 Q4
C5: =B1 -> FLD | H5: =B1 -> FLD
C6: multipliers | D6: =B2 -> 2025 Q1 | E6: =B3 -> 2025 Q4 | H6: population % | I6: =B2 -> 2025 Q1 | J6: =B3 -> 2025 Q4 | L6: =B1 -> FLD | M6: =B2 -> 2025 Q1 | N6: =B3 -> 2025 Q4
C7: Previous ACA Chargeoff | D7: =INDEX(multipliers!$A3:$BD3,MATCH($B$1&" | "&D$6,Mult[#Headers], 0)) -> 1.0005481 | E7: =INDEX(multipliers!$A3:$BD3,MATCH($B$1&" | "&E$6,Mult[#Headers], 0)) -> 1.0002115 | H7: =populations!A2 -> prev_co_flag | I7: =INDEX(populations!$A2:$BD2,MATCH($B$1&" | "&I$6,flag[#Headers], 0)) -> 0.0054808171 | J7: =INDEX(populations!$A2:$BD2,MATCH($B$1&" | "&J$6,flag[#Headers], 0)) -> 0.0021152829 | L7: Good Dealer % | M7: =INDEX(dll[good_dealer],MATCH($B$1&" "&M$6,dll[lookup], 0)) -> 0.48391282 | N7: =INDEX(dll[good_dealer],MATCH($B$1&" "&N$6,dll[lookup], 0)) -> 0.5343
C8: Small Amount Financed | D8: =INDEX(multipliers!$A4:$BD4,MATCH($B$1&" | "&D$6,Mult[#Headers], 0)) -> 1.0005481 | E8: =INDEX(multipliers!$A4:$BD4,MATCH($B$1&" | "&E$6,Mult[#Headers], 0)) -> 1.0002115 | H8: =populations!A3 -> small_amt_financed_flag | I8: =INDEX(populations!$A3:$BD3,MATCH($B$1&" | "&I$6,flag[#Headers], 0)) -> 0.0004982561 | J8: =INDEX(populations!$A3:$BD3,MATCH($B$1&" | "&J$6,flag[#Headers], 0)) -> 0.00052882073 | L8: Bad Dealer % | M8: =INDEX(dll[bad_dealer],MATCH($B$1&" "&M$6,dll[lookup], 0)) -> 0.051282051 | N8: =INDEX(dll[bad_dealer],MATCH($B$1&" "&N$6,dll[lookup], 0)) -> 0.059375
C9: Zero Cash Down | D9: =INDEX(multipliers!$A5:$BD5,MATCH($B$1&" | "&D$6,Mult[#Headers], 0)) -> 1.0005481 | E9: =INDEX(multipliers!$A5:$BD5,MATCH($B$1&" | "&E$6,Mult[#Headers], 0)) -> 1.0002115 | H9: =populations!A4 -> pricing_change_flag | I9: =INDEX(populations!$A4:$BD4,MATCH($B$1&" | "&I$6,flag[#Headers], 0)) -> 1 | J9: =INDEX(populations!$A4:$BD4,MATCH($B$1&" | "&J$6,flag[#Headers], 0)) -> 1
C10: High Mileage | D10: =INDEX(multipliers!$A6:$BD6,MATCH($B$1&" | "&D$6,Mult[#Headers], 0)) -> 1.0012955 | E10: =INDEX(multipliers!$A6:$BD6,MATCH($B$1&" | "&E$6,Mult[#Headers], 0)) -> 1.0002115 | H10: =populations!A5 -> zero_cash_down_flag | I10: =INDEX(populations!$A5:$BD5,MATCH($B$1&" | "&I$6,flag[#Headers], 0)) -> 0.069755855 | J10: =INDEX(populations!$A5:$BD5,MATCH($B$1&" | "&J$6,flag[#Headers], 0)) -> 0.13326282
C11: High PTI | D11: =INDEX(multipliers!$A7:$BD7,MATCH($B$1&" | "&D$6,Mult[#Headers], 0)) -> 1.0012955 | E11: =INDEX(multipliers!$A7:$BD7,MATCH($B$1&" | "&E$6,Mult[#Headers], 0)) -> 1.0002115 | H11: =populations!A6 -> high_mileage_vehicle_flag | I11: =INDEX(populations!$A6:$BD6,MATCH($B$1&" | "&I$6,flag[#Headers], 0)) -> 0.0074738416 | J11: =INDEX(populations!$A6:$BD6,MATCH($B$1&" | "&J$6,flag[#Headers], 0)) -> 0
C12: Toyota/Honda | D12: =INDEX(multipliers!$A8:$BD8,MATCH($B$1&" | "&D$6,Mult[#Headers], 0)) -> 0.96003986 | E12: =INDEX(multipliers!$A8:$BD8,MATCH($B$1&" | "&E$6,Mult[#Headers], 0)) -> 0.94986779 | H12: =populations!A7 -> high_pti_flag | I12: =INDEX(populations!$A7:$BD7,MATCH($B$1&" | "&I$6,flag[#Headers], 0)) -> 0.0099651221 | J12: =INDEX(populations!$A7:$BD7,MATCH($B$1&" | "&J$6,flag[#Headers], 0)) -> 0.013220518 | L12: =B1 -> FLD | M12: =B2 -> 2025 Q1 | N12: =B3 -> 2025 Q4
C13: Theft Risk | D13: =INDEX(multipliers!$A9:$BD9,MATCH($B$1&" | "&D$6,Mult[#Headers], 0)) -> 0.96003986 | E13: =INDEX(multipliers!$A9:$BD9,MATCH($B$1&" | "&E$6,Mult[#Headers], 0)) -> 0.94986779 | H13: =populations!A8 -> car_make_penalty_flag | I13: =INDEX(populations!$A8:$BD8,MATCH($B$1&" | "&I$6,flag[#Headers], 0)) -> 0 | J13: =INDEX(populations!$A8:$BD8,MATCH($B$1&" | "&J$6,flag[#Headers], 0)) -> 0 | L13: Positive Fraud | M13: =INDEX(fraud[pos_fraud],MATCH($B$1&" "&M$12,fraud[lookup], 0)) -> 0.2137 | N13: =INDEX(fraud[pos_fraud],MATCH($B$1&" "&N$12,fraud[lookup], 0)) -> 0.1659
C14: 08_mcy_low_mileage | D14: =INDEX(multipliers!$A10:$BD10,MATCH($B$1&" | "&D$6,Mult[#Headers], 0)) -> 0.96003986 | E14: =INDEX(multipliers!$A10:$BD10,MATCH($B$1&" | "&E$6,Mult[#Headers], 0)) -> 0.94986779 | H14: =populations!A9 -> car_make_benefit_flag | I14: =INDEX(populations!$A9:$BD9,MATCH($B$1&" | "&I$6,flag[#Headers], 0)) -> 0.20627803 | J14: =INDEX(populations!$A9:$BD9,MATCH($B$1&" | "&J$6,flag[#Headers], 0)) -> 0.25171867 | L14: Negative Fraud | M14: =INDEX(fraud[neg_fraud],MATCH($B$1&" "&M$12,fraud[lookup], 0)) -> 0.032 | N14: =INDEX(fraud[neg_fraud],MATCH($B$1&" "&N$12,fraud[lookup], 0)) -> 0.0739
C15: Weekday/Weekend | D15: =INDEX(multipliers!$A11:$BD11,MATCH($B$1&" | "&D$6,Mult[#Headers], 0)) -> 0.95886497 | E15: =INDEX(multipliers!$A11:$BD11,MATCH($B$1&" | "&E$6,Mult[#Headers], 0)) -> 0.94915336 | H15: =populations!A10 -> theft_risk_flag | I15: =INDEX(populations!$A10:$BD10,MATCH($B$1&" | "&I$6,flag[#Headers], 0)) -> 0.064275037 | J15: =INDEX(populations!$A10:$BD10,MATCH($B$1&" | "&J$6,flag[#Headers], 0)) -> 0.03648863
C16: Student Loans | D16: =INDEX(multipliers!$A12:$BD12,MATCH($B$1&" | "&D$6,Mult[#Headers], 0)) -> 0.96787514 | E16: =INDEX(multipliers!$A12:$BD12,MATCH($B$1&" | "&E$6,Mult[#Headers], 0)) -> 0.9490828 | H16: =populations!A11 -> mcy_low_mileage_flag | I16: =INDEX(populations!$A11:$BD11,MATCH($B$1&" | "&I$6,flag[#Headers], 0)) -> 0 | J16: =INDEX(populations!$A11:$BD11,MATCH($B$1&" | "&J$6,flag[#Headers], 0)) -> 0
C17: Low PTI | D17: =INDEX(multipliers!$A13:$BD13,MATCH($B$1&" | "&D$6,Mult[#Headers], 0)) -> 0.96172353 | E17: =INDEX(multipliers!$A13:$BD13,MATCH($B$1&" | "&E$6,Mult[#Headers], 0)) -> 0.94256779 | H17: =populations!A12 -> weekend_flag | I17: =INDEX(populations!$A12:$BD12,MATCH($B$1&" | "&I$6,flag[#Headers], 0)) -> 0.30293971 | J17: =INDEX(populations!$A12:$BD12,MATCH($B$1&" | "&J$6,flag[#Headers], 0)) -> 0.29613961
C18: Chime | D18: =INDEX(multipliers!$A14:$BD14,MATCH($B$1&" | "&D$6,Mult[#Headers], 0)) -> 0.99006136 | E18: =INDEX(multipliers!$A14:$BD14,MATCH($B$1&" | "&E$6,Mult[#Headers], 0)) -> 0.95590668 | H18: =populations!A13 -> weekday_flag | I18: =INDEX(populations!$A13:$BD13,MATCH($B$1&" | "&I$6,flag[#Headers], 0)) -> 0.69706029 | J18: =INDEX(populations!$A13:$BD13,MATCH($B$1&" | "&J$6,flag[#Headers], 0)) -> 0.70386039
C19: Waiter/Seasonal | D19: =INDEX(multipliers!$A15:$BD15,MATCH($B$1&" | "&D$6,Mult[#Headers], 0)) -> 0.98939699 | E19: =INDEX(multipliers!$A15:$BD15,MATCH($B$1&" | "&E$6,Mult[#Headers], 0)) -> 0.95515159 | H19: =populations!A14 -> student_loan_flag | I19: =INDEX(populations!$A14:$BD14,MATCH($B$1&" | "&I$6,flag[#Headers], 0)) -> 0.26208271 | J19: =INDEX(populations!$A14:$BD14,MATCH($B$1&" | "&J$6,flag[#Headers], 0)) -> 0.20306716 | L19: =B1 -> FLD | M19: =B2 -> 2025 Q1 | N19: =B3 -> 2025 Q4
C20: Authorized Tradelines | D20: =INDEX(multipliers!$A16:$BD16,MATCH($B$1&" | "&D$6,Mult[#Headers], 0)) -> 0.99114741 | E20: =INDEX(multipliers!$A16:$BD16,MATCH($B$1&" | "&E$6,Mult[#Headers], 0)) -> 0.9571671 | H20: =populations!A15 -> student_loans_cutoff_date | I20: =INDEX(populations!$A15:$BD15,MATCH($B$1&" | "&I$6,flag[#Headers], 0)) -> 1 | J20: =INDEX(populations!$A15:$BD15,MATCH($B$1&" | "&J$6,flag[#Headers], 0)) -> 1 | L20: DQ MOB 3 | M20: =INDEX(dq[dq_3],MATCH($B$1&" "&M$19,dq[lookup], 0)) -> 0.186 | N20: =INDEX(dq[dq_3],MATCH($B$1&" "&N$19,dq[lookup], 0)) -> #N/A
C21: Fraud | D21: =INDEX(multipliers!$A17:$BD17,MATCH($B$1&" | "&D$6,Mult[#Headers], 0)) -> 0.98255731 | E21: =INDEX(multipliers!$A17:$BD17,MATCH($B$1&" | "&E$6,Mult[#Headers], 0)) -> 0.9499005 | H21: =populations!A16 -> low_pti_flag | I21: =INDEX(populations!$A16:$BD16,MATCH($B$1&" | "&I$6,flag[#Headers], 0)) -> 0.045341305 | J21: =INDEX(populations!$A16:$BD16,MATCH($B$1&" | "&J$6,flag[#Headers], 0)) -> 0.044949762 | L21: DQ MOB 6 | M21: =INDEX(dq[dq_6],MATCH($B$1&" "&M$19,dq[lookup], 0)) -> 0.2091 | N21: =INDEX(dq[dq_6],MATCH($B$1&" "&N$19,dq[lookup], 0)) -> #N/A
C22: Driver | D22: =INDEX(multipliers!$A18:$BD18,MATCH($B$1&" | "&D$6,Mult[#Headers], 0)) -> 0.98521821 | E22: =INDEX(multipliers!$A18:$BD18,MATCH($B$1&" | "&E$6,Mult[#Headers], 0)) -> 0.95366538 | H22: =populations!A17 -> nonkmx_chime_flag | I22: =INDEX(populations!$A17:$BD17,MATCH($B$1&" | "&I$6,flag[#Headers], 0)) -> 0.22720478 | J22: =INDEX(populations!$A17:$BD17,MATCH($B$1&" | "&J$6,flag[#Headers], 0)) -> 0.18085669 | L22: CO Rate MOB 6 | M22: =INDEX(dq[co_6],MATCH($B$1&" "&M$19,dq[lookup], 0)) -> 0.0356 | N22: =INDEX(dq[co_6],MATCH($B$1&" "&N$19,dq[lookup], 0)) -> #N/A
C23: Dealer Level Loss | D23: =INDEX(multipliers!$A19:$BD19,MATCH($B$1&" | "&D$6,Mult[#Headers], 0)) -> 0.90094692 | E23: =INDEX(multipliers!$A19:$BD19,MATCH($B$1&" | "&E$6,Mult[#Headers], 0)) -> 0.93240953 | H23: =populations!A18 -> seasonal_employment_pct | I23: =INDEX(populations!$A18:$BD18,MATCH($B$1&" | "&I$6,flag[#Headers], 0)) -> 0.0069755855 | J23: =INDEX(populations!$A18:$BD18,MATCH($B$1&" | "&J$6,flag[#Headers], 0)) -> 0.011634056 | L23: CO Rate MOB 12 | M23: =INDEX(dq[co_12],MATCH($B$1&" "&M$19,dq[lookup], 0)) -> 0.1288 | N23: =INDEX(dq[co_12],MATCH($B$1&" "&N$19,dq[lookup], 0)) -> #N/A
C24: Clip | D24: =INDEX(multipliers!$A20:$BD20,MATCH($B$1&" | "&D$6,Mult[#Headers], 0)) -> 0.90433308 | E24: =INDEX(multipliers!$A20:$BD20,MATCH($B$1&" | "&E$6,Mult[#Headers], 0)) -> 0.93068818 | H24: =populations!A19 -> waiter_employment_pct | I24: =INDEX(populations!$A19:$BD19,MATCH($B$1&" | "&I$6,flag[#Headers], 0)) -> 0.014449427 | J24: =INDEX(populations!$A19:$BD19,MATCH($B$1&" | "&J$6,flag[#Headers], 0)) -> 0.018508726
C25: Final Multplier | D25: =INDEX(multipliers!$A21:$BD21,MATCH($B$1&" | "&D$6,Mult[#Headers], 0)) -> 0.90433308 | E25: =INDEX(multipliers!$A21:$BD21,MATCH($B$1&" | "&E$6,Mult[#Headers], 0)) -> 0.93068818 | H25: =populations!A20 -> other_employment_pct | I25: =INDEX(populations!$A20:$BD20,MATCH($B$1&" | "&I$6,flag[#Headers], 0)) -> 0.97857499 | J25: =INDEX(populations!$A20:$BD20,MATCH($B$1&" | "&J$6,flag[#Headers], 0)) -> 0.96985722
C26: Weighted Multiplier | D26: =INDEX(multipliers!$A22:$BD22,MATCH($B$1&" | "&D$6,Mult[#Headers], 0)) -> 0.90369402 | E26: =INDEX(multipliers!$A22:$BD22,MATCH($B$1&" | "&E$6,Mult[#Headers], 0)) -> 0.93518247 | H26: =populations!A21 -> nonkmx_auth_tradelines_flag | I26: =INDEX(populations!$A21:$BD21,MATCH($B$1&" | "&I$6,flag[#Headers], 0)) -> 0.018933732 | J26: =INDEX(populations!$A21:$BD21,MATCH($B$1&" | "&J$6,flag[#Headers], 0)) -> 0.022210471 | L26: =B1 -> FLD | M26: =B2 -> 2025 Q1 | N26: =B3 -> 2025 Q4 | Q26: KMX | R26: =B2 -> 2025 Q1 | S26: =B3 -> 2025 Q4 | U26: POS | V26: =B2 -> 2025 Q1 | W26: =B3 -> 2025 Q4
C27: RAGU Impact | D27: =INDEX(multipliers!$A23:$BD23,MATCH($B$1&" | "&D$6,Mult[#Headers], 0)) -> 2.4076495 | E27: =INDEX(multipliers!$A23:$BD23,MATCH($B$1&" | "&E$6,Mult[#Headers], 0)) -> 1.6204382 | H27: =populations!A22 -> fraud_adjustment_mean | I27: =INDEX(populations!$A22:$BD22,MATCH($B$1&" | "&I$6,flag[#Headers], 0)) -> 0.99033881 | J27: =INDEX(populations!$A22:$BD22,MATCH($B$1&" | "&J$6,flag[#Headers], 0)) -> 0.99207827 | L27: Model Score | M27: =INDEX(ragu!$B3:$BZ3,MATCH($L$26&" "&M$26,ragu!$B$1:$BZ$1, 0)) -> 136.70743 | N27: =INDEX(ragu!$B3:$BZ3,MATCH($L$26&" "&N$26,ragu!$B$1:$BZ$1, 0)) -> 138.94555 | Q27: Model Score | R27: =INDEX(ragu!$B3:$BZ3,MATCH($Q$26&" "&R$26,ragu!$B$1:$BZ$1, 0)) -> 139.70877 | S27: =INDEX(ragu!$B3:$BZ3,MATCH($Q$26&" "&S$26,ragu!$B$1:$BZ$1, 0)) -> 140.94205 | U27: Model Score | V27: =INDEX(ragu!$B3:$BZ3,MATCH($U$26&" "&V$26,ragu!$B$1:$BZ$1, 0)) -> 138.29936 | W27: =INDEX(ragu!$B3:$BZ3,MATCH($U$26&" "&W$26,ragu!$B$1:$BZ$1, 0)) -> 140.32
H28: =populations!A23 -> driver_flag | I28: =INDEX(populations!$A23:$BD23,MATCH($B$1&" | "&I$6,flag[#Headers], 0)) -> 0.019431988 | J28: =INDEX(populations!$A23:$BD23,MATCH($B$1&" | "&J$6,flag[#Headers], 0)) -> 0.026969857 | L28: Gross Loss | M28: =INDEX(ragu!$B4:$BZ4,MATCH($L$26&" "&M$26,ragu!$B$1:$BZ$1, 0)) -> 2.4076495 | N28: =INDEX(ragu!$B4:$BZ4,MATCH($L$26&" "&N$26,ragu!$B$1:$BZ$1, 0)) -> 1.6204382 | Q28: Gross Loss | R28: =INDEX(ragu!$B4:$BZ4,MATCH($Q$26&" "&R$26,ragu!$B$1:$BZ$1, 0)) -> -0.34039323 | S28: =INDEX(ragu!$B4:$BZ4,MATCH($Q$26&" "&S$26,ragu!$B$1:$BZ$1, 0)) -> 1.489745 | U28: Gross Loss | V28: =INDEX(ragu!$B4:$BZ4,MATCH($U$26&" "&V$26,ragu!$B$1:$BZ$1, 0)) -> 0.21131625 | W28: =INDEX(ragu!$B4:$BZ4,MATCH($U$26&" "&W$26,ragu!$B$1:$BZ$1, 0)) -> 1.9565456
L29: Recovery + LTV | M29: =INDEX(ragu!$B7:$BZ7,MATCH($L$26&" "&M$26,ragu!$B$1:$BZ$1, 0)) -> 2.5711353 | N29: =INDEX(ragu!$B7:$BZ7,MATCH($L$26&" "&N$26,ragu!$B$1:$BZ$1, 0)) -> 3.4826662 | Q29: Recovery + LTV | R29: =INDEX(ragu!$B7:$BZ7,MATCH($Q$26&" "&R$26,ragu!$B$1:$BZ$1, 0)) -> -2.1096884 | S29: =INDEX(ragu!$B7:$BZ7,MATCH($Q$26&" "&S$26,ragu!$B$1:$BZ$1, 0)) -> 0.041753596 | U29: Recovery + LTV | V29: =INDEX(ragu!$B7:$BZ7,MATCH($U$26&" "&V$26,ragu!$B$1:$BZ$1, 0)) -> 2.1597741 | W29: =INDEX(ragu!$B7:$BZ7,MATCH($U$26&" "&W$26,ragu!$B$1:$BZ$1, 0)) -> 3.7818078
L30: RAGU Score | M30: =INDEX(ragu!$B8:$BZ8,MATCH($L$26&" "&M$26,ragu!$B$1:$BZ$1, 0)) -> 141.68621 | N30: =INDEX(ragu!$B8:$BZ8,MATCH($L$26&" "&N$26,ragu!$B$1:$BZ$1, 0)) -> 144.04866 | Q30: RAGU Score | R30: =INDEX(ragu!$B8:$BZ8,MATCH($Q$26&" "&R$26,ragu!$B$1:$BZ$1, 0)) -> 137.25869 | S30: =INDEX(ragu!$B8:$BZ8,MATCH($Q$26&" "&S$26,ragu!$B$1:$BZ$1, 0)) -> 142.47355 | U30: RAGU Score | V30: =INDEX(ragu!$B8:$BZ8,MATCH($U$26&" "&V$26,ragu!$B$1:$BZ$1, 0)) -> 140.67045 | W30: =INDEX(ragu!$B8:$BZ8,MATCH($U$26&" "&W$26,ragu!$B$1:$BZ$1, 0)) -> 146.05835
C36: =B1 -> FLD | J36: =B1 -> FLD
C37: =B2 -> 2025 Q1 | D37: mult before adjustment | E37: adjustment size | F37: ln | G37: share | H37: Ragu impact per adjustment | J37: =B3 -> 2025 Q4 | K37: mult before adjustment | L37: adjustment size | M37: ln | N37: share | O37: Ragu impact per adjustment | T37: Delta
C38: Previous ACA Chargeoff | D38: =$D$26/D7 -> 0.90319899 | E38: =D7/1 -> 1.0005481 | F38: =LN(E38) -> 0.00054793157 | G38: =F38/SUM($F$38:$F$57) -> -0.0054108977 | H38: =25*G38*(1-$D$26) -> -0.013027545 | J38: Previous ACA Chargeoff | K38: =$E$26/E7 -> 0.9349847 | L38: =E7/1 -> 1.0002115 | M38: =LN(L38) -> 0.00021150592 | N38: =M38/SUM($M$38:$M$57) -> -0.0031561636 | O38: =25*N38*(1-$E$26) -> -0.0051143681 | S38: Previous ACA Chargeoff | T38: =O38-H38 -> 0.007913177 | U38: =-ABS(T38) -> -0.007913177 | V38: {=_xlfn._xlws.SORT(U38:U57)} -> -1.58091 | W38: {=_xlfn.XLOOKUP(_xlfn.ANCHORARRAY(V38),U38:U57,S38:S57)} -> Dealer Level Loss
C39: Small Amount Financed | D39: =$D$26/D8 -> 0.90319899 | E39: =D8/D7 -> 1 | F39: =LN(E39) -> 0 | G39: =F39/SUM($F$38:$F$57) -> 0 | H39: =25*G39*(1-$D$26) -> 0 | J39: Small Amount Financed | K39: =$E$26/E8 -> 0.9349847 | L39: =E8/E7 -> 1 | M39: =LN(L39) -> 0 | N39: =M39/SUM($M$38:$M$57) -> 0 | O39: =25*N39*(1-$E$26) -> 0 | S39: Small Amount Financed | T39: =O39-H39 -> 0 | U39: =-ABS(T39) -> 0 | V39: -0.35065032 | W39: Chime
C40: Zero Cash Down | D40: =$D$26/D9 -> 0.90319899 | E40: =D9/D8 -> 1 | F40: =LN(E40) -> 0 | G40: =F40/SUM($F$38:$F$57) -> 0 | H40: =25*G40*(1-$D$26) -> 0 | J40: Zero Cash Down | K40: =$E$26/E9 -> 0.9349847 | L40: =E9/E8 -> 1 | M40: =LN(L40) -> 0 | N40: =M40/SUM($M$38:$M$57) -> 0 | O40: =25*N40*(1-$E$26) -> 0 | S40: Zero Cash Down | T40: =O40-H40 -> 0 | U40: =-ABS(T40) -> 0 | V40: -0.24841732 | W40: Toyota/Honda
C41: High Mileage | D41: =$D$26/D10 -> 0.90252483 | E41: =D10/D9 -> 1.000747 | F41: =LN(E41) -> 0.00074669591 | G41: =F41/SUM($F$38:$F$57) -> -0.0073737221 | H41: =25*G41*(1-$D$26) -> -0.017753338 | J41: High Mileage | K41: =$E$26/E10 -> 0.9349847 | L41: =E10/E9 -> 1 | M41: =LN(L41) -> 0 | N41: =M41/SUM($M$38:$M$57) -> 0 | O41: =25*N41*(1-$E$26) -> 0 | S41: High Mileage | T41: =O41-H41 -> 0.017753338 | U41: =-ABS(T41) -> -0.017753338 | V41: -0.22416916 | W41: Student Loans
C42: High PTI | D42: =$D$26/D11 -> 0.90252483 | E42: =D11/D10 -> 1 | F42: =LN(E42) -> 0 | G42: =F42/SUM($F$38:$F$57) -> 0 | H42: =25*G42*(1-$D$26) -> 0 | J42: High PTI | K42: =$E$26/E11 -> 0.9349847 | L42: =E11/E10 -> 1 | M42: =LN(L42) -> 0 | N42: =M42/SUM($M$38:$M$57) -> 0 | O42: =25*N42*(1-$E$26) -> 0 | S42: High PTI | T42: =O42-H42 -> 0 | U42: =-ABS(T42) -> 0 | V42: -0.13387451 | W42: Clip
C43: Toyota/Honda | D43: =$D$26/D12 -> 0.94130885 | E43: =D12/D11 -> 0.95879777 | F43: =LN(E43) -> -0.042075102 | G43: =F43/SUM($F$38:$F$57) -> 0.41549726 | H43: =25*G43*(1-$D$26) -> 1.0003718 | J43: Toyota/Honda | K43: =$E$26/E12 -> 0.98453961 | L43: =E12/E11 -> 0.94966691 | M43: =LN(L43) -> -0.051643973 | N43: =M43/SUM($M$38:$M$57) -> 0.77064901 | O43: =25*N43*(1-$E$26) -> 1.2487891 | S43: Toyota/Honda | T43: =O43-H43 -> 0.24841732 | U43: =-ABS(T43) -> -0.24841732 | V43: -0.13329503 | W43: Weighted Multiplier
C44: Theft Risk | D44: =$D$26/D13 -> 0.94130885 | E44: =D13/D12 -> 1 | F44: =LN(E44) -> 0 | G44: =F44/SUM($F$38:$F$57) -> 0 | H44: =25*G44*(1-$D$26) -> 0 | J44: Theft Risk | K44: =$E$26/E13 -> 0.98453961 | L44: =E13/E12 -> 1 | M44: =LN(L44) -> 0 | N44: =M44/SUM($M$38:$M$57) -> 0 | O44: =25*N44*(1-$E$26) -> 0 | S44: Theft Risk | T44: =O44-H44 -> 0 | U44: =-ABS(T44) -> 0 | V44: -0.03134844 | W44: Driver
C45: 08_mcy_low_mileage | D45: =$D$26/D14 -> 0.94130885 | E45: =D14/D13 -> 1 | F45: =LN(E45) -> 0 | G45: =F45/SUM($F$38:$F$57) -> 0 | H45: =25*G45*(1-$D$26) -> 0 | J45: 08_mcy_low_mileage | K45: =$E$26/E14 -> 0.98453961 | L45: =E14/E13 -> 1 | M45: =LN(L45) -> 0 | N45: =M45/SUM($M$38:$M$57) -> 0 | O45: =25*N45*(1-$E$26) -> 0 | S45: 08_mcy_low_mileage | T45: =O45-H45 -> 0 | U45: =-ABS(T45) -> 0 | V45: -0.022684517 | W45: Fraud
C46: Weekday/Weekend | D46: =$D$26/D15 -> 0.94246223 | E46: =D15/D14 -> 0.99877621 | F46: =LN(E46) -> -0.0012245402 | G46: =F46/SUM($F$38:$F$57) -> 0.012092498 | H46: =25*G46*(1-$D$26) -> 0.029114498 | J46: Weekday/Weekend | K46: =$E$26/E15 -> 0.98528069 | L46: =E15/E14 -> 0.99924786 | M46: =LN(L46) -> -0.00075242642 | N46: =M46/SUM($M$38:$M$57) -> 0.011227964 | O46: =25*N46*(1-$E$26) -> 0.018194222 | S46: Weekday/Weekend | T46: =O46-H46 -> -0.010920276 | U46: =-ABS(T46) -> -0.010920276 | V46: -0.017753338 | W46: High Mileage
C47: Student Loans | D47: =$D$26/D16 -> 0.93368864 | E47: =D16/D15 -> 1.0093967 | F47: =LN(E47) -> 0.0093528256 | G47: =F47/SUM($F$38:$F$57) -> -0.092360406 | H47: =25*G47*(1-$D$26) -> -0.22237148 | J47: Student Loans | K47: =$E$26/E16 -> 0.98535394 | L47: =E16/E15 -> 0.99992566 | M47: =LN(L47) -> -7.4343279e-05 | N47: =M47/SUM($M$38:$M$57) -> 0.0011093758 | O47: =25*N47*(1-$E$26) -> 0.0017976749 | S47: Student Loans | T47: =O47-H47 -> 0.22416916 | U47: =-ABS(T47) -> -0.22416916 | V47: -0.014965058 | W47: Low PTI
C48: Low PTI | D48: =$D$26/D17 -> 0.93966093 | E48: =D17/D16 -> 0.99364421 | F48: =LN(E48) -> -0.006376077 | G48: =F48/SUM($F$38:$F$57) -> 0.062964615 | H48: =25*G48*(1-$D$26) -> 0.15159672 | J48: Low PTI | K48: =$E$26/E17 -> 0.99216469 | L48: =E17/E16 -> 0.99313547 | M48: =LN(L48) -> -0.0068882025 | N48: =M48/SUM($M$38:$M$57) -> 0.10278811 | O48: =25*N48*(1-$E$26) -> 0.16656178 | S48: Low PTI | T48: =O48-H48 -> 0.014965058 | U48: =-ABS(T48) -> -0.014965058 | V48: -0.010920276 | W48: Weekday/Weekend
C49: Chime | D49: =$D$26/D18 -> 0.91276567 | E49: =D18/D17 -> 1.0294657 | F49: =LN(E49) -> 0.029039908 | G49: =F49/SUM($F$38:$F$57) -> -0.28677298 | H49: =25*G49*(1-$D$26) -> -0.69044883 | J49: Chime | K49: =$E$26/E18 -> 0.97831985 | L49: =E18/E17 -> 1.0141516 | M49: =LN(L49) -> 0.014052449 | N49: =M49/SUM($M$38:$M$57) -> -0.20969544 | O49: =25*N49*(1-$E$26) -> -0.3397985 | S49: Chime | T49: =O49-H49 -> 0.35065032 | U49: =-ABS(T49) -> -0.35065032 | V49: -0.0089443436 | W49: Authorized Tradelines
C50: Waiter/Seasonal | D50: =$D$26/D19 -> 0.91337858 | E50: =D19/D18 -> 0.99932896 | F50: =LN(E50) -> -0.00067126579 | G50: =F50/SUM($F$38:$F$57) -> 0.0066288396 | H50: =25*G50*(1-$D$26) -> 0.015959922 | J50: Waiter/Seasonal | K50: =$E$26/E19 -> 0.97909325 | L50: =E19/E18 -> 0.99921008 | M50: =LN(L50) -> -0.00079022878 | N50: =M50/SUM($M$38:$M$57) -> 0.011792064 | O50: =25*N50*(1-$E$26) -> 0.01910831 | S50: Waiter/Seasonal | T50: =O50-H50 -> 0.0031483882 | U50: =-ABS(T50) -> -0.0031483882 | V50: -0.007913177 | W50: Previous ACA Chargeoff
... C57: Weighted Multiplier | D57: =$D$26/D26 -> 1 | E57: =D26/D25 -> 0.99929334 | F57: =LN(E57) -> -0.00070691113 | G57: =F57/SUM($F$38:$F$57) -> 0.0069808421 | H57: =25*G57*(1-$D$26) -> 0.016807421 | J57: Weighted Multiplier | K57: =$E$26/E26 -> 1 | L57: =E26/E25 -> 1.004829 | M57: =LN(L57) -> 0.0048173729 | N57: =M57/SUM($M$38:$M$57) -> -0.071886484 | O57: =25*N57*(1-$E$26) -> -0.1164876 | S57: Weighted Multiplier | T57: =O57-H57 -> -0.13329503 | U57: =-ABS(T57) -> -0.13329503 | V57: 0 | W57: Small Amount Financed
G58: =SUM(G38:G57) -> 1 | H58: =SUM(H38:H57) -> 2.4076495 | O58: =SUM(O38:O57) -> 1.6204382
C62: KMX multipliers | D62: =B2 -> 2025 Q1 | E62: =B3 -> 2025 Q4
C63: 00_initial | D63: =INDEX('KMX Multipliers'!$B2:$L2,MATCH("KMX | "&D$6,'KMX Multipliers'!$B$1:$L$1, 0)) -> 1 | E63: =INDEX('KMX Multipliers'!$B2:$L2,MATCH("KMX | "&E$6,'KMX Multipliers'!$B$1:$L$1, 0)) -> 1
C64: 02_low_fico_3.0 | D64: =INDEX('KMX Multipliers'!$B3:$L3,MATCH("KMX | "&D$6,'KMX Multipliers'!$B$1:$L$1, 0)) -> 1.0001231 | E64: =INDEX('KMX Multipliers'!$B3:$L3,MATCH("KMX | "&E$6,'KMX Multipliers'!$B$1:$L$1, 0)) -> 1
C65: 03_low_vantage_3.0 | D65: =INDEX('KMX Multipliers'!$B4:$L4,MATCH("KMX | "&D$6,'KMX Multipliers'!$B$1:$L$1, 0)) -> 1.0008906 | E65: =INDEX('KMX Multipliers'!$B4:$L4,MATCH("KMX | "&E$6,'KMX Multipliers'!$B$1:$L$1, 0)) -> 1.0006312
C66: 04_high_pti_3.0 | D66: =INDEX('KMX Multipliers'!$B5:$L5,MATCH("KMX | "&D$6,'KMX Multipliers'!$B$1:$L$1, 0)) -> 1.0060587 | E66: =INDEX('KMX Multipliers'!$B5:$L5,MATCH("KMX | "&E$6,'KMX Multipliers'!$B$1:$L$1, 0)) -> 1.0043743
C67: 07_loss_scale_div_3.0 | D67: =INDEX('KMX Multipliers'!$B6:$L6,MATCH("KMX | "&D$6,'KMX Multipliers'!$B$1:$L$1, 0)) -> 0.97622211 | E67: =INDEX('KMX Multipliers'!$B6:$L6,MATCH("KMX | "&E$6,'KMX Multipliers'!$B$1:$L$1, 0)) -> 0.98199376
C68: 08_secured_credit_3.0 | D68: =INDEX('KMX Multipliers'!$B7:$L7,MATCH("KMX | "&D$6,'KMX Multipliers'!$B$1:$L$1, 0)) -> 0.98507398 | E68: =INDEX('KMX Multipliers'!$B7:$L7,MATCH("KMX | "&E$6,'KMX Multipliers'!$B$1:$L$1, 0)) -> 0.99320663
C69: 09_auth_tradelines_3.0 | D69: =INDEX('KMX Multipliers'!$B8:$L8,MATCH("KMX | "&D$6,'KMX Multipliers'!$B$1:$L$1, 0)) -> 0.98313574 | E69: =INDEX('KMX Multipliers'!$B8:$L8,MATCH("KMX | "&E$6,'KMX Multipliers'!$B$1:$L$1, 0)) -> 0.99234645
C70: 11_soft_pull_3.0 | D70: =INDEX('KMX Multipliers'!$B9:$L9,MATCH("KMX | "&D$6,'KMX Multipliers'!$B$1:$L$1, 0)) -> 0.972448 | E70: =INDEX('KMX Multipliers'!$B9:$L9,MATCH("KMX | "&E$6,'KMX Multipliers'!$B$1:$L$1, 0)) -> 0.98545447
C71: 12_fraud_all | D71: =INDEX('KMX Multipliers'!$B10:$L10,MATCH("KMX | "&D$6,'KMX Multipliers'!$B$1:$L$1, 0)) -> 0.96777865 | E71: =INDEX('KMX Multipliers'!$B10:$L10,MATCH("KMX | "&E$6,'KMX Multipliers'!$B$1:$L$1, 0)) -> 0.98504806
C72: 13_clip_3.0 | D72: =INDEX('KMX Multipliers'!$B11:$L11,MATCH("KMX | "&D$6,'KMX Multipliers'!$B$1:$L$1, 0)) -> 0.96702611 | E72: =INDEX('KMX Multipliers'!$B11:$L11,MATCH("KMX | "&E$6,'KMX Multipliers'!$B$1:$L$1, 0)) -> 0.98432426
C73: 14_vehicle_age_3.0 | D73: =INDEX('KMX Multipliers'!$B12:$L12,MATCH("KMX | "&D$6,'KMX Multipliers'!$B$1:$L$1, 0)) -> 0.95121574 | E73: =INDEX('KMX Multipliers'!$B12:$L12,MATCH("KMX | "&E$6,'KMX Multipliers'!$B$1:$L$1, 0)) -> 0.97524713
C74: 15_npc_all | D74: =INDEX('KMX Multipliers'!$B13:$L13,MATCH("KMX | "&D$6,'KMX Multipliers'!$B$1:$L$1, 0)) -> 0.95537873 | E74: =INDEX('KMX Multipliers'!$B13:$L13,MATCH("KMX | "&E$6,'KMX Multipliers'!$B$1:$L$1, 0)) -> 0.97741594
... C92: --- N_RECORDS | D92: =INDEX('KMX Multipliers'!$B31:$L31,MATCH("KMX | "&D$6,'KMX Multipliers'!$B$1:$L$1, 0)) -> 18819 | E92: =INDEX('KMX Multipliers'!$B31:$L31,MATCH("KMX | "&E$6,'KMX Multipliers'!$B$1:$L$1, 0)) -> 13629
C96: =B2 -> 2025 Q1
C97: KMX | D97: adjustment size | E97: ln | F97: share | G97: =C96 -> 2025 Q1 | H97: =C131 -> 2025 Q4
C98: Low Fico | D98: =D64/D63 -> 1.0001231 | E98: =LN(D98) -> 0.00012311267 | F98: =E98/SUM($E$98:$E$124) -> 0.0091033625 | G98: =25*F98*(1-$D$90) -> -0.0030987229 | H98: =G133 -> 0
C99: Low Vantage | D99: =D65/D64 -> 1.0007674 | E99: =LN(D99) -> 0.00076708029 | F99: =E99/SUM($E$98:$E$124) -> 0.056720481 | G99: =25*F99*(1-$D$90) -> -0.019307267 | H99: =G134 -> -0.015300861
C100: High PRI | D100: =D66/D65 -> 1.0051635 | E100: =LN(D100) -> 0.0051502388 | F100: =E100/SUM($E$98:$E$124) -> 0.38082587 | G100: =25*F100*(1-$D$90) -> -0.12963055 | H100: =G135 -> -0.090532549
C101: Scalar division | D101: =D67/D66 -> 0.97034308 | E101: =LN(D101) -> -0.030105583 | F101: =E101/SUM($E$98:$E$124) -> -2.2261074 | G101: =25*F101*(1-$D$90) -> 0.75775189 | H101: =G136 -> 0.54641835
C102: Secured Credit | D102: =D68/D67 -> 1.0090675 | E102: =LN(D102) -> 0.0090266178 | F102: =E102/SUM($E$98:$E$124) -> 0.66745829 | G102: =25*F102*(1-$D$90) -> -0.22719828 | H102: =G137 -> -0.27530067
C103: Auth Tradelines | D103: =D69/D68 -> 0.99803239 | E103: =LN(D103) -> -0.0019695524 | F103: =E103/SUM($E$98:$E$124) -> -0.14563529 | G103: =25*F103*(1-$D$90) -> 0.049573266 | H103: =G138 -> 0.021009106
C104: Soft Pull | D104: =D70/D69 -> 0.98912893 | E104: =LN(D104) -> -0.010930589 | F104: =E104/SUM($E$98:$E$124) -> -0.80824428 | G104: =25*F104*(1-$D$90) -> 0.27512088 | H104: =G139 -> 0.16898964
C105: Fraud | D105: =D71/D70 -> 0.99519836 | E105: =LN(D105) -> -0.0048132071 | F105: =E105/SUM($E$98:$E$124) -> -0.35590462 | G105: =25*F105*(1-$D$90) -> 0.12114752 | H105: =G140 -> 0.010001986
C106: Clip | D106: =D72/D71 -> 0.9992224 | E106: =LN(D106) -> -0.00077790602 | F106: =E106/SUM($E$98:$E$124) -> -0.057520971 | G106: =25*F106*(1-$D$90) -> 0.019579749 | H106: =G141 -> 0.017823186
C107: Age | D107: =D73/D72 -> 0.98365053 | E107: =LN(D107) -> -0.016484597 | F107: =E107/SUM($E$98:$E$124) -> -1.2189262 | G107: =25*F107*(1-$D$90) -> 0.41491423 | H107: =G142 -> 0.22464027
C108: NPC | D108: =D74/D73 -> 1.0043765 | E108: =LN(D108) -> 0.0043669412 | F108: =E108/SUM($E$98:$E$124) -> 0.32290623 | G108: =25*F108*(1-$D$90) -> -0.10991509 | H108: =G143 -> -0.053863131
C109: Student Loans | D109: =D75/D74 -> 1.0047877 | E109: =LN(D109) -> 0.0047762847 | F109: =E109/SUM($E$98:$E$124) -> 0.35317446 | G109: =25*F109*(1-$D$90) -> -0.12021819 | H109: =G144 -> 0.288322
... C124: --- WTD_MULT_RAGU | D124: =D90/D89 -> 0.9835014 | E124: =LN(D124) -> -0.016636216 | F124: =E124/SUM($E$98:$E$124) -> -1.2301374 | G124: =25*F124*(1-$D$90) -> 0.41873045 | H124: =G159 -> 0.612729
G126: =SUM(G98:G124) -> -0.34039323 | H126: =SUM(H98:H124) -> 1.489745
C131: =B3 -> 2025 Q4
C132: KMX | D132: adjustment size | E132: ln | F132: share | G132: impact
C133: 02_low_fico_3.0 | D133: =E64/E63 -> 1 | E133: =LN(D133) -> 0 | F133: =E133/SUM($E$133:$E$159) -> 0 | G133: =25*F133*(1-$E$90) -> 0
C134: 03_low_vantage_3.0 | D134: =E65/E64 -> 1.0006312 | E134: =LN(D134) -> 0.00063102839 | F134: =E134/SUM($E$133:$E$159) -> -0.010270792 | G134: =25*F134*(1-$E$90) -> -0.015300861
C135: 04_high_pti_3.0 | D135: =E66/E65 -> 1.0037407 | E135: =LN(D135) -> 0.0037336858 | F135: =E135/SUM($E$133:$E$159) -> -0.060770501 | G135: =25*F135*(1-$E$90) -> -0.090532549
C136: 07_loss_scale_div_3.0 | D136: =E67/E66 -> 0.97771698 | E136: =LN(D136) -> -0.022535038 | F136: =E136/SUM($E$133:$E$159) -> 0.3667865 | G136: =25*F136*(1-$E$90) -> 0.54641835
C137: 08_secured_credit_3.0 | D137: =E68/E67 -> 1.0114185 | E137: =LN(D137) -> 0.011353775 | F137: =E137/SUM($E$133:$E$159) -> -0.18479718 | G137: =25*F137*(1-$E$90) -> -0.27530067
C138: 09_auth_tradelines_3.0 | D138: =E69/E68 -> 0.99913393 | E138: =LN(D138) -> -0.00086644419 | F138: =E138/SUM($E$133:$E$159) -> 0.014102485 | G138: =25*F138*(1-$E$90) -> 0.021009106
C139: 11_soft_pull_3.0 | D139: =E70/E69 -> 0.99305487 | E139: =LN(D139) -> -0.0069693633 | F139: =E139/SUM($E$133:$E$159) -> 0.11343528 | G139: =25*F139*(1-$E$90) -> 0.16898964
C140: 12_fraud_all | D140: =E71/E70 -> 0.99958759 | E140: =LN(D140) -> -0.00041249555 | F140: =E140/SUM($E$133:$E$159) -> 0.0067138914 | G140: =25*F140*(1-$E$90) -> 0.010001986
C141: 13_clip_3.0 | D141: =E72/E71 -> 0.99926522 | E141: =LN(D141) -> -0.00073505251 | F141: =E141/SUM($E$133:$E$159) -> 0.011963918 | G141: =25*F141*(1-$E$90) -> 0.017823186
C142: 14_vehicle_age_3.0 | D142: =E73/E72 -> 0.99077831 | E142: =LN(D142) -> -0.0092644714 | F142: =E142/SUM($E$133:$E$159) -> 0.15079109 | G142: =25*F142*(1-$E$90) -> 0.22464027
C143: 15_npc_all | D143: =E74/E73 -> 1.0022239 | E143: =LN(D143) -> 0.002221389 | F143: =E143/SUM($E$133:$E$159) -> -0.036155941 | G143: =25*F143*(1-$E$90) -> -0.053863131
C144: 16_student_loans_all | D144: =E75/E74 -> 0.98817962 | E144: =LN(D144) -> -0.011890793 | F144: =E144/SUM($E$133:$E$159) -> 0.19353782 | G144: =25*F144*(1-$E$90) -> 0.288322
... C159: --- WTD_MULT_RAGU | D159: =E90/E89 -> 0.97504683 | E159: =LN(D159) -> -0.02526978 | F159: =E159/SUM($E$133:$E$159) -> 0.41129791 | G159: =25*F159*(1-$E$90) -> 0.612729
G161: =SUM(G133:G159) -> 1.489745

Sheet recovery
A1: time | B1: lob | C1: ltv | D1: age | E1: mileage | F1: toyho | G1: driver | H1: truck | I1: lookup
A2: 2023 Q1 | B2: AN | C2: 1.829784 | D2: 9.4471088 | E2: 109832 | F2: 0.27959184 | G2: 0.02755102 | H2: 0.089795918 | I2: =_xlfn.CONCAT(rec[[#This Row],[lob]], " ",rec[[#This Row],[time]]) -> AN 2023 Q1
A3: 2023 Q2 | B3: AN | C3: 1.7423592 | D3: 9.3572724 | E3: 105401 | F3: 0.23177367 | G3: 0.031556039 | H3: 0.096844396 | I3: =_xlfn.CONCAT(rec[[#This Row],[lob]], " ",rec[[#This Row],[time]]) -> AN 2023 Q2
A4: 2023 Q3 | B4: AN | C4: 1.7141356 | D4: 9.3047582 | E4: 104992 | F4: 0.23196276 | G4: 0.025601241 | H4: 0.1132661 | I4: =_xlfn.CONCAT(rec[[#This Row],[lob]], " ",rec[[#This Row],[time]]) -> AN 2023 Q3
A5: 2023 Q4 | B5: AN | C5: 1.7553392 | D5: 9.3594378 | E5: 105760 | F5: 0.24984147 | G5: 0.029169309 | H5: 0.097653773 | I5: =_xlfn.CONCAT(rec[[#This Row],[lob]], " ",rec[[#This Row],[time]]) -> AN 2023 Q4
A6: 2024 Q1 | B6: AN | C6: 1.7314752 | D6: 8.8026368 | E6: 97273 | F6: 0.25265643 | G6: 0.024399843 | H6: 0.079496261 | I6: =_xlfn.CONCAT(rec[[#This Row],[lob]], " ",rec[[#This Row],[time]]) -> AN 2024 Q1
A7: 2024 Q2 | B7: AN | C7: 1.6712965 | D7: 8.5337544 | E7: 94439 | F7: 0.2630662 | G7: 0.025696864 | H7: 0.097996516 | I7: =_xlfn.CONCAT(rec[[#This Row],[lob]], " ",rec[[#This Row],[time]]) -> AN 2024 Q2
A8: 2024 Q3 | B8: AN | C8: 1.660222 | D8: 8.5916105 | E8: 92777 | F8: 0.28203556 | G8: 0.028816677 | H8: 0.12017167 | I8: =_xlfn.CONCAT(rec[[#This Row],[lob]], " ",rec[[#This Row],[time]]) -> AN 2024 Q3
A9: 2024 Q4 | B9: AN | C9: 1.6412285 | D9: 8.2111042 | E9: 90398 | F9: 0.37911746 | G9: 0.027346178 | H9: 0.09695463 | I9: =_xlfn.CONCAT(rec[[#This Row],[lob]], " ",rec[[#This Row],[time]]) -> AN 2024 Q4
A10: 2025 Q1 | B10: AN | C10: 1.6178952 | D10: 8.1085769 | E10: 88830 | F10: 0.36279401 | G10: 0.032430506 | H10: 0.087312901 | I10: =_xlfn.CONCAT(rec[[#This Row],[lob]], " ",rec[[#This Row],[time]]) -> AN 2025 Q1
A11: 2025 Q2 | B11: AN | C11: 1.5778556 | D11: 7.8671303 | E11: 86477 | F11: 0.33784773 | G11: 0.037701318 | H11: 0.12262079 | I11: =_xlfn.CONCAT(rec[[#This Row],[lob]], " ",rec[[#This Row],[time]]) -> AN 2025 Q2
A12: 2025 Q3 | B12: AN | C12: 1.5875164 | D12: 7.6328671 | E12: 83214 | F12: 0.36625874 | G12: 0.038461538 | H12: 0.12805944 | I12: =_xlfn.CONCAT(rec[[#This Row],[lob]], " ",rec[[#This Row],[time]]) -> AN 2025 Q3
A13: 2025 Q4 | B13: AN | C13: 1.560188 | D13: 7.1423651 | E13: 78693 | F13: 0.37887486 | G13: 0.038461538 | H13: 0.11366246 | I13: =_xlfn.CONCAT(rec[[#This Row],[lob]], " ",rec[[#This Row],[time]]) -> AN 2025 Q4
... A79: 2026 Q1 | B79: STG | C79: 1.502466 | D79: 6.1592462 | E79: 69524 | F79: 0.41127482 | G79: 0.055092889 | H79: 0.13645099 | I79: =_xlfn.CONCAT(rec[[#This Row],[lob]], " ",rec[[#This Row],[time]]) -> STG 2026 Q1

Sheet multipliers
A1: Column1 | B1: FRN | 2023 Q3 | C1: AN | 2023 Q3 | D1: STG | 2023 Q3 | E1: FLD | 2023 Q3 | F1: ENT | 2023 Q3 | G1: FRN | 2023 Q4 | H1: AN | 2023 Q4 | I1: STG | 2023 Q4 | J1: FLD | 2023 Q4 | K1: ENT | 2023 Q4 | L1: FRN | 2024 Q1 | M1: AN | 2024 Q1 | N1: STG | 2024 Q1 | O1: FLD | 2024 Q1 | P1: ENT | 2024 Q1 | Q1: FRN | 2024 Q2 | R1: AN | 2024 Q2 | S1: STG | 2024 Q2 | T1: FLD | 2024 Q2 | U1: ENT | 2024 Q2 | V1: FRN | 2024 Q3 | W1: AN | 2024 Q3 | X1: STG | 2024 Q3 | Y1: FLD | 2024 Q3 | Z1: ENT | 2024 Q3 | AA1: FRN | 2024 Q4 | AB1: AN | 2024 Q4 | AC1: STG | 2024 Q4 | AD1: FLD | 2024 Q4 | AE1: ENT | 2024 Q4 | AF1: FRN | 2025 Q1 | AG1: AN | 2025 Q1 | AH1: STG | 2025 Q1 | AI1: FLD | 2025 Q1 | AJ1: ENT | 2025 Q1 | AK1: FRN | 2025 Q2 | AL1: AN | 2025 Q2 | AM1: STG | 2025 Q2 | AN1: FLD | 2025 Q2 | AO1: ENT | 2025 Q2 | AP1: FRN | 2025 Q3 | AQ1: AN | 2025 Q3 | AR1: STG | 2025 Q3 | AS1: FLD | 2025 Q3 | AT1: ENT | 2025 Q3 | AU1: FRN | 2025 Q4 | AV1: AN | 2025 Q4 | AW1: STG | 2025 Q4 | AX1: FLD | 2025 Q4 | AY1: ENT | 2025 Q4 | AZ1: FRN | 2026 Q1 | BA1: AN | 2026 Q1 | BB1: STG | 2026 Q1 | BC1: FLD | 2026 Q1 | BD1: ENT | 2026 Q1
A2: 00_initial | B2: 1 | C2: 1 | D2: 1 | E2: 1 | F2: 1 | G2: 1 | H2: 1 | I2: 1 | J2: 1 | K2: 1 | L2: 1 | M2: 1 | N2: 1 | O2: 1 | P2: 1 | Q2: 1 | R2: 1 | S2: 1 | T2: 1 | U2: 1 | V2: 1 | W2: 1 | X2: 1 | Y2: 1 | Z2: 1 | AA2: 1 | AB2: 1 | AC2: 1 | AD2: 1 | AE2: 1 | AF2: 1 | AG2: 1 | AH2: 1 | AI2: 1 | AJ2: 1 | AK2: 1 | AL2: 1 | AM2: 1 | AN2: 1 | AO2: 1 | AP2: 1 | AQ2: 1 | AR2: 1 | AS2: 1 | AT2: 1 | AU2: 1 | AV2: 1 | AW2: 1 | AX2: 1 | AY2: 1 | AZ2: 1 | BA2: 1 | BB2: 1 | BC2: 1 | BD2: 1 | BF2: =AVERAGE(B2:BD2) -> 1
A3: 01_prev_aca_chargeoff | B3: 1.0001704 | C3: 1.0002327 | D3: 1.0001429 | E3: 1.0001517 | F3: 1.0001511 | G3: 1.0002363 | H3: 1.0001901 | I3: 1.000236 | J3: 1.0001481 | K3: 1.0000569 | L3: 1.0002033 | M3: 1.0003148 | N3: 1.0000852 | O3: 1.000224 | P3: 1.000196 | Q3: 1.0001803 | R3: 1.0003049 | S3: 1.0002341 | T3: 1.0001213 | U3: 1.0001479 | V3: 1.0002942 | W3: 1.0003679 | X3: 1.0001596 | Y3: 1.0006616 | Z3: 1.000137 | AA3: 1.0003471 | AB3: 1.0002488 | AC3: 1.0001917 | AD3: 1.0004086 | AE3: 1.0001514 | AF3: 1.0003382 | AG3: 1.0003202 | AH3: 1.0003428 | AI3: 1.0005481 | AJ3: 1.0001764 | AK3: 1.0005695 | AL3: 1.0004743 | AM3: 1.0003686 | AN3: 1.0004226 | AO3: 1.0001405 | AP3: 1.0002975 | AQ3: 1.0003932 | AR3: 1.0002407 | AS3: 1.0001596 | AT3: 1.0002214 | AU3: 1.0002706 | AV3: 1.0002867 | AW3: 1.0002782 | AX3: 1.0002115 | AY3: 1.0003447 | AZ3: 1.0003968 | BA3: 1.0002275 | BB3: 1.0001908 | BC3: 1.0004086 | BD3: 1.0002363 | BF3: =AVERAGE(B3:BD3) -> 1.0002647 | BG3: =BF3/BF2 -> 1.0002647 | BH3: =1-BG3 -> -0.00026474926 | BI3: =A3 -> 01_prev_aca_chargeoff
A4: 02_small_amt_financed | B4: 1.0021721 | C4: 1.0006982 | D4: 1.0007857 | E4: 1.0003035 | F4: 1.0001511 | G4: 1.0012864 | H4: 1.0003802 | I4: 1.0010382 | J4: 1.0005926 | K4: 1.0000569 | L4: 1.0010456 | M4: 1.0005903 | N4: 1.0007948 | O4: 1.0007468 | P4: 1.000196 | Q4: 1.0009985 | R4: 1.0005662 | S4: 1.0006556 | T4: 1.0004851 | U4: 1.0001479 | V4: 1.0011217 | W4: 1.0008584 | X4: 1.000894 | Y4: 1.0008507 | Z4: 1.000137 | AA4: 1.0003471 | AB4: 1.0002488 | AC4: 1.0001917 | AD4: 1.0004086 | AE4: 1.0001514 | AF4: 1.0003382 | AG4: 1.0003202 | AH4: 1.0003428 | AI4: 1.0005481 | AJ4: 1.0001764 | AK4: 1.0005695 | AL4: 1.0004743 | AM4: 1.0003686 | AN4: 1.0004226 | AO4: 1.0001405 | AP4: 1.0002975 | AQ4: 1.0003932 | AR4: 1.0002407 | AS4: 1.0001596 | AT4: 1.0002214 | AU4: 1.0002706 | AV4: 1.0002867 | AW4: 1.0002782 | AX4: 1.0002115 | AY4: 1.0003447 | AZ4: 1.0003968 | BA4: 1.0002275 | BB4: 1.0001908 | BC4: 1.0004086 | BD4: 1.0002363 | BF4: =AVERAGE(B4:BD4) -> 1.0004867 | BG4: =BF4/BF3 -> 1.0002219 | BH4: =1-BG4 -> -0.00022185295 | BI4: =A4 -> 02_small_amt_financed
A5: 03_zero_cash_down | B5: 1.0029472 | C5: 1.0022498 | D5: 1.00315 | E5: 1.0022762 | F5: 1.0068299 | G5: 1.0022316 | H5: 1.0035488 | I5: 1.0036904 | J5: 1.0040148 | K5: 1.007023 | L5: 1.0014261 | M5: 1.0032664 | N5: 1.0028129 | O5: 1.0028379 | P5: 1.00433 | Q5: 1.0016516 | R5: 1.0024826 | S5: 1.0029806 | T5: 1.0046089 | U5: 1.0036763 | V5: 1.001861 | W5: 1.0030043 | X5: 1.0031003 | Y5: 1.0035066 | Z5: 1.006137 | AA5: 1.0003471 | AB5: 1.0002488 | AC5: 1.0001917 | AD5: 1.0004086 | AE5: 1.0001514 | AF5: 1.0003382 | AG5: 1.0003202 | AH5: 1.0003428 | AI5: 1.0005481 | AJ5: 1.0001764 | AK5: 1.0005695 | AL5: 1.0004743 | AM5: 1.0003686 | AN5: 1.0004226 | AO5: 1.0001405 | AP5: 1.0002975 | AQ5: 1.0003932 | AR5: 1.0002407 | AS5: 1.0001596 | AT5: 1.0002214 | AU5: 1.0002706 | AV5: 1.0002867 | AW5: 1.0002782 | AX5: 1.0002115 | AY5: 1.0003447 | AZ5: 1.0003968 | BA5: 1.0002275 | BB5: 1.0001908 | BC5: 1.0004086 | BD5: 1.0002363 | BF5: =AVERAGE(B5:BD5) -> 1.0017247 | BG5: =BF5/BF4 -> 1.0012374 | BH5: =1-BG5 -> -0.0012374092 | BI5: =A5 -> 03_zero_cash_down
A6: 04_high_mileage | B6: 1.0047019 | C6: 1.006827 | D6: 1.0064007 | E6: 1.0027314 | F6: 1.0068299 | G6: 1.0034392 | H6: 1.0079278 | I6: 1.0066163 | J6: 1.0043259 | K6: 1.007023 | L6: 1.0030685 | M6: 1.0066627 | N6: 1.0056035 | O6: 1.0032114 | P6: 1.00433 | Q6: 1.0024574 | R6: 1.0043206 | S6: 1.0046387 | T6: 1.0049727 | U6: 1.0036763 | V6: 1.002214 | W6: 1.0046045 | X6: 1.0042944 | Y6: 1.0036957 | Z6: 1.006137 | AA6: 1.0010934 | AB6: 1.0031095 | AC6: 1.0022684 | AD6: 1.000715 | AE6: 1.0001514 | AF6: 1.0007348 | AG6: 1.0017076 | AH6: 1.001835 | AI6: 1.0012955 | AJ6: 1.0001764 | AK6: 1.0008099 | AL6: 1.0011675 | AM6: 1.0009216 | AN6: 1.0005811 | AO6: 1.0001405 | AP6: 1.0005637 | AQ6: 1.0011796 | AR6: 1.0009093 | AS6: 1.0002128 | AT6: 1.0002214 | AU6: 1.0005827 | AV6: 1.0009748 | AW6: 1.000765 | AX6: 1.0002115 | AY6: 1.0003447 | AZ6: 1.000873 | BA6: 1.0006826 | BB6: 1.0005725 | BC6: 1.0005107 | BD6: 1.0002363 | BF6: =AVERAGE(B6:BD6) -> 1.0026592 | BG6: =BF6/BF5 -> 1.000933 | BH6: =1-BG6 -> -0.00093296471 | BI6: =A6 -> 04_high_mileage
A7: 05_high_pti | B7: 1.005 | C7: 1.0074554 | D7: 1.0066864 | E7: 1.0047041 | F7: 1.0088909 | G7: 1.0036755 | H7: 1.0081179 | I7: 1.0067579 | J7: 1.0050667 | K7: 1.0085641 | L7: 1.0032283 | M7: 1.0070996 | N7: 1.0057454 | O7: 1.0036594 | P7: 1.0052584 | Q7: 1.0026238 | R7: 1.0045819 | S7: 1.0050602 | T7: 1.0055185 | U7: 1.004944 | V7: 1.0024531 | W7: 1.0052299 | X7: 1.0048052 | Y7: 1.0042628 | Z7: 1.0073726 | AA7: 1.0010934 | AB7: 1.0031095 | AC7: 1.0022684 | AD7: 1.000715 | AE7: 1.0001514 | AF7: 1.0007348 | AG7: 1.0017076 | AH7: 1.001835 | AI7: 1.0012955 | AJ7: 1.0001764 | AK7: 1.0008099 | AL7: 1.0011675 | AM7: 1.0009216 | AN7: 1.0005811 | AO7: 1.0001405 | AP7: 1.0005637 | AQ7: 1.0011796 | AR7: 1.0009093 | AS7: 1.0002128 | AT7: 1.0002214 | AU7: 1.0005827 | AV7: 1.0009748 | AW7: 1.000765 | AX7: 1.0002115 | AY7: 1.0003447 | AZ7: 1.000873 | BA7: 1.0006826 | BB7: 1.0005725 | BC7: 1.0005107 | BD7: 1.0002363 | BF7: =AVERAGE(B7:BD7) -> 1.0029511 | BG7: =BF7/BF6 -> 1.0002911 | BH7: =1-BG7 -> -0.00029106996 | BI7: =A7 -> 05_high_pti
A8: 06_car_make | B8: 0.99313842 | C8: 0.99276183 | D8: 0.99315143 | E8: 0.98889226 | F8: 1.0055817 | G8: 0.99313993 | H8: 0.99085551 | I8: 0.99152855 | J8: 0.9914963 | K8: 1.0017032 | L8: 0.99376706 | M8: 0.99028335 | N8: 0.98902756 | O8: 0.99066468 | P8: 0.99998218 | Q8: 0.99012883 | R8: 0.9848824 | S8: 0.98679747 | T8: 0.99226804 | U8: 0.99738855 | V8: 0.98722692 | W8: 0.98341447 | X8: 0.9832152 | Y8: 0.98811909 | Z8: 0.99749041 | AA8: 0.95653593 | AB8: 0.95429726 | AC8: 0.95338019 | AD8: 0.95903984 | AE8: 0.9712664 | AF8: 0.95198974 | AG8: 0.95488794 | AH8: 0.95291389 | AI8: 0.96003986 | AJ8: 0.96465814 | AK8: 0.94916983 | AL8: 0.94931047 | AM8: 0.94437846 | AN8: 0.95186476 | AO8: 0.94753206 | AP8: 0.94559349 | AQ8: 0.94131935 | AR8: 0.94292859 | AS8: 0.95110638 | AT8: 0.94359973 | AU8: 0.93593757 | AV8: 0.93788417 | AW8: 0.93069889 | AX8: 0.94986779 | AY8: 0.93300981 | AZ8: 0.93813492 | BA8: 0.93492605 | BB8: 0.92536896 | BC8: 0.95597549 | BD8: 0.93313644 | BF8: =AVERAGE(B8:BD8) -> 0.96759378 | BG8: =BF8/BF7 -> 0.96474672 | BH8: =1-BG8 -> 0.035253277 | BI8: =A8 -> 06_car_make
A9: 07_theft_risk | B9: 0.98567515 | C9: 0.98457168 | D9: 0.98585517 | E9: 0.98309736 | F9: 1.0105353 | G9: 0.98598354 | H9: 0.9830185 | I9: 0.98345553 | J9: 0.98522151 | K9: 0.99970416 | L9: 0.98820336 | M9: 0.98315253 | N9: 0.98249294 | O9: 0.98639216 | P9: 0.99572694 | Q9: 0.98351485 | R9: 0.97718416 | S9: 0.9789504 | T9: 0.98816389 | U9: 0.99142968 | V9: 0.98038067 | W9: 0.97453909 | X9: 0.97363541 | Y9: 0.98117799 | Z9: 0.98851016 | AA9: 0.95653593 | AB9: 0.95429726 | AC9: 0.95338019 | AD9: 0.95903984 | AE9: 0.9712664 | AF9: 0.95198974 | AG9: 0.95488794 | AH9: 0.95291389 | AI9: 0.96003986 | AJ9: 0.96465814 | AK9: 0.94916983 | AL9: 0.94931047 | AM9: 0.94437846 | AN9: 0.95186476 | AO9: 0.94753206 | AP9: 0.94559349 | AQ9: 0.94131935 | AR9: 0.94292859 | AS9: 0.95110638 | AT9: 0.94359973 | AU9: 0.93593757 | AV9: 0.93788417 | AW9: 0.93069889 | AX9: 0.94986779 | AY9: 0.93300981 | AZ9: 0.93813492 | BA9: 0.93492605 | BB9: 0.92536896 | BC9: 0.95597549 | BD9: 0.93313644 | BF9: =AVERAGE(B9:BD9) -> 0.96475136 | BG9: =BF9/BF8 -> 0.99706238 | BH9: =1-BG9 -> 0.0029376194 | BI9: =A9 -> 07_theft_risk
A10: 08_mcy_low_mileage | B10: 0.98567515 | C10: 0.98457168 | D10: 0.98585517 | E10: 0.98309736 | F10: 1.0105353 | G10: 0.98598354 | H10: 0.9830185 | I10: 0.98345553 | J10: 0.98522151 | K10: 0.99970416 | L10: 0.98820336 | M10: 0.98315253 | N10: 0.98249294 | O10: 0.98639216 | P10: 0.99572694 | Q10: 0.98351485 | R10: 0.97718416 | S10: 0.9789504 | T10: 0.98816389 | U10: 0.99142968 | V10: 0.98038067 | W10: 0.97453909 | X10: 0.97363541 | Y10: 0.98117799 | Z10: 0.98851016 | AA10: 0.95653593 | AB10: 0.95429726 | AC10: 0.95338019 | AD10: 0.95903984 | AE10: 0.9712664 | AF10: 0.95198974 | AG10: 0.95488794 | AH10: 0.95291389 | AI10: 0.96003986 | AJ10: 0.96465814 | AK10: 0.94916983 | AL10: 0.94931047 | AM10: 0.94437846 | AN10: 0.95186476 | AO10: 0.94753206 | AP10: 0.94559349 | AQ10: 0.94131935 | AR10: 0.94292859 | AS10: 0.95110638 | AT10: 0.94359973 | AU10: 0.93593757 | AV10: 0.93788417 | AW10: 0.93069889 | AX10: 0.94986779 | AY10: 0.93300981 | AZ10: 0.93813492 | BA10: 0.93492605 | BB10: 0.92536896 | BC10: 0.95597549 | BD10: 0.93313644 | BF10: =AVERAGE(B10:BD10) -> 0.96475136 | BG10: =BF10/BF9 -> 1 | BH10: =1-BG10 -> 0 | BI10: =A10 -> 08_mcy_low_mileage
A11: 09_weekend_weekday | B11: 0.98992933 | C11: 0.98466665 | D11: 0.98884726 | E11: 0.98143538 | F11: 1.018942 | G11: 0.99078408 | H11: 0.98369107 | I11: 0.98523277 | J11: 0.98307151 | K11: 1.0046721 | L11: 0.99221672 | M11: 0.98378183 | N11: 0.98432433 | O11: 0.98769017 | P11: 1.0005353 | Q11: 0.9872308 | R11: 0.97725956 | S11: 0.98063285 | T11: 0.98930005 | U11: 0.99800377 | V11: 0.98304946 | W11: 0.97511321 | X11: 0.97529167 | Y11: 0.98519394 | Z11: 0.99366322 | AA11: 0.95864068 | AB11: 0.95385025 | AC11: 0.95451169 | AD11: 0.95922268 | AE11: 0.97616726 | AF11: 0.9521906 | AG11: 0.95201999 | AH11: 0.95247959 | AI11: 0.95886497 | AJ11: 0.9674607 | AK11: 0.95023511 | AL11: 0.9475421 | AM11: 0.94430295 | AN11: 0.95162525 | AO11: 0.95143633 | AP11: 0.94641256 | AQ11: 0.94097754 | AR11: 0.94326384 | AS11: 0.95100511 | AT11: 0.94806106 | AU11: 0.93569877 | AV11: 0.93547769 | AW11: 0.92964642 | AX11: 0.94915336 | AY11: 0.93691822 | AZ11: 0.93755595 | BA11: 0.93120705 | BB11: 0.92438142 | BC11: 0.95474566 | BD11: 0.93562434 | BF11: =AVERAGE(B11:BD11) -> 0.96609524 | BG11: =BF11/BF10 -> 1.001393 | BH11: =1-BG11 -> -0.0013929851 | BI11: =A11 -> 09_weekend_weekday
A12: 10_student_loans | B12: 0.96515484 | C12: 0.96651065 | D12: 0.96740342 | E12: 0.95970558 | F12: 0.99825249 | G12: 0.96841232 | H12: 0.9646786 | I12: 0.96481362 | J12: 0.95978425 | K12: 0.98194633 | L12: 0.99221985 | M12: 0.98767741 | N12: 0.98330863 | O12: 0.98841711 | P12: 1.0054552 | Q12: 0.98057671 | R12: 0.97759936 | S12: 0.97688803 | T12: 0.98981395 | U12: 1.0023078 | V12: 0.97548077 | W12: 0.97243135 | X12: 0.97074417 | Y12: 0.986064 | Z12: 0.99900875 | AA12: 0.95485281 | AB12: 0.95528701 | AC12: 0.95613224 | AD12: 0.96369359 | AE12: 0.9861476 | AF12: 0.94972862 | AG12: 0.95530995 | AH12: 0.95520387 | AI12: 0.96787514 | AJ12: 0.97914136 | AK12: 0.94096935 | AL12: 0.94282845 | AM12: 0.93958532 | AN12: 0.95491524 | AO12: 0.95486369 | AP12: 0.93793326 | AQ12: 0.93728422 | AR12: 0.93901751 | AS12: 0.95132207 | AT12: 0.95018726 | AU12: 0.92267481 | AV12: 0.92680135 | AW12: 0.92111983 | AX12: 0.9490828 | AY12: 0.9331586 | AZ12: 0.92345245 | BA12: 0.92210023 | BB12: 0.91415723 | BC12: 0.95087967 | BD12: 0.92940771 | BF12: =AVERAGE(B12:BD12) -> 0.96090488 | BG12: =BF12/BF11 -> 0.99462749 | BH12: =1-BG12 -> 0.0053725123 | BI12: =A12 -> 10_student_loans
A13: 11_low_pti | B13: 0.95788014 | C13: 0.95971233 | D13: 0.96168474 | E13: 0.95596694 | F13: 0.99825249 | G13: 0.96217672 | H13: 0.95965809 | I13: 0.96061196 | J13: 0.95723029 | K13: 0.98194633 | L13: 0.98612845 | M13: 0.98070256 | N13: 0.97837789 | O13: 0.98232101 | P13: 1.0054552 | Q13: 0.97329214 | R13: 0.96932879 | S13: 0.97102494 | T13: 0.9817851 | U13: 1.0023078 | V13: 0.96766323 | W13: 0.96506597 | X13: 0.96478 | Y13: 0.97818641 | Z13: 0.99900875 | AA13: 0.94750583 | AB13: 0.94749252 | AC13: 0.95048088 | AD13: 0.95657966 | AE13: 0.9861476 | AF13: 0.94187347 | AG13: 0.94780773 | AH13: 0.9488806 | AI13: 0.96172353 | AJ13: 0.97914136 | AK13: 0.93451711 | AL13: 0.93453802 | AM13: 0.9343588 | AN13: 0.94714501 | AO13: 0.95486369 | AP13: 0.93198996 | AQ13: 0.93041535 | AR13: 0.93331355 | AS13: 0.94428412 | AT13: 0.95018726 | AU13: 0.91739379 | AV13: 0.92078035 | AW13: 0.91531062 | AX13: 0.94256779 | AY13: 0.9331586 | AZ13: 0.91745585 | BA13: 0.91637854 | BB13: 0.90823255 | BC13: 0.94571839 | BD13: 0.92940771 | BF13: =AVERAGE(B13:BD13) -> 0.95582179 | BG13: =BF13/BF12 -> 0.9947101 | BH13: =1-BG13 -> 0.0052898979 | BI13: =A13 -> 11_low_pti
A14: 12_chime | B14: 0.95078565 | C14: 0.94437273 | D14: 0.94787306 | E14: 0.94333686 | F14: 0.9902009 | G14: 0.9596938 | H14: 0.94765637 | I14: 0.9468773 | J14: 0.94005289 | K14: 0.9772351 | L14: 0.99922051 | M14: 0.9769273 | N14: 0.98101573 | O14: 0.97921582 | P14: 1.0160442 | Q14: 0.97500425 | R14: 0.9625974 | S14: 0.96559661 | T14: 0.97393064 | U14: 1.0055181 | V14: 0.96404965 | W14: 0.95813974 | X14: 0.95850913 | Y14: 0.96968519 | Z14: 1.0018748 | AA14: 0.94861712 | AB14: 0.94993655 | AC14: 0.95040262 | AD14: 0.96172112 | AE14: 0.99913435 | AF14: 0.96495739 | AG14: 0.96092332 | AH14: 0.96478322 | AI14: 0.99006136 | AJ14: 1.0150713 | AK14: 0.94000841 | AL14: 0.93257321 | AM14: 0.93424762 | AN14: 0.95654853 | AO14: 0.9708509 | AP14: 0.94056378 | AQ14: 0.93201297 | AR14: 0.93651552 | AS14: 0.9593659 | AT14: 0.96561499 | AU14: 0.91878434 | AV14: 0.92013637 | AW14: 0.91390528 | AX14: 0.95590668 | AY14: 0.9419836 | AZ14: 0.90844352 | BA14: 0.90846273 | BB14: 0.89882258 | BC14: 0.94193598 | BD14: 0.92667073 | BF14: =AVERAGE(B14:BD14) -> 0.95717047 | BG14: =BF14/BF13 -> 1.001411 | BH14: =1-BG14 -> -0.0014110113 | BI14: =A14 -> 12_chime
... A20: 18_final | B20: 0.95222965 | C20: 0.96852051 | D20: 0.94113459 | E20: 0.92907713 | F20: 1.0310877 | G20: 0.97454999 | H20: 0.96720009 | I20: 0.95161413 | J20: 0.92232325 | K20: 0.98492164 | L20: 1.0154434 | M20: 0.97336274 | N20: 0.96513308 | O20: 0.93470429 | P20: 1.0275065 | Q20: 0.99165615 | R20: 0.95183082 | S20: 0.92620137 | T20: 0.89627674 | U20: 1.0165922 | V20: 0.97494226 | W20: 0.96308429 | X20: 0.92278715 | Y20: 0.8681367 | Z20: 1.0211013 | AA20: 0.977357 | AB20: 0.95871445 | AC20: 0.92334897 | AD20: 0.8819025 | AE20: 1.0118259 | AF20: 0.97580053 | AG20: 0.94063439 | AH20: 0.93202412 | AI20: 0.90433308 | AJ20: 1.0424267 | AK20: 0.95138359 | AL20: 0.90101376 | AM20: 0.91926639 | AN20: 0.90035264 | AO20: 0.99308547 | AP20: 0.92805939 | AQ20: 0.88449758 | AR20: 0.90893255 | AS20: 0.88144536 | AT20: 0.99547122 | AU20: 0.89049588 | AV20: 0.8732917 | AW20: 0.88814741 | AX20: 0.93068818 | AY20: 0.94561229 | AZ20: 0.90785896 | BA20: 0.91874607 | BB20: 0.91408871 | BC20: 0.95345657 | BD20: 0.93580669 | BF20: =AVERAGE(B20:BD20) -> 0.94620883 | BG20: =BF20/BF19 -> 0.9978969 | BH20: =1-BG20 -> 0.002103095 | BI20: =A20 -> 18_final
A21: --- FINAL_MULT (mean) | B21: 0.95222965 | C21: 0.96852051 | D21: 0.94113459 | E21: 0.92907713 | F21: 1.0310877 | G21: 0.97454999 | H21: 0.96720009 | I21: 0.95161413 | J21: 0.92232325 | K21: 0.98492164 | L21: 1.0154434 | M21: 0.97336274 | N21: 0.96513308 | O21: 0.93470429 | P21: 1.0275065 | Q21: 0.99165615 | R21: 0.95183082 | S21: 0.92620137 | T21: 0.89627674 | U21: 1.0165922 | V21: 0.97494226 | W21: 0.96308429 | X21: 0.92278715 | Y21: 0.8681367 | Z21: 1.0211013 | AA21: 0.977357 | AB21: 0.95871445 | AC21: 0.92334897 | AD21: 0.8819025 | AE21: 1.0118259 | AF21: 0.97580053 | AG21: 0.94063439 | AH21: 0.93202412 | AI21: 0.90433308 | AJ21: 1.0424267 | AK21: 0.95138359 | AL21: 0.90101376 | AM21: 0.91926639 | AN21: 0.90035264 | AO21: 0.99308547 | AP21: 0.92805939 | AQ21: 0.88449758 | AR21: 0.90893255 | AS21: 0.88144536 | AT21: 0.99547122 | AU21: 0.89049588 | AV21: 0.8732917 | AW21: 0.88814741 | AX21: 0.93068818 | AY21: 0.94561229 | AZ21: 0.90785896 | BA21: 0.91874607 | BB21: 0.91408871 | BC21: 0.95345657 | BD21: 0.93580669
A22: --- WTD_MULT_RAGU | B22: 0.93501647 | C22: 0.97221155 | D22: 0.94163316 | E22: 0.9587511 | F22: 1.0288243 | G22: 0.96435785 | H22: 0.96679866 | I22: 0.94899479 | J22: 0.93944119 | K22: 0.98178296 | L22: 1.0077013 | M22: 0.97369986 | N22: 0.95908584 | O22: 0.9379511 | P22: 1.023392 | Q22: 0.9876603 | R22: 0.95274855 | S22: 0.91905434 | T22: 0.90245595 | U22: 1.0131926 | V22: 0.96969302 | W22: 0.96111098 | X22: 0.90914591 | Y22: 0.86869643 | Z22: 1.0191615 | AA22: 0.97886215 | AB22: 0.95278864 | AC22: 0.91736569 | AD22: 0.88135188 | AE22: 1.011313 | AF22: 0.97324878 | AG22: 0.94166839 | AH22: 0.92641114 | AI22: 0.90369402 | AJ22: 1.0390083 | AK22: 0.94907815 | AL22: 0.90110794 | AM22: 0.91881725 | AN22: 0.90036955 | AO22: 0.99170923 | AP22: 0.92813378 | AQ22: 0.88275727 | AR22: 0.91015415 | AS22: 0.87961684 | AT22: 0.99289652 | AU22: 0.88857344 | AV22: 0.86681613 | AW22: 0.88228998 | AX22: 0.93518247 | AY22: 0.94297899 | AZ22: 0.90223853 | BA22: 0.91587504 | BB22: 0.90655016 | BC22: 0.9527119 | BD22: 0.93384736
A23: --- GROSS_LOSS_IMPACT | B23: 1.6245882 | C23: 0.6947113 | D23: 1.4591709 | E23: 1.0312225 | F23: -0.72060842 | G23: 0.89105376 | H23: 0.83003342 | I23: 1.2751302 | J23: 1.5139703 | K23: 0.4554259 | L23: -0.19253143 | M23: 0.65750359 | N23: 1.0228541 | O23: 1.5512225 | P23: -0.58479913 | Q23: 0.30849242 | R23: 1.1812862 | S23: 2.0236416 | T23: 2.4386011 | U23: -0.32981376 | V23: 0.75767443 | W23: 0.97222553 | X23: 2.2713522 | Y23: 3.2825892 | Z23: -0.47903773 | AA23: 0.52844615 | AB23: 1.180284 | AC23: 2.0658579 | AD23: 2.9662031 | AE23: -0.28282436 | AF23: 0.66878042 | AG23: 1.4582901 | AH23: 1.8397214 | AI23: 2.4076495 | AJ23: -0.97520672 | AK23: 1.2730461 | AL23: 2.4723015 | AM23: 2.0295688 | AN23: 2.4907613 | AO23: 0.20726925 | AP23: 1.7966555 | AQ23: 2.9310683 | AR23: 2.2461463 | AS23: 3.0095789 | AT23: 0.17758706 | AU23: 2.7856639 | AV23: 3.3295966 | AW23: 2.9427504 | AX23: 1.6204382 | AY23: 1.4255253 | AZ23: 2.4440368 | BA23: 2.1031239 | BB23: 2.3362459 | BC23: 1.1822025 | BD23: 1.653816
A24: --- N_RECORDS | B24: 2348 | C24: 1289 | D24: 1400 | E24: 659 | F24: 3309 | G24: 3809 | H24: 1578 | I24: 2119 | J24: 675 | K24: 3517 | L24: 6886 | M24: 2541 | N24: 3523 | O24: 1339 | P24: 5612 | Q24: 7211 | R24: 2296 | S24: 4271 | T24: 1649 | U24: 4733 | V24: 5438 | W24: 1631 | X24: 3132 | Y24: 1058 | Z24: 3650 | AA24: 5762 | AB24: 1608 | AC24: 3130 | AD24: 979 | AE24: 3964 | AF24: 8574 | AG24: 2811 | AH24: 4959 | AI24: 2007 | AJ24: 6801 | AK24: 7902 | AL24: 2741 | AM24: 4883 | AN24: 1893 | AO24: 5693 | AP24: 6386 | AQ24: 2289 | AR24: 3739 | AS24: 1880 | AT24: 4517 | AU24: 4805 | AV24: 1744 | AW24: 2876 | AX24: 1891 | AY24: 3771 | AZ24: 2520 | BA24: 879 | BB24: 1572 | BC24: 979 | BD24: 1693

Sheet KMX Multipliers
B1: KMX | 2023 Q3 | C1: KMX | 2023 Q4 | D1: KMX | 2024 Q1 | E1: KMX | 2024 Q2 | F1: KMX | 2024 Q3 | G1: KMX | 2024 Q4 | H1: KMX | 2025 Q1 | I1: KMX | 2025 Q2 | J1: KMX | 2025 Q3 | K1: KMX | 2025 Q4 | L1: KMX | 2026 Q1
A2: 00_initial | B2: 1 | C2: 1 | D2: 1 | E2: 1 | F2: 1 | G2: 1 | H2: 1 | I2: 1 | J2: 1 | K2: 1 | L2: 1
A3: 02_low_fico_3.0 | B3: 1.0124672 | C3: 1.0103868 | D3: 1.0084699 | E3: 1.006254 | F3: 1.005926 | G3: 1.0040448 | H3: 1.0001231 | I3: 1 | J3: 1 | K3: 1 | L3: 1
A4: 03_low_vantage_3.0 | B4: 1.0124672 | C4: 1.0103868 | D4: 1.0084699 | E4: 1.006254 | F4: 1.005926 | G4: 1.0040503 | H4: 1.0008906 | I4: 1.0009864 | J4: 1.0008417 | K4: 1.0006312 | L4: 1
A5: 04_high_pti_3.0 | B5: 1.0254775 | C5: 1.0249392 | D5: 1.0189146 | E5: 1.0183695 | F5: 1.0179062 | G5: 1.0128685 | H5: 1.0060587 | I5: 1.0053989 | J5: 1.0050461 | K5: 1.0043743 | L5: 1
A6: 07_loss_scale_div_3.0 | B6: 0.96108481 | C6: 0.9605803 | D6: 0.95493404 | E6: 0.95442318 | F6: 0.9539889 | G6: 0.96593771 | H6: 0.97622211 | I6: 0.97507551 | J6: 0.97524952 | K6: 0.98199376 | L6: 1
A7: 08_secured_credit_3.0 | B7: 0.96380975 | C7: 0.9622463 | D7: 0.95953336 | E7: 0.95911013 | F7: 0.95889284 | G7: 0.96985682 | H7: 0.98507398 | I7: 0.98317472 | J7: 0.98649507 | K7: 0.99320663 | L7: 1.0045556
A8: 09_auth_tradelines_3.0 | B8: 0.96301397 | C8: 0.95964583 | D8: 0.95568511 | E8: 0.95634166 | F8: 0.95624287 | G8: 0.96713788 | H8: 0.98313574 | I8: 0.98137732 | J8: 0.98467154 | K8: 0.99234645 | L8: 1.0045556
A9: 11_soft_pull_3.0 | B9: 0.94080108 | C9: 0.93628711 | D9: 0.93166418 | E9: 0.93241737 | F9: 0.93187697 | G9: 0.94919036 | H9: 0.972448 | I9: 0.97074259 | J9: 0.97512198 | K9: 0.98545447 | L9: 1.0045556
A10: 12_fraud_all | B10: 0.94469765 | C10: 0.93898938 | D10: 0.92456783 | E10: 0.92267122 | F10: 0.92770254 | G10: 0.94537075 | H10: 0.96777865 | I10: 0.96470872 | J10: 0.97033434 | K10: 0.98504806 | L10: 1.0015093
A11: 13_clip_3.0 | B11: 0.94275851 | C11: 0.93760829 | D11: 0.92414318 | E11: 0.92161795 | F11: 0.9264673 | G11: 0.94378937 | H11: 0.96702611 | I11: 0.96417145 | J11: 0.96957704 | K11: 0.98432426 | L11: 1.0015093
A12: 14_vehicle_age_3.0 | B12: 0.9337169 | C12: 0.92217226 | D12: 0.90843352 | E12: 0.88976272 | F12: 0.89797249 | G12: 0.9207353 | H12: 0.95121574 | I12: 0.94997301 | J12: 0.95752912 | K12: 0.97524713 | L12: 1.0015093
A13: 15_npc_all | B13: 0.93888291 | C13: 0.92584139 | D13: 0.91120661 | E13: 0.8932152 | F13: 0.90078925 | G13: 0.92402708 | H13: 0.95537873 | I13: 0.95283015 | J13: 0.95991669 | K13: 0.97741594 | L13: 1.0020803
... A31: --- N_RECORDS | B31: 6336 | C31: 5383 | D31: 18142 | E31: 13849 | F31: 13019 | G31: 12178 | H31: 18819 | I31: 15520 | J31: 15234 | K31: 13629 | L31: 8743

Sheet populations
A1: Column1 | B1: FRN | 2023 Q3 | C1: AN | 2023 Q3 | D1: STG | 2023 Q3 | E1: FLD | 2023 Q3 | F1: ENT | 2023 Q3 | G1: FRN | 2023 Q4 | H1: AN | 2023 Q4 | I1: STG | 2023 Q4 | J1: FLD | 2023 Q4 | K1: ENT | 2023 Q4 | L1: FRN | 2024 Q1 | M1: AN | 2024 Q1 | N1: STG | 2024 Q1 | O1: FLD | 2024 Q1 | P1: ENT | 2024 Q1 | Q1: FRN | 2024 Q2 | R1: AN | 2024 Q2 | S1: STG | 2024 Q2 | T1: FLD | 2024 Q2 | U1: ENT | 2024 Q2 | V1: FRN | 2024 Q3 | W1: AN | 2024 Q3 | X1: STG | 2024 Q3 | Y1: FLD | 2024 Q3 | Z1: ENT | 2024 Q3 | AA1: FRN | 2024 Q4 | AB1: AN | 2024 Q4 | AC1: STG | 2024 Q4 | AD1: FLD | 2024 Q4 | AE1: ENT | 2024 Q4 | AF1: FRN | 2025 Q1 | AG1: AN | 2025 Q1 | AH1: STG | 2025 Q1 | AI1: FLD | 2025 Q1 | AJ1: ENT | 2025 Q1 | AK1: FRN | 2025 Q2 | AL1: AN | 2025 Q2 | AM1: STG | 2025 Q2 | AN1: FLD | 2025 Q2 | AO1: ENT | 2025 Q2 | AP1: FRN | 2025 Q3 | AQ1: AN | 2025 Q3 | AR1: STG | 2025 Q3 | AS1: FLD | 2025 Q3 | AT1: ENT | 2025 Q3 | AU1: FRN | 2025 Q4 | AV1: AN | 2025 Q4 | AW1: STG | 2025 Q4 | AX1: FLD | 2025 Q4 | AY1: ENT | 2025 Q4 | AZ1: FRN | 2026 Q1 | BA1: AN | 2026 Q1 | BB1: STG | 2026 Q1 | BC1: FLD | 2026 Q1 | BD1: ENT | 2026 Q1
A2: prev_co_flag | B2: 0.0017035775 | C2: 0.0023273856 | D2: 0.0014285714 | E2: 0.0015174507 | F2: 0.0015110305 | G2: 0.0023628249 | H2: 0.0019011407 | I2: 0.0023596036 | J2: 0.0014814815 | K2: 0.00056866648 | L2: 0.0020331107 | M2: 0.0031483668 | N2: 0.00085154698 | O2: 0.002240478 | P2: 0.0019600855 | Q2: 0.0018028013 | R2: 0.0030487805 | S2: 0.002341372 | T2: 0.0012128563 | U2: 0.0014789774 | V2: 0.0029422582 | W2: 0.0036787247 | X2: 0.001596424 | Y2: 0.0066162571 | Z2: 0.001369863 | AA2: 0.003471017 | AB2: 0.0024875622 | AC2: 0.0019169329 | AD2: 0.0040858018 | AE2: 0.0015136226 | AF2: 0.0033823186 | AG2: 0.0032017076 | AH2: 0.0034281105 | AI2: 0.0054808171 | AJ2: 0.0017644464 | AK2: 0.0056947608 | AL2: 0.0047427946 | AM2: 0.0036862584 | AN2: 0.0042260961 | AO2: 0.0014052345 | AP2: 0.0029752584 | AQ2: 0.003931848 | AR2: 0.0024070607 | AS2: 0.0015957447 | AT2: 0.0022138588 | AU2: 0.0027055151 | AV2: 0.0028669725 | AW2: 0.0027816412 | AX2: 0.0021152829 | AY2: 0.0034473614 | AZ2: 0.003968254 | BA2: 0.0022753129 | BB2: 0.0019083969 | BC2: 0.0040858018 | BD2: 0.0023626698
A3: small_amt_financed_flag | B3: 0.020017036 | C3: 0.0046547711 | D3: 0.0064285714 | E3: 0.0015174507 | F3: 0 | G3: 0.010501444 | H3: 0.0019011407 | I3: 0.0080226522 | J3: 0.0044444444 | K3: 0 | L3: 0.008422887 | M3: 0.0027548209 | N3: 0.0070962248 | O3: 0.0052277819 | P3: 0 | Q3: 0.0081819443 | R3: 0.0026132404 | S3: 0.0042144697 | T3: 0.0036385688 | U3: 0 | V3: 0.0082751011 | W3: 0.0049049663 | X3: 0.0073435504 | Y3: 0.0018903592 | Z3: 0 | AA3: 0.011107254 | AB3: 0.0018656716 | AC3: 0.0060702875 | AD3: 0.0040858018 | AE3: 0 | AF3: 0.0080475857 | AG3: 0.0028459623 | AH3: 0.0074611817 | AI3: 0.0004982561 | AJ3: 0 | AK3: 0.0082257656 | AL3: 0.0043779642 | AM3: 0.0055293877 | AN3: 0.0015847861 | AO3: 0 | AP3: 0.0075164422 | AQ3: 0.003494976 | AR3: 0.0072211821 | AS3: 0.0021276596 | AT3: 0 | AU3: 0.0085327784 | AV3: 0.0040137615 | AW3: 0.0093880389 | AX3: 0.00052882073 | AY3: 0 | AZ3: 0.0091269841 | BA3: 0.0056882821 | BB3: 0.0082697201 | BC3: 0.0040858018 | BD3: 0
A4: pricing_change_flag | B4: 0 | C4: 0 | D4: 0 | E4: 0 | F4: 0 | G4: 0 | H4: 0 | I4: 0 | J4: 0 | K4: 0 | L4: 0 | M4: 0 | N4: 0 | O4: 0 | P4: 0 | Q4: 0 | R4: 0 | S4: 0 | T4: 0 | U4: 0 | V4: 0 | W4: 0 | X4: 0 | Y4: 0 | Z4: 0 | AA4: 1 | AB4: 1 | AC4: 1 | AD4: 1 | AE4: 1 | AF4: 1 | AG4: 1 | AH4: 1 | AI4: 1 | AJ4: 1 | AK4: 1 | AL4: 1 | AM4: 1 | AN4: 1 | AO4: 1 | AP4: 1 | AQ4: 1 | AR4: 1 | AS4: 1 | AT4: 1 | AU4: 1 | AV4: 1 | AW4: 1 | AX4: 1 | AY4: 1 | AZ4: 1 | BA4: 1 | BB4: 1 | BC4: 1 | BD4: 1
A5: zero_cash_down_flag | B5: 0.0076660988 | C5: 0.015515904 | D5: 0.023571429 | E5: 0.019726859 | F5: 0.066787549 | G5: 0.0094512996 | H5: 0.031685678 | I5: 0.02642756 | J5: 0.034074074 | K5: 0.069661643 | L5: 0.0037757769 | M5: 0.026761118 | N5: 0.020153278 | O5: 0.020911128 | P5: 0.041339986 | Q5: 0.00651782 | R5: 0.019163763 | S5: 0.023179583 | T5: 0.041237113 | U5: 0.035284175 | V5: 0.0073556455 | W5: 0.021459227 | X5: 0.022030651 | Y5: 0.026465028 | Z5: 0.06 | AA5: 0.021173204 | AB5: 0.052238806 | AC5: 0.049201278 | AD5: 0.062308478 | AE5: 0.12512614 | AF5: 0.011663168 | AG5: 0.038776236 | AH5: 0.036902601 | AI5: 0.069755855 | AJ5: 0.10248493 | AK5: 0.013793976 | AL5: 0.045968625 | AM5: 0.04505427 | AN5: 0.0681458 | AO5: 0.1203232 | AP5: 0.024898215 | AQ5: 0.081695063 | AR5: 0.055362396 | AS5: 0.1143617 | AT5: 0.16980297 | AU5: 0.026014568 | AV5: 0.078555046 | AW5: 0.057371349 | AX5: 0.13326282 | AY5: 0.17104216 | AZ5: 0.028968254 | BA5: 0.098976109 | BB5: 0.081424936 | BC5: 0.16343207 | BD5: 0.16774956
A6: high_mileage_vehicle_flag | B6: 0.01746167 | C6: 0.045771916 | D6: 0.032142857 | E6: 0.004552352 | F6: 0 | G6: 0.012076661 | H6: 0.043726236 | I6: 0.029259084 | J6: 0.002962963 | K6: 0 | L6: 0.016410107 | M6: 0.033844943 | N6: 0.027817201 | O6: 0.0037341299 | P6: 0 | Q6: 0.0080432672 | R6: 0.018292683 | S6: 0.016389604 | T6: 0.0036385688 | U6: 0 | V6: 0.0034939316 | W6: 0.01594114 | X6: 0.011813538 | Y6: 0.0018903592 | Z6: 0 | AA6: 0.0074626866 | AB6: 0.028606965 | AC6: 0.020766773 | AD6: 0.0030643514 | AE6: 0 | AF6: 0.003965477 | AG6: 0.013874066 | AH6: 0.014922363 | AI6: 0.0074738416 | AJ6: 0 | AK6: 0.0024044546 | AL6: 0.0069317767 | AM6: 0.0055293877 | AN6: 0.0015847861 | AO6: 0 | AP6: 0.0026620733 | AQ6: 0.0078636959 | AR6: 0.0066862798 | AS6: 0.00053191489 | AT6: 0 | AU6: 0.0031217482 | AV6: 0.0068807339 | AW6: 0.004867872 | AX6: 0 | AY6: 0 | AZ6: 0.0047619048 | BA6: 0.0045506257 | BB6: 0.0038167939 | BC6: 0.0010214505 | BD6: 0
A7: high_pti_flag | B7: 0.0029812606 | C7: 0.0062063615 | D7: 0.0028571429 | E7: 0.019726859 | F7: 0.020550015 | G7: 0.0023628249 | H7: 0.0019011407 | I7: 0.0014157622 | J7: 0.0074074074 | K7: 0.015353995 | L7: 0.0015974441 | M7: 0.0043290043 | N7: 0.001419245 | O7: 0.0044809559 | P7: 0.0092658589 | Q7: 0.0016641243 | R7: 0.0026132404 | S7: 0.0042144697 | T7: 0.0054578532 | U7: 0.012676949 | V7: 0.0023905848 | W7: 0.0061312078 | X7: 0.0051085568 | Y7: 0.0056710775 | Z7: 0.012328767 | AA7: 0.004685873 | AB7: 0.006840796 | AC7: 0.0067092652 | AD7: 0.0051072523 | AE7: 0.018668012 | AF7: 0.0044320037 | AG7: 0.0042689434 | AH7: 0.0058479532 | AI7: 0.0099651221 | AJ7: 0.015880018 | AK7: 0.0058213111 | AL7: 0.0065669464 | AM7: 0.010034815 | AN7: 0.0089804543 | AO7: 0.020551555 | AP7: 0.0079862199 | AQ7: 0.005242464 | AR7: 0.0082909869 | AS7: 0.012234043 | AT7: 0.018153642 | AU7: 0.0072840791 | AV7: 0.0051605505 | AW7: 0.0079972184 | AX7: 0.013220518 | AY7: 0.014319809 | AZ7: 0.0023809524 | BA7: 0.0056882821 | BB7: 0.0038167939 | BC7: 0.0061287028 | BD7: 0.016538689
A8: car_make_penalty_flag | B8: 0.0025553663 | C8: 0.0069821567 | D8: 0.0014285714 | E8: 0.0015174507 | F8: 0.0060441221 | G8: 0.0023628249 | H8: 0.0057034221 | I8: 0.0056630486 | J8: 0.002962963 | K8: 0.001137333 | L8: 0.006099332 | M8: 0.0074773711 | N8: 0.0036900369 | O8: 0.002240478 | P8: 0.0017818959 | Q8: 0.0019414783 | R8: 0.00087108014 | S8: 0.0014048232 | T8: 0 | U8: 0.0014789774 | V8: 0 | W8: 0.0030656039 | X8: 0.0006385696 | Y8: 0.00094517958 | Z8: 0.0002739726 | AA8: 0.00017355085 | AB8: 0.0018656716 | AC8: 0.00063897764 | AD8: 0 | AE8: 0.0012613522 | AF8: 0.00058315839 | AG8: 0.0014229811 | AH8: 0.0016132285 | AI8: 0 | AJ8: 0.0001470372 | AK8: 0.00025310048 | AL8: 0.0018241518 | AM8: 0.0010239607 | AN8: 0 | AO8: 0.00052696294 | AP8: 0 | AQ8: 0 | AR8: 0.0010698048 | AS8: 0.00053191489 | AT8: 0.00022138588 | AU8: 0.00083246618 | AV8: 0.001146789 | AW8: 0.0010431154 | AX8: 0 | AY8: 0.00026518165 | AZ8: 0.0011904762 | BA8: 0 | BB8: 0 | BC8: 0 | BD8: 0
A9: car_make_benefit_flag | B9: 0.120954 | C9: 0.15360745 | D9: 0.13642857 | E9: 0.15933232 | F9: 0.038984587 | G9: 0.1076398 | H9: 0.1774398 | I9: 0.1571496 | J9: 0.13777778 | K9: 0.068808644 | L9: 0.10049376 | M9: 0.1751279 | N9: 0.17059324 | O9: 0.13144137 | P9: 0.053991447 | Q9: 0.12661212 | R9: 0.19686411 | S9: 0.18332943 | T9: 0.13159491 | U9: 0.076484259 | V9: 0.15189408 | W9: 0.22011036 | X9: 0.21551724 | Y9: 0.16162571 | Z9: 0.098082192 | AA9: 0.22283929 | AB9: 0.24502488 | AC9: 0.24472843 | AD9: 0.20837589 | AE9: 0.1450555 | AF9: 0.24399347 | AG9: 0.23479189 | AH9: 0.24541238 | AI9: 0.20627803 | AJ9: 0.17762094 | AK9: 0.25828904 | AL9: 0.26012404 | AM9: 0.28322752 | AN9: 0.24352879 | AO9: 0.26330581 | AP9: 0.27481992 | AQ9: 0.29925732 | AR9: 0.29045199 | AS9: 0.24574468 | AT9: 0.28315253 | AU9: 0.32362123 | AV9: 0.31594037 | AW9: 0.35083449 | AX9: 0.25171867 | AY9: 0.33678069 | AZ9: 0.31428571 | BA9: 0.32878271 | BB9: 0.3759542 | BC9: 0.2226762 | BD9: 0.33549911
A10: theft_risk_flag | B10: 0.054940375 | C10: 0.047323507 | D10: 0.056428571 | E10: 0.071320182 | F10: 0.18011484 | G10: 0.058020478 | H10: 0.050697085 | I10: 0.048607834 | J10: 0.066666667 | K10: 0.1103213 | L10: 0.074208539 | M10: 0.05785124 | N10: 0.063582174 | O10: 0.086631815 | P10: 0.08784747 | Q10: 0.063098045 | R10: 0.051393728 | S10: 0.050105362 | T10: 0.088538508 | U10: 0.070357067 | V10: 0.060316293 | W10: 0.03923973 | X10: 0.032247765 | Y10: 0.059546314 | Z10: 0.04 | AA10: 0.055536272 | AB10: 0.052860697 | AC10: 0.042811502 | AD10: 0.040858018 | AE10: 0.025731584 | AF10: 0.055749942 | AG10: 0.052650302 | AH10: 0.04759024 | AI10: 0.064275037 | AJ10: 0.0092633436 | AK10: 0.050366996 | AL10: 0.046333455 | AM10: 0.045668646 | AN10: 0.06550449 | AO10: 0.0075531354 | AP10: 0.038678359 | AQ10: 0.03713412 | AR10: 0.044396898 | AS10: 0.058510638 | AT10: 0.0044277175 | AU10: 0.024765869 | AV10: 0.047591743 | AW10: 0.031293463 | AX10: 0.03648863 | AY10: 0.0026518165 | AZ10: 0.032539683 | BA10: 0.038680319 | BB10: 0.03307888 | BC10: 0.04392237 | BD10: 0.0041346722
A11: mcy_low_mileage_flag | B11: 0 | C11: 0 | D11: 0 | E11: 0 | F11: 0 | G11: 0 | H11: 0 | I11: 0 | J11: 0 | K11: 0 | L11: 0 | M11: 0 | N11: 0 | O11: 0 | P11: 0 | Q11: 0 | R11: 0 | S11: 0 | T11: 0 | U11: 0 | V11: 0 | W11: 0 | X11: 0 | Y11: 0 | Z11: 0 | AA11: 0 | AB11: 0 | AC11: 0 | AD11: 0 | AE11: 0 | AF11: 0 | AG11: 0 | AH11: 0 | AI11: 0 | AJ11: 0 | AK11: 0 | AL11: 0 | AM11: 0 | AN11: 0 | AO11: 0 | AP11: 0 | AQ11: 0 | AR11: 0 | AS11: 0 | AT11: 0 | AU11: 0 | AV11: 0 | AW11: 0 | AX11: 0 | AY11: 0 | AZ11: 0 | BA11: 0 | BB11: 0 | BC11: 0 | BD11: 0
A12: weekend_flag | B12: 0.22359455 | C12: 0.28394104 | D12: 0.24214286 | E12: 0.30955994 | F12: 0.16651556 | G12: 0.21606721 | H12: 0.27629911 | I12: 0.25908447 | J12: 0.31555556 | K12: 0.21438726 | L12: 0.22741795 | M12: 0.27587564 | N12: 0.25915413 | O12: 0.26661688 | P12: 0.21650036 | Q12: 0.23186798 | R12: 0.28397213 | S12: 0.26106298 | T12: 0.26986052 | U12: 0.19099937 | V12: 0.2469658 | W12: 0.27835684 | X12: 0.26149425 | Y12: 0.2268431 | Z12: 0.2109589 | AA12: 0.2552933 | AB12: 0.29166667 | AC12: 0.26805112 | AD12: 0.28396323 | AE12: 0.21316852 | AF12: 0.28283182 | AG12: 0.32692992 | AH12: 0.29118774 | AI12: 0.30293971 | AJ12: 0.24275842 | AK12: 0.26955201 | AL12: 0.31229478 | AM12: 0.28507065 | AN12: 0.28843106 | AO12: 0.22554014 | AP12: 0.2730974 | AQ12: 0.29008301 | AR12: 0.27895159 | AS12: 0.28510638 | AT12: 0.21651539 | AU12: 0.28969823 | AV12: 0.32224771 | AW12: 0.30180807 | AX12: 0.29613961 | AY12: 0.22460886 | AZ12: 0.29285714 | BA12: 0.34357224 | BB12: 0.30279898 | BC12: 0.30337079 | BD12: 0.24630833
A13: weekday_flag | B13: 0.77640545 | C13: 0.71605896 | D13: 0.75785714 | E13: 0.69044006 | F13: 0.83348444 | G13: 0.78393279 | H13: 0.72370089 | I13: 0.74091553 | J13: 0.68444444 | K13: 0.78561274 | L13: 0.77258205 | M13: 0.72412436 | N13: 0.74084587 | O13: 0.73338312 | P13: 0.78349964 | Q13: 0.76813202 | R13: 0.71602787 | S13: 0.73893702 | T13: 0.73013948 | U13: 0.80900063 | V13: 0.7530342 | W13: 0.72164316 | X13: 0.73850575 | Y13: 0.7731569 | Z13: 0.7890411 | AA13: 0.7447067 | AB13: 0.70833333 | AC13: 0.73194888 | AD13: 0.71603677 | AE13: 0.78683148 | AF13: 0.71716818 | AG13: 0.67307008 | AH13: 0.70881226 | AI13: 0.69706029 | AJ13: 0.75724158 | AK13: 0.73044799 | AL13: 0.68770522 | AM13: 0.71492935 | AN13: 0.71156894 | AO13: 0.77445986 | AP13: 0.7269026 | AQ13: 0.70991699 | AR13: 0.72104841 | AS13: 0.71489362 | AT13: 0.78348461 | AU13: 0.71030177 | AV13: 0.67775229 | AW13: 0.69819193 | AX13: 0.70386039 | AY13: 0.77539114 | AZ13: 0.70714286 | BA13: 0.65642776 | BB13: 0.69720102 | BC13: 0.69662921 | BD13: 0.75369167
... A25: --- N_RECORDS | B25: 2348 | C25: 1289 | D25: 1400 | E25: 659 | F25: 3309 | G25: 3809 | H25: 1578 | I25: 2119 | J25: 675 | K25: 3517 | L25: 6886 | M25: 2541 | N25: 3523 | O25: 1339 | P25: 5612 | Q25: 7211 | R25: 2296 | S25: 4271 | T25: 1649 | U25: 4733 | V25: 5438 | W25: 1631 | X25: 3132 | Y25: 1058 | Z25: 3650 | AA25: 5762 | AB25: 1608 | AC25: 3130 | AD25: 979 | AE25: 3964 | AF25: 8574 | AG25: 2811 | AH25: 4959 | AI25: 2007 | AJ25: 6801 | AK25: 7902 | AL25: 2741 | AM25: 4883 | AN25: 1893 | AO25: 5693 | AP25: 6386 | AQ25: 2289 | AR25: 3739 | AS25: 1880 | AT25: 4517 | AU25: 4805 | AV25: 1744 | AW25: 2876 | AX25: 1891 | AY25: 3771 | AZ25: 2520 | BA25: 879 | BB25: 1572 | BC25: 979 | BD25: 1693
B28: FRN | 2023 Q3 | C28: AN | 2023 Q3 | D28: STG | 2023 Q3 | E28: FLD | 2023 Q3 | F28: ENT | 2023 Q3
A29: 2023 Q3 | B29: 0.095826235 | C29: 0.065166796 | D29: 0.071428571 | E29: 0.075872534 | F29: 0.095194923
A30: 2024 Q2 | B30: 0.12910831 | C30: 0.097125436 | D30: 0.10231796 | E30: 0.09460279 | F30: 0.13564336
A31: 2025 Q1 | B31: 0.21308607 | C31: 0.17253646 | D31: 0.18249647 | E31: 0.22720478 | F31: 0.25922658
A32: 2025 Q3 | B32: 0.1554964 | C32: 0.12975098 | D32: 0.13506285 | E32: 0.18191489 | F32: 0.18729245
A33: 2026 Q1 | B33: 0.088888889 | C33: 0.089874858 | D33: 0.08524173 | E33: 0.11031665 | F33: 0.11577082
B35: 2023 Q3 | C35: 2024 Q2 | D35: 2025 Q1 | E35: 2025 Q3 | F35: 2026 Q1 | H35: 2023 Q3 | I35: 2024 Q2 | J35: 2025 Q1 | K35: 2025 Q3 | L35: 2026 Q1
A36: AN | B36: 0.070929096 | C36: 0.058338772 | D36: 0.057133574 | E36: 0.062308989 | F36: 0.050346189 | G36: AN | H36: =B36/SUM(B$36:B$40) -> 0.1261865 | I36: =C36/SUM(C$36:C$40) -> 0.10331993 | J36: =D36/SUM(D$36:D$40) -> 0.10446652 | K36: =E36/SUM(E$36:E$40) -> 0.11539696 | L36: =F36/SUM(F$36:F$40) -> 0.11212407
A37: FRN | B37: 0.13173055 | C37: 0.19601919 | D37: 0.17853916 | E37: 0.18284774 | F37: 0.14858861 | G37: FRN | H37: =B37/SUM(B$36:B$40) -> 0.23435541 | I37: =C37/SUM(C$36:C$40) -> 0.34715659 | J37: =D37/SUM(D$36:D$40) -> 0.32645192 | K37: =E37/SUM(E$36:E$40) -> 0.3386361 | L37: =F37/SUM(F$36:F$40) -> 0.33091599
A38: STG | B38: 0.087174269 | C38: 0.12671234 | D38: 0.11209916 | E38: 0.11076505 | F38: 0.09685136 | G38: STG | H38: =B38/SUM(B$36:B$40) -> 0.1550875 | I38: =C38/SUM(C$36:C$40) -> 0.22441183 | J38: =D38/SUM(D$36:D$40) -> 0.20496896 | K38: =E38/SUM(E$36:E$40) -> 0.20513813 | L38: =F38/SUM(F$36:F$40) -> 0.21569395
A39: FLD | B39: 0.04692546 | C39: 0.047661722 | D39: 0.044575499 | E39: 0.052429385 | F39: 0.054321767 | G39: FLD | H39: =B39/SUM(B$36:B$40) -> 0.0834828 | I39: =C39/SUM(C$36:C$40) -> 0.084410515 | J39: =D39/SUM(D$36:D$40) -> 0.081504567 | K39: =E39/SUM(E$36:E$40) -> 0.097099821 | L39: =F39/SUM(F$36:F$40) -> 0.12097793
A40: ENT | B40: 0.22533796 | C40: 0.13590997 | D40: 0.1545606 | E40: 0.13160231 | F40: 0.098914219 | G40: ENT | H40: =B40/SUM(B$36:B$40) -> 0.40088779 | I40: =C40/SUM(C$36:C$40) -> 0.24070114 | J40: =D40/SUM(D$36:D$40) -> 0.28260804 | K40: =E40/SUM(E$36:E$40) -> 0.24372898 | L40: =F40/SUM(F$36:F$40) -> 0.22028806
A41: KMX | B41: 0.43790266 | C41: 0.435358 | D41: 0.453092 | E41: 0.46004653 | F41: 0.55097786 | H41: =SUM(H36:H40) -> 1 | I41: =SUM(I36:I40) -> 1 | J41: =SUM(J36:J40) -> 1 | K41: =SUM(K36:K40) -> 1 | L41: =SUM(L36:L40) -> 1
H43: 2023 Q3 | I43: 2024 Q2 | J43: 2025 Q1 | K43: 2025 Q3 | L43: 2026 Q1
G44: AN | 2023 Q3 | H44: 0.065166796 | I44: 0.097125436 | J44: 0.17253646 | K44: 0.12975098 | L44: 0.089874858
G45: FRN | 2023 Q3 | H45: 0.095826235 | I45: 0.12910831 | J45: 0.21308607 | K45: 0.1554964 | L45: 0.088888889
G46: STG | 2023 Q3 | H46: 0.071428571 | I46: 0.10231796 | J46: 0.18249647 | K46: 0.13506285 | L46: 0.08524173
G47: FLD | 2023 Q3 | H47: 0.075872534 | I47: 0.09460279 | J47: 0.22720478 | K47: 0.18191489 | L47: 0.11031665
G48: ENT | 2023 Q3 | H48: 0.095194923 | I48: 0.13564336 | J48: 0.25922658 | K48: 0.18729245 | L48: 0.11577082
G51: nonkmx | H51: =SUMPRODUCT(H36:H40,H44:H48) -> 0.086254779 | I51: =SUMPRODUCT(I36:I40,I44:I48) -> 0.11845213 | J51: =SUMPRODUCT(J36:J40,J44:J48) -> 0.2167705 | K51: =SUMPRODUCT(K36:K40,K44:K48) -> 0.15864861 | L51: =SUMPRODUCT(L36:L40,L44:L48) -> 0.096726825

Sheet fraud
A1: time | B1: lob | C1: neg_fraud | D1: pos_fraud | E1: other_fraud | F1: lookup
A2: 2023 Q3 | B2: FRN | C2: 0.0891 | D2: 0.2678 | E2: 0.643 | F2: =_xlfn.CONCAT(fraud[[#This Row],[lob]], " ",fraud[[#This Row],[time]]) -> FRN 2023 Q3
A3: 2023 Q3 | B3: FLD | C3: 0.0634 | D3: 0.2698 | E3: 0.6666 | F3: =_xlfn.CONCAT(fraud[[#This Row],[lob]], " ",fraud[[#This Row],[time]]) -> FLD 2023 Q3
A4: 2023 Q3 | B4: KMX | C4: 0.084 | D4: 0.26 | E4: 0.6558 | F4: =_xlfn.CONCAT(fraud[[#This Row],[lob]], " ",fraud[[#This Row],[time]]) -> KMX 2023 Q3
A5: 2023 Q3 | B5: ENT | C5: 0.0585 | D5: 0.1723 | E5: 0.769 | F5: =_xlfn.CONCAT(fraud[[#This Row],[lob]], " ",fraud[[#This Row],[time]]) -> ENT 2023 Q3
A6: 2023 Q3 | B6: AN | C6: 0.0798 | D6: 0.1857 | E6: 0.7343 | F6: =_xlfn.CONCAT(fraud[[#This Row],[lob]], " ",fraud[[#This Row],[time]]) -> AN 2023 Q3
A7: 2023 Q3 | B7: STG | C7: 0.0881 | D7: 0.22 | E7: 0.6917 | F7: =_xlfn.CONCAT(fraud[[#This Row],[lob]], " ",fraud[[#This Row],[time]]) -> STG 2023 Q3
A8: 2023 Q4 | B8: AN | C8: 0.0905 | D8: 0.1865 | E8: 0.7229 | F8: =_xlfn.CONCAT(fraud[[#This Row],[lob]], " ",fraud[[#This Row],[time]]) -> AN 2023 Q4
A9: 2023 Q4 | B9: FRN | C9: 0.0794 | D9: 0.2455 | E9: 0.675 | F9: =_xlfn.CONCAT(fraud[[#This Row],[lob]], " ",fraud[[#This Row],[time]]) -> FRN 2023 Q4
A10: 2023 Q4 | B10: FLD | C10: 0.0937 | D10: 0.2755 | E10: 0.6306 | F10: =_xlfn.CONCAT(fraud[[#This Row],[lob]], " ",fraud[[#This Row],[time]]) -> FLD 2023 Q4
A11: 2023 Q4 | B11: KMX | C11: 0.0856 | D11: 0.2775 | E11: 0.6368 | F11: =_xlfn.CONCAT(fraud[[#This Row],[lob]], " ",fraud[[#This Row],[time]]) -> KMX 2023 Q4
A12: 2023 Q4 | B12: ENT | C12: 0.0503 | D12: 0.2688 | E12: 0.6807 | F12: =_xlfn.CONCAT(fraud[[#This Row],[lob]], " ",fraud[[#This Row],[time]]) -> ENT 2023 Q4
A13: 2023 Q4 | B13: STG | C13: 0.0936 | D13: 0.1773 | E13: 0.7289 | F13: =_xlfn.CONCAT(fraud[[#This Row],[lob]], " ",fraud[[#This Row],[time]]) -> STG 2023 Q4
... A68: 2026 Q1 | B68: ORL | C68: 0 | D68: 0 | E68: 1 | F68: =_xlfn.CONCAT(fraud[[#This Row],[lob]], " ",fraud[[#This Row],[time]]) -> ORL 2026 Q1
A69: 2023 Q3 | B69: nonkmx | C69: 0.0737 | D69: 0.2143 | F69: =_xlfn.CONCAT(fraud[[#This Row],[lob]], " ",fraud[[#This Row],[time]]) -> nonkmx 2023 Q3
A70: 2023 Q4 | B70: nonkmx | C70: 0.0757 | D70: 0.2324 | F70: =_xlfn.CONCAT(fraud[[#This Row],[lob]], " ",fraud[[#This Row],[time]]) -> nonkmx 2023 Q4
A71: 2024 Q1 | B71: nonkmx | C71: 0.0604 | D71: 0.2604 | F71: =_xlfn.CONCAT(fraud[[#This Row],[lob]], " ",fraud[[#This Row],[time]]) -> nonkmx 2024 Q1
A72: 2024 Q2 | B72: nonkmx | C72: 0.0664 | D72: 0.2899 | F72: =_xlfn.CONCAT(fraud[[#This Row],[lob]], " ",fraud[[#This Row],[time]]) -> nonkmx 2024 Q2
A73: 2024 Q3 | B73: nonkmx | C73: 0.0699 | D73: 0.3075 | F73: =_xlfn.CONCAT(fraud[[#This Row],[lob]], " ",fraud[[#This Row],[time]]) -> nonkmx 2024 Q3
A74: 2024 Q4 | B74: nonkmx | C74: 0.0557 | D74: 0.2328 | F74: =_xlfn.CONCAT(fraud[[#This Row],[lob]], " ",fraud[[#This Row],[time]]) -> nonkmx 2024 Q4
A75: 2025 Q1 | B75: nonkmx | C75: 0.0581 | D75: 0.1737 | F75: =_xlfn.CONCAT(fraud[[#This Row],[lob]], " ",fraud[[#This Row],[time]]) -> nonkmx 2025 Q1
A76: 2025 Q2 | B76: nonkmx | C76: 0.0659 | D76: 0.2 | F76: =_xlfn.CONCAT(fraud[[#This Row],[lob]], " ",fraud[[#This Row],[time]]) -> nonkmx 2025 Q2
A77: 2025 Q3 | B77: nonkmx | C77: 0.0609 | D77: 0.1932 | F77: =_xlfn.CONCAT(fraud[[#This Row],[lob]], " ",fraud[[#This Row],[time]]) -> nonkmx 2025 Q3
A78: 2025 Q4 | B78: nonkmx | C78: 0.0761 | D78: 0.1826 | F78: =_xlfn.CONCAT(fraud[[#This Row],[lob]], " ",fraud[[#This Row],[time]]) -> nonkmx 2025 Q4
A79: 2026 Q1 | B79: nonkmx | C79: 0.0644 | D79: 0.1969 | F79: =_xlfn.CONCAT(fraud[[#This Row],[lob]], " ",fraud[[#This Row],[time]]) -> nonkmx 2026 Q1
A84: 2023 Q3 | B84: 0.0737 | C84: 0.2143
A85: 2024 Q2 | B85: 0.0664 | C85: 0.2899
A86: 2025 Q1 | B86: 0.0581 | C86: 0.1737
A87: 2025 Q3 | B87: 0.0609 | C87: 0.1932
A88: 2026 Q1 | B88: 0.0644 | C88: 0.1969
A90: 2023 Q3 | B90: 2024 Q2 | C90: 2025 Q1 | D90: 2025 Q3 | E90: 2026 Q1
A91: 0.0737 | B91: 0.0664 | C91: 0.0581 | D91: 0.0609 | E91: 0.0644 | F91: high fraud
A92: 0.2143 | B92: 0.2899 | C92: 0.1737 | D92: 0.1932 | E92: 0.1969 | F92: low fraud

Sheet dealer
A1: valid_vintage | B1: lob | C1: a_dealers | D1: b_dealers | E1: c_dealers | F1: d_dealers | G1: e_dealers | H1: f_dealers | I1: good_dealer | J1: bad_dealer | K1: lookup
A2: 2026 Q1 | B2: ENT | C2: 0.017 | D2: 0.17613636 | E2: 0.68181818 | F2: 0.125 | G2: 0 | H2: 0 | I2: 0.19313636 | K2: =_xlfn.CONCAT(dll[[#This Row],[lob]], " ", dll[[#This Row],[valid_vintage]]) -> ENT 2026 Q1
A3: 2026 Q1 | B3: STG | C3: 0.0264 | D3: 0.23589436 | E3: 0.59903962 | F3: 0.085234094 | G3: 0.044417767 | H3: 0.0090036014 | I3: 0.26229436 | J3: 0.13865546 | K3: =_xlfn.CONCAT(dll[[#This Row],[lob]], " ", dll[[#This Row],[valid_vintage]]) -> STG 2026 Q1
A4: 2026 Q1 | B4: FRN | C4: 0.012 | D4: 0.16746511 | E4: 0.75275984 | F4: 0.040824828 | G4: 0.026036242 | H4: 0.00083315976 | I4: 0.17946511 | J4: 0.06769423 | K4: =_xlfn.CONCAT(dll[[#This Row],[lob]], " ", dll[[#This Row],[valid_vintage]]) -> FRN 2026 Q1
A5: 2026 Q1 | B5: AN | C5: 0.0643 | D5: 0.25146199 | E5: 0.56725146 | F5: 0.081871345 | G5: 0.035087719 | H5: 0 | I5: 0.31576199 | J5: 0.11695906 | K5: =_xlfn.CONCAT(dll[[#This Row],[lob]], " ", dll[[#This Row],[valid_vintage]]) -> AN 2026 Q1
A6: 2026 Q1 | B6: FLD | C6: 0.1156 | D6: 0.346875 | E6: 0.475 | F6: 0.0375 | G6: 0.025 | H6: 0 | I6: 0.462475 | J6: 0.0625 | K6: =_xlfn.CONCAT(dll[[#This Row],[lob]], " ", dll[[#This Row],[valid_vintage]]) -> FLD 2026 Q1
A7: 2025 Q4 | B7: STG | C7: 0.0264 | D7: 0.21248499 | E7: 0.62605042 | F7: 0.083433373 | G7: 0.042617047 | H7: 0.0090036014 | I7: 0.23888499 | J7: 0.13505402 | K7: =_xlfn.CONCAT(dll[[#This Row],[lob]], " ", dll[[#This Row],[valid_vintage]]) -> STG 2025 Q4
A8: 2025 Q4 | B8: FRN | C8: 0.0093 | D8: 0.17142262 | E8: 0.75796709 | F8: 0.03478442 | G8: 0.026036242 | H8: 0.00041657988 | I8: 0.18072262 | J8: 0.061237242 | K8: =_xlfn.CONCAT(dll[[#This Row],[lob]], " ", dll[[#This Row],[valid_vintage]]) -> FRN 2025 Q4
A9: 2025 Q4 | B9: AN | C9: 0.0672 | D9: 0.25146199 | E9: 0.54678363 | F9: 0.099415205 | G9: 0.035087719 | H9: 0 | I9: 0.31866199 | J9: 0.13450292 | K9: =_xlfn.CONCAT(dll[[#This Row],[lob]], " ", dll[[#This Row],[valid_vintage]]) -> AN 2025 Q4
A10: 2025 Q4 | B10: FLD | C10: 0.1093 | D10: 0.425 | E10: 0.40625 | F10: 0.0375 | G10: 0.01875 | H10: 0.003125 | I10: 0.5343 | J10: 0.059375 | K10: =_xlfn.CONCAT(dll[[#This Row],[lob]], " ", dll[[#This Row],[valid_vintage]]) -> FLD 2025 Q4
A11: 2025 Q4 | B11: ENT | C11: 0 | D11: 0.17613636 | E11: 0.69318182 | F11: 0.13068182 | G11: 0 | H11: 0 | I11: 0.17613636 | J11: 0.13068182 | K11: =_xlfn.CONCAT(dll[[#This Row],[lob]], " ", dll[[#This Row],[valid_vintage]]) -> ENT 2025 Q4
A12: 2025 Q3 | B12: AN | C12: 0.0351 | D12: 0.28445748 | E12: 0.56304985 | F12: 0.090909091 | G12: 0.026392962 | H12: 0 | I12: 0.31955748 | J12: 0.11730205 | K12: =_xlfn.CONCAT(dll[[#This Row],[lob]], " ", dll[[#This Row],[valid_vintage]]) -> AN 2025 Q3
A13: 2025 Q3 | B13: FRN | C13: 0.0099 | D13: 0.16060093 | E13: 0.75243335 | F13: 0.052475667 | G13: 0.024121879 | H13: 0.00042319086 | I13: 0.17050093 | J13: 0.077020736 | K13: =_xlfn.CONCAT(dll[[#This Row],[lob]], " ", dll[[#This Row],[valid_vintage]]) -> FRN 2025 Q3
A14: 2025 Q3 | B14: ENT | C14: 0 | D14: 0.21590909 | E14: 0.51136364 | F14: 0.24431818 | G14: 0.028409091 | H14: 0 | I14: 0.21590909 | J14: 0.27272727 | K14: =_xlfn.CONCAT(dll[[#This Row],[lob]], " ", dll[[#This Row],[valid_vintage]]) -> ENT 2025 Q3
... A229: 2026 Q1 | B229: NONKMX | C229: 0.0224 | D229: 0.19507187 | E229: 0.69514031 | F229: 0.054757016 | G229: 0.029979466 | H229: 0.0026009582 | I229: 0.21747187 | J229: 0.08733744 | K229: =_xlfn.CONCAT(dll[[#This Row],[lob]], " ", dll[[#This Row],[valid_vintage]]) -> NONKMX 2026 Q1
A237: good dealer | B237: bad dealer
A238: 0.23863359 | B238: 0.13542992 | C238: NONKMX 2023 Q3
A239: 0.22137231 | B239: 0.089115316 | C239: NONKMX 2024 Q2
A240: 0.23151672 | B240: 0.089713618 | C240: NONKMX 2025 Q1
A241: 0.2274079 | B241: 0.088728684 | C241: NONKMX 2025 Q3
A242: 0.21747187 | B242: 0.08733744 | C242: NONKMX 2026 Q1
A245: NONKMX 2023 Q3 | B245: NONKMX 2024 Q2 | C245: NONKMX 2025 Q1 | D245: NONKMX 2025 Q3 | E245: NONKMX 2026 Q1
A246: 0.23863359 | B246: 0.22137231 | C246: 0.23151672 | D246: 0.2274079 | E246: 0.21747187
A247: 0.13542992 | B247: 0.089115316 | C247: 0.089713618 | D247: 0.088728684 | E247: 0.08733744

Sheet tc
A1: vintage | B1: lob | C1: dq_3 | D1: dq_6 | E1: co_6 | F1: co_12 | G1: lookup
A2: 2023 Q3 | B2: AN | C2: 0.1846 | D2: 0.1658 | E2: 0.0528 | F2: 0.1322 | G2: =_xlfn.CONCAT(dq[[#This Row],[lob]]," ", dq[[#This Row],[vintage]]) -> AN 2023 Q3
A3: 2023 Q4 | B3: AN | C3: 0.1478 | D3: 0.138 | E3: 0.038 | F3: 0.1305 | G3: =_xlfn.CONCAT(dq[[#This Row],[lob]]," ", dq[[#This Row],[vintage]]) -> AN 2023 Q4
A4: 2024 Q1 | B4: AN | C4: 0.1518 | D4: 0.1625 | E4: 0.0364 | F4: 0.1368 | G4: =_xlfn.CONCAT(dq[[#This Row],[lob]]," ", dq[[#This Row],[vintage]]) -> AN 2024 Q1
A5: 2024 Q2 | B5: AN | C5: 0.1709 | D5: 0.1747 | E5: 0.0446 | F5: 0.1401 | G5: =_xlfn.CONCAT(dq[[#This Row],[lob]]," ", dq[[#This Row],[vintage]]) -> AN 2024 Q2
A6: 2024 Q3 | B6: AN | C6: 0.1679 | D6: 0.1688 | E6: 0.0449 | F6: 0.142 | G6: =_xlfn.CONCAT(dq[[#This Row],[lob]]," ", dq[[#This Row],[vintage]]) -> AN 2024 Q3
A7: 2024 Q4 | B7: AN | C7: 0.1683 | D7: 0.1494 | E7: 0.0358 | F7: 0.1521 | G7: =_xlfn.CONCAT(dq[[#This Row],[lob]]," ", dq[[#This Row],[vintage]]) -> AN 2024 Q4
A8: 2025 Q1 | B8: AN | C8: 0.1923 | D8: 0.1858 | E8: 0.0484 | F8: 0.1579 | G8: =_xlfn.CONCAT(dq[[#This Row],[lob]]," ", dq[[#This Row],[vintage]]) -> AN 2025 Q1
A9: 2025 Q2 | B9: AN | C9: 0.1683 | D9: 0.1775 | E9: 0.0382 | G9: =_xlfn.CONCAT(dq[[#This Row],[lob]]," ", dq[[#This Row],[vintage]]) -> AN 2025 Q2
A10: 2025 Q3 | B10: AN | C10: 0.1724 | D10: 0.1693 | E10: 0.0265 | G10: =_xlfn.CONCAT(dq[[#This Row],[lob]]," ", dq[[#This Row],[vintage]]) -> AN 2025 Q3
A11: 2023 Q3 | B11: ENT | C11: 0.1628 | D11: 0.1814 | E11: 0.0348 | F11: 0.1416 | G11: =_xlfn.CONCAT(dq[[#This Row],[lob]]," ", dq[[#This Row],[vintage]]) -> ENT 2023 Q3
A12: 2023 Q4 | B12: ENT | C12: 0.1561 | D12: 0.1573 | E12: 0.0307 | F12: 0.1298 | G12: =_xlfn.CONCAT(dq[[#This Row],[lob]]," ", dq[[#This Row],[vintage]]) -> ENT 2023 Q4
A13: 2024 Q1 | B13: ENT | C13: 0.1618 | D13: 0.181 | E13: 0.0322 | F13: 0.1311 | G13: =_xlfn.CONCAT(dq[[#This Row],[lob]]," ", dq[[#This Row],[vintage]]) -> ENT 2024 Q1
A14: 2024 Q2 | B14: ENT | C14: 0.1946 | D14: 0.1839 | E14: 0.0366 | F14: 0.1248 | G14: =_xlfn.CONCAT(dq[[#This Row],[lob]]," ", dq[[#This Row],[vintage]]) -> ENT 2024 Q2
A15: 2024 Q3 | B15: ENT | C15: 0.1733 | D15: 0.1842 | E15: 0.0303 | F15: 0.1244 | G15: =_xlfn.CONCAT(dq[[#This Row],[lob]]," ", dq[[#This Row],[vintage]]) -> ENT 2024 Q3
A16: 2024 Q4 | B16: ENT | C16: 0.1977 | D16: 0.1731 | E16: 0.0341 | F16: 0.1492 | G16: =_xlfn.CONCAT(dq[[#This Row],[lob]]," ", dq[[#This Row],[vintage]]) -> ENT 2024 Q4
A17: 2025 Q1 | B17: ENT | C17: 0.1988 | D17: 0.2152 | E17: 0.0412 | F17: 0.1358 | G17: =_xlfn.CONCAT(dq[[#This Row],[lob]]," ", dq[[#This Row],[vintage]]) -> ENT 2025 Q1
A18: 2025 Q2 | B18: ENT | C18: 0.2357 | D18: 0.2179 | E18: 0.0468 | G18: =_xlfn.CONCAT(dq[[#This Row],[lob]]," ", dq[[#This Row],[vintage]]) -> ENT 2025 Q2
A19: 2025 Q3 | B19: ENT | C19: 0.2254 | D19: 0.2302 | E19: 0.0398 | G19: =_xlfn.CONCAT(dq[[#This Row],[lob]]," ", dq[[#This Row],[vintage]]) -> ENT 2025 Q3
A20: 2023 Q3 | B20: FLD | C20: 0.1258 | D20: 0.1402 | E20: 0.0429 | F20: 0.1213 | G20: =_xlfn.CONCAT(dq[[#This Row],[lob]]," ", dq[[#This Row],[vintage]]) -> FLD 2023 Q3
A21: 2023 Q4 | B21: FLD | C21: 0.1218 | D21: 0.1206 | E21: 0.0492 | F21: 0.1141 | G21: =_xlfn.CONCAT(dq[[#This Row],[lob]]," ", dq[[#This Row],[vintage]]) -> FLD 2023 Q4
A22: 2024 Q1 | B22: FLD | C22: 0.15 | D22: 0.1597 | E22: 0.0401 | F22: 0.1216 | G22: =_xlfn.CONCAT(dq[[#This Row],[lob]]," ", dq[[#This Row],[vintage]]) -> FLD 2024 Q1
A23: 2024 Q2 | B23: FLD | C23: 0.1505 | D23: 0.1247 | E23: 0.0289 | F23: 0.0992 | G23: =_xlfn.CONCAT(dq[[#This Row],[lob]]," ", dq[[#This Row],[vintage]]) -> FLD 2024 Q2
A24: 2024 Q3 | B24: FLD | C24: 0.126 | D24: 0.128 | E24: 0.0152 | F24: 0.1019 | G24: =_xlfn.CONCAT(dq[[#This Row],[lob]]," ", dq[[#This Row],[vintage]]) -> FLD 2024 Q3
A25: 2024 Q4 | B25: FLD | C25: 0.1563 | D25: 0.143 | E25: 0.0229 | F25: 0.105 | G25: =_xlfn.CONCAT(dq[[#This Row],[lob]]," ", dq[[#This Row],[vintage]]) -> FLD 2024 Q4
A26: 2025 Q1 | B26: FLD | C26: 0.186 | D26: 0.2091 | E26: 0.0356 | F26: 0.1288 | G26: =_xlfn.CONCAT(dq[[#This Row],[lob]]," ", dq[[#This Row],[vintage]]) -> FLD 2025 Q1
A27: 2025 Q2 | B27: FLD | C27: 0.1884 | D27: 0.1962 | E27: 0.0506 | G27: =_xlfn.CONCAT(dq[[#This Row],[lob]]," ", dq[[#This Row],[vintage]]) -> FLD 2025 Q2
A28: 2025 Q3 | B28: FLD | C28: 0.1902 | D28: 0.1584 | E28: 0.0296 | G28: =_xlfn.CONCAT(dq[[#This Row],[lob]]," ", dq[[#This Row],[vintage]]) -> FLD 2025 Q3
A29: 2023 Q3 | B29: FRN | C29: 0.1996 | D29: 0.2113 | E29: 0.0644 | F29: 0.1942 | G29: =_xlfn.CONCAT(dq[[#This Row],[lob]]," ", dq[[#This Row],[vintage]]) -> FRN 2023 Q3
A30: 2023 Q4 | B30: FRN | C30: 0.1961 | D30: 0.1961 | E30: 0.0513 | F30: 0.1876 | G30: =_xlfn.CONCAT(dq[[#This Row],[lob]]," ", dq[[#This Row],[vintage]]) -> FRN 2023 Q4
A31: 2024 Q1 | B31: FRN | C31: 0.2093 | D31: 0.2312 | E31: 0.0578 | F31: 0.1871 | G31: =_xlfn.CONCAT(dq[[#This Row],[lob]]," ", dq[[#This Row],[vintage]]) -> FRN 2024 Q1
A32: 2024 Q2 | B32: FRN | C32: 0.1922 | D32: 0.2045 | E32: 0.0558 | F32: 0.1756 | G32: =_xlfn.CONCAT(dq[[#This Row],[lob]]," ", dq[[#This Row],[vintage]]) -> FRN 2024 Q2
A33: 2024 Q3 | B33: FRN | C33: 0.182 | D33: 0.2 | E33: 0.0498 | F33: 0.1821 | G33: =_xlfn.CONCAT(dq[[#This Row],[lob]]," ", dq[[#This Row],[vintage]]) -> FRN 2024 Q3
A34: 2024 Q4 | B34: FRN | C34: 0.2089 | D34: 0.2197 | E34: 0.0663 | F34: 0.2139 | G34: =_xlfn.CONCAT(dq[[#This Row],[lob]]," ", dq[[#This Row],[vintage]]) -> FRN 2024 Q4
A35: 2025 Q1 | B35: FRN | C35: 0.216 | D35: 0.2396 | E35: 0.069 | F35: 0.2069 | G35: =_xlfn.CONCAT(dq[[#This Row],[lob]]," ", dq[[#This Row],[vintage]]) -> FRN 2025 Q1
A36: 2025 Q2 | B36: FRN | C36: 0.2386 | D36: 0.25 | E36: 0.0786 | G36: =_xlfn.CONCAT(dq[[#This Row],[lob]]," ", dq[[#This Row],[vintage]]) -> FRN 2025 Q2
A37: 2025 Q3 | B37: FRN | C37: 0.2324 | D37: 0.2651 | E37: 0.0734 | G37: =_xlfn.CONCAT(dq[[#This Row],[lob]]," ", dq[[#This Row],[vintage]]) -> FRN 2025 Q3
A38: 2023 Q3 | B38: MCY | C38: 0.1817 | D38: 0.2431 | E38: 0.1087 | F38: 0.219 | G38: =_xlfn.CONCAT(dq[[#This Row],[lob]]," ", dq[[#This Row],[vintage]]) -> MCY 2023 Q3
A39: 2023 Q4 | B39: MCY | C39: 0.1785 | D39: 0.2059 | E39: 0.0811 | F39: 0.2623 | G39: =_xlfn.CONCAT(dq[[#This Row],[lob]]," ", dq[[#This Row],[vintage]]) -> MCY 2023 Q4
A40: 2024 Q1 | B40: MCY | C40: 0.1893 | D40: 0.2291 | E40: 0.0941 | F40: 0.264 | G40: =_xlfn.CONCAT(dq[[#This Row],[lob]]," ", dq[[#This Row],[vintage]]) -> MCY 2024 Q1
A41: 2024 Q2 | B41: MCY | C41: 0.1826 | D41: 0.2152 | E41: 0.0964 | F41: 0.2806 | G41: =_xlfn.CONCAT(dq[[#This Row],[lob]]," ", dq[[#This Row],[vintage]]) -> MCY 2024 Q2
A42: 2024 Q3 | B42: MCY | C42: 0.1966 | D42: 0.2121 | E42: 0.094 | F42: 0.2285 | G42: =_xlfn.CONCAT(dq[[#This Row],[lob]]," ", dq[[#This Row],[vintage]]) -> MCY 2024 Q3
A43: 2024 Q4 | B43: MCY | C43: 0.1957 | D43: 0.2166 | E43: 0.0955 | F43: 0.2449 | G43: =_xlfn.CONCAT(dq[[#This Row],[lob]]," ", dq[[#This Row],[vintage]]) -> MCY 2024 Q4
A44: 2025 Q1 | B44: MCY | C44: 0.1336 | D44: 0.193 | E44: 0.0634 | F44: 0.2361 | G44: =_xlfn.CONCAT(dq[[#This Row],[lob]]," ", dq[[#This Row],[vintage]]) -> MCY 2025 Q1
A45: 2025 Q2 | B45: MCY | C45: 0.1744 | D45: 0.2301 | E45: 0.0777 | G45: =_xlfn.CONCAT(dq[[#This Row],[lob]]," ", dq[[#This Row],[vintage]]) -> MCY 2025 Q2
A46: 2025 Q3 | B46: MCY | C46: 0.2148 | D46: 0.2753 | E46: 0.0918 | G46: =_xlfn.CONCAT(dq[[#This Row],[lob]]," ", dq[[#This Row],[vintage]]) -> MCY 2025 Q3
A47: 2023 Q3 | B47: STG | C47: 0.1679 | D47: 0.1576 | E47: 0.0516 | F47: 0.1514 | G47: =_xlfn.CONCAT(dq[[#This Row],[lob]]," ", dq[[#This Row],[vintage]]) -> STG 2023 Q3
A48: 2023 Q4 | B48: STG | C48: 0.1774 | D48: 0.1675 | E48: 0.0537 | F48: 0.1687 | G48: =_xlfn.CONCAT(dq[[#This Row],[lob]]," ", dq[[#This Row],[vintage]]) -> STG 2023 Q4
A49: 2024 Q1 | B49: STG | C49: 0.1538 | D49: 0.1756 | E49: 0.0415 | F49: 0.1558 | G49: =_xlfn.CONCAT(dq[[#This Row],[lob]]," ", dq[[#This Row],[vintage]]) -> STG 2024 Q1
A50: 2024 Q2 | B50: STG | C50: 0.1737 | D50: 0.176 | E50: 0.0535 | F50: 0.1542 | G50: =_xlfn.CONCAT(dq[[#This Row],[lob]]," ", dq[[#This Row],[vintage]]) -> STG 2024 Q2
A51: 2024 Q3 | B51: STG | C51: 0.1673 | D51: 0.1715 | E51: 0.0489 | F51: 0.1591 | G51: =_xlfn.CONCAT(dq[[#This Row],[lob]]," ", dq[[#This Row],[vintage]]) -> STG 2024 Q3
A52: 2024 Q4 | B52: STG | C52: 0.1688 | D52: 0.1622 | E52: 0.0516 | F52: 0.1675 | G52: =_xlfn.CONCAT(dq[[#This Row],[lob]]," ", dq[[#This Row],[vintage]]) -> STG 2024 Q4
A53: 2025 Q1 | B53: STG | C53: 0.1719 | D53: 0.1851 | E53: 0.0479 | F53: 0.1565 | G53: =_xlfn.CONCAT(dq[[#This Row],[lob]]," ", dq[[#This Row],[vintage]]) -> STG 2025 Q1
A54: 2025 Q2 | B54: STG | C54: 0.204 | D54: 0.1961 | E54: 0.0525 | G54: =_xlfn.CONCAT(dq[[#This Row],[lob]]," ", dq[[#This Row],[vintage]]) -> STG 2025 Q2
A55: 2025 Q3 | B55: STG | C55: 0.2058 | D55: 0.2154 | E55: 0.0545 | G55: =_xlfn.CONCAT(dq[[#This Row],[lob]]," ", dq[[#This Row],[vintage]]) -> STG 2025 Q3
